Workbook

Sheet 事業評価【A案・税引前】
E1: 1 | F1: 2 | G1: 3 | H1: 4 | I1: 5 | J1: 6 | K1: 7 | L1: 8 | M1: 9
B2: 企業価値A案（税引前） | M2: 【千円】
D3: H23年度 | E3: H24年度 | F3: H25年度 | G3: H26年度 | H3: H27年度 | I3: H28年度 | J3: H29年度 | K3: H30年度 | L3: H31年度 | M3: H32年度
B4: 前年度繰越 | D4: 0 | E4: =D40 -> #REF! | F4: =E40 -> #REF! | G4: =F40 -> #REF! | H4: =G40 -> #REF! | I4: =H40 -> #REF! | J4: =I40 -> #REF! | K4: =J40 -> #REF! | L4: =K40 -> #REF! | M4: =L40 -> #REF!
B5: 経常収入 | D5: =SUM(基礎!D50:O50) -> 100000 | E5: =SUM(基礎!U50:AF50) -> 12207511 | F5: =SUM(基礎!AL50:AW50) -> 15790055 | G5: =SUM(基礎!BC50:BN50) -> 751036.8 | H5: =SUM(基礎!BT50:CE50) -> 352000 | I5: =SUM(基礎!CK50:CV50) -> 6000 | J5: =SUM(基礎!DB50:DM50) -> 0 | K5: =SUM(基礎!DS50:ED50) -> 0 | L5: =SUM(基礎!EJ50:EU50) -> 0 | M5: =SUM(基礎!FA50:FL50) -> 0
C6: 店舗現金売上 | D6: =SUM(基礎!D51:O51) -> 0 | E6: =SUM(基礎!U51:AF51) -> 11727511 | F6: =SUM(基礎!AL51:AW51) -> 15070055 | G6: =SUM(基礎!BC51:BN51) -> 281600 | H6: =SUM(基礎!BT51:CE51) -> 281600 | I6: =SUM(基礎!CK51:CV51) -> 0 | J6: =SUM(基礎!DB51:DM51) -> 0 | K6: =SUM(基礎!DS51:ED51) -> 0 | L6: =SUM(基礎!EJ51:EU51) -> 0 | M6: =SUM(基礎!FA51:FL51) -> 0
C7: 店舗催事売掛入金 | D7: =SUM(基礎!D52:O52) -> 0 | E7: =SUM(基礎!U52:AF52) -> 480000 | F7: =SUM(基礎!AL52:AW52) -> 720000 | G7: =SUM(基礎!BC52:BN52) -> 409436.8 | H7: =SUM(基礎!BT52:CE52) -> 70400 | I7: =SUM(基礎!CK52:CV52) -> 6000 | J7: =SUM(基礎!DB52:DM52) -> 0 | K7: =SUM(基礎!DS52:ED52) -> 0 | L7: =SUM(基礎!EJ52:EU52) -> 0 | M7: =SUM(基礎!FA52:FL52) -> 0
C8: FCロイヤリティ | D8: =SUM(基礎!D53:O53) -> 100000 | E8: =SUM(基礎!U53:AF53) -> 0 | F8: =SUM(基礎!AL53:AW53) -> 0 | G8: =SUM(基礎!BC53:BN53) -> 60000 | H8: =SUM(基礎!BT53:CE53) -> 0 | I8: =SUM(基礎!CK53:CV53) -> 0 | J8: =SUM(基礎!DB53:DM53) -> 0 | K8: =SUM(基礎!DS53:ED53) -> 0 | L8: =SUM(基礎!EJ53:EU53) -> 0 | M8: =SUM(基礎!FA53:FL53) -> 0
C9: 他収入 | D9: =SUM(基礎!D54:O54) -> 0 | E9: =SUM(基礎!U54:AF54) -> 0 | F9: =SUM(基礎!AL54:AW54) -> 0 | G9: =SUM(基礎!BC54:BN54) -> 0 | H9: =SUM(基礎!BT54:CE54) -> 0 | I9: =SUM(基礎!CK54:CV54) -> 0 | J9: =SUM(基礎!DB54:DM54) -> 0 | K9: =SUM(基礎!DS54:ED54) -> 0 | L9: =SUM(基礎!EJ54:EU54) -> 0 | M9: =SUM(基礎!FA54:FL54) -> 0
B10: 経常支出 | D10: =SUM(基礎!D55:O55) -> 0 | E10: =SUM(基礎!U55:AF55) -> 9628066.7 | F10: =SUM(基礎!AL55:AW55) -> 11109826 | G10: =SUM(基礎!BC55:BN55) -> 625120 | H10: =SUM(基礎!BT55:CE55) -> 393160 | I10: =SUM(基礎!CK55:CV55) -> #REF! | J10: =SUM(基礎!DB55:DM55) -> #REF! | K10: =SUM(基礎!DS55:ED55) -> #REF! | L10: =SUM(基礎!EJ55:EU55) -> #REF! | M10: =SUM(基礎!FA55:FL55) -> #REF!
C11: 店舗仕入買掛 | D11: =SUM(基礎!D56:O56) -> 0 | E11: =SUM(基礎!U56:AF56) -> 1052000 | F11: =SUM(基礎!AL56:AW56) -> 662000 | G11: =SUM(基礎!BC56:BN56) -> 80500 | H11: =SUM(基礎!BT56:CE56) -> 88000 | I11: =SUM(基礎!CK56:CV56) -> 7500 | J11: =SUM(基礎!DB56:DM56) -> 0 | K11: =SUM(基礎!DS56:ED56) -> 0 | L11: =SUM(基礎!EJ56:EU56) -> 0 | M11: =SUM(基礎!FA56:FL56) -> 0
C12: 店舗人件費 | D12: =SUM(基礎!D57:O57) -> 0 | E12: =SUM(基礎!U57:AF57) -> 8576066.7 | F12: =SUM(基礎!AL57:AW57) -> 10447826 | G12: =SUM(基礎!BC57:BN57) -> 352600 | H12: =SUM(基礎!BT57:CE57) -> 105600 | I12: =SUM(基礎!CK57:CV57) -> 9000 | J12: =SUM(基礎!DB57:DM57) -> 0 | K12: =SUM(基礎!DS57:ED57) -> 0 | L12: =SUM(基礎!EJ57:EU57) -> 0 | M12: =SUM(基礎!FA57:FL57) -> 0
C13: 販管費（ｻｲﾄ１） | D13: =SUM(基礎!D58:O58) -> 0 | E13: =SUM(基礎!U58:AF58) -> 0 | F13: =SUM(基礎!AL58:AW58) -> 0 | G13: =SUM(基礎!BC58:BN58) -> 192020 | H13: =SUM(基礎!BT58:CE58) -> 199560 | I13: =SUM(基礎!CK58:CV58) -> 335428 | J13: =SUM(基礎!DB58:DM58) -> #REF! | K13: =SUM(基礎!DS58:ED58) -> #REF! | L13: =SUM(基礎!EJ58:EU58) -> #REF! | M13: =SUM(基礎!FA58:FL58) -> #REF!
C14: 販管費（ｻｲﾄ２） | D14: =SUM(基礎!D59:O59) -> 0 | E14: =SUM(基礎!U59:AF59) -> 0 | F14: =SUM(基礎!AL59:AW59) -> 0 | G14: =SUM(基礎!BC59:BN59) -> 0 | H14: =SUM(基礎!BT59:CE59) -> 0 | I14: =SUM(基礎!CK59:CV59) -> 0 | J14: =SUM(基礎!DB59:DM59) -> 0 | K14: =SUM(基礎!DS59:ED59) -> 0 | L14: =SUM(基礎!EJ59:EU59) -> 0 | M14: =SUM(基礎!FA59:FL59) -> 0
C15: 支払利息 | D15: =SUM(基礎!D60:O60) -> 0 | E15: =SUM(基礎!U60:AF60) -> 0 | F15: =SUM(基礎!AL60:AW60) -> 0 | G15: =SUM(基礎!BC60:BN60) -> 0 | H15: =SUM(基礎!BT60:CE60) -> 0 | I15: =SUM(基礎!CK60:CV60) -> 0 | J15: =SUM(基礎!DB60:DM60) -> 0 | K15: =SUM(基礎!DS60:ED60) -> 0 | L15: =SUM(基礎!EJ60:EU60) -> 0 | M15: =SUM(基礎!FA60:FL60) -> 0
C16: 固定資産購入等 | D16: =SUM(基礎!D61:O61) -> 0 | E16: =SUM(基礎!U61:AF61) -> 0 | F16: =SUM(基礎!AL61:AW61) -> 0 | G16: =SUM(基礎!BC61:BN61) -> 0 | H16: =SUM(基礎!BT61:CE61) -> 0 | I16: =SUM(基礎!CK61:CV61) -> 0 | J16: =SUM(基礎!DB61:DM61) -> 0 | K16: =SUM(基礎!DS61:ED61) -> 0 | L16: =SUM(基礎!EJ61:EU61) -> 0 | M16: =SUM(基礎!FA61:FL61) -> 0
C17: 他支出 | D17: =SUM(基礎!D62:O62) -> 0 | E17: =SUM(基礎!U62:AF62) -> 0 | F17: =SUM(基礎!AL62:AW62) -> 0 | G17: =SUM(基礎!BC62:BN62) -> 0 | H17: =SUM(基礎!BT62:CE62) -> 0 | I17: =SUM(基礎!CK62:CV62) -> #REF! | J17: =SUM(基礎!DB62:DM62) -> #REF! | K17: =SUM(基礎!DS62:ED62) -> #REF! | L17: =SUM(基礎!EJ62:EU62) -> #REF! | M17: =SUM(基礎!FA62:FL62) -> #REF!
B18: 経常収支差額 | D18: =SUM(基礎!D63:O63) -> 100000 | E18: =SUM(基礎!U63:AF63) -> 2579444.1 | F18: =SUM(基礎!AL63:AW63) -> 4680229.2 | G18: =SUM(基礎!BC63:BN63) -> 125916.8 | H18: =SUM(基礎!BT63:CE63) -> -41160 | I18: =SUM(基礎!CK63:CV63) -> #REF! | J18: =SUM(基礎!DB63:DM63) -> #REF! | K18: =SUM(基礎!DS63:ED63) -> #REF! | L18: =SUM(基礎!EJ63:EU63) -> #REF! | M18: =SUM(基礎!FA63:FL63) -> #REF!
B19: 財務収入 | D19: =SUM(D20:D27) -> #REF! | E19: =SUM(基礎!U64:AF64) -> 0 | F19: =SUM(基礎!AL64:AW64) -> 0 | G19: =SUM(基礎!BC64:BN64) -> -120000000 | H19: =SUM(基礎!BT64:CE64) -> 0 | I19: =SUM(基礎!CK64:CV64) -> -26000 | J19: =SUM(基礎!DB64:DM64) -> 0 | K19: =SUM(基礎!DS64:ED64) -> 0 | L19: =SUM(基礎!EJ64:EU64) -> 0 | M19: =SUM(基礎!FA64:FL64) -> 0
C20: 資本金 | D20: 0 | E20: =SUM(基礎!U65:AF65) -> 0 | F20: =SUM(基礎!AL65:AW65) -> 0 | G20: =SUM(基礎!BC65:BN65) -> 0 | H20: =SUM(基礎!BT65:CE65) -> 0 | I20: =SUM(基礎!CK65:CV65) -> 0 | J20: =SUM(基礎!DB65:DM65) -> 0 | K20: =SUM(基礎!DS65:ED65) -> 0 | L20: =SUM(基礎!EJ65:EU65) -> 0 | M20: =SUM(基礎!FA65:FL65) -> 0
C21: 役員借入 | D21: =SUM(基礎!D66:O66) -> 0 | E21: =SUM(基礎!U66:AF66) -> 0 | F21: =SUM(基礎!AL66:AW66) -> 0 | G21: =SUM(基礎!BC66:BN66) -> 0 | H21: =SUM(基礎!BT66:CE66) -> 0 | I21: =SUM(基礎!CK66:CV66) -> -26000 | J21: =SUM(基礎!DB66:DM66) -> 0 | K21: =SUM(基礎!DS66:ED66) -> 0 | L21: =SUM(基礎!EJ66:EU66) -> 0 | M21: =SUM(基礎!FA66:FL66) -> 0
C22: 金融機関借入 | D22: =SUM(基礎!D67:O67) -> 0 | E22: =SUM(基礎!U67:AF67) -> 0 | F22: =SUM(基礎!AL67:AW67) -> 0 | G22: =SUM(基礎!BC67:BN67) -> 0 | H22: =SUM(基礎!BT67:CE67) -> 0 | I22: =SUM(基礎!CK67:CV67) -> 0 | J22: =SUM(基礎!DB67:DM67) -> 0 | K22: =SUM(基礎!DS67:ED67) -> 0 | L22: =SUM(基礎!EJ67:EU67) -> 0 | M22: =SUM(基礎!FA67:FL67) -> 0
C23: 固定資産売却 | D23: =SUM(基礎!D68:O68) -> 0 | E23: =SUM(基礎!U68:AF68) -> 0 | F23: =SUM(基礎!AL68:AW68) -> 0 | G23: =SUM(基礎!BC68:BN68) -> 0 | H23: =SUM(基礎!BT68:CE68) -> 0 | I23: =SUM(基礎!CK68:CV68) -> 0 | J23: =SUM(基礎!DB68:DM68) -> 0 | K23: =SUM(基礎!DS68:ED68) -> 0 | L23: =SUM(基礎!EJ68:EU68) -> 0 | M23: =SUM(基礎!FA68:FL68) -> 0
C24: FC保証金 | D24: =SUM(基礎!D69:O69) -> 0 | E24: =SUM(基礎!U69:AF69) -> 0 | F24: =SUM(基礎!AL69:AW69) -> 0 | G24: =SUM(基礎!BC69:BN69) -> -120000000 | H24: =SUM(基礎!BT69:CE69) -> 0 | I24: =SUM(基礎!CK69:CV69) -> 0 | J24: =SUM(基礎!DB69:DM69) -> 0 | K24: =SUM(基礎!DS69:ED69) -> 0 | L24: =SUM(基礎!EJ69:EU69) -> 0 | M24: =SUM(基礎!FA69:FL69) -> 0
C25: 地区本部保証金 | D25: =SUM(基礎!#REF!) -> #REF! | E25: =SUM(基礎!#REF!) -> #REF! | F25: =SUM(基礎!#REF!) -> #REF! | G25: =SUM(基礎!#REF!) -> #REF! | H25: =SUM(基礎!#REF!) -> #REF! | I25: =SUM(基礎!#REF!) -> #REF! | J25: =SUM(基礎!#REF!) -> #REF! | K25: =SUM(基礎!#REF!) -> #REF! | ... M25: =SUM(基礎!#REF!) -> #REF!
C26: 減価償却 | D26: =SUM(基礎!#REF!) -> #REF! | E26: =SUM(基礎!#REF!) -> #REF! | F26: =SUM(基礎!#REF!) -> #REF! | G26: =SUM(基礎!#REF!) -> #REF! | H26: =SUM(基礎!#REF!) -> #REF! | I26: =SUM(基礎!#REF!) -> #REF! | J26: =SUM(基礎!#REF!) -> #REF! | K26: =SUM(基礎!#REF!) -> #REF! | ... M26: =SUM(基礎!#REF!) -> #REF!
C27: その他 | D27: =SUM(基礎!#REF!) -> #REF! | E27: =SUM(基礎!#REF!) -> #REF! | F27: =SUM(基礎!#REF!) -> #REF! | G27: =SUM(基礎!#REF!) -> #REF! | H27: =SUM(基礎!#REF!) -> #REF! | I27: =SUM(基礎!#REF!) -> #REF! | J27: =SUM(基礎!#REF!) -> #REF! | K27: =SUM(基礎!#REF!) -> #REF! | ... M27: =SUM(基礎!#REF!) -> #REF!
B28: 財務支出 | D28: =SUM(D29:D35) -> #REF! | E28: =SUM(E29:E35) -> #REF! | F28: =SUM(F29:F35) -> #REF! | G28: =SUM(G29:G35) -> #REF! | H28: =SUM(H29:H35) -> #REF! | I28: =SUM(I29:I35) -> #REF! | J28: =SUM(J29:J35) -> #REF! | K28: =SUM(K29:K35) -> #REF! | ... N28: =SUM(N29:N35) -> 0
C29: 役員返済 | D29: 24000 | E29: 24000 | F29: 24000 | G29: 24000 | H29: 24000 | I29: 0 | J29: 0 | K29: 0 | L29: 0 | M29: 0
C30: 金融機関返済 | D30: =SUM(基礎!D72:O72) -> 0 | E30: =SUM(基礎!U72:AF72) -> 0 | F30: =SUM(基礎!AL72:AW72) -> 0 | G30: =SUM(基礎!BC72:BN72) -> 0 | H30: =SUM(基礎!BT72:CE72) -> 0 | I30: =SUM(基礎!CK72:CV72) -> 1112 | J30: =SUM(基礎!DB72:DM72) -> 0 | K30: =SUM(基礎!DS72:ED72) -> 0 | L30: =SUM(基礎!EJ72:EU72) -> 0 | M30: =SUM(基礎!FA72:FL72) -> 0
C31: FC保証金返却 | D31: =SUM(基礎!#REF!) -> #REF! | E31: =SUM(基礎!#REF!) -> #REF! | F31: =SUM(基礎!#REF!) -> #REF! | G31: =SUM(基礎!#REF!) -> #REF! | H31: =SUM(基礎!#REF!) -> #REF! | I31: =SUM(基礎!#REF!) -> #REF! | J31: =SUM(基礎!#REF!) -> #REF! | K31: =SUM(基礎!#REF!) -> #REF! | ... M31: =SUM(基礎!#REF!) -> #REF!
C32: 地区本部保証金返却 | D32: =SUM(基礎!#REF!) -> #REF! | E32: =SUM(基礎!#REF!) -> #REF! | F32: =SUM(基礎!#REF!) -> #REF! | G32: =SUM(基礎!#REF!) -> #REF! | H32: =SUM(基礎!#REF!) -> #REF! | I32: =SUM(基礎!#REF!) -> #REF! | J32: =SUM(基礎!#REF!) -> #REF! | K32: =SUM(基礎!#REF!) -> #REF! | ... M32: =SUM(基礎!#REF!) -> #REF!
C33: FC本部（システム等） | D33: =SUM(基礎!#REF!) -> #REF! | E33: =SUM(基礎!#REF!) -> #REF! | F33: =SUM(基礎!#REF!) -> #REF! | G33: =SUM(基礎!#REF!) -> #REF! | H33: =SUM(基礎!#REF!) -> #REF! | I33: =SUM(基礎!#REF!) -> #REF! | J33: =SUM(基礎!#REF!) -> #REF! | K33: =SUM(基礎!#REF!) -> #REF! | ... M33: =SUM(基礎!#REF!) -> #REF!
C34: 店舗出店コスト | D34: =SUM(基礎!#REF!) -> #REF! | E34: =SUM(基礎!#REF!) -> #REF! | F34: =SUM(基礎!#REF!) -> #REF! | G34: =SUM(基礎!#REF!) -> #REF! | H34: =SUM(基礎!#REF!) -> #REF! | I34: =SUM(基礎!#REF!) -> #REF! | J34: =SUM(基礎!#REF!) -> #REF! | K34: =SUM(基礎!#REF!) -> #REF! | ... M34: =SUM(基礎!#REF!) -> #REF!
C35: その他 | D35: =SUM(基礎!D73:O73) -> 0 | E35: =SUM(基礎!U73:AF73) -> 0 | F35: =SUM(基礎!AL73:AW73) -> 0 | G35: =SUM(基礎!BC73:BN73) -> 0 | H35: =SUM(基礎!BT73:CE73) -> 0 | I35: =SUM(基礎!CK73:CV73) -> 0 | J35: =SUM(基礎!DB73:DM73) -> 0 | K35: =SUM(基礎!DS73:ED73) -> 0 | L35: =SUM(基礎!EJ73:EU73) -> 0 | M35: =SUM(基礎!FA73:FL73) -> 0
B36: 財務収支差額 | D36: =D19-D28 -> #REF! | E36: =E19-E28 -> #REF! | F36: =F19-F28 -> #REF! | G36: =G19-G28 -> #REF! | H36: =H19-H28 -> #REF! | I36: =I19-I28 -> #REF! | J36: =J19-J28 -> #REF! | K36: =K19-K28 -> #REF! | ... M36: =M19-M28 -> #REF!
B37: CF | D37: =D18+D36 -> #REF! | E37: =E18+E36 -> #REF! | F37: =F18+F36 -> #REF! | G37: =G18+G36 -> #REF! | H37: =H18+H36 -> #REF! | I37: =I18+I36 -> #REF! | J37: =J18+J36 -> #REF! | K37: =K18+K36 -> #REF! | ... M37: =M18+M36 -> #REF!
B38: 税金 | D38: =PL!D44 -> 40000 | E38: =PL!E44 -> 2707115.4 | F38: =PL!F44 -> 2553539.4 | G38: =PL!G44 -> -20160 | H38: =PL!H44 -> -25344 | I38: =PL!I44 -> #REF! | J38: =PL!J44 -> #REF! | K38: =PL!K44 -> #REF! | ... M38: =PL!M44 -> #REF!
B39: 税引後CF | D39: =D37-D38 -> #REF! | E39: =E37-E38 -> #REF! | F39: =F37-F38 -> #REF! | G39: =G37-G38 -> #REF! | H39: =H37-H38 -> #REF! | I39: =I37-I38 -> #REF! | J39: =J37-J38 -> #REF! | K39: =K37-K38 -> #REF! | ... M39: =M37-M38 -> #REF!
B40: 翌年度繰越 | D40: =D4+D39 -> #REF! | E40: =E4+E39 -> #REF! | F40: =F4+F39 -> #REF! | G40: =G4+G39 -> #REF! | H40: =H4+H39 -> #REF! | I40: =I4+I39 -> #REF! | J40: =J4+J39 -> #REF! | K40: =K4+K39 -> #REF! | ... M40: =M4+M39 -> #REF!
B42: 現在価値（税引前）【割引率1.5％】 | D42: =D37 -> #REF! | E42: =E37/(1+$N$42)^(E1-1) -> #REF! | F42: =F37/(1+$N$42)^(F1) -> #REF! | G42: =G37/(1+$N$42)^(G1) -> #REF! | H42: =H37/(1+$N$42)^(H1) -> #REF! | I42: =I37/(1+$N$42)^(I1) -> #REF! | J42: =J37/(1+$N$42)^(J1) -> #REF! | K42: =K37/(1+$N$42)^(K1) -> #REF! | L42: =L37/(1+$N$42)^(L1) -> #REF! | M42: =M37/(1+$N$42)^(M1) -> #REF! | N42: 0.015
B43: 現在価値（税引後）【割引率1.5％】 | D43: =D39/(1+$N$42) -> #REF! | E43: =E39/(1+$N$42)^(E1) -> #REF! | F43: =F39/(1+$N$42)^(F1) -> #REF! | G43: =G39/(1+$N$42)^(G1) -> #REF! | H43: =H39/(1+$N$42)^(H1) -> #REF! | I43: =I39/(1+$N$42)^(I1) -> #REF! | J43: =J39/(1+$N$42)^(J1) -> #REF! | K43: =K39/(1+$N$42)^(K1) -> #REF! | L43: =L39/(1+$N$42)^(L1) -> #REF! | M43: =M39/(1+$N$42)^(M1) -> #REF! | N43: 0.015
B45: 事業費算定
B46: ＤＣＦ方式の評価額（税引前当期利益ベース） | E46: =SUM(D42:M42) -> #REF!
B47: ＤＣＦ方式の評価額（税引後当期利益ベース） | E47: =SUM(D43:M43) -> #REF!
G49: 事業価値の評価額 | I49: 算入割合
B50: ＤＣＦ方式による評価額（税引前当期利益ベース） | G50: =E46 -> #REF! | I50: =66.7% -> 0.667
B51: 純資産方式による評価額 | G51: 0 | I51: 0.333
B52: ＤＣＦ方式を２、純資産方式を１として加重平均で求めた修正評価額 | G52: =G50*I50+G51*I51 -> #REF!
B53: 事業価値の範囲（+10％） | G53: =G52*1.1 -> #REF! | I53: 0.1
B54: 事業価値の範囲（-10％） | G54: =G52*0.9 -> #REF! | I54: -0.1

Sheet 事業評価【A案・税引後】
E1: 1 | F1: 2 | G1: 3 | H1: 4 | I1: 5 | J1: 6 | K1: 7 | L1: 8 | M1: 9
B2: 企業価値A案（税引後） | M2: 【千円】
D3: H23年度 | E3: H24年度 | F3: H25年度 | G3: H26年度 | H3: H27年度 | I3: H28年度 | J3: H29年度 | K3: H30年度 | L3: H31年度 | M3: H32年度
B4: 前年度繰越 | D4: 0 | E4: =D40 -> #REF! | F4: =E40 -> #REF! | G4: =F40 -> #REF! | H4: =G40 -> #REF! | I4: =H40 -> #REF! | J4: =I40 -> #REF! | K4: =J40 -> #REF! | L4: =K40 -> #REF! | M4: =L40 -> #REF!
B5: 経常収入 | D5: =SUM(基礎!D50:O50) -> 100000 | E5: =SUM(基礎!U50:AF50) -> 12207511 | F5: =SUM(基礎!AL50:AW50) -> 15790055 | G5: =SUM(基礎!BC50:BN50) -> 751036.8 | H5: =SUM(基礎!BT50:CE50) -> 352000 | I5: =SUM(基礎!CK50:CV50) -> 6000 | J5: =SUM(基礎!DB50:DM50) -> 0 | K5: =SUM(基礎!DS50:ED50) -> 0 | L5: =SUM(基礎!EJ50:EU50) -> 0 | M5: =SUM(基礎!FA50:FL50) -> 0
C6: 店舗現金売上 | D6: =SUM(基礎!D51:O51) -> 0 | E6: =SUM(基礎!U51:AF51) -> 11727511 | F6: =SUM(基礎!AL51:AW51) -> 15070055 | G6: =SUM(基礎!BC51:BN51) -> 281600 | H6: =SUM(基礎!BT51:CE51) -> 281600 | I6: =SUM(基礎!CK51:CV51) -> 0 | J6: =SUM(基礎!DB51:DM51) -> 0 | K6: =SUM(基礎!DS51:ED51) -> 0 | L6: =SUM(基礎!EJ51:EU51) -> 0 | M6: =SUM(基礎!FA51:FL51) -> 0
C7: 店舗催事売掛入金 | D7: =SUM(基礎!D52:O52) -> 0 | E7: =SUM(基礎!U52:AF52) -> 480000 | F7: =SUM(基礎!AL52:AW52) -> 720000 | G7: =SUM(基礎!BC52:BN52) -> 409436.8 | H7: =SUM(基礎!BT52:CE52) -> 70400 | I7: =SUM(基礎!CK52:CV52) -> 6000 | J7: =SUM(基礎!DB52:DM52) -> 0 | K7: =SUM(基礎!DS52:ED52) -> 0 | L7: =SUM(基礎!EJ52:EU52) -> 0 | M7: =SUM(基礎!FA52:FL52) -> 0
C8: FCロイヤリティ | D8: =SUM(基礎!D53:O53) -> 100000 | E8: =SUM(基礎!U53:AF53) -> 0 | F8: =SUM(基礎!AL53:AW53) -> 0 | G8: =SUM(基礎!BC53:BN53) -> 60000 | H8: =SUM(基礎!BT53:CE53) -> 0 | I8: =SUM(基礎!CK53:CV53) -> 0 | J8: =SUM(基礎!DB53:DM53) -> 0 | K8: =SUM(基礎!DS53:ED53) -> 0 | L8: =SUM(基礎!EJ53:EU53) -> 0 | M8: =SUM(基礎!FA53:FL53) -> 0
C9: 他収入 | D9: =SUM(基礎!D54:O54) -> 0 | E9: =SUM(基礎!U54:AF54) -> 0 | F9: =SUM(基礎!AL54:AW54) -> 0 | G9: =SUM(基礎!BC54:BN54) -> 0 | H9: =SUM(基礎!BT54:CE54) -> 0 | I9: =SUM(基礎!CK54:CV54) -> 0 | J9: =SUM(基礎!DB54:DM54) -> 0 | K9: =SUM(基礎!DS54:ED54) -> 0 | L9: =SUM(基礎!EJ54:EU54) -> 0 | M9: =SUM(基礎!FA54:FL54) -> 0
B10: 経常支出 | D10: =SUM(基礎!D55:O55) -> 0 | E10: =SUM(基礎!U55:AF55) -> 9628066.7 | F10: =SUM(基礎!AL55:AW55) -> 11109826 | G10: =SUM(基礎!BC55:BN55) -> 625120 | H10: =SUM(基礎!BT55:CE55) -> 393160 | I10: =SUM(基礎!CK55:CV55) -> #REF! | J10: =SUM(基礎!DB55:DM55) -> #REF! | K10: =SUM(基礎!DS55:ED55) -> #REF! | L10: =SUM(基礎!EJ55:EU55) -> #REF! | M10: =SUM(基礎!FA55:FL55) -> #REF!
C11: 店舗仕入買掛 | D11: =SUM(基礎!D56:O56) -> 0 | E11: =SUM(基礎!U56:AF56) -> 1052000 | F11: =SUM(基礎!AL56:AW56) -> 662000 | G11: =SUM(基礎!BC56:BN56) -> 80500 | H11: =SUM(基礎!BT56:CE56) -> 88000 | I11: =SUM(基礎!CK56:CV56) -> 7500 | J11: =SUM(基礎!DB56:DM56) -> 0 | K11: =SUM(基礎!DS56:ED56) -> 0 | L11: =SUM(基礎!EJ56:EU56) -> 0 | M11: =SUM(基礎!FA56:FL56) -> 0
C12: 店舗人件費 | D12: =SUM(基礎!D57:O57) -> 0 | E12: =SUM(基礎!U57:AF57) -> 8576066.7 | F12: =SUM(基礎!AL57:AW57) -> 10447826 | G12: =SUM(基礎!BC57:BN57) -> 352600 | H12: =SUM(基礎!BT57:CE57) -> 105600 | I12: =SUM(基礎!CK57:CV57) -> 9000 | J12: =SUM(基礎!DB57:DM57) -> 0 | K12: =SUM(基礎!DS57:ED57) -> 0 | L12: =SUM(基礎!EJ57:EU57) -> 0 | M12: =SUM(基礎!FA57:FL57) -> 0
C13: 販管費（ｻｲﾄ１） | D13: =SUM(基礎!D58:O58) -> 0 | E13: =SUM(基礎!U58:AF58) -> 0 | F13: =SUM(基礎!AL58:AW58) -> 0 | G13: =SUM(基礎!BC58:BN58) -> 192020 | H13: =SUM(基礎!BT58:CE58) -> 199560 | I13: =SUM(基礎!CK58:CV58) -> 335428 | J13: =SUM(基礎!DB58:DM58) -> #REF! | K13: =SUM(基礎!DS58:ED58) -> #REF! | L13: =SUM(基礎!EJ58:EU58) -> #REF! | M13: =SUM(基礎!FA58:FL58) -> #REF!
C14: 販管費（ｻｲﾄ２） | D14: =SUM(基礎!D59:O59) -> 0 | E14: =SUM(基礎!U59:AF59) -> 0 | F14: =SUM(基礎!AL59:AW59) -> 0 | G14: =SUM(基礎!BC59:BN59) -> 0 | H14: =SUM(基礎!BT59:CE59) -> 0 | I14: =SUM(基礎!CK59:CV59) -> 0 | J14: =SUM(基礎!DB59:DM59) -> 0 | K14: =SUM(基礎!DS59:ED59) -> 0 | L14: =SUM(基礎!EJ59:EU59) -> 0 | M14: =SUM(基礎!FA59:FL59) -> 0
C15: 支払利息 | D15: =SUM(基礎!D60:O60) -> 0 | E15: =SUM(基礎!U60:AF60) -> 0 | F15: =SUM(基礎!AL60:AW60) -> 0 | G15: =SUM(基礎!BC60:BN60) -> 0 | H15: =SUM(基礎!BT60:CE60) -> 0 | I15: =SUM(基礎!CK60:CV60) -> 0 | J15: =SUM(基礎!DB60:DM60) -> 0 | K15: =SUM(基礎!DS60:ED60) -> 0 | L15: =SUM(基礎!EJ60:EU60) -> 0 | M15: =SUM(基礎!FA60:FL60) -> 0
C16: 固定資産購入等 | D16: =SUM(基礎!D61:O61) -> 0 | E16: =SUM(基礎!U61:AF61) -> 0 | F16: =SUM(基礎!AL61:AW61) -> 0 | G16: =SUM(基礎!BC61:BN61) -> 0 | H16: =SUM(基礎!BT61:CE61) -> 0 | I16: =SUM(基礎!CK61:CV61) -> 0 | J16: =SUM(基礎!DB61:DM61) -> 0 | K16: =SUM(基礎!DS61:ED61) -> 0 | L16: =SUM(基礎!EJ61:EU61) -> 0 | M16: =SUM(基礎!FA61:FL61) -> 0
C17: 他支出 | D17: =SUM(基礎!D62:O62) -> 0 | E17: =SUM(基礎!U62:AF62) -> 0 | F17: =SUM(基礎!AL62:AW62) -> 0 | G17: =SUM(基礎!BC62:BN62) -> 0 | H17: =SUM(基礎!BT62:CE62) -> 0 | I17: =SUM(基礎!CK62:CV62) -> #REF! | J17: =SUM(基礎!DB62:DM62) -> #REF! | K17: =SUM(基礎!DS62:ED62) -> #REF! | L17: =SUM(基礎!EJ62:EU62) -> #REF! | M17: =SUM(基礎!FA62:FL62) -> #REF!
B18: 経常収支差額 | D18: =SUM(基礎!D63:O63) -> 100000 | E18: =SUM(基礎!U63:AF63) -> 2579444.1 | F18: =SUM(基礎!AL63:AW63) -> 4680229.2 | G18: =SUM(基礎!BC63:BN63) -> 125916.8 | H18: =SUM(基礎!BT63:CE63) -> -41160 | I18: =SUM(基礎!CK63:CV63) -> #REF! | J18: =SUM(基礎!DB63:DM63) -> #REF! | K18: =SUM(基礎!DS63:ED63) -> #REF! | L18: =SUM(基礎!EJ63:EU63) -> #REF! | M18: =SUM(基礎!FA63:FL63) -> #REF!
B19: 財務収入 | D19: =SUM(D20:D27) -> #REF! | E19: =SUM(基礎!U64:AF64) -> 0 | F19: =SUM(基礎!AL64:AW64) -> 0 | G19: =SUM(基礎!BC64:BN64) -> -120000000 | H19: =SUM(基礎!BT64:CE64) -> 0 | I19: =SUM(基礎!CK64:CV64) -> -26000 | J19: =SUM(基礎!DB64:DM64) -> 0 | K19: =SUM(基礎!DS64:ED64) -> 0 | L19: =SUM(基礎!EJ64:EU64) -> 0 | M19: =SUM(基礎!FA64:FL64) -> 0
C20: 資本金 | D20: 0 | E20: =SUM(基礎!U65:AF65) -> 0 | F20: =SUM(基礎!AL65:AW65) -> 0 | G20: =SUM(基礎!BC65:BN65) -> 0 | H20: =SUM(基礎!BT65:CE65) -> 0 | I20: =SUM(基礎!CK65:CV65) -> 0 | J20: =SUM(基礎!DB65:DM65) -> 0 | K20: =SUM(基礎!DS65:ED65) -> 0 | L20: =SUM(基礎!EJ65:EU65) -> 0 | M20: =SUM(基礎!FA65:FL65) -> 0
C21: 役員借入 | D21: =SUM(基礎!D66:O66) -> 0 | E21: =SUM(基礎!U66:AF66) -> 0 | F21: =SUM(基礎!AL66:AW66) -> 0 | G21: =SUM(基礎!BC66:BN66) -> 0 | H21: =SUM(基礎!BT66:CE66) -> 0 | I21: =SUM(基礎!CK66:CV66) -> -26000 | J21: =SUM(基礎!DB66:DM66) -> 0 | K21: =SUM(基礎!DS66:ED66) -> 0 | L21: =SUM(基礎!EJ66:EU66) -> 0 | M21: =SUM(基礎!FA66:FL66) -> 0
C22: 金融機関借入 | D22: =SUM(基礎!D67:O67) -> 0 | E22: =SUM(基礎!U67:AF67) -> 0 | F22: =SUM(基礎!AL67:AW67) -> 0 | G22: =SUM(基礎!BC67:BN67) -> 0 | H22: =SUM(基礎!BT67:CE67) -> 0 | I22: =SUM(基礎!CK67:CV67) -> 0 | J22: =SUM(基礎!DB67:DM67) -> 0 | K22: =SUM(基礎!DS67:ED67) -> 0 | L22: =SUM(基礎!EJ67:EU67) -> 0 | M22: =SUM(基礎!FA67:FL67) -> 0
C23: 固定資産売却 | D23: =SUM(基礎!D68:O68) -> 0 | E23: =SUM(基礎!U68:AF68) -> 0 | F23: =SUM(基礎!AL68:AW68) -> 0 | G23: =SUM(基礎!BC68:BN68) -> 0 | H23: =SUM(基礎!BT68:CE68) -> 0 | I23: =SUM(基礎!CK68:CV68) -> 0 | J23: =SUM(基礎!DB68:DM68) -> 0 | K23: =SUM(基礎!DS68:ED68) -> 0 | L23: =SUM(基礎!EJ68:EU68) -> 0 | M23: =SUM(基礎!FA68:FL68) -> 0
C24: FC保証金 | D24: =SUM(基礎!D69:O69) -> 0 | E24: =SUM(基礎!U69:AF69) -> 0 | F24: =SUM(基礎!AL69:AW69) -> 0 | G24: =SUM(基礎!BC69:BN69) -> -120000000 | H24: =SUM(基礎!BT69:CE69) -> 0 | I24: =SUM(基礎!CK69:CV69) -> 0 | J24: =SUM(基礎!DB69:DM69) -> 0 | K24: =SUM(基礎!DS69:ED69) -> 0 | L24: =SUM(基礎!EJ69:EU69) -> 0 | M24: =SUM(基礎!FA69:FL69) -> 0
C25: 地区本部保証金 | D25: =SUM(基礎!#REF!) -> #REF! | E25: =SUM(基礎!#REF!) -> #REF! | F25: =SUM(基礎!#REF!) -> #REF! | G25: =SUM(基礎!#REF!) -> #REF! | H25: =SUM(基礎!#REF!) -> #REF! | I25: =SUM(基礎!#REF!) -> #REF! | J25: =SUM(基礎!#REF!) -> #REF! | K25: =SUM(基礎!#REF!) -> #REF! | ... M25: =SUM(基礎!#REF!) -> #REF!
C26: 減価償却 | D26: =SUM(基礎!#REF!) -> #REF! | E26: =SUM(基礎!#REF!) -> #REF! | F26: =SUM(基礎!#REF!) -> #REF! | G26: =SUM(基礎!#REF!) -> #REF! | H26: =SUM(基礎!#REF!) -> #REF! | I26: =SUM(基礎!#REF!) -> #REF! | J26: =SUM(基礎!#REF!) -> #REF! | K26: =SUM(基礎!#REF!) -> #REF! | ... M26: =SUM(基礎!#REF!) -> #REF!
C27: その他 | D27: =SUM(基礎!#REF!) -> #REF! | E27: =SUM(基礎!#REF!) -> #REF! | F27: =SUM(基礎!#REF!) -> #REF! | G27: =SUM(基礎!#REF!) -> #REF! | H27: =SUM(基礎!#REF!) -> #REF! | I27: =SUM(基礎!#REF!) -> #REF! | J27: =SUM(基礎!#REF!) -> #REF! | K27: =SUM(基礎!#REF!) -> #REF! | ... M27: =SUM(基礎!#REF!) -> #REF!
B28: 財務支出 | D28: =SUM(D29:D35) -> #REF! | E28: =SUM(E29:E35) -> #REF! | F28: =SUM(F29:F35) -> #REF! | G28: =SUM(G29:G35) -> #REF! | H28: =SUM(H29:H35) -> #REF! | I28: =SUM(I29:I35) -> #REF! | J28: =SUM(J29:J35) -> #REF! | K28: =SUM(K29:K35) -> #REF! | ... N28: =SUM(N29:N35) -> 0
C29: 役員返済 | D29: 24000 | E29: 24000 | F29: 24000 | G29: 24000 | H29: 24000 | I29: 0 | J29: 0 | K29: 0 | L29: 0 | M29: 0
C30: 金融機関返済 | D30: =SUM(基礎!D72:O72) -> 0 | E30: =SUM(基礎!U72:AF72) -> 0 | F30: =SUM(基礎!AL72:AW72) -> 0 | G30: =SUM(基礎!BC72:BN72) -> 0 | H30: =SUM(基礎!BT72:CE72) -> 0 | I30: =SUM(基礎!CK72:CV72) -> 1112 | J30: =SUM(基礎!DB72:DM72) -> 0 | K30: =SUM(基礎!DS72:ED72) -> 0 | L30: =SUM(基礎!EJ72:EU72) -> 0 | M30: =SUM(基礎!FA72:FL72) -> 0
C31: FC保証金返却 | D31: =SUM(基礎!#REF!) -> #REF! | E31: =SUM(基礎!#REF!) -> #REF! | F31: =SUM(基礎!#REF!) -> #REF! | G31: =SUM(基礎!#REF!) -> #REF! | H31: =SUM(基礎!#REF!) -> #REF! | I31: =SUM(基礎!#REF!) -> #REF! | J31: =SUM(基礎!#REF!) -> #REF! | K31: =SUM(基礎!#REF!) -> #REF! | ... M31: =SUM(基礎!#REF!) -> #REF!
C32: 地区本部保証金返却 | D32: =SUM(基礎!#REF!) -> #REF! | E32: =SUM(基礎!#REF!) -> #REF! | F32: =SUM(基礎!#REF!) -> #REF! | G32: =SUM(基礎!#REF!) -> #REF! | H32: =SUM(基礎!#REF!) -> #REF! | I32: =SUM(基礎!#REF!) -> #REF! | J32: =SUM(基礎!#REF!) -> #REF! | K32: =SUM(基礎!#REF!) -> #REF! | ... M32: =SUM(基礎!#REF!) -> #REF!
C33: FC本部（システム等） | D33: =SUM(基礎!#REF!) -> #REF! | E33: =SUM(基礎!#REF!) -> #REF! | F33: =SUM(基礎!#REF!) -> #REF! | G33: =SUM(基礎!#REF!) -> #REF! | H33: =SUM(基礎!#REF!) -> #REF! | I33: =SUM(基礎!#REF!) -> #REF! | J33: =SUM(基礎!#REF!) -> #REF! | K33: =SUM(基礎!#REF!) -> #REF! | ... M33: =SUM(基礎!#REF!) -> #REF!
C34: 店舗出店コスト | D34: =SUM(基礎!#REF!) -> #REF! | E34: =SUM(基礎!#REF!) -> #REF! | F34: =SUM(基礎!#REF!) -> #REF! | G34: =SUM(基礎!#REF!) -> #REF! | H34: =SUM(基礎!#REF!) -> #REF! | I34: =SUM(基礎!#REF!) -> #REF! | J34: =SUM(基礎!#REF!) -> #REF! | K34: =SUM(基礎!#REF!) -> #REF! | ... M34: =SUM(基礎!#REF!) -> #REF!
C35: その他 | D35: =SUM(基礎!D73:O73) -> 0 | E35: =SUM(基礎!U73:AF73) -> 0 | F35: =SUM(基礎!AL73:AW73) -> 0 | G35: =SUM(基礎!BC73:BN73) -> 0 | H35: =SUM(基礎!BT73:CE73) -> 0 | I35: =SUM(基礎!CK73:CV73) -> 0 | J35: =SUM(基礎!DB73:DM73) -> 0 | K35: =SUM(基礎!DS73:ED73) -> 0 | L35: =SUM(基礎!EJ73:EU73) -> 0 | M35: =SUM(基礎!FA73:FL73) -> 0
B36: 財務収支差額 | D36: =D19-D28 -> #REF! | E36: =E19-E28 -> #REF! | F36: =F19-F28 -> #REF! | G36: =G19-G28 -> #REF! | H36: =H19-H28 -> #REF! | I36: =I19-I28 -> #REF! | J36: =J19-J28 -> #REF! | K36: =K19-K28 -> #REF! | ... M36: =M19-M28 -> #REF!
B37: CF | D37: =D18+D36 -> #REF! | E37: =E18+E36 -> #REF! | F37: =F18+F36 -> #REF! | G37: =G18+G36 -> #REF! | H37: =H18+H36 -> #REF! | I37: =I18+I36 -> #REF! | J37: =J18+J36 -> #REF! | K37: =K18+K36 -> #REF! | ... M37: =M18+M36 -> #REF!
B38: 税金 | D38: =PL!D44 -> 40000 | E38: =PL!E44 -> 2707115.4 | F38: =PL!F44 -> 2553539.4 | G38: =PL!G44 -> -20160 | H38: =PL!H44 -> -25344 | I38: =PL!I44 -> #REF! | J38: =PL!J44 -> #REF! | K38: =PL!K44 -> #REF! | ... M38: =PL!M44 -> #REF!
B39: 税引後CF | D39: =D37-D38 -> #REF! | E39: =E37-E38 -> #REF! | F39: =F37-F38 -> #REF! | G39: =G37-G38 -> #REF! | H39: =H37-H38 -> #REF! | I39: =I37-I38 -> #REF! | J39: =J37-J38 -> #REF! | K39: =K37-K38 -> #REF! | ... M39: =M37-M38 -> #REF!
B40: 翌年度繰越 | D40: =D4+D39 -> #REF! | E40: =E4+E39 -> #REF! | F40: =F4+F39 -> #REF! | G40: =G4+G39 -> #REF! | H40: =H4+H39 -> #REF! | I40: =I4+I39 -> #REF! | J40: =J4+J39 -> #REF! | K40: =K4+K39 -> #REF! | ... M40: =M4+M39 -> #REF!
B42: 現在価値（税引前）【割引率1.5％】 | D42: =D37 -> #REF! | E42: =E37/(1+$N$42)^(E1-1) -> #REF! | F42: =F37/(1+$N$42)^(F1) -> #REF! | G42: =G37/(1+$N$42)^(G1) -> #REF! | H42: =H37/(1+$N$42)^(H1) -> #REF! | I42: =I37/(1+$N$42)^(I1) -> #REF! | J42: =J37/(1+$N$42)^(J1) -> #REF! | K42: =K37/(1+$N$42)^(K1) -> #REF! | L42: =L37/(1+$N$42)^(L1) -> #REF! | M42: =M37/(1+$N$42)^(M1) -> #REF! | N42: 0.015
B43: 現在価値（税引後）【割引率1.5％】 | D43: =D39/(1+$N$42) -> #REF! | E43: =E39/(1+$N$42)^(E1) -> #REF! | F43: =F39/(1+$N$42)^(F1) -> #REF! | G43: =G39/(1+$N$42)^(G1) -> #REF! | H43: =H39/(1+$N$42)^(H1) -> #REF! | I43: =I39/(1+$N$42)^(I1) -> #REF! | J43: =J39/(1+$N$42)^(J1) -> #REF! | K43: =K39/(1+$N$42)^(K1) -> #REF! | L43: =L39/(1+$N$42)^(L1) -> #REF! | M43: =M39/(1+$N$42)^(M1) -> #REF! | N43: 0.015
B45: 事業費算定
B46: ＤＣＦ方式の評価額（税引前当期利益ベース） | E46: =SUM(D42:M42) -> #REF!
B47: ＤＣＦ方式の評価額（税引後当期利益ベース） | E47: =SUM(D43:M43) -> #REF!
G49: 事業価値の評価額 | I49: 算入割合
B50: ＤＣＦ方式による評価額（税引後当期利益ベース） | G50: =E47 -> #REF! | I50: =66.7% -> 0.667
B51: 純資産方式による評価額 | G51: 0 | I51: 0.333
B52: ＤＣＦ方式を２、純資産方式を１として加重平均で求めた修正評価額 | G52: =G50*I50+G51*I51 -> #REF!
B53: 事業価値の範囲（+10％） | G53: =G52*1.1 -> #REF! | I53: 0.1
B54: 事業価値の範囲（-10％） | G54: =G52*0.9 -> #REF! | I54: -0.1

Sheet 予備
D1: H23年度 | H1: H24年度 | L1: H25年度 | P1: H26年度 | T1: H27年度 | X1: H28年度 | AB1: H29年度 | AF1: H30年度
D2: Phase 1：基盤構築フェーズ | I2: Phase 2：高成長フェーズ（目標は100%成長） | P2: Phase3：安定成長フェーズ（目標は50%成長） | X2: Phase4：海外進出基盤構築フェーズ | AB2: Phase5：海外成長フェーズ | AF2: Phase6：海外安定成長フェーズ
C3: 月平均売上 | D3: 5 | E3: 6-8 | F3: 9-11 | G3: 12-2 | H3: 3-5 | I3: 6-8 | J3: 9-11 | K3: 12-2 | L3: 3-5 | M3: 6-8 | N3: 9-11 | O3: 12-2 | P3: 3-5 | Q3: 6-8 | R3: 9-11 | S3: 12-2 | T3: 3-5 | U3: 6-8 | V3: 9-11 | W3: 12-2 | X3: 3-5 | Y3: 6-8 | Z3: 9-11 | AA3: 12-2 | AB3: 3-5 | AC3: 6-8 | AD3: 9-11 | AE3: 12-2 | AF3: 3-5 | AG3: 6-8 | AH3: 9-11 | AI3: 12-2
A4: 直営 | B4: 都市型 | C4: 9000 | D4: 1 | E4: 1 | F4: 1 | G4: 2 | H4: 3 | I4: 3 | J4: 3 | K4: 3 | L4: 3 | M4: 4 | N4: 5 | O4: 6 | P4: 6 | Q4: 6 | R4: 7 | S4: 7 | T4: 7 | U4: 9 | V4: 9 | W4: 10 | X4: 10 | Y4: 12 | Z4: 14 | AA4: 16 | AB4: 18 | AC4: 20 | AD4: 22 | AE4: 24 | AF4: 26 | AG4: 28 | AH4: 30 | AI4: 31
B5: サテライト型 | C5: 6000 | D5: 1 | E5: 1 | F5: 1 | G5: 2 | H5: 3 | I5: 3 | J5: 3 | K5: 3 | L5: 3 | M5: 4 | N5: 5 | O5: 6 | P5: 6 | Q5: 6 | R5: 6 | S5: 7 | T5: 7 | U5: 9 | V5: 9 | W5: 10 | X5: 11 | Y5: 12 | Z5: 13 | AA5: 14 | AB5: 14 | AC5: 15 | AD5: 16 | AE5: 18 | AF5: 18 | AG5: 19 | AH5: 20 | AI5: 20
B6: 郊外型 | C6: 7500 | D6: 1 | E6: 1 | F6: 1 | G6: 2 | H6: 2 | I6: 2 | J6: 3 | K6: 3 | L6: 3 | M6: 4 | N6: 4 | O6: 5 | P6: 6 | Q6: 6 | R6: 6 | S6: 7 | T6: 7 | U6: 9 | V6: 9 | W6: 10 | X6: 10 | Y6: 10 | Z6: 10 | AA6: 10 | AB6: 10 | AC6: 10 | AD6: 10 | AE6: 12 | AF6: 12 | AG6: 12 | AH6: 13 | AI6: 13
B7: SC内 | C7: 6000 | D7: 1 | E7: 1 | F7: 1 | G7: 2 | H7: 2 | I7: 2 | J7: 2 | K7: 2 | L7: 2 | M7: 2 | N7: 2 | O7: 3 | P7: 3 | Q7: 3 | R7: 3 | S7: 4 | T7: 4 | U7: 4 | V7: 4 | W7: 5 | X7: 5 | Y7: 5 | Z7: 5 | AA7: 5 | AB7: 5 | AC7: 5 | AD7: 5 | AE7: 6 | AF7: 6 | AG7: 6 | AH7: 6 | AI7: 6
B8: 売上小計 | D8: =(($C4*D4)+($C5*D5)+($C6*D6)+($C7*D7))*1 -> 28500 | E8: =(($C4*E4)+($C5*E5)+($C6*E6)+($C7*E7))*3 -> 85500 | F8: =(($C4*F4)+($C5*F5)+($C6*F6)+($C7*F7))*3 -> 85500 | G8: =(($C4*G4)+($C5*G5)+($C6*G6)+($C7*G7))*3 -> 171000 | H8: =(($C4*H4)+($C5*H5)+($C6*H6)+($C7*H7))*3 -> 216000 | I8: =(($C4*I4)+($C5*I5)+($C6*I6)+($C7*I7))*3 -> 216000 | J8: =(($C4*J4)+($C5*J5)+($C6*J6)+($C7*J7))*3 -> 238500 | K8: =(($C4*K4)+($C5*K5)+($C6*K6)+($C7*K7))*3 -> 238500 | L8: =(($C4*L4)+($C5*L5)+($C6*L6)+($C7*L7))*3 -> 238500 | ... AI8: =(($C4*AI4)+($C5*AI5)+($C6*AI6)+($C7*AI7))*3 -> 1597500
B9: 店舗数 | D9: =SUM(D4:D7) -> 4 | E9: =SUM(E4:E7) -> 4 | F9: =SUM(F4:F7) -> 4 | G9: =SUM(G4:G7) -> 8 | H9: =SUM(H4:H7) -> 10 | I9: =SUM(I4:I7) -> 10 | J9: =SUM(J4:J7) -> 11 | K9: =SUM(K4:K7) -> 11 | ... AI9: =SUM(AI4:AI7) -> 70
A11: FC | B11: 都市型 | C11: =9000 -> 9000 | E11: 1 | F11: 2 | G11: 2 | H11: 3 | I11: 4 | J11: 4 | K11: 6 | L11: 6 | M11: 9 | N11: 9 | O11: 12 | P11: 14 | Q11: 16 | R11: 18 | S11: 20 | T11: 22 | U11: 24 | V11: 26 | W11: 28 | X11: 31 | Y11: 34 | Z11: 37 | AA11: 40 | AB11: 43 | AC11: 46 | AD11: 49 | AE11: 54 | AF11: 55 | AG11: 58 | AH11: 61 | AI11: 64
B12: サテライト型 | C12: =6000 -> 6000 | E12: 1 | F12: 1 | G12: 2 | H12: 2 | I12: 4 | J12: 4 | K12: 6 | L12: 6 | M12: 9 | N12: 9 | O12: 12 | P12: 14 | Q12: 16 | R12: 18 | S12: 20 | T12: 22 | U12: 24 | V12: 26 | W12: 28 | X12: 31 | Y12: 34 | Z12: 37 | AA12: 42 | AB12: 43 | AC12: 46 | AD12: 49 | AE12: 54 | AF12: 55 | AG12: 58 | AH12: 61 | AI12: 64
B13: 郊外型 | C13: =7500 -> 7500 | E13: 1 | F13: 1 | G13: 2 | H13: 2 | I13: 4 | J13: 4 | K13: 6 | L13: 6 | M13: 9 | N13: 9 | O13: 12 | P13: 14 | Q13: 16 | R13: 18 | S13: 20 | T13: 22 | U13: 24 | V13: 26 | W13: 28 | X13: 31 | Y13: 34 | Z13: 37 | AA13: 40 | AB13: 43 | AC13: 46 | AD13: 49 | AE13: 52 | AF13: 55 | AG13: 58 | AH13: 61 | AI13: 64
B14: SC内 | C14: =6000 -> 6000 | E14: 1 | F14: 2 | G14: 2 | H14: 2 | I14: 2 | J14: 2 | K14: 3 | L14: 3 | M14: 3 | N14: 4 | O14: 4 | P14: 4 | Q14: 4 | R14: 4 | S14: 5 | T14: 5 | U14: 5 | V14: 5 | W14: 6 | X14: 6 | Y14: 6 | Z14: 6 | AA14: 8 | AB14: 8 | AC14: 10 | AD14: 10 | AE14: 10 | AF14: 12 | AG14: 12 | AH14: 12 | AI14: 13
B15: 店舗売上小計 | D15: =(($C11*D11)+($C12*D12)+($C13*D13)+($C14*D14))*3 -> 0 | E15: =(($C11*E11)+($C12*E12)+($C13*E13)+($C14*E14))*3 -> 85500 | F15: =(($C11*F11)+($C12*F12)+($C13*F13)+($C14*F14))*3 -> 130500 | G15: =(($C11*G11)+($C12*G12)+($C13*G13)+($C14*G14))*3 -> 171000 | H15: =(($C11*H11)+($C12*H12)+($C13*H13)+($C14*H14))*3 -> 198000 | I15: =(($C11*I11)+($C12*I12)+($C13*I13)+($C14*I14))*3 -> 306000 | J15: =(($C11*J11)+($C12*J12)+($C13*J13)+($C14*J14))*3 -> 306000 | K15: =(($C11*K11)+($C12*K12)+($C13*K13)+($C14*K14))*3 -> 459000 | ... AI15: =(($C11*AI11)+($C12*AI12)+($C13*AI13)+($C14*AI14))*3 -> 4554000
B16: ロイヤルティ売上 | D16: =D15*0.06 -> 0 | E16: =E15*0.06 -> 5130 | F16: =F15*0.06 -> 7830 | G16: =G15*0.06 -> 10260 | H16: =H15*0.06 -> 11880 | I16: =I15*0.06 -> 18360 | J16: =J15*0.06 -> 18360 | K16: =K15*0.06 -> 27540 | ... AI16: =AI15*0.06 -> 273240
B17: 店舗数 | D17: =SUM(D11:D14) -> 0 | E17: =SUM(E11:E14) -> 4 | F17: =SUM(F11:F14) -> 6 | G17: =SUM(G11:G14) -> 8 | H17: =SUM(H11:H14) -> 9 | I17: =SUM(I11:I14) -> 14 | J17: =SUM(J11:J14) -> 14 | K17: =SUM(K11:K14) -> 21 | ... AI17: =SUM(AI11:AI14) -> 205
B19: 全店舗数 | D19: =D9+D17 -> 4 | E19: =E9+E17 -> 8 | F19: =F9+F17 -> 10 | G19: =G9+G17 -> 16 | H19: =H9+H17 -> 19 | I19: =I9+I17 -> 24 | J19: =J9+J17 -> 25 | K19: =K9+K17 -> 32 | ... AI19: =AI9+AI17 -> 275
B20: 直営FC合計売上 | D20: =D8+D16 -> 28500 | E20: =E8+E16 -> 90630 | F20: =F8+F16 -> 93330 | G20: =G8+G16 -> 181260 | H20: =H8+H16 -> 227880 | I20: =I8+I16 -> 234360 | J20: =J8+J16 -> 256860 | K20: =K8+K16 -> 266040 | ... AI20: =AI8+AI16 -> 1870740
B21: 年間売上 | G21: =SUM(D20:G20) -> 393720 | K21: =SUM(H20:K20) -> 985140 | O21: =SUM(L20:O20) -> 1492920 | S21: =SUM(P20:S20) -> 2242260 | W21: =SUM(T20:W20) -> 3096180 | AA21: =SUM(X20:AA20) -> 4169340 | AE21: =SUM(AB20:AE20) -> 5540940 | AI21: =SUM(AF20:AI20) -> 7064820
B22: 前年比 | K22: =K21/G21 -> 2.5021335 | O22: =O21/K21 -> 1.5154394 | S22: =S21/O21 -> 1.5019291 | W22: =W21/S21 -> 1.3808301 | AA22: =AA21/W21 -> 1.3466078 | AE22: =AE21/AA21 -> 1.3289729 | AI22: =AI21/AE21 -> 1.2750219
K23: ※２年目までに政令指定都市をカバー | O23: ※３年目までに中核市をカバー | S23: ※４年目終了で上場基準を満たして上場準備。海外進出準備 | AI23: ※５年間で展開して店舗数を３年間で達成し倍増する
W24: ※５年目終了で上場し、海外進出に向けて資金調達
U25: ■海外展開分
X26: Phase4：海外進出基盤構築フェーズ | AB26: Phase5：海外成長フェーズ
W27: 月平均売上 | X27: 3-5 | Y27: 6-8 | Z27: 9-11 | AA27: 12-2 | AB27: 3-5 | AC27: 6-8 | AD27: 9-11 | AE27: 12-2 | AF27: 3-5 | AG27: 6-8 | AH27: 9-11 | AI27: 12-2
U28: 直営 | V28: 都市型 | W28: 500 | X28: 3 | Y28: 3 | Z28: 3 | AA28: 5 | AB28: 6 | AC28: 9 | AD28: 12 | AE28: 15 | AF28: 17 | AG28: 19 | AH28: 21 | AI28: 23
V29: サテライト型 | W29: 200 | X29: 3 | Y29: 3 | Z29: 3 | AA29: 5 | AB29: 6 | AC29: 9 | AD29: 12 | AE29: 15 | AF29: 17 | AG29: 19 | AH29: 21 | AI29: 23
V30: 郊外型 | W30: 250 | X30: 3 | Y30: 3 | Z30: 3 | AA30: 5 | AB30: 6 | AC30: 9 | AD30: 12 | AE30: 15 | AF30: 17 | AG30: 19 | AH30: 21 | AI30: 23
V31: SC内 | W31: 100 | X31: 3 | Y31: 3 | Z31: 3 | AA31: 5 | AB31: 6 | AC31: 9 | AD31: 12 | AE31: 15 | AF31: 17 | AG31: 19 | AH31: 21 | AI31: 23
V32: 売上小計 | X32: =(($W28*X28)+($W29*X29)+($W30*X30)+($W31*X31))*3 -> 9450 | Y32: =(($W28*Y28)+($W29*Y29)+($W30*Y30)+($W31*Y31))*3 -> 9450 | Z32: =(($W28*Z28)+($W29*Z29)+($W30*Z30)+($W31*Z31))*3 -> 9450 | AA32: =(($W28*AA28)+($W29*AA29)+($W30*AA30)+($W31*AA31))*3 -> 15750 | AB32: =(($W28*AB28)+($W29*AB29)+($W30*AB30)+($W31*AB31))*3 -> 18900 | AC32: =(($W28*AC28)+($W29*AC29)+($W30*AC30)+($W31*AC31))*3 -> 28350 | AD32: =(($W28*AD28)+($W29*AD29)+($W30*AD30)+($W31*AD31))*3 -> 37800 | AE32: =(($W28*AE28)+($W29*AE29)+($W30*AE30)+($W31*AE31))*3 -> 47250 | ... AI32: =(($W28*AI28)+($W29*AI29)+($W30*AI30)+($W31*AI31))*3 -> 72450
V33: 店舗数 | X33: =SUM(X28:X31) -> 12 | Y33: =SUM(Y28:Y31) -> 12 | Z33: =SUM(Z28:Z31) -> 12 | AA33: =SUM(AA28:AA31) -> 20 | AB33: =SUM(AB28:AB31) -> 24 | AC33: =SUM(AC28:AC31) -> 36 | AD33: =SUM(AD28:AD31) -> 48 | AE33: =SUM(AE28:AE31) -> 60 | ... AI33: =SUM(AI28:AI31) -> 92
U35: FC | V35: 都市型 | W35: 500 | X35: 0 | Y35: 0 | Z35: 1 | AA35: 1 | AB35: 3 | AC35: 5 | AD35: 11 | AE35: 17 | AF35: 29 | AG35: 41 | AH35: 53 | AI35: 65
V36: サテライト型 | W36: 200 | X36: 0 | Y36: 0 | Z36: 1 | AA36: 1 | AB36: 3 | AC36: 5 | AD36: 11 | AE36: 17 | AF36: 29 | AG36: 41 | AH36: 53 | AI36: 65
V37: 郊外型 | W37: 250 | X37: 0 | Y37: 0 | Z37: 1 | AA37: 1 | AB37: 3 | AC37: 5 | AD37: 11 | AE37: 17 | AF37: 29 | AG37: 41 | AH37: 53 | AI37: 65
V38: SC内 | W38: 100 | X38: 0 | Y38: 0 | Z38: 1 | AA38: 1 | AB38: 3 | AC38: 5 | AD38: 11 | AE38: 17 | AF38: 29 | AG38: 41 | AH38: 53 | AI38: 65
V39: 店舗売上小計 | X39: =(($W35*X35)+($W36*X36)+($W37*X37)+($W38*X38))*3 -> 0 | Y39: =(($W35*Y35)+($W36*Y36)+($W37*Y37)+($W38*Y38))*3 -> 0 | Z39: =(($W35*Z35)+($W36*Z36)+($W37*Z37)+($W38*Z38))*3 -> 3150 | AA39: =(($W35*AA35)+($W36*AA36)+($W37*AA37)+($W38*AA38))*3 -> 3150 | AB39: =(($W35*AB35)+($W36*AB36)+($W37*AB37)+($W38*AB38))*3 -> 9450 | AC39: =(($W35*AC35)+($W36*AC36)+($W37*AC37)+($W38*AC38))*3 -> 15750 | AD39: =(($W35*AD35)+($W36*AD36)+($W37*AD37)+($W38*AD38))*3 -> 34650 | AE39: =(($W35*AE35)+($W36*AE36)+($W37*AE37)+($W38*AE38))*3 -> 53550 | ... AI39: =(($W35*AI35)+($W36*AI36)+($W37*AI37)+($W38*AI38))*3 -> 204750
V40: ロイヤルティ売上 | X40: =X39*0.06 -> 0 | Y40: =Y39*0.06 -> 0 | Z40: =Z39*0.06 -> 189 | AA40: =AA39*0.06 -> 189 | AB40: =AB39*0.06 -> 567 | AC40: =AC39*0.06 -> 945 | AD40: =AD39*0.06 -> 2079 | AE40: =AE39*0.06 -> 3213 | ... AI40: =AI39*0.06 -> 12285
V41: 店舗数 | X41: =SUM(X35:X38) -> 0 | Y41: =SUM(Y35:Y38) -> 0 | Z41: =SUM(Z35:Z38) -> 4 | AA41: =SUM(AA35:AA38) -> 4 | AB41: =SUM(AB35:AB38) -> 12 | AC41: =SUM(AC35:AC38) -> 20 | AD41: =SUM(AD35:AD38) -> 44 | AE41: =SUM(AE35:AE38) -> 68 | ... AI41: =SUM(AI35:AI38) -> 260
V43: 海外店舗数 | X43: =X33+X41 -> 12 | Y43: =Y33+Y41 -> 12 | Z43: =Z33+Z41 -> 16 | AA43: =AA33+AA41 -> 24 | AB43: =AB33+AB41 -> 36 | AC43: =AC33+AC41 -> 56 | AD43: =AD33+AD41 -> 92 | AE43: =AE33+AE41 -> 128 | ... AI43: =AI33+AI41 -> 352
V44: 直営FC合計売上 | X44: =X32+X40 -> 9450 | Y44: =Y32+Y40 -> 9450 | Z44: =Z32+Z40 -> 9639 | AA44: =AA32+AA40 -> 15939 | AB44: =AB32+AB40 -> 19467 | AC44: =AC32+AC40 -> 29295 | AD44: =AD32+AD40 -> 39879 | AE44: =AE32+AE40 -> 50463 | ... AI44: =AI32+AI40 -> 84735
V45: 年間売上 | AA45: =SUM(X44:AA44) -> 44478 | AE45: =SUM(AB44:AE44) -> 139104 | AI45: =SUM(AF44:AI44) -> 287532
V46: 前年比 | AE46: =AE45/AA45 -> 3.1274788 | AI46: =AI45/AE45 -> 2.067029
X47: ※米国、アジア２カ国で各国1店舗を展開 | AA47: ※展開好調国で進出都市拡大 | AD47: ※未進出国への進出 | AF47: ※展開好調国で進出都市拡大
Z48: ※海外FC展開開始 | AD48: ※各国でのFC本格展開 | AG48: ※各国でのFC本格展開

Sheet 売上計画 
AJ1: ※５年間で展開して店舗数を３年間で達成し倍増する
E2: 2011 | Q2: 2012 | AC2: 2013 | AO2: 2014 | BA2: 2015 | BM2: 2016 | BY2: 2017 | CK2: 2018
C3: 月平均売上 | E3: Mar | F3: Apr | G3: May | H3: Jun | I3: Jul | J3: Aug | K3: Sep | L3: Oct | M3: Nov | N3: Dec | O3: Jan | P3: Feb | Q3: Mar | R3: Apr | S3: May | T3: Jun | U3: Jul | V3: Aug | W3: Sep | X3: Oct | Y3: Nov | Z3: Dec | AA3: Jan | AB3: Feb | AC3: Mar | AD3: Apr | AE3: May | AF3: Jun | AG3: Jul | AH3: Aug | AI3: Sep | AJ3: Oct | AK3: Nov | AL3: Dec | AM3: Jan | AN3: Feb | AO3: Mar | AP3: Apr | AQ3: May | AR3: Jun | AS3: Jul | AT3: Aug | AU3: Sep | AV3: Oct | AW3: Nov | AX3: Dec | AY3: Jan | AZ3: Feb | BA3: Mar | BB3: Apr | BC3: May | BD3: Jun | BE3: Jul | BF3: Aug | BG3: Sep | BH3: Oct | BI3: Nov | BJ3: Dec | BK3: Jan | BL3: Feb | BM3: Mar | BN3: Apr | BO3: May | BP3: Jun | BQ3: Jul | BR3: Aug | BS3: Sep | BT3: Oct | BU3: Nov | BV3: Dec | BW3: Jan | BX3: Feb | BY3: Mar | BZ3: Apr | CA3: May | CB3: Jun | CC3: Jul | CD3: Aug | CE3: Sep | CF3: Oct | CG3: Nov | CH3: Dec | CI3: Jan | CJ3: Feb | CK3: Mar | CL3: Apr | CM3: May | CN3: Jun | CO3: Jul | CP3: Aug | CQ3: Sep | CR3: Oct | CS3: Nov | CT3: Dec | CU3: Jan | CV3: Feb
A4: 直営 | B4: 都市型 | C4: 7500 | G4: 1 | H4: 1 | I4: 1 | J4: 1 | K4: 1 | L4: 1 | M4: 1 | N4: 2 | O4: 2 | P4: 2 | Q4: 2 | R4: 2 | S4: 2 | T4: 3 | U4: 3 | V4: 3 | W4: 3 | X4: 3 | Y4: 4 | Z4: 4 | AA4: 4 | AB4: 4 | AC4: 6 | AD4: 6 | AE4: 6 | AF4: 7 | AG4: 7 | AH4: 7 | AI4: 8 | AJ4: 8 | AK4: 8 | AL4: 8 | AM4: 8 | AN4: 8 | AO4: 9 | AP4: 9 | AQ4: 9 | AR4: 10 | AS4: 10 | AT4: 10 | AU4: 11 | AV4: 11 | AW4: 11 | AX4: 12 | AY4: 12 | AZ4: 12 | BA4: 13 | BB4: 13 | BC4: 13 | BD4: 14 | BE4: 14 | BF4: 14 | BG4: 15 | BH4: 15 | BI4: 15 | BJ4: 16 | BK4: 16 | BL4: 16 | BM4: 17 | BN4: 17 | BO4: 17 | BP4: 18 | BQ4: 18 | BR4: 18 | BS4: 19 | BT4: 19 | BU4: 19 | BV4: 20 | BW4: 20 | BX4: 20 | BY4: 21 | BZ4: 21 | CA4: 21 | CB4: 22 | CC4: 22 | CD4: 22 | CE4: 23 | CF4: 23 | CG4: 23 | CH4: 24 | CI4: 24 | CJ4: 24 | CK4: 25 | CL4: 25 | CM4: 25 | CN4: 26 | CO4: 26 | CP4: 26 | CQ4: 27 | CR4: 27 | CS4: 27 | CT4: 28 | CU4: 28 | CV4: 28
B5: サテライト型 | C5: 6000 | G5: 1 | H5: 1 | I5: 1 | J5: 1 | K5: 1 | L5: 1 | M5: 1 | N5: 2 | O5: 2 | P5: 2 | Q5: 2 | R5: 2 | S5: 2 | T5: 3 | U5: 3 | V5: 3 | W5: 3 | X5: 3 | Y5: 4 | Z5: 4 | AA5: 4 | AB5: 4 | AC5: 6 | AD5: 6 | AE5: 6 | AF5: 7 | AG5: 7 | AH5: 7 | AI5: 8 | AJ5: 8 | AK5: 8 | AL5: 8 | AM5: 8 | AN5: 8 | AO5: 9 | AP5: 9 | AQ5: 9 | AR5: 10 | AS5: 10 | AT5: 10 | AU5: 11 | AV5: 11 | AW5: 11 | AX5: 12 | AY5: 12 | AZ5: 12 | BA5: 13 | BB5: 13 | BC5: 13 | BD5: 14 | BE5: 14 | BF5: 14 | BG5: 15 | BH5: 15 | BI5: 15 | BJ5: 16 | BK5: 16 | BL5: 16 | BM5: 17 | BN5: 17 | BO5: 17 | BP5: 18 | BQ5: 18 | BR5: 18 | BS5: 19 | BT5: 19 | BU5: 19 | BV5: 20 | BW5: 20 | BX5: 20 | BY5: 21 | BZ5: 21 | CA5: 21 | CB5: 22 | CC5: 22 | CD5: 22 | CE5: 23 | CF5: 23 | CG5: 23 | CH5: 24 | CI5: 24 | CJ5: 24 | CK5: 25 | CL5: 25 | CM5: 25 | CN5: 26 | CO5: 26 | CP5: 26 | CQ5: 27 | CR5: 27 | CS5: 27 | CT5: 28 | CU5: 28 | CV5: 28
B6: 郊外型 | C6: 6000 | G6: 1 | H6: 1 | I6: 1 | J6: 1 | K6: 1 | L6: 1 | M6: 1 | N6: 2 | O6: 2 | P6: 2 | Q6: 2 | R6: 2 | S6: 2 | T6: 3 | U6: 3 | V6: 3 | W6: 3 | X6: 3 | Y6: 4 | Z6: 4 | AA6: 4 | AB6: 4 | AC6: 6 | AD6: 6 | AE6: 6 | AF6: 7 | AG6: 7 | AH6: 7 | AI6: 8 | AJ6: 8 | AK6: 8 | AL6: 8 | AM6: 8 | AN6: 8 | AO6: 9 | AP6: 9 | AQ6: 9 | AR6: 10 | AS6: 10 | AT6: 10 | AU6: 11 | AV6: 11 | AW6: 11 | AX6: 12 | AY6: 12 | AZ6: 12 | BA6: 13 | BB6: 13 | BC6: 13 | BD6: 14 | BE6: 14 | BF6: 14 | BG6: 15 | BH6: 15 | BI6: 15 | BJ6: 16 | BK6: 16 | BL6: 16 | BM6: 17 | BN6: 17 | BO6: 17 | BP6: 18 | BQ6: 18 | BR6: 18 | BS6: 19 | BT6: 19 | BU6: 19 | BV6: 20 | BW6: 20 | BX6: 20 | BY6: 21 | BZ6: 21 | CA6: 21 | CB6: 22 | CC6: 22 | CD6: 22 | CE6: 23 | CF6: 23 | CG6: 23 | CH6: 24 | CI6: 24 | CJ6: 24 | CK6: 25 | CL6: 25 | CM6: 25 | CN6: 26 | CO6: 26 | CP6: 26 | CQ6: 27 | CR6: 27 | CS6: 27 | CT6: 28 | CU6: 28 | CV6: 28
B7: SC内 | C7: 4500 | G7: 1 | H7: 1 | I7: 1 | J7: 1 | K7: 1 | L7: 1 | M7: 1 | N7: 2 | O7: 2 | P7: 2 | Q7: 2 | R7: 2 | S7: 2 | T7: 3 | U7: 3 | V7: 3 | W7: 3 | X7: 3 | Y7: 4 | Z7: 4 | AA7: 4 | AB7: 4 | AC7: 6 | AD7: 6 | AE7: 6 | AF7: 7 | AG7: 7 | AH7: 7 | AI7: 8 | AJ7: 8 | AK7: 8 | AL7: 8 | AM7: 8 | AN7: 8 | AO7: 9 | AP7: 9 | AQ7: 9 | AR7: 9 | AS7: 9 | AT7: 9 | AU7: 10 | AV7: 10 | AW7: 10 | AX7: 10 | AY7: 10 | AZ7: 10 | BA7: 11 | BB7: 11 | BC7: 11 | BD7: 11 | BE7: 11 | BF7: 11 | BG7: 11 | BH7: 11 | BI7: 11 | BJ7: 11 | BK7: 11 | BL7: 11 | BM7: 12 | BN7: 12 | BO7: 12 | BP7: 12 | BQ7: 12 | BR7: 12 | BS7: 13 | BT7: 13 | BU7: 13 | BV7: 13 | BW7: 13 | BX7: 13 | BY7: 14 | BZ7: 14 | CA7: 14 | CB7: 14 | CC7: 14 | CD7: 14 | CE7: 15 | CF7: 15 | CG7: 15 | CH7: 15 | CI7: 15 | CJ7: 15 | CK7: 16 | CL7: 16 | CM7: 16 | CN7: 16 | CO7: 16 | CP7: 16 | CQ7: 17 | CR7: 17 | CS7: 17 | CT7: 17 | CU7: 17 | CV7: 17
B8: 売上小計 | E8: =$C4*E4+$C5*E5+$C6*E6+$C7*E7 -> 0 | F8: =$C4*F4+$C5*F5+$C6*F6+$C7*F7 -> 0 | G8: =$C4*G4+$C5*G5+$C6*G6+$C7*G7 -> 24000 | H8: =$C4*H4+$C5*H5+$C6*H6+$C7*H7 -> 24000 | I8: =$C4*I4+$C5*I5+$C6*I6+$C7*I7 -> 24000 | J8: =$C4*J4+$C5*J5+$C6*J6+$C7*J7 -> 24000 | K8: =$C4*K4+$C5*K5+$C6*K6+$C7*K7 -> 24000 | L8: =$C4*L4+$C5*L5+$C6*L6+$C7*L7 -> 24000 | ... CV8: =$C4*CV4+$C5*CV5+$C6*CV6+$C7*CV7 -> 622500
B9: 店舗数 | E9: =SUM(E4:E7) -> 0 | F9: =SUM(F4:F7) -> 0 | G9: =SUM(G4:G7) -> 4 | H9: =SUM(H4:H7) -> 4 | I9: =SUM(I4:I7) -> 4 | J9: =SUM(J4:J7) -> 4 | K9: =SUM(K4:K7) -> 4 | L9: =SUM(L4:L7) -> 4 | ... CV9: =SUM(CV4:CV7) -> 101
A11: FC | B11: 都市型 | C11: 7500 | E11: 0 | F11: 0 | G11: 1 | H11: 1 | I11: 1 | J11: 1 | K11: 1 | L11: 1 | M11: 1 | N11: 2 | O11: 2 | P11: 2 | Q11: 3 | R11: 3 | S11: 3 | T11: 4 | U11: 4 | V11: 4 | W11: 4 | X11: 4 | Y11: 5 | Z11: 5 | AA11: 5 | AB11: 5 | AC11: 7 | AD11: 7 | AE11: 7 | AF11: 8 | AG11: 8 | AH11: 8 | AI11: 9 | AJ11: 9 | AK11: 9 | AL11: 10 | AM11: 10 | AN11: 10 | AO11: 11 | AP11: 11 | AQ11: 11 | AR11: 13 | AS11: 13 | AT11: 13 | AU11: 15 | AV11: 15 | AW11: 15 | AX11: 17 | AY11: 17 | AZ11: 17 | BA11: 19 | BB11: 19 | BC11: 19 | BD11: 21 | BE11: 21 | BF11: 21 | BG11: 23 | BH11: 23 | BI11: 23 | BJ11: 25 | BK11: 25 | BL11: 25 | BM11: 27 | BN11: 27 | BO11: 27 | BP11: 29 | BQ11: 29 | BR11: 29 | BS11: 31 | BT11: 31 | BU11: 31 | BV11: 33 | BW11: 33 | BX11: 33 | BY11: 35 | BZ11: 35 | CA11: 35 | CB11: 37 | CC11: 37 | CD11: 37 | CE11: 39 | CF11: 39 | CG11: 39 | CH11: 41 | CI11: 41 | CJ11: 41 | CK11: 43 | CL11: 43 | CM11: 43 | CN11: 45 | CO11: 45 | CP11: 45 | CQ11: 47 | CR11: 47 | CS11: 47 | CT11: 49 | CU11: 49 | CV11: 49
B12: サテライト型 | C12: 6000 | E12: 0 | F12: 0 | G12: 0 | H12: 0 | I12: 0 | J12: 0 | K12: 0 | L12: 0 | M12: 0 | N12: 1 | O12: 1 | P12: 1 | Q12: 2 | R12: 2 | S12: 2 | T12: 3 | U12: 3 | V12: 3 | W12: 3 | X12: 3 | Y12: 4 | Z12: 4 | AA12: 4 | AB12: 4 | AC12: 6 | AD12: 6 | AE12: 6 | AF12: 7 | AG12: 7 | AH12: 7 | AI12: 8 | AJ12: 8 | AK12: 8 | AL12: 9 | AM12: 9 | AN12: 9 | AO12: 10 | AP12: 10 | AQ12: 10 | AR12: 12 | AS12: 12 | AT12: 12 | AU12: 15 | AV12: 15 | AW12: 15 | AX12: 17 | AY12: 17 | AZ12: 17 | BA12: 19 | BB12: 19 | BC12: 19 | BD12: 21 | BE12: 21 | BF12: 21 | BG12: 23 | BH12: 23 | BI12: 23 | BJ12: 25 | BK12: 25 | BL12: 25 | BM12: 27 | BN12: 27 | BO12: 27 | BP12: 29 | BQ12: 29 | BR12: 29 | BS12: 31 | BT12: 31 | BU12: 31 | BV12: 33 | BW12: 33 | BX12: 33 | BY12: 35 | BZ12: 35 | CA12: 35 | CB12: 37 | CC12: 37 | CD12: 37 | CE12: 39 | CF12: 39 | CG12: 39 | CH12: 41 | CI12: 41 | CJ12: 41 | CK12: 43 | CL12: 43 | CM12: 43 | CN12: 45 | CO12: 45 | CP12: 45 | CQ12: 47 | CR12: 47 | CS12: 47 | CT12: 49 | CU12: 49 | CV12: 49
B13: 郊外型 | C13: 6000 | G13: 2 | H13: 3 | I13: 3 | J13: 3 | K13: 3 | L13: 3 | M13: 3 | N13: 4 | O13: 4 | P13: 4 | Q13: 4 | R13: 4 | S13: 4 | T13: 5 | U13: 5 | V13: 5 | W13: 5 | X13: 5 | Y13: 6 | Z13: 6 | AA13: 6 | AB13: 6 | AC13: 8 | AD13: 8 | AE13: 8 | AF13: 9 | AG13: 9 | AH13: 9 | AI13: 10 | AJ13: 10 | AK13: 10 | AL13: 11 | AM13: 11 | AN13: 11 | AO13: 12 | AP13: 12 | AQ13: 12 | AR13: 14 | AS13: 14 | AT13: 14 | AU13: 15 | AV13: 15 | AW13: 15 | AX13: 16 | AY13: 16 | AZ13: 16 | BA13: 17 | BB13: 17 | BC13: 17 | BD13: 18 | BE13: 18 | BF13: 18 | BG13: 19 | BH13: 19 | BI13: 19 | BJ13: 20 | BK13: 20 | BL13: 20 | BM13: 21 | BN13: 21 | BO13: 21 | BP13: 22 | BQ13: 22 | BR13: 22 | BS13: 23 | BT13: 23 | BU13: 23 | BV13: 24 | BW13: 24 | BX13: 24 | BY13: 25 | BZ13: 25 | CA13: 25 | CB13: 26 | CC13: 26 | CD13: 26 | CE13: 27 | CF13: 27 | CG13: 27 | CH13: 28 | CI13: 28 | CJ13: 28 | CK13: 29 | CL13: 29 | CM13: 29 | CN13: 30 | CO13: 30 | CP13: 30 | CQ13: 31 | CR13: 31 | CS13: 31 | CT13: 32 | CU13: 32 | CV13: 32
B14: SC内 | C14: 4500 | E14: 0 | F14: 0 | G14: 0 | H14: 1 | I14: 1 | J14: 1 | K14: 1 | L14: 1 | M14: 2 | N14: 2 | O14: 3 | P14: 3 | Q14: 3 | R14: 3 | S14: 3 | T14: 4 | U14: 4 | V14: 4 | W14: 4 | X14: 4 | Y14: 5 | Z14: 5 | AA14: 5 | AB14: 5 | AC14: 7 | AD14: 7 | AE14: 7 | AF14: 8 | AG14: 8 | AH14: 8 | AI14: 9 | AJ14: 9 | AK14: 9 | AL14: 10 | AM14: 10 | AN14: 10 | AO14: 10 | AP14: 10 | AQ14: 10 | AR14: 10 | AS14: 10 | AT14: 10 | AU14: 10 | AV14: 10 | AW14: 10 | AX14: 10 | AY14: 10 | AZ14: 10 | BA14: 11 | BB14: 11 | BC14: 11 | BD14: 11 | BE14: 11 | BF14: 11 | BG14: 12 | BH14: 12 | BI14: 12 | BJ14: 12 | BK14: 12 | BL14: 12 | BM14: 13 | BN14: 13 | BO14: 13 | BP14: 13 | BQ14: 13 | BR14: 13 | BS14: 14 | BT14: 14 | BU14: 14 | BV14: 14 | BW14: 14 | BX14: 14 | BY14: 15 | BZ14: 15 | CA14: 15 | CB14: 15 | CC14: 15 | CD14: 15 | CE14: 16 | CF14: 16 | CG14: 16 | CH14: 16 | CI14: 16 | CJ14: 16 | CK14: 17 | CL14: 17 | CM14: 17 | CN14: 17 | CO14: 17 | CP14: 17 | CQ14: 18 | CR14: 18 | CS14: 18 | CT14: 18 | CU14: 18 | CV14: 18
B15: 店舗売上小計 | E15: =$C11*E11+$C12*E12+$C13*E13+$C14*E14 -> 0 | F15: =$C11*F11+$C12*F12+$C13*F13+$C14*F14 -> 0 | G15: =$C11*G11+$C12*G12+$C13*G13+$C14*G14 -> 19500 | H15: =$C11*H11+$C12*H12+$C13*H13+$C14*H14 -> 30000 | I15: =$C11*I11+$C12*I12+$C13*I13+$C14*I14 -> 30000 | J15: =$C11*J11+$C12*J12+$C13*J13+$C14*J14 -> 30000 | K15: =$C11*K11+$C12*K12+$C13*K13+$C14*K14 -> 30000 | L15: =$C11*L11+$C12*L12+$C13*L13+$C14*L14 -> 30000 | ... CV15: =$C11*CV11+$C12*CV12+$C13*CV13+$C14*CV14 -> 934500
B16: ロイヤルティ売上 | C16: 0.06 | E16: =$C16*E15 -> 0 | F16: =$C16*F15 -> 0 | G16: =$C16*G15 -> 1170 | H16: =$C16*H15 -> 1800 | I16: =$C16*I15 -> 1800 | J16: =$C16*J15 -> 1800 | K16: =$C16*K15 -> 1800 | L16: =$C16*L15 -> 1800 | ... CV16: =$C16*CV15 -> 56070
B17: 店舗数 | E17: =SUM(E11:E14) -> 0 | F17: =SUM(F11:F14) -> 0 | G17: =SUM(G11:G14) -> 3 | H17: =SUM(H11:H14) -> 5 | I17: =SUM(I11:I14) -> 5 | J17: =SUM(J11:J14) -> 5 | K17: =SUM(K11:K14) -> 5 | L17: =SUM(L11:L14) -> 5 | ... CV17: =SUM(CV11:CV14) -> 148
B19: 全店舗数 | E19: =E9+E17 -> 0 | F19: =F9+F17 -> 0 | G19: =G9+G17 -> 7 | H19: =H9+H17 -> 9 | I19: =I9+I17 -> 9 | J19: =J9+J17 -> 9 | K19: =K9+K17 -> 9 | L19: =L9+L17 -> 9 | ... CV19: =CV9+CV17 -> 249
B20: 総売上 | E20: =E8+E16 -> 0 | F20: =F8+F16 -> 0 | G20: =G8+G16 -> 25170 | H20: =H8+H16 -> 25800 | I20: =I8+I16 -> 25800 | J20: =J8+J16 -> 25800 | K20: =K8+K16 -> 25800 | L20: =L8+L16 -> 25800 | ... CV20: =CV8+CV16 -> 678570
B21: 年間売上 | P21: =SUM(E20:P20) -> 334500 | AB21: =SUM(Q20:AB20) -> 958560 | AN21: =SUM(AC20:AN20) -> 2234880 | AZ21: =SUM(AO20:AZ20) -> 3197880 | BL21: =SUM(BA20:BL20) -> 4318020 | BX21: =SUM(BM20:BX20) -> 5436540 | CJ21: =SUM(BY20:CJ20) -> 6582060 | CV21: =SUM(CK20:CV20) -> 7727580
B23: マイルストーン | AB23: ※２年目までに政令指定都市をカバー | AN23: ※３年目までに中核市をカバー | AZ23: ※４年目終了で上場基準を満たして上場準備。海外進出準備 | BL23: ※5期中で上場し、海外進出資金を得る
E26: Ph1：基盤構築フェーズ | G26: Ph 2：高成長フェーズ（目標は50〜100%成長） | M26: Ph3：安定成長フェーズ（目標は20%成長）
E27: 2011 | G27: 2012 | I27: 2013 | K27: 2014 | M27: 2015 | O27: 2016 | Q27: 2017 | S27: 2018
E28: 1H | F28: 2H | G28: 1H | H28: 2H | I28: 1H | J28: 2H | K28: 1H | L28: 2H | M28: 1H | N28: 2H | O28: 1H | P28: 2H | Q28: 1H | R28: 2H | S28: 1H | T28: 2H
B29: 直営店 | C29: 店舗数合計 | E29: =SUM(E9:J9) -> 16 | F29: =SUM(K9:P9) -> 36 | G29: =SUM(Q9:V9) -> 60 | H29: =SUM(W9:AB9) -> 88 | I29: =SUM(AC9:AH9) -> 156 | J29: =SUM(AI9:AN9) -> 192 | K29: =SUM(AO9:AT9) -> 225 | L29: =SUM(AU9:AZ9) -> 267 | M29: =SUM(BA9:BF9) -> 309 | N29: =SUM(BG9:BL9) -> 345 | O29: =SUM(BM9:BR9) -> 387 | P29: =SUM(BS9:BX9) -> 429 | Q29: =SUM(BY9:CD9) -> 471 | R29: =SUM(CE9:CJ9) -> 513 | S29: =SUM(CK9:CP9) -> 555 | T29: =SUM(CQ9:CV9) -> 597
C30: 売上高 | E30: =SUM(E8:J8) -> 96000 | F30: =SUM(K8:P8) -> 216000 | G30: =SUM(Q8:V8) -> 360000 | H30: =SUM(W8:AB8) -> 528000 | I30: =SUM(AC8:AH8) -> 936000 | J30: =SUM(AI8:AN8) -> 1152000 | K30: =SUM(AO8:AT8) -> 1354500 | L30: =SUM(AU8:AZ8) -> 1615500 | M30: =SUM(BA8:BF8) -> 1876500 | N30: =SUM(BG8:BL8) -> 2110500 | O30: =SUM(BM8:BR8) -> 2371500 | P30: =SUM(BS8:BX8) -> 2632500 | Q30: =SUM(BY8:CD8) -> 2893500 | R30: =SUM(CE8:CJ8) -> 3154500 | S30: =SUM(CK8:CP8) -> 3415500 | T30: =SUM(CQ8:CV8) -> 3676500
B31: FC店 | C31: 店舗数合計 | E31: =SUM(E17:J17) -> 18 | F31: =SUM(K17:P17) -> 45 | G31: =SUM(Q17:V17) -> 84 | H31: =SUM(W17:AB17) -> 112 | I31: =SUM(AC17:AH17) -> 180 | J31: =SUM(AI17:AN17) -> 228 | K31: =SUM(AO17:AT17) -> 276 | L31: =SUM(AU17:AZ17) -> 345 | M31: =SUM(BA17:BF17) -> 411 | N31: =SUM(BG17:BL17) -> 477 | O31: =SUM(BM17:BR17) -> 543 | P31: =SUM(BS17:BX17) -> 609 | Q31: =SUM(BY17:CD17) -> 675 | R31: =SUM(CE17:CJ17) -> 741 | S31: =SUM(CK17:CP17) -> 807 | T31: =SUM(CQ17:CV17) -> 873
C32: 売上高 | E32: =SUM(E16:J16) -> 6570 | F32: =SUM(K16:P16) -> 15930 | G32: =SUM(Q16:V16) -> 30240 | H32: =SUM(W16:AB16) -> 40320 | I32: =SUM(AC16:AH16) -> 64800 | J32: =SUM(AI16:AN16) -> 82080 | K32: =SUM(AO16:AT16) -> 100440 | L32: =SUM(AU16:AZ16) -> 127440 | M32: =SUM(BA16:BF16) -> 152820 | N32: =SUM(BG16:BL16) -> 178200 | O32: =SUM(BM16:BR16) -> 203580 | P32: =SUM(BS16:BX16) -> 228960 | Q32: =SUM(BY16:CD16) -> 254340 | R32: =SUM(CE16:CJ16) -> 279720 | S32: =SUM(CK16:CP16) -> 305100 | T32: =SUM(CQ16:CV16) -> 330480
B33: 合計 | C33: 店舗数合計 | E33: =E29+E31 -> 34 | F33: =F29+F31 -> 81 | G33: =G29+G31 -> 144 | H33: =H29+H31 -> 200 | I33: =I29+I31 -> 336 | J33: =J29+J31 -> 420 | K33: =K29+K31 -> 501 | L33: =L29+L31 -> 612 | ... T33: =T29+T31 -> 1470
C34: 売上高 | E34: =E30+E32 -> 102570 | F34: =F30+F32 -> 231930 | G34: =G30+G32 -> 390240 | H34: =H30+H32 -> 568320 | I34: =I30+I32 -> 1000800 | J34: =J30+J32 -> 1234080 | K34: =K30+K32 -> 1454940 | L34: =L30+L32 -> 1742940 | ... T34: =T30+T32 -> 4006980
B35: 年間売上 | F35: =E34+F34 -> 334500 | H35: =G34+H34 -> 958560 | J35: =I34+J34 -> 2234880 | L35: =K34+L34 -> 3197880 | N35: =M34+N34 -> 4318020 | P35: =O34+P34 -> 5436540 | R35: =Q34+R34 -> 6582060 | T35: =S34+T34 -> 7727580
E37: 2011 | F37: 2012 | G37: 2013 | H37: 2014 | I37: 2015 | J37: 2016 | K37: 2017 | L37: 2018 | N37: 店舗計画 | O37: 2011 | P37: 2012 | Q37: 2013 | R37: 2014 | S37: 2015 | T37: 2016 | U37: 2017 | V37: 2018
B38: 直営店 | C38: 店舗数合計 | E38: =SUM(E29:F29) -> 52 | F38: =SUM(G29:H29) -> 148 | G38: =SUM(I29:J29) -> 348 | H38: =SUM(K29:L29) -> 492 | I38: =SUM(M29:N29) -> 654 | J38: =SUM(O29:P29) -> 816 | K38: =SUM(Q29:R29) -> 984 | L38: =SUM(S29:T29) -> 1152 | N38: 5 | O38: 13 | P38: 18 | Q38: 36 | R38: 34 | S38: 35 | T38: 36 | U38: 36 | V38: 36
C39: 売上高 | E39: =SUM(E30:F30) -> 312000 | F39: =SUM(G30:H30) -> 888000 | G39: =SUM(I30:J30) -> 2088000 | H39: =SUM(K30:L30) -> 2970000 | I39: =SUM(M30:N30) -> 3987000 | J39: =SUM(O30:P30) -> 5004000 | K39: =SUM(Q30:R30) -> 6048000 | L39: =SUM(S30:T30) -> 7092000 | N39: 大元 | O39: 千田
B40: FC店 | C40: 店舗数合計 | E40: =SUM(E33:F33) -> 115 | F40: =SUM(G31:H31) -> 196 | G40: =SUM(I31:J31) -> 408 | H40: =SUM(K31:L31) -> 621 | I40: =SUM(M31:N31) -> 888 | J40: =SUM(O31:P31) -> 1152 | K40: =SUM(Q31:R31) -> 1416 | L40: =SUM(S31:T31) -> 1680 | N40: 自由が丘 | O40: 赤坂
C41: 売上高 | E41: =SUM(E32:F32) -> 22500 | F41: =SUM(G32:H32) -> 70560 | G41: =SUM(I32:J32) -> 146880 | H41: =SUM(K32:L32) -> 227880 | I41: =SUM(M32:N32) -> 331020 | J41: =SUM(O32:P32) -> 432540 | K41: =SUM(Q32:R32) -> 534060 | L41: =SUM(S32:T32) -> 635580 | N41: 都立大学 | O41: 葛西
B42: 合計 | C42: 店舗数合計 | E42: =E38+E40 -> 167 | F42: =F38+F40 -> 344 | G42: =G38+G40 -> 756 | H42: =H38+H40 -> 1113 | I42: =I38+I40 -> 1542 | J42: =J38+J40 -> 1968 | K42: =K38+K40 -> 2400 | L42: =L38+L40 -> 2832 | N42: 豊中緑丘 | O42: 鷺沼
C43: 売上高 | E43: =E39+E41 -> 334500 | F43: =F39+F41 -> 958560 | G43: =G39+G41 -> 2234880 | H43: =H39+H41 -> 3197880 | I43: =I39+I41 -> 4318020 | J43: =J39+J41 -> 5436540 | K43: =K39+K41 -> 6582060 | L43: =L39+L41 -> 7727580 | N43: 静岡 | O43: 倉敷
B44: 売上高成長率 | F44: =F43/E43 -> 2.8656502 | G44: =G43/F43 -> 2.3314972 | H44: =H43/G43 -> 1.4308956 | I44: =I43/H43 -> 1.3502758 | J44: =J43/I43 -> 1.2590354 | K44: =K43/J43 -> 1.2107075 | L44: =L43/K43 -> 1.1740367

Sheet 営業権譲渡関連
B1: 譲渡スキーム
I2: 単位：千円
B3: 資金調達（短期） | G3: 資金使途（短期）
B4: 調達主体 | C4: 調達方法 | D4: 金額 | G4: 総額 | H4: 使途名称 | I4: 主体者
B5: アドタッチ | C5: カーブス | D5: 40,000～ | E5: ⇒ | G5: 30000 | H5: 個人借入（超） | I5: アドタッチ
G6: 9,000？ | H6: アドプロ債務 | I6: アドタッチ
G7: 残 | H7: アド運転資金 | I7: アドタッチ
B8: 和良 | C8: 資本＋私募債 | D8: 30000 | E8: 営業権譲渡金⇒ | G8: 30000 | H8: 和良運転資金(4月以前） | I8: アドタッチ
B9: 和良 | C9: 債務引受 | D9: 110000 | E9: 営業権譲渡金⇒ | G9: 110000 | H9: 金融（和良） | I9: アドタッチ
B10: 和良 | C10: 債務引受 | D10: 20000 | E10: 営業権譲渡金⇒ | G10: 20000 | H10: リース残債 | I10: アドタッチ
B11: 和良 | C11: 私募債等 | D11: =260000-D8-D9-D10 -> 100000 | E11: 営業権譲渡金⇒ | G11: 112000 | H11: 個人借入（中） | I11: アドタッチ
D12: ↑但し私募債等が100,000千円に満たない場合は差額分÷100万/月額で返済
D13: またリース債務等の額が想定額より大きい場合は減額調整。
B15: 営業権金額 | D15: 上限：260,000

Sheet Sheet2
B2: 初期３ヶ月
B3: 管理者兼サビ管 | C3: 900円/時間 | D3: ６．５時間 | E3: ２２日 | F3: =900*6.5*22 -> 128700
B4: 職業指導員 | C4: ８００円/時間 | D4: ６．５時間 | E4: ２２日 | F4: =800*6.5*22 -> 114400
B5: 生活支援員 | C5: ８００円/時間 | D5: ６．５時間 | E5: ２２日 | F5: =800*6.5*22 -> 114400
B6: 生活支援員 | C6: ８００円/時間 | D6: ３時間 | E6: ２２日 | F6: =800*3*22 -> 52800
F9: =SUM(F3:F6) -> 410300 | G9: =F4+F5+F6 -> 281600
C10: 雇用保険 | D10: ７／１０００ | F10: =F9/1000*7 -> 2872.1
B12: 初期３ヶ月
B13: 管理者兼サビ管 | C13: 1200円/時間 | D13: ６．５時間 | E13: ２２日 | F13: =1200*6.5*22 -> 171600
B14: 職業指導員 | C14: 9００円/時間 | D14: ６．５時間 | E14: ２２日 | F14: =900*6.5*22 -> 128700
B15: 生活支援員 | C15: 900円/時間 | D15: ６．５時間 | E15: ２２日 | F15: =900*6.5*22 -> 128700
B16: 生活支援員 | C16: 900円/時間 | D16: ３時間 | E16: ２２日 | F16: =900*3*22 -> 59400
F19: =SUM(F13:F16) -> 488400 | G19: =F14+F15+F16 -> 316800
C20: 雇用保険 | D20: ７／１０００ | F20: =F19/1000*7 -> 3418.8

Sheet 基礎
A1: H28年度 P/L | S1: H29年度 | AJ1: H24年度 | BA1: H26年度 | BR1: H27年度 | CI1: H28年度 | CZ1: H29年度 | DQ1: H30年度 | EH1: H31年度 | EY1: H32年度
D2: 4月 | E2: 5月 | F2: 6月 | G2: 7月 | H2: 8月 | I2: 9月 | J2: 10月 | K2: 11月 | L2: 12月 | M2: 1月 | N2: 2月 | O2: 3月 | P2: 合計 | Q2: 対売上比率 | U2: 4月 | V2: 5月 | W2: 6月 | X2: 7月 | Y2: 8月 | Z2: 9月 | AA2: 10月 | AB2: 11月 | AC2: 12月 | AD2: 1月 | AE2: 2月 | AF2: 3月 | AG2: 合計 | AH2: 対売上比率 | AL2: 4月 | AM2: 5月 | AN2: 6月 | AO2: 7月 | AP2: 8月 | AQ2: 9月 | AR2: 10月 | AS2: 11月 | AT2: 12月 | AU2: 1月 | AV2: 2月 | AW2: 3月 | AX2: 合計 | AY2: 対売上比率 | BC2: 3月 | BD2: 4月 | BE2: 5月 | BF2: 6月 | BG2: 7月 | BH2: 8月 | BI2: 9月 | BJ2: 10月 | BK2: 11月 | BL2: 12月 | BM2: 1月 | BN2: 2月 | BO2: 合計 | BP2: 対売上比率 | BT2: 3月 | BU2: 4月 | BV2: 5月 | BW2: 6月 | BX2: 7月 | BY2: 8月 | BZ2: 9月 | CA2: 10月 | CB2: 11月 | CC2: 12月 | CD2: 1月 | CE2: 2月 | CF2: 合計 | CG2: 対売上比率 | CK2: 3月 | CL2: 4月 | CM2: 5月 | CN2: 6月 | CO2: 7月 | CP2: 8月 | CQ2: 9月 | CR2: 10月 | CS2: 11月 | CT2: 12月 | CU2: 1月 | CV2: 2月 | CW2: 合計 | CX2: 対売上比率 | DB2: 3月 | DC2: 4月 | DD2: 5月 | DE2: 6月 | DF2: 7月 | DG2: 8月 | DH2: 9月 | DI2: 10月 | DJ2: 11月 | DK2: 12月 | DL2: 1月 | DM2: 2月 | DN2: 合計 | DO2: 対売上比率 | DS2: 3月 | DT2: 4月 | DU2: 5月 | DV2: 6月 | DW2: 7月 | DX2: 8月 | DY2: 9月 | DZ2: 10月 | EA2: 11月 | EB2: 12月 | EC2: 1月 | ED2: 2月 | EE2: 合計 | EF2: 対売上比率 | EJ2: 3月 | EK2: 4月 | EL2: 5月 | EM2: 6月 | EN2: 7月 | EO2: 8月 | EP2: 9月 | EQ2: 10月 | ER2: 11月 | ES2: 12月 | ET2: 1月 | EU2: 2月 | EV2: 合計 | EW2: 対売上比率 | FA2: 3月 | FB2: 4月 | FC2: 5月 | FD2: 6月 | FE2: 7月 | FF2: 8月 | FG2: 9月 | FH2: 10月 | FI2: 11月 | FJ2: 12月 | FK2: 1月 | FL2: 2月 | FM2: 合計 | FN2: 対売上比率
B3: 総売上 | D3: =D4+D9+D15+D17+D16 -> 0 | E3: =E4+E9+E15+E17+E16 -> 0 | F3: =F4+F9+F15+F17+F16 -> 0 | G3: =G4+G9+G15+G17+G16 -> 0 | H3: =H4+H9+H15+H17+H16 -> 0 | I3: =I4+I9+I15+I17+I16 -> 0 | J3: =J4+J9+J15+J17+J16 -> 0 | K3: =K4+K9+K15+K17+K16 -> 0 | ... O3: =O4+O9+O15+O17+O16 -> 0 | P3: =SUM(D3:O3) -> 100000 | Q3: =P3/P3 -> 1 | S3: 総売上 | U3: =U4+U9+U15+U17+U16 -> 1031370 | V3: =V4+V9+V15+V17+V16 -> 1186064 | W3: =W4+W9+W15+W17+W16 -> 1186064 | X3: =X4+X9+X15+X17+X16 -> 1353888 | Y3: =Y4+Y9+Y15+Y17+Y16 -> 1353888 | Z3: =Z4+Z9+Z15+Z17+Z16 -> 1461712 | AA3: =AA4+AA9+AA15+AA17+AA16 -> 1461712 | AB3: =AB4+AB9+AB15+AB17+AB16 -> 1569536 | ... AF3: =AF4+AF9+AF15+AF17+AF16 -> 1785184 | AG3: =SUM(U3:AF3) -> 17313674 | AH3: =AG3/P3 -> 173.13674 | AJ3: 総売上 | AL3: =AL4+AL9+AL15+AL17+AL16 -> 1091370 | AM3: =AM4+AM9+AM15+AM17+AM16 -> 1246064 | AN3: =AN4+AN9+AN15+AN17+AN16 -> 1246064 | AO3: =AO4+AO9+AO15+AO17+AO16 -> 1353888 | AP3: =AP4+AP9+AP15+AP17+AP16 -> 1353888 | AQ3: =AQ4+AQ9+AQ15+AQ17+AQ16 -> 1461712 | AR3: =AR4+AR9+AR15+AR17+AR16 -> 1461712 | AS3: =AS4+AS9+AS15+AS17+AS16 -> 1569536 | ... AW3: =AW4+AW9+AW15+AW17+AW16 -> 1785184 | AX3: =SUM(AL3:AW3) -> 17493674 | AY3: =AX3/AG3 -> 1.0103964 | BA3: 総売上 | BC3: =BC4+BC9+BC15+BC17+BC16 -> 29000 | BD3: =BD4+BD9+BD15+BD17+BD16 -> 29000 | BE3: =BE4+BE9+BE15+BE17+BE16 -> 29000 | BF3: =BF4+BF9+BF15+BF17+BF16 -> 29000 | BG3: =BG4+BG9+BG15+BG17+BG16 -> 29000 | BH3: =BH4+BH9+BH15+BH17+BH16 -> 28000 | BI3: =BI4+BI9+BI15+BI17+BI16 -> 29000 | BJ3: =BJ4+BJ9+BJ15+BJ17+BJ16 -> 30000 | ... BN3: =BN4+BN9+BN15+BN17+BN16 -> 30000 | BO3: =SUM(BC3:BN3) -> 352000 | BP3: =BO3/AX3 -> 0.020121559 | BR3: 総売上 | BT3: =BT4+BT9+BT15+BT17+BT16 -> 29000 | BU3: =BU4+BU9+BU15+BU17+BU16 -> 29000 | BV3: =BV4+BV9+BV15+BV17+BV16 -> 29000 | BW3: =BW4+BW9+BW15+BW17+BW16 -> 29000 | BX3: =BX4+BX9+BX15+BX17+BX16 -> 29000 | BY3: =BY4+BY9+BY15+BY17+BY16 -> 28000 | BZ3: =BZ4+BZ9+BZ15+BZ17+BZ16 -> 29000 | CA3: =CA4+CA9+CA15+CA17+CA16 -> 30000 | ... CE3: =CE4+CE9+CE15+CE17+CE16 -> 30000 | CF3: =SUM(BT3:CE3) -> 352000 | CG3: =CF3/BO3 -> 1 | CI3: 総売上 | CK3: =CK4+CK9+CK15+CK17+CK16 -> 0 | CL3: =CL4+CL9+CL15+CL17+CL16 -> 0 | CM3: =CM4+CM9+CM15+CM17+CM16 -> 0 | CN3: =CN4+CN9+CN15+CN17+CN16 -> 0 | CO3: =CO4+CO9+CO15+CO17+CO16 -> 0 | CP3: =CP4+CP9+CP15+CP17+CP16 -> 0 | CQ3: =CQ4+CQ9+CQ15+CQ17+CQ16 -> 0 | CR3: =CR4+CR9+CR15+CR17+CR16 -> 0 | ... CV3: =CV4+CV9+CV15+CV17+CV16 -> 0 | CW3: =SUM(CK3:CV3) -> 0 | CX3: =CW3/CF3 -> 0 | CZ3: 総売上 | DB3: =DB4+DB9+DB15+DB17+DB16 -> 0 | DC3: =DC4+DC9+DC15+DC17+DC16 -> 0 | DD3: =DD4+DD9+DD15+DD17+DD16 -> 0 | DE3: =DE4+DE9+DE15+DE17+DE16 -> 0 | DF3: =DF4+DF9+DF15+DF17+DF16 -> 0 | DG3: =DG4+DG9+DG15+DG17+DG16 -> 0 | DH3: =DH4+DH9+DH15+DH17+DH16 -> 0 | DI3: =DI4+DI9+DI15+DI17+DI16 -> 0 | ... DM3: =DM4+DM9+DM15+DM17+DM16 -> 0 | DN3: =SUM(DB3:DM3) -> 0 | DO3: =DN3/CW3 -> #DIV/0! | DQ3: 総売上 | DS3: =DS4+DS9+DS15+DS17+DS16 -> 0 | DT3: =DT4+DT9+DT15+DT17+DT16 -> 0 | DU3: =DU4+DU9+DU15+DU17+DU16 -> 0 | DV3: =DV4+DV9+DV15+DV17+DV16 -> 0 | DW3: =DW4+DW9+DW15+DW17+DW16 -> 0 | DX3: =DX4+DX9+DX15+DX17+DX16 -> 0 | DY3: =DY4+DY9+DY15+DY17+DY16 -> 0 | DZ3: =DZ4+DZ9+DZ15+DZ17+DZ16 -> 0 | ... ED3: =ED4+ED9+ED15+ED17+ED16 -> 0 | EE3: =SUM(DS3:ED3) -> 0 | EF3: =EE3/DN3 -> #DIV/0! | EH3: 総売上 | EJ3: =EJ4+EJ9+EJ15+EJ17+EJ16 -> 0 | EK3: =EK4+EK9+EK15+EK17+EK16 -> 0 | EL3: =EL4+EL9+EL15+EL17+EL16 -> 0 | EM3: =EM4+EM9+EM15+EM17+EM16 -> 0 | EN3: =EN4+EN9+EN15+EN17+EN16 -> 0 | EO3: =EO4+EO9+EO15+EO17+EO16 -> 0 | EP3: =EP4+EP9+EP15+EP17+EP16 -> 0 | EQ3: =EQ4+EQ9+EQ15+EQ17+EQ16 -> 0 | ... EU3: =EU4+EU9+EU15+EU17+EU16 -> 0 | EV3: =SUM(EJ3:EU3) -> 0 | EW3: =EV3/EE3 -> #DIV/0! | EY3: 総売上 | FA3: =FA4+FA9+FA15+FA17+FA16 -> 0 | FB3: =FB4+FB9+FB15+FB17+FB16 -> 0 | FC3: =FC4+FC9+FC15+FC17+FC16 -> 0 | FD3: =FD4+FD9+FD15+FD17+FD16 -> 0 | FE3: =FE4+FE9+FE15+FE17+FE16 -> 0 | FF3: =FF4+FF9+FF15+FF17+FF16 -> 0 | FG3: =FG4+FG9+FG15+FG17+FG16 -> 0 | FH3: =FH4+FH9+FH15+FH17+FH16 -> 0 | ... FL3: =FL4+FL9+FL15+FL17+FL16 -> 0 | FM3: =SUM(FA3:FL3) -> 0 | FN3: =FM3/EV3 -> #DIV/0!
B4: 障害福祉サービス | D4: =SUM(D5:D8) -> 0 | E4: =E6+E8 -> 0 | F4: =F6+F8 -> 0 | G4: =G6+G8 -> 0 | H4: =H6+H8 -> 0 | I4: =I6+I8 -> 0 | J4: =J6+J8 -> 0 | K4: =K6+K8 -> 0 | L4: =L6+L8 -> 0 | ... O4: =O6+O8 -> 0 | P4: =SUM(D4:O4) -> 0 | Q4: =IF(P4=0,"",P4/$P$3) | S4: =IF(B4="","",B4) -> 障害福祉サービス | U4: =SUM(U5:U8) -> 1031370 | V4: =V6+V8 -> 1186064 | W4: =W6+W8 -> 1186064 | X4: =X6+X8 -> 1293888 | Y4: =Y6+Y8 -> 1293888 | Z4: =Z6+Z8 -> 1401712 | AA4: =AA6+AA8 -> 1401712 | AB4: =AB6+AB8 -> 1509536 | AC4: =AC6+AC8 -> 1509536 | ... AF4: =AF6+AF8 -> 1725184 | AG4: =SUM(U4:AF4) -> 16773674 | AH4: =IF(AG4=0,"",AG4/AG$3) -> 0.96881078 | AJ4: =IF(S4="","",S4) -> 障害福祉サービス | AL4: =SUM(AL5:AL8) -> 1031370 | AM4: =AM6+AM8 -> 1186064 | AN4: =AN6+AN8 -> 1186064 | AO4: =AO6+AO8 -> 1293888 | AP4: =AP6+AP8 -> 1293888 | AQ4: =AQ6+AQ8 -> 1401712 | AR4: =AR6+AR8 -> 1401712 | AS4: =AS6+AS8 -> 1509536 | AT4: =AT6+AT8 -> 1509536 | ... AW4: =AW6+AW8 -> 1725184 | AX4: =SUM(AL4:AW4) -> 16773674 | AY4: =IF(AX4=0,"",AX4/AX$3) -> 0.95884226 | BA4: 飲食収入 | BC4: =SUM(BC5:BC15) -> 29000 | BD4: =SUM(BD5:BD15) -> 29000 | BE4: =SUM(BE5:BE15) -> 29000 | BF4: =SUM(BF5:BF15) -> 29000 | BG4: =SUM(BG5:BG15) -> 29000 | BH4: =SUM(BH5:BH15) -> 28000 | BI4: =SUM(BI5:BI15) -> 29000 | BJ4: =SUM(BJ5:BJ15) -> 30000 | ... BN4: =SUM(BN5:BN15) -> 30000 | BO4: =SUM(BC4:BN4) -> 352000 | BP4: =IF(BO4=0,"",BO4/BO$3) -> 1 | BR4: 飲食収入 | BT4: =SUM(BT5:BT8) -> 29000 | BU4: =SUM(BU5:BU8) -> 29000 | BV4: =SUM(BV5:BV8) -> 29000 | BW4: =SUM(BW5:BW8) -> 29000 | BX4: =SUM(BX5:BX8) -> 29000 | BY4: =SUM(BY5:BY8) -> 28000 | BZ4: =SUM(BZ5:BZ8) -> 29000 | CA4: =SUM(CA5:CA8) -> 30000 | ... CE4: =SUM(CE5:CE8) -> 30000 | CF4: =SUM(BT4:CE4) -> 352000 | CG4: =IF(CF4=0,"",CF4/CF$3) -> 1 | CI4: 飲食収入 | CK4: =((CK5*'売上計画 '!$C$4)+(CK6*'売上計画 '!$C$5)+(CK7*'売上計画 '!$C$6)+(CK8*'売上計画 '!$C$7))*$E$1 -> 0 | CL4: =((CL5*'売上計画 '!$C$4)+(CL6*'売上計画 '!$C$5)+(CL7*'売上計画 '!$C$6)+(CL8*'売上計画 '!$C$7))*$E$1 -> 0 | CM4: =((CM5*'売上計画 '!$C$4)+(CM6*'売上計画 '!$C$5)+(CM7*'売上計画 '!$C$6)+(CM8*'売上計画 '!$C$7))*$E$1 -> 0 | CN4: =((CN5*'売上計画 '!$C$4)+(CN6*'売上計画 '!$C$5)+(CN7*'売上計画 '!$C$6)+(CN8*'売上計画 '!$C$7))*$E$1 -> 0 | CO4: =((CO5*'売上計画 '!$C$4)+(CO6*'売上計画 '!$C$5)+(CO7*'売上計画 '!$C$6)+(CO8*'売上計画 '!$C$7))*$E$1 -> 0 | CP4: =((CP5*'売上計画 '!$C$4)+(CP6*'売上計画 '!$C$5)+(CP7*'売上計画 '!$C$6)+(CP8*'売上計画 '!$C$7))*$E$1 -> 0 | CQ4: =((CQ5*'売上計画 '!$C$4)+(CQ6*'売上計画 '!$C$5)+(CQ7*'売上計画 '!$C$6)+(CQ8*'売上計画 '!$C$7))*$E$1 -> 0 | CR4: =((CR5*'売上計画 '!$C$4)+(CR6*'売上計画 '!$C$5)+(CR7*'売上計画 '!$C$6)+(CR8*'売上計画 '!$C$7))*$E$1 -> 0 | ... CV4: =((CV5*'売上計画 '!$C$4)+(CV6*'売上計画 '!$C$5)+(CV7*'売上計画 '!$C$6)+(CV8*'売上計画 '!$C$7))*$E$1 -> 0 | CW4: =SUM(CK4:CV4) -> 0 | CX4: =IF(CW4=0,"",CW4/CW$3) | CZ4: 飲食収入 | DB4: =((DB5*'売上計画 '!$C$4)+(DB6*'売上計画 '!$C$5)+(DB7*'売上計画 '!$C$6)+(DB8*'売上計画 '!$C$7))*$E$1 -> 0 | DC4: =((DC5*'売上計画 '!$C$4)+(DC6*'売上計画 '!$C$5)+(DC7*'売上計画 '!$C$6)+(DC8*'売上計画 '!$C$7))*$E$1 -> 0 | DD4: =((DD5*'売上計画 '!$C$4)+(DD6*'売上計画 '!$C$5)+(DD7*'売上計画 '!$C$6)+(DD8*'売上計画 '!$C$7))*$E$1 -> 0 | DE4: =((DE5*'売上計画 '!$C$4)+(DE6*'売上計画 '!$C$5)+(DE7*'売上計画 '!$C$6)+(DE8*'売上計画 '!$C$7))*$E$1 -> 0 | DF4: =((DF5*'売上計画 '!$C$4)+(DF6*'売上計画 '!$C$5)+(DF7*'売上計画 '!$C$6)+(DF8*'売上計画 '!$C$7))*$E$1 -> 0 | DG4: =((DG5*'売上計画 '!$C$4)+(DG6*'売上計画 '!$C$5)+(DG7*'売上計画 '!$C$6)+(DG8*'売上計画 '!$C$7))*$E$1 -> 0 | DH4: =((DH5*'売上計画 '!$C$4)+(DH6*'売上計画 '!$C$5)+(DH7*'売上計画 '!$C$6)+(DH8*'売上計画 '!$C$7))*$E$1 -> 0 | DI4: =((DI5*'売上計画 '!$C$4)+(DI6*'売上計画 '!$C$5)+(DI7*'売上計画 '!$C$6)+(DI8*'売上計画 '!$C$7))*$E$1 -> 0 | ... DM4: =((DM5*'売上計画 '!$C$4)+(DM6*'売上計画 '!$C$5)+(DM7*'売上計画 '!$C$6)+(DM8*'売上計画 '!$C$7))*$E$1 -> 0 | DN4: =SUM(DB4:DM4) -> 0 | DO4: =IF(DN4=0,"",DN4/DN$3) | DQ4: 飲食収入 | DS4: =((DS5*'売上計画 '!$C$4)+(DS6*'売上計画 '!$C$5)+(DS7*'売上計画 '!$C$6)+(DS8*'売上計画 '!$C$7))*$E$1 -> 0 | DT4: =((DT5*'売上計画 '!$C$4)+(DT6*'売上計画 '!$C$5)+(DT7*'売上計画 '!$C$6)+(DT8*'売上計画 '!$C$7))*$E$1 -> 0 | DU4: =((DU5*'売上計画 '!$C$4)+(DU6*'売上計画 '!$C$5)+(DU7*'売上計画 '!$C$6)+(DU8*'売上計画 '!$C$7))*$E$1 -> 0 | DV4: =((DV5*'売上計画 '!$C$4)+(DV6*'売上計画 '!$C$5)+(DV7*'売上計画 '!$C$6)+(DV8*'売上計画 '!$C$7))*$E$1 -> 0 | DW4: =((DW5*'売上計画 '!$C$4)+(DW6*'売上計画 '!$C$5)+(DW7*'売上計画 '!$C$6)+(DW8*'売上計画 '!$C$7))*$E$1 -> 0 | DX4: =((DX5*'売上計画 '!$C$4)+(DX6*'売上計画 '!$C$5)+(DX7*'売上計画 '!$C$6)+(DX8*'売上計画 '!$C$7))*$E$1 -> 0 | DY4: =((DY5*'売上計画 '!$C$4)+(DY6*'売上計画 '!$C$5)+(DY7*'売上計画 '!$C$6)+(DY8*'売上計画 '!$C$7))*$E$1 -> 0 | DZ4: =((DZ5*'売上計画 '!$C$4)+(DZ6*'売上計画 '!$C$5)+(DZ7*'売上計画 '!$C$6)+(DZ8*'売上計画 '!$C$7))*$E$1 -> 0 | ... ED4: =((ED5*'売上計画 '!$C$4)+(ED6*'売上計画 '!$C$5)+(ED7*'売上計画 '!$C$6)+(ED8*'売上計画 '!$C$7))*$E$1 -> 0 | EE4: =SUM(DS4:ED4) -> 0 | EF4: =IF(EE4=0,"",EE4/EE$3) | EH4: 飲食収入 | EJ4: =((EJ5*'売上計画 '!$C$4)+(EJ6*'売上計画 '!$C$5)+(EJ7*'売上計画 '!$C$6)+(EJ8*'売上計画 '!$C$7))*$E$1 -> 0 | EK4: =((EK5*'売上計画 '!$C$4)+(EK6*'売上計画 '!$C$5)+(EK7*'売上計画 '!$C$6)+(EK8*'売上計画 '!$C$7))*$E$1 -> 0 | EL4: =((EL5*'売上計画 '!$C$4)+(EL6*'売上計画 '!$C$5)+(EL7*'売上計画 '!$C$6)+(EL8*'売上計画 '!$C$7))*$E$1 -> 0 | EM4: =((EM5*'売上計画 '!$C$4)+(EM6*'売上計画 '!$C$5)+(EM7*'売上計画 '!$C$6)+(EM8*'売上計画 '!$C$7))*$E$1 -> 0 | EN4: =((EN5*'売上計画 '!$C$4)+(EN6*'売上計画 '!$C$5)+(EN7*'売上計画 '!$C$6)+(EN8*'売上計画 '!$C$7))*$E$1 -> 0 | EO4: =((EO5*'売上計画 '!$C$4)+(EO6*'売上計画 '!$C$5)+(EO7*'売上計画 '!$C$6)+(EO8*'売上計画 '!$C$7))*$E$1 -> 0 | EP4: =((EP5*'売上計画 '!$C$4)+(EP6*'売上計画 '!$C$5)+(EP7*'売上計画 '!$C$6)+(EP8*'売上計画 '!$C$7))*$E$1 -> 0 | EQ4: =((EQ5*'売上計画 '!$C$4)+(EQ6*'売上計画 '!$C$5)+(EQ7*'売上計画 '!$C$6)+(EQ8*'売上計画 '!$C$7))*$E$1 -> 0 | ... EU4: =((EU5*'売上計画 '!$C$4)+(EU6*'売上計画 '!$C$5)+(EU7*'売上計画 '!$C$6)+(EU8*'売上計画 '!$C$7))*$E$1 -> 0 | EV4: =SUM(EJ4:EU4) -> 0 | EW4: =IF(EV4=0,"",EV4/EV$3) | EY4: 飲食収入 | FA4: =((FA5*'売上計画 '!$C$4)+(FA6*'売上計画 '!$C$5)+(FA7*'売上計画 '!$C$6)+(FA8*'売上計画 '!$C$7))*$E$1 -> 0 | FB4: =((FB5*'売上計画 '!$C$4)+(FB6*'売上計画 '!$C$5)+(FB7*'売上計画 '!$C$6)+(FB8*'売上計画 '!$C$7))*$E$1 -> 0 | FC4: =((FC5*'売上計画 '!$C$4)+(FC6*'売上計画 '!$C$5)+(FC7*'売上計画 '!$C$6)+(FC8*'売上計画 '!$C$7))*$E$1 -> 0 | FD4: =((FD5*'売上計画 '!$C$4)+(FD6*'売上計画 '!$C$5)+(FD7*'売上計画 '!$C$6)+(FD8*'売上計画 '!$C$7))*$E$1 -> 0 | FE4: =((FE5*'売上計画 '!$C$4)+(FE6*'売上計画 '!$C$5)+(FE7*'売上計画 '!$C$6)+(FE8*'売上計画 '!$C$7))*$E$1 -> 0 | FF4: =((FF5*'売上計画 '!$C$4)+(FF6*'売上計画 '!$C$5)+(FF7*'売上計画 '!$C$6)+(FF8*'売上計画 '!$C$7))*$E$1 -> 0 | FG4: =((FG5*'売上計画 '!$C$4)+(FG6*'売上計画 '!$C$5)+(FG7*'売上計画 '!$C$6)+(FG8*'売上計画 '!$C$7))*$E$1 -> 0 | FH4: =((FH5*'売上計画 '!$C$4)+(FH6*'売上計画 '!$C$5)+(FH7*'売上計画 '!$C$6)+(FH8*'売上計画 '!$C$7))*$E$1 -> 0 | ... FL4: =((FL5*'売上計画 '!$C$4)+(FL6*'売上計画 '!$C$5)+(FL7*'売上計画 '!$C$6)+(FL8*'売上計画 '!$C$7))*$E$1 -> 0 | FM4: =SUM(FA4:FL4) -> 0 | FN4: =IF(FM4=0,"",FM4/FM$3)
C5: 利用者数 | P5: =SUM(D5:O5) -> 0 | Q5: =IF(P5=0,"",P5/$P$3) | T5: =IF(C5="","",C5) -> 利用者数 | U5: 10 | V5: 11 | W5: 11 | X5: 12 | Y5: 12 | Z5: 13 | AA5: 13 | AB5: 14 | AC5: 14 | AD5: 15 | AE5: 15 | AF5: 16 | AG5: =SUM(U5:AF5) -> 156 | AH5: =IF(AG5=0,"",AG5/$P$3) -> 0.00156 | AK5: =IF(T5="","",T5) -> 利用者数 | AL5: 10 | AM5: 11 | AN5: 11 | AO5: 12 | AP5: 12 | AQ5: 13 | AR5: 13 | AS5: 14 | AT5: 14 | AU5: 15 | AV5: 15 | AW5: 16 | AX5: =SUM(AL5:AW5) -> 156 | AY5: =IF(AX5=0,"",AX5/$P$3) -> 0.00156 | BB5: =AK5 -> 利用者数 | BC5: 12000 | BD5: 12000 | BE5: 12000 | BF5: 12000 | BG5: 12000 | BH5: 11000 | BI5: 12000 | BJ5: 13000 | BK5: 13000 | BL5: 13000 | BM5: 13000 | BN5: 13000 | BO5: =SUM(BC5:BN5) -> 148000 | BP5: =IF(BO5=0,"",BO5/BO$3) -> 0.42045455 | BS5: =BB5 -> 利用者数 | BT5: 12000 | BU5: 12000 | BV5: 12000 | BW5: 12000 | BX5: 12000 | BY5: 11000 | BZ5: 12000 | CA5: 13000 | CB5: 13000 | CC5: 13000 | CD5: 13000 | CE5: 13000 | CF5: =SUM(BT5:CE5) -> 148000 | CG5: =IF(CF5=0,"",CF5/CF$3) -> 0.42045455 | CJ5: =BS5 -> 利用者数 | CK5: 5 | CL5: 5 | CM5: 5 | CN5: 5 | CO5: 5 | CP5: 5 | CQ5: 6 | CR5: 6 | CS5: 6 | CT5: 6 | CU5: 6 | CV5: 6 | CW5: =SUM(CK5:CV5)*5000 -> 330000 | CX5: =IF(CW5=0,"",CW5/CW$3) -> #DIV/0! | DA5: =CJ5 -> 利用者数 | DB5: 6 | DC5: 6 | DD5: 6 | DE5: 6 | DF5: 6 | DG5: 6 | DH5: 7 | DI5: 7 | DJ5: 7 | DK5: 7 | DL5: 7 | DM5: 7 | DN5: =SUM(DB5:DM5)*5000 -> 390000 | DO5: =IF(DN5=0,"",DN5/DN$3) -> #DIV/0! | DR5: =DA5 -> 利用者数 | DS5: 7 | DT5: 7 | DU5: 7 | DV5: 7 | DW5: 8 | DX5: 8 | DY5: 8 | DZ5: 8 | EA5: 8 | EB5: 8 | EC5: 8 | ED5: 8 | EE5: =SUM(DS5:ED5)*5000 -> 460000 | EF5: =IF(EE5=0,"",EE5/EE$3) -> #DIV/0! | EI5: =DR5 -> 利用者数 | EJ5: =ED5 -> 8 | EK5: =EJ5 -> 8 | EL5: =EK5 -> 8 | EM5: =EL5 -> 8 | EN5: =EM5 -> 8 | EO5: 9 | EP5: =EO5 -> 9 | EQ5: =EP5 -> 9 | ER5: =EQ5 -> 9 | ES5: =ER5 -> 9 | ET5: =ES5 -> 9 | EU5: =ET5 -> 9 | EV5: =SUM(EJ5:EU5)*5000 -> 515000 | EW5: =IF(EV5=0,"",EV5/EV$3) -> #DIV/0! | EZ5: =EI5 -> 利用者数 | FA5: 10 | FB5: =FA5 -> 10 | FC5: =FB5 -> 10 | FD5: =FC5 -> 10 | FE5: =FD5 -> 10 | FF5: =FE5 -> 10 | FG5: =FF5 -> 10 | FH5: =FG5 -> 10 | FI5: =FH5 -> 10 | ... FL5: =FK5 -> 10 | FM5: =SUM(FA5:FL5)*5000 -> 600000 | FN5: =IF(FM5=0,"",FM5/FM$3) -> #DIV/0!
C6: 訓練給付金等 | E6: =5860*23*E5*0.8 -> 0 | F6: =5860*23*F5*0.8 -> 0 | G6: =5860*23*G5*0.8 -> 0 | H6: =5860*23*H5*0.8 -> 0 | I6: =5860*23*I5*0.8 -> 0 | J6: =5860*23*J5*0.8 -> 0 | K6: =5860*23*K5*0.8 -> 0 | L6: =5860*23*L5*0.8 -> 0 | ... O6: =5860*23*O5*0.8 -> 0 | P6: =SUM(D6:O6) -> 0 | Q6: =IF(P6=0,"",P6/$P$3) | T6: =IF(C6="","",C6) -> 訓練給付金等 | U6: =5860*22*U5*0.8 -> 1031360 | V6: =5860*23*V5*0.8 -> 1186064 | W6: =5860*23*W5*0.8 -> 1186064 | X6: =5860*23*X5*0.8 -> 1293888 | Y6: =5860*23*Y5*0.8 -> 1293888 | Z6: =5860*23*Z5*0.8 -> 1401712 | AA6: =5860*23*AA5*0.8 -> 1401712 | AB6: =5860*23*AB5*0.8 -> 1509536 | AC6: =5860*23*AC5*0.8 -> 1509536 | ... AF6: =5860*23*AF5*0.8 -> 1725184 | AG6: =SUM(U6:AF6) -> 16773664 | AH6: =IF(AG6=0,"",AG6/$P$3) -> 167.73664 | AK6: =IF(T6="","",T6) -> 訓練給付金等 | AL6: =5860*22*AL5*0.8 -> 1031360 | AM6: =5860*23*AM5*0.8 -> 1186064 | AN6: =5860*23*AN5*0.8 -> 1186064 | AO6: =5860*23*AO5*0.8 -> 1293888 | AP6: =5860*23*AP5*0.8 -> 1293888 | AQ6: =5860*23*AQ5*0.8 -> 1401712 | AR6: =5860*23*AR5*0.8 -> 1401712 | AS6: =5860*23*AS5*0.8 -> 1509536 | AT6: =5860*23*AT5*0.8 -> 1509536 | ... AW6: =5860*23*AW5*0.8 -> 1725184 | AX6: =SUM(AL6:AW6) -> 16773664 | AY6: =IF(AX6=0,"",AX6/$P$3) -> 167.73664 | BB6: =AK6 -> 訓練給付金等 | BC6: 6000 | BD6: 6000 | BE6: 6000 | BF6: 6000 | BG6: 6000 | BH6: 6000 | BI6: 6000 | BJ6: 6000 | BK6: 6000 | BL6: 6000 | BM6: 6000 | BN6: 6000 | BO6: =SUM(BC6:BN6) -> 72000 | BP6: =IF(BO6=0,"",BO6/BO$3) -> 0.20454545 | BS6: =BB6 -> 訓練給付金等 | BT6: 6000 | BU6: 6000 | BV6: 6000 | BW6: 6000 | BX6: 6000 | BY6: 6000 | BZ6: 6000 | CA6: 6000 | CB6: 6000 | CC6: 6000 | CD6: 6000 | CE6: 6000 | CF6: =SUM(BT6:CE6) -> 72000 | CG6: =IF(CF6=0,"",CF6/CF$3) -> 0.20454545 | CJ6: =BS6 -> 訓練給付金等 | CK6: 4 | CL6: 4 | CM6: 4 | CN6: 4 | CO6: 4 | CP6: 4 | CQ6: 5 | CR6: 5 | CS6: 5 | CT6: 5 | CU6: 5 | CV6: 5 | CW6: =SUM(CK6:CV6)*10000 -> 540000 | CX6: =IF(CW6=0,"",CW6/CW$3) -> #DIV/0! | DA6: =CJ6 -> 訓練給付金等 | DB6: 5 | DC6: 5 | DD6: 5 | DE6: 5 | DF6: 5 | DG6: 5 | DH6: 6 | DI6: 6 | DJ6: 6 | DK6: 6 | DL6: 6 | DM6: 6 | DN6: =SUM(DB6:DM6)*10000 -> 660000 | DO6: =IF(DN6=0,"",DN6/DN$3) -> #DIV/0! | DR6: =DA6 -> 訓練給付金等 | DS6: 6 | DT6: 6 | DU6: 6 | DV6: 6 | DW6: 7 | DX6: 8 | DY6: 8 | DZ6: 8 | EA6: 8 | EB6: 8 | EC6: 8 | ED6: 8 | EE6: =SUM(DS6:ED6)*10000 -> 870000 | EF6: =IF(EE6=0,"",EE6/EE$3) -> #DIV/0! | EI6: =DR6 -> 訓練給付金等 | EJ6: =ED6 -> 8 | EK6: =EJ6 -> 8 | EL6: =EK6 -> 8 | EM6: =EL6 -> 8 | EN6: =EM6 -> 8 | EO6: 9 | EP6: =EO6 -> 9 | EQ6: =EP6 -> 9 | ER6: =EQ6 -> 9 | ES6: =ER6 -> 9 | ET6: =ES6 -> 9 | EU6: =ET6 -> 9 | EV6: =SUM(EJ6:EU6)*10000 -> 1030000 | EW6: =IF(EV6=0,"",EV6/EV$3) -> #DIV/0! | EZ6: =EI6 -> 訓練給付金等 | FA6: 10 | FB6: =FA6 -> 10 | FC6: =FB6 -> 10 | FD6: =FC6 -> 10 | FE6: =FD6 -> 10 | FF6: =FE6 -> 10 | FG6: =FF6 -> 10 | FH6: =FG6 -> 10 | FI6: =FH6 -> 10 | ... FL6: =FK6 -> 10 | FM6: =SUM(FA6:FL6)*10000 -> 1200000 | FN6: =IF(FM6=0,"",FM6/FM$3) -> #DIV/0!
C7: 利用者数 | P7: =SUM(D7:O7) -> 0 | Q7: =IF(P7=0,"",P7/$P$3) | T7: =IF(C7="","",C7) -> 利用者数 | AG7: =SUM(U7:AF7) -> 0 | AH7: =IF(AG7=0,"",AG7/AG$3) | AK7: =IF(T7="","",T7) -> 利用者数 | AX7: =SUM(AL7:AW7) -> 0 | AY7: =IF(AX7=0,"",AX7/AX$3) | BB7: =AK7 -> 利用者数 | BC7: 6000 | BD7: 6000 | BE7: 6000 | BF7: 6000 | BG7: 6000 | BH7: 6000 | BI7: 6000 | BJ7: 6000 | BK7: 6000 | BL7: 6000 | BM7: 6000 | BN7: 6000 | BO7: =SUM(BC7:BN7) -> 72000 | BP7: =IF(BO7=0,"",BO7/BO$3) -> 0.20454545 | BS7: =BB7 -> 利用者数 | BT7: 6000 | BU7: 6000 | BV7: 6000 | BW7: 6000 | BX7: 6000 | BY7: 6000 | BZ7: 6000 | CA7: 6000 | CB7: 6000 | CC7: 6000 | CD7: 6000 | CE7: 6000 | CF7: =SUM(BT7:CE7) -> 72000 | CG7: =IF(CF7=0,"",CF7/CF$3) -> 0.20454545 | CJ7: =BS7 -> 利用者数 | CK7: 5 | CL7: 5 | CM7: 5 | CN7: 5 | CO7: 5 | CP7: 5 | CQ7: 5 | CR7: 5 | CS7: 5 | CT7: 5 | CU7: 5 | CV7: 5 | CW7: =SUM(CK7:CV7)*3000 -> 180000 | CX7: =IF(CW7=0,"",CW7/CW$3) -> #DIV/0! | DA7: =CJ7 -> 利用者数 | DB7: 6 | DC7: 6 | DD7: 6 | DE7: 6 | DF7: 6 | DG7: 6 | DH7: 5 | DI7: 5 | DJ7: 5 | DK7: 5 | DL7: 5 | DM7: 5 | DN7: =SUM(DB7:DM7)*3000 -> 198000 | DO7: =IF(DN7=0,"",DN7/DN$3) -> #DIV/0! | DR7: =DA7 -> 利用者数 | DS7: 6 | DT7: 6 | DU7: 6 | DV7: 6 | DW7: 6 | DX7: 6 | DY7: 6 | DZ7: 6 | EA7: 6 | EB7: 6 | EC7: 6 | ED7: 6 | EE7: =SUM(DS7:ED7)*3000 -> 216000 | EF7: =IF(EE7=0,"",EE7/EE$3) -> #DIV/0! | EI7: =DR7 -> 利用者数 | EJ7: =ED7 -> 6 | EK7: =EJ7 -> 6 | EL7: =EK7 -> 6 | EM7: =EL7 -> 6 | EN7: =EM7 -> 6 | EO7: =EN7 -> 6 | EP7: =EO7 -> 6 | EQ7: =EP7 -> 6 | ER7: =EQ7 -> 6 | ... ET7: =ES7 -> 6 | EU7: 7 | EV7: =SUM(EJ7:EU7)*3000 -> 219000 | EW7: =IF(EV7=0,"",EV7/EV$3) -> #DIV/0! | EZ7: =EI7 -> 利用者数 | FA7: 10 | FB7: =FA7 -> 10 | FC7: =FB7 -> 10 | FD7: =FC7 -> 10 | FE7: =FD7 -> 10 | FF7: =FE7 -> 10 | FG7: =FF7 -> 10 | FH7: =FG7 -> 10 | FI7: =FH7 -> 10 | ... FL7: =FK7 -> 10 | FM7: =SUM(FA7:FL7)*3000 -> 360000 | FN7: =IF(FM7=0,"",FM7/FM$3) -> #DIV/0!
C8: 訓練給付金等 | E8: =5860*23*E7*0.8 -> 0 | F8: =5860*23*F7*0.8 -> 0 | G8: =5860*23*G7*0.8 -> 0 | H8: =5860*23*H7*0.8 -> 0 | I8: =5860*23*I7*0.8 -> 0 | J8: =5860*23*J7*0.8 -> 0 | K8: =5860*23*K7*0.8 -> 0 | L8: =5860*23*L7*0.8 -> 0 | ... O8: =5860*23*O7*0.8 -> 0 | P8: =SUM(D8:O8) -> 0 | Q8: =IF(P8=0,"",P8/$P$3) | T8: =IF(C8="","",C8) -> 訓練給付金等 | V8: =5860*23*V7*0.8 -> 0 | W8: =5860*23*W7*0.8 -> 0 | X8: =5860*23*X7*0.8 -> 0 | Y8: =5860*23*Y7*0.8 -> 0 | Z8: =5860*23*Z7*0.8 -> 0 | AA8: =5860*23*AA7*0.8 -> 0 | AB8: =5860*23*AB7*0.8 -> 0 | AC8: =5860*23*AC7*0.8 -> 0 | ... AF8: =5860*23*AF7*0.8 -> 0 | AG8: =SUM(U8:AF8) -> 0 | AH8: =IF(AG8=0,"",AG8/AG$3) | AK8: =IF(T8="","",T8) -> 訓練給付金等 | AM8: =5860*23*AM7*0.8 -> 0 | AN8: =5860*23*AN7*0.8 -> 0 | AO8: =5860*23*AO7*0.8 -> 0 | AP8: =5860*23*AP7*0.8 -> 0 | AQ8: =5860*23*AQ7*0.8 -> 0 | AR8: =5860*23*AR7*0.8 -> 0 | AS8: =5860*23*AS7*0.8 -> 0 | AT8: =5860*23*AT7*0.8 -> 0 | ... AW8: =5860*23*AW7*0.8 -> 0 | AX8: =SUM(AL8:AW8) -> 0 | AY8: =IF(AX8=0,"",AX8/AX$3) | BB8: =AK8 -> 訓練給付金等 | BC8: 5000 | BD8: 5000 | BE8: 5000 | BF8: 5000 | BG8: 5000 | BH8: 5000 | BI8: 5000 | BJ8: 5000 | BK8: 5000 | BL8: 5000 | BM8: 5000 | BN8: 5000 | BO8: =SUM(BC8:BN8) -> 60000 | BP8: =IF(BO8=0,"",BO8/BO$3) -> 0.17045455 | BS8: =BB8 -> 訓練給付金等 | BT8: 5000 | BU8: 5000 | BV8: 5000 | BW8: 5000 | BX8: 5000 | BY8: 5000 | BZ8: 5000 | CA8: 5000 | CB8: 5000 | CC8: 5000 | CD8: 5000 | CE8: 5000 | CF8: =SUM(BT8:CE8) -> 60000 | CG8: =IF(CF8=0,"",CF8/CF$3) -> 0.17045455 | CJ8: =BS8 -> 訓練給付金等 | CK8: 4 | CL8: 4 | CM8: 4 | CN8: 4 | CO8: 4 | CP8: 4 | CQ8: 4 | CR8: 4 | CS8: 4 | CT8: 4 | CU8: 4 | CV8: 4 | CW8: =SUM(CK8:CV8)*2500 -> 120000 | CX8: =IF(CW8=0,"",CW8/CW$3) -> #DIV/0! | DA8: =CJ8 -> 訓練給付金等 | DB8: 4 | DC8: 4 | DD8: 4 | DE8: 4 | DF8: 4 | DG8: 4 | DH8: 4 | DI8: 4 | DJ8: 4 | DK8: 4 | DL8: 4 | DM8: 4 | DN8: =SUM(DB8:DM8)*2500 -> 120000 | DO8: =IF(DN8=0,"",DN8/DN$3) -> #DIV/0! | DR8: =DA8 -> 訓練給付金等 | DS8: 4 | DT8: 4 | DU8: 4 | DV8: 4 | DW8: 4 | DX8: 4 | DY8: 4 | DZ8: 4 | EA8: 4 | EB8: 4 | EC8: 4 | ED8: 4 | EE8: =SUM(DS8:ED8)*2500 -> 120000 | EF8: =IF(EE8=0,"",EE8/EE$3) -> #DIV/0! | EI8: =DR8 -> 訓練給付金等 | EJ8: =ED8 -> 4 | EK8: =EJ8 -> 4 | EL8: =EK8 -> 4 | EM8: =EL8 -> 4 | EN8: =EM8 -> 4 | EO8: =EN8 -> 4 | EP8: =EO8 -> 4 | EQ8: =EP8 -> 4 | ER8: =EQ8 -> 4 | ... ET8: =ES8 -> 4 | EU8: 5 | EV8: =SUM(EJ8:EU8)*2500 -> 122500 | EW8: =IF(EV8=0,"",EV8/EV$3) -> #DIV/0! | EZ8: =EI8 -> 訓練給付金等 | FA8: =EU8 -> 5 | FB8: =FA8 -> 5 | FC8: =FB8 -> 5 | FD8: =FC8 -> 5 | FE8: =FD8 -> 5 | FF8: =FE8 -> 5 | FG8: =FF8 -> 5 | FH8: =FG8 -> 5 | FI8: =FH8 -> 5 | ... FL8: =FK8 -> 5 | FM8: =SUM(FA8:FL8)*2500 -> 150000 | FN8: =IF(FM8=0,"",FM8/FM$3) -> #DIV/0!
B9: 利用者作業収入 | D9: =SUM(D10:D12) -> 0 | E9: =SUM(E10:E12) -> 0 | F9: =SUM(F10:F12) -> 0 | G9: =SUM(G10:G12) -> 0 | H9: =SUM(H10:H12) -> 0 | I9: =SUM(I10:I12) -> 0 | J9: =SUM(J10:J12) -> 0 | K9: =SUM(K10:K12) -> 0 | ... O9: =SUM(O10:O12) -> 0 | P9: =SUM(D9:O9) -> 0 | Q9: =IF(P9=0,"",P9/$P$3) | S9: =IF(B9="","",B9) -> 利用者作業収入 | U9: =SUM(U10:U12) -> 0 | V9: =SUM(V10:V12) -> 0 | W9: =SUM(W10:W12) -> 0 | X9: =SUM(X10:X12) -> 60000 | Y9: =SUM(Y10:Y12) -> 60000 | Z9: =SUM(Z10:Z12) -> 60000 | AA9: =SUM(AA10:AA12) -> 60000 | AB9: =SUM(AB10:AB12) -> 60000 | ... AF9: =SUM(AF10:AF12) -> 60000 | AG9: =SUM(U9:AF9) -> 540000 | AH9: =IF(AG9=0,"",AG9/AG$3) -> 0.031189221 | AJ9: =IF(S9="","",S9) -> 利用者作業収入 | AL9: =SUM(AL10:AL12) -> 60000 | AM9: =SUM(AM10:AM12) -> 60000 | AN9: =SUM(AN10:AN12) -> 60000 | AO9: =SUM(AO10:AO12) -> 60000 | AP9: =SUM(AP10:AP12) -> 60000 | AQ9: =SUM(AQ10:AQ12) -> 60000 | AR9: =SUM(AR10:AR12) -> 60000 | AS9: =SUM(AS10:AS12) -> 60000 | ... AW9: =SUM(AW10:AW12) -> 60000 | AX9: =SUM(AL9:AW9) -> 720000 | AY9: =IF(AX9=0,"",AX9/AX$3) -> 0.041157735 | BA9: FCロイヤリティ | BC9: =(((BC10*'売上計画 '!$C$11)+(BC11*'売上計画 '!$C$12)+(BC12*'売上計画 '!$C$13)+(BC13*'売上計画 '!$C$14))*0.06)*$E$1 -> 0 | BD9: =(((BD10*'売上計画 '!$C$11)+(BD11*'売上計画 '!$C$12)+(BD12*'売上計画 '!$C$13)+(BD13*'売上計画 '!$C$14))*0.06)*$E$1 -> 0 | BE9: =(((BE10*'売上計画 '!$C$11)+(BE11*'売上計画 '!$C$12)+(BE12*'売上計画 '!$C$13)+(BE13*'売上計画 '!$C$14))*0.06)*$E$1 -> 0 | BF9: =(((BF10*'売上計画 '!$C$11)+(BF11*'売上計画 '!$C$12)+(BF12*'売上計画 '!$C$13)+(BF13*'売上計画 '!$C$14))*0.06)*$E$1 -> 0 | BG9: =(((BG10*'売上計画 '!$C$11)+(BG11*'売上計画 '!$C$12)+(BG12*'売上計画 '!$C$13)+(BG13*'売上計画 '!$C$14))*0.06)*$E$1 -> 0 | BH9: =(((BH10*'売上計画 '!$C$11)+(BH11*'売上計画 '!$C$12)+(BH12*'売上計画 '!$C$13)+(BH13*'売上計画 '!$C$14))*0.06)*$E$1 -> 0 | BI9: =(((BI10*'売上計画 '!$C$11)+(BI11*'売上計画 '!$C$12)+(BI12*'売上計画 '!$C$13)+(BI13*'売上計画 '!$C$14))*0.06)*$E$1 -> 0 | BJ9: =(((BJ10*'売上計画 '!$C$11)+(BJ11*'売上計画 '!$C$12)+(BJ12*'売上計画 '!$C$13)+(BJ13*'売上計画 '!$C$14))*0.06)*$E$1 -> 0 | ... BN9: =(((BN10*'売上計画 '!$C$11)+(BN11*'売上計画 '!$C$12)+(BN12*'売上計画 '!$C$13)+(BN13*'売上計画 '!$C$14))*0.06)*$E$1 -> 0 | BO9: =SUM(BC9:BN9) -> 0 | BP9: =IF(BO9=0,"",BO9/BO$3) | BR9: FCロイヤリティ | BT9: =(((BT10*'売上計画 '!$C$11)+(BT11*'売上計画 '!$C$12)+(BT12*'売上計画 '!$C$13)+(BT13*'売上計画 '!$C$14))*0.06)*$E$1 -> 0 | BU9: =(((BU10*'売上計画 '!$C$11)+(BU11*'売上計画 '!$C$12)+(BU12*'売上計画 '!$C$13)+(BU13*'売上計画 '!$C$14))*0.06)*$E$1 -> 0 | BV9: =(((BV10*'売上計画 '!$C$11)+(BV11*'売上計画 '!$C$12)+(BV12*'売上計画 '!$C$13)+(BV13*'売上計画 '!$C$14))*0.06)*$E$1 -> 0 | BW9: =(((BW10*'売上計画 '!$C$11)+(BW11*'売上計画 '!$C$12)+(BW12*'売上計画 '!$C$13)+(BW13*'売上計画 '!$C$14))*0.06)*$E$1 -> 0 | BX9: =(((BX10*'売上計画 '!$C$11)+(BX11*'売上計画 '!$C$12)+(BX12*'売上計画 '!$C$13)+(BX13*'売上計画 '!$C$14))*0.06)*$E$1 -> 0 | BY9: =(((BY10*'売上計画 '!$C$11)+(BY11*'売上計画 '!$C$12)+(BY12*'売上計画 '!$C$13)+(BY13*'売上計画 '!$C$14))*0.06)*$E$1 -> 0 | BZ9: =(((BZ10*'売上計画 '!$C$11)+(BZ11*'売上計画 '!$C$12)+(BZ12*'売上計画 '!$C$13)+(BZ13*'売上計画 '!$C$14))*0.06)*$E$1 -> 0 | CA9: =(((CA10*'売上計画 '!$C$11)+(CA11*'売上計画 '!$C$12)+(CA12*'売上計画 '!$C$13)+(CA13*'売上計画 '!$C$14))*0.06)*$E$1 -> 0 | ... CE9: =(((CE10*'売上計画 '!$C$11)+(CE11*'売上計画 '!$C$12)+(CE12*'売上計画 '!$C$13)+(CE13*'売上計画 '!$C$14))*0.06)*$E$1 -> 0 | CF9: =SUM(BT9:CE9) -> 0 | CG9: =IF(CF9=0,"",CF9/CF$3) | CI9: FCロイヤリティ | CK9: =(((CK10*'売上計画 '!$C$11)+(CK11*'売上計画 '!$C$12)+(CK12*'売上計画 '!$C$13)+(CK13*'売上計画 '!$C$14))*0.06)*$E$1 -> 0 | CL9: =(((CL10*'売上計画 '!$C$11)+(CL11*'売上計画 '!$C$12)+(CL12*'売上計画 '!$C$13)+(CL13*'売上計画 '!$C$14))*0.06)*$E$1 -> 0 | CM9: =(((CM10*'売上計画 '!$C$11)+(CM11*'売上計画 '!$C$12)+(CM12*'売上計画 '!$C$13)+(CM13*'売上計画 '!$C$14))*0.06)*$E$1 -> 0 | CN9: =(((CN10*'売上計画 '!$C$11)+(CN11*'売上計画 '!$C$12)+(CN12*'売上計画 '!$C$13)+(CN13*'売上計画 '!$C$14))*0.06)*$E$1 -> 0 | CO9: =(((CO10*'売上計画 '!$C$11)+(CO11*'売上計画 '!$C$12)+(CO12*'売上計画 '!$C$13)+(CO13*'売上計画 '!$C$14))*0.06)*$E$1 -> 0 | CP9: =(((CP10*'売上計画 '!$C$11)+(CP11*'売上計画 '!$C$12)+(CP12*'売上計画 '!$C$13)+(CP13*'売上計画 '!$C$14))*0.06)*$E$1 -> 0 | CQ9: =(((CQ10*'売上計画 '!$C$11)+(CQ11*'売上計画 '!$C$12)+(CQ12*'売上計画 '!$C$13)+(CQ13*'売上計画 '!$C$14))*0.06)*$E$1 -> 0 | CR9: =(((CR10*'売上計画 '!$C$11)+(CR11*'売上計画 '!$C$12)+(CR12*'売上計画 '!$C$13)+(CR13*'売上計画 '!$C$14))*0.06)*$E$1 -> 0 | ... CV9: =(((CV10*'売上計画 '!$C$11)+(CV11*'売上計画 '!$C$12)+(CV12*'売上計画 '!$C$13)+(CV13*'売上計画 '!$C$14))*0.06)*$E$1 -> 0 | CW9: =SUM(CK9:CV9) -> 0 | CX9: =IF(CW9=0,"",CW9/CW$3) | CZ9: FCロイヤリティ | DB9: =(((DB10*'売上計画 '!$C$11)+(DB11*'売上計画 '!$C$12)+(DB12*'売上計画 '!$C$13)+(DB13*'売上計画 '!$C$14))*0.06)*$E$1 -> 0 | DC9: =(((DC10*'売上計画 '!$C$11)+(DC11*'売上計画 '!$C$12)+(DC12*'売上計画 '!$C$13)+(DC13*'売上計画 '!$C$14))*0.06)*$E$1 -> 0 | DD9: =(((DD10*'売上計画 '!$C$11)+(DD11*'売上計画 '!$C$12)+(DD12*'売上計画 '!$C$13)+(DD13*'売上計画 '!$C$14))*0.06)*$E$1 -> 0 | DE9: =(((DE10*'売上計画 '!$C$11)+(DE11*'売上計画 '!$C$12)+(DE12*'売上計画 '!$C$13)+(DE13*'売上計画 '!$C$14))*0.06)*$E$1 -> 0 | DF9: =(((DF10*'売上計画 '!$C$11)+(DF11*'売上計画 '!$C$12)+(DF12*'売上計画 '!$C$13)+(DF13*'売上計画 '!$C$14))*0.06)*$E$1 -> 0 | DG9: =(((DG10*'売上計画 '!$C$11)+(DG11*'売上計画 '!$C$12)+(DG12*'売上計画 '!$C$13)+(DG13*'売上計画 '!$C$14))*0.06)*$E$1 -> 0 | DH9: =(((DH10*'売上計画 '!$C$11)+(DH11*'売上計画 '!$C$12)+(DH12*'売上計画 '!$C$13)+(DH13*'売上計画 '!$C$14))*0.06)*$E$1 -> 0 | DI9: =(((DI10*'売上計画 '!$C$11)+(DI11*'売上計画 '!$C$12)+(DI12*'売上計画 '!$C$13)+(DI13*'売上計画 '!$C$14))*0.06)*$E$1 -> 0 | ... DM9: =(((DM10*'売上計画 '!$C$11)+(DM11*'売上計画 '!$C$12)+(DM12*'売上計画 '!$C$13)+(DM13*'売上計画 '!$C$14))*0.06)*$E$1 -> 0 | DN9: =SUM(DB9:DM9) -> 0 | DO9: =IF(DN9=0,"",DN9/DN$3) | DQ9: FCロイヤリティ | DS9: =(((DS10*'売上計画 '!$C$11)+(DS11*'売上計画 '!$C$12)+(DS12*'売上計画 '!$C$13)+(DS13*'売上計画 '!$C$14))*0.06)*$E$1 -> 0 | DT9: =(((DT10*'売上計画 '!$C$11)+(DT11*'売上計画 '!$C$12)+(DT12*'売上計画 '!$C$13)+(DT13*'売上計画 '!$C$14))*0.06)*$E$1 -> 0 | DU9: =(((DU10*'売上計画 '!$C$11)+(DU11*'売上計画 '!$C$12)+(DU12*'売上計画 '!$C$13)+(DU13*'売上計画 '!$C$14))*0.06)*$E$1 -> 0 | DV9: =(((DV10*'売上計画 '!$C$11)+(DV11*'売上計画 '!$C$12)+(DV12*'売上計画 '!$C$13)+(DV13*'売上計画 '!$C$14))*0.06)*$E$1 -> 0 | DW9: =(((DW10*'売上計画 '!$C$11)+(DW11*'売上計画 '!$C$12)+(DW12*'売上計画 '!$C$13)+(DW13*'売上計画 '!$C$14))*0.06)*$E$1 -> 0 | DX9: =(((DX10*'売上計画 '!$C$11)+(DX11*'売上計画 '!$C$12)+(DX12*'売上計画 '!$C$13)+(DX13*'売上計画 '!$C$14))*0.06)*$E$1 -> 0 | DY9: =(((DY10*'売上計画 '!$C$11)+(DY11*'売上計画 '!$C$12)+(DY12*'売上計画 '!$C$13)+(DY13*'売上計画 '!$C$14))*0.06)*$E$1 -> 0 | DZ9: =(((DZ10*'売上計画 '!$C$11)+(DZ11*'売上計画 '!$C$12)+(DZ12*'売上計画 '!$C$13)+(DZ13*'売上計画 '!$C$14))*0.06)*$E$1 -> 0 | ... ED9: =(((ED10*'売上計画 '!$C$11)+(ED11*'売上計画 '!$C$12)+(ED12*'売上計画 '!$C$13)+(ED13*'売上計画 '!$C$14))*0.06)*$E$1 -> 0 | EE9: =SUM(DS9:ED9) -> 0 | EF9: =IF(EE9=0,"",EE9/EE$3) | EH9: FCロイヤリティ | EJ9: =(((EJ10*'売上計画 '!$C$11)+(EJ11*'売上計画 '!$C$12)+(EJ12*'売上計画 '!$C$13)+(EJ13*'売上計画 '!$C$14))*0.06)*$E$1 -> 0 | EK9: =(((EK10*'売上計画 '!$C$11)+(EK11*'売上計画 '!$C$12)+(EK12*'売上計画 '!$C$13)+(EK13*'売上計画 '!$C$14))*0.06)*$E$1 -> 0 | EL9: =(((EL10*'売上計画 '!$C$11)+(EL11*'売上計画 '!$C$12)+(EL12*'売上計画 '!$C$13)+(EL13*'売上計画 '!$C$14))*0.06)*$E$1 -> 0 | EM9: =(((EM10*'売上計画 '!$C$11)+(EM11*'売上計画 '!$C$12)+(EM12*'売上計画 '!$C$13)+(EM13*'売上計画 '!$C$14))*0.06)*$E$1 -> 0 | EN9: =(((EN10*'売上計画 '!$C$11)+(EN11*'売上計画 '!$C$12)+(EN12*'売上計画 '!$C$13)+(EN13*'売上計画 '!$C$14))*0.06)*$E$1 -> 0 | EO9: =(((EO10*'売上計画 '!$C$11)+(EO11*'売上計画 '!$C$12)+(EO12*'売上計画 '!$C$13)+(EO13*'売上計画 '!$C$14))*0.06)*$E$1 -> 0 | EP9: =(((EP10*'売上計画 '!$C$11)+(EP11*'売上計画 '!$C$12)+(EP12*'売上計画 '!$C$13)+(EP13*'売上計画 '!$C$14))*0.06)*$E$1 -> 0 | EQ9: =(((EQ10*'売上計画 '!$C$11)+(EQ11*'売上計画 '!$C$12)+(EQ12*'売上計画 '!$C$13)+(EQ13*'売上計画 '!$C$14))*0.06)*$E$1 -> 0 | ... EU9: =(((EU10*'売上計画 '!$C$11)+(EU11*'売上計画 '!$C$12)+(EU12*'売上計画 '!$C$13)+(EU13*'売上計画 '!$C$14))*0.06)*$E$1 -> 0 | EV9: =SUM(EJ9:EU9) -> 0 | EW9: =IF(EV9=0,"",EV9/EV$3) | EY9: FCロイヤリティ | FA9: =(((FA10*'売上計画 '!$C$11)+(FA11*'売上計画 '!$C$12)+(FA12*'売上計画 '!$C$13)+(FA13*'売上計画 '!$C$14))*0.06)*$E$1 -> 0 | FB9: =(((FB10*'売上計画 '!$C$11)+(FB11*'売上計画 '!$C$12)+(FB12*'売上計画 '!$C$13)+(FB13*'売上計画 '!$C$14))*0.06)*$E$1 -> 0 | FC9: =(((FC10*'売上計画 '!$C$11)+(FC11*'売上計画 '!$C$12)+(FC12*'売上計画 '!$C$13)+(FC13*'売上計画 '!$C$14))*0.06)*$E$1 -> 0 | FD9: =(((FD10*'売上計画 '!$C$11)+(FD11*'売上計画 '!$C$12)+(FD12*'売上計画 '!$C$13)+(FD13*'売上計画 '!$C$14))*0.06)*$E$1 -> 0 | FE9: =(((FE10*'売上計画 '!$C$11)+(FE11*'売上計画 '!$C$12)+(FE12*'売上計画 '!$C$13)+(FE13*'売上計画 '!$C$14))*0.06)*$E$1 -> 0 | FF9: =(((FF10*'売上計画 '!$C$11)+(FF11*'売上計画 '!$C$12)+(FF12*'売上計画 '!$C$13)+(FF13*'売上計画 '!$C$14))*0.06)*$E$1 -> 0 | FG9: =(((FG10*'売上計画 '!$C$11)+(FG11*'売上計画 '!$C$12)+(FG12*'売上計画 '!$C$13)+(FG13*'売上計画 '!$C$14))*0.06)*$E$1 -> 0 | FH9: =(((FH10*'売上計画 '!$C$11)+(FH11*'売上計画 '!$C$12)+(FH12*'売上計画 '!$C$13)+(FH13*'売上計画 '!$C$14))*0.06)*$E$1 -> 0 | ... FL9: =(((FL10*'売上計画 '!$C$11)+(FL11*'売上計画 '!$C$12)+(FL12*'売上計画 '!$C$13)+(FL13*'売上計画 '!$C$14))*0.06)*$E$1 -> 0 | FM9: =SUM(FA9:FL9) -> 0 | FN9: =IF(FM9=0,"",FM9/FM$3)
P10: =SUM(D10:O10) -> 0 | Q10: =IF(P10=0,"",P10/$P$3) | T10: =IF(C10="","",C10) | X10: 60000 | Y10: 60000 | Z10: 60000 | AA10: 60000 | AB10: 60000 | AC10: 60000 | AD10: 60000 | AE10: 60000 | AF10: 60000 | AG10: =SUM(U10:AF10) -> 540000 | AH10: =IF(AG10=0,"",AG10/AG$3) -> 0.031189221 | AK10: =IF(T10="","",T10) | AL10: 60000 | AM10: 60000 | AN10: 60000 | AO10: 60000 | AP10: 60000 | AQ10: 60000 | AR10: 60000 | AS10: 60000 | AT10: 60000 | AU10: 60000 | AV10: 60000 | AW10: 60000 | AX10: =SUM(AL10:AW10) -> 720000 | AY10: =IF(AX10=0,"",AX10/AX$3) -> 0.041157735 | BB10: 地方郊外型 | BO10: =SUM(BC10:BN10)*予備!$C$13 -> 0 | BP10: =IF(BO10=0,"",BO10/BO$3) | BS10: 地方郊外型 | CF10: =SUM(BT10:CE10)*予備!$C$13 -> 0 | CG10: =IF(CF10=0,"",CF10/CF$3) | CJ10: 地方郊外型 | CW10: =SUM(CK10:CV10)*予備!$C$13 -> 0 | CX10: =IF(CW10=0,"",CW10/CW$3) | DA10: 地方郊外型 | DN10: =SUM(DB10:DM10)*予備!$C$13 -> 0 | DO10: =IF(DN10=0,"",DN10/DN$3) | DR10: 地方郊外型 | EE10: =SUM(DS10:ED10)*予備!$C$13 -> 0 | EF10: =IF(EE10=0,"",EE10/EE$3) | EI10: 地方郊外型 | EJ10: =ED10 -> 0 | EK10: =EJ10 -> 0 | EL10: =EK10 -> 0 | EM10: =EL10 -> 0 | EN10: =EM10 -> 0 | EO10: =EN10 -> 0 | EP10: =EO10 -> 0 | EQ10: =EP10 -> 0 | ER10: =EQ10 -> 0 | ... EU10: =ET10 -> 0 | EV10: =SUM(EJ10:EU10)*予備!$C$13 -> 0 | EW10: =IF(EV10=0,"",EV10/EV$3) | EZ10: 地方郊外型 | FA10: =EU10 -> 0 | FB10: =FA10 -> 0 | FC10: =FB10 -> 0 | FD10: =FC10 -> 0 | FE10: =FD10 -> 0 | FF10: =FE10 -> 0 | FG10: =FF10 -> 0 | FH10: =FG10 -> 0 | FI10: =FH10 -> 0 | ... FL10: =FK10 -> 0 | FM10: =SUM(FA10:FL10)*予備!$C$13 -> 0 | FN10: =IF(FM10=0,"",FM10/FM$3)
P11: =SUM(D11:O11)*予備!$C$11 -> 0 | Q11: =IF(P11=0,"",P11/$P$3) | T11: =IF(C11="","",C11) | AG11: =SUM(U11:AF11)*予備!$C$11 -> 0 | AH11: =IF(AG11=0,"",AG11/AG$3) | AK11: =IF(T11="","",T11) | AX11: =SUM(AL11:AW11)*予備!$C$11 -> 0 | AY11: =IF(AX11=0,"",AX11/AX$3) | BB11: 都心型 | BO11: =SUM(BC11:BN11)*予備!$C$11 -> 0 | BP11: =IF(BO11=0,"",BO11/BO$3) | BS11: 都心型 | CF11: =SUM(BT11:CE11)*予備!$C$11 -> 0 | CG11: =IF(CF11=0,"",CF11/CF$3) | CJ11: 都心型 | CW11: =SUM(CK11:CV11)*予備!$C$11 -> 0 | CX11: =IF(CW11=0,"",CW11/CW$3) | DA11: 都心型 | DN11: =SUM(DB11:DM11)*予備!$C$11 -> 0 | DO11: =IF(DN11=0,"",DN11/DN$3) | DR11: 都心型 | EE11: =SUM(DS11:ED11)*予備!$C$11 -> 0 | EF11: =IF(EE11=0,"",EE11/EE$3) | EI11: 都心型 | EJ11: =ED11 -> 0 | EK11: =EJ11 -> 0 | EL11: =EK11 -> 0 | EM11: =EL11 -> 0 | EN11: =EM11 -> 0 | EO11: =EN11 -> 0 | EP11: =EO11 -> 0 | EQ11: =EP11 -> 0 | ER11: =EQ11 -> 0 | ... EU11: =ET11 -> 0 | EV11: =SUM(EJ11:EU11)*予備!$C$11 -> 0 | EW11: =IF(EV11=0,"",EV11/EV$3) | EZ11: 都心型 | FA11: =EU11 -> 0 | FB11: =FA11 -> 0 | FC11: =FB11 -> 0 | FD11: =FC11 -> 0 | FE11: =FD11 -> 0 | FF11: =FE11 -> 0 | FG11: =FF11 -> 0 | FH11: =FG11 -> 0 | FI11: =FH11 -> 0 | ... FL11: =FK11 -> 0 | FM11: =SUM(FA11:FL11)*予備!$C$11 -> 0 | FN11: =IF(FM11=0,"",FM11/FM$3)
P12: =SUM(D12:O12)*予備!$C$12 -> 0 | Q12: =IF(P12=0,"",P12/$P$3) | T12: =IF(C12="","",C12) | AG12: =SUM(U12:AF12)*予備!$C$12 -> 0 | AH12: =IF(AG12=0,"",AG12/AG$3) | AK12: =IF(T12="","",T12) | AX12: =SUM(AL12:AW12)*予備!$C$12 -> 0 | AY12: =IF(AX12=0,"",AX12/AX$3) | BB12: サテライト型 | BO12: =SUM(BC12:BN12)*予備!$C$12 -> 0 | BP12: =IF(BO12=0,"",BO12/BO$3) | BS12: サテライト型 | CF12: =SUM(BT12:CE12)*予備!$C$12 -> 0 | CG12: =IF(CF12=0,"",CF12/CF$3) | CJ12: サテライト型 | CW12: =SUM(CK12:CV12)*予備!$C$12 -> 0 | CX12: =IF(CW12=0,"",CW12/CW$3) | DA12: サテライト型 | DN12: =SUM(DB12:DM12)*予備!$C$12 -> 0 | DO12: =IF(DN12=0,"",DN12/DN$3) | DR12: サテライト型 | EE12: =SUM(DS12:ED12)*予備!$C$12 -> 0 | EF12: =IF(EE12=0,"",EE12/EE$3) | EI12: サテライト型 | EJ12: =ED12 -> 0 | EK12: =EJ12 -> 0 | EL12: =EK12 -> 0 | EM12: =EL12 -> 0 | EN12: =EM12 -> 0 | EO12: =EN12 -> 0 | EP12: =EO12 -> 0 | EQ12: =EP12 -> 0 | ER12: =EQ12 -> 0 | ... EU12: =ET12 -> 0 | EV12: =SUM(EJ12:EU12)*予備!$C$12 -> 0 | EW12: =IF(EV12=0,"",EV12/EV$3) | EZ12: サテライト型 | FA12: =EU12 -> 0 | FB12: =FA12 -> 0 | FC12: =FB12 -> 0 | FD12: =FC12 -> 0 | FE12: =FD12 -> 0 | FF12: =FE12 -> 0 | FG12: =FF12 -> 0 | FH12: =FG12 -> 0 | FI12: =FH12 -> 0 | ... FL12: =FK12 -> 0 | FM12: =SUM(FA12:FL12)*予備!$C$12 -> 0 | FN12: =IF(FM12=0,"",FM12/FM$3)
P13: =SUM(D13:O13)*予備!$C$14 -> 0 | Q13: =IF(P13=0,"",P13/$P$3) | T13: SC併設型 | AG13: =SUM(U13:AF13)*予備!$C$14 -> 0 | AH13: =IF(AG13=0,"",AG13/AG$3) | AK13: SC併設型 | AX13: =SUM(AL13:AW13)*予備!$C$14 -> 0 | AY13: =IF(AX13=0,"",AX13/AX$3) | BB13: SC併設型 | BO13: =SUM(BC13:BN13)*予備!$C$14 -> 0 | BP13: =IF(BO13=0,"",BO13/BO$3) | BS13: SC併設型 | CF13: =SUM(BT13:CE13)*予備!$C$14 -> 0 | CG13: =IF(CF13=0,"",CF13/CF$3) | CJ13: SC併設型 | CW13: =SUM(CK13:CV13)*予備!$C$14 -> 0 | CX13: =IF(CW13=0,"",CW13/CW$3) | DA13: SC併設型 | DN13: =SUM(DB13:DM13)*予備!$C$14 -> 0 | DO13: =IF(DN13=0,"",DN13/DN$3) | DR13: SC併設型 | EE13: =SUM(DS13:ED13)*予備!$C$14 -> 0 | EF13: =IF(EE13=0,"",EE13/EE$3) | EI13: SC併設型 | EJ13: =ED13 -> 0 | EK13: =EJ13 -> 0 | EL13: =EK13 -> 0 | EM13: =EL13 -> 0 | EN13: =EM13 -> 0 | EO13: =EN13 -> 0 | EP13: =EO13 -> 0 | EQ13: =EP13 -> 0 | ER13: =EQ13 -> 0 | ... EU13: =ET13 -> 0 | EV13: =SUM(EJ13:EU13)*予備!$C$14 -> 0 | EW13: =IF(EV13=0,"",EV13/EV$3) | EZ13: SC併設型 | FA13: =EU13 -> 0 | FB13: =FA13 -> 0 | FC13: =FB13 -> 0 | FD13: =FC13 -> 0 | FE13: =FD13 -> 0 | FF13: =FE13 -> 0 | FG13: =FF13 -> 0 | FH13: =FG13 -> 0 | FI13: =FH13 -> 0 | ... FL13: =FK13 -> 0 | FM13: =SUM(FA13:FL13)*予備!$C$14 -> 0 | FN13: =IF(FM13=0,"",FM13/FM$3)
P14: =SUM(D14:O14) -> 0 | Q14: =IF(P14=0,"",P14/$P$3) | AG14: =SUM(U14:AF14) -> 0 | AH14: =IF(AG14=0,"",AG14/AG$3) | AX14: =SUM(AL14:AW14) -> 0 | AY14: =IF(AX14=0,"",AX14/AX$3) | BO14: =SUM(BC14:BN14) -> 0 | BP14: =IF(BO14=0,"",BO14/BO$3) | CF14: =SUM(BT14:CE14) -> 0 | CG14: =IF(CF14=0,"",CF14/CF$3) | CW14: =SUM(CK14:CV14) -> 0 | CX14: =IF(CW14=0,"",CW14/CW$3) | DN14: =SUM(DB14:DM14) -> 0 | DO14: =IF(DN14=0,"",DN14/DN$3) | EE14: =SUM(DS14:ED14) -> 0 | EF14: =IF(EE14=0,"",EE14/EE$3) | EV14: =SUM(EJ14:EU14) -> 0 | EW14: =IF(EV14=0,"",EV14/EV$3) | FM14: =SUM(FA14:FL14) -> 0 | FN14: =IF(FM14=0,"",FM14/FM$3)
B15: 入会金・年会費 | N15: 100000 | P15: =SUM(D15:O15) -> 100000 | Q15: =IF(P15=0,"",P15/$P$3) -> 1 | S15: =IF(B15="","",B15) -> 入会金・年会費 | AG15: =SUM(U15:AF15) -> 0 | AH15: =IF(AG15=0,"",AG15/AG$3) | AJ15: =IF(S15="","",S15) -> 入会金・年会費 | AX15: =SUM(AL15:AW15) -> 0 | AY15: =IF(AX15=0,"",AX15/AX$3) | BA15: FC収入 | BO15: =SUM(BC15:BN15) -> 0 | BP15: =IF(BO15=0,"",BO15/BO$3) | BR15: FC収入 | CF15: =SUM(BT15:CE15) -> 0 | CG15: =IF(CF15=0,"",CF15/CF$3) | CI15: FC収入 | CW15: =SUM(CK15:CV15) -> 0 | CX15: =IF(CW15=0,"",CW15/CW$3) | CZ15: FC収入 | DN15: =SUM(DB15:DM15) -> 0 | DO15: =IF(DN15=0,"",DN15/DN$3) | DQ15: FC収入 | EE15: =SUM(DS15:ED15) -> 0 | EF15: =IF(EE15=0,"",EE15/EE$3) | EH15: FC収入 | EV15: =SUM(EJ15:EU15) -> 0 | EW15: =IF(EV15=0,"",EV15/EV$3) | EY15: FC収入 | FM15: =SUM(FA15:FL15) -> 0 | FN15: =IF(FM15=0,"",FM15/FM$3)
B16: ネット販売 | P16: =SUM(D16:O16) -> 0 | S16: ネット販売 | AH16: =IF(AG16=0,"",AG16/AG$3) | AJ16: ネット販売 | AY16: =IF(AX16=0,"",AX16/AX$3) | BA16: 工場収入 | BP16: =IF(BO16=0,"",BO16/BO$3) | BR16: 工場収入 | CG16: =IF(CF16=0,"",CF16/CF$3) | CI16: 工場収入 | CX16: =IF(CW16=0,"",CW16/CW$3) | CZ16: 工場収入 | DO16: =IF(DN16=0,"",DN16/DN$3) | DQ16: 工場収入 | EF16: =IF(EE16=0,"",EE16/EE$3) | EH16: 工場収入 | EW16: =IF(EV16=0,"",EV16/EV$3) | EY16: 工場収入 | FN16: =IF(FM16=0,"",FM16/FM$3)
B17: その他収入 | P17: =SUM(D17:O17) -> 0 | Q17: =IF(P17=0,"",P17/$P$3) | S17: =IF(B17="","",B17) -> その他収入 | AG17: =SUM(U17:AF17) -> 0 | AH17: =IF(AG17=0,"",AG17/AG$3) | AJ17: =IF(S17="","",S17) -> その他収入 | AX17: =SUM(AL17:AW17) -> 0 | AY17: =IF(AX17=0,"",AX17/AX$3) | BA17: その他収入 | BO17: =SUM(BC17:BN17) -> 0 | BP17: =IF(BO17=0,"",BO17/BO$3) | BR17: その他収入 | CF17: =SUM(BT17:CE17) -> 0 | CG17: =IF(CF17=0,"",CF17/CF$3) | CI17: その他収入 | CW17: =SUM(CK17:CV17) -> 0 | CX17: =IF(CW17=0,"",CW17/CW$3) | CZ17: その他収入 | DN17: =SUM(DB17:DM17) -> 0 | DO17: =IF(DN17=0,"",DN17/DN$3) | DQ17: その他収入 | EE17: =SUM(DS17:ED17) -> 0 | EF17: =IF(EE17=0,"",EE17/EE$3) | EH17: その他収入 | EV17: =SUM(EJ17:EU17) -> 0 | EW17: =IF(EV17=0,"",EV17/EV$3) | EY17: その他収入 | FM17: =SUM(FA17:FL17) -> 0 | FN17: =IF(FM17=0,"",FM17/FM$3)
B18: 福祉サービス原価 | D18: =SUM(D19:D29) -> 0 | E18: =SUM(E19:E29) -> 0 | F18: =SUM(F19:F29) -> 0 | G18: =SUM(G19:G29) -> 0 | H18: =SUM(H19:H29) -> 0 | I18: =SUM(I19:I29) -> 0 | J18: =SUM(J19:J29) -> 0 | K18: =SUM(K19:K29) -> 0 | ... O18: =SUM(O19:O29) -> 0 | P18: =SUM(D18:O18) -> 0 | Q18: =IF(P18=0,"",P18/$P$3) | S18: =IF(B18="","",B18) -> 福祉サービス原価 | U18: =SUM(U19:U29) -> 578172.1 | V18: =SUM(V19:V29) -> 578172.1 | W18: =SUM(W19:W29) -> 671172.1 | X18: =SUM(X19:X29) -> 897818.8 | Y18: =SUM(Y19:Y29) -> 897818.8 | Z18: =SUM(Z19:Z29) -> 965818.8 | AA18: =SUM(AA19:AA29) -> 965818.8 | AB18: =SUM(AB19:AB29) -> 983818.8 | ... AF18: =SUM(AF19:AF29) -> 1019818.8 | AG18: =SUM(U18:AF18) -> 10545886 | AH18: =IF(AG18=0,"",AG18/AG$3) -> 0.60910732 | AJ18: =IF(S18="","",S18) -> 福祉サービス原価 | AL18: =SUM(AL19:AL29) -> 876818.8 | AM18: =SUM(AM19:AM29) -> 884818.8 | AN18: =SUM(AN19:AN29) -> 889818.8 | AO18: =SUM(AO19:AO29) -> 907818.8 | AP18: =SUM(AP19:AP29) -> 907818.8 | AQ18: =SUM(AQ19:AQ29) -> 925818.8 | AR18: =SUM(AR19:AR29) -> 925818.8 | AS18: =SUM(AS19:AS29) -> 943818.8 | ... AW18: =SUM(AW19:AW29) -> 979818.8 | AX18: =SUM(AL18:AW18) -> 11109826 | AY18: =IF(AX18=0,"",AX18/AX$3) -> 0.63507675 | BA18: 売上原価 | BC18: =SUM(BC19:BC29) -> 18560 | BD18: =SUM(BD19:BD29) -> 18560 | BE18: =SUM(BE19:BE29) -> 18560 | BF18: =SUM(BF19:BF29) -> 18560 | BG18: =SUM(BG19:BG29) -> 18560 | BH18: =SUM(BH19:BH29) -> 17920 | BI18: =SUM(BI19:BI29) -> 18560 | BJ18: =SUM(BJ19:BJ29) -> 19200 | ... BN18: =SUM(BN19:BN29) -> 19200 | BO18: =SUM(BC18:BN18) -> 225280 | BP18: =IF(BO18=0,"",BO18/BO$3) -> 0.64 | BR18: 売上原価 | BT18: =SUM(BT19:BT29) -> 18560 | BU18: =SUM(BU19:BU29) -> 18560 | BV18: =SUM(BV19:BV29) -> 18560 | BW18: =SUM(BW19:BW29) -> 18560 | BX18: =SUM(BX19:BX29) -> 18560 | BY18: =SUM(BY19:BY29) -> 17920 | BZ18: =SUM(BZ19:BZ29) -> 18560 | CA18: =SUM(CA19:CA29) -> 19200 | ... CE18: =SUM(CE19:CE29) -> 19200 | CF18: =SUM(BT18:CE18) -> 225280 | CG18: =IF(CF18=0,"",CF18/CF$3) -> 0.64 | CI18: 売上原価 | CK18: =SUM(CK19:CK29) -> 0 | CL18: =SUM(CL19:CL29) -> 0 | CM18: =SUM(CM19:CM29) -> 0 | CN18: =SUM(CN19:CN29) -> 0 | CO18: =SUM(CO19:CO29) -> 0 | CP18: =SUM(CP19:CP29) -> 0 | CQ18: =SUM(CQ19:CQ29) -> 0 | CR18: =SUM(CR19:CR29) -> 0 | ... CV18: =SUM(CV19:CV29) -> 0 | CW18: =SUM(CK18:CV18) -> 0 | CX18: =IF(CW18=0,"",CW18/CW$3) | CZ18: 売上原価 | DB18: =SUM(DB19:DB29) -> 0 | DC18: =SUM(DC19:DC29) -> 0 | DD18: =SUM(DD19:DD29) -> 0 | DE18: =SUM(DE19:DE29) -> 0 | DF18: =SUM(DF19:DF29) -> 0 | DG18: =SUM(DG19:DG29) -> 0 | DH18: =SUM(DH19:DH29) -> 0 | DI18: =SUM(DI19:DI29) -> 0 | ... DM18: =SUM(DM19:DM29) -> 0 | DN18: =SUM(DB18:DM18) -> 0 | DO18: =IF(DN18=0,"",DN18/DN$3) | DQ18: 売上原価 | DS18: =SUM(DS19:DS29) -> 0 | DT18: =SUM(DT19:DT29) -> 0 | DU18: =SUM(DU19:DU29) -> 0 | DV18: =SUM(DV19:DV29) -> 0 | DW18: =SUM(DW19:DW29) -> 0 | DX18: =SUM(DX19:DX29) -> 0 | DY18: =SUM(DY19:DY29) -> 0 | DZ18: =SUM(DZ19:DZ29) -> 0 | ... ED18: =SUM(ED19:ED29) -> 0 | EE18: =SUM(DS18:ED18) -> 0 | EF18: =IF(EE18=0,"",EE18/EE$3) | EH18: 売上原価 | EJ18: =SUM(EJ19:EJ29) -> 0 | EK18: =SUM(EK19:EK29) -> 0 | EL18: =SUM(EL19:EL29) -> 0 | EM18: =SUM(EM19:EM29) -> 0 | EN18: =SUM(EN19:EN29) -> 0 | EO18: =SUM(EO19:EO29) -> 0 | EP18: =SUM(EP19:EP29) -> 0 | EQ18: =SUM(EQ19:EQ29) -> 0 | ... EU18: =SUM(EU19:EU29) -> 0 | EV18: =SUM(EJ18:EU18) -> 0 | EW18: =IF(EV18=0,"",EV18/EV$3) | EY18: 売上原価 | FA18: =SUM(FA19:FA29) -> 0 | FB18: =SUM(FB19:FB29) -> 0 | FC18: =SUM(FC19:FC29) -> 0 | FD18: =SUM(FD19:FD29) -> 0 | FE18: =SUM(FE19:FE29) -> 0 | FF18: =SUM(FF19:FF29) -> 0 | FG18: =SUM(FG19:FG29) -> 0 | FH18: =SUM(FH19:FH29) -> 0 | ... FL18: =SUM(FL19:FL29) -> 0 | FM18: =SUM(FA18:FL18) -> 0 | FN18: =IF(FM18=0,"",FM18/FM$3)
C19: 作業原価 | P19: =SUM(D19:O19) -> 0 | T19: =IF(C19="","",C19) -> 作業原価 | AG19: =SUM(U19:AF19) -> 0 | AH19: 0.27 | AK19: =IF(T19="","",T19) -> 作業原価 | AX19: =SUM(AL19:AW19) -> 0 | AY19: 0.27 | BB19: =AK19 -> 作業原価 | BC19: =BC4*0.25 -> 7250 | BD19: =BD4*0.25 -> 7250 | BE19: =BE4*0.25 -> 7250 | BF19: =BF4*0.25 -> 7250 | BG19: =BG4*0.25 -> 7250 | BH19: =BH4*0.25 -> 7000 | BI19: =BI4*0.25 -> 7250 | BJ19: =BJ4*0.25 -> 7500 | ... BN19: =BN4*0.25 -> 7500 | BO19: =SUM(BC19:BN19) -> 88000 | BP19: =IF(BO19=0,"",BO19/BO$3) -> 0.25 | BS19: =BB19 -> 作業原価 | BT19: =BT4*0.25 -> 7250 | BU19: =BU4*0.25 -> 7250 | BV19: =BV4*0.25 -> 7250 | BW19: =BW4*0.25 -> 7250 | BX19: =BX4*0.25 -> 7250 | BY19: =BY4*0.25 -> 7000 | BZ19: =BZ4*0.25 -> 7250 | CA19: =CA4*0.25 -> 7500 | ... CE19: =CE4*0.25 -> 7500 | CF19: =SUM(BT19:CE19) -> 88000 | CG19: =IF(CF19=0,"",CF19/CF$3) -> 0.25 | CJ19: =BS19 -> 作業原価 | CK19: =CK4*0.25 -> 0 | CL19: =CL4*0.25 -> 0 | CM19: =CM4*0.25 -> 0 | CN19: =CN4*0.25 -> 0 | CO19: =CO4*0.25 -> 0 | CP19: =CP4*0.25 -> 0 | CQ19: =CQ4*0.25 -> 0 | CR19: =CR4*0.25 -> 0 | ... CV19: =CV4*0.25 -> 0 | CW19: =SUM(CK19:CV19) -> 0 | CX19: =IF(CW19=0,"",CW19/CW$3) | DA19: =CJ19 -> 作業原価 | DB19: =DB4*0.25 -> 0 | DC19: =DC4*0.25 -> 0 | DD19: =DD4*0.25 -> 0 | DE19: =DE4*0.25 -> 0 | DF19: =DF4*0.25 -> 0 | DG19: =DG4*0.25 -> 0 | DH19: =DH4*0.25 -> 0 | DI19: =DI4*0.25 -> 0 | ... DM19: =DM4*0.25 -> 0 | DN19: =SUM(DB19:DM19) -> 0 | DO19: =IF(DN19=0,"",DN19/DN$3) | DR19: =DA19 -> 作業原価 | DS19: =DS4*0.25 -> 0 | DT19: =DT4*0.25 -> 0 | DU19: =DU4*0.25 -> 0 | DV19: =DV4*0.25 -> 0 | DW19: =DW4*0.25 -> 0 | DX19: =DX4*0.25 -> 0 | DY19: =DY4*0.25 -> 0 | DZ19: =DZ4*0.25 -> 0 | ... ED19: =ED4*0.25 -> 0 | EE19: =SUM(DS19:ED19) -> 0 | EF19: =IF(EE19=0,"",EE19/EE$3) | EI19: =DR19 -> 作業原価 | EJ19: =EJ4*0.25 -> 0 | EK19: =EK4*0.25 -> 0 | EL19: =EL4*0.25 -> 0 | EM19: =EM4*0.25 -> 0 | EN19: =EN4*0.25 -> 0 | EO19: =EO4*0.25 -> 0 | EP19: =EP4*0.25 -> 0 | EQ19: =EQ4*0.25 -> 0 | ... EU19: =EU4*0.25 -> 0 | EV19: =SUM(EJ19:EU19) -> 0 | EW19: =IF(EV19=0,"",EV19/EV$3) | EZ19: =EI19 -> 作業原価 | FA19: =FA4*0.25 -> 0 | FB19: =FB4*0.25 -> 0 | FC19: =FC4*0.25 -> 0 | FD19: =FD4*0.25 -> 0 | FE19: =FE4*0.25 -> 0 | FF19: =FF4*0.25 -> 0 | FG19: =FG4*0.25 -> 0 | FH19: =FH4*0.25 -> 0 | ... FL19: =FL4*0.25 -> 0 | FM19: =SUM(FA19:FL19) -> 0 | FN19: =IF(FM19=0,"",FM19/FM$3)
C20: 利用者工賃 | P20: =SUM(D20:O20) -> 0 | T20: =IF(C20="","",C20) -> 利用者工賃 | U20: =U5*10000*0.8 -> 80000 | V20: =V5*10000*0.8 -> 88000 | W20: =W5*20000*0.8 -> 176000 | X20: =X5*20000*0.8 -> 192000 | Y20: =Y5*20000*0.8 -> 192000 | Z20: =Z5*20000*0.8 -> 208000 | AA20: =AA5*20000*0.8 -> 208000 | AB20: =AB5*20000*0.8 -> 224000 | AC20: =AC5*20000*0.8 -> 224000 | AD20: =AD5*20000*0.8 -> 240000 | ... AF20: =AF5*20000*0.8 -> 256000 | AG20: =SUM(U20:AF20) -> 2328000 | AH20: 0.31 | AK20: =IF(T20="","",T20) -> 利用者工賃 | AL20: =AL5*20000*0.8 -> 160000 | AM20: =AM5*20000*0.8 -> 176000 | AN20: =AN5*20000*0.8 -> 176000 | AO20: =AO5*20000*0.8 -> 192000 | AP20: =AP5*20000*0.8 -> 192000 | AQ20: =AQ5*20000*0.8 -> 208000 | AR20: =AR5*20000*0.8 -> 208000 | AS20: =AS5*20000*0.8 -> 224000 | ... AW20: =AW5*20000*0.8 -> 256000 | AX20: =SUM(AL20:AW20) -> 2496000 | AY20: 0.31 | BB20: =AK20 -> 利用者工賃 | BC20: =BC4*0.3 -> 8700 | BD20: =BD4*0.3 -> 8700 | BE20: =BE4*0.3 -> 8700 | BF20: =BF4*0.3 -> 8700 | BG20: =BG4*0.3 -> 8700 | BH20: =BH4*0.3 -> 8400 | BI20: =BI4*0.3 -> 8700 | BJ20: =BJ4*0.3 -> 9000 | ... BN20: =BN4*0.3 -> 9000 | BO20: =SUM(BC20:BN20) -> 105600 | BP20: =IF(BO20=0,"",BO20/BO$3) -> 0.3 | BS20: =BB20 -> 利用者工賃 | BT20: =BT4*0.3 -> 8700 | BU20: =BU4*0.3 -> 8700 | BV20: =BV4*0.3 -> 8700 | BW20: =BW4*0.3 -> 8700 | BX20: =BX4*0.3 -> 8700 | BY20: =BY4*0.3 -> 8400 | BZ20: =BZ4*0.3 -> 8700 | CA20: =CA4*0.3 -> 9000 | ... CE20: =CE4*0.3 -> 9000 | CF20: =SUM(BT20:CE20) -> 105600 | CG20: =IF(CF20=0,"",CF20/CF$3) -> 0.3 | CJ20: =BS20 -> 利用者工賃 | CK20: =CK4*0.3 -> 0 | CL20: =CL4*0.3 -> 0 | CM20: =CM4*0.3 -> 0 | CN20: =CN4*0.3 -> 0 | CO20: =CO4*0.3 -> 0 | CP20: =CP4*0.3 -> 0 | CQ20: =CQ4*0.3 -> 0 | CR20: =CR4*0.3 -> 0 | ... CV20: =CV4*0.3 -> 0 | CW20: =SUM(CK20:CV20) -> 0 | CX20: =IF(CW20=0,"",CW20/CW$3) | DA20: =CJ20 -> 利用者工賃 | DB20: =DB4*0.3 -> 0 | DC20: =DC4*0.3 -> 0 | DD20: =DD4*0.3 -> 0 | DE20: =DE4*0.3 -> 0 | DF20: =DF4*0.3 -> 0 | DG20: =DG4*0.3 -> 0 | DH20: =DH4*0.3 -> 0 | DI20: =DI4*0.3 -> 0 | ... DM20: =DM4*0.3 -> 0 | DN20: =SUM(DB20:DM20) -> 0 | DO20: =IF(DN20=0,"",DN20/DN$3) | DR20: =DA20 -> 利用者工賃 | DS20: =DS4*0.3 -> 0 | DT20: =DT4*0.3 -> 0 | DU20: =DU4*0.3 -> 0 | DV20: =DV4*0.3 -> 0 | DW20: =DW4*0.3 -> 0 | DX20: =DX4*0.3 -> 0 | DY20: =DY4*0.3 -> 0 | DZ20: =DZ4*0.3 -> 0 | ... ED20: =ED4*0.3 -> 0 | EE20: =SUM(DS20:ED20) -> 0 | EF20: =IF(EE20=0,"",EE20/EE$3) | EI20: =DR20 -> 利用者工賃 | EJ20: =EJ4*0.3 -> 0 | EK20: =EK4*0.3 -> 0 | EL20: =EL4*0.3 -> 0 | EM20: =EM4*0.3 -> 0 | EN20: =EN4*0.3 -> 0 | EO20: =EO4*0.3 -> 0 | EP20: =EP4*0.3 -> 0 | EQ20: =EQ4*0.3 -> 0 | ... EU20: =EU4*0.3 -> 0 | EV20: =SUM(EJ20:EU20) -> 0 | EW20: =IF(EV20=0,"",EV20/EV$3) | EZ20: =EI20 -> 利用者工賃 | FA20: =FA4*0.3 -> 0 | FB20: =FB4*0.3 -> 0 | FC20: =FC4*0.3 -> 0 | FD20: =FD4*0.3 -> 0 | FE20: =FE4*0.3 -> 0 | FF20: =FF4*0.3 -> 0 | FG20: =FG4*0.3 -> 0 | FH20: =FH4*0.3 -> 0 | ... FL20: =FL4*0.3 -> 0 | FM20: =SUM(FA20:FL20) -> 0 | FN20: =IF(FM20=0,"",FM20/FM$3)
C21: スタッフ給料 | T21: =IF(C21="","",C21) -> スタッフ給料 | U21: =Sheet2!F9 -> 410300 | V21: =U21 -> 410300 | W21: =V21 -> 410300 | X21: =Sheet2!F19 -> 488400 | Y21: =X21 -> 488400 | Z21: =Y21 -> 488400 | AA21: =Z21 -> 488400 | AB21: =AA21 -> 488400 | AC21: =AB21 -> 488400 | AD21: =AC21 -> 488400 | AE21: =AD21 -> 488400 | AF21: =AE21 -> 488400 | AG21: =SUM(U21:AF21) -> 5626500 | AK21: =IF(T21="","",T21) -> スタッフ給料 | AL21: =AF21 -> 488400 | AM21: =AL21 -> 488400 | AN21: =AM21 -> 488400 | AO21: =AN21 -> 488400 | AP21: =AO21 -> 488400 | AQ21: =AP21 -> 488400 | AR21: =AQ21 -> 488400 | AS21: =AR21 -> 488400 | AT21: =AS21 -> 488400 | ... AW21: =AV21 -> 488400 | AX21: =SUM(AL21:AW21) -> 5860800
C22: 法定福利費 | T22: =IF(C22="","",C22) -> 法定福利費 | U22: =Sheet2!F10 -> 2872.1 | V22: =U22 -> 2872.1 | W22: =V22 -> 2872.1 | X22: =Sheet2!F20 -> 3418.8 | Y22: =X22 -> 3418.8 | Z22: =Y22 -> 3418.8 | AA22: =Z22 -> 3418.8 | AB22: =AA22 -> 3418.8 | AC22: =AB22 -> 3418.8 | AD22: =AC22 -> 3418.8 | AE22: =AD22 -> 3418.8 | AF22: =AE22 -> 3418.8 | AG22: =SUM(U22:AF22) -> 39385.5 | AK22: =IF(T22="","",T22) -> 法定福利費 | AL22: =AF22 -> 3418.8 | AM22: =AL22 -> 3418.8 | AN22: =AM22 -> 3418.8 | AO22: =AN22 -> 3418.8 | AP22: =AO22 -> 3418.8 | AQ22: =AP22 -> 3418.8 | AR22: =AQ22 -> 3418.8 | AS22: =AR22 -> 3418.8 | AT22: =AS22 -> 3418.8 | ... AW22: =AV22 -> 3418.8 | AX22: =SUM(AL22:AW22) -> 41025.6
C23: 家賃 | T23: =IF(C23="","",C23) -> 家賃 | Z23: 50000 | AA23: 50000 | AB23: 50000 | AC23: 50000 | AD23: 50000 | AE23: 50000 | AF23: 50000 | AG23: =SUM(U23:AF23) -> 350000 | AK23: =IF(T23="","",T23) -> 家賃 | AL23: 50000 | AM23: 50000 | AN23: 50000 | AO23: 50000 | AP23: 50000 | AQ23: 50000 | AR23: 50000 | AS23: 50000 | AT23: 50000 | AU23: 50000 | AV23: 50000 | AW23: 50000 | AX23: =SUM(AL23:AW23) -> 600000
C24: 水道光熱費・通信費 | T24: =IF(C24="","",C24) -> 水道光熱費・通信費 | U24: 20000 | V24: =U24 -> 20000 | W24: =V24 -> 20000 | X24: =W24 -> 20000 | Y24: =X24 -> 20000 | Z24: =Y24 -> 20000 | AA24: =Z24 -> 20000 | AB24: =AA24 -> 20000 | AC24: =AB24 -> 20000 | ... AF24: =AE24 -> 20000 | AG24: =SUM(U24:AF24) -> 240000 | AK24: =IF(T24="","",T24) -> 水道光熱費・通信費 | AL24: 20000 | AM24: =AL24 -> 20000 | AN24: =AM24 -> 20000 | AO24: =AN24 -> 20000 | AP24: =AO24 -> 20000 | AQ24: =AP24 -> 20000 | AR24: =AQ24 -> 20000 | AS24: =AR24 -> 20000 | AT24: =AS24 -> 20000 | ... AW24: =AV24 -> 20000 | AX24: =SUM(AL24:AW24) -> 240000
C25: 燃料費 | P25: =SUM(D25:O25) -> 0 | T25: =IF(C25="","",C25) -> 燃料費 | U25: 30000 | V25: =U25 -> 30000 | W25: =V25 -> 30000 | X25: 60000 | Y25: =X25 -> 60000 | Z25: =Y25 -> 60000 | AA25: =Z25 -> 60000 | AB25: =AA25 -> 60000 | AC25: =AB25 -> 60000 | AD25: =AC25 -> 60000 | AE25: =AD25 -> 60000 | AF25: =AE25 -> 60000 | AG25: =SUM(U25:AF25) -> 630000 | AH25: 0.03 | AK25: =IF(T25="","",T25) -> 燃料費 | AL25: 20000 | AM25: =AL25 -> 20000 | AN25: =AM25 -> 20000 | AO25: =AN25 -> 20000 | AP25: =AO25 -> 20000 | AQ25: =AP25 -> 20000 | AR25: =AQ25 -> 20000 | AS25: =AR25 -> 20000 | AT25: =AS25 -> 20000 | ... AW25: =AV25 -> 20000 | AX25: =SUM(AL25:AW25) -> 240000 | AY25: 0.03 | BB25: =AK25 -> 燃料費 | BC25: =BC4*0.03 -> 870 | BD25: =BD4*0.03 -> 870 | BE25: =BE4*0.03 -> 870 | BF25: =BF4*0.03 -> 870 | BG25: =BG4*0.03 -> 870 | BH25: =BH4*0.03 -> 840 | BI25: =BI4*0.03 -> 870 | BJ25: =BJ4*0.03 -> 900 | ... BN25: =BN4*0.03 -> 900 | BO25: =SUM(BC25:BN25) -> 10560 | BP25: =IF(BO25=0,"",BO25/BO$3) -> 0.03 | BS25: =BB25 -> 燃料費 | BT25: =BT4*0.03 -> 870 | BU25: =BU4*0.03 -> 870 | BV25: =BV4*0.03 -> 870 | BW25: =BW4*0.03 -> 870 | BX25: =BX4*0.03 -> 870 | BY25: =BY4*0.03 -> 840 | BZ25: =BZ4*0.03 -> 870 | CA25: =CA4*0.03 -> 900 | ... CE25: =CE4*0.03 -> 900 | CF25: =SUM(BT25:CE25) -> 10560 | CG25: =IF(CF25=0,"",CF25/CF$3) -> 0.03 | CJ25: =BS25 -> 燃料費 | CK25: =CK4*0.03 -> 0 | CL25: =CL4*0.03 -> 0 | CM25: =CM4*0.03 -> 0 | CN25: =CN4*0.03 -> 0 | CO25: =CO4*0.03 -> 0 | CP25: =CP4*0.03 -> 0 | CQ25: =CQ4*0.03 -> 0 | CR25: =CR4*0.03 -> 0 | ... CV25: =CV4*0.03 -> 0 | CW25: =SUM(CK25:CV25) -> 0 | CX25: =IF(CW25=0,"",CW25/CW$3) | DA25: =CJ25 -> 燃料費 | DB25: =DB4*0.03 -> 0 | DC25: =DC4*0.03 -> 0 | DD25: =DD4*0.03 -> 0 | DE25: =DE4*0.03 -> 0 | DF25: =DF4*0.03 -> 0 | DG25: =DG4*0.03 -> 0 | DH25: =DH4*0.03 -> 0 | DI25: =DI4*0.03 -> 0 | ... DM25: =DM4*0.03 -> 0 | DN25: =SUM(DB25:DM25) -> 0 | DO25: =IF(DN25=0,"",DN25/DN$3) | DR25: =DA25 -> 燃料費 | DS25: =DS4*0.03 -> 0 | DT25: =DT4*0.03 -> 0 | DU25: =DU4*0.03 -> 0 | DV25: =DV4*0.03 -> 0 | DW25: =DW4*0.03 -> 0 | DX25: =DX4*0.03 -> 0 | DY25: =DY4*0.03 -> 0 | DZ25: =DZ4*0.03 -> 0 | ... ED25: =ED4*0.03 -> 0 | EE25: =SUM(DS25:ED25) -> 0 | EF25: =IF(EE25=0,"",EE25/EE$3) | EI25: =DR25 -> 燃料費 | EJ25: =EJ4*0.03 -> 0 | EK25: =EK4*0.03 -> 0 | EL25: =EL4*0.03 -> 0 | EM25: =EM4*0.03 -> 0 | EN25: =EN4*0.03 -> 0 | EO25: =EO4*0.03 -> 0 | EP25: =EP4*0.03 -> 0 | EQ25: =EQ4*0.03 -> 0 | ... EU25: =EU4*0.03 -> 0 | EV25: =SUM(EJ25:EU25) -> 0 | EW25: =IF(EV25=0,"",EV25/EV$3) | EZ25: =EI25 -> 燃料費 | FA25: =FA4*0.03 -> 0 | FB25: =FB4*0.03 -> 0 | FC25: =FC4*0.03 -> 0 | FD25: =FD4*0.03 -> 0 | FE25: =FE4*0.03 -> 0 | FF25: =FF4*0.03 -> 0 | FG25: =FG4*0.03 -> 0 | FH25: =FH4*0.03 -> 0 | ... FL25: =FL4*0.03 -> 0 | FM25: =SUM(FA25:FL25) -> 0 | FN25: =IF(FM25=0,"",FM25/FM$3)
C26: 会費・保険料等 | T26: =IF(C26="","",C26) -> 会費・保険料等 | U26: 10000 | AG26: =SUM(U26:AF26) -> 10000 | AK26: =IF(T26="","",T26) -> 会費・保険料等 | AL26: 10000 | AX26: =SUM(AL26:AW26) -> 10000
C27: 事務管理費 | T27: =IF(C27="","",C27) -> 事務管理費 | X27: 100000 | Y27: =X27 -> 100000 | Z27: =Y27 -> 100000 | AA27: =Z27 -> 100000 | AB27: =AA27 -> 100000 | AC27: =AB27 -> 100000 | AD27: =AC27 -> 100000 | AE27: =AD27 -> 100000 | AF27: =AE27 -> 100000 | AG27: =SUM(U27:AF27) -> 900000 | AK27: =IF(T27="","",T27) -> 事務管理費 | AL27: 100000 | AM27: =AL27 -> 100000 | AN27: =AM27 -> 100000 | AO27: 100000 | AP27: =AO27 -> 100000 | AQ27: =AP27 -> 100000 | AR27: =AQ27 -> 100000 | AS27: =AR27 -> 100000 | AT27: =AS27 -> 100000 | AU27: =AT27 -> 100000 | AV27: =AU27 -> 100000 | AW27: =AV27 -> 100000 | AX27: =SUM(AL27:AW27) -> 1200000
C28: 消耗品費 | P28: =SUM(D28:O28) -> 0 | T28: =IF(C28="","",C28) -> 消耗品費 | U28: 20000 | V28: =V5*2000 -> 22000 | W28: =W5*2000 -> 22000 | X28: =X5*2000 -> 24000 | Y28: =Y5*2000 -> 24000 | Z28: =Z5*2000 -> 26000 | AA28: =AA5*2000 -> 26000 | AB28: =AB5*2000 -> 28000 | AC28: =AC5*2000 -> 28000 | ... AF28: =AF5*2000 -> 32000 | AG28: =SUM(U28:AF28) -> 312000 | AH28: 0.06 | AK28: =IF(T28="","",T28) -> 消耗品費 | AL28: 20000 | AM28: =AM5*2000 -> 22000 | AN28: =AN5*2000 -> 22000 | AO28: =AO5*2000 -> 24000 | AP28: =AP5*2000 -> 24000 | AQ28: =AQ5*2000 -> 26000 | AR28: =AR5*2000 -> 26000 | AS28: =AS5*2000 -> 28000 | AT28: =AT5*2000 -> 28000 | ... AW28: =AW5*2000 -> 32000 | AX28: =SUM(AL28:AW28) -> 312000 | AY28: 0.06 | BB28: ＦＣロイヤリティ(6%) | BC28: =BC4*0.06 -> 1740 | BD28: =BD4*0.06 -> 1740 | BE28: =BE4*0.06 -> 1740 | BF28: =BF4*0.06 -> 1740 | BG28: =BG4*0.06 -> 1740 | BH28: =BH4*0.06 -> 1680 | BI28: =BI4*0.06 -> 1740 | BJ28: =BJ4*0.06 -> 1800 | ... BN28: =BN4*0.06 -> 1800 | BO28: =SUM(BC28:BN28) -> 21120 | BP28: =IF(BO28=0,"",BO28/BO$3) -> 0.06 | BS28: ＦＣロイヤリティ(6%) | BT28: =BT4*0.06 -> 1740 | BU28: =BU4*0.06 -> 1740 | BV28: =BV4*0.06 -> 1740 | BW28: =BW4*0.06 -> 1740 | BX28: =BX4*0.06 -> 1740 | BY28: =BY4*0.06 -> 1680 | BZ28: =BZ4*0.06 -> 1740 | CA28: =CA4*0.06 -> 1800 | ... CE28: =CE4*0.06 -> 1800 | CF28: =SUM(BT28:CE28) -> 21120 | CG28: =IF(CF28=0,"",CF28/CF$3) -> 0.06 | CJ28: ＦＣロイヤリティ(6%) | CK28: =CK4*0.06 -> 0 | CL28: =CL4*0.06 -> 0 | CM28: =CM4*0.06 -> 0 | CN28: =CN4*0.06 -> 0 | CO28: =CO4*0.06 -> 0 | CP28: =CP4*0.06 -> 0 | CQ28: =CQ4*0.06 -> 0 | CR28: =CR4*0.06 -> 0 | ... CV28: =CV4*0.06 -> 0 | CW28: =SUM(CK28:CV28) -> 0 | CX28: =IF(CW28=0,"",CW28/CW$3) | DO28: =IF(DN28=0,"",DN28/DN$3) | EF28: =IF(EE28=0,"",EE28/EE$3) | EW28: =IF(EV28=0,"",EV28/EV$3) | FN28: =IF(FM28=0,"",FM28/FM$3)
C29: 雑費 | P29: =SUM(D29:O29) -> 0 | T29: =IF(C29="","",C29) -> 雑費 | U29: 5000 | V29: 5000 | W29: 10000 | X29: 10000 | Y29: 10000 | Z29: 10000 | AA29: 10000 | AB29: 10000 | AC29: 10000 | AD29: 10000 | AE29: 10000 | AF29: 10000 | AG29: =SUM(U29:AF29) -> 110000 | AH29: =IF(AG29=0,"",AG29/$P$3) -> 1.1 | AK29: =IF(T29="","",T29) -> 雑費 | AL29: 5000 | AM29: 5000 | AN29: 10000 | AO29: 10000 | AP29: 10000 | AQ29: 10000 | AR29: 10000 | AS29: 10000 | AT29: 10000 | AU29: 10000 | AV29: 10000 | AW29: 10000 | AX29: =SUM(AL29:AW29) -> 110000 | AY29: =IF(AX29=0,"",AX29/$P$3) -> 1.1 | BB29: =AK29 -> 雑費 | BO29: =SUM(BC29:BN29) -> 0 | BP29: =IF(BO29=0,"",BO29/BO$3) | BS29: =BB29 -> 雑費 | CF29: =SUM(BT29:CE29) -> 0 | CG29: =IF(CF29=0,"",CF29/CF$3) | CJ29: =BS29 -> 雑費 | CW29: =SUM(CK29:CV29) -> 0 | CX29: =IF(CW29=0,"",CW29/CW$3) | DA29: =CJ29 -> 雑費 | DN29: =SUM(DB29:DM29) -> 0 | DO29: =IF(DN29=0,"",DN29/DN$3) | DR29: =DA29 -> 雑費 | EE29: =SUM(DS29:ED29) -> 0 | EF29: =IF(EE29=0,"",EE29/EE$3) | EI29: =DR29 -> 雑費 | EV29: =SUM(EJ29:EU29) -> 0 | EW29: =IF(EV29=0,"",EV29/EV$3) | EZ29: =EI29 -> 雑費 | FM29: =SUM(FA29:FL29) -> 0 | FN29: =IF(FM29=0,"",FM29/FM$3)
B30: （原価率） | D30: =D3-D18 -> 0 | E30: =E3-E18 -> 0 | F30: =F3-F18 -> 0 | G30: =G3-G18 -> 0 | H30: =H3-H18 -> 0 | I30: =I3-I18 -> 0 | J30: =J3-J18 -> 0 | K30: =K3-K18 -> 0 | ... O30: =O3-O18 -> 0 | P30: =SUM(D30:O30) -> 100000 | Q30: =IF(P30=0,"",P30/$P$3) -> 1 | S30: =IF(B30="","",B30) -> （原価率） | U30: =U3-U18 -> 453197.9 | V30: =V3-V18 -> 607891.9 | W30: =W3-W18 -> 514891.9 | X30: =X3-X18 -> 456069.2 | Y30: =Y3-Y18 -> 456069.2 | Z30: =Z3-Z18 -> 495893.2 | AA30: =AA3-AA18 -> 495893.2 | AB30: =AB3-AB18 -> 585717.2 | ... AF30: =AF3-AF18 -> 765365.2 | AG30: =SUM(U30:AF30) -> 6767788.5 | AH30: =IF(AG30=0,"",AG30/AG$3) -> 0.39089268 | AJ30: =IF(S30="","",S30) -> （原価率） | AL30: =AL3-AL18 -> 214551.2 | AM30: =AM3-AM18 -> 361245.2 | AN30: =AN3-AN18 -> 356245.2 | AO30: =AO3-AO18 -> 446069.2 | AP30: =AP3-AP18 -> 446069.2 | AQ30: =AQ3-AQ18 -> 535893.2 | AR30: =AR3-AR18 -> 535893.2 | AS30: =AS3-AS18 -> 625717.2 | ... AW30: =AW3-AW18 -> 805365.2 | AX30: =SUM(AL30:AW30) -> 6383848.4 | AY30: =IF(AX30=0,"",AX30/AX$3) -> 0.36492325 | BA30: （売上総利益） | BC30: =BC3-BC18 -> 10440 | BD30: =BD3-BD18 -> 10440 | BE30: =BE3-BE18 -> 10440 | BF30: =BF3-BF18 -> 10440 | BG30: =BG3-BG18 -> 10440 | BH30: =BH3-BH18 -> 10080 | BI30: =BI3-BI18 -> 10440 | BJ30: =BJ3-BJ18 -> 10800 | ... BN30: =BN3-BN18 -> 10800 | BO30: =SUM(BC30:BN30) -> 126720 | BP30: =IF(BO30=0,"",BO30/BO$3) -> 0.36 | BR30: （売上総利益） | BT30: =BT3-BT18 -> 10440 | BU30: =BU3-BU18 -> 10440 | BV30: =BV3-BV18 -> 10440 | BW30: =BW3-BW18 -> 10440 | BX30: =BX3-BX18 -> 10440 | BY30: =BY3-BY18 -> 10080 | BZ30: =BZ3-BZ18 -> 10440 | CA30: =CA3-CA18 -> 10800 | ... CE30: =CE3-CE18 -> 10800 | CF30: =SUM(BT30:CE30) -> 126720 | CG30: =IF(CF30=0,"",CF30/CF$3) -> 0.36 | CI30: （売上総利益） | CK30: =CK3-CK18 -> 0 | CL30: =CL3-CL18 -> 0 | CM30: =CM3-CM18 -> 0 | CN30: =CN3-CN18 -> 0 | CO30: =CO3-CO18 -> 0 | CP30: =CP3-CP18 -> 0 | CQ30: =CQ3-CQ18 -> 0 | CR30: =CR3-CR18 -> 0 | ... CV30: =CV3-CV18 -> 0 | CW30: =SUM(CK30:CV30) -> 0 | CX30: =IF(CW30=0,"",CW30/CW$3) | CZ30: （売上総利益） | DB30: =DB3-DB18 -> 0 | DC30: =DC3-DC18 -> 0 | DD30: =DD3-DD18 -> 0 | DE30: =DE3-DE18 -> 0 | DF30: =DF3-DF18 -> 0 | DG30: =DG3-DG18 -> 0 | DH30: =DH3-DH18 -> 0 | DI30: =DI3-DI18 -> 0 | ... DM30: =DM3-DM18 -> 0 | DN30: =SUM(DB30:DM30) -> 0 | DO30: =IF(DN30=0,"",DN30/DN$3) | DQ30: （売上総利益） | DS30: =DS3-DS18 -> 0 | DT30: =DT3-DT18 -> 0 | DU30: =DU3-DU18 -> 0 | DV30: =DV3-DV18 -> 0 | DW30: =DW3-DW18 -> 0 | DX30: =DX3-DX18 -> 0 | DY30: =DY3-DY18 -> 0 | DZ30: =DZ3-DZ18 -> 0 | ... ED30: =ED3-ED18 -> 0 | EE30: =SUM(DS30:ED30) -> 0 | EF30: =IF(EE30=0,"",EE30/EE$3) | EH30: （売上総利益） | EJ30: =EJ3-EJ18 -> 0 | EK30: =EK3-EK18 -> 0 | EL30: =EL3-EL18 -> 0 | EM30: =EM3-EM18 -> 0 | EN30: =EN3-EN18 -> 0 | EO30: =EO3-EO18 -> 0 | EP30: =EP3-EP18 -> 0 | EQ30: =EQ3-EQ18 -> 0 | ... EU30: =EU3-EU18 -> 0 | EV30: =SUM(EJ30:EU30) -> 0 | EW30: =IF(EV30=0,"",EV30/EV$3) | EY30: （売上総利益） | FA30: =FA3-FA18 -> 0 | FB30: =FB3-FB18 -> 0 | FC30: =FC3-FC18 -> 0 | FD30: =FD3-FD18 -> 0 | FE30: =FE3-FE18 -> 0 | FF30: =FF3-FF18 -> 0 | FG30: =FG3-FG18 -> 0 | FH30: =FH3-FH18 -> 0 | ... FL30: =FL3-FL18 -> 0 | FM30: =SUM(FA30:FL30) -> 0 | FN30: =IF(FM30=0,"",FM30/FM$3)
B31: （販管費） | D31: =SUM(D32:D39) -> 0 | E31: =SUM(E32:E39) -> 0 | F31: =SUM(F32:F39) -> 0 | G31: =SUM(G32:G39) -> 0 | H31: =SUM(H32:H39) -> 0 | I31: =SUM(I32:I39) -> 0 | J31: =SUM(J32:J39) -> 0 | K31: =SUM(K32:K39) -> 0 | ... P31: =SUM(P32:P39) -> 0 | Q31: =IF(P31=0,"",P31/$P$3) | S31: （販管費） | U31: =SUM(U32:U39) -> 0 | V31: =SUM(V32:V39) -> 0 | W31: =SUM(W32:W39) -> 0 | X31: =SUM(X32:X39) -> 0 | Y31: =SUM(Y32:Y39) -> 0 | Z31: =SUM(Z32:Z39) -> 0 | AA31: =SUM(AA32:AA39) -> 0 | AB31: =SUM(AB32:AB39) -> 0 | ... AG31: =SUM(AG32:AG39) -> 0 | AH31: =IF(AG31=0,"",AG31/AG$3) | AJ31: （販管費） | AL31: =SUM(AL32:AL39) -> 0 | AM31: =SUM(AM32:AM39) -> 0 | AN31: =SUM(AN32:AN39) -> 0 | AO31: =SUM(AO32:AO39) -> 0 | AP31: =SUM(AP32:AP39) -> 0 | AQ31: =SUM(AQ32:AQ39) -> 0 | AR31: =SUM(AR32:AR39) -> 0 | AS31: =SUM(AS32:AS39) -> 0 | ... AX31: =SUM(AX32:AX39) -> 0 | AY31: =IF(AX31=0,"",AX31/AX$3) | BA31: （販管費） | BC31: =SUM(BC32:BC39) -> 14760 | BD31: =SUM(BD32:BD39) -> 14760 | BE31: =SUM(BE32:BE39) -> 14760 | BF31: =SUM(BF32:BF39) -> 14760 | BG31: =SUM(BG32:BG39) -> 14760 | BH31: =SUM(BH32:BH39) -> 14760 | BI31: =SUM(BI32:BI39) -> 14760 | BJ31: =SUM(BJ32:BJ39) -> 14760 | ... BO31: =SUM(BO32:BO39) -> 177120 | BP31: =IF(BO31=0,"",BO31/BO$3) -> 0.50318182 | BR31: （販管費） | BT31: =SUM(BT32:BT39) -> 15840 | BU31: =SUM(BU32:BU39) -> 15840 | BV31: =SUM(BV32:BV39) -> 15840 | BW31: =SUM(BW32:BW39) -> 15840 | BX31: =SUM(BX32:BX39) -> 15840 | BY31: =SUM(BY32:BY39) -> 15840 | BZ31: =SUM(BZ32:BZ39) -> 15840 | CA31: =SUM(CA32:CA39) -> 15840 | ... CF31: =SUM(CF32:CF39) -> 190080 | CG31: =IF(CF31=0,"",CF31/CF$3) -> 0.54 | CI31: （販管費） | CK31: =SUM(CK32:CK39) -> 27548 | CL31: =SUM(CL32:CL39) -> 27548 | CM31: =SUM(CM32:CM39) -> 27548 | CN31: =SUM(CN32:CN39) -> 27548 | CO31: =SUM(CO32:CO39) -> 27548 | CP31: =SUM(CP32:CP39) -> 27548 | CQ31: =SUM(CQ32:CQ39) -> 30680 | CR31: =SUM(CR32:CR39) -> 30680 | ... CW31: =SUM(CW32:CW39) -> #REF! | CX31: =IF(CW31=0,"",CW31/CW$3) -> #REF! | CZ31: （販管費） | DB31: =SUM(DB32:DB39) -> 32826 | DC31: =SUM(DC32:DC39) -> 32826 | DD31: =SUM(DD32:DD39) -> 32826 | DE31: =SUM(DE32:DE39) -> 32826 | DF31: =SUM(DF32:DF39) -> 32826 | DG31: =SUM(DG32:DG39) -> 32826 | DH31: =SUM(DH32:DH39) -> 34892 | DI31: =SUM(DI32:DI39) -> 34892 | ... DN31: =SUM(DN32:DN39) -> #REF! | DO31: =IF(DN31=0,"",DN31/DN$3) -> #REF! | DQ31: （販管費） | DS31: =SUM(DS32:DS39) -> 37038 | DT31: =SUM(DT32:DT39) -> 37038 | DU31: =SUM(DU32:DU39) -> 37038 | DV31: =SUM(DV32:DV39) -> 37038 | DW31: =SUM(DW32:DW39) -> 40170 | DX31: =SUM(DX32:DX39) -> 42236 | DY31: =SUM(DY32:DY39) -> 42236 | DZ31: =SUM(DZ32:DZ39) -> 42236 | ... EE31: =SUM(EE32:EE39) -> #REF! | EF31: =IF(EE31=0,"",EE31/EE$3) -> #REF! | EH31: （販管費） | EJ31: =SUM(EJ32:EJ39) -> 43316 | EK31: =SUM(EK32:EK39) -> 43316 | EL31: =SUM(EL32:EL39) -> 43316 | EM31: =SUM(EM32:EM39) -> 43316 | EN31: =SUM(EN32:EN39) -> 43316 | EO31: =SUM(EO32:EO39) -> 46448 | EP31: =SUM(EP32:EP39) -> 46448 | EQ31: =SUM(EQ32:EQ39) -> 46448 | ... EV31: =SUM(EV32:EV39) -> #REF! | EW31: =IF(EV31=0,"",EV31/EV$3) -> #REF! | EY31: （販管費） | FA31: =SUM(FA32:FA39) -> 54560 | FB31: =SUM(FB32:FB39) -> 54560 | FC31: =SUM(FC32:FC39) -> 54560 | FD31: =SUM(FD32:FD39) -> 54560 | FE31: =SUM(FE32:FE39) -> 54560 | FF31: =SUM(FF32:FF39) -> 54560 | FG31: =SUM(FG32:FG39) -> 54560 | FH31: =SUM(FH32:FH39) -> 54560 | ... FM31: =SUM(FM32:FM39) -> 654720 | FN31: =IF(FM31=0,"",FM31/FM$3) -> #DIV/0!
C32: 役員報酬 | P32: =SUM(D32:O32) -> 0 | Q32: =IF(P32=0,"",P32/$P$3) | T32: =IF(C32="","",C32) -> 役員報酬 | AG32: =SUM(U32:AF32) -> 0 | AH32: =IF(AG32=0,"",AG32/AG$3) | AK32: =IF(T32="","",T32) -> 役員報酬 | AX32: =SUM(AL32:AW32) -> 0 | AY32: =IF(AX32=0,"",AX32/AX$3) | BB32: 役員報酬 | BC32: 3000 | BD32: 3000 | BE32: 3000 | BF32: 3000 | BG32: 3000 | BH32: 3000 | BI32: 3000 | BJ32: 3000 | BK32: 3000 | BL32: 3000 | BM32: 3000 | BN32: 3000 | BO32: =SUM(BC32:BN32) -> 36000 | BP32: =IF(BO32=0,"",BO32/BO$3) -> 0.10227273 | BS32: 役員報酬 | BT32: 4000 | BU32: 4000 | BV32: 4000 | BW32: 4000 | BX32: 4000 | BY32: 4000 | BZ32: 4000 | CA32: 4000 | CB32: 4000 | CC32: 4000 | CD32: 4000 | CE32: 4000 | CF32: =SUM(BT32:CE32) -> 48000 | CG32: =IF(CF32=0,"",CF32/CF$3) -> 0.13636364 | CJ32: 役員報酬 | CK32: 5000 | CL32: 5000 | CM32: 5000 | CN32: 5000 | CO32: 5000 | CP32: 5000 | CQ32: 5000 | CR32: 5000 | CS32: 5000 | CT32: 5000 | CU32: 5000 | CV32: 5000 | CW32: =SUM(CK32:CV32) -> 60000 | CX32: =IF(CW32=0,"",CW32/CW$3) -> #DIV/0! | DA32: 役員報酬 | DB32: 6000 | DC32: 6000 | DD32: 6000 | DE32: 6000 | DF32: 6000 | DG32: 6000 | DH32: 6000 | DI32: 6000 | DJ32: 6000 | DK32: 6000 | DL32: 6000 | DM32: 6000 | DN32: =SUM(DB32:DM32) -> 72000 | DO32: =IF(DN32=0,"",DN32/DN$3) -> #DIV/0! | DR32: 役員報酬 | DS32: 7000 | DT32: 7000 | DU32: 7000 | DV32: 7000 | DW32: 7000 | DX32: 7000 | DY32: 7000 | DZ32: 7000 | EA32: 7000 | EB32: 7000 | EC32: 7000 | ED32: 7000 | EE32: =SUM(DS32:ED32) -> 84000 | EF32: =IF(EE32=0,"",EE32/EE$3) -> #DIV/0! | EI32: 役員報酬 | EJ32: 8000 | EK32: 8000 | EL32: 8000 | EM32: 8000 | EN32: 8000 | EO32: 8000 | EP32: 8000 | EQ32: 8000 | ER32: 8000 | ES32: 8000 | ET32: 8000 | EU32: 8000 | EV32: =SUM(EJ32:EU32) -> 96000 | EW32: =IF(EV32=0,"",EV32/EV$3) -> #DIV/0! | EZ32: 役員報酬 | FA32: 8000 | FB32: 8000 | FC32: 8000 | FD32: 8000 | FE32: 8000 | FF32: 8000 | FG32: 8000 | FH32: 8000 | FI32: 8000 | FJ32: 8000 | FK32: 8000 | FL32: 8000 | FM32: =SUM(FA32:FL32) -> 96000 | FN32: =IF(FM32=0,"",FM32/FM$3) -> #DIV/0!
C33: 給料手当 | P33: =SUM(D33:O33) -> 0 | Q33: =IF(P33=0,"",P33/$P$3) | T33: =IF(C33="","",C33) -> 給料手当 | AG33: =SUM(U33:AF33) -> 0 | AH33: =IF(AG33=0,"",AG33/AG$3) | AK33: =IF(T33="","",T33) -> 給料手当 | AX33: =SUM(AL33:AW33) -> 0 | AY33: =IF(AX33=0,"",AX33/AX$3) | BB33: 給料手当 | BC33: 2000 | BD33: 2000 | BE33: 2000 | BF33: 2000 | BG33: 2000 | BH33: 2000 | BI33: 2000 | BJ33: 2000 | BK33: 2000 | BL33: 2000 | BM33: 2000 | BN33: 2000 | BO33: =SUM(BC33:BN33) -> 24000 | BP33: =IF(BO33=0,"",BO33/BO$3) -> 0.068181818 | BS33: 給料手当 | BT33: 2000 | BU33: 2000 | BV33: 2000 | BW33: 2000 | BX33: 2000 | BY33: 2000 | BZ33: 2000 | CA33: 2000 | CB33: 2000 | CC33: 2000 | CD33: 2000 | CE33: 2000 | CF33: =SUM(BT33:CE33) -> 24000 | CG33: =IF(CF33=0,"",CF33/CF$3) -> 0.068181818 | CJ33: 給料手当 | CK33: =SUM(CK5:CK8)*400/2+SUM(CK10:CK13)/4*400 -> 3600 | CL33: =SUM(CL5:CL8)*400/2+SUM(CL10:CL13)/4*400 -> 3600 | CM33: =SUM(CM5:CM8)*400/2+SUM(CM10:CM13)/4*400 -> 3600 | CN33: =SUM(CN5:CN8)*400/2+SUM(CN10:CN13)/4*400 -> 3600 | CO33: =SUM(CO5:CO8)*400/2+SUM(CO10:CO13)/4*400 -> 3600 | CP33: =SUM(CP5:CP8)*400/2+SUM(CP10:CP13)/4*400 -> 3600 | CQ33: =SUM(CQ5:CQ8)*400/2+SUM(CQ10:CQ13)/4*400 -> 4000 | CR33: =SUM(CR5:CR8)*400/2+SUM(CR10:CR13)/4*400 -> 4000 | ... CV33: =SUM(CV5:CV8)*400/2+SUM(CV10:CV13)/4*400 -> 4000 | CW33: =SUM(CK33:CV33) -> 45600 | CX33: =IF(CW33=0,"",CW33/CW$3) -> #DIV/0! | DA33: 給料手当 | DB33: =SUM(DB5:DB8)*400/2+SUM(DB10:DB13)/4*400 -> 4200 | DC33: =SUM(DC5:DC8)*400/2+SUM(DC10:DC13)/4*400 -> 4200 | DD33: =SUM(DD5:DD8)*400/2+SUM(DD10:DD13)/4*400 -> 4200 | DE33: =SUM(DE5:DE8)*400/2+SUM(DE10:DE13)/4*400 -> 4200 | DF33: =SUM(DF5:DF8)*400/2+SUM(DF10:DF13)/4*400 -> 4200 | DG33: =SUM(DG5:DG8)*400/2+SUM(DG10:DG13)/4*400 -> 4200 | DH33: =SUM(DH5:DH8)*400/2+SUM(DH10:DH13)/4*400 -> 4400 | DI33: =SUM(DI5:DI8)*400/2+SUM(DI10:DI13)/4*400 -> 4400 | ... DM33: =SUM(DM5:DM8)*400/2+SUM(DM10:DM13)/4*400 -> 4400 | DN33: =SUM(DB33:DM33) -> 51600 | DO33: =IF(DN33=0,"",DN33/DN$3) -> #DIV/0! | DR33: 給料手当 | DS33: =SUM(DS5:DS8)*400/2+SUM(DS10:DS13)/4*400 -> 4600 | DT33: =SUM(DT5:DT8)*400/2+SUM(DT10:DT13)/4*400 -> 4600 | DU33: =SUM(DU5:DU8)*400/2+SUM(DU10:DU13)/4*400 -> 4600 | DV33: =SUM(DV5:DV8)*400/2+SUM(DV10:DV13)/4*400 -> 4600 | DW33: =SUM(DW5:DW8)*400/2+SUM(DW10:DW13)/4*400 -> 5000 | DX33: =SUM(DX5:DX8)*400/2+SUM(DX10:DX13)/4*400 -> 5200 | DY33: =SUM(DY5:DY8)*400/2+SUM(DY10:DY13)/4*400 -> 5200 | DZ33: =SUM(DZ5:DZ8)*400/2+SUM(DZ10:DZ13)/4*400 -> 5200 | ... ED33: =SUM(ED5:ED8)*400/2+SUM(ED10:ED13)/4*400 -> 5200 | EE33: =SUM(DS33:ED33) -> 59800 | EF33: =IF(EE33=0,"",EE33/EE$3) -> #DIV/0! | EI33: 給料手当 | EJ33: =SUM(EJ5:EJ8)*400/2+SUM(EJ10:EJ13)/4*400 -> 5200 | EK33: =SUM(EK5:EK8)*400/2+SUM(EK10:EK13)/4*400 -> 5200 | EL33: =SUM(EL5:EL8)*400/2+SUM(EL10:EL13)/4*400 -> 5200 | EM33: =SUM(EM5:EM8)*400/2+SUM(EM10:EM13)/4*400 -> 5200 | EN33: =SUM(EN5:EN8)*400/2+SUM(EN10:EN13)/4*400 -> 5200 | EO33: =SUM(EO5:EO8)*400/2+SUM(EO10:EO13)/4*400 -> 5600 | EP33: =SUM(EP5:EP8)*400/2+SUM(EP10:EP13)/4*400 -> 5600 | EQ33: =SUM(EQ5:EQ8)*400/2+SUM(EQ10:EQ13)/4*400 -> 5600 | ... EU33: =SUM(EU5:EU8)*400/2+SUM(EU10:EU13)/4*400 -> 6000 | EV33: =SUM(EJ33:EU33) -> 65600 | EW33: =IF(EV33=0,"",EV33/EV$3) -> #DIV/0! | EZ33: 給料手当 | FA33: =SUM(FA5:FA8)*400/2+SUM(FA10:FA13)/4*400 -> 7000 | FB33: =SUM(FB5:FB8)*400/2+SUM(FB10:FB13)/4*400 -> 7000 | FC33: =SUM(FC5:FC8)*400/2+SUM(FC10:FC13)/4*400 -> 7000 | FD33: =SUM(FD5:FD8)*400/2+SUM(FD10:FD13)/4*400 -> 7000 | FE33: =SUM(FE5:FE8)*400/2+SUM(FE10:FE13)/4*400 -> 7000 | FF33: =SUM(FF5:FF8)*400/2+SUM(FF10:FF13)/4*400 -> 7000 | FG33: =SUM(FG5:FG8)*400/2+SUM(FG10:FG13)/4*400 -> 7000 | FH33: =SUM(FH5:FH8)*400/2+SUM(FH10:FH13)/4*400 -> 7000 | ... FL33: =SUM(FL5:FL8)*400/2+SUM(FL10:FL13)/4*400 -> 7000 | FM33: =SUM(FA33:FL33) -> 84000 | FN33: =IF(FM33=0,"",FM33/FM$3) -> #DIV/0!
C34: 法定福利費 | P34: =SUM(D34:O34) -> 0 | Q34: =IF(P34=0,"",P34/$P$3) | T34: =IF(C34="","",C34) -> 法定福利費 | AG34: =SUM(U34:AF34) -> 0 | AH34: =IF(AG34=0,"",AG34/AG$3) | AK34: =IF(T34="","",T34) -> 法定福利費 | AX34: =SUM(AL34:AW34) -> 0 | AY34: =IF(AX34=0,"",AX34/AX$3) | BB34: 法定福利費 | BC34: =(BC32+BC33)*0.08 -> 400 | BD34: =(BD32+BD33)*0.08 -> 400 | BE34: =(BE32+BE33)*0.08 -> 400 | BF34: =(BF32+BF33)*0.08 -> 400 | BG34: =(BG32+BG33)*0.08 -> 400 | BH34: =(BH32+BH33)*0.08 -> 400 | BI34: =(BI32+BI33)*0.08 -> 400 | BJ34: =(BJ32+BJ33)*0.08 -> 400 | ... BN34: =(BN32+BN33)*0.08 -> 400 | BO34: =SUM(BC34:BN34) -> 4800 | BP34: =IF(BO34=0,"",BO34/BO$3) -> 0.013636364 | BS34: 法定福利費 | BT34: =(BT32+BT33)*0.08 -> 480 | BU34: =(BU32+BU33)*0.08 -> 480 | BV34: =(BV32+BV33)*0.08 -> 480 | BW34: =(BW32+BW33)*0.08 -> 480 | BX34: =(BX32+BX33)*0.08 -> 480 | BY34: =(BY32+BY33)*0.08 -> 480 | BZ34: =(BZ32+BZ33)*0.08 -> 480 | CA34: =(CA32+CA33)*0.08 -> 480 | ... CE34: =(CE32+CE33)*0.08 -> 480 | CF34: =SUM(BT34:CE34) -> 5760 | CG34: =IF(CF34=0,"",CF34/CF$3) -> 0.016363636 | CJ34: 法定福利費 | CK34: =(CK32+CK33)*0.08 -> 688 | CL34: =(CL32+CL33)*0.08 -> 688 | CM34: =(CM32+CM33)*0.08 -> 688 | CN34: =(CN32+CN33)*0.08 -> 688 | CO34: =(CO32+CO33)*0.08 -> 688 | CP34: =(CP32+CP33)*0.08 -> 688 | CQ34: =(CQ32+CQ33)*0.08 -> 720 | CR34: =(CR32+CR33)*0.08 -> 720 | ... CV34: =(CV32+CV33)*0.08 -> 720 | CW34: =SUM(CK34:CV34) -> 8448 | CX34: =IF(CW34=0,"",CW34/CW$3) -> #DIV/0! | DA34: 法定福利費 | DB34: =(DB32+DB33)*0.08 -> 816 | DC34: =(DC32+DC33)*0.08 -> 816 | DD34: =(DD32+DD33)*0.08 -> 816 | DE34: =(DE32+DE33)*0.08 -> 816 | DF34: =(DF32+DF33)*0.08 -> 816 | DG34: =(DG32+DG33)*0.08 -> 816 | DH34: =(DH32+DH33)*0.08 -> 832 | DI34: =(DI32+DI33)*0.08 -> 832 | ... DM34: =(DM32+DM33)*0.08 -> 832 | DN34: =SUM(DB34:DM34) -> 9888 | DO34: =IF(DN34=0,"",DN34/DN$3) -> #DIV/0! | DR34: 法定福利費 | DS34: =(DS32+DS33)*0.08 -> 928 | DT34: =(DT32+DT33)*0.08 -> 928 | DU34: =(DU32+DU33)*0.08 -> 928 | DV34: =(DV32+DV33)*0.08 -> 928 | DW34: =(DW32+DW33)*0.08 -> 960 | DX34: =(DX32+DX33)*0.08 -> 976 | DY34: =(DY32+DY33)*0.08 -> 976 | DZ34: =(DZ32+DZ33)*0.08 -> 976 | ... ED34: =(ED32+ED33)*0.08 -> 976 | EE34: =SUM(DS34:ED34) -> 11504 | EF34: =IF(EE34=0,"",EE34/EE$3) -> #DIV/0! | EI34: 法定福利費 | EJ34: =(EJ32+EJ33)*0.08 -> 1056 | EK34: =(EK32+EK33)*0.08 -> 1056 | EL34: =(EL32+EL33)*0.08 -> 1056 | EM34: =(EM32+EM33)*0.08 -> 1056 | EN34: =(EN32+EN33)*0.08 -> 1056 | EO34: =(EO32+EO33)*0.08 -> 1088 | EP34: =(EP32+EP33)*0.08 -> 1088 | EQ34: =(EQ32+EQ33)*0.08 -> 1088 | ... EU34: =(EU32+EU33)*0.08 -> 1120 | EV34: =SUM(EJ34:EU34) -> 12928 | EW34: =IF(EV34=0,"",EV34/EV$3) -> #DIV/0! | EZ34: 法定福利費 | FA34: =(FA32+FA33)*0.08 -> 1200 | FB34: =(FB32+FB33)*0.08 -> 1200 | FC34: =(FC32+FC33)*0.08 -> 1200 | FD34: =(FD32+FD33)*0.08 -> 1200 | FE34: =(FE32+FE33)*0.08 -> 1200 | FF34: =(FF32+FF33)*0.08 -> 1200 | FG34: =(FG32+FG33)*0.08 -> 1200 | FH34: =(FH32+FH33)*0.08 -> 1200 | ... FL34: =(FL32+FL33)*0.08 -> 1200 | FM34: =SUM(FA34:FL34) -> 14400 | FN34: =IF(FM34=0,"",FM34/FM$3) -> #DIV/0!
C35: 事務管理費 | P35: =SUM(D35:O35) -> 0 | Q35: =IF(P35=0,"",P35/$P$3) | T35: =IF(C35="","",C35) -> 事務管理費 | AG35: =SUM(U35:AF35) -> 0 | AH35: =IF(AG35=0,"",AG35/AG$3) | AK35: =IF(T35="","",T35) -> 事務管理費 | AX35: =SUM(AL35:AW35) -> 0 | AY35: =IF(AX35=0,"",AX35/AX$3) | BB35: 店舗管理費 | BC35: 2000 | BD35: 2000 | BE35: 2000 | BF35: 2000 | BG35: 2000 | BH35: 2000 | BI35: 2000 | BJ35: 2000 | BK35: 2000 | BL35: 2000 | BM35: 2000 | BN35: 2000 | BO35: =SUM(BC35:BN35) -> 24000 | BP35: =IF(BO35=0,"",BO35/BO$3) -> 0.068181818 | BS35: 店舗管理費 | BT35: 2000 | BU35: 2000 | BV35: 2000 | BW35: 2000 | BX35: 2000 | BY35: 2000 | BZ35: 2000 | CA35: 2000 | CB35: 2000 | CC35: 2000 | CD35: 2000 | CE35: 2000 | CF35: =SUM(BT35:CE35) -> 24000 | CG35: =IF(CF35=0,"",CF35/CF$3) -> 0.068181818 | CJ35: 店舗管理費 | CK35: =(CK5+CK6+CK7+CK8)*200 -> 3600 | CL35: =(CL5+CL6+CL7+CL8)*200 -> 3600 | CM35: =(CM5+CM6+CM7+CM8)*200 -> 3600 | CN35: =(CN5+CN6+CN7+CN8)*200 -> 3600 | CO35: =(CO5+CO6+CO7+CO8)*200 -> 3600 | CP35: =(CP5+CP6+CP7+CP8)*200 -> 3600 | CQ35: =(CQ5+CQ6+CQ7+CQ8)*200 -> 4000 | CR35: =(CR5+CR6+CR7+CR8)*200 -> 4000 | ... CV35: =(CV5+CV6+CV7+CV8)*200 -> 4000 | CW35: =SUM(CK35:CV35) -> 45600 | CX35: =IF(CW35=0,"",CW35/CW$3) -> #DIV/0! | DA35: 店舗管理費 | DB35: =(DB5+DB6+DB7+DB8)*200 -> 4200 | DC35: =(DC5+DC6+DC7+DC8)*200 -> 4200 | DD35: =(DD5+DD6+DD7+DD8)*200 -> 4200 | DE35: =(DE5+DE6+DE7+DE8)*200 -> 4200 | DF35: =(DF5+DF6+DF7+DF8)*200 -> 4200 | DG35: =(DG5+DG6+DG7+DG8)*200 -> 4200 | DH35: =(DH5+DH6+DH7+DH8)*200 -> 4400 | DI35: =(DI5+DI6+DI7+DI8)*200 -> 4400 | ... DM35: =(DM5+DM6+DM7+DM8)*200 -> 4400 | DN35: =SUM(DB35:DM35) -> 51600 | DO35: =IF(DN35=0,"",DN35/DN$3) -> #DIV/0! | DR35: 店舗管理費 | DS35: =(DS5+DS6+DS7+DS8)*200 -> 4600 | DT35: =(DT5+DT6+DT7+DT8)*200 -> 4600 | DU35: =(DU5+DU6+DU7+DU8)*200 -> 4600 | DV35: =(DV5+DV6+DV7+DV8)*200 -> 4600 | DW35: =(DW5+DW6+DW7+DW8)*200 -> 5000 | DX35: =(DX5+DX6+DX7+DX8)*200 -> 5200 | DY35: =(DY5+DY6+DY7+DY8)*200 -> 5200 | DZ35: =(DZ5+DZ6+DZ7+DZ8)*200 -> 5200 | ... ED35: =(ED5+ED6+ED7+ED8)*200 -> 5200 | EE35: =SUM(DS35:ED35) -> 59800 | EF35: =IF(EE35=0,"",EE35/EE$3) -> #DIV/0! | EI35: 店舗管理費 | EJ35: =(EJ5+EJ6+EJ7+EJ8)*200 -> 5200 | EK35: =(EK5+EK6+EK7+EK8)*200 -> 5200 | EL35: =(EL5+EL6+EL7+EL8)*200 -> 5200 | EM35: =(EM5+EM6+EM7+EM8)*200 -> 5200 | EN35: =(EN5+EN6+EN7+EN8)*200 -> 5200 | EO35: =(EO5+EO6+EO7+EO8)*200 -> 5600 | EP35: =(EP5+EP6+EP7+EP8)*200 -> 5600 | EQ35: =(EQ5+EQ6+EQ7+EQ8)*200 -> 5600 | ... EU35: =(EU5+EU6+EU7+EU8)*200 -> 6000 | EV35: =SUM(EJ35:EU35) -> 65600 | EW35: =IF(EV35=0,"",EV35/EV$3) -> #DIV/0! | EZ35: 店舗管理費 | FA35: =(FA5+FA6+FA7+FA8)*200 -> 7000 | FB35: =(FB5+FB6+FB7+FB8)*200 -> 7000 | FC35: =(FC5+FC6+FC7+FC8)*200 -> 7000 | FD35: =(FD5+FD6+FD7+FD8)*200 -> 7000 | FE35: =(FE5+FE6+FE7+FE8)*200 -> 7000 | FF35: =(FF5+FF6+FF7+FF8)*200 -> 7000 | FG35: =(FG5+FG6+FG7+FG8)*200 -> 7000 | FH35: =(FH5+FH6+FH7+FH8)*200 -> 7000 | ... FL35: =(FL5+FL6+FL7+FL8)*200 -> 7000 | FM35: =SUM(FA35:FL35) -> 84000 | FN35: =IF(FM35=0,"",FM35/FM$3) -> #DIV/0!
C36: 運営管理費 | P36: =SUM(D36:O36) -> 0 | Q36: =IF(P36=0,"",P36/$P$3) | T36: =IF(C36="","",C36) -> 運営管理費 | AG36: =SUM(U36:AF36) -> 0 | AH36: =IF(AG36=0,"",AG36/AG$3) | AK36: =IF(T36="","",T36) -> 運営管理費 | AX36: =SUM(AL36:AW36) -> 0 | AY36: =IF(AX36=0,"",AX36/AX$3) | BB36: 本部管理費 | BC36: 1000 | BD36: 1000 | BE36: 1000 | BF36: 1000 | BG36: 1000 | BH36: 1000 | BI36: 1000 | BJ36: 1000 | BK36: 1000 | BL36: 1000 | BM36: 1000 | BN36: 1000 | BO36: =SUM(BC36:BN36) -> 12000 | BP36: =IF(BO36=0,"",BO36/BO$3) -> 0.034090909 | BS36: 本部管理費 | BT36: 1000 | BU36: 1000 | BV36: 1000 | BW36: 1000 | BX36: 1000 | BY36: 1000 | BZ36: 1000 | CA36: 1000 | CB36: 1000 | CC36: 1000 | CD36: 1000 | CE36: 1000 | CF36: =SUM(BT36:CE36) -> 12000 | CG36: =IF(CF36=0,"",CF36/CF$3) -> 0.034090909 | CJ36: 本部管理費 | CK36: =(CK10+CK11+CK12+CK13)*100 -> 0 | CL36: =(CL10+CL11+CL12+CL13)*100 -> 0 | CM36: =(CM10+CM11+CM12+CM13)*100 -> 0 | CN36: =(CN10+CN11+CN12+CN13)*100 -> 0 | CO36: =(CO10+CO11+CO12+CO13)*100 -> 0 | CP36: =(CP10+CP11+CP12+CP13)*100 -> 0 | CQ36: =(CQ10+CQ11+CQ12+CQ13)*100 -> 0 | CR36: =(CR10+CR11+CR12+CR13)*100 -> 0 | ... CV36: =(CV10+CV11+CV12+CV13)*100 -> 0 | CW36: =SUM(CK36:CV36) -> 0 | CX36: =IF(CW36=0,"",CW36/CW$3) | DA36: 本部管理費 | DB36: =(DB10+DB11+DB12+DB13)*100 -> 0 | DC36: =(DC10+DC11+DC12+DC13)*100 -> 0 | DD36: =(DD10+DD11+DD12+DD13)*100 -> 0 | DE36: =(DE10+DE11+DE12+DE13)*100 -> 0 | DF36: =(DF10+DF11+DF12+DF13)*100 -> 0 | DG36: =(DG10+DG11+DG12+DG13)*100 -> 0 | DH36: =(DH10+DH11+DH12+DH13)*100 -> 0 | DI36: =(DI10+DI11+DI12+DI13)*100 -> 0 | ... DM36: =(DM10+DM11+DM12+DM13)*100 -> 0 | DN36: =SUM(DB36:DM36) -> 0 | DO36: =IF(DN36=0,"",DN36/DN$3) | DR36: 本部管理費 | DS36: =(DS10+DS11+DS12+DS13)*100 -> 0 | DT36: =(DT10+DT11+DT12+DT13)*100 -> 0 | DU36: =(DU10+DU11+DU12+DU13)*100 -> 0 | DV36: =(DV10+DV11+DV12+DV13)*100 -> 0 | DW36: =(DW10+DW11+DW12+DW13)*100 -> 0 | DX36: =(DX10+DX11+DX12+DX13)*100 -> 0 | DY36: =(DY10+DY11+DY12+DY13)*100 -> 0 | DZ36: =(DZ10+DZ11+DZ12+DZ13)*100 -> 0 | ... ED36: =(ED10+ED11+ED12+ED13)*100 -> 0 | EE36: =SUM(DS36:ED36) -> 0 | EF36: =IF(EE36=0,"",EE36/EE$3) | EI36: 本部管理費 | EJ36: =(EJ10+EJ11+EJ12+EJ13)*100 -> 0 | EK36: =(EK10+EK11+EK12+EK13)*100 -> 0 | EL36: =(EL10+EL11+EL12+EL13)*100 -> 0 | EM36: =(EM10+EM11+EM12+EM13)*100 -> 0 | EN36: =(EN10+EN11+EN12+EN13)*100 -> 0 | EO36: =(EO10+EO11+EO12+EO13)*100 -> 0 | EP36: =(EP10+EP11+EP12+EP13)*100 -> 0 | EQ36: =(EQ10+EQ11+EQ12+EQ13)*100 -> 0 | ... EU36: =(EU10+EU11+EU12+EU13)*100 -> 0 | EV36: =SUM(EJ36:EU36) -> 0 | EW36: =IF(EV36=0,"",EV36/EV$3) | EZ36: 本部管理費 | FA36: =(FA10+FA11+FA12+FA13)*100 -> 0 | FB36: =(FB10+FB11+FB12+FB13)*100 -> 0 | FC36: =(FC10+FC11+FC12+FC13)*100 -> 0 | FD36: =(FD10+FD11+FD12+FD13)*100 -> 0 | FE36: =(FE10+FE11+FE12+FE13)*100 -> 0 | FF36: =(FF10+FF11+FF12+FF13)*100 -> 0 | FG36: =(FG10+FG11+FG12+FG13)*100 -> 0 | FH36: =(FH10+FH11+FH12+FH13)*100 -> 0 | ... FL36: =(FL10+FL11+FL12+FL13)*100 -> 0 | FM36: =SUM(FA36:FL36) -> 0 | FN36: =IF(FM36=0,"",FM36/FM$3)
P37: =SUM(D37:O37) -> 0 | Q37: =IF(P37=0,"",P37/$P$3) | T37: =IF(C37="","",C37) | AG37: =SUM(U37:AF37) -> 0 | AH37: =IF(AG37=0,"",AG37/AG$3) | AK37: =IF(T37="","",T37) | AX37: =SUM(AL37:AW37) -> 0 | AY37: =IF(AX37=0,"",AX37/AX$3) | BB37: リース料 | BC37: 360 | BD37: 360 | BE37: 360 | BF37: 360 | BG37: 360 | BH37: 360 | BI37: 360 | BJ37: 360 | BK37: 360 | BL37: 360 | BM37: 360 | BN37: 360 | BO37: =SUM(BC37:BN37) -> 4320 | BP37: =IF(BO37=0,"",BO37/BO$3) -> 0.012272727 | BS37: リース料 | BT37: 360 | BU37: 360 | BV37: 360 | BW37: 360 | BX37: 360 | BY37: 360 | BZ37: 360 | CA37: 360 | CB37: 360 | CC37: 360 | CD37: 360 | CE37: 360 | CF37: =SUM(BT37:CE37) -> 4320 | CG37: =IF(CF37=0,"",CF37/CF$3) -> 0.012272727 | CJ37: リース料 | CK37: 360 | CL37: 360 | CM37: 360 | CN37: 360 | CO37: 360 | CP37: 360 | CQ37: 360 | CR37: 360 | CS37: 360 | CT37: 360 | CU37: 360 | CV37: 360 | CW37: =SUM(CK37:CV37) -> 4320 | CX37: =IF(CW37=0,"",CW37/CW$3) -> #DIV/0! | DA37: リース料 | DB37: 360 | DC37: 360 | DD37: 360 | DE37: 360 | DF37: 360 | DG37: 360 | DH37: 360 | DI37: 360 | DJ37: 360 | DK37: 360 | DL37: 360 | DM37: 360 | DN37: =SUM(DB37:DM37) -> 4320 | DO37: =IF(DN37=0,"",DN37/DN$3) -> #DIV/0! | DR37: リース料 | DS37: 360 | DT37: 360 | DU37: 360 | DV37: 360 | DW37: 360 | DX37: 360 | DY37: 360 | DZ37: 360 | EA37: 360 | EB37: 360 | EC37: 360 | ED37: 360 | EE37: =SUM(DS37:ED37) -> 4320 | EF37: =IF(EE37=0,"",EE37/EE$3) -> #DIV/0! | EI37: リース料 | EJ37: 360 | EK37: 360 | EL37: 360 | EM37: 360 | EN37: 360 | EO37: 360 | EP37: 360 | EQ37: 360 | ER37: 360 | ES37: 360 | ET37: 360 | EU37: 360 | EV37: =SUM(EJ37:EU37) -> 4320 | EW37: =IF(EV37=0,"",EV37/EV$3) -> #DIV/0! | EZ37: リース料 | FA37: 360 | FB37: 360 | FC37: 360 | FD37: 360 | FE37: 360 | FF37: 360 | FG37: 360 | FH37: 360 | FI37: 360 | FJ37: 360 | FK37: 360 | FL37: 360 | FM37: =SUM(FA37:FL37) -> 4320 | FN37: =IF(FM37=0,"",FM37/FM$3) -> #DIV/0!
C38: 地代家賃 | P38: =SUM(D38:O38) -> 0 | Q38: =IF(P38=0,"",P38/$P$3) | T38: =IF(C38="","",C38) -> 地代家賃 | AG38: =SUM(U38:AF38) -> 0 | AH38: =IF(AG38=0,"",AG38/AG$3) | AK38: =IF(T38="","",T38) -> 地代家賃 | AX38: =SUM(AL38:AW38) -> 0 | AY38: =IF(AX38=0,"",AX38/AX$3) | BB38: 地代家賃 | BC38: 6000 | BD38: 6000 | BE38: 6000 | BF38: 6000 | BG38: 6000 | BH38: 6000 | BI38: 6000 | BJ38: 6000 | BK38: 6000 | BL38: 6000 | BM38: 6000 | BN38: 6000 | BO38: =SUM(BC38:BN38) -> 72000 | BP38: =IF(BO38=0,"",BO38/BO$3) -> 0.20454545 | BS38: 地代家賃 | BT38: 6000 | BU38: 6000 | BV38: 6000 | BW38: 6000 | BX38: 6000 | BY38: 6000 | BZ38: 6000 | CA38: 6000 | CB38: 6000 | CC38: 6000 | CD38: 6000 | CE38: 6000 | CF38: =SUM(BT38:CE38) -> 72000 | CG38: =IF(CF38=0,"",CF38/CF$3) -> 0.20454545 | CJ38: 地代家賃 | CK38: =CK5*$F$82+CK6*$F$83+CK7*$F$84+CK8*$F$85 -> 14300 | CL38: =CL5*$F$82+CL6*$F$83+CL7*$F$84+CL8*$F$85 -> 14300 | CM38: =CM5*$F$82+CM6*$F$83+CM7*$F$84+CM8*$F$85 -> 14300 | CN38: =CN5*$F$82+CN6*$F$83+CN7*$F$84+CN8*$F$85 -> 14300 | CO38: =CO5*$F$82+CO6*$F$83+CO7*$F$84+CO8*$F$85 -> 14300 | CP38: =CP5*$F$82+CP6*$F$83+CP7*$F$84+CP8*$F$85 -> 14300 | CQ38: =CQ5*$F$82+CQ6*$F$83+CQ7*$F$84+CQ8*$F$85 -> 16600 | CR38: =CR5*$F$82+CR6*$F$83+CR7*$F$84+CR8*$F$85 -> 16600 | ... CV38: =CV5*$F$82+CV6*$F$83+CV7*$F$84+CV8*$F$85 -> 16600 | CW38: =SUM(CK38:CV38) -> 185400 | CX38: =IF(CW38=0,"",CW38/CW$3) -> #DIV/0! | DA38: 地代家賃 | DB38: =DB5*$F$82+DB6*$F$83+DB7*$F$84+DB8*$F$85 -> 17250 | DC38: =DC5*$F$82+DC6*$F$83+DC7*$F$84+DC8*$F$85 -> 17250 | DD38: =DD5*$F$82+DD6*$F$83+DD7*$F$84+DD8*$F$85 -> 17250 | DE38: =DE5*$F$82+DE6*$F$83+DE7*$F$84+DE8*$F$85 -> 17250 | DF38: =DF5*$F$82+DF6*$F$83+DF7*$F$84+DF8*$F$85 -> 17250 | DG38: =DG5*$F$82+DG6*$F$83+DG7*$F$84+DG8*$F$85 -> 17250 | DH38: =DH5*$F$82+DH6*$F$83+DH7*$F$84+DH8*$F$85 -> 18900 | DI38: =DI5*$F$82+DI6*$F$83+DI7*$F$84+DI8*$F$85 -> 18900 | ... DM38: =DM5*$F$82+DM6*$F$83+DM7*$F$84+DM8*$F$85 -> 18900 | DN38: =SUM(DB38:DM38) -> 216900 | DO38: =IF(DN38=0,"",DN38/DN$3) -> #DIV/0! | DR38: 地代家賃 | DS38: =DS5*$F$82+DS6*$F$83+DS7*$F$84+DS8*$F$85 -> 19550 | DT38: =DT5*$F$82+DT6*$F$83+DT7*$F$84+DT8*$F$85 -> 19550 | DU38: =DU5*$F$82+DU6*$F$83+DU7*$F$84+DU8*$F$85 -> 19550 | DV38: =DV5*$F$82+DV6*$F$83+DV7*$F$84+DV8*$F$85 -> 19550 | DW38: =DW5*$F$82+DW6*$F$83+DW7*$F$84+DW8*$F$85 -> 21850 | DX38: =DX5*$F$82+DX6*$F$83+DX7*$F$84+DX8*$F$85 -> 23500 | DY38: =DY5*$F$82+DY6*$F$83+DY7*$F$84+DY8*$F$85 -> 23500 | DZ38: =DZ5*$F$82+DZ6*$F$83+DZ7*$F$84+DZ8*$F$85 -> 23500 | ... ED38: =ED5*$F$82+ED6*$F$83+ED7*$F$84+ED8*$F$85 -> 23500 | EE38: =SUM(DS38:ED38) -> 264550 | EF38: =IF(EE38=0,"",EE38/EE$3) -> #DIV/0! | EI38: 地代家賃 | EJ38: =EJ5*$F$82+EJ6*$F$83+EJ7*$F$84+EJ8*$F$85 -> 23500 | EK38: =EK5*$F$82+EK6*$F$83+EK7*$F$84+EK8*$F$85 -> 23500 | EL38: =EL5*$F$82+EL6*$F$83+EL7*$F$84+EL8*$F$85 -> 23500 | EM38: =EM5*$F$82+EM6*$F$83+EM7*$F$84+EM8*$F$85 -> 23500 | EN38: =EN5*$F$82+EN6*$F$83+EN7*$F$84+EN8*$F$85 -> 23500 | EO38: =EO5*$F$82+EO6*$F$83+EO7*$F$84+EO8*$F$85 -> 25800 | EP38: =EP5*$F$82+EP6*$F$83+EP7*$F$84+EP8*$F$85 -> 25800 | EQ38: =EQ5*$F$82+EQ6*$F$83+EQ7*$F$84+EQ8*$F$85 -> 25800 | ... EU38: =EU5*$F$82+EU6*$F$83+EU7*$F$84+EU8*$F$85 -> 26750 | EV38: =SUM(EJ38:EU38) -> 299050 | EW38: =IF(EV38=0,"",EV38/EV$3) -> #DIV/0! | EZ38: 地代家賃 | FA38: =FA5*$F$82+FA6*$F$83+FA7*$F$84+FA8*$F$85 -> 31000 | FB38: =FB5*$F$82+FB6*$F$83+FB7*$F$84+FB8*$F$85 -> 31000 | FC38: =FC5*$F$82+FC6*$F$83+FC7*$F$84+FC8*$F$85 -> 31000 | FD38: =FD5*$F$82+FD6*$F$83+FD7*$F$84+FD8*$F$85 -> 31000 | FE38: =FE5*$F$82+FE6*$F$83+FE7*$F$84+FE8*$F$85 -> 31000 | FF38: =FF5*$F$82+FF6*$F$83+FF7*$F$84+FF8*$F$85 -> 31000 | FG38: =FG5*$F$82+FG6*$F$83+FG7*$F$84+FG8*$F$85 -> 31000 | FH38: =FH5*$F$82+FH6*$F$83+FH7*$F$84+FH8*$F$85 -> 31000 | ... FL38: =FL5*$F$82+FL6*$F$83+FL7*$F$84+FL8*$F$85 -> 31000 | FM38: =SUM(FA38:FL38) -> 372000 | FN38: =IF(FM38=0,"",FM38/FM$3) -> #DIV/0!
C39: 減価償却 | Q39: =IF(P39=0,"",P39/$P$3) | T39: =IF(C39="","",C39) -> 減価償却 | AG39: =SUM(U39:AF39) -> 0 | AH39: =IF(AG39=0,"",AG39/AG$3) | AK39: =IF(T39="","",T39) -> 減価償却 | AX39: =SUM(AL39:AW39) -> 0 | AY39: =IF(AX39=0,"",AX39/AX$3) | BB39: 減価償却 | BO39: =SUM(BC39:BN39) -> 0 | BP39: =IF(BO39=0,"",BO39/BO$3) | BS39: 減価償却 | CF39: =SUM(BT39:CE39) -> 0 | CG39: =IF(CF39=0,"",CF39/CF$3) | CJ39: 減価償却 | CV39: =BS!C38 -> #REF! | CW39: =SUM(CK39:CV39) -> #REF! | CX39: =IF(CW39=0,"",CW39/CW$3) -> #REF! | DA39: 減価償却 | DM39: =BS!G38 -> #REF! | DN39: =SUM(DB39:DM39) -> #REF! | DO39: =IF(DN39=0,"",DN39/DN$3) -> #REF! | DR39: 減価償却 | ED39: =BS!K38 -> #REF! | EE39: =SUM(DS39:ED39) -> #REF! | EF39: =IF(EE39=0,"",EE39/EE$3) -> #REF! | EI39: 減価償却 | EU39: =BS!O38 -> #REF! | EV39: =SUM(EJ39:EU39) -> #REF! | EW39: =IF(EV39=0,"",EV39/EV$3) -> #REF! | EZ39: 減価償却 | FL39: =BS!S38 -> #REF! | FN39: =IF(FM39=0,"",FM39/FM$3)
B40: （事業収益） | D40: =D30-D31 -> 0 | E40: =E30-E31 -> 0 | F40: =F30-F31 -> 0 | G40: =G30-G31 -> 0 | H40: =H30-H31 -> 0 | I40: =I30-I31 -> 0 | J40: =J30-J31 -> 0 | K40: =K30-K31 -> 0 | ... O40: =O30-O31 -> 0 | P40: =SUM(D40:O40) -> 100000 | Q40: =IF(P40=0,"",P40/$P$3) -> 1 | S40: （営業利益） | U40: =U30-U31 -> 453197.9 | V40: =V30-V31 -> 607891.9 | W40: =W30-W31 -> 514891.9 | X40: =X30-X31 -> 456069.2 | Y40: =Y30-Y31 -> 456069.2 | Z40: =Z30-Z31 -> 495893.2 | AA40: =AA30-AA31 -> 495893.2 | AB40: =AB30-AB31 -> 585717.2 | ... AF40: =AF30-AF31 -> 765365.2 | AG40: =SUM(U40:AF40) -> 6767788.5 | AH40: =IF(AG40=0,"",AG40/AG$3) -> 0.39089268 | AJ40: （営業利益） | AL40: =AL30-AL31 -> 214551.2 | AM40: =AM30-AM31 -> 361245.2 | AN40: =AN30-AN31 -> 356245.2 | AO40: =AO30-AO31 -> 446069.2 | AP40: =AP30-AP31 -> 446069.2 | AQ40: =AQ30-AQ31 -> 535893.2 | AR40: =AR30-AR31 -> 535893.2 | AS40: =AS30-AS31 -> 625717.2 | ... AW40: =AW30-AW31 -> 805365.2 | AX40: =SUM(AL40:AW40) -> 6383848.4 | AY40: =IF(AX40=0,"",AX40/AX$3) -> 0.36492325 | BA40: （営業利益） | BC40: =BC30-BC31 -> -4320 | BD40: =BD30-BD31 -> -4320 | BE40: =BE30-BE31 -> -4320 | BF40: =BF30-BF31 -> -4320 | BG40: =BG30-BG31 -> -4320 | BH40: =BH30-BH31 -> -4680 | BI40: =BI30-BI31 -> -4320 | BJ40: =BJ30-BJ31 -> -3960 | ... BN40: =BN30-BN31 -> -3960 | BO40: =SUM(BC40:BN40) -> -50400 | BP40: =IF(BO40=0,"",BO40/BO$3) -> -0.14318182 | BR40: （営業利益） | BT40: =BT30-BT31 -> -5400 | BU40: =BU30-BU31 -> -5400 | BV40: =BV30-BV31 -> -5400 | BW40: =BW30-BW31 -> -5400 | BX40: =BX30-BX31 -> -5400 | BY40: =BY30-BY31 -> -5760 | BZ40: =BZ30-BZ31 -> -5400 | CA40: =CA30-CA31 -> -5040 | ... CE40: =CE30-CE31 -> -5040 | CF40: =SUM(BT40:CE40) -> -63360 | CG40: =IF(CF40=0,"",CF40/CF$3) -> -0.18 | CI40: （営業利益） | CK40: =CK30-CK31 -> -27548 | CL40: =CL30-CL31 -> -27548 | CM40: =CM30-CM31 -> -27548 | CN40: =CN30-CN31 -> -27548 | CO40: =CO30-CO31 -> -27548 | CP40: =CP30-CP31 -> -27548 | CQ40: =CQ30-CQ31 -> -30680 | CR40: =CR30-CR31 -> -30680 | ... CV40: =CV30-CV31 -> #REF! | CW40: =SUM(CK40:CV40) -> #REF! | CX40: =IF(CW40=0,"",CW40/CW$3) -> #REF! | CZ40: （営業利益） | DB40: =DB30-DB31 -> -32826 | DC40: =DC30-DC31 -> -32826 | DD40: =DD30-DD31 -> -32826 | DE40: =DE30-DE31 -> -32826 | DF40: =DF30-DF31 -> -32826 | DG40: =DG30-DG31 -> -32826 | DH40: =DH30-DH31 -> -34892 | DI40: =DI30-DI31 -> -34892 | ... DM40: =DM30-DM31 -> #REF! | DN40: =SUM(DB40:DM40) -> #REF! | DO40: =IF(DN40=0,"",DN40/DN$3) -> #REF! | DQ40: （営業利益） | DS40: =DS30-DS31 -> -37038 | DT40: =DT30-DT31 -> -37038 | DU40: =DU30-DU31 -> -37038 | DV40: =DV30-DV31 -> -37038 | DW40: =DW30-DW31 -> -40170 | DX40: =DX30-DX31 -> -42236 | DY40: =DY30-DY31 -> -42236 | DZ40: =DZ30-DZ31 -> -42236 | ... ED40: =ED30-ED31 -> #REF! | EE40: =SUM(DS40:ED40) -> #REF! | EF40: =IF(EE40=0,"",EE40/EE$3) -> #REF! | EH40: （営業利益） | EJ40: =EJ30-EJ31 -> -43316 | EK40: =EK30-EK31 -> -43316 | EL40: =EL30-EL31 -> -43316 | EM40: =EM30-EM31 -> -43316 | EN40: =EN30-EN31 -> -43316 | EO40: =EO30-EO31 -> -46448 | EP40: =EP30-EP31 -> -46448 | EQ40: =EQ30-EQ31 -> -46448 | ... EU40: =EU30-EU31 -> #REF! | EV40: =SUM(EJ40:EU40) -> #REF! | EW40: =IF(EV40=0,"",EV40/EV$3) -> #REF! | EY40: （営業利益） | FA40: =FA30-FA31 -> -54560 | FB40: =FB30-FB31 -> -54560 | FC40: =FC30-FC31 -> -54560 | FD40: =FD30-FD31 -> -54560 | FE40: =FE30-FE31 -> -54560 | FF40: =FF30-FF31 -> -54560 | FG40: =FG30-FG31 -> -54560 | FH40: =FH30-FH31 -> -54560 | ... FL40: =FL30-FL31 -> #REF! | FM40: =SUM(FA40:FL40) -> #REF! | FN40: =IF(FM40=0,"",FM40/FM$3) -> #REF!
B41: （営業外収益） | P41: =SUM(D41:O41) -> 0 | Q41: =IF(P41=0,"",P41/$P$3) | S41: （営業外収益） | AG41: =SUM(U41:AF41) -> 0 | AH41: =IF(AG41=0,"",AG41/AG$3) | AJ41: （営業外収益） | AX41: =SUM(AL41:AW41) -> 0 | AY41: =IF(AX41=0,"",AX41/AX$3) | BA41: （営業外収益） | BO41: =SUM(BC41:BN41) -> 0 | BP41: =IF(BO41=0,"",BO41/BO$3) | BR41: （営業外収益） | CF41: =SUM(BT41:CE41) -> 0 | CG41: =IF(CF41=0,"",CF41/CF$3) | CI41: （営業外収益） | CW41: =SUM(CK41:CV41) -> 0 | CX41: =IF(CW41=0,"",CW41/CW$3) | CZ41: （営業外収益） | DN41: =SUM(DB41:DM41) -> 0 | DO41: =IF(DN41=0,"",DN41/DN$3) | DQ41: （営業外収益） | EE41: =SUM(DS41:ED41) -> 0 | EF41: =IF(EE41=0,"",EE41/EE$3) | EH41: （営業外収益） | EV41: =SUM(EJ41:EU41) -> 0 | EW41: =IF(EV41=0,"",EV41/EV$3) | EY41: （営業外収益） | FM41: =SUM(FA41:FL41) -> 0 | FN41: =IF(FM41=0,"",FM41/FM$3)
B42: （営業外損失） | D42: =SUM(D43:D44) -> 0 | E42: =SUM(E43:E44) -> 0 | F42: =SUM(F43:F44) -> 0 | G42: =SUM(G43:G44) -> 0 | H42: =SUM(H43:H44) -> 0 | I42: =SUM(I43:I44) -> 0 | J42: =SUM(J43:J44) -> 0 | K42: =SUM(K43:K44) -> 0 | ... O42: =SUM(O43:O44) -> 0 | P42: =SUM(D42:O42) -> 0 | Q42: =IF(P42=0,"",P42/$P$3) | S42: （営業外損失） | U42: =SUM(U43:U44) -> 0 | V42: =SUM(V43:V44) -> 0 | W42: =SUM(W43:W44) -> 0 | X42: =SUM(X43:X44) -> 0 | Y42: =SUM(Y43:Y44) -> 0 | Z42: =SUM(Z43:Z44) -> 0 | AA42: =SUM(AA43:AA44) -> 0 | AB42: =SUM(AB43:AB44) -> 0 | ... AF42: =SUM(AF43:AF44) -> 0 | AG42: =SUM(U42:AF42) -> 0 | AH42: =IF(AG42=0,"",AG42/AG$3) | AJ42: （営業外損失） | AL42: =SUM(AL43:AL44) -> 0 | AM42: =SUM(AM43:AM44) -> 0 | AN42: =SUM(AN43:AN44) -> 0 | AO42: =SUM(AO43:AO44) -> 0 | AP42: =SUM(AP43:AP44) -> 0 | AQ42: =SUM(AQ43:AQ44) -> 0 | AR42: =SUM(AR43:AR44) -> 0 | AS42: =SUM(AS43:AS44) -> 0 | ... AW42: =SUM(AW43:AW44) -> 0 | AX42: =SUM(AL42:AW42) -> 0 | AY42: =IF(AX42=0,"",AX42/AX$3) | BA42: （営業外損失） | BC42: =SUM(BC43:BC44) -> 0 | BD42: =SUM(BD43:BD44) -> 0 | BE42: =SUM(BE43:BE44) -> 0 | BF42: =SUM(BF43:BF44) -> 0 | BG42: =SUM(BG43:BG44) -> 0 | BH42: =SUM(BH43:BH44) -> 0 | BI42: =SUM(BI43:BI44) -> 0 | BJ42: =SUM(BJ43:BJ44) -> 0 | ... BN42: =SUM(BN43:BN44) -> 0 | BO42: =SUM(BC42:BN42) -> 0 | BP42: =IF(BO42=0,"",BO42/BO$3) | BR42: （営業外損失） | BT42: =SUM(BT43:BT44) -> 0 | BU42: =SUM(BU43:BU44) -> 0 | BV42: =SUM(BV43:BV44) -> 0 | BW42: =SUM(BW43:BW44) -> 0 | BX42: =SUM(BX43:BX44) -> 0 | BY42: =SUM(BY43:BY44) -> 0 | BZ42: =SUM(BZ43:BZ44) -> 0 | CA42: =SUM(CA43:CA44) -> 0 | ... CE42: =SUM(CE43:CE44) -> 0 | CF42: =SUM(BT42:CE42) -> 0 | CG42: =IF(CF42=0,"",CF42/CF$3) | CI42: （営業外損失） | CK42: =SUM(CK43:CK44) -> 0 | CL42: =SUM(CL43:CL44) -> 0 | CM42: =SUM(CM43:CM44) -> 0 | CN42: =SUM(CN43:CN44) -> 0 | CO42: =SUM(CO43:CO44) -> 0 | CP42: =SUM(CP43:CP44) -> 0 | CQ42: =SUM(CQ43:CQ44) -> 0 | CR42: =SUM(CR43:CR44) -> 0 | ... CV42: =SUM(CV43:CV44) -> 0 | CW42: =SUM(CK42:CV42) -> 0 | CX42: =IF(CW42=0,"",CW42/CW$3) | CZ42: （営業外損失） | DB42: =SUM(DB43:DB44) -> 0 | DC42: =SUM(DC43:DC44) -> 0 | DD42: =SUM(DD43:DD44) -> 0 | DE42: =SUM(DE43:DE44) -> 0 | DF42: =SUM(DF43:DF44) -> 0 | DG42: =SUM(DG43:DG44) -> 0 | DH42: =SUM(DH43:DH44) -> 0 | DI42: =SUM(DI43:DI44) -> 0 | ... DM42: =SUM(DM43:DM44) -> 0 | DN42: =SUM(DB42:DM42) -> 0 | DO42: =IF(DN42=0,"",DN42/DN$3) | DQ42: （営業外損失） | DS42: =SUM(DS43:DS44) -> 0 | DT42: =SUM(DT43:DT44) -> 0 | DU42: =SUM(DU43:DU44) -> 0 | DV42: =SUM(DV43:DV44) -> 0 | DW42: =SUM(DW43:DW44) -> 0 | DX42: =SUM(DX43:DX44) -> 0 | DY42: =SUM(DY43:DY44) -> 0 | DZ42: =SUM(DZ43:DZ44) -> 0 | ... ED42: =SUM(ED43:ED44) -> 0 | EE42: =SUM(DS42:ED42) -> 0 | EF42: =IF(EE42=0,"",EE42/EE$3) | EH42: （営業外損失） | EJ42: =SUM(EJ43:EJ44) -> 0 | EK42: =SUM(EK43:EK44) -> 0 | EL42: =SUM(EL43:EL44) -> 0 | EM42: =SUM(EM43:EM44) -> 0 | EN42: =SUM(EN43:EN44) -> 0 | EO42: =SUM(EO43:EO44) -> 0 | EP42: =SUM(EP43:EP44) -> 0 | EQ42: =SUM(EQ43:EQ44) -> 0 | ... EU42: =SUM(EU43:EU44) -> 0 | EV42: =SUM(EJ42:EU42) -> 0 | EW42: =IF(EV42=0,"",EV42/EV$3) | EY42: （営業外損失） | FA42: =SUM(FA43:FA44) -> 0 | FB42: =SUM(FB43:FB44) -> 0 | FC42: =SUM(FC43:FC44) -> 0 | FD42: =SUM(FD43:FD44) -> 0 | FE42: =SUM(FE43:FE44) -> 0 | FF42: =SUM(FF43:FF44) -> 0 | FG42: =SUM(FG43:FG44) -> 0 | FH42: =SUM(FH43:FH44) -> 0 | ... FL42: =SUM(FL43:FL44) -> 0 | FM42: =SUM(FA42:FL42) -> 0 | FN42: =IF(FM42=0,"",FM42/FM$3)
C43: 支払利息 | P43: =SUM(D43:O43) -> 0 | Q43: =IF(P43=0,"",P43/$P$3) | T43: 支払利息 | AG43: =SUM(U43:AF43) -> 0 | AH43: =IF(AG43=0,"",AG43/AG$3) | AK43: 支払利息 | AX43: =SUM(AL43:AW43) -> 0 | AY43: =IF(AX43=0,"",AX43/AX$3) | BB43: 支払利息 | BC43: ='金融借入（移行計算）'!AL6/1000 -> 0 | BD43: ='金融借入（移行計算）'!AM6/1000 -> 0 | BE43: ='金融借入（移行計算）'!AN6/1000 -> 0 | BF43: ='金融借入（移行計算）'!AO6/1000 -> 0 | BG43: ='金融借入（移行計算）'!AP6/1000 -> 0 | BH43: ='金融借入（移行計算）'!AQ6/1000 -> 0 | BI43: ='金融借入（移行計算）'!AR6/1000 -> 0 | BJ43: ='金融借入（移行計算）'!AS6/1000 -> 0 | ... BN43: ='金融借入（移行計算）'!AW6/1000 -> 0 | BO43: =SUM(BC43:BN43) -> 0 | BP43: =IF(BO43=0,"",BO43/BO$3) | BS43: 支払利息 | BT43: ='金融借入（移行計算）'!AW6/1000 -> 0 | BU43: ='金融借入（移行計算）'!AX6/1000 -> 0 | BV43: ='金融借入（移行計算）'!AY6/1000 -> 0 | BW43: ='金融借入（移行計算）'!AZ6/1000 -> 0 | BX43: ='金融借入（移行計算）'!BA6/1000 -> 0 | BY43: ='金融借入（移行計算）'!BB6/1000 -> 0 | BZ43: ='金融借入（移行計算）'!BC6/1000 -> 0 | CA43: ='金融借入（移行計算）'!BD6/1000 -> 0 | ... CE43: ='金融借入（移行計算）'!BH6/1000 -> 0 | CF43: =SUM(BT43:CE43) -> 0 | CG43: =IF(CF43=0,"",CF43/CF$3) | CJ43: 支払利息 | CK43: ='金融借入（移行計算）'!BI6/1000 -> 0 | CL43: ='金融借入（移行計算）'!BJ6/1000 -> 0 | CM43: ='金融借入（移行計算）'!BK6/1000 -> 0 | CN43: ='金融借入（移行計算）'!BL6/1000 -> 0 | CO43: ='金融借入（移行計算）'!BM6/1000 -> 0 | CP43: ='金融借入（移行計算）'!BN6/1000 -> 0 | CQ43: ='金融借入（移行計算）'!BO6/1000 -> 0 | CR43: ='金融借入（移行計算）'!BP6/1000 -> 0 | ... CV43: ='金融借入（移行計算）'!BT6/1000 -> 0 | CW43: =SUM(CK43:CV43) -> 0 | CX43: =IF(CW43=0,"",CW43/CW$3) | DA43: 支払利息 | DB43: ='金融借入（移行計算）'!BU6/1000 -> 0 | DC43: ='金融借入（移行計算）'!BV6/1000 -> 0 | DD43: ='金融借入（移行計算）'!BW6/1000 -> 0 | DE43: ='金融借入（移行計算）'!BX6/1000 -> 0 | DF43: ='金融借入（移行計算）'!BY6/1000 -> 0 | DG43: ='金融借入（移行計算）'!BZ6/1000 -> 0 | DH43: ='金融借入（移行計算）'!CA6/1000 -> 0 | DI43: ='金融借入（移行計算）'!CB6/1000 -> 0 | ... DM43: ='金融借入（移行計算）'!CF6/1000 -> 0 | DN43: =SUM(DB43:DM43) -> 0 | DO43: =IF(DN43=0,"",DN43/DN$3) | DR43: 支払利息 | DS43: ='金融借入（移行計算）'!CG6/1000 -> 0 | DT43: ='金融借入（移行計算）'!CH6/1000 -> 0 | DU43: ='金融借入（移行計算）'!CI6/1000 -> 0 | DV43: ='金融借入（移行計算）'!CJ6/1000 -> 0 | DW43: ='金融借入（移行計算）'!CK6/1000 -> 0 | DX43: ='金融借入（移行計算）'!CL6/1000 -> 0 | DY43: ='金融借入（移行計算）'!CM6/1000 -> 0 | DZ43: ='金融借入（移行計算）'!CN6/1000 -> 0 | ... ED43: ='金融借入（移行計算）'!CR6/1000 -> 0 | EE43: =SUM(DS43:ED43) -> 0 | EF43: =IF(EE43=0,"",EE43/EE$3) | EI43: 支払利息 | EJ43: ='金融借入（移行計算）'!CS6/1000 -> 0 | EK43: ='金融借入（移行計算）'!CT6/1000 -> 0 | EL43: ='金融借入（移行計算）'!CU6/1000 -> 0 | EM43: ='金融借入（移行計算）'!CV6/1000 -> 0 | EN43: ='金融借入（移行計算）'!CW6/1000 -> 0 | EO43: ='金融借入（移行計算）'!CX6/1000 -> 0 | EP43: ='金融借入（移行計算）'!CY6/1000 -> 0 | EQ43: ='金融借入（移行計算）'!CZ6/1000 -> 0 | ... EU43: ='金融借入（移行計算）'!DD6/1000 -> 0 | EV43: =SUM(EJ43:EU43) -> 0 | EW43: =IF(EV43=0,"",EV43/EV$3) | EZ43: 支払利息 | FA43: ='金融借入（移行計算）'!DE6/1000 -> 0 | FB43: ='金融借入（移行計算）'!DF6/1000 -> 0 | FC43: ='金融借入（移行計算）'!DG6/1000 -> 0 | FD43: ='金融借入（移行計算）'!DH6/1000 -> 0 | FE43: ='金融借入（移行計算）'!DI6/1000 -> 0 | FF43: ='金融借入（移行計算）'!DJ6/1000 -> 0 | FG43: ='金融借入（移行計算）'!DK6/1000 -> 0 | FH43: ='金融借入（移行計算）'!DL6/1000 -> 0 | ... FL43: ='金融借入（移行計算）'!DP6/1000 -> 0 | FM43: =SUM(FA43:FL43) -> 0 | FN43: =IF(FM43=0,"",FM43/FM$3)
C44: 雑損失 | P44: =SUM(D44:O44) -> 0 | Q44: =IF(P44=0,"",P44/$P$3) | T44: 雑損失 | AG44: =SUM(U44:AF44) -> 0 | AH44: =IF(AG44=0,"",AG44/AG$3) | AK44: 雑損失 | AX44: =SUM(AL44:AW44) -> 0 | AY44: =IF(AX44=0,"",AX44/AX$3) | BB44: 雑損失 | BO44: =SUM(BC44:BN44) -> 0 | BP44: =IF(BO44=0,"",BO44/BO$3) | BS44: 雑損失 | CF44: =SUM(BT44:CE44) -> 0 | CG44: =IF(CF44=0,"",CF44/CF$3) | CJ44: 雑損失 | CW44: =SUM(CK44:CV44) -> 0 | CX44: =IF(CW44=0,"",CW44/CW$3) | DA44: 雑損失 | DN44: =SUM(DB44:DM44) -> 0 | DO44: =IF(DN44=0,"",DN44/DN$3) | DR44: 雑損失 | EE44: =SUM(DS44:ED44) -> 0 | EF44: =IF(EE44=0,"",EE44/EE$3) | EI44: 雑損失 | EV44: =SUM(EJ44:EU44) -> 0 | EW44: =IF(EV44=0,"",EV44/EV$3) | EZ44: 雑損失 | FM44: =SUM(FA44:FL44) -> 0 | FN44: =IF(FM44=0,"",FM44/FM$3)
B45: （経常収支） | F45: =F40+F41-F42 -> 0 | G45: =G40+G41-G42 -> 0 | H45: =H40+H41-H42 -> 0 | I45: =I40+I41-I42 -> 0 | J45: =J40+J41-J42 -> 0 | K45: =K40+K41-K42 -> 0 | L45: =L40+L41-L42 -> 0 | M45: =M40+M41-M42 -> 0 | ... O45: =O40+O41-O42 -> 0 | P45: =SUM(D45:O45) -> 100000 | Q45: =IF(P45=0,"",P45/$P$3) -> 1 | S45: （経常利益） | U45: =U40+U41-U42 -> 453197.9 | V45: =V40+V41-V42 -> 607891.9 | W45: =W40+W41-W42 -> 514891.9 | X45: =X40+X41-X42 -> 456069.2 | Y45: =Y40+Y41-Y42 -> 456069.2 | Z45: =Z40+Z41-Z42 -> 495893.2 | AA45: =AA40+AA41-AA42 -> 495893.2 | AB45: =AB40+AB41-AB42 -> 585717.2 | ... AF45: =AF40+AF41-AF42 -> 765365.2 | AG45: =SUM(U45:AF45) -> 6767788.5 | AH45: =IF(AG45=0,"",AG45/AG$3) -> 0.39089268 | AJ45: （経常利益） | AL45: =AL40+AL41-AL42 -> 214551.2 | AM45: =AM40+AM41-AM42 -> 361245.2 | AN45: =AN40+AN41-AN42 -> 356245.2 | AO45: =AO40+AO41-AO42 -> 446069.2 | AP45: =AP40+AP41-AP42 -> 446069.2 | AQ45: =AQ40+AQ41-AQ42 -> 535893.2 | AR45: =AR40+AR41-AR42 -> 535893.2 | AS45: =AS40+AS41-AS42 -> 625717.2 | ... AW45: =AW40+AW41-AW42 -> 805365.2 | AX45: =SUM(AL45:AW45) -> 6383848.4 | AY45: =IF(AX45=0,"",AX45/AX$3) -> 0.36492325 | BA45: （経常利益） | BC45: =BC40+BC41-BC42 -> -4320 | BD45: =BD40+BD41-BD42 -> -4320 | BE45: =BE40+BE41-BE42 -> -4320 | BF45: =BF40+BF41-BF42 -> -4320 | BG45: =BG40+BG41-BG42 -> -4320 | BH45: =BH40+BH41-BH42 -> -4680 | BI45: =BI40+BI41-BI42 -> -4320 | BJ45: =BJ40+BJ41-BJ42 -> -3960 | ... BN45: =BN40+BN41-BN42 -> -3960 | BO45: =SUM(BC45:BN45) -> -50400 | BP45: =IF(BO45=0,"",BO45/BO$3) -> -0.14318182 | BR45: （経常利益） | BT45: =BT40+BT41-BT42 -> -5400 | BU45: =BU40+BU41-BU42 -> -5400 | BV45: =BV40+BV41-BV42 -> -5400 | BW45: =BW40+BW41-BW42 -> -5400 | BX45: =BX40+BX41-BX42 -> -5400 | BY45: =BY40+BY41-BY42 -> -5760 | BZ45: =BZ40+BZ41-BZ42 -> -5400 | CA45: =CA40+CA41-CA42 -> -5040 | ... CE45: =CE40+CE41-CE42 -> -5040 | CF45: =SUM(BT45:CE45) -> -63360 | CG45: =IF(CF45=0,"",CF45/CF$3) -> -0.18 | CI45: （経常利益） | CK45: =CK40+CK41-CK42 -> -27548 | CL45: =CL40+CL41-CL42 -> -27548 | CM45: =CM40+CM41-CM42 -> -27548 | CN45: =CN40+CN41-CN42 -> -27548 | CO45: =CO40+CO41-CO42 -> -27548 | CP45: =CP40+CP41-CP42 -> -27548 | CQ45: =CQ40+CQ41-CQ42 -> -30680 | CR45: =CR40+CR41-CR42 -> -30680 | ... CV45: =CV40+CV41-CV42 -> #REF! | CW45: =SUM(CK45:CV45) -> #REF! | CX45: =IF(CW45=0,"",CW45/CW$3) -> #REF! | CZ45: （経常利益） | DB45: =DB40+DB41-DB42 -> -32826 | DC45: =DC40+DC41-DC42 -> -32826 | DD45: =DD40+DD41-DD42 -> -32826 | DE45: =DE40+DE41-DE42 -> -32826 | DF45: =DF40+DF41-DF42 -> -32826 | DG45: =DG40+DG41-DG42 -> -32826 | DH45: =DH40+DH41-DH42 -> -34892 | DI45: =DI40+DI41-DI42 -> -34892 | ... DM45: =DM40+DM41-DM42 -> #REF! | DN45: =SUM(DB45:DM45) -> #REF! | DO45: =IF(DN45=0,"",DN45/DN$3) -> #REF! | DQ45: （経常利益） | DS45: =DS40+DS41-DS42 -> -37038 | DT45: =DT40+DT41-DT42 -> -37038 | DU45: =DU40+DU41-DU42 -> -37038 | DV45: =DV40+DV41-DV42 -> -37038 | DW45: =DW40+DW41-DW42 -> -40170 | DX45: =DX40+DX41-DX42 -> -42236 | DY45: =DY40+DY41-DY42 -> -42236 | DZ45: =DZ40+DZ41-DZ42 -> -42236 | ... ED45: =ED40+ED41-ED42 -> #REF! | EE45: =SUM(DS45:ED45) -> #REF! | EF45: =IF(EE45=0,"",EE45/EE$3) -> #REF! | EH45: （経常利益） | EJ45: =EJ40+EJ41-EJ42 -> -43316 | EK45: =EK40+EK41-EK42 -> -43316 | EL45: =EL40+EL41-EL42 -> -43316 | EM45: =EM40+EM41-EM42 -> -43316 | EN45: =EN40+EN41-EN42 -> -43316 | EO45: =EO40+EO41-EO42 -> -46448 | EP45: =EP40+EP41-EP42 -> -46448 | EQ45: =EQ40+EQ41-EQ42 -> -46448 | ... EU45: =EU40+EU41-EU42 -> #REF! | EV45: =SUM(EJ45:EU45) -> #REF! | EW45: =IF(EV45=0,"",EV45/EV$3) -> #REF! | EY45: （経常利益） | FA45: =FA40+FA41-FA42 -> -54560 | FB45: =FB40+FB41-FB42 -> -54560 | FC45: =FC40+FC41-FC42 -> -54560 | FD45: =FD40+FD41-FD42 -> -54560 | FE45: =FE40+FE41-FE42 -> -54560 | FF45: =FF40+FF41-FF42 -> -54560 | FG45: =FG40+FG41-FG42 -> -54560 | FH45: =FH40+FH41-FH42 -> -54560 | ... FL45: =FL40+FL41-FL42 -> #REF! | FM45: =SUM(FA45:FL45) -> #REF! | FN45: =IF(FM45=0,"",FM45/FM$3) -> #REF!
B46: （税引後収支） | P46: =P45*0 -> 0 | AG46: =AG45*1 -> 6767788.5 | AX46: =AX45*1 -> 6383848.4 | BO46: =BO45*0.6 -> -30240 | CF46: =CF45*0.6 -> -38016 | CW46: =CW45*0.6 -> #REF! | DN46: =DN45*0.6 -> #REF! | EE46: =EE45*0.6 -> #REF! | EV46: =EV45*0.6 -> #REF! | FM46: =FM45*0.6 -> #REF!
A47: H23年度 資金繰表
D48: 4月 | E48: 5月 | F48: 6月 | G48: 7月 | H48: 8月 | I48: 9月 | J48: 10月 | K48: 11月 | L48: 12月 | M48: 1月 | N48: 2月 | O48: 3月 | P48: 条件 | U48: 4月 | V48: 5月 | W48: 6月 | X48: 7月 | Y48: 8月 | Z48: 9月 | AA48: 10月 | AB48: 11月 | AC48: 12月 | AD48: 1月 | AE48: 2月 | AF48: 3月 | AL48: 4月 | AM48: 5月 | AN48: 6月 | AO48: 7月 | AP48: 8月 | AQ48: 9月 | AR48: 10月 | AS48: 11月 | AT48: 12月 | AU48: 1月 | AV48: 2月 | AW48: 3月 | BC48: 3月 | BD48: 4月 | BE48: 5月 | BF48: 6月 | BG48: 7月 | BH48: 8月 | BI48: 9月 | BJ48: 10月 | BK48: 11月 | BL48: 12月 | BM48: 1月 | BN48: 2月 | BO48: 条件 | BT48: 3月 | BU48: 4月 | BV48: 5月 | BW48: 6月 | BX48: 7月 | BY48: 8月 | BZ48: 9月 | CA48: 10月 | CB48: 11月 | CC48: 12月 | CD48: 1月 | CE48: 2月 | CF48: 条件 | CK48: 3月 | CL48: 4月 | CM48: 5月 | CN48: 6月 | CO48: 7月 | CP48: 8月 | CQ48: 9月 | CR48: 10月 | CS48: 11月 | CT48: 12月 | CU48: 1月 | CV48: 2月 | CW48: 条件 | DB48: 3月 | DC48: 4月 | DD48: 5月 | DE48: 6月 | DF48: 7月 | DG48: 8月 | DH48: 9月 | DI48: 10月 | DJ48: 11月 | DK48: 12月 | DL48: 1月 | DM48: 2月 | DN48: 条件 | DS48: 3月 | DT48: 4月 | DU48: 5月 | DV48: 6月 | DW48: 7月 | DX48: 8月 | DY48: 9月 | DZ48: 10月 | EA48: 11月 | EB48: 12月 | EC48: 1月 | ED48: 2月 | EE48: 条件 | EJ48: 3月 | EK48: 4月 | EL48: 5月 | EM48: 6月 | EN48: 7月 | EO48: 8月 | EP48: 9月 | EQ48: 10月 | ER48: 11月 | ES48: 12月 | ET48: 1月 | EU48: 2月 | EV48: 条件 | FA48: 3月 | FB48: 4月 | FC48: 5月 | FD48: 6月 | FE48: 7月 | FF48: 8月 | FG48: 9月 | FH48: 10月 | FI48: 11月 | FJ48: 12月 | FK48: 1月 | FL48: 2月 | FM48: 条件
B49: 前月繰越 | E49: =D76 -> 0 | F49: =E76 -> 0 | G49: =F76 -> 0 | H49: =G76 -> 0 | I49: =H76 -> 0 | J49: =I76 -> 0 | K49: =J76 -> 0 | L49: =K76 -> 0 | ... O49: =N76 -> 100000 | S49: 前月繰越 | U49: =O76 -> 0 | V49: =U76 -> 345000 | W49: =V76 -> 46427.9 | X49: =W76 -> 213025.8 | Y49: =X76 -> 144964.1 | Z49: =Y76 -> 342255.7 | AA49: =Z76 -> 623806.5 | AB49: =AA76 -> 839357.3 | AC49: =AB76 -> 1139167.3 | ... AF49: =AE76 -> 2143115.7 | AJ49: 前月繰越 | AL49: =AF76 -> 2579444.1 | AM49: =AL76 -> 3293985.3 | AN49: =AM76 -> 4200350.5 | AO49: =AN76 -> 4401901.7 | AP49: =AO76 -> 4605193.3 | AQ49: =AP76 -> 4792484.9 | AR49: =AQ76 -> 5064035.7 | AS49: =AR76 -> 5319586.5 | AT49: =AS76 -> 5659396.5 | ... AW49: =AV76 -> 6783344.9 | BA49: 前月繰越 | BC49: =AW76 -> 7259673.3 | BD49: =BC76 -> -1.1258809e+08 | BE49: =BD76 -> -1.1259067e+08 | BF49: =BE76 -> -1.1259325e+08 | BG49: =BF76 -> -1.1259583e+08 | BH49: =BG76 -> -1.1259841e+08 | BI49: =BH76 -> -1.1260179e+08 | BJ49: =BI76 -> -1.1260399e+08 | BK49: =BJ76 -> -1.1260577e+08 | ... BN49: =BM76 -> -1.1261225e+08 | BR49: 前月繰越 | BT49: =BN76 -> -1.1259425e+08 | BU49: =BT76 -> -1.1259721e+08 | BV49: =BU76 -> -1.1260087e+08 | BW49: =BV76 -> -1.1260453e+08 | BX49: =BW76 -> -1.1260819e+08 | BY49: =BX76 -> -1.1261185e+08 | BZ49: =BY76 -> -1.1261631e+08 | CA49: =BZ76 -> -1.1261959e+08 | CB49: =CA76 -> -1.1262245e+08 | ... CE49: =CD76 -> -1.1263217e+08 | CI49: 前月繰越 | CK49: =CE76 -> -1.1261007e+08 | CL49: =CK76 -> -1.1263731e+08 | CM49: =CL76 -> -1.1266485e+08 | CN49: =CM76 -> -1.1269351e+08 | CO49: =CN76 -> -1.1274706e+08 | CP49: =CO76 -> -1.1277461e+08 | CQ49: =CP76 -> -1.1280216e+08 | CR49: =CQ76 -> -1.1282971e+08 | CS49: =CR76 -> -1.1286039e+08 | ... CV49: =CU76 -> -1.1295243e+08 | CZ49: 前月繰越 | DB49: =CV76 -> #REF! | DC49: =DB76 -> #REF! | DD49: =DC76 -> #REF! | DE49: =DD76 -> #REF! | DF49: =DE76 -> #REF! | DG49: =DF76 -> #REF! | DH49: =DG76 -> #REF! | DI49: =DH76 -> #REF! | DJ49: =DI76 -> #REF! | ... DM49: =DL76 -> #REF! | DQ49: 前月繰越 | DS49: =DM76 -> #REF! | DT49: =DS76 -> #REF! | DU49: =DT76 -> #REF! | DV49: =DU76 -> #REF! | DW49: =DV76 -> #REF! | DX49: =DW76 -> #REF! | DY49: =DX76 -> #REF! | DZ49: =DY76 -> #REF! | EA49: =DZ76 -> #REF! | ... ED49: =EC76 -> #REF! | EH49: 前月繰越 | EJ49: =ED76 -> #REF! | EK49: =EJ76 -> #REF! | EL49: =EK76 -> #REF! | EM49: =EL76 -> #REF! | EN49: =EM76 -> #REF! | EO49: =EN76 -> #REF! | EP49: =EO76 -> #REF! | EQ49: =EP76 -> #REF! | ER49: =EQ76 -> #REF! | ... EU49: =ET76 -> #REF! | EY49: 前月繰越 | FA49: =EU76 -> #REF! | FB49: =FA76 -> #REF! | FC49: =FB76 -> #REF! | FD49: =FC76 -> #REF! | FE49: =FD76 -> #REF! | FF49: =FE76 -> #REF! | FG49: =FF76 -> #REF! | FH49: =FG76 -> #REF! | FI49: =FH76 -> #REF! | ... FL49: =FK76 -> #REF!
B50: 経常収入 | D50: =SUM(D51:D54) -> 0 | E50: =SUM(E51:E54) -> 0 | F50: =SUM(F51:F54) -> 0 | G50: =SUM(G51:G54) -> 0 | H50: =SUM(H51:H54) -> 0 | I50: =SUM(I51:I54) -> 0 | J50: =SUM(J51:J54) -> 0 | K50: =SUM(K51:K54) -> 0 | ... O50: =SUM(O51:O54) -> 0 | S50: 経常収入 | U50: =SUM(U51:U54) -> 0 | V50: =SUM(V51:V54) -> 0 | W50: =SUM(W51:W54) -> 1031370 | X50: =SUM(X51:X54) -> 1035110.4 | Y50: =SUM(Y51:Y54) -> 1095110.4 | Z50: =SUM(Z51:Z54) -> 1181369.6 | AA50: =SUM(AA51:AA54) -> 1181369.6 | AB50: =SUM(AB51:AB54) -> 1267628.8 | ... AF50: =SUM(AF51:AF54) -> 1440147.2 | AJ50: 経常収入 | AL50: =SUM(AL51:AL54) -> 1677360 | AM50: =SUM(AM51:AM54) -> 1785184 | AN50: =SUM(AN51:AN54) -> 1091370 | AO50: =SUM(AO51:AO54) -> 1095110.4 | AP50: =SUM(AP51:AP54) -> 1095110.4 | AQ50: =SUM(AQ51:AQ54) -> 1181369.6 | AR50: =SUM(AR51:AR54) -> 1181369.6 | AS50: =SUM(AS51:AS54) -> 1267628.8 | ... AW50: =SUM(AW51:AW54) -> 1440147.2 | BA50: 経常収入 | BC50: =SUM(BC51:BC54) -> 428236.8 | BD50: =SUM(BD51:BD54) -> 29000 | BE50: =SUM(BE51:BE54) -> 29000 | BF50: =SUM(BF51:BF54) -> 29000 | BG50: =SUM(BG51:BG54) -> 29000 | BH50: =SUM(BH51:BH54) -> 28200 | BI50: =SUM(BI51:BI54) -> 28800 | BJ50: =SUM(BJ51:BJ54) -> 29800 | ... BN50: =SUM(BN51:BN54) -> 30000 | BR50: 経常収入 | BT50: =SUM(BT51:BT54) -> 29200 | BU50: =SUM(BU51:BU54) -> 29000 | BV50: =SUM(BV51:BV54) -> 29000 | BW50: =SUM(BW51:BW54) -> 29000 | BX50: =SUM(BX51:BX54) -> 29000 | BY50: =SUM(BY51:BY54) -> 28200 | BZ50: =SUM(BZ51:BZ54) -> 28800 | CA50: =SUM(CA51:CA54) -> 29800 | ... CE50: =SUM(CE51:CE54) -> 30000 | CI50: 経常収入 | CK50: =SUM(CK51:CK54) -> 6000 | CL50: =SUM(CL51:CL54) -> 0 | CM50: =SUM(CM51:CM54) -> 0 | CN50: =SUM(CN51:CN54) -> 0 | CO50: =SUM(CO51:CO54) -> 0 | CP50: =SUM(CP51:CP54) -> 0 | CQ50: =SUM(CQ51:CQ54) -> 0 | CR50: =SUM(CR51:CR54) -> 0 | ... CV50: =SUM(CV51:CV54) -> 0 | CZ50: 経常収入 | DB50: =SUM(DB51:DB54) -> 0 | DC50: =SUM(DC51:DC54) -> 0 | DD50: =SUM(DD51:DD54) -> 0 | DE50: =SUM(DE51:DE54) -> 0 | DF50: =SUM(DF51:DF54) -> 0 | DG50: =SUM(DG51:DG54) -> 0 | DH50: =SUM(DH51:DH54) -> 0 | DI50: =SUM(DI51:DI54) -> 0 | ... DM50: =SUM(DM51:DM54) -> 0 | DQ50: 経常収入 | DS50: =SUM(DS51:DS54) -> 0 | DT50: =SUM(DT51:DT54) -> 0 | DU50: =SUM(DU51:DU54) -> 0 | DV50: =SUM(DV51:DV54) -> 0 | DW50: =SUM(DW51:DW54) -> 0 | DX50: =SUM(DX51:DX54) -> 0 | DY50: =SUM(DY51:DY54) -> 0 | DZ50: =SUM(DZ51:DZ54) -> 0 | ... ED50: =SUM(ED51:ED54) -> 0 | EH50: 経常収入 | EJ50: =SUM(EJ51:EJ54) -> 0 | EK50: =SUM(EK51:EK54) -> 0 | EL50: =SUM(EL51:EL54) -> 0 | EM50: =SUM(EM51:EM54) -> 0 | EN50: =SUM(EN51:EN54) -> 0 | EO50: =SUM(EO51:EO54) -> 0 | EP50: =SUM(EP51:EP54) -> 0 | EQ50: =SUM(EQ51:EQ54) -> 0 | ... EU50: =SUM(EU51:EU54) -> 0 | EY50: 経常収入 | FA50: =SUM(FA51:FA54) -> 0 | FB50: =SUM(FB51:FB54) -> 0 | FC50: =SUM(FC51:FC54) -> 0 | FD50: =SUM(FD51:FD54) -> 0 | FE50: =SUM(FE51:FE54) -> 0 | FF50: =SUM(FF51:FF54) -> 0 | FG50: =SUM(FG51:FG54) -> 0 | FH50: =SUM(FH51:FH54) -> 0 | ... FL50: =SUM(FL51:FL54) -> 0
C51: 訓練給付金等 | F51: =D4 -> 0 | G51: =E4 -> 0 | H51: =F4 -> 0 | I51: =G4 -> 0 | J51: =H4 -> 0 | K51: =I4 -> 0 | L51: =J4 -> 0 | M51: =K4 -> 0 | ... O51: =M4 -> 0 | P51: 末〆翌々15日 | T51: =IF(C51="","",C51) -> 訓練給付金等 | U51: =N4 -> 0 | V51: =O4 -> 0 | W51: =U4 -> 1031370 | X51: =X4*0.8 -> 1035110.4 | Y51: =Y4*0.8 -> 1035110.4 | Z51: =Z4*0.8 -> 1121369.6 | AA51: =AA4*0.8 -> 1121369.6 | AB51: =AB4*0.8 -> 1207628.8 | AC51: =AC4*0.8 -> 1207628.8 | AD51: =AD4*0.8 -> 1293888 | AE51: =AE4*0.8 -> 1293888 | AF51: =AF4*0.8 -> 1380147.2 | AG51: 当月計上（80%） | AK51: =IF(T51="","",T51) -> 訓練給付金等 | AL51: =AE4 -> 1617360 | AM51: =AF4 -> 1725184 | AN51: =AL4 -> 1031370 | AO51: =AO4*0.8 -> 1035110.4 | AP51: =AP4*0.8 -> 1035110.4 | AQ51: =AQ4*0.8 -> 1121369.6 | AR51: =AR4*0.8 -> 1121369.6 | AS51: =AS4*0.8 -> 1207628.8 | AT51: =AT4*0.8 -> 1207628.8 | AU51: =AU4*0.8 -> 1293888 | AV51: =AV4*0.8 -> 1293888 | AW51: =AW4*0.8 -> 1380147.2 | AX51: 当月計上（80%） | BB51: 店舗現金売上 | BC51: =BC4*0.8 -> 23200 | BD51: =BD4*0.8 -> 23200 | BE51: =BE4*0.8 -> 23200 | BF51: =BF4*0.8 -> 23200 | BG51: =BG4*0.8 -> 23200 | BH51: =BH4*0.8 -> 22400 | BI51: =BI4*0.8 -> 23200 | BJ51: =BJ4*0.8 -> 24000 | ... BN51: =BN4*0.8 -> 24000 | BO51: 当月計上（82%） | BS51: 店舗現金売上 | BT51: =BT4*0.8 -> 23200 | BU51: =BU4*0.8 -> 23200 | BV51: =BV4*0.8 -> 23200 | BW51: =BW4*0.8 -> 23200 | BX51: =BX4*0.8 -> 23200 | BY51: =BY4*0.8 -> 22400 | BZ51: =BZ4*0.8 -> 23200 | CA51: =CA4*0.8 -> 24000 | ... CE51: =CE4*0.8 -> 24000 | CF51: 当月計上（81%） | CJ51: 店舗現金売上 | CK51: =CK4*0.8 -> 0 | CL51: =CL4*0.8 -> 0 | CM51: =CM4*0.8 -> 0 | CN51: =CN4*0.8 -> 0 | CO51: =CO4*0.8 -> 0 | CP51: =CP4*0.8 -> 0 | CQ51: =CQ4*0.8 -> 0 | CR51: =CR4*0.8 -> 0 | ... CV51: =CV4*0.8 -> 0 | CW51: 当月計上（82%） | DA51: 店舗現金売上 | DB51: =DB4*0.8 -> 0 | DC51: =DC4*0.8 -> 0 | DD51: =DD4*0.8 -> 0 | DE51: =DE4*0.8 -> 0 | DF51: =DF4*0.8 -> 0 | DG51: =DG4*0.8 -> 0 | DH51: =DH4*0.8 -> 0 | DI51: =DI4*0.8 -> 0 | ... DM51: =DM4*0.8 -> 0 | DN51: 当月計上（83%） | DR51: 店舗現金売上 | DS51: =DS4*0.8 -> 0 | DT51: =DT4*0.8 -> 0 | DU51: =DU4*0.8 -> 0 | DV51: =DV4*0.8 -> 0 | DW51: =DW4*0.8 -> 0 | DX51: =DX4*0.8 -> 0 | DY51: =DY4*0.8 -> 0 | DZ51: =DZ4*0.8 -> 0 | ... ED51: =ED4*0.8 -> 0 | EE51: 当月計上（84%） | EI51: 店舗現金売上 | EJ51: =EJ4*0.8 -> 0 | EK51: =EK4*0.8 -> 0 | EL51: =EL4*0.8 -> 0 | EM51: =EM4*0.8 -> 0 | EN51: =EN4*0.8 -> 0 | EO51: =EO4*0.8 -> 0 | EP51: =EP4*0.8 -> 0 | EQ51: =EQ4*0.8 -> 0 | ... EU51: =EU4*0.8 -> 0 | EV51: 当月計上（85%） | EZ51: 店舗現金売上 | FA51: =FA4*0.8 -> 0 | FB51: =FB4*0.8 -> 0 | FC51: =FC4*0.8 -> 0 | FD51: =FD4*0.8 -> 0 | FE51: =FE4*0.8 -> 0 | FF51: =FF4*0.8 -> 0 | FG51: =FG4*0.8 -> 0 | FH51: =FH4*0.8 -> 0 | ... FL51: =FL4*0.8 -> 0 | FM51: 当月計上（86%）
C52: 作業収入 | E52: =D9 -> 0 | F52: =E9 -> 0 | G52: =F9 -> 0 | H52: =G9 -> 0 | I52: =H9 -> 0 | J52: =I9 -> 0 | K52: =J9 -> 0 | L52: =K9 -> 0 | ... O52: =N9 -> 0 | P52: 月末締め翌月末 | T52: =IF(C52="","",C52) -> 作業収入 | U52: =O9 -> 0 | V52: =U9 -> 0 | W52: =V9 -> 0 | X52: =W9 -> 0 | Y52: =X9 -> 60000 | Z52: =Y9 -> 60000 | AA52: =Z9 -> 60000 | AB52: =AA9 -> 60000 | AC52: =AB9 -> 60000 | ... AF52: =AE9 -> 60000 | AG52: 売上（20%）月末締め翌月末払い | AK52: =IF(T52="","",T52) -> 作業収入 | AL52: =AF9 -> 60000 | AM52: =AL9 -> 60000 | AN52: =AM9 -> 60000 | AO52: =AN9 -> 60000 | AP52: =AO9 -> 60000 | AQ52: =AP9 -> 60000 | AR52: =AQ9 -> 60000 | AS52: =AR9 -> 60000 | AT52: =AS9 -> 60000 | ... AW52: =AV9 -> 60000 | AX52: 売上（20%）月末締め翌月末払い | BB52: 店舗催事売掛入金 | BC52: =AW4*0.2 -> 345036.8 | BD52: =BC4*0.2 -> 5800 | BE52: =BD4*0.2 -> 5800 | BF52: =BE4*0.2 -> 5800 | BG52: =BF4*0.2 -> 5800 | BH52: =BG4*0.2 -> 5800 | BI52: =BH4*0.2 -> 5600 | BJ52: =BI4*0.2 -> 5800 | BK52: =BJ4*0.2 -> 6000 | ... BN52: =BM4*0.2 -> 6000 | BO52: 売上（22%）月末締め翌月末払い | BS52: 店舗催事売掛入金 | BT52: =BN4*0.2 -> 6000 | BU52: =BT4*0.2 -> 5800 | BV52: =BU4*0.2 -> 5800 | BW52: =BV4*0.2 -> 5800 | BX52: =BW4*0.2 -> 5800 | BY52: =BX4*0.2 -> 5800 | BZ52: =BY4*0.2 -> 5600 | CA52: =BZ4*0.2 -> 5800 | CB52: =CA4*0.2 -> 6000 | ... CE52: =CD4*0.2 -> 6000 | CF52: 売上（21%）月末締め翌月末払い | CJ52: 店舗催事売掛入金 | CK52: =CE4*0.2 -> 6000 | CL52: =CK4*0.2 -> 0 | CM52: =CL4*0.2 -> 0 | CN52: =CM4*0.2 -> 0 | CO52: =CN4*0.2 -> 0 | CP52: =CO4*0.2 -> 0 | CQ52: =CP4*0.2 -> 0 | CR52: =CQ4*0.2 -> 0 | CS52: =CR4*0.2 -> 0 | ... CV52: =CU4*0.2 -> 0 | CW52: 売上（22%）月末締め翌月末払い | DA52: 店舗催事売掛入金 | DB52: =CV4*0.2 -> 0 | DC52: =DB4*0.2 -> 0 | DD52: =DC4*0.2 -> 0 | DE52: =DD4*0.2 -> 0 | DF52: =DE4*0.2 -> 0 | DG52: =DF4*0.2 -> 0 | DH52: =DG4*0.2 -> 0 | DI52: =DH4*0.2 -> 0 | DJ52: =DI4*0.2 -> 0 | ... DM52: =DL4*0.2 -> 0 | DN52: 売上（23%）月末締め翌月末払い | DR52: 店舗催事売掛入金 | DS52: =DM4*0.2 -> 0 | DT52: =DS4*0.2 -> 0 | DU52: =DT4*0.2 -> 0 | DV52: =DU4*0.2 -> 0 | DW52: =DV4*0.2 -> 0 | DX52: =DW4*0.2 -> 0 | DY52: =DX4*0.2 -> 0 | DZ52: =DY4*0.2 -> 0 | EA52: =DZ4*0.2 -> 0 | ... ED52: =EC4*0.2 -> 0 | EE52: 売上（24%）月末締め翌月末払い | EI52: 店舗催事売掛入金 | EJ52: =ED4*0.2 -> 0 | EK52: =EJ4*0.2 -> 0 | EL52: =EK4*0.2 -> 0 | EM52: =EL4*0.2 -> 0 | EN52: =EM4*0.2 -> 0 | EO52: =EN4*0.2 -> 0 | EP52: =EO4*0.2 -> 0 | EQ52: =EP4*0.2 -> 0 | ER52: =EQ4*0.2 -> 0 | ... EU52: =ET4*0.2 -> 0 | EV52: 売上（25%）月末締め翌月末払い | EZ52: 店舗催事売掛入金 | FA52: =EU4*0.2 -> 0 | FB52: =FA4*0.2 -> 0 | FC52: =FB4*0.2 -> 0 | FD52: =FC4*0.2 -> 0 | FE52: =FD4*0.2 -> 0 | FF52: =FE4*0.2 -> 0 | FG52: =FF4*0.2 -> 0 | FH52: =FG4*0.2 -> 0 | FI52: =FH4*0.2 -> 0 | ... FL52: =FK4*0.2 -> 0 | FM52: 売上（26%）月末締め翌月末払い
C53: 会費等収入 | E53: =E15 -> 0 | F53: =F15 -> 0 | G53: =G15 -> 0 | H53: =H15 -> 0 | I53: =I15 -> 0 | J53: =J15 -> 0 | K53: =K15 -> 0 | L53: =L15 -> 0 | ... O53: =O15 -> 0 | P53: 当月入金 | T53: =IF(C53="","",C53) -> 会費等収入 | U53: =U15 -> 0 | V53: =V15 -> 0 | W53: =W15 -> 0 | X53: =X15 -> 0 | Y53: =Y15 -> 0 | Z53: =Z15 -> 0 | AA53: =AA15 -> 0 | AB53: =AB15 -> 0 | ... AF53: =AF15 -> 0 | AG53: 月末締め翌月末払い | AK53: =IF(T53="","",T53) -> 会費等収入 | AL53: =AL15 -> 0 | AM53: =AM15 -> 0 | AN53: =AN15 -> 0 | AO53: =AO15 -> 0 | AP53: =AP15 -> 0 | AQ53: =AQ15 -> 0 | AR53: =AR15 -> 0 | AS53: =AS15 -> 0 | ... AW53: =AW15 -> 0 | AX53: 月末締め翌月末払い | BB53: FCロイヤリティ | BC53: =AW9 -> 60000 | BD53: =BC9 -> 0 | BE53: =BD9 -> 0 | BF53: =BE9 -> 0 | BG53: =BF9 -> 0 | BH53: =BG9 -> 0 | BI53: =BH9 -> 0 | BJ53: =BI9 -> 0 | BK53: =BJ9 -> 0 | ... BN53: =BM9 -> 0 | BO53: 月末締め翌月末払い | BS53: FCロイヤリティ | BT53: =BN9 -> 0 | BU53: =BT9 -> 0 | BV53: =BU9 -> 0 | BW53: =BV9 -> 0 | BX53: =BW9 -> 0 | BY53: =BX9 -> 0 | BZ53: =BY9 -> 0 | CA53: =BZ9 -> 0 | CB53: =CA9 -> 0 | ... CE53: =CD9 -> 0 | CF53: 月末締め翌月末払い | CJ53: FCロイヤリティ | CK53: =CE9 -> 0 | CL53: =CK9 -> 0 | CM53: =CL9 -> 0 | CN53: =CM9 -> 0 | CO53: =CN9 -> 0 | CP53: =CO9 -> 0 | CQ53: =CP9 -> 0 | CR53: =CQ9 -> 0 | CS53: =CR9 -> 0 | ... CV53: =CU9 -> 0 | CW53: 月末締め翌月末払い | DA53: FCロイヤリティ | DB53: =CV9 -> 0 | DC53: =DB9 -> 0 | DD53: =DC9 -> 0 | DE53: =DD9 -> 0 | DF53: =DE9 -> 0 | DG53: =DF9 -> 0 | DH53: =DG9 -> 0 | DI53: =DH9 -> 0 | DJ53: =DI9 -> 0 | ... DM53: =DL9 -> 0 | DN53: 月末締め翌月末払い | DR53: FCロイヤリティ | DS53: =DM9 -> 0 | DT53: =DS9 -> 0 | DU53: =DT9 -> 0 | DV53: =DU9 -> 0 | DW53: =DV9 -> 0 | DX53: =DW9 -> 0 | DY53: =DX9 -> 0 | DZ53: =DY9 -> 0 | EA53: =DZ9 -> 0 | ... ED53: =EC9 -> 0 | EE53: 月末締め翌月末払い | EI53: FCロイヤリティ | EJ53: =ED9 -> 0 | EK53: =EJ9 -> 0 | EL53: =EK9 -> 0 | EM53: =EL9 -> 0 | EN53: =EM9 -> 0 | EO53: =EN9 -> 0 | EP53: =EO9 -> 0 | EQ53: =EP9 -> 0 | ER53: =EQ9 -> 0 | ... EU53: =ET9 -> 0 | EV53: 月末締め翌月末払い | EZ53: FCロイヤリティ | FA53: =EU9 -> 0 | FB53: =FA9 -> 0 | FC53: =FB9 -> 0 | FD53: =FC9 -> 0 | FE53: =FD9 -> 0 | FF53: =FE9 -> 0 | FG53: =FF9 -> 0 | FH53: =FG9 -> 0 | FI53: =FH9 -> 0 | ... FL53: =FK9 -> 0 | FM53: 月末締め翌月末払い
C54: その他収入 | E54: =D17 -> 0 | F54: =E17 -> 0 | G54: =F17 -> 0 | H54: =G17 -> 0 | I54: =H17 -> 0 | J54: =I17 -> 0 | K54: =J17 -> 0 | L54: =K17 -> 0 | ... O54: =N17 -> 0 | P54: 月末締め翌月末 | T54: =IF(C54="","",C54) -> その他収入 | U54: =O17 -> 0 | V54: =U17 -> 0 | W54: =V17 -> 0 | AG54: 月末締め翌月末払い | AK54: =IF(T54="","",T54) -> その他収入 | AL54: =AF17 -> 0 | AM54: =AL17 -> 0 | AN54: =AM17 -> 0 | AX54: 月末締め翌月末払い | BB54: 他収入 | BO54: 月末締め翌月末払い | BS54: 他収入 | CF54: 月末締め翌月末払い | CJ54: 他収入 | CW54: 月末締め翌月末払い | DA54: 他収入 | DN54: 月末締め翌月末払い | DR54: 他収入 | EE54: 月末締め翌月末払い | EI54: 他収入 | EV54: 月末締め翌月末払い | EZ54: 他収入 | FM54: 月末締め翌月末払い
B55: 経常支出 | D55: =SUM(D56:D62) -> 0 | E55: =SUM(E56:E62) -> 0 | F55: =SUM(F56:F62) -> 0 | G55: =SUM(G56:G62) -> 0 | H55: =SUM(H56:H62) -> 0 | I55: =SUM(I56:I62) -> 0 | J55: =SUM(J56:J62) -> 0 | K55: =SUM(K56:K62) -> 0 | ... O55: =SUM(O56:O62) -> 0 | S55: 経常支出 | U55: =SUM(U56:U62) -> 55000 | V55: =SUM(V56:V62) -> 580172.1 | W55: =SUM(W56:W62) -> 583172.1 | X55: =SUM(X56:X62) -> 703172.1 | Y55: =SUM(Y56:Y62) -> 897818.8 | Z55: =SUM(Z56:Z62) -> 899818.8 | AA55: =SUM(AA56:AA62) -> 965818.8 | AB55: =SUM(AB56:AB62) -> 967818.8 | ... AF55: =SUM(AF56:AF62) -> 1003818.8 | AJ55: 経常支出 | AL55: =SUM(AL56:AL62) -> 962818.8 | AM55: =SUM(AM56:AM62) -> 878818.8 | AN55: =SUM(AN56:AN62) -> 889818.8 | AO55: =SUM(AO56:AO62) -> 891818.8 | AP55: =SUM(AP56:AP62) -> 907818.8 | AQ55: =SUM(AQ56:AQ62) -> 909818.8 | AR55: =SUM(AR56:AR62) -> 925818.8 | AS55: =SUM(AS56:AS62) -> 927818.8 | ... AW55: =SUM(AW56:AW62) -> 963818.8 | BA55: 経常支出 | BC55: =SUM(BC56:BC62) -> 276000 | BD55: =SUM(BD56:BD62) -> 31580 | BE55: =SUM(BE56:BE62) -> 31580 | BF55: =SUM(BF56:BF62) -> 31580 | BG55: =SUM(BG56:BG62) -> 31580 | BH55: =SUM(BH56:BH62) -> 31580 | BI55: =SUM(BI56:BI62) -> 31000 | BJ55: =SUM(BJ56:BJ62) -> 31580 | ... BN55: =SUM(BN56:BN62) -> 32160 | BR55: 経常支出 | BT55: =SUM(BT56:BT62) -> 32160 | BU55: =SUM(BU56:BU62) -> 32660 | BV55: =SUM(BV56:BV62) -> 32660 | BW55: =SUM(BW56:BW62) -> 32660 | BX55: =SUM(BX56:BX62) -> 32660 | BY55: =SUM(BY56:BY62) -> 32660 | BZ55: =SUM(BZ56:BZ62) -> 32080 | CA55: =SUM(CA56:CA62) -> 32660 | ... CE55: =SUM(CE56:CE62) -> 33240 | CI55: 経常支出 | CK55: =SUM(CK56:CK62) -> 33240 | CL55: =SUM(CL56:CL62) -> 27548 | CM55: =SUM(CM56:CM62) -> 27548 | CN55: =SUM(CN56:CN62) -> 27548 | CO55: =SUM(CO56:CO62) -> 27548 | CP55: =SUM(CP56:CP62) -> 27548 | CQ55: =SUM(CQ56:CQ62) -> 27548 | CR55: =SUM(CR56:CR62) -> 30680 | ... CV55: =SUM(CV56:CV62) -> #REF! | CZ55: 経常支出 | DB55: =SUM(DB56:DB62) -> #REF! | DC55: =SUM(DC56:DC62) -> 32826 | DD55: =SUM(DD56:DD62) -> 32826 | DE55: =SUM(DE56:DE62) -> 32826 | DF55: =SUM(DF56:DF62) -> 32826 | DG55: =SUM(DG56:DG62) -> 32826 | DH55: =SUM(DH56:DH62) -> 32826 | DI55: =SUM(DI56:DI62) -> 34892 | ... DM55: =SUM(DM56:DM62) -> #REF! | DQ55: 経常支出 | DS55: =SUM(DS56:DS62) -> #REF! | DT55: =SUM(DT56:DT62) -> 37038 | DU55: =SUM(DU56:DU62) -> 37038 | DV55: =SUM(DV56:DV62) -> 37038 | DW55: =SUM(DW56:DW62) -> 37038 | DX55: =SUM(DX56:DX62) -> 40170 | DY55: =SUM(DY56:DY62) -> 42236 | DZ55: =SUM(DZ56:DZ62) -> 42236 | ... ED55: =SUM(ED56:ED62) -> #REF! | EH55: 経常支出 | EJ55: =SUM(EJ56:EJ62) -> #REF! | EK55: =SUM(EK56:EK62) -> 43316 | EL55: =SUM(EL56:EL62) -> 43316 | EM55: =SUM(EM56:EM62) -> 43316 | EN55: =SUM(EN56:EN62) -> 43316 | EO55: =SUM(EO56:EO62) -> 43316 | EP55: =SUM(EP56:EP62) -> 46448 | EQ55: =SUM(EQ56:EQ62) -> 46448 | ... EU55: =SUM(EU56:EU62) -> #REF! | EY55: 経常支出 | FA55: =SUM(FA56:FA62) -> #REF! | FB55: =SUM(FB56:FB62) -> 54560 | FC55: =SUM(FC56:FC62) -> 54560 | FD55: =SUM(FD56:FD62) -> 54560 | FE55: =SUM(FE56:FE62) -> 54560 | FF55: =SUM(FF56:FF62) -> 54560 | FG55: =SUM(FG56:FG62) -> 54560 | FH55: =SUM(FH56:FH62) -> 54560 | ... FL55: =SUM(FL56:FL62) -> #REF!
C56: 福祉サービス原価１ | D56: =D25+D28+D29 -> 0 | E56: =E25+E28+E29 -> 0 | F56: =F25+F28+F29 -> 0 | G56: =G25+G28+G29 -> 0 | H56: =H25+H28+H29 -> 0 | I56: =I25+I28+I29 -> 0 | J56: =J25+J28+J29 -> 0 | K56: =K25+K28+K29 -> 0 | ... O56: =O25+O28+O29 -> 0 | P56: 当月払い | T56: =IF(C56="","",C56) -> 福祉サービス原価１ | U56: =U25+U28+U29 -> 55000 | V56: =V25+V28+V29 -> 57000 | W56: =W25+W28+W29 -> 62000 | X56: =X25+X28+X29 -> 94000 | Y56: =Y25+Y28+Y29 -> 94000 | Z56: =Z25+Z28+Z29 -> 96000 | AA56: =AA25+AA28+AA29 -> 96000 | AB56: =AB25+AB28+AB29 -> 98000 | ... AF56: =AF25+AF28+AF29 -> 102000 | AG56: 月末締め翌月末払い | AK56: =IF(T56="","",T56) -> 福祉サービス原価１ | AL56: =AL25+AL28+AL29 -> 45000 | AM56: =AM25+AM28+AM29 -> 47000 | AN56: =AN25+AN28+AN29 -> 52000 | AO56: =AO25+AO28+AO29 -> 54000 | AP56: =AP25+AP28+AP29 -> 54000 | AQ56: =AQ25+AQ28+AQ29 -> 56000 | AR56: =AR25+AR28+AR29 -> 56000 | AS56: =AS25+AS28+AS29 -> 58000 | ... AW56: =AW25+AW28+AW29 -> 62000 | AX56: 月末締め翌月末払い | BB56: 店舗仕入買掛 | BC56: =AW19 -> 0 | BD56: =BC19 -> 7250 | BE56: =BD19 -> 7250 | BF56: =BE19 -> 7250 | BG56: =BF19 -> 7250 | BH56: =BG19 -> 7250 | BI56: =BH19 -> 7000 | BJ56: =BI19 -> 7250 | BK56: =BJ19 -> 7500 | ... BN56: =BM19 -> 7500 | BO56: 月末締め翌月末払い | BS56: 店舗仕入買掛 | BT56: =BN19 -> 7500 | BU56: =BT19 -> 7250 | BV56: =BU19 -> 7250 | BW56: =BV19 -> 7250 | BX56: =BW19 -> 7250 | BY56: =BX19 -> 7250 | BZ56: =BY19 -> 7000 | CA56: =BZ19 -> 7250 | CB56: =CA19 -> 7500 | ... CE56: =CD19 -> 7500 | CF56: 月末締め翌月末払い | CJ56: 店舗仕入買掛 | CK56: =CE19 -> 7500 | CL56: =CK19 -> 0 | CM56: =CL19 -> 0 | CN56: =CM19 -> 0 | CO56: =CN19 -> 0 | CP56: =CO19 -> 0 | CQ56: =CP19 -> 0 | CR56: =CQ19 -> 0 | CS56: =CR19 -> 0 | ... CV56: =CU19 -> 0 | CW56: 月末締め翌月末払い | DA56: 店舗仕入買掛 | DB56: =CV19 -> 0 | DC56: =DB19 -> 0 | DD56: =DC19 -> 0 | DE56: =DD19 -> 0 | DF56: =DE19 -> 0 | DG56: =DF19 -> 0 | DH56: =DG19 -> 0 | DI56: =DH19 -> 0 | DJ56: =DI19 -> 0 | ... DM56: =DL19 -> 0 | DN56: 月末締め翌月末払い | DR56: 店舗仕入買掛 | DS56: =DM19 -> 0 | DT56: =DS19 -> 0 | DU56: =DT19 -> 0 | DV56: =DU19 -> 0 | DW56: =DV19 -> 0 | DX56: =DW19 -> 0 | DY56: =DX19 -> 0 | DZ56: =DY19 -> 0 | EA56: =DZ19 -> 0 | ... ED56: =EC19 -> 0 | EE56: 月末締め翌月末払い | EI56: 店舗仕入買掛 | EJ56: =ED19 -> 0 | EK56: =EJ19 -> 0 | EL56: =EK19 -> 0 | EM56: =EL19 -> 0 | EN56: =EM19 -> 0 | EO56: =EN19 -> 0 | EP56: =EO19 -> 0 | EQ56: =EP19 -> 0 | ER56: =EQ19 -> 0 | ... EU56: =ET19 -> 0 | EV56: 月末締め翌月末払い | EZ56: 店舗仕入買掛 | FA56: =EU19 -> 0 | FB56: =FA19 -> 0 | FC56: =FB19 -> 0 | FD56: =FC19 -> 0 | FE56: =FD19 -> 0 | FF56: =FE19 -> 0 | FG56: =FF19 -> 0 | FH56: =FG19 -> 0 | FI56: =FH19 -> 0 | ... FL56: =FK19 -> 0 | FM56: 月末締め翌月末払い
C57: 福祉サービス原価２ | E57: =D18-D28-D29-D25 -> 0 | F57: =E18-E28-E29-E25 -> 0 | G57: =F18-F28-F29-F25 -> 0 | H57: =G18-G28-G29-G25 -> 0 | I57: =H18-H28-H29-H25 -> 0 | J57: =I18-I28-I29-I25 -> 0 | K57: =J18-J28-J29-J25 -> 0 | L57: =K18-K28-K29-K25 -> 0 | ... O57: =N18-N28-N29-N25 -> 0 | P57: 末〆翌末払い | T57: =IF(C57="","",C57) -> 福祉サービス原価２ | U57: =O18-O25-O28-O29 -> 0 | V57: =U18-U28-U29-U25 -> 523172.1 | W57: =V18-V28-V29-V25 -> 521172.1 | X57: =W18-W28-W29-W25 -> 609172.1 | Y57: =X18-X28-X29-X25 -> 803818.8 | Z57: =Y18-Y28-Y29-Y25 -> 803818.8 | AA57: =Z18-Z28-Z29-Z25 -> 869818.8 | AB57: =AA18-AA28-AA29-AA25 -> 869818.8 | AC57: =AB18-AB28-AB29-AB25 -> 885818.8 | ... AF57: =AE18-AE28-AE29-AE25 -> 901818.8 | AG57: 原価人件費 | AK57: =IF(T57="","",T57) -> 福祉サービス原価２ | AL57: =AF18-AF25-AF28-AF29 -> 917818.8 | AM57: =AL18-AL28-AL29-AL25 -> 831818.8 | AN57: =AM18-AM28-AM29-AM25 -> 837818.8 | AO57: =AN18-AN28-AN29-AN25 -> 837818.8 | AP57: =AO18-AO28-AO29-AO25 -> 853818.8 | AQ57: =AP18-AP28-AP29-AP25 -> 853818.8 | AR57: =AQ18-AQ28-AQ29-AQ25 -> 869818.8 | AS57: =AR18-AR28-AR29-AR25 -> 869818.8 | AT57: =AS18-AS28-AS29-AS25 -> 885818.8 | ... AW57: =AV18-AV28-AV29-AV25 -> 901818.8 | AX57: 原価人件費 | BB57: 店舗人件費 | BC57: =AW20 -> 256000 | BD57: =BC20 -> 8700 | BE57: =BD20 -> 8700 | BF57: =BE20 -> 8700 | BG57: =BF20 -> 8700 | BH57: =BG20 -> 8700 | BI57: =BH20 -> 8400 | BJ57: =BI20 -> 8700 | BK57: =BJ20 -> 9000 | ... BN57: =BM20 -> 9000 | BO57: 原価人件費 | BS57: 店舗人件費 | BT57: =BN20 -> 9000 | BU57: =BT20 -> 8700 | BV57: =BU20 -> 8700 | BW57: =BV20 -> 8700 | BX57: =BW20 -> 8700 | BY57: =BX20 -> 8700 | BZ57: =BY20 -> 8400 | CA57: =BZ20 -> 8700 | CB57: =CA20 -> 9000 | ... CE57: =CD20 -> 9000 | CF57: 原価人件費 | CJ57: 店舗人件費 | CK57: =CE20 -> 9000 | CL57: =CK20 -> 0 | CM57: =CL20 -> 0 | CN57: =CM20 -> 0 | CO57: =CN20 -> 0 | CP57: =CO20 -> 0 | CQ57: =CP20 -> 0 | CR57: =CQ20 -> 0 | CS57: =CR20 -> 0 | ... CV57: =CU20 -> 0 | CW57: 原価人件費 | DA57: 店舗人件費 | DB57: =CV20 -> 0 | DC57: =DB20 -> 0 | DD57: =DC20 -> 0 | DE57: =DD20 -> 0 | DF57: =DE20 -> 0 | DG57: =DF20 -> 0 | DH57: =DG20 -> 0 | DI57: =DH20 -> 0 | DJ57: =DI20 -> 0 | ... DM57: =DL20 -> 0 | DN57: 原価人件費 | DR57: 店舗人件費 | DS57: =DM20 -> 0 | DT57: =DS20 -> 0 | DU57: =DT20 -> 0 | DV57: =DU20 -> 0 | DW57: =DV20 -> 0 | DX57: =DW20 -> 0 | DY57: =DX20 -> 0 | DZ57: =DY20 -> 0 | EA57: =DZ20 -> 0 | ... ED57: =EC20 -> 0 | EE57: 原価人件費 | EI57: 店舗人件費 | EJ57: =ED20 -> 0 | EK57: =EJ20 -> 0 | EL57: =EK20 -> 0 | EM57: =EL20 -> 0 | EN57: =EM20 -> 0 | EO57: =EN20 -> 0 | EP57: =EO20 -> 0 | EQ57: =EP20 -> 0 | ER57: =EQ20 -> 0 | ... EU57: =ET20 -> 0 | EV57: 原価人件費 | EZ57: 店舗人件費 | FA57: =EU20 -> 0 | FB57: =FA20 -> 0 | FC57: =FB20 -> 0 | FD57: =FC20 -> 0 | FE57: =FD20 -> 0 | FF57: =FE20 -> 0 | FG57: =FF20 -> 0 | FH57: =FG20 -> 0 | FI57: =FH20 -> 0 | ... FL57: =FK20 -> 0 | FM57: 原価人件費
C58: 販管費（ｻｲﾄ１） | E58: =D31 -> 0 | F58: =E31 -> 0 | G58: =F31 -> 0 | H58: =G31 -> 0 | I58: =H31 -> 0 | J58: =I31 -> 0 | K58: =J31 -> 0 | L58: =K31 -> 0 | ... O58: =N31 -> 0 | P58: 販管費（月末締め翌月末払い） | T58: =IF(C58="","",C58) -> 販管費（ｻｲﾄ１） | U58: =O31 -> 0 | V58: =U31 -> 0 | W58: =V31 -> 0 | X58: =W31 -> 0 | Y58: =X31 -> 0 | Z58: =Y31 -> 0 | AA58: =Z31 -> 0 | AB58: =AA31 -> 0 | AC58: =AB31 -> 0 | ... AF58: =AE31 -> 0 | AG58: 販管費（月末締め翌月末払い） | AK58: =IF(T58="","",T58) -> 販管費（ｻｲﾄ１） | AL58: =AF31 -> 0 | AM58: =AL31 -> 0 | AN58: =AM31 -> 0 | AO58: =AN31 -> 0 | AP58: =AO31 -> 0 | AQ58: =AP31 -> 0 | AR58: =AQ31 -> 0 | AS58: =AR31 -> 0 | AT58: =AS31 -> 0 | ... AW58: =AV31 -> 0 | AX58: 販管費（月末締め翌月末払い） | BB58: 販管費（ｻｲﾄ３） | BC58: =AW31+AW25-AW39 -> 20000 | BD58: =BC25+BC29+BC31 -> 15630 | BE58: =BD25+BD29+BD31 -> 15630 | BF58: =BE25+BE29+BE31 -> 15630 | BG58: =BF25+BF29+BF31 -> 15630 | BH58: =BG25+BG29+BG31 -> 15630 | BI58: =BH25+BH29+BH31 -> 15600 | BJ58: =BI25+BI29+BI31 -> 15630 | BK58: =BJ25+BJ29+BJ31 -> 15660 | ... BN58: =BM25+BM29+BM31 -> 15660 | BO58: 販管費（月末締め翌月末払い） | BS58: 販管費（ｻｲﾄ２） | BT58: =BN31+BN25-BN39 -> 15660 | BU58: =BT25+BT29+BT31 -> 16710 | BV58: =BU25+BU29+BU31 -> 16710 | BW58: =BV25+BV29+BV31 -> 16710 | BX58: =BW25+BW29+BW31 -> 16710 | BY58: =BX25+BX29+BX31 -> 16710 | BZ58: =BY25+BY29+BY31 -> 16680 | CA58: =BZ25+BZ29+BZ31 -> 16710 | CB58: =CA25+CA29+CA31 -> 16740 | ... CE58: =CD25+CD29+CD31 -> 16740 | CF58: 販管費（月末締め翌月末払い） | CJ58: 販管費（ｻｲﾄ３） | CK58: =CE31+CE25-CE39 -> 16740 | CL58: =CK25+CK29+CK31 -> 27548 | CM58: =CL25+CL29+CL31 -> 27548 | CN58: =CM25+CM29+CM31 -> 27548 | CO58: =CN25+CN29+CN31 -> 27548 | CP58: =CO25+CO29+CO31 -> 27548 | CQ58: =CP25+CP29+CP31 -> 27548 | CR58: =CQ25+CQ29+CQ31 -> 30680 | CS58: =CR25+CR29+CR31 -> 30680 | ... CV58: =CU25+CU29+CU31 -> 30680 | CW58: 販管費（月末締め翌月末払い） | DA58: 販管費（ｻｲﾄ４） | DB58: =CV31+CV25-CV62 -> #REF! | DC58: =DB25+DB29+DB31 -> 32826 | DD58: =DC25+DC29+DC31 -> 32826 | DE58: =DD25+DD29+DD31 -> 32826 | DF58: =DE25+DE29+DE31 -> 32826 | DG58: =DF25+DF29+DF31 -> 32826 | DH58: =DG25+DG29+DG31 -> 32826 | DI58: =DH25+DH29+DH31 -> 34892 | DJ58: =DI25+DI29+DI31 -> 34892 | ... DM58: =DL25+DL29+DL31 -> 34892 | DN58: 販管費（月末締め翌月末払い） | DR58: 販管費（ｻｲﾄ５） | DS58: =DM31+DM25-DM62 -> #REF! | DT58: =DS25+DS29+DS31 -> 37038 | DU58: =DT25+DT29+DT31 -> 37038 | DV58: =DU25+DU29+DU31 -> 37038 | DW58: =DV25+DV29+DV31 -> 37038 | DX58: =DW25+DW29+DW31 -> 40170 | DY58: =DX25+DX29+DX31 -> 42236 | DZ58: =DY25+DY29+DY31 -> 42236 | EA58: =DZ25+DZ29+DZ31 -> 42236 | ... ED58: =EC25+EC29+EC31 -> 42236 | EE58: 販管費（月末締め翌月末払い） | EI58: 販管費（ｻｲﾄ６） | EJ58: =ED31+ED25-ED62 -> #REF! | EK58: =EJ25+EJ29+EJ31 -> 43316 | EL58: =EK25+EK29+EK31 -> 43316 | EM58: =EL25+EL29+EL31 -> 43316 | EN58: =EM25+EM29+EM31 -> 43316 | EO58: =EN25+EN29+EN31 -> 43316 | EP58: =EO25+EO29+EO31 -> 46448 | EQ58: =EP25+EP29+EP31 -> 46448 | ER58: =EQ25+EQ29+EQ31 -> 46448 | ... EU58: =ET25+ET29+ET31 -> 46448 | EV58: 販管費（月末締め翌月末払い） | EZ58: 販管費（ｻｲﾄ７） | FA58: =EU31+EU25-EU62 -> #REF! | FB58: =FA25+FA29+FA31 -> 54560 | FC58: =FB25+FB29+FB31 -> 54560 | FD58: =FC25+FC29+FC31 -> 54560 | FE58: =FD25+FD29+FD31 -> 54560 | FF58: =FE25+FE29+FE31 -> 54560 | FG58: =FF25+FF29+FF31 -> 54560 | FH58: =FG25+FG29+FG31 -> 54560 | FI58: =FH25+FH29+FH31 -> 54560 | ... FL58: =FK25+FK29+FK31 -> 54560 | FM58: 販管費（月末締め翌月末払い）
T59: =IF(C59="","",C59) | AG59: 販管費（月末締め翌々月末払い） | AK59: =IF(T59="","",T59) | AX59: 販管費（月末締め翌々月末払い） | BB59: 販管費（ｻｲﾄ４） | BO59: 販管費（月末締め翌々月末払い） | BS59: 販管費（ｻｲﾄ３） | CF59: 販管費（月末締め翌々月末払い） | CJ59: 販管費（ｻｲﾄ４） | CW59: 販管費（月末締め翌々月末払い） | DA59: 販管費（ｻｲﾄ５） | DN59: 販管費（月末締め翌々月末払い） | DR59: 販管費（ｻｲﾄ６） | EE59: 販管費（月末締め翌々月末払い） | EI59: 販管費（ｻｲﾄ７） | EV59: 販管費（月末締め翌々月末払い） | EZ59: 販管費（ｻｲﾄ８） | FM59: 販管費（月末締め翌々月末払い）
C60: 支払利息 | D60: =D43 -> 0 | E60: =E43 -> 0 | F60: =F43 -> 0 | G60: =G43 -> 0 | H60: =H43 -> 0 | I60: =I43 -> 0 | J60: =J43 -> 0 | K60: =K43 -> 0 | ... O60: =O43 -> 0 | T60: =IF(C60="","",C60) -> 支払利息 | U60: =U43 -> 0 | V60: =V43 -> 0 | W60: =W43 -> 0 | X60: =X43 -> 0 | Y60: =Y43 -> 0 | Z60: =Z43 -> 0 | AA60: =AA43 -> 0 | AB60: =AB43 -> 0 | ... AF60: =AF43 -> 0 | AK60: =IF(T60="","",T60) -> 支払利息 | AL60: =AL43 -> 0 | AM60: =AM43 -> 0 | AN60: =AN43 -> 0 | AO60: =AO43 -> 0 | AP60: =AP43 -> 0 | AQ60: =AQ43 -> 0 | AR60: =AR43 -> 0 | AS60: =AS43 -> 0 | ... AW60: =AW43 -> 0 | BB60: 支払利息 | BC60: =BC43 -> 0 | BD60: =BD43 -> 0 | BE60: =BE43 -> 0 | BF60: =BF43 -> 0 | BG60: =BG43 -> 0 | BH60: =BH43 -> 0 | BI60: =BI43 -> 0 | BJ60: =BJ43 -> 0 | ... BN60: =BN43 -> 0 | BS60: 支払利息 | BT60: =BT43 -> 0 | BU60: =BU43 -> 0 | BV60: =BV43 -> 0 | BW60: =BW43 -> 0 | BX60: =BX43 -> 0 | BY60: =BY43 -> 0 | BZ60: =BZ43 -> 0 | CA60: =CA43 -> 0 | ... CE60: =CE43 -> 0 | CJ60: 支払利息 | CK60: =CK43 -> 0 | CL60: =CL43 -> 0 | CM60: =CM43 -> 0 | CN60: =CN43 -> 0 | CO60: =CO43 -> 0 | CP60: =CP43 -> 0 | CQ60: =CQ43 -> 0 | CR60: =CR43 -> 0 | ... CV60: =CV43 -> 0 | DA60: 支払利息 | DB60: =DB43 -> 0 | DC60: =DC43 -> 0 | DD60: =DD43 -> 0 | DE60: =DE43 -> 0 | DF60: =DF43 -> 0 | DG60: =DG43 -> 0 | DH60: =DH43 -> 0 | DI60: =DI43 -> 0 | ... DM60: =DM43 -> 0 | DR60: 支払利息 | DS60: =DS43 -> 0 | DT60: =DT43 -> 0 | DU60: =DU43 -> 0 | DV60: =DV43 -> 0 | DW60: =DW43 -> 0 | DX60: =DX43 -> 0 | DY60: =DY43 -> 0 | DZ60: =DZ43 -> 0 | ... ED60: =ED43 -> 0 | EI60: 支払利息 | EJ60: =EJ43 -> 0 | EK60: =EK43 -> 0 | EL60: =EL43 -> 0 | EM60: =EM43 -> 0 | EN60: =EN43 -> 0 | EO60: =EO43 -> 0 | EP60: =EP43 -> 0 | EQ60: =EQ43 -> 0 | ... EU60: =EU43 -> 0 | EZ60: 支払利息 | FA60: =FA43 -> 0 | FB60: =FB43 -> 0 | FC60: =FC43 -> 0 | FD60: =FD43 -> 0 | FE60: =FE43 -> 0 | FF60: =FF43 -> 0 | FG60: =FG43 -> 0 | FH60: =FH43 -> 0 | ... FL60: =FL43 -> 0
C61: 固定資産購入等 | T61: =IF(C61="","",C61) -> 固定資産購入等 | AK61: =IF(T61="","",T61) -> 固定資産購入等 | BB61: 固定資産購入等 | BS61: 固定資産購入等 | CJ61: 固定資産購入等 | DA61: 固定資産購入等 | DR61: 固定資産購入等 | EI61: 固定資産購入等 | EZ61: 固定資産購入等
C62: 他支出 | D62: =D39 -> 0 | E62: =E39 -> 0 | F62: =F39 -> 0 | G62: =G39 -> 0 | H62: =H39 -> 0 | I62: =I39 -> 0 | J62: =J39 -> 0 | K62: =K39 -> 0 | ... O62: =O39 -> 0 | T62: =IF(C62="","",C62) -> 他支出 | U62: =U39 -> 0 | V62: =V39 -> 0 | W62: =W39 -> 0 | X62: =X39 -> 0 | Y62: =Y39 -> 0 | Z62: =Z39 -> 0 | AA62: =AA39 -> 0 | AB62: =AB39 -> 0 | ... AF62: =AF39 -> 0 | AK62: =IF(T62="","",T62) -> 他支出 | AL62: =AL39 -> 0 | AM62: =AM39 -> 0 | AN62: =AN39 -> 0 | AO62: =AO39 -> 0 | AP62: =AP39 -> 0 | AQ62: =AQ39 -> 0 | AR62: =AR39 -> 0 | AS62: =AS39 -> 0 | ... AW62: =AW39 -> 0 | BB62: 他支出 | BN62: =BN39 -> 0 | BS62: 他支出 | CE62: =CE39 -> 0 | CJ62: 他支出 | CV62: =CV39 -> #REF! | DA62: 他支出 | DM62: =DM39 -> #REF! | DR62: 他支出 | ED62: =ED39 -> #REF! | EI62: 他支出 | EU62: =EU39 -> #REF! | EZ62: 他支出 | FL62: =FL39 -> #REF!
B63: 経常収支差額 | D63: =D50-D55 -> 0 | E63: =E50-E55 -> 0 | F63: =F50-F55 -> 0 | G63: =G50-G55 -> 0 | H63: =H50-H55 -> 0 | I63: =I50-I55 -> 0 | J63: =J50-J55 -> 0 | K63: =K50-K55 -> 0 | ... O63: =O50-O55 -> 0 | S63: 経常収支差額 | U63: =U50-U55 -> -55000 | V63: =V50-V55 -> -580172.1 | W63: =W50-W55 -> 448197.9 | X63: =X50-X55 -> 331938.3 | Y63: =Y50-Y55 -> 197291.6 | Z63: =Z50-Z55 -> 281550.8 | AA63: =AA50-AA55 -> 215550.8 | AB63: =AB50-AB55 -> 299810 | ... AF63: =AF50-AF55 -> 436328.4 | AJ63: 経常収支差額 | AL63: =AL50-AL55 -> 714541.2 | AM63: =AM50-AM55 -> 906365.2 | AN63: =AN50-AN55 -> 201551.2 | AO63: =AO50-AO55 -> 203291.6 | AP63: =AP50-AP55 -> 187291.6 | AQ63: =AQ50-AQ55 -> 271550.8 | AR63: =AR50-AR55 -> 255550.8 | AS63: =AS50-AS55 -> 339810 | ... AW63: =AW50-AW55 -> 476328.4 | BA63: 経常収支差額 | BC63: =BC50-BC55 -> 152236.8 | BD63: =BD50-BD55 -> -2580 | BE63: =BE50-BE55 -> -2580 | BF63: =BF50-BF55 -> -2580 | BG63: =BG50-BG55 -> -2580 | BH63: =BH50-BH55 -> -3380 | BI63: =BI50-BI55 -> -2200 | BJ63: =BJ50-BJ55 -> -1780 | ... BN63: =BN50-BN55 -> -2160 | BR63: 経常収支差額 | BT63: =BT50-BT55 -> -2960 | BU63: =BU50-BU55 -> -3660 | BV63: =BV50-BV55 -> -3660 | BW63: =BW50-BW55 -> -3660 | BX63: =BX50-BX55 -> -3660 | BY63: =BY50-BY55 -> -4460 | BZ63: =BZ50-BZ55 -> -3280 | CA63: =CA50-CA55 -> -2860 | ... CE63: =CE50-CE55 -> -3240 | CI63: 経常収支差額 | CK63: =CK50-CK55 -> -27240 | CL63: =CL50-CL55 -> -27548 | CM63: =CM50-CM55 -> -27548 | CN63: =CN50-CN55 -> -27548 | CO63: =CO50-CO55 -> -27548 | CP63: =CP50-CP55 -> -27548 | CQ63: =CQ50-CQ55 -> -27548 | CR63: =CR50-CR55 -> -30680 | ... CV63: =CV50-CV55 -> #REF! | CZ63: 経常収支差額 | DB63: =DB50-DB55 -> #REF! | DC63: =DC50-DC55 -> -32826 | DD63: =DD50-DD55 -> -32826 | DE63: =DE50-DE55 -> -32826 | DF63: =DF50-DF55 -> -32826 | DG63: =DG50-DG55 -> -32826 | DH63: =DH50-DH55 -> -32826 | DI63: =DI50-DI55 -> -34892 | ... DM63: =DM50-DM55 -> #REF! | DQ63: 経常収支差額 | DS63: =DS50-DS55 -> #REF! | DT63: =DT50-DT55 -> -37038 | DU63: =DU50-DU55 -> -37038 | DV63: =DV50-DV55 -> -37038 | DW63: =DW50-DW55 -> -37038 | DX63: =DX50-DX55 -> -40170 | DY63: =DY50-DY55 -> -42236 | DZ63: =DZ50-DZ55 -> -42236 | ... ED63: =ED50-ED55 -> #REF! | EH63: 経常収支差額 | EJ63: =EJ50-EJ55 -> #REF! | EK63: =EK50-EK55 -> -43316 | EL63: =EL50-EL55 -> -43316 | EM63: =EM50-EM55 -> -43316 | EN63: =EN50-EN55 -> -43316 | EO63: =EO50-EO55 -> -43316 | EP63: =EP50-EP55 -> -46448 | EQ63: =EQ50-EQ55 -> -46448 | ... EU63: =EU50-EU55 -> #REF! | EY63: 経常収支差額 | FA63: =FA50-FA55 -> #REF! | FB63: =FB50-FB55 -> -54560 | FC63: =FC50-FC55 -> -54560 | FD63: =FD50-FD55 -> -54560 | FE63: =FE50-FE55 -> -54560 | FF63: =FF50-FF55 -> -54560 | FG63: =FG50-FG55 -> -54560 | FH63: =FH50-FH55 -> -54560 | ... FL63: =FL50-FL55 -> #REF!
B64: 財務収入 | D64: =SUM(D65:D69) -> 0 | E64: =SUM(E65:E69) -> 0 | F64: =SUM(F65:F69) -> 0 | G64: =SUM(G65:G69) -> 0 | H64: =SUM(H65:H69) -> 0 | I64: =SUM(I65:I69) -> 0 | J64: =SUM(J65:J69) -> 0 | K64: =SUM(K65:K69) -> 0 | ... O64: =SUM(O65:O69) -> 0 | S64: 財務収入 | U64: =SUM(U65:U69) -> 400000 | V64: =SUM(V65:V69) -> 281600 | W64: =SUM(W65:W69) -> -281600 | X64: =SUM(X65:X69) -> -400000 | Y64: =SUM(Y65:Y69) -> 0 | Z64: =SUM(Z65:Z69) -> 0 | AA64: =SUM(AA65:AA69) -> 0 | AB64: =SUM(AB65:AB69) -> 0 | ... AF64: =SUM(AF65:AF69) -> 0 | AJ64: 財務収入 | AL64: =SUM(AL65:AL69) -> 0 | AM64: =SUM(AM65:AM69) -> 0 | AN64: =SUM(AN65:AN69) -> 0 | AO64: =SUM(AO65:AO69) -> 0 | AP64: =SUM(AP65:AP69) -> 0 | AQ64: =SUM(AQ65:AQ69) -> 0 | AR64: =SUM(AR65:AR69) -> 0 | AS64: =SUM(AS65:AS69) -> 0 | ... AW64: =SUM(AW65:AW69) -> 0 | BA64: 財務収入 | BC64: =SUM(BC65:BC69) -> -120000000 | BD64: =SUM(BD65:BD69) -> 0 | BE64: =SUM(BE65:BE69) -> 0 | BF64: =SUM(BF65:BF69) -> 0 | BG64: =SUM(BG65:BG69) -> 0 | BH64: =SUM(BH65:BH69) -> 0 | BI64: =SUM(BI65:BI69) -> 0 | BJ64: =SUM(BJ65:BJ69) -> 0 | ... BN64: =SUM(BN65:BN69) -> 0 | BR64: 財務収入 | BT64: =SUM(BT65:BT69) -> 0 | BU64: =SUM(BU65:BU69) -> 0 | BV64: =SUM(BV65:BV69) -> 0 | BW64: =SUM(BW65:BW69) -> 0 | BX64: =SUM(BX65:BX69) -> 0 | BY64: =SUM(BY65:BY69) -> 0 | BZ64: =SUM(BZ65:BZ69) -> 0 | CA64: =SUM(CA65:CA69) -> 0 | ... CE64: =SUM(CE65:CE69) -> 0 | CI64: 財務収入 | CK64: =SUM(CK65:CK69) -> 0 | CL64: =SUM(CL65:CL69) -> 0 | CM64: =SUM(CM65:CM69) -> 0 | CN64: =SUM(CN65:CN69) -> -26000 | CO64: =SUM(CO65:CO69) -> 0 | CP64: =SUM(CP65:CP69) -> 0 | CQ64: =SUM(CQ65:CQ69) -> 0 | CR64: =SUM(CR65:CR69) -> 0 | ... CV64: =SUM(CV65:CV69) -> 0 | CZ64: 財務収入 | DB64: =SUM(DB65:DB69) -> 0 | DC64: =SUM(DC65:DC69) -> 0 | DD64: =SUM(DD65:DD69) -> 0 | DE64: =SUM(DE65:DE69) -> 0 | DF64: =SUM(DF65:DF69) -> 0 | DG64: =SUM(DG65:DG69) -> 0 | DH64: =SUM(DH65:DH69) -> 0 | DI64: =SUM(DI65:DI69) -> 0 | ... DM64: =SUM(DM65:DM69) -> 0 | DQ64: 財務収入 | DS64: =SUM(DS65:DS69) -> 0 | DT64: =SUM(DT65:DT69) -> 0 | DU64: =SUM(DU65:DU69) -> 0 | DV64: =SUM(DV65:DV69) -> 0 | DW64: =SUM(DW65:DW69) -> 0 | DX64: =SUM(DX65:DX69) -> 0 | DY64: =SUM(DY65:DY69) -> 0 | DZ64: =SUM(DZ65:DZ69) -> 0 | ... ED64: =SUM(ED65:ED69) -> 0 | EH64: 財務収入 | EJ64: =SUM(EJ65:EJ69) -> 0 | EK64: =SUM(EK65:EK69) -> 0 | EL64: =SUM(EL65:EL69) -> 0 | EM64: =SUM(EM65:EM69) -> 0 | EN64: =SUM(EN65:EN69) -> 0 | EO64: =SUM(EO65:EO69) -> 0 | EP64: =SUM(EP65:EP69) -> 0 | EQ64: =SUM(EQ65:EQ69) -> 0 | ... EU64: =SUM(EU65:EU69) -> 0 | EY64: 財務収入 | FA64: =SUM(FA65:FA69) -> 0 | FB64: =SUM(FB65:FB69) -> 0 | FC64: =SUM(FC65:FC69) -> 0 | FD64: =SUM(FD65:FD69) -> 0 | FE64: =SUM(FE65:FE69) -> 0 | FF64: =SUM(FF65:FF69) -> 0 | FG64: =SUM(FG65:FG69) -> 0 | FH64: =SUM(FH65:FH69) -> 0 | ... FL64: =SUM(FL65:FL69) -> 0
C65: 役員借入 | T65: =IF(C65="","",C65) -> 役員借入 | U65: 400000 | X65: -400000 | AK65: =IF(T65="","",T65) -> 役員借入 | BB65: 資本金 | BS65: 資本金 | CJ65: 資本金 | DA65: 資本金 | DR65: 資本金 | EI65: 資本金 | EZ65: 資本金
C66: 減価償却 | T66: =IF(C66="","",C66) -> 減価償却 | AK66: =IF(T66="","",T66) -> 減価償却 | BB66: 社債 | BS66: 社債 | CJ66: 社債 | CN66: -26000 | DA66: 社債 | DR66: 社債 | EI66: 社債 | EZ66: 社債
C67: 固定資産売却 | T67: =IF(C67="","",C67) -> 固定資産売却 | AK67: =IF(T67="","",T67) -> 固定資産売却 | BB67: 金融機関借入 | BS67: 金融機関借入 | CJ67: 金融機関借入 | DA67: 金融機関借入 | DR67: 金融機関借入 | EI67: 金融機関借入 | EZ67: 金融機関借入
T68: =IF(C68="","",C68) | AK68: =IF(T68="","",T68) | BB68: 固定資産売却 | BS68: 固定資産売却 | CJ68: 固定資産売却 | DA68: 固定資産売却 | DR68: 固定資産売却 | EI68: 固定資産売却 | EZ68: 固定資産売却
T69: 給料繰り延べ | V69: =Sheet2!G9 -> 281600 | W69: -281600 | AK69: 給料繰り延べ | AM69: =Sheet2!X9 -> 0 | BB69: FC保証金 | BC69: =(BC10-AW10)*$K$82+(BC11-AW11)*$K$83+(BC12-AW12)*AS84+(BC13-AW13)*$K$85 -> -120000000 | BD69: =(BD10-BC10)*$K$82+(BD11-BC11)*$K$83+(BD12-BC12)*$K$84+(BD13-BC13)*$K$85 -> 0 | BE69: =(BE10-BD10)*$K$82+(BE11-BD11)*$K$83+(BE12-BD12)*$K$84+(BE13-BD13)*$K$85 -> 0 | BF69: =(BF10-BE10)*$K$82+(BF11-BE11)*$K$83+(BF12-BE12)*$K$84+(BF13-BE13)*$K$85 -> 0 | BG69: =(BG10-BF10)*$K$82+(BG11-BF11)*$K$83+(BG12-BF12)*$K$84+(BG13-BF13)*$K$85 -> 0 | BH69: =(BH10-BG10)*$K$82+(BH11-BG11)*$K$83+(BH12-BG12)*$K$84+(BH13-BG13)*$K$85 -> 0 | BI69: =(BI10-BH10)*$K$82+(BI11-BH11)*$K$83+(BI12-BH12)*$K$84+(BI13-BH13)*$K$85 -> 0 | BJ69: =(BJ10-BI10)*$K$82+(BJ11-BI11)*$K$83+(BJ12-BI12)*$K$84+(BJ13-BI13)*$K$85 -> 0 | BK69: =(BK10-BJ10)*$K$82+(BK11-BJ11)*$K$83+(BK12-BJ12)*$K$84+(BK13-BJ13)*$K$85 -> 0 | ... BN69: =(BN10-BM10)*$K$82+(BN11-BM11)*$K$83+(BN12-BM12)*$K$84+(BN13-BM13)*$K$85 -> 0 | BS69: FC保証金 | BT69: =(BT10-BN10)*$K$82+(BT11-BN11)*$K$83+(BT12-BN12)*BJ84+(BT13-BN13)*$K$85 -> 0 | BU69: =(BU10-BT10)*$K$82+(BU11-BT11)*$K$83+(BU12-BT12)*$K$84+(BU13-BT13)*$K$85 -> 0 | BV69: =(BV10-BU10)*$K$82+(BV11-BU11)*$K$83+(BV12-BU12)*$K$84+(BV13-BU13)*$K$85 -> 0 | BW69: =(BW10-BV10)*$K$82+(BW11-BV11)*$K$83+(BW12-BV12)*$K$84+(BW13-BV13)*$K$85 -> 0 | BX69: =(BX10-BW10)*$K$82+(BX11-BW11)*$K$83+(BX12-BW12)*$K$84+(BX13-BW13)*$K$85 -> 0 | BY69: =(BY10-BX10)*$K$82+(BY11-BX11)*$K$83+(BY12-BX12)*$K$84+(BY13-BX13)*$K$85 -> 0 | BZ69: =(BZ10-BY10)*$K$82+(BZ11-BY11)*$K$83+(BZ12-BY12)*$K$84+(BZ13-BY13)*$K$85 -> 0 | CA69: =(CA10-BZ10)*$K$82+(CA11-BZ11)*$K$83+(CA12-BZ12)*$K$84+(CA13-BZ13)*$K$85 -> 0 | CB69: =(CB10-CA10)*$K$82+(CB11-CA11)*$K$83+(CB12-CA12)*$K$84+(CB13-CA13)*$K$85 -> 0 | ... CE69: =(CE10-CD10)*$K$82+(CE11-CD11)*$K$83+(CE12-CD12)*$K$84+(CE13-CD13)*$K$85 -> 0 | CJ69: FC保証金 | CK69: =(CK10-CE10)*$K$82+(CK11-CE11)*$K$83+(CK12-CE12)*CA84+(CK13-CE13)*$K$85 -> 0 | CL69: =(CL10-CK10)*$K$82+(CL11-CK11)*$K$83+(CL12-CK12)*$K$84+(CL13-CK13)*$K$85 -> 0 | CM69: =(CM10-CL10)*$K$82+(CM11-CL11)*$K$83+(CM12-CL12)*$K$84+(CM13-CL13)*$K$85 -> 0 | CN69: =(CN10-CM10)*$K$82+(CN11-CM11)*$K$83+(CN12-CM12)*$K$84+(CN13-CM13)*$K$85 -> 0 | CO69: =(CO10-CN10)*$K$82+(CO11-CN11)*$K$83+(CO12-CN12)*$K$84+(CO13-CN13)*$K$85 -> 0 | CP69: =(CP10-CO10)*$K$82+(CP11-CO11)*$K$83+(CP12-CO12)*$K$84+(CP13-CO13)*$K$85 -> 0 | CQ69: =(CQ10-CP10)*$K$82+(CQ11-CP11)*$K$83+(CQ12-CP12)*$K$84+(CQ13-CP13)*$K$85 -> 0 | CR69: =(CR10-CQ10)*$K$82+(CR11-CQ11)*$K$83+(CR12-CQ12)*$K$84+(CR13-CQ13)*$K$85 -> 0 | CS69: =(CS10-CR10)*$K$82+(CS11-CR11)*$K$83+(CS12-CR12)*$K$84+(CS13-CR13)*$K$85 -> 0 | ... CV69: =(CV10-CU10)*$K$82+(CV11-CU11)*$K$83+(CV12-CU12)*$K$84+(CV13-CU13)*$K$85 -> 0 | DA69: FC保証金 | DB69: =(DB10-CV10)*$K$82+(DB11-CV11)*$K$83+(DB12-CV12)*CR84+(DB13-CV13)*$K$85 -> 0 | DC69: =(DC10-DB10)*$K$82+(DC11-DB11)*$K$83+(DC12-DB12)*$K$84+(DC13-DB13)*$K$85 -> 0 | DD69: =(DD10-DC10)*$K$82+(DD11-DC11)*$K$83+(DD12-DC12)*$K$84+(DD13-DC13)*$K$85 -> 0 | DE69: =(DE10-DD10)*$K$82+(DE11-DD11)*$K$83+(DE12-DD12)*$K$84+(DE13-DD13)*$K$85 -> 0 | DF69: =(DF10-DE10)*$K$82+(DF11-DE11)*$K$83+(DF12-DE12)*$K$84+(DF13-DE13)*$K$85 -> 0 | DG69: =(DG10-DF10)*$K$82+(DG11-DF11)*$K$83+(DG12-DF12)*$K$84+(DG13-DF13)*$K$85 -> 0 | DH69: =(DH10-DG10)*$K$82+(DH11-DG11)*$K$83+(DH12-DG12)*$K$84+(DH13-DG13)*$K$85 -> 0 | DI69: =(DI10-DH10)*$K$82+(DI11-DH11)*$K$83+(DI12-DH12)*$K$84+(DI13-DH13)*$K$85 -> 0 | DJ69: =(DJ10-DI10)*$K$82+(DJ11-DI11)*$K$83+(DJ12-DI12)*$K$84+(DJ13-DI13)*$K$85 -> 0 | ... DM69: =(DM10-DL10)*$K$82+(DM11-DL11)*$K$83+(DM12-DL12)*$K$84+(DM13-DL13)*$K$85 -> 0 | DR69: FC保証金 | DS69: =(DS10-DM10)*$K$82+(DS11-DM11)*$K$83+(DS12-DM12)*DI84+(DS13-DM13)*$K$85 -> 0 | DT69: =(DT10-DS10)*$K$82+(DT11-DS11)*$K$83+(DT12-DS12)*$K$84+(DT13-DS13)*$K$85 -> 0 | DU69: =(DU10-DT10)*$K$82+(DU11-DT11)*$K$83+(DU12-DT12)*$K$84+(DU13-DT13)*$K$85 -> 0 | DV69: =(DV10-DU10)*$K$82+(DV11-DU11)*$K$83+(DV12-DU12)*$K$84+(DV13-DU13)*$K$85 -> 0 | DW69: =(DW10-DV10)*$K$82+(DW11-DV11)*$K$83+(DW12-DV12)*$K$84+(DW13-DV13)*$K$85 -> 0 | DX69: =(DX10-DW10)*$K$82+(DX11-DW11)*$K$83+(DX12-DW12)*$K$84+(DX13-DW13)*$K$85 -> 0 | DY69: =(DY10-DX10)*$K$82+(DY11-DX11)*$K$83+(DY12-DX12)*$K$84+(DY13-DX13)*$K$85 -> 0 | DZ69: =(DZ10-DY10)*$K$82+(DZ11-DY11)*$K$83+(DZ12-DY12)*$K$84+(DZ13-DY13)*$K$85 -> 0 | EA69: =(EA10-DZ10)*$K$82+(EA11-DZ11)*$K$83+(EA12-DZ12)*$K$84+(EA13-DZ13)*$K$85 -> 0 | ... ED69: =(ED10-EC10)*$K$82+(ED11-EC11)*$K$83+(ED12-EC12)*$K$84+(ED13-EC13)*$K$85 -> 0 | EI69: FC保証金 | EJ69: =(EJ10-ED10)*$K$82+(EJ11-ED11)*$K$83+(EJ12-ED12)*DZ84+(EJ13-ED13)*$K$85 -> 0 | EK69: =(EK10-EJ10)*$K$82+(EK11-EJ11)*$K$83+(EK12-EJ12)*$K$84+(EK13-EJ13)*$K$85 -> 0 | EL69: =(EL10-EK10)*$K$82+(EL11-EK11)*$K$83+(EL12-EK12)*$K$84+(EL13-EK13)*$K$85 -> 0 | EM69: =(EM10-EL10)*$K$82+(EM11-EL11)*$K$83+(EM12-EL12)*$K$84+(EM13-EL13)*$K$85 -> 0 | EN69: =(EN10-EM10)*$K$82+(EN11-EM11)*$K$83+(EN12-EM12)*$K$84+(EN13-EM13)*$K$85 -> 0 | EO69: =(EO10-EN10)*$K$82+(EO11-EN11)*$K$83+(EO12-EN12)*$K$84+(EO13-EN13)*$K$85 -> 0 | EP69: =(EP10-EO10)*$K$82+(EP11-EO11)*$K$83+(EP12-EO12)*$K$84+(EP13-EO13)*$K$85 -> 0 | EQ69: =(EQ10-EP10)*$K$82+(EQ11-EP11)*$K$83+(EQ12-EP12)*$K$84+(EQ13-EP13)*$K$85 -> 0 | ER69: =(ER10-EQ10)*$K$82+(ER11-EQ11)*$K$83+(ER12-EQ12)*$K$84+(ER13-EQ13)*$K$85 -> 0 | ... EU69: =(EU10-ET10)*$K$82+(EU11-ET11)*$K$83+(EU12-ET12)*$K$84+(EU13-ET13)*$K$85 -> 0 | EZ69: FC保証金 | FA69: =(FA10-EU10)*$K$82+(FA11-EU11)*$K$83+(FA12-EU12)*EQ84+(FA13-EU13)*$K$85 -> 0 | FB69: =(FB10-FA10)*$K$82+(FB11-FA11)*$K$83+(FB12-FA12)*$K$84+(FB13-FA13)*$K$85 -> 0 | FC69: =(FC10-FB10)*$K$82+(FC11-FB11)*$K$83+(FC12-FB12)*$K$84+(FC13-FB13)*$K$85 -> 0 | FD69: =(FD10-FC10)*$K$82+(FD11-FC11)*$K$83+(FD12-FC12)*$K$84+(FD13-FC13)*$K$85 -> 0 | FE69: =(FE10-FD10)*$K$82+(FE11-FD11)*$K$83+(FE12-FD12)*$K$84+(FE13-FD13)*$K$85 -> 0 | FF69: =(FF10-FE10)*$K$82+(FF11-FE11)*$K$83+(FF12-FE12)*$K$84+(FF13-FE13)*$K$85 -> 0 | FG69: =(FG10-FF10)*$K$82+(FG11-FF11)*$K$83+(FG12-FF12)*$K$84+(FG13-FF13)*$K$85 -> 0 | FH69: =(FH10-FG10)*$K$82+(FH11-FG11)*$K$83+(FH12-FG12)*$K$84+(FH13-FG13)*$K$85 -> 0 | FI69: =(FI10-FH10)*$K$82+(FI11-FH11)*$K$83+(FI12-FH12)*$K$84+(FI13-FH13)*$K$85 -> 0 | ... FL69: =(FL10-FK10)*$K$82+(FL11-FK11)*$K$83+(FL12-FK12)*$K$84+(FL13-FK13)*$K$85 -> 0
B70: 財務支出 | D70: =SUM(D71:D73) -> 0 | E70: =SUM(E71:E73) -> 0 | F70: =SUM(F71:F73) -> 0 | G70: =SUM(G71:G73) -> 0 | H70: =SUM(H71:H73) -> 0 | I70: =SUM(I71:I73) -> 0 | J70: =SUM(J71:J73) -> 0 | K70: =SUM(K71:K73) -> 0 | ... O70: =SUM(O71:O73) -> 0 | S70: 財務支出 | U70: =SUM(U71:U73) -> 0 | V70: =SUM(V71:V73) -> 0 | W70: =SUM(W71:W73) -> 0 | X70: =SUM(X71:X73) -> 0 | Y70: =SUM(Y71:Y73) -> 0 | Z70: =SUM(Z71:Z73) -> 0 | AA70: =SUM(AA71:AA73) -> 0 | AB70: =SUM(AB71:AB73) -> 0 | ... AF70: =SUM(AF71:AF73) -> 0 | AJ70: 財務支出 | AL70: =SUM(AL71:AL73) -> 0 | AM70: =SUM(AM71:AM73) -> 0 | AN70: =SUM(AN71:AN73) -> 0 | AO70: =SUM(AO71:AO73) -> 0 | AP70: =SUM(AP71:AP73) -> 0 | AQ70: =SUM(AQ71:AQ73) -> 0 | AR70: =SUM(AR71:AR73) -> 0 | AS70: =SUM(AS71:AS73) -> 0 | ... AW70: =SUM(AW71:AW73) -> 0 | BA70: 財務支出 | BC70: =SUM(BC71:BC73) -> 0 | BD70: =SUM(BD71:BD73) -> 0 | BE70: =SUM(BE71:BE73) -> 0 | BF70: =SUM(BF71:BF73) -> 0 | BG70: =SUM(BG71:BG73) -> 0 | BH70: =SUM(BH71:BH73) -> 0 | BI70: =SUM(BI71:BI73) -> 0 | BJ70: =SUM(BJ71:BJ73) -> 0 | ... BN70: =SUM(BN71:BN73) -> 0 | BR70: 財務支出 | BT70: =SUM(BT71:BT73) -> 0 | BU70: =SUM(BU71:BU73) -> 0 | BV70: =SUM(BV71:BV73) -> 0 | BW70: =SUM(BW71:BW73) -> 0 | BX70: =SUM(BX71:BX73) -> 0 | BY70: =SUM(BY71:BY73) -> 0 | BZ70: =SUM(BZ71:BZ73) -> 0 | CA70: =SUM(CA71:CA73) -> 0 | ... CE70: =SUM(CE71:CE73) -> 0 | CI70: 財務支出 | CK70: =SUM(CK71:CK73) -> 0 | CL70: =SUM(CL71:CL73) -> 0 | CM70: =SUM(CM71:CM73) -> 1112 | CN70: =SUM(CN71:CN73) -> 0 | CO70: =SUM(CO71:CO73) -> 0 | CP70: =SUM(CP71:CP73) -> 0 | CQ70: =SUM(CQ71:CQ73) -> 0 | CR70: =SUM(CR71:CR73) -> 0 | ... CV70: =SUM(CV71:CV73) -> 0 | CZ70: 財務支出 | DB70: =SUM(DB71:DB73) -> 0 | DC70: =SUM(DC71:DC73) -> 0 | DD70: =SUM(DD71:DD73) -> 0 | DE70: =SUM(DE71:DE73) -> 0 | DF70: =SUM(DF71:DF73) -> 0 | DG70: =SUM(DG71:DG73) -> 0 | DH70: =SUM(DH71:DH73) -> 0 | DI70: =SUM(DI71:DI73) -> 0 | ... DM70: =SUM(DM71:DM73) -> 0 | DQ70: 財務支出 | DS70: =SUM(DS71:DS73) -> 0 | DT70: =SUM(DT71:DT73) -> 0 | DU70: =SUM(DU71:DU73) -> 0 | DV70: =SUM(DV71:DV73) -> 0 | DW70: =SUM(DW71:DW73) -> 0 | DX70: =SUM(DX71:DX73) -> 0 | DY70: =SUM(DY71:DY73) -> 0 | DZ70: =SUM(DZ71:DZ73) -> 0 | ... ED70: =SUM(ED71:ED73) -> 0 | EH70: 財務支出 | EJ70: =SUM(EJ71:EJ73) -> 0 | EK70: =SUM(EK71:EK73) -> 0 | EL70: =SUM(EL71:EL73) -> 0 | EM70: =SUM(EM71:EM73) -> 0 | EN70: =SUM(EN71:EN73) -> 0 | EO70: =SUM(EO71:EO73) -> 0 | EP70: =SUM(EP71:EP73) -> 0 | EQ70: =SUM(EQ71:EQ73) -> 0 | ... EU70: =SUM(EU71:EU73) -> 0 | EY70: 財務支出 | FA70: =SUM(FA71:FA73) -> 0 | FB70: =SUM(FB71:FB73) -> 0 | FC70: =SUM(FC71:FC73) -> 0 | FD70: =SUM(FD71:FD73) -> 0 | FE70: =SUM(FE71:FE73) -> 0 | FF70: =SUM(FF71:FF73) -> 0 | FG70: =SUM(FG71:FG73) -> 0 | FH70: =SUM(FH71:FH73) -> 0 | ... FL70: =SUM(FL71:FL73) -> 0
C71: 店舗設備等 | T71: =IF(C71="","",C71) -> 店舗設備等 | AK71: =IF(T71="","",T71) -> 店舗設備等 | BB71: 営業権買取等 | BS71: 営業権買取等 | CJ71: 役員返済 | DA71: 役員返済 | DR71: 役員返済 | EI71: 役員返済 | EZ71: 役員返済
