Workbook

Sheet Claude Log
A1: Turn # | B1: Date | C1: User Request | D1: Action Taken | E1: Details | F1: Outcome
A2: 1 | B2: 46070 | C2: 「初年度末BS」シートが追加されたか確認してほしいとのリクエスト | D2: シートの存在と内容を確認 | E2: H23年度B/Sシート。借方（資産）と貸方（負債・資本）の構成を確認。数式は「初年度 損益資金計画」シートを参照。 | F2: シート確認完了。貸借差額235,200円あり（資産2,865,360 vs 負債・資本3,100,560）。修正要否をユーザーに確認中。
A3: 2 | B3: 46069 | C3: 全シートのデータを読み込んで内容を確認してほしい | D3: 6シート全てを読み込み、内容の概要をまとめて報告 | E3: 表紙（空白）、収支計画書（人材配置等）（R3～R7年の5年分の利用者数・給付費・人件費等）、損益及び資金計画書（R3・R4年度の損益計算書＋資金繰表）、稼働カレンダー（2021～2023年）を読み込み。損益計画書は数式で構成されており資金繰りシミュレーションが組まれている。 | F3: 全データ読み込み完了。R3年度は営業赤字▲5,847,900円、R4年度は経常利益18,371,340円で黒字転換。ユーザーからの次の指示を待機中。
A4: 3 | B4: 46069 | C4: 損益及び資金計画書を各年度1シートに分割してほしい | D4: 元シートを複製し、R3年度・R4年度の独立シートを作成。#REF!エラーを全て修正。 | E4: 元シート(R3+R4横並び)を2回複製。R3シートからR4列(S:AI)削除、R4シートからR3列(A:R)削除。R4シートで発生した#REF!エラー（減価償却=0、対売上比率、資金繰りのR3参照6箇所）を全て静的値で修正。前月繰越▲2,287,140円等。元シートはバックアップとして保持。 | F4: R3年度・R4年度シート作成完了。全数値が元シートと一致（総売上・営業利益・経常利益・期末繰越）。エラー0件。
A5: 4 | B5: 46069 | C5: 収支計画書（人材配置等）も各年度に分けてほしい | D5: 元シートを5回複製し、R3～R7年度の独立シートを作成。年度間参照エラーを修正。 | E5: 5年度分(R3:D-P, R4:Q-AC, R5:AD-AP, R6:AQ-BC, R7:BD-BP)を各シートに分割。R4年度で年度間参照（行25移行基本報酬=P25、行38-62の人件費・固定費=P列参照）が#REF!エラー化 → 元の値(8200, 230000, 126000等)で静的修正。全5シートエラー0件、給付費合計が元データと完全一致を確認。元シートはバックアップ保持。 | F5: R3～R7年度の収支計画書5シート作成完了。全数値一致・エラー0件。
A6: 5 | B6: 46069 | C6: R3〜R7全収支計画書の罫線途切れ・レイアウト統一を依頼 | D6: 5シートの罫線とフォントサイズをR3基準で統一修正 | E6: R5-R7: フォントサイズをsz:6に統一(E列〜P列の全データエリア)。R6: 行39-55の罫線完全欠落を修正(A-P全列)。R7: E38:P38のbottom罫線欠落、E57:P57のbottom罫線欠落を修正。R5-R7: D38/D48のright:medium罫線修正、D58-D62のleft/right:thin統一。 | F6: 全5シートの罫線パターンがR3基準と一致。フォントサイズ統一完了。検証済み。
A7: 6 | B7: 46069 | C7: 5か年計画の開始年月を設定するシートを作成したい。稼働日数と基本報酬単価も含める。 | D7: 「設定」シートを新規作成。計画開始設定（年・月・年度区切り）、5か年度一覧（自動生成）、報酬単価・稼働率テーブルを配置。 | E7: 開始年(西暦)→令和自動変換。年度区切り(4月/1月)ドロップダウン。年度名称・西暦・期間を数式で自動生成。報酬単価6項目×5年度(既存データから初期値設定)。稼働日数・稼働率も年度別入力。入力セルは黄色背景・青文字、計算セルは灰色背景。データ検証(年:2020-2050, 月:1-12)追加。 | F7: 設定シート完成。B4=2021(令和3年)開始、4月始まりで5年分自動生成。初期値は既存R3-R7データに基づき設定済み。
A8: 6 | B8: 46069 | C8: 稼働日を「歴日−8日」の数式に変更してほしいと依頼 | D8: 全5シートの収支計画書の稼働日（行4）を動的数式に変更。設定シートの年間稼働日も連動数式に更新 | E8: 数式: =DAY(EOMONTH(DATE(年,月,1),0))-8 を使用。R3〜R7の各収支計画書E4:P4に適用。設定シートC14等は=SUM('RX年度 収支計画書'!E4:P4)で自動集計。損益資金計画シートには稼働日行は存在しなかった | F8: 全5シート（R3〜R7収支計画書）の稼働日が歴日-8の動的数式に変更完了。設定シートの年間稼働日も連動。例: 4月=30-8=22日, 2月=28-8=20日（閏年は29-8=21日）
A9: 7 | B9: 46069 | C9: R3損益資金計画のA1等の年度固定値を設定シートに基づき自動変更してほしい | D9: 全7シートの年度表記を設定シート参照の数式に変更 | E9: R3/R4損益資金計画のA1、R3〜R7収支計画書のD2を設定シートの年度名称(C11,E11,G11,I11,K11)への参照数式に変更。ユーザーはB4を2026、B7を8に変更済みで、全シートが「令和8年度」〜「令和12年度」に自動更新された | F9: 全7シートの年度表記が設定シート連動に変更完了。設定シートの開始年を変えるだけで全シート一括更新される
A10: 8 | B10: 46069 | C10: 設定シートに基本報酬単価・社会保険料率等の毎年変更項目の参照を作成してほしい | D10: 設定シートに社会保険料率(行26)を追加。全5シートの収支計画書(R3〜R7)の報酬単価・稼働率・社保率を設定シート参照数式に書き換え | E10: 設定シート: セクション名を「基本報酬単価・料率設定」に変更、行26に社会保険料率を追加(R3/R4=13%, R5-R7=15%)。各収支計画書: 行23-29(単価6項目+稼働率)を=設定!$X$Yの絶対参照に、行55(社保)を=E54*設定!$X$26に変更。E列設定後copyToRangeでF〜P列に展開。稼働率はR3=0.8, R4-R7=0.8に統一（設定シート値を反映） | F10: 全5シートの報酬単価・稼働率・社会保険料率が設定シートから一元管理可能に。設定シートの値を変えるだけで全シート一括更新される
A11: 9 | B11: 46069 | C11: シート名を設定シートの年度名に基づいて変更してほしい | D11: 全7シート(損益資金計画2枚+収支計画書5枚)を設定シートの年度名称でリネーム | E11: R3年度→令和8年度, R4年度→令和9年度, R5年度→令和10年度, R6年度→令和11年度, R7年度→令和12年度。Excelがシート間参照の数式を自動更新。注意: シート名は数式で動的に変更不可のため、設定シートの年度変更時は再度リネームが必要 | F11: 全7シートが令和8〜12年度の名称に変更完了。シート間参照も自動更新済み
A12: 10 | B12: 46069 | C12: シート名を「初年度」「2年目」〜「5年目」の表現に変更してほしい | D12: 全7シートを初年度/2年目〜5年目の表記にリネーム | E12: 令和X年度→初年度〜5年目に変更。損益資金計画2枚+収支計画書5枚。設定シート等のシート間参照数式もExcelが自動更新済み | F12: 完了。年度に依存しない汎用的なシート名になり、設定シートで年度を変えてもシート名変更不要
A13: 11 | B13: 46070 | C13: 初年度末BSの貸借差額235,200円の修正依頼 | D13: E4とE5の数式を修正し、重複参照と不要項目を除去 | E13: E4: O34(地代家賃=10,000)がE3と重複→除去。E5: O30(法定福利費=25,200)がE4と重複→除去。E5: O22(工賃=200,000)は月次支払済のため除去。修正後: E4=146,200、E5=1,267,060 | F13: 貸借一致: 資産合計2,865,360 = 負債・資本合計2,865,360。差額0円。
... A16: 14 | B16: 46070 | C16: ユーザーが追加したPL・CFシートの内容確認を依頼 | D16: PLシート(sheetId:25)とCFシート(sheetId:26)の全データ・数式・構造を確認 | E16: PL: 5年分(H23-H27)の損益計算書。外部ファイル(和良経営管理表)から数式リンク。D-H列にデータあり。下部にサマリー(行46-51)と比率分析(行53-58)。CF: 5年分のキャッシュフロー計算書。経常収支・財務収支・DCF評価額を含む。I-M列は年度番号と割引率パラメータ。全数式が外部ファイル参照。 | F16: PL・CF両シートとも外部ファイル[和良経営管理表(Ver1.0).xlsx]基礎シートへの数式リンクで構成。旧年度(H23-H27)のデータ。I-M列は削除済みだが年度番号のみ残存。
A17: Turn 16 | B17: 46070 | C17: PLシートに損益資金計画（初年度～5年目）のデータを反映させてほしい | D17: PLシートの行ラベル書き換え、年度ヘッダー更新、数式リンク作成 | E17: 行構造: 旧飲食FC用→福祉事業用に全面書き換え。3行挿入(原価内訳5→8項目)。D-H列を各年度の損益資金計画!P列にリンク。年度ヘッダー=設定シート参照。税金=IF(経常利益<0,0,経常利益*0.4)。サマリー行49-54・比率行56-61も再計算。 | F17: PL完成: 令和8-12年度の5年間PL。総売上2,719,700→78,124,100へ成長。初年度赤字(-5,847,900)、2年目以降黒字化。全セル数式リンク済み、動的更新対応。
A18: 18 | B18: 46070 | C18: CFシート更新依頼（CFお願い）- 損益資金計画データとリンク | D18: CFシート全面更新: ラベル変更、5年分の数式作成、DCF評価更新 | E18: 行ラベルを飲食FC→福祉事業に変更（訓練給付金、就労売上、人件費等）。D-H列に5年分の数式を設定。数式パターン: =SUM('N年目 損益資金計画'!D行:O行)で月次→年間合計。内部計算式: 経常収支差額=収入-支出、CF=経常+財務、税引後CF=CF-税金、翌年度繰越=前年度+税引後CF。DCF行(43-48)も更新。年度ヘッダーは設定シート参照。 | F18: CF完了。全数式エラーなし。5年目翌年度繰越=64,316,221円。2年目以降の財務収支は損益資金計画未入力のため0。割引率(I43)未設定のためDCF割引未適用。
A19: 19 | B19: 46070 | C19: 設定シートにサービス種類（A型・B型・移行支援）、定員数（入力）、必要人員数（自動計算）のセクションを追加してほしい | D19: 設定シート行32-49に2セクション追加: 入力セクション（サービス種類/定員/配置比率）+ 自動計算セクション（利用者数/管理者/サビ管/指導員・支援員/就労支援員/合計） | E19: 入力: B35=サービス種類(ドロップダウン:A型/B型/移行支援)、B36=定員数(整数1-200)、B37=配置比率(ドロップダウン:6:1/7.5:1/10:1)。自動計算: B42=定員×0.9(利用者数)、B43=管理者1名固定、B44=サビ管(60人以下:1)、B45=指導員・支援員(利用者数÷配置比率)、B46=就労支援員(移行支援のみ:利用者数÷15)、B48=合計。法定人員配置基準に基づく計算式。デフォルト: B型/定員20/7.5:1。 | F19: 完了。B型・定員20名・7.5:1で利用者数18人→合計4.4人（管理者1+サビ管1+指導員・支援員2.4+就労支援員0）。ドロップダウン変更で自動再計算される。
A20: Turn 20 | B20: 46070 | C20: 人件費計算シート完成（前ターン継続）。初年度の総合計行追加、数式検証、その後2年目～5年目のテンプレートを展開、5年間サマリーテーブル作成 | D20: 人件費計算シート(sheetId:27)に5年分完成。各年度: 個人別給与10人枠+社保5項目+合計行。サマリーテーブルを行118-125に追加 | E20: 構造: R13-32(初年度), R34-53(2年目), R55-74(3年目), R76-95(4年目), R97-116(5年目), R118-125(サマリー)。社保率はB5:B9参照。介護保険はSUMPRODUCTで○印のみ計算。初年度は入社月制御付き。月額ヘッダーのテキスト比較問題を発見・修正済。年間合計: 初年度¥6,167,440, 2-5年目各¥15,291,360 | F20: 5年分完成。合計: 給与¥58,120,000+社保¥9,212,880=人件費¥67,332,880。次: 損益資金計画・収支計画書へのリンク接続
A21: Turn 21 | B21: 46070 | C21: 5つの損益資金計画シート（初年度～5年目）をドロップダウン式で1シートに集約できるか質問 | D21: 損益資金計画（集約）シート作成。A1にドロップダウン、CHOOSE関数で全セルを動的参照 | E21: INDIRECT関数がブロックされたため、CHOOSE($U$2,各シート!$X$Y)方式に切替。A1:P73全セル（ラベル+数値）を5シート対応のCHOOSE関数化。U2=MATCH(A1,S1:S5)でインデックス算出。S1:T5にルックアップテーブル配置・グループ化で非表示。書式はcopyFrom(formats)でソースシートから複製。ゼロ非表示:#,##0;-#,##0;""。相対参照ずれバグを発見→絶対参照($X$Y)で全数式を再構築。行1-2フリーズ。P1に「▼年度切替」表示。 | F21: 完成。A1ドロップダウンで初年度～5年目を切替可能。初年度表示確認済: 総売上2,719,700、経常利益-5,847,900。2年目切替時は総売上39,574,500に変わる見込み。元の5シートは変更なし。
A22: Turn 22 | B22: 46070 | C22: 初年度 損益資金計画のA43が集約シートに反映されていない→設定シート連動に変更を選択 | D22: 全5シートの損益資金計画A43を設定シート連動の数式に変更 | E22: 各シートA43: 旧「ＲX年度 資金繰表」(固定値) → 新=設定!X11&" 資金繰表"(数式)。初年度=C11, 2年目=E11, 3年目=G11, 4年目=I11, 5年目=K11。集約シートのCHOOSE関数は変更不要（元シートのA43を参照しているため自動反映）。 | F22: 完了。全5シートA43が設定シート連動に。初年度=令和8年度 資金繰表、2年目=令和9年度 資金繰表...5年目=令和12年度 資金繰表。集約シートでも正常反映確認済み。

Sheet 設定
A1: ５か年 収支計画 設定シート
A3: ■ 計画開始設定
A4: 開始年（西暦） | B4: 2026 | C4: ← 年を入力
A5: 開始月 | B5: 4 | C5: ← 月を入力（1〜12）
A6: 年度区切り | B6: 4月始まり | C6: ← 4月始まり / 1月始まり
A7: 令和年対応 | B7: =B4-2018 -> 8 | C7: ← 自動計算（令和）
A9: ■ ５か年度 一覧（自動生成）
C10: 初年度 | E10: 2年度 | G10: 3年度 | I10: 4年度 | K10: 5年度
A11: 年度名称 | C11: ="令和"&B7&"年度" -> 令和8年度 | E11: ="令和"&B7+1&"年度" -> 令和9年度 | G11: ="令和"&B7+2&"年度" -> 令和10年度 | I11: ="令和"&B7+3&"年度" -> 令和11年度 | K11: ="令和"&B7+4&"年度" -> 令和12年度
A12: 西暦 | C12: =B4&"年" -> 2026年 | E12: =B4+1&"年" -> 2027年 | G12: =B4+2&"年" -> 2028年 | I12: =B4+3&"年" -> 2029年 | K12: =B4+4&"年" -> 2030年
A13: 期間 | C13: =B5&"月〜"&IF(B6="4月始まり","3月","12月") -> 4月〜3月 | E13: =IF(B6="4月始まり","4月〜3月","1月〜12月") -> 4月〜3月 | G13: =E13 -> 4月〜3月 | I13: =E13 -> 4月〜3月 | K13: =E13 -> 4月〜3月
A14: 稼働日数（年間） | C14: =SUM('初年度 収支計画書'!E4:P4) -> 269 | D14: 日 | E14: =SUM('2年目 収支計画書'!E4:P4) -> 269 | F14: 日 | G14: =SUM('3年目 収支計画書'!E4:P4) -> 269 | H14: 日 | I14: =SUM('4年目 収支計画書'!E4:P4) -> 270 | J14: 日 | K14: =SUM('5年目 収支計画書'!E4:P4) -> 269 | L14: 日
A16: ■ 基本報酬単価・料率設定
A17: 項目 | C17: =C11 -> 令和8年度 | E17: =E11 -> 令和9年度 | G17: =G11 -> 令和10年度 | I17: =I11 -> 令和11年度 | K17: =K11 -> 令和12年度
A18: B基本報酬 | C18: 5890 | E18: 5890 | G18: 5890 | I18: 5890 | K18: 5890
A19: B施設外基本報酬 | C19: 6890 | E19: 6890 | G19: 6890 | I19: 6890 | K19: 6890
A20: 移行基本報酬 | C20: 8200 | E20: 8200 | G20: 8080 | I20: 8080 | K20: 8080
A21: 移行施設外基本報酬 | C21: 8200 | E21: 8200 | G21: 9080 | I21: 9080 | K21: 9080
A22: 目標工賃達成指導員加算 | C22: 890 | E22: 890 | G22: 890 | I22: 890 | K22: 890
A23: 送迎加算 | C23: 540 | E23: 540 | G23: 540 | I23: 540 | K23: 540
A25: 稼働率 | C25: 0.8 | E25: 0.8 | G25: 0.8 | I25: 0.8 | K25: 0.8
A26: 社会保険料率 | C26: 0.13 | E26: 0.13 | G26: 0.15 | I26: 0.15 | K26: 0.15
A28: ■ 凡例
A29: █ 黄色背景・青文字 | B29: 入力セル（変更可能）
A30: █ 灰色背景 | B30: 自動計算セル（変更不可）
A32: ■ サービス種類・定員・人員配置設定
A34: 項目 | B34: 設定値 | C34: 説明
A35: サービス種類 | B35: 移行支援 | C35: ← A型 / B型 / 移行支援
A36: 定員数 | B36: 20 | C36: ← 人数を入力
A37: 配置比率 | B37: 7.5:1 | C37: ← 6:1 / 7.5:1 / 10:1（移行支援は6:1固定）
A39: ■ 必要人員数（自動計算）
A41: 職種 | B41: 必要人数（常勤換算） | C41: 算出根拠
A42: 利用者数（定員×0.9） | B42: =B36*0.9 -> 18 | C42: 定員×0.9（新規指定6ヶ月未満の場合）
A43: 管理者 | B43: 1 | C43: 常勤1人（サビ管兼務可）
A44: サービス管理責任者 | B44: =IF(B42<=60,1,1+ROUNDUP((B42-60)/40,0)) -> 1 | C44: 利用者60人以下:1人、61人以上:+40人ごとに1人
A45: 職業指導員・生活支援員 | B45: =ROUNDUP(B42/IF(B37="6:1",6,IF(B37="7.5:1",7.5,10)),1) -> 2.4 | C45: ="利用者数÷"&IF(B37="6:1","6",IF(B37="7.5:1","7.5","10"))&"（常勤換算）※いずれか1人以上常勤" -> 利用者数÷7.5（常勤換算）※いずれか1人以上常勤
A46: 就労支援員 | B46: =IF(B35="移行支援",MAX(1,ROUNDUP(B42/15,1)),0) -> 1.2 | C46: =IF(B35="移行支援","利用者数÷15（常勤換算）※移行支援のみ","※移行支援のみ配置") -> 利用者数÷15（常勤換算）※移行支援のみ
A48: 合計必要人員数 | B48: =B43+B44+B45+B46 -> 5.6 | C48: ="管理者+サビ管+指導員・支援員"&IF(B35="移行支援","+就労支援員","") -> 管理者+サビ管+指導員・支援員+就労支援員
A49: ※管理者とサビ管の兼務が可能な場合、実質的な最低人数は合計-1人

Sheet 損益資金計画（集約）
A1: 2年目 | B1: =CHOOSE($U$2,'初年度 損益資金計画'!$A$1,'2年目 損益資金計画'!$A$1,'3年目 損益資金計画'!$A$1,'4年目 損益資金計画'!$A$1,'5年目 損益資金計画'!$A$1) -> 令和9年度 | D1: =CHOOSE($U$2,'初年度 損益資金計画'!$D$1,'2年目 損益資金計画'!$D$1,'3年目 損益資金計画'!$D$1,'4年目 損益資金計画'!$D$1,'5年目 損益資金計画'!$D$1) -> 0 | E1: =CHOOSE($U$2,'初年度 損益資金計画'!$E$1,'2年目 損益資金計画'!$E$1,'3年目 損益資金計画'!$E$1,'4年目 損益資金計画'!$E$1,'5年目 損益資金計画'!$E$1) -> 0 | F1: =CHOOSE($U$2,'初年度 損益資金計画'!$F$1,'2年目 損益資金計画'!$F$1,'3年目 損益資金計画'!$F$1,'4年目 損益資金計画'!$F$1,'5年目 損益資金計画'!$F$1) -> 0 | G1: =CHOOSE($U$2,'初年度 損益資金計画'!$G$1,'2年目 損益資金計画'!$G$1,'3年目 損益資金計画'!$G$1,'4年目 損益資金計画'!$G$1,'5年目 損益資金計画'!$G$1) -> 0 | H1: =CHOOSE($U$2,'初年度 損益資金計画'!$H$1,'2年目 損益資金計画'!$H$1,'3年目 損益資金計画'!$H$1,'4年目 損益資金計画'!$H$1,'5年目 損益資金計画'!$H$1) -> 0 | I1: =CHOOSE($U$2,'初年度 損益資金計画'!$I$1,'2年目 損益資金計画'!$I$1,'3年目 損益資金計画'!$I$1,'4年目 損益資金計画'!$I$1,'5年目 損益資金計画'!$I$1) -> 0 | J1: =CHOOSE($U$2,'初年度 損益資金計画'!$J$1,'2年目 損益資金計画'!$J$1,'3年目 損益資金計画'!$J$1,'4年目 損益資金計画'!$J$1,'5年目 損益資金計画'!$J$1) -> 0 | K1: =CHOOSE($U$2,'初年度 損益資金計画'!$K$1,'2年目 損益資金計画'!$K$1,'3年目 損益資金計画'!$K$1,'4年目 損益資金計画'!$K$1,'5年目 損益資金計画'!$K$1) -> 0 | L1: =CHOOSE($U$2,'初年度 損益資金計画'!$L$1,'2年目 損益資金計画'!$L$1,'3年目 損益資金計画'!$L$1,'4年目 損益資金計画'!$L$1,'5年目 損益資金計画'!$L$1) -> 0 | M1: =CHOOSE($U$2,'初年度 損益資金計画'!$M$1,'2年目 損益資金計画'!$M$1,'3年目 損益資金計画'!$M$1,'4年目 損益資金計画'!$M$1,'5年目 損益資金計画'!$M$1) -> 0 | N1: =CHOOSE($U$2,'初年度 損益資金計画'!$N$1,'2年目 損益資金計画'!$N$1,'3年目 損益資金計画'!$N$1,'4年目 損益資金計画'!$N$1,'5年目 損益資金計画'!$N$1) -> 0 | O1: =CHOOSE($U$2,'初年度 損益資金計画'!$O$1,'2年目 損益資金計画'!$O$1,'3年目 損益資金計画'!$O$1,'4年目 損益資金計画'!$O$1,'5年目 損益資金計画'!$O$1) -> 0 | P1: =CHOOSE($U$2,'初年度 損益資金計画'!$P$1,'2年目 損益資金計画'!$P$1,'3年目 損益資金計画'!$P$1,'4年目 損益資金計画'!$P$1,'5年目 損益資金計画'!$P$1) -> 0 | S1: 初年度 | T1: 初年度 損益資金計画 | U1: YearIndex
A2: =CHOOSE($U$2,'初年度 損益資金計画'!$A$2,'2年目 損益資金計画'!$A$2,'3年目 損益資金計画'!$A$2,'4年目 損益資金計画'!$A$2,'5年目 損益資金計画'!$A$2) -> 0 | D2: =CHOOSE($U$2,'初年度 損益資金計画'!$D$2,'2年目 損益資金計画'!$D$2,'3年目 損益資金計画'!$D$2,'4年目 損益資金計画'!$D$2,'5年目 損益資金計画'!$D$2) -> ４月 | E2: =CHOOSE($U$2,'初年度 損益資金計画'!$E$2,'2年目 損益資金計画'!$E$2,'3年目 損益資金計画'!$E$2,'4年目 損益資金計画'!$E$2,'5年目 損益資金計画'!$E$2) -> ５月 | F2: =CHOOSE($U$2,'初年度 損益資金計画'!$F$2,'2年目 損益資金計画'!$F$2,'3年目 損益資金計画'!$F$2,'4年目 損益資金計画'!$F$2,'5年目 損益資金計画'!$F$2) -> ６月 | G2: =CHOOSE($U$2,'初年度 損益資金計画'!$G$2,'2年目 損益資金計画'!$G$2,'3年目 損益資金計画'!$G$2,'4年目 損益資金計画'!$G$2,'5年目 損益資金計画'!$G$2) -> ７月 | H2: =CHOOSE($U$2,'初年度 損益資金計画'!$H$2,'2年目 損益資金計画'!$H$2,'3年目 損益資金計画'!$H$2,'4年目 損益資金計画'!$H$2,'5年目 損益資金計画'!$H$2) -> ８月 | I2: =CHOOSE($U$2,'初年度 損益資金計画'!$I$2,'2年目 損益資金計画'!$I$2,'3年目 損益資金計画'!$I$2,'4年目 損益資金計画'!$I$2,'5年目 損益資金計画'!$I$2) -> ９月 | J2: =CHOOSE($U$2,'初年度 損益資金計画'!$J$2,'2年目 損益資金計画'!$J$2,'3年目 損益資金計画'!$J$2,'4年目 損益資金計画'!$J$2,'5年目 損益資金計画'!$J$2) -> １０月 | K2: =CHOOSE($U$2,'初年度 損益資金計画'!$K$2,'2年目 損益資金計画'!$K$2,'3年目 損益資金計画'!$K$2,'4年目 損益資金計画'!$K$2,'5年目 損益資金計画'!$K$2) -> １１月 | L2: =CHOOSE($U$2,'初年度 損益資金計画'!$L$2,'2年目 損益資金計画'!$L$2,'3年目 損益資金計画'!$L$2,'4年目 損益資金計画'!$L$2,'5年目 損益資金計画'!$L$2) -> １２月 | M2: =CHOOSE($U$2,'初年度 損益資金計画'!$M$2,'2年目 損益資金計画'!$M$2,'3年目 損益資金計画'!$M$2,'4年目 損益資金計画'!$M$2,'5年目 損益資金計画'!$M$2) -> １月 | N2: =CHOOSE($U$2,'初年度 損益資金計画'!$N$2,'2年目 損益資金計画'!$N$2,'3年目 損益資金計画'!$N$2,'4年目 損益資金計画'!$N$2,'5年目 損益資金計画'!$N$2) -> ２月 | O2: =CHOOSE($U$2,'初年度 損益資金計画'!$O$2,'2年目 損益資金計画'!$O$2,'3年目 損益資金計画'!$O$2,'4年目 損益資金計画'!$O$2,'5年目 損益資金計画'!$O$2) -> ３月 | P2: =CHOOSE($U$2,'初年度 損益資金計画'!$P$2,'2年目 損益資金計画'!$P$2,'3年目 損益資金計画'!$P$2,'4年目 損益資金計画'!$P$2,'5年目 損益資金計画'!$P$2) -> 合計 | S2: 2年目 | T2: 2年目 損益資金計画 | U2: =MATCH(A1,$S$1:$S$5,0) -> 2
A3: =CHOOSE($U$2,'初年度 損益資金計画'!$A$3,'2年目 損益資金計画'!$A$3,'3年目 損益資金計画'!$A$3,'4年目 損益資金計画'!$A$3,'5年目 損益資金計画'!$A$3) -> 総売上 | D3: =CHOOSE($U$2,'初年度 損益資金計画'!$D$3,'2年目 損益資金計画'!$D$3,'3年目 損益資金計画'!$D$3,'4年目 損益資金計画'!$D$3,'5年目 損益資金計画'!$D$3) -> 1898400 | E3: =CHOOSE($U$2,'初年度 損益資金計画'!$E$3,'2年目 損益資金計画'!$E$3,'3年目 損益資金計画'!$E$3,'4年目 損益資金計画'!$E$3,'5年目 損益資金計画'!$E$3) -> 2359800 | F3: =CHOOSE($U$2,'初年度 損益資金計画'!$F$3,'2年目 損益資金計画'!$F$3,'3年目 損益資金計画'!$F$3,'4年目 損益資金計画'!$F$3,'5年目 損益資金計画'!$F$3) -> 2807300 | G3: =CHOOSE($U$2,'初年度 損益資金計画'!$G$3,'2年目 損益資金計画'!$G$3,'3年目 損益資金計画'!$G$3,'4年目 損益資金計画'!$G$3,'5年目 損益資金計画'!$G$3) -> 2849200 | H3: =CHOOSE($U$2,'初年度 損益資金計画'!$H$3,'2年目 損益資金計画'!$H$3,'3年目 損益資金計画'!$H$3,'4年目 損益資金計画'!$H$3,'5年目 損益資金計画'!$H$3) -> 3156900 | I3: =CHOOSE($U$2,'初年度 損益資金計画'!$I$3,'2年目 損益資金計画'!$I$3,'3年目 損益資金計画'!$I$3,'4年目 損益資金計画'!$I$3,'5年目 損益資金計画'!$I$3) -> 3436500 | J3: =CHOOSE($U$2,'初年度 損益資金計画'!$J$3,'2年目 損益資金計画'!$J$3,'3年目 損益資金計画'!$J$3,'4年目 損益資金計画'!$J$3,'5年目 損益資金計画'!$J$3) -> 3583400 | K3: =CHOOSE($U$2,'初年度 損益資金計画'!$K$3,'2年目 損益資金計画'!$K$3,'3年目 損益資金計画'!$K$3,'4年目 損益資金計画'!$K$3,'5年目 損益資金計画'!$K$3) -> 3730200 | L3: =CHOOSE($U$2,'初年度 損益資金計画'!$L$3,'2年目 損益資金計画'!$L$3,'3年目 損益資金計画'!$L$3,'4年目 損益資金計画'!$L$3,'5年目 損益資金計画'!$L$3) -> 3555300 | M3: =CHOOSE($U$2,'初年度 損益資金計画'!$M$3,'2年目 損益資金計画'!$M$3,'3年目 損益資金計画'!$M$3,'4年目 損益資金計画'!$M$3,'5年目 損益資金計画'!$M$3) -> 3520400 | N3: =CHOOSE($U$2,'初年度 損益資金計画'!$N$3,'2年目 損益資金計画'!$N$3,'3年目 損益資金計画'!$N$3,'4年目 損益資金計画'!$N$3,'5年目 損益資金計画'!$N$3) -> 3996000 | O3: =CHOOSE($U$2,'初年度 損益資金計画'!$O$3,'2年目 損益資金計画'!$O$3,'3年目 損益資金計画'!$O$3,'4年目 損益資金計画'!$O$3,'5年目 損益資金計画'!$O$3) -> 4681100 | P3: =CHOOSE($U$2,'初年度 損益資金計画'!$P$3,'2年目 損益資金計画'!$P$3,'3年目 損益資金計画'!$P$3,'4年目 損益資金計画'!$P$3,'5年目 損益資金計画'!$P$3) -> 39574500 | S3: 3年目 | T3: 3年目 損益資金計画
A4: =CHOOSE($U$2,'初年度 損益資金計画'!$A$4,'2年目 損益資金計画'!$A$4,'3年目 損益資金計画'!$A$4,'4年目 損益資金計画'!$A$4,'5年目 損益資金計画'!$A$4) -> 0 | B4: =CHOOSE($U$2,'初年度 損益資金計画'!$B$4,'2年目 損益資金計画'!$B$4,'3年目 損益資金計画'!$B$4,'4年目 損益資金計画'!$B$4,'5年目 損益資金計画'!$B$4) -> 0 | C4: =CHOOSE($U$2,'初年度 損益資金計画'!$C$4,'2年目 損益資金計画'!$C$4,'3年目 損益資金計画'!$C$4,'4年目 損益資金計画'!$C$4,'5年目 損益資金計画'!$C$4) -> 利用者総数 | D4: =CHOOSE($U$2,'初年度 損益資金計画'!$D$4,'2年目 損益資金計画'!$D$4,'3年目 損益資金計画'!$D$4,'4年目 損益資金計画'!$D$4,'5年目 損益資金計画'!$D$4) -> 10 | E4: =CHOOSE($U$2,'初年度 損益資金計画'!$E$4,'2年目 損益資金計画'!$E$4,'3年目 損益資金計画'!$E$4,'4年目 損益資金計画'!$E$4,'5年目 損益資金計画'!$E$4) -> 14 | F4: =CHOOSE($U$2,'初年度 損益資金計画'!$F$4,'2年目 損益資金計画'!$F$4,'3年目 損益資金計画'!$F$4,'4年目 損益資金計画'!$F$4,'5年目 損益資金計画'!$F$4) -> 15 | G4: =CHOOSE($U$2,'初年度 損益資金計画'!$G$4,'2年目 損益資金計画'!$G$4,'3年目 損益資金計画'!$G$4,'4年目 損益資金計画'!$G$4,'5年目 損益資金計画'!$G$4) -> 16 | H4: =CHOOSE($U$2,'初年度 損益資金計画'!$H$4,'2年目 損益資金計画'!$H$4,'3年目 損益資金計画'!$H$4,'4年目 損益資金計画'!$H$4,'5年目 損益資金計画'!$H$4) -> 19 | I4: =CHOOSE($U$2,'初年度 損益資金計画'!$I$4,'2年目 損益資金計画'!$I$4,'3年目 損益資金計画'!$I$4,'4年目 損益資金計画'!$I$4,'5年目 損益資金計画'!$I$4) -> 20 | J4: =CHOOSE($U$2,'初年度 損益資金計画'!$J$4,'2年目 損益資金計画'!$J$4,'3年目 損益資金計画'!$J$4,'4年目 損益資金計画'!$J$4,'5年目 損益資金計画'!$J$4) -> 21 | K4: =CHOOSE($U$2,'初年度 損益資金計画'!$K$4,'2年目 損益資金計画'!$K$4,'3年目 損益資金計画'!$K$4,'4年目 損益資金計画'!$K$4,'5年目 損益資金計画'!$K$4) -> 22 | L4: =CHOOSE($U$2,'初年度 損益資金計画'!$L$4,'2年目 損益資金計画'!$L$4,'3年目 損益資金計画'!$L$4,'4年目 損益資金計画'!$L$4,'5年目 損益資金計画'!$L$4) -> 23 | M4: =CHOOSE($U$2,'初年度 損益資金計画'!$M$4,'2年目 損益資金計画'!$M$4,'3年目 損益資金計画'!$M$4,'4年目 損益資金計画'!$M$4,'5年目 損益資金計画'!$M$4) -> 24 | N4: =CHOOSE($U$2,'初年度 損益資金計画'!$N$4,'2年目 損益資金計画'!$N$4,'3年目 損益資金計画'!$N$4,'4年目 損益資金計画'!$N$4,'5年目 損益資金計画'!$N$4) -> 25 | O4: =CHOOSE($U$2,'初年度 損益資金計画'!$O$4,'2年目 損益資金計画'!$O$4,'3年目 損益資金計画'!$O$4,'4年目 損益資金計画'!$O$4,'5年目 損益資金計画'!$O$4) -> 26 | P4: =CHOOSE($U$2,'初年度 損益資金計画'!$P$4,'2年目 損益資金計画'!$P$4,'3年目 損益資金計画'!$P$4,'4年目 損益資金計画'!$P$4,'5年目 損益資金計画'!$P$4) -> 0 | S4: 4年目 | T4: 4年目 損益資金計画
B5: =CHOOSE($U$2,'初年度 損益資金計画'!$B$5,'2年目 損益資金計画'!$B$5,'3年目 損益資金計画'!$B$5,'4年目 損益資金計画'!$B$5,'5年目 損益資金計画'!$B$5) -> 訓練給付金等 | D5: =CHOOSE($U$2,'初年度 損益資金計画'!$D$5,'2年目 損益資金計画'!$D$5,'3年目 損益資金計画'!$D$5,'4年目 損益資金計画'!$D$5,'5年目 損益資金計画'!$D$5) -> 1398400 | E5: =CHOOSE($U$2,'初年度 損益資金計画'!$E$5,'2年目 損益資金計画'!$E$5,'3年目 損益資金計画'!$E$5,'4年目 損益資金計画'!$E$5,'5年目 損益資金計画'!$E$5) -> 1859800 | F5: =CHOOSE($U$2,'初年度 損益資金計画'!$F$5,'2年目 損益資金計画'!$F$5,'3年目 損益資金計画'!$F$5,'4年目 損益資金計画'!$F$5,'5年目 損益資金計画'!$F$5) -> 2307300 | G5: =CHOOSE($U$2,'初年度 損益資金計画'!$G$5,'2年目 損益資金計画'!$G$5,'3年目 損益資金計画'!$G$5,'4年目 損益資金計画'!$G$5,'5年目 損益資金計画'!$G$5) -> 2349200 | H5: =CHOOSE($U$2,'初年度 損益資金計画'!$H$5,'2年目 損益資金計画'!$H$5,'3年目 損益資金計画'!$H$5,'4年目 損益資金計画'!$H$5,'5年目 損益資金計画'!$H$5) -> 2656900 | I5: =CHOOSE($U$2,'初年度 損益資金計画'!$I$5,'2年目 損益資金計画'!$I$5,'3年目 損益資金計画'!$I$5,'4年目 損益資金計画'!$I$5,'5年目 損益資金計画'!$I$5) -> 2936500 | J5: =CHOOSE($U$2,'初年度 損益資金計画'!$J$5,'2年目 損益資金計画'!$J$5,'3年目 損益資金計画'!$J$5,'4年目 損益資金計画'!$J$5,'5年目 損益資金計画'!$J$5) -> 3083400 | K5: =CHOOSE($U$2,'初年度 損益資金計画'!$K$5,'2年目 損益資金計画'!$K$5,'3年目 損益資金計画'!$K$5,'4年目 損益資金計画'!$K$5,'5年目 損益資金計画'!$K$5) -> 3230200 | L5: =CHOOSE($U$2,'初年度 損益資金計画'!$L$5,'2年目 損益資金計画'!$L$5,'3年目 損益資金計画'!$L$5,'4年目 損益資金計画'!$L$5,'5年目 損益資金計画'!$L$5) -> 3055300 | M5: =CHOOSE($U$2,'初年度 損益資金計画'!$M$5,'2年目 損益資金計画'!$M$5,'3年目 損益資金計画'!$M$5,'4年目 損益資金計画'!$M$5,'5年目 損益資金計画'!$M$5) -> 3020400 | N5: =CHOOSE($U$2,'初年度 損益資金計画'!$N$5,'2年目 損益資金計画'!$N$5,'3年目 損益資金計画'!$N$5,'4年目 損益資金計画'!$N$5,'5年目 損益資金計画'!$N$5) -> 3496000 | O5: =CHOOSE($U$2,'初年度 損益資金計画'!$O$5,'2年目 損益資金計画'!$O$5,'3年目 損益資金計画'!$O$5,'4年目 損益資金計画'!$O$5,'5年目 損益資金計画'!$O$5) -> 4181100 | P5: =CHOOSE($U$2,'初年度 損益資金計画'!$P$5,'2年目 損益資金計画'!$P$5,'3年目 損益資金計画'!$P$5,'4年目 損益資金計画'!$P$5,'5年目 損益資金計画'!$P$5) -> 33574500 | S5: 5年目 | T5: 5年目 損益資金計画
B6: =CHOOSE($U$2,'初年度 損益資金計画'!$B$6,'2年目 損益資金計画'!$B$6,'3年目 損益資金計画'!$B$6,'4年目 損益資金計画'!$B$6,'5年目 損益資金計画'!$B$6) -> 0 | C6: =CHOOSE($U$2,'初年度 損益資金計画'!$C$6,'2年目 損益資金計画'!$C$6,'3年目 損益資金計画'!$C$6,'4年目 損益資金計画'!$C$6,'5年目 損益資金計画'!$C$6) -> コーリングサポ笠岡 | D6: =CHOOSE($U$2,'初年度 損益資金計画'!$D$6,'2年目 損益資金計画'!$D$6,'3年目 損益資金計画'!$D$6,'4年目 損益資金計画'!$D$6,'5年目 損益資金計画'!$D$6) -> 1398400 | E6: =CHOOSE($U$2,'初年度 損益資金計画'!$E$6,'2年目 損益資金計画'!$E$6,'3年目 損益資金計画'!$E$6,'4年目 損益資金計画'!$E$6,'5年目 損益資金計画'!$E$6) -> 1859800 | F6: =CHOOSE($U$2,'初年度 損益資金計画'!$F$6,'2年目 損益資金計画'!$F$6,'3年目 損益資金計画'!$F$6,'4年目 損益資金計画'!$F$6,'5年目 損益資金計画'!$F$6) -> 2307300 | G6: =CHOOSE($U$2,'初年度 損益資金計画'!$G$6,'2年目 損益資金計画'!$G$6,'3年目 損益資金計画'!$G$6,'4年目 損益資金計画'!$G$6,'5年目 損益資金計画'!$G$6) -> 2349200 | H6: =CHOOSE($U$2,'初年度 損益資金計画'!$H$6,'2年目 損益資金計画'!$H$6,'3年目 損益資金計画'!$H$6,'4年目 損益資金計画'!$H$6,'5年目 損益資金計画'!$H$6) -> 2656900 | I6: =CHOOSE($U$2,'初年度 損益資金計画'!$I$6,'2年目 損益資金計画'!$I$6,'3年目 損益資金計画'!$I$6,'4年目 損益資金計画'!$I$6,'5年目 損益資金計画'!$I$6) -> 2936500 | J6: =CHOOSE($U$2,'初年度 損益資金計画'!$J$6,'2年目 損益資金計画'!$J$6,'3年目 損益資金計画'!$J$6,'4年目 損益資金計画'!$J$6,'5年目 損益資金計画'!$J$6) -> 3083400 | K6: =CHOOSE($U$2,'初年度 損益資金計画'!$K$6,'2年目 損益資金計画'!$K$6,'3年目 損益資金計画'!$K$6,'4年目 損益資金計画'!$K$6,'5年目 損益資金計画'!$K$6) -> 3230200 | L6: =CHOOSE($U$2,'初年度 損益資金計画'!$L$6,'2年目 損益資金計画'!$L$6,'3年目 損益資金計画'!$L$6,'4年目 損益資金計画'!$L$6,'5年目 損益資金計画'!$L$6) -> 3055300 | M6: =CHOOSE($U$2,'初年度 損益資金計画'!$M$6,'2年目 損益資金計画'!$M$6,'3年目 損益資金計画'!$M$6,'4年目 損益資金計画'!$M$6,'5年目 損益資金計画'!$M$6) -> 3020400 | N6: =CHOOSE($U$2,'初年度 損益資金計画'!$N$6,'2年目 損益資金計画'!$N$6,'3年目 損益資金計画'!$N$6,'4年目 損益資金計画'!$N$6,'5年目 損益資金計画'!$N$6) -> 3496000 | O6: =CHOOSE($U$2,'初年度 損益資金計画'!$O$6,'2年目 損益資金計画'!$O$6,'3年目 損益資金計画'!$O$6,'4年目 損益資金計画'!$O$6,'5年目 損益資金計画'!$O$6) -> 4181100 | P6: =CHOOSE($U$2,'初年度 損益資金計画'!$P$6,'2年目 損益資金計画'!$P$6,'3年目 損益資金計画'!$P$6,'4年目 損益資金計画'!$P$6,'5年目 損益資金計画'!$P$6) -> 33574500
C7: =CHOOSE($U$2,'初年度 損益資金計画'!$C$7,'2年目 損益資金計画'!$C$7,'3年目 損益資金計画'!$C$7,'4年目 損益資金計画'!$C$7,'5年目 損益資金計画'!$C$7) -> 0 | D7: =CHOOSE($U$2,'初年度 損益資金計画'!$D$7,'2年目 損益資金計画'!$D$7,'3年目 損益資金計画'!$D$7,'4年目 損益資金計画'!$D$7,'5年目 損益資金計画'!$D$7) -> 0 | E7: =CHOOSE($U$2,'初年度 損益資金計画'!$E$7,'2年目 損益資金計画'!$E$7,'3年目 損益資金計画'!$E$7,'4年目 損益資金計画'!$E$7,'5年目 損益資金計画'!$E$7) -> 0 | F7: =CHOOSE($U$2,'初年度 損益資金計画'!$F$7,'2年目 損益資金計画'!$F$7,'3年目 損益資金計画'!$F$7,'4年目 損益資金計画'!$F$7,'5年目 損益資金計画'!$F$7) -> 0 | G7: =CHOOSE($U$2,'初年度 損益資金計画'!$G$7,'2年目 損益資金計画'!$G$7,'3年目 損益資金計画'!$G$7,'4年目 損益資金計画'!$G$7,'5年目 損益資金計画'!$G$7) -> 0 | H7: =CHOOSE($U$2,'初年度 損益資金計画'!$H$7,'2年目 損益資金計画'!$H$7,'3年目 損益資金計画'!$H$7,'4年目 損益資金計画'!$H$7,'5年目 損益資金計画'!$H$7) -> 0 | I7: =CHOOSE($U$2,'初年度 損益資金計画'!$I$7,'2年目 損益資金計画'!$I$7,'3年目 損益資金計画'!$I$7,'4年目 損益資金計画'!$I$7,'5年目 損益資金計画'!$I$7) -> 0 | J7: =CHOOSE($U$2,'初年度 損益資金計画'!$J$7,'2年目 損益資金計画'!$J$7,'3年目 損益資金計画'!$J$7,'4年目 損益資金計画'!$J$7,'5年目 損益資金計画'!$J$7) -> 0 | K7: =CHOOSE($U$2,'初年度 損益資金計画'!$K$7,'2年目 損益資金計画'!$K$7,'3年目 損益資金計画'!$K$7,'4年目 損益資金計画'!$K$7,'5年目 損益資金計画'!$K$7) -> 0 | L7: =CHOOSE($U$2,'初年度 損益資金計画'!$L$7,'2年目 損益資金計画'!$L$7,'3年目 損益資金計画'!$L$7,'4年目 損益資金計画'!$L$7,'5年目 損益資金計画'!$L$7) -> 0 | M7: =CHOOSE($U$2,'初年度 損益資金計画'!$M$7,'2年目 損益資金計画'!$M$7,'3年目 損益資金計画'!$M$7,'4年目 損益資金計画'!$M$7,'5年目 損益資金計画'!$M$7) -> 0 | N7: =CHOOSE($U$2,'初年度 損益資金計画'!$N$7,'2年目 損益資金計画'!$N$7,'3年目 損益資金計画'!$N$7,'4年目 損益資金計画'!$N$7,'5年目 損益資金計画'!$N$7) -> 0 | O7: =CHOOSE($U$2,'初年度 損益資金計画'!$O$7,'2年目 損益資金計画'!$O$7,'3年目 損益資金計画'!$O$7,'4年目 損益資金計画'!$O$7,'5年目 損益資金計画'!$O$7) -> 0 | P7: =CHOOSE($U$2,'初年度 損益資金計画'!$P$7,'2年目 損益資金計画'!$P$7,'3年目 損益資金計画'!$P$7,'4年目 損益資金計画'!$P$7,'5年目 損益資金計画'!$P$7) -> 0
C8: =CHOOSE($U$2,'初年度 損益資金計画'!$C$8,'2年目 損益資金計画'!$C$8,'3年目 損益資金計画'!$C$8,'4年目 損益資金計画'!$C$8,'5年目 損益資金計画'!$C$8) -> 0 | D8: =CHOOSE($U$2,'初年度 損益資金計画'!$D$8,'2年目 損益資金計画'!$D$8,'3年目 損益資金計画'!$D$8,'4年目 損益資金計画'!$D$8,'5年目 損益資金計画'!$D$8) -> 0 | E8: =CHOOSE($U$2,'初年度 損益資金計画'!$E$8,'2年目 損益資金計画'!$E$8,'3年目 損益資金計画'!$E$8,'4年目 損益資金計画'!$E$8,'5年目 損益資金計画'!$E$8) -> 0 | F8: =CHOOSE($U$2,'初年度 損益資金計画'!$F$8,'2年目 損益資金計画'!$F$8,'3年目 損益資金計画'!$F$8,'4年目 損益資金計画'!$F$8,'5年目 損益資金計画'!$F$8) -> 0 | G8: =CHOOSE($U$2,'初年度 損益資金計画'!$G$8,'2年目 損益資金計画'!$G$8,'3年目 損益資金計画'!$G$8,'4年目 損益資金計画'!$G$8,'5年目 損益資金計画'!$G$8) -> 0 | H8: =CHOOSE($U$2,'初年度 損益資金計画'!$H$8,'2年目 損益資金計画'!$H$8,'3年目 損益資金計画'!$H$8,'4年目 損益資金計画'!$H$8,'5年目 損益資金計画'!$H$8) -> 0 | I8: =CHOOSE($U$2,'初年度 損益資金計画'!$I$8,'2年目 損益資金計画'!$I$8,'3年目 損益資金計画'!$I$8,'4年目 損益資金計画'!$I$8,'5年目 損益資金計画'!$I$8) -> 0 | J8: =CHOOSE($U$2,'初年度 損益資金計画'!$J$8,'2年目 損益資金計画'!$J$8,'3年目 損益資金計画'!$J$8,'4年目 損益資金計画'!$J$8,'5年目 損益資金計画'!$J$8) -> 0 | K8: =CHOOSE($U$2,'初年度 損益資金計画'!$K$8,'2年目 損益資金計画'!$K$8,'3年目 損益資金計画'!$K$8,'4年目 損益資金計画'!$K$8,'5年目 損益資金計画'!$K$8) -> 0 | L8: =CHOOSE($U$2,'初年度 損益資金計画'!$L$8,'2年目 損益資金計画'!$L$8,'3年目 損益資金計画'!$L$8,'4年目 損益資金計画'!$L$8,'5年目 損益資金計画'!$L$8) -> 0 | M8: =CHOOSE($U$2,'初年度 損益資金計画'!$M$8,'2年目 損益資金計画'!$M$8,'3年目 損益資金計画'!$M$8,'4年目 損益資金計画'!$M$8,'5年目 損益資金計画'!$M$8) -> 0 | N8: =CHOOSE($U$2,'初年度 損益資金計画'!$N$8,'2年目 損益資金計画'!$N$8,'3年目 損益資金計画'!$N$8,'4年目 損益資金計画'!$N$8,'5年目 損益資金計画'!$N$8) -> 0 | O8: =CHOOSE($U$2,'初年度 損益資金計画'!$O$8,'2年目 損益資金計画'!$O$8,'3年目 損益資金計画'!$O$8,'4年目 損益資金計画'!$O$8,'5年目 損益資金計画'!$O$8) -> 0 | P8: =CHOOSE($U$2,'初年度 損益資金計画'!$P$8,'2年目 損益資金計画'!$P$8,'3年目 損益資金計画'!$P$8,'4年目 損益資金計画'!$P$8,'5年目 損益資金計画'!$P$8) -> 0
B9: =CHOOSE($U$2,'初年度 損益資金計画'!$B$9,'2年目 損益資金計画'!$B$9,'3年目 損益資金計画'!$B$9,'4年目 損益資金計画'!$B$9,'5年目 損益資金計画'!$B$9) -> 福祉的就労売上 | D9: =CHOOSE($U$2,'初年度 損益資金計画'!$D$9,'2年目 損益資金計画'!$D$9,'3年目 損益資金計画'!$D$9,'4年目 損益資金計画'!$D$9,'5年目 損益資金計画'!$D$9) -> 500000 | E9: =CHOOSE($U$2,'初年度 損益資金計画'!$E$9,'2年目 損益資金計画'!$E$9,'3年目 損益資金計画'!$E$9,'4年目 損益資金計画'!$E$9,'5年目 損益資金計画'!$E$9) -> 500000 | F9: =CHOOSE($U$2,'初年度 損益資金計画'!$F$9,'2年目 損益資金計画'!$F$9,'3年目 損益資金計画'!$F$9,'4年目 損益資金計画'!$F$9,'5年目 損益資金計画'!$F$9) -> 500000 | G9: =CHOOSE($U$2,'初年度 損益資金計画'!$G$9,'2年目 損益資金計画'!$G$9,'3年目 損益資金計画'!$G$9,'4年目 損益資金計画'!$G$9,'5年目 損益資金計画'!$G$9) -> 500000 | H9: =CHOOSE($U$2,'初年度 損益資金計画'!$H$9,'2年目 損益資金計画'!$H$9,'3年目 損益資金計画'!$H$9,'4年目 損益資金計画'!$H$9,'5年目 損益資金計画'!$H$9) -> 500000 | I9: =CHOOSE($U$2,'初年度 損益資金計画'!$I$9,'2年目 損益資金計画'!$I$9,'3年目 損益資金計画'!$I$9,'4年目 損益資金計画'!$I$9,'5年目 損益資金計画'!$I$9) -> 500000 | J9: =CHOOSE($U$2,'初年度 損益資金計画'!$J$9,'2年目 損益資金計画'!$J$9,'3年目 損益資金計画'!$J$9,'4年目 損益資金計画'!$J$9,'5年目 損益資金計画'!$J$9) -> 500000 | K9: =CHOOSE($U$2,'初年度 損益資金計画'!$K$9,'2年目 損益資金計画'!$K$9,'3年目 損益資金計画'!$K$9,'4年目 損益資金計画'!$K$9,'5年目 損益資金計画'!$K$9) -> 500000 | L9: =CHOOSE($U$2,'初年度 損益資金計画'!$L$9,'2年目 損益資金計画'!$L$9,'3年目 損益資金計画'!$L$9,'4年目 損益資金計画'!$L$9,'5年目 損益資金計画'!$L$9) -> 500000 | M9: =CHOOSE($U$2,'初年度 損益資金計画'!$M$9,'2年目 損益資金計画'!$M$9,'3年目 損益資金計画'!$M$9,'4年目 損益資金計画'!$M$9,'5年目 損益資金計画'!$M$9) -> 500000 | N9: =CHOOSE($U$2,'初年度 損益資金計画'!$N$9,'2年目 損益資金計画'!$N$9,'3年目 損益資金計画'!$N$9,'4年目 損益資金計画'!$N$9,'5年目 損益資金計画'!$N$9) -> 500000 | O9: =CHOOSE($U$2,'初年度 損益資金計画'!$O$9,'2年目 損益資金計画'!$O$9,'3年目 損益資金計画'!$O$9,'4年目 損益資金計画'!$O$9,'5年目 損益資金計画'!$O$9) -> 500000 | P9: =CHOOSE($U$2,'初年度 損益資金計画'!$P$9,'2年目 損益資金計画'!$P$9,'3年目 損益資金計画'!$P$9,'4年目 損益資金計画'!$P$9,'5年目 損益資金計画'!$P$9) -> 6000000
B10: =CHOOSE($U$2,'初年度 損益資金計画'!$B$10,'2年目 損益資金計画'!$B$10,'3年目 損益資金計画'!$B$10,'4年目 損益資金計画'!$B$10,'5年目 損益資金計画'!$B$10) -> 0 | C10: =CHOOSE($U$2,'初年度 損益資金計画'!$C$10,'2年目 損益資金計画'!$C$10,'3年目 損益資金計画'!$C$10,'4年目 損益資金計画'!$C$10,'5年目 損益資金計画'!$C$10) -> 0 | D10: =CHOOSE($U$2,'初年度 損益資金計画'!$D$10,'2年目 損益資金計画'!$D$10,'3年目 損益資金計画'!$D$10,'4年目 損益資金計画'!$D$10,'5年目 損益資金計画'!$D$10) -> 500000 | E10: =CHOOSE($U$2,'初年度 損益資金計画'!$E$10,'2年目 損益資金計画'!$E$10,'3年目 損益資金計画'!$E$10,'4年目 損益資金計画'!$E$10,'5年目 損益資金計画'!$E$10) -> 500000 | F10: =CHOOSE($U$2,'初年度 損益資金計画'!$F$10,'2年目 損益資金計画'!$F$10,'3年目 損益資金計画'!$F$10,'4年目 損益資金計画'!$F$10,'5年目 損益資金計画'!$F$10) -> 500000 | G10: =CHOOSE($U$2,'初年度 損益資金計画'!$G$10,'2年目 損益資金計画'!$G$10,'3年目 損益資金計画'!$G$10,'4年目 損益資金計画'!$G$10,'5年目 損益資金計画'!$G$10) -> 500000 | H10: =CHOOSE($U$2,'初年度 損益資金計画'!$H$10,'2年目 損益資金計画'!$H$10,'3年目 損益資金計画'!$H$10,'4年目 損益資金計画'!$H$10,'5年目 損益資金計画'!$H$10) -> 500000 | I10: =CHOOSE($U$2,'初年度 損益資金計画'!$I$10,'2年目 損益資金計画'!$I$10,'3年目 損益資金計画'!$I$10,'4年目 損益資金計画'!$I$10,'5年目 損益資金計画'!$I$10) -> 500000 | J10: =CHOOSE($U$2,'初年度 損益資金計画'!$J$10,'2年目 損益資金計画'!$J$10,'3年目 損益資金計画'!$J$10,'4年目 損益資金計画'!$J$10,'5年目 損益資金計画'!$J$10) -> 500000 | K10: =CHOOSE($U$2,'初年度 損益資金計画'!$K$10,'2年目 損益資金計画'!$K$10,'3年目 損益資金計画'!$K$10,'4年目 損益資金計画'!$K$10,'5年目 損益資金計画'!$K$10) -> 500000 | L10: =CHOOSE($U$2,'初年度 損益資金計画'!$L$10,'2年目 損益資金計画'!$L$10,'3年目 損益資金計画'!$L$10,'4年目 損益資金計画'!$L$10,'5年目 損益資金計画'!$L$10) -> 500000 | M10: =CHOOSE($U$2,'初年度 損益資金計画'!$M$10,'2年目 損益資金計画'!$M$10,'3年目 損益資金計画'!$M$10,'4年目 損益資金計画'!$M$10,'5年目 損益資金計画'!$M$10) -> 500000 | N10: =CHOOSE($U$2,'初年度 損益資金計画'!$N$10,'2年目 損益資金計画'!$N$10,'3年目 損益資金計画'!$N$10,'4年目 損益資金計画'!$N$10,'5年目 損益資金計画'!$N$10) -> 500000 | O10: =CHOOSE($U$2,'初年度 損益資金計画'!$O$10,'2年目 損益資金計画'!$O$10,'3年目 損益資金計画'!$O$10,'4年目 損益資金計画'!$O$10,'5年目 損益資金計画'!$O$10) -> 500000 | P10: =CHOOSE($U$2,'初年度 損益資金計画'!$P$10,'2年目 損益資金計画'!$P$10,'3年目 損益資金計画'!$P$10,'4年目 損益資金計画'!$P$10,'5年目 損益資金計画'!$P$10) -> 6000000
C11: =CHOOSE($U$2,'初年度 損益資金計画'!$C$11,'2年目 損益資金計画'!$C$11,'3年目 損益資金計画'!$C$11,'4年目 損益資金計画'!$C$11,'5年目 損益資金計画'!$C$11) -> 0 | D11: =CHOOSE($U$2,'初年度 損益資金計画'!$D$11,'2年目 損益資金計画'!$D$11,'3年目 損益資金計画'!$D$11,'4年目 損益資金計画'!$D$11,'5年目 損益資金計画'!$D$11) -> 0 | E11: =CHOOSE($U$2,'初年度 損益資金計画'!$E$11,'2年目 損益資金計画'!$E$11,'3年目 損益資金計画'!$E$11,'4年目 損益資金計画'!$E$11,'5年目 損益資金計画'!$E$11) -> 0 | F11: =CHOOSE($U$2,'初年度 損益資金計画'!$F$11,'2年目 損益資金計画'!$F$11,'3年目 損益資金計画'!$F$11,'4年目 損益資金計画'!$F$11,'5年目 損益資金計画'!$F$11) -> 0 | G11: =CHOOSE($U$2,'初年度 損益資金計画'!$G$11,'2年目 損益資金計画'!$G$11,'3年目 損益資金計画'!$G$11,'4年目 損益資金計画'!$G$11,'5年目 損益資金計画'!$G$11) -> 0 | H11: =CHOOSE($U$2,'初年度 損益資金計画'!$H$11,'2年目 損益資金計画'!$H$11,'3年目 損益資金計画'!$H$11,'4年目 損益資金計画'!$H$11,'5年目 損益資金計画'!$H$11) -> 0 | I11: =CHOOSE($U$2,'初年度 損益資金計画'!$I$11,'2年目 損益資金計画'!$I$11,'3年目 損益資金計画'!$I$11,'4年目 損益資金計画'!$I$11,'5年目 損益資金計画'!$I$11) -> 0 | J11: =CHOOSE($U$2,'初年度 損益資金計画'!$J$11,'2年目 損益資金計画'!$J$11,'3年目 損益資金計画'!$J$11,'4年目 損益資金計画'!$J$11,'5年目 損益資金計画'!$J$11) -> 0 | K11: =CHOOSE($U$2,'初年度 損益資金計画'!$K$11,'2年目 損益資金計画'!$K$11,'3年目 損益資金計画'!$K$11,'4年目 損益資金計画'!$K$11,'5年目 損益資金計画'!$K$11) -> 0 | L11: =CHOOSE($U$2,'初年度 損益資金計画'!$L$11,'2年目 損益資金計画'!$L$11,'3年目 損益資金計画'!$L$11,'4年目 損益資金計画'!$L$11,'5年目 損益資金計画'!$L$11) -> 0 | M11: =CHOOSE($U$2,'初年度 損益資金計画'!$M$11,'2年目 損益資金計画'!$M$11,'3年目 損益資金計画'!$M$11,'4年目 損益資金計画'!$M$11,'5年目 損益資金計画'!$M$11) -> 0 | N11: =CHOOSE($U$2,'初年度 損益資金計画'!$N$11,'2年目 損益資金計画'!$N$11,'3年目 損益資金計画'!$N$11,'4年目 損益資金計画'!$N$11,'5年目 損益資金計画'!$N$11) -> 0 | O11: =CHOOSE($U$2,'初年度 損益資金計画'!$O$11,'2年目 損益資金計画'!$O$11,'3年目 損益資金計画'!$O$11,'4年目 損益資金計画'!$O$11,'5年目 損益資金計画'!$O$11) -> 0 | P11: =CHOOSE($U$2,'初年度 損益資金計画'!$P$11,'2年目 損益資金計画'!$P$11,'3年目 損益資金計画'!$P$11,'4年目 損益資金計画'!$P$11,'5年目 損益資金計画'!$P$11) -> 0
B12: =CHOOSE($U$2,'初年度 損益資金計画'!$B$12,'2年目 損益資金計画'!$B$12,'3年目 損益資金計画'!$B$12,'4年目 損益資金計画'!$B$12,'5年目 損益資金計画'!$B$12) -> 特定困難者受給 | D12: =CHOOSE($U$2,'初年度 損益資金計画'!$D$12,'2年目 損益資金計画'!$D$12,'3年目 損益資金計画'!$D$12,'4年目 損益資金計画'!$D$12,'5年目 損益資金計画'!$D$12) -> 0 | E12: =CHOOSE($U$2,'初年度 損益資金計画'!$E$12,'2年目 損益資金計画'!$E$12,'3年目 損益資金計画'!$E$12,'4年目 損益資金計画'!$E$12,'5年目 損益資金計画'!$E$12) -> 0 | F12: =CHOOSE($U$2,'初年度 損益資金計画'!$F$12,'2年目 損益資金計画'!$F$12,'3年目 損益資金計画'!$F$12,'4年目 損益資金計画'!$F$12,'5年目 損益資金計画'!$F$12) -> 0 | G12: =CHOOSE($U$2,'初年度 損益資金計画'!$G$12,'2年目 損益資金計画'!$G$12,'3年目 損益資金計画'!$G$12,'4年目 損益資金計画'!$G$12,'5年目 損益資金計画'!$G$12) -> 0 | H12: =CHOOSE($U$2,'初年度 損益資金計画'!$H$12,'2年目 損益資金計画'!$H$12,'3年目 損益資金計画'!$H$12,'4年目 損益資金計画'!$H$12,'5年目 損益資金計画'!$H$12) -> 0 | I12: =CHOOSE($U$2,'初年度 損益資金計画'!$I$12,'2年目 損益資金計画'!$I$12,'3年目 損益資金計画'!$I$12,'4年目 損益資金計画'!$I$12,'5年目 損益資金計画'!$I$12) -> 0 | J12: =CHOOSE($U$2,'初年度 損益資金計画'!$J$12,'2年目 損益資金計画'!$J$12,'3年目 損益資金計画'!$J$12,'4年目 損益資金計画'!$J$12,'5年目 損益資金計画'!$J$12) -> 0 | K12: =CHOOSE($U$2,'初年度 損益資金計画'!$K$12,'2年目 損益資金計画'!$K$12,'3年目 損益資金計画'!$K$12,'4年目 損益資金計画'!$K$12,'5年目 損益資金計画'!$K$12) -> 0 | L12: =CHOOSE($U$2,'初年度 損益資金計画'!$L$12,'2年目 損益資金計画'!$L$12,'3年目 損益資金計画'!$L$12,'4年目 損益資金計画'!$L$12,'5年目 損益資金計画'!$L$12) -> 0 | M12: =CHOOSE($U$2,'初年度 損益資金計画'!$M$12,'2年目 損益資金計画'!$M$12,'3年目 損益資金計画'!$M$12,'4年目 損益資金計画'!$M$12,'5年目 損益資金計画'!$M$12) -> 0 | N12: =CHOOSE($U$2,'初年度 損益資金計画'!$N$12,'2年目 損益資金計画'!$N$12,'3年目 損益資金計画'!$N$12,'4年目 損益資金計画'!$N$12,'5年目 損益資金計画'!$N$12) -> 0 | O12: =CHOOSE($U$2,'初年度 損益資金計画'!$O$12,'2年目 損益資金計画'!$O$12,'3年目 損益資金計画'!$O$12,'4年目 損益資金計画'!$O$12,'5年目 損益資金計画'!$O$12) -> 0 | P12: =CHOOSE($U$2,'初年度 損益資金計画'!$P$12,'2年目 損益資金計画'!$P$12,'3年目 損益資金計画'!$P$12,'4年目 損益資金計画'!$P$12,'5年目 損益資金計画'!$P$12) -> 0
B13: =CHOOSE($U$2,'初年度 損益資金計画'!$B$13,'2年目 損益資金計画'!$B$13,'3年目 損益資金計画'!$B$13,'4年目 損益資金計画'!$B$13,'5年目 損益資金計画'!$B$13) -> その他収入 | D13: =CHOOSE($U$2,'初年度 損益資金計画'!$D$13,'2年目 損益資金計画'!$D$13,'3年目 損益資金計画'!$D$13,'4年目 損益資金計画'!$D$13,'5年目 損益資金計画'!$D$13) -> 0 | E13: =CHOOSE($U$2,'初年度 損益資金計画'!$E$13,'2年目 損益資金計画'!$E$13,'3年目 損益資金計画'!$E$13,'4年目 損益資金計画'!$E$13,'5年目 損益資金計画'!$E$13) -> 0 | F13: =CHOOSE($U$2,'初年度 損益資金計画'!$F$13,'2年目 損益資金計画'!$F$13,'3年目 損益資金計画'!$F$13,'4年目 損益資金計画'!$F$13,'5年目 損益資金計画'!$F$13) -> 0 | G13: =CHOOSE($U$2,'初年度 損益資金計画'!$G$13,'2年目 損益資金計画'!$G$13,'3年目 損益資金計画'!$G$13,'4年目 損益資金計画'!$G$13,'5年目 損益資金計画'!$G$13) -> 0 | H13: =CHOOSE($U$2,'初年度 損益資金計画'!$H$13,'2年目 損益資金計画'!$H$13,'3年目 損益資金計画'!$H$13,'4年目 損益資金計画'!$H$13,'5年目 損益資金計画'!$H$13) -> 0 | I13: =CHOOSE($U$2,'初年度 損益資金計画'!$I$13,'2年目 損益資金計画'!$I$13,'3年目 損益資金計画'!$I$13,'4年目 損益資金計画'!$I$13,'5年目 損益資金計画'!$I$13) -> 0 | J13: =CHOOSE($U$2,'初年度 損益資金計画'!$J$13,'2年目 損益資金計画'!$J$13,'3年目 損益資金計画'!$J$13,'4年目 損益資金計画'!$J$13,'5年目 損益資金計画'!$J$13) -> 0 | K13: =CHOOSE($U$2,'初年度 損益資金計画'!$K$13,'2年目 損益資金計画'!$K$13,'3年目 損益資金計画'!$K$13,'4年目 損益資金計画'!$K$13,'5年目 損益資金計画'!$K$13) -> 0 | L13: =CHOOSE($U$2,'初年度 損益資金計画'!$L$13,'2年目 損益資金計画'!$L$13,'3年目 損益資金計画'!$L$13,'4年目 損益資金計画'!$L$13,'5年目 損益資金計画'!$L$13) -> 0 | M13: =CHOOSE($U$2,'初年度 損益資金計画'!$M$13,'2年目 損益資金計画'!$M$13,'3年目 損益資金計画'!$M$13,'4年目 損益資金計画'!$M$13,'5年目 損益資金計画'!$M$13) -> 0 | N13: =CHOOSE($U$2,'初年度 損益資金計画'!$N$13,'2年目 損益資金計画'!$N$13,'3年目 損益資金計画'!$N$13,'4年目 損益資金計画'!$N$13,'5年目 損益資金計画'!$N$13) -> 0 | O13: =CHOOSE($U$2,'初年度 損益資金計画'!$O$13,'2年目 損益資金計画'!$O$13,'3年目 損益資金計画'!$O$13,'4年目 損益資金計画'!$O$13,'5年目 損益資金計画'!$O$13) -> 0 | P13: =CHOOSE($U$2,'初年度 損益資金計画'!$P$13,'2年目 損益資金計画'!$P$13,'3年目 損益資金計画'!$P$13,'4年目 損益資金計画'!$P$13,'5年目 損益資金計画'!$P$13) -> 0
A14: =CHOOSE($U$2,'初年度 損益資金計画'!$A$14,'2年目 損益資金計画'!$A$14,'3年目 損益資金計画'!$A$14,'4年目 損益資金計画'!$A$14,'5年目 損益資金計画'!$A$14) -> 0 | B14: =CHOOSE($U$2,'初年度 損益資金計画'!$B$14,'2年目 損益資金計画'!$B$14,'3年目 損益資金計画'!$B$14,'4年目 損益資金計画'!$B$14,'5年目 損益資金計画'!$B$14) -> 部門別経費 | D14: =CHOOSE($U$2,'初年度 損益資金計画'!$D$14,'2年目 損益資金計画'!$D$14,'3年目 損益資金計画'!$D$14,'4年目 損益資金計画'!$D$14,'5年目 損益資金計画'!$D$14) -> 1853830 | E14: =CHOOSE($U$2,'初年度 損益資金計画'!$E$14,'2年目 損益資金計画'!$E$14,'3年目 損益資金計画'!$E$14,'4年目 損益資金計画'!$E$14,'5年目 損益資金計画'!$E$14) -> 1353830 | F14: =CHOOSE($U$2,'初年度 損益資金計画'!$F$14,'2年目 損益資金計画'!$F$14,'3年目 損益資金計画'!$F$14,'4年目 損益資金計画'!$F$14,'5年目 損益資金計画'!$F$14) -> 1353830 | G14: =CHOOSE($U$2,'初年度 損益資金計画'!$G$14,'2年目 損益資金計画'!$G$14,'3年目 損益資金計画'!$G$14,'4年目 損益資金計画'!$G$14,'5年目 損益資金計画'!$G$14) -> 1353830 | H14: =CHOOSE($U$2,'初年度 損益資金計画'!$H$14,'2年目 損益資金計画'!$H$14,'3年目 損益資金計画'!$H$14,'4年目 損益資金計画'!$H$14,'5年目 損益資金計画'!$H$14) -> 1353830 | I14: =CHOOSE($U$2,'初年度 損益資金計画'!$I$14,'2年目 損益資金計画'!$I$14,'3年目 損益資金計画'!$I$14,'4年目 損益資金計画'!$I$14,'5年目 損益資金計画'!$I$14) -> 1353830 | J14: =CHOOSE($U$2,'初年度 損益資金計画'!$J$14,'2年目 損益資金計画'!$J$14,'3年目 損益資金計画'!$J$14,'4年目 損益資金計画'!$J$14,'5年目 損益資金計画'!$J$14) -> 1353830 | K14: =CHOOSE($U$2,'初年度 損益資金計画'!$K$14,'2年目 損益資金計画'!$K$14,'3年目 損益資金計画'!$K$14,'4年目 損益資金計画'!$K$14,'5年目 損益資金計画'!$K$14) -> 1353830 | L14: =CHOOSE($U$2,'初年度 損益資金計画'!$L$14,'2年目 損益資金計画'!$L$14,'3年目 損益資金計画'!$L$14,'4年目 損益資金計画'!$L$14,'5年目 損益資金計画'!$L$14) -> 2257830 | M14: =CHOOSE($U$2,'初年度 損益資金計画'!$M$14,'2年目 損益資金計画'!$M$14,'3年目 損益資金計画'!$M$14,'4年目 損益資金計画'!$M$14,'5年目 損益資金計画'!$M$14) -> 1353830 | N14: =CHOOSE($U$2,'初年度 損益資金計画'!$N$14,'2年目 損益資金計画'!$N$14,'3年目 損益資金計画'!$N$14,'4年目 損益資金計画'!$N$14,'5年目 損益資金計画'!$N$14) -> 1353830 | O14: =CHOOSE($U$2,'初年度 損益資金計画'!$O$14,'2年目 損益資金計画'!$O$14,'3年目 損益資金計画'!$O$14,'4年目 損益資金計画'!$O$14,'5年目 損益資金計画'!$O$14) -> 1353830 | P14: =CHOOSE($U$2,'初年度 損益資金計画'!$P$14,'2年目 損益資金計画'!$P$14,'3年目 損益資金計画'!$P$14,'4年目 損益資金計画'!$P$14,'5年目 損益資金計画'!$P$14) -> 17649960
A15: =CHOOSE($U$2,'初年度 損益資金計画'!$A$15,'2年目 損益資金計画'!$A$15,'3年目 損益資金計画'!$A$15,'4年目 損益資金計画'!$A$15,'5年目 損益資金計画'!$A$15) -> 0 | B15: =CHOOSE($U$2,'初年度 損益資金計画'!$B$15,'2年目 損益資金計画'!$B$15,'3年目 損益資金計画'!$B$15,'4年目 損益資金計画'!$B$15,'5年目 損益資金計画'!$B$15) -> 訓練給付金等 | D15: =CHOOSE($U$2,'初年度 損益資金計画'!$D$15,'2年目 損益資金計画'!$D$15,'3年目 損益資金計画'!$D$15,'4年目 損益資金計画'!$D$15,'5年目 損益資金計画'!$D$15) -> 1353830 | E15: =CHOOSE($U$2,'初年度 損益資金計画'!$E$15,'2年目 損益資金計画'!$E$15,'3年目 損益資金計画'!$E$15,'4年目 損益資金計画'!$E$15,'5年目 損益資金計画'!$E$15) -> 1353830 | F15: =CHOOSE($U$2,'初年度 損益資金計画'!$F$15,'2年目 損益資金計画'!$F$15,'3年目 損益資金計画'!$F$15,'4年目 損益資金計画'!$F$15,'5年目 損益資金計画'!$F$15) -> 1353830 | G15: =CHOOSE($U$2,'初年度 損益資金計画'!$G$15,'2年目 損益資金計画'!$G$15,'3年目 損益資金計画'!$G$15,'4年目 損益資金計画'!$G$15,'5年目 損益資金計画'!$G$15) -> 1353830 | H15: =CHOOSE($U$2,'初年度 損益資金計画'!$H$15,'2年目 損益資金計画'!$H$15,'3年目 損益資金計画'!$H$15,'4年目 損益資金計画'!$H$15,'5年目 損益資金計画'!$H$15) -> 1353830 | I15: =CHOOSE($U$2,'初年度 損益資金計画'!$I$15,'2年目 損益資金計画'!$I$15,'3年目 損益資金計画'!$I$15,'4年目 損益資金計画'!$I$15,'5年目 損益資金計画'!$I$15) -> 1353830 | J15: =CHOOSE($U$2,'初年度 損益資金計画'!$J$15,'2年目 損益資金計画'!$J$15,'3年目 損益資金計画'!$J$15,'4年目 損益資金計画'!$J$15,'5年目 損益資金計画'!$J$15) -> 1353830 | K15: =CHOOSE($U$2,'初年度 損益資金計画'!$K$15,'2年目 損益資金計画'!$K$15,'3年目 損益資金計画'!$K$15,'4年目 損益資金計画'!$K$15,'5年目 損益資金計画'!$K$15) -> 1353830 | L15: =CHOOSE($U$2,'初年度 損益資金計画'!$L$15,'2年目 損益資金計画'!$L$15,'3年目 損益資金計画'!$L$15,'4年目 損益資金計画'!$L$15,'5年目 損益資金計画'!$L$15) -> 2257830 | M15: =CHOOSE($U$2,'初年度 損益資金計画'!$M$15,'2年目 損益資金計画'!$M$15,'3年目 損益資金計画'!$M$15,'4年目 損益資金計画'!$M$15,'5年目 損益資金計画'!$M$15) -> 1353830 | N15: =CHOOSE($U$2,'初年度 損益資金計画'!$N$15,'2年目 損益資金計画'!$N$15,'3年目 損益資金計画'!$N$15,'4年目 損益資金計画'!$N$15,'5年目 損益資金計画'!$N$15) -> 1353830 | O15: =CHOOSE($U$2,'初年度 損益資金計画'!$O$15,'2年目 損益資金計画'!$O$15,'3年目 損益資金計画'!$O$15,'4年目 損益資金計画'!$O$15,'5年目 損益資金計画'!$O$15) -> 1353830 | P15: =CHOOSE($U$2,'初年度 損益資金計画'!$P$15,'2年目 損益資金計画'!$P$15,'3年目 損益資金計画'!$P$15,'4年目 損益資金計画'!$P$15,'5年目 損益資金計画'!$P$15) -> 17149960
A16: =CHOOSE($U$2,'初年度 損益資金計画'!$A$16,'2年目 損益資金計画'!$A$16,'3年目 損益資金計画'!$A$16,'4年目 損益資金計画'!$A$16,'5年目 損益資金計画'!$A$16) -> 0 | B16: =CHOOSE($U$2,'初年度 損益資金計画'!$B$16,'2年目 損益資金計画'!$B$16,'3年目 損益資金計画'!$B$16,'4年目 損益資金計画'!$B$16,'5年目 損益資金計画'!$B$16) -> 0 | C16: =CHOOSE($U$2,'初年度 損益資金計画'!$C$16,'2年目 損益資金計画'!$C$16,'3年目 損益資金計画'!$C$16,'4年目 損益資金計画'!$C$16,'5年目 損益資金計画'!$C$16) -> 人件費 | D16: =CHOOSE($U$2,'初年度 損益資金計画'!$D$16,'2年目 損益資金計画'!$D$16,'3年目 損益資金計画'!$D$16,'4年目 損益資金計画'!$D$16,'5年目 損益資金計画'!$D$16) -> 1091000 | E16: =CHOOSE($U$2,'初年度 損益資金計画'!$E$16,'2年目 損益資金計画'!$E$16,'3年目 損益資金計画'!$E$16,'4年目 損益資金計画'!$E$16,'5年目 損益資金計画'!$E$16) -> 1091000 | F16: =CHOOSE($U$2,'初年度 損益資金計画'!$F$16,'2年目 損益資金計画'!$F$16,'3年目 損益資金計画'!$F$16,'4年目 損益資金計画'!$F$16,'5年目 損益資金計画'!$F$16) -> 1091000 | G16: =CHOOSE($U$2,'初年度 損益資金計画'!$G$16,'2年目 損益資金計画'!$G$16,'3年目 損益資金計画'!$G$16,'4年目 損益資金計画'!$G$16,'5年目 損益資金計画'!$G$16) -> 1091000 | H16: =CHOOSE($U$2,'初年度 損益資金計画'!$H$16,'2年目 損益資金計画'!$H$16,'3年目 損益資金計画'!$H$16,'4年目 損益資金計画'!$H$16,'5年目 損益資金計画'!$H$16) -> 1091000 | I16: =CHOOSE($U$2,'初年度 損益資金計画'!$I$16,'2年目 損益資金計画'!$I$16,'3年目 損益資金計画'!$I$16,'4年目 損益資金計画'!$I$16,'5年目 損益資金計画'!$I$16) -> 1091000 | J16: =CHOOSE($U$2,'初年度 損益資金計画'!$J$16,'2年目 損益資金計画'!$J$16,'3年目 損益資金計画'!$J$16,'4年目 損益資金計画'!$J$16,'5年目 損益資金計画'!$J$16) -> 1091000 | K16: =CHOOSE($U$2,'初年度 損益資金計画'!$K$16,'2年目 損益資金計画'!$K$16,'3年目 損益資金計画'!$K$16,'4年目 損益資金計画'!$K$16,'5年目 損益資金計画'!$K$16) -> 1091000 | L16: =CHOOSE($U$2,'初年度 損益資金計画'!$L$16,'2年目 損益資金計画'!$L$16,'3年目 損益資金計画'!$L$16,'4年目 損益資金計画'!$L$16,'5年目 損益資金計画'!$L$16) -> 1891000 | M16: =CHOOSE($U$2,'初年度 損益資金計画'!$M$16,'2年目 損益資金計画'!$M$16,'3年目 損益資金計画'!$M$16,'4年目 損益資金計画'!$M$16,'5年目 損益資金計画'!$M$16) -> 1091000 | N16: =CHOOSE($U$2,'初年度 損益資金計画'!$N$16,'2年目 損益資金計画'!$N$16,'3年目 損益資金計画'!$N$16,'4年目 損益資金計画'!$N$16,'5年目 損益資金計画'!$N$16) -> 1091000 | O16: =CHOOSE($U$2,'初年度 損益資金計画'!$O$16,'2年目 損益資金計画'!$O$16,'3年目 損益資金計画'!$O$16,'4年目 損益資金計画'!$O$16,'5年目 損益資金計画'!$O$16) -> 1091000 | P16: =CHOOSE($U$2,'初年度 損益資金計画'!$P$16,'2年目 損益資金計画'!$P$16,'3年目 損益資金計画'!$P$16,'4年目 損益資金計画'!$P$16,'5年目 損益資金計画'!$P$16) -> 13892000
A17: =CHOOSE($U$2,'初年度 損益資金計画'!$A$17,'2年目 損益資金計画'!$A$17,'3年目 損益資金計画'!$A$17,'4年目 損益資金計画'!$A$17,'5年目 損益資金計画'!$A$17) -> 0 | C17: =CHOOSE($U$2,'初年度 損益資金計画'!$C$17,'2年目 損益資金計画'!$C$17,'3年目 損益資金計画'!$C$17,'4年目 損益資金計画'!$C$17,'5年目 損益資金計画'!$C$17) -> 社会保険料 | D17: =CHOOSE($U$2,'初年度 損益資金計画'!$D$17,'2年目 損益資金計画'!$D$17,'3年目 損益資金計画'!$D$17,'4年目 損益資金計画'!$D$17,'5年目 損益資金計画'!$D$17) -> 141830 | E17: =CHOOSE($U$2,'初年度 損益資金計画'!$E$17,'2年目 損益資金計画'!$E$17,'3年目 損益資金計画'!$E$17,'4年目 損益資金計画'!$E$17,'5年目 損益資金計画'!$E$17) -> 141830 | F17: =CHOOSE($U$2,'初年度 損益資金計画'!$F$17,'2年目 損益資金計画'!$F$17,'3年目 損益資金計画'!$F$17,'4年目 損益資金計画'!$F$17,'5年目 損益資金計画'!$F$17) -> 141830 | G17: =CHOOSE($U$2,'初年度 損益資金計画'!$G$17,'2年目 損益資金計画'!$G$17,'3年目 損益資金計画'!$G$17,'4年目 損益資金計画'!$G$17,'5年目 損益資金計画'!$G$17) -> 141830 | H17: =CHOOSE($U$2,'初年度 損益資金計画'!$H$17,'2年目 損益資金計画'!$H$17,'3年目 損益資金計画'!$H$17,'4年目 損益資金計画'!$H$17,'5年目 損益資金計画'!$H$17) -> 141830 | I17: =CHOOSE($U$2,'初年度 損益資金計画'!$I$17,'2年目 損益資金計画'!$I$17,'3年目 損益資金計画'!$I$17,'4年目 損益資金計画'!$I$17,'5年目 損益資金計画'!$I$17) -> 141830 | J17: =CHOOSE($U$2,'初年度 損益資金計画'!$J$17,'2年目 損益資金計画'!$J$17,'3年目 損益資金計画'!$J$17,'4年目 損益資金計画'!$J$17,'5年目 損益資金計画'!$J$17) -> 141830 | K17: =CHOOSE($U$2,'初年度 損益資金計画'!$K$17,'2年目 損益資金計画'!$K$17,'3年目 損益資金計画'!$K$17,'4年目 損益資金計画'!$K$17,'5年目 損益資金計画'!$K$17) -> 141830 | L17: =CHOOSE($U$2,'初年度 損益資金計画'!$L$17,'2年目 損益資金計画'!$L$17,'3年目 損益資金計画'!$L$17,'4年目 損益資金計画'!$L$17,'5年目 損益資金計画'!$L$17) -> 245830 | M17: =CHOOSE($U$2,'初年度 損益資金計画'!$M$17,'2年目 損益資金計画'!$M$17,'3年目 損益資金計画'!$M$17,'4年目 損益資金計画'!$M$17,'5年目 損益資金計画'!$M$17) -> 141830 | N17: =CHOOSE($U$2,'初年度 損益資金計画'!$N$17,'2年目 損益資金計画'!$N$17,'3年目 損益資金計画'!$N$17,'4年目 損益資金計画'!$N$17,'5年目 損益資金計画'!$N$17) -> 141830 | O17: =CHOOSE($U$2,'初年度 損益資金計画'!$O$17,'2年目 損益資金計画'!$O$17,'3年目 損益資金計画'!$O$17,'4年目 損益資金計画'!$O$17,'5年目 損益資金計画'!$O$17) -> 141830 | P17: =CHOOSE($U$2,'初年度 損益資金計画'!$P$17,'2年目 損益資金計画'!$P$17,'3年目 損益資金計画'!$P$17,'4年目 損益資金計画'!$P$17,'5年目 損益資金計画'!$P$17) -> 1805960
A18: =CHOOSE($U$2,'初年度 損益資金計画'!$A$18,'2年目 損益資金計画'!$A$18,'3年目 損益資金計画'!$A$18,'4年目 損益資金計画'!$A$18,'5年目 損益資金計画'!$A$18) -> 0 | C18: =CHOOSE($U$2,'初年度 損益資金計画'!$C$18,'2年目 損益資金計画'!$C$18,'3年目 損益資金計画'!$C$18,'4年目 損益資金計画'!$C$18,'5年目 損益資金計画'!$C$18) -> 管理費（水道光熱燃料等） | D18: =CHOOSE($U$2,'初年度 損益資金計画'!$D$18,'2年目 損益資金計画'!$D$18,'3年目 損益資金計画'!$D$18,'4年目 損益資金計画'!$D$18,'5年目 損益資金計画'!$D$18) -> 121000 | E18: =CHOOSE($U$2,'初年度 損益資金計画'!$E$18,'2年目 損益資金計画'!$E$18,'3年目 損益資金計画'!$E$18,'4年目 損益資金計画'!$E$18,'5年目 損益資金計画'!$E$18) -> 121000 | F18: =CHOOSE($U$2,'初年度 損益資金計画'!$F$18,'2年目 損益資金計画'!$F$18,'3年目 損益資金計画'!$F$18,'4年目 損益資金計画'!$F$18,'5年目 損益資金計画'!$F$18) -> 121000 | G18: =CHOOSE($U$2,'初年度 損益資金計画'!$G$18,'2年目 損益資金計画'!$G$18,'3年目 損益資金計画'!$G$18,'4年目 損益資金計画'!$G$18,'5年目 損益資金計画'!$G$18) -> 121000 | H18: =CHOOSE($U$2,'初年度 損益資金計画'!$H$18,'2年目 損益資金計画'!$H$18,'3年目 損益資金計画'!$H$18,'4年目 損益資金計画'!$H$18,'5年目 損益資金計画'!$H$18) -> 121000 | I18: =CHOOSE($U$2,'初年度 損益資金計画'!$I$18,'2年目 損益資金計画'!$I$18,'3年目 損益資金計画'!$I$18,'4年目 損益資金計画'!$I$18,'5年目 損益資金計画'!$I$18) -> 121000 | J18: =CHOOSE($U$2,'初年度 損益資金計画'!$J$18,'2年目 損益資金計画'!$J$18,'3年目 損益資金計画'!$J$18,'4年目 損益資金計画'!$J$18,'5年目 損益資金計画'!$J$18) -> 121000 | K18: =CHOOSE($U$2,'初年度 損益資金計画'!$K$18,'2年目 損益資金計画'!$K$18,'3年目 損益資金計画'!$K$18,'4年目 損益資金計画'!$K$18,'5年目 損益資金計画'!$K$18) -> 121000 | L18: =CHOOSE($U$2,'初年度 損益資金計画'!$L$18,'2年目 損益資金計画'!$L$18,'3年目 損益資金計画'!$L$18,'4年目 損益資金計画'!$L$18,'5年目 損益資金計画'!$L$18) -> 121000 | M18: =CHOOSE($U$2,'初年度 損益資金計画'!$M$18,'2年目 損益資金計画'!$M$18,'3年目 損益資金計画'!$M$18,'4年目 損益資金計画'!$M$18,'5年目 損益資金計画'!$M$18) -> 121000 | N18: =CHOOSE($U$2,'初年度 損益資金計画'!$N$18,'2年目 損益資金計画'!$N$18,'3年目 損益資金計画'!$N$18,'4年目 損益資金計画'!$N$18,'5年目 損益資金計画'!$N$18) -> 121000 | O18: =CHOOSE($U$2,'初年度 損益資金計画'!$O$18,'2年目 損益資金計画'!$O$18,'3年目 損益資金計画'!$O$18,'4年目 損益資金計画'!$O$18,'5年目 損益資金計画'!$O$18) -> 121000 | P18: =CHOOSE($U$2,'初年度 損益資金計画'!$P$18,'2年目 損益資金計画'!$P$18,'3年目 損益資金計画'!$P$18,'4年目 損益資金計画'!$P$18,'5年目 損益資金計画'!$P$18) -> 1452000
A19: =CHOOSE($U$2,'初年度 損益資金計画'!$A$19,'2年目 損益資金計画'!$A$19,'3年目 損益資金計画'!$A$19,'4年目 損益資金計画'!$A$19,'5年目 損益資金計画'!$A$19) -> 0 | C19: =CHOOSE($U$2,'初年度 損益資金計画'!$C$19,'2年目 損益資金計画'!$C$19,'3年目 損益資金計画'!$C$19,'4年目 損益資金計画'!$C$19,'5年目 損益資金計画'!$C$19) -> 燃料代 | D19: =CHOOSE($U$2,'初年度 損益資金計画'!$D$19,'2年目 損益資金計画'!$D$19,'3年目 損益資金計画'!$D$19,'4年目 損益資金計画'!$D$19,'5年目 損益資金計画'!$D$19) -> 0 | E19: =CHOOSE($U$2,'初年度 損益資金計画'!$E$19,'2年目 損益資金計画'!$E$19,'3年目 損益資金計画'!$E$19,'4年目 損益資金計画'!$E$19,'5年目 損益資金計画'!$E$19) -> 0 | F19: =CHOOSE($U$2,'初年度 損益資金計画'!$F$19,'2年目 損益資金計画'!$F$19,'3年目 損益資金計画'!$F$19,'4年目 損益資金計画'!$F$19,'5年目 損益資金計画'!$F$19) -> 0 | G19: =CHOOSE($U$2,'初年度 損益資金計画'!$G$19,'2年目 損益資金計画'!$G$19,'3年目 損益資金計画'!$G$19,'4年目 損益資金計画'!$G$19,'5年目 損益資金計画'!$G$19) -> 0 | H19: =CHOOSE($U$2,'初年度 損益資金計画'!$H$19,'2年目 損益資金計画'!$H$19,'3年目 損益資金計画'!$H$19,'4年目 損益資金計画'!$H$19,'5年目 損益資金計画'!$H$19) -> 0 | I19: =CHOOSE($U$2,'初年度 損益資金計画'!$I$19,'2年目 損益資金計画'!$I$19,'3年目 損益資金計画'!$I$19,'4年目 損益資金計画'!$I$19,'5年目 損益資金計画'!$I$19) -> 0 | J19: =CHOOSE($U$2,'初年度 損益資金計画'!$J$19,'2年目 損益資金計画'!$J$19,'3年目 損益資金計画'!$J$19,'4年目 損益資金計画'!$J$19,'5年目 損益資金計画'!$J$19) -> 0 | K19: =CHOOSE($U$2,'初年度 損益資金計画'!$K$19,'2年目 損益資金計画'!$K$19,'3年目 損益資金計画'!$K$19,'4年目 損益資金計画'!$K$19,'5年目 損益資金計画'!$K$19) -> 0 | L19: =CHOOSE($U$2,'初年度 損益資金計画'!$L$19,'2年目 損益資金計画'!$L$19,'3年目 損益資金計画'!$L$19,'4年目 損益資金計画'!$L$19,'5年目 損益資金計画'!$L$19) -> 0 | M19: =CHOOSE($U$2,'初年度 損益資金計画'!$M$19,'2年目 損益資金計画'!$M$19,'3年目 損益資金計画'!$M$19,'4年目 損益資金計画'!$M$19,'5年目 損益資金計画'!$M$19) -> 0 | N19: =CHOOSE($U$2,'初年度 損益資金計画'!$N$19,'2年目 損益資金計画'!$N$19,'3年目 損益資金計画'!$N$19,'4年目 損益資金計画'!$N$19,'5年目 損益資金計画'!$N$19) -> 0 | O19: =CHOOSE($U$2,'初年度 損益資金計画'!$O$19,'2年目 損益資金計画'!$O$19,'3年目 損益資金計画'!$O$19,'4年目 損益資金計画'!$O$19,'5年目 損益資金計画'!$O$19) -> 0 | P19: =CHOOSE($U$2,'初年度 損益資金計画'!$P$19,'2年目 損益資金計画'!$P$19,'3年目 損益資金計画'!$P$19,'4年目 損益資金計画'!$P$19,'5年目 損益資金計画'!$P$19) -> 0
A20: =CHOOSE($U$2,'初年度 損益資金計画'!$A$20,'2年目 損益資金計画'!$A$20,'3年目 損益資金計画'!$A$20,'4年目 損益資金計画'!$A$20,'5年目 損益資金計画'!$A$20) -> 0 | C20: =CHOOSE($U$2,'初年度 損益資金計画'!$C$20,'2年目 損益資金計画'!$C$20,'3年目 損益資金計画'!$C$20,'4年目 損益資金計画'!$C$20,'5年目 損益資金計画'!$C$20) -> 諸費 | D20: =CHOOSE($U$2,'初年度 損益資金計画'!$D$20,'2年目 損益資金計画'!$D$20,'3年目 損益資金計画'!$D$20,'4年目 損益資金計画'!$D$20,'5年目 損益資金計画'!$D$20) -> 0 | E20: =CHOOSE($U$2,'初年度 損益資金計画'!$E$20,'2年目 損益資金計画'!$E$20,'3年目 損益資金計画'!$E$20,'4年目 損益資金計画'!$E$20,'5年目 損益資金計画'!$E$20) -> 0 | F20: =CHOOSE($U$2,'初年度 損益資金計画'!$F$20,'2年目 損益資金計画'!$F$20,'3年目 損益資金計画'!$F$20,'4年目 損益資金計画'!$F$20,'5年目 損益資金計画'!$F$20) -> 0 | G20: =CHOOSE($U$2,'初年度 損益資金計画'!$G$20,'2年目 損益資金計画'!$G$20,'3年目 損益資金計画'!$G$20,'4年目 損益資金計画'!$G$20,'5年目 損益資金計画'!$G$20) -> 0 | H20: =CHOOSE($U$2,'初年度 損益資金計画'!$H$20,'2年目 損益資金計画'!$H$20,'3年目 損益資金計画'!$H$20,'4年目 損益資金計画'!$H$20,'5年目 損益資金計画'!$H$20) -> 0 | I20: =CHOOSE($U$2,'初年度 損益資金計画'!$I$20,'2年目 損益資金計画'!$I$20,'3年目 損益資金計画'!$I$20,'4年目 損益資金計画'!$I$20,'5年目 損益資金計画'!$I$20) -> 0 | J20: =CHOOSE($U$2,'初年度 損益資金計画'!$J$20,'2年目 損益資金計画'!$J$20,'3年目 損益資金計画'!$J$20,'4年目 損益資金計画'!$J$20,'5年目 損益資金計画'!$J$20) -> 0 | K20: =CHOOSE($U$2,'初年度 損益資金計画'!$K$20,'2年目 損益資金計画'!$K$20,'3年目 損益資金計画'!$K$20,'4年目 損益資金計画'!$K$20,'5年目 損益資金計画'!$K$20) -> 0 | L20: =CHOOSE($U$2,'初年度 損益資金計画'!$L$20,'2年目 損益資金計画'!$L$20,'3年目 損益資金計画'!$L$20,'4年目 損益資金計画'!$L$20,'5年目 損益資金計画'!$L$20) -> 0 | M20: =CHOOSE($U$2,'初年度 損益資金計画'!$M$20,'2年目 損益資金計画'!$M$20,'3年目 損益資金計画'!$M$20,'4年目 損益資金計画'!$M$20,'5年目 損益資金計画'!$M$20) -> 0 | N20: =CHOOSE($U$2,'初年度 損益資金計画'!$N$20,'2年目 損益資金計画'!$N$20,'3年目 損益資金計画'!$N$20,'4年目 損益資金計画'!$N$20,'5年目 損益資金計画'!$N$20) -> 0 | O20: =CHOOSE($U$2,'初年度 損益資金計画'!$O$20,'2年目 損益資金計画'!$O$20,'3年目 損益資金計画'!$O$20,'4年目 損益資金計画'!$O$20,'5年目 損益資金計画'!$O$20) -> 0 | P20: =CHOOSE($U$2,'初年度 損益資金計画'!$P$20,'2年目 損益資金計画'!$P$20,'3年目 損益資金計画'!$P$20,'4年目 損益資金計画'!$P$20,'5年目 損益資金計画'!$P$20) -> 0
A21: =CHOOSE($U$2,'初年度 損益資金計画'!$A$21,'2年目 損益資金計画'!$A$21,'3年目 損益資金計画'!$A$21,'4年目 損益資金計画'!$A$21,'5年目 損益資金計画'!$A$21) -> 0 | B21: =CHOOSE($U$2,'初年度 損益資金計画'!$B$21,'2年目 損益資金計画'!$B$21,'3年目 損益資金計画'!$B$21,'4年目 損益資金計画'!$B$21,'5年目 損益資金計画'!$B$21) -> 福祉的就労 | D21: =CHOOSE($U$2,'初年度 損益資金計画'!$D$21,'2年目 損益資金計画'!$D$21,'3年目 損益資金計画'!$D$21,'4年目 損益資金計画'!$D$21,'5年目 損益資金計画'!$D$21) -> 500000 | E21: =CHOOSE($U$2,'初年度 損益資金計画'!$E$21,'2年目 損益資金計画'!$E$21,'3年目 損益資金計画'!$E$21,'4年目 損益資金計画'!$E$21,'5年目 損益資金計画'!$E$21) -> 500000 | F21: =CHOOSE($U$2,'初年度 損益資金計画'!$F$21,'2年目 損益資金計画'!$F$21,'3年目 損益資金計画'!$F$21,'4年目 損益資金計画'!$F$21,'5年目 損益資金計画'!$F$21) -> 500000 | G21: =CHOOSE($U$2,'初年度 損益資金計画'!$G$21,'2年目 損益資金計画'!$G$21,'3年目 損益資金計画'!$G$21,'4年目 損益資金計画'!$G$21,'5年目 損益資金計画'!$G$21) -> 500000 | H21: =CHOOSE($U$2,'初年度 損益資金計画'!$H$21,'2年目 損益資金計画'!$H$21,'3年目 損益資金計画'!$H$21,'4年目 損益資金計画'!$H$21,'5年目 損益資金計画'!$H$21) -> 500000 | I21: =CHOOSE($U$2,'初年度 損益資金計画'!$I$21,'2年目 損益資金計画'!$I$21,'3年目 損益資金計画'!$I$21,'4年目 損益資金計画'!$I$21,'5年目 損益資金計画'!$I$21) -> 500000 | J21: =CHOOSE($U$2,'初年度 損益資金計画'!$J$21,'2年目 損益資金計画'!$J$21,'3年目 損益資金計画'!$J$21,'4年目 損益資金計画'!$J$21,'5年目 損益資金計画'!$J$21) -> 500000 | K21: =CHOOSE($U$2,'初年度 損益資金計画'!$K$21,'2年目 損益資金計画'!$K$21,'3年目 損益資金計画'!$K$21,'4年目 損益資金計画'!$K$21,'5年目 損益資金計画'!$K$21) -> 500000 | L21: =CHOOSE($U$2,'初年度 損益資金計画'!$L$21,'2年目 損益資金計画'!$L$21,'3年目 損益資金計画'!$L$21,'4年目 損益資金計画'!$L$21,'5年目 損益資金計画'!$L$21) -> 500000 | M21: =CHOOSE($U$2,'初年度 損益資金計画'!$M$21,'2年目 損益資金計画'!$M$21,'3年目 損益資金計画'!$M$21,'4年目 損益資金計画'!$M$21,'5年目 損益資金計画'!$M$21) -> 500000 | N21: =CHOOSE($U$2,'初年度 損益資金計画'!$N$21,'2年目 損益資金計画'!$N$21,'3年目 損益資金計画'!$N$21,'4年目 損益資金計画'!$N$21,'5年目 損益資金計画'!$N$21) -> 500000 | O21: =CHOOSE($U$2,'初年度 損益資金計画'!$O$21,'2年目 損益資金計画'!$O$21,'3年目 損益資金計画'!$O$21,'4年目 損益資金計画'!$O$21,'5年目 損益資金計画'!$O$21) -> 500000 | P21: =CHOOSE($U$2,'初年度 損益資金計画'!$P$21,'2年目 損益資金計画'!$P$21,'3年目 損益資金計画'!$P$21,'4年目 損益資金計画'!$P$21,'5年目 損益資金計画'!$P$21) -> 6000000
A22: =CHOOSE($U$2,'初年度 損益資金計画'!$A$22,'2年目 損益資金計画'!$A$22,'3年目 損益資金計画'!$A$22,'4年目 損益資金計画'!$A$22,'5年目 損益資金計画'!$A$22) -> 0 | B22: =CHOOSE($U$2,'初年度 損益資金計画'!$B$22,'2年目 損益資金計画'!$B$22,'3年目 損益資金計画'!$B$22,'4年目 損益資金計画'!$B$22,'5年目 損益資金計画'!$B$22) -> 0 | C22: =CHOOSE($U$2,'初年度 損益資金計画'!$C$22,'2年目 損益資金計画'!$C$22,'3年目 損益資金計画'!$C$22,'4年目 損益資金計画'!$C$22,'5年目 損益資金計画'!$C$22) -> 工賃 | D22: =CHOOSE($U$2,'初年度 損益資金計画'!$D$22,'2年目 損益資金計画'!$D$22,'3年目 損益資金計画'!$D$22,'4年目 損益資金計画'!$D$22,'5年目 損益資金計画'!$D$22) -> 500000 | E22: =CHOOSE($U$2,'初年度 損益資金計画'!$E$22,'2年目 損益資金計画'!$E$22,'3年目 損益資金計画'!$E$22,'4年目 損益資金計画'!$E$22,'5年目 損益資金計画'!$E$22) -> 500000 | F22: =CHOOSE($U$2,'初年度 損益資金計画'!$F$22,'2年目 損益資金計画'!$F$22,'3年目 損益資金計画'!$F$22,'4年目 損益資金計画'!$F$22,'5年目 損益資金計画'!$F$22) -> 500000 | G22: =CHOOSE($U$2,'初年度 損益資金計画'!$G$22,'2年目 損益資金計画'!$G$22,'3年目 損益資金計画'!$G$22,'4年目 損益資金計画'!$G$22,'5年目 損益資金計画'!$G$22) -> 500000 | H22: =CHOOSE($U$2,'初年度 損益資金計画'!$H$22,'2年目 損益資金計画'!$H$22,'3年目 損益資金計画'!$H$22,'4年目 損益資金計画'!$H$22,'5年目 損益資金計画'!$H$22) -> 500000 | I22: =CHOOSE($U$2,'初年度 損益資金計画'!$I$22,'2年目 損益資金計画'!$I$22,'3年目 損益資金計画'!$I$22,'4年目 損益資金計画'!$I$22,'5年目 損益資金計画'!$I$22) -> 500000 | J22: =CHOOSE($U$2,'初年度 損益資金計画'!$J$22,'2年目 損益資金計画'!$J$22,'3年目 損益資金計画'!$J$22,'4年目 損益資金計画'!$J$22,'5年目 損益資金計画'!$J$22) -> 500000 | K22: =CHOOSE($U$2,'初年度 損益資金計画'!$K$22,'2年目 損益資金計画'!$K$22,'3年目 損益資金計画'!$K$22,'4年目 損益資金計画'!$K$22,'5年目 損益資金計画'!$K$22) -> 500000 | L22: =CHOOSE($U$2,'初年度 損益資金計画'!$L$22,'2年目 損益資金計画'!$L$22,'3年目 損益資金計画'!$L$22,'4年目 損益資金計画'!$L$22,'5年目 損益資金計画'!$L$22) -> 500000 | M22: =CHOOSE($U$2,'初年度 損益資金計画'!$M$22,'2年目 損益資金計画'!$M$22,'3年目 損益資金計画'!$M$22,'4年目 損益資金計画'!$M$22,'5年目 損益資金計画'!$M$22) -> 500000 | N22: =CHOOSE($U$2,'初年度 損益資金計画'!$N$22,'2年目 損益資金計画'!$N$22,'3年目 損益資金計画'!$N$22,'4年目 損益資金計画'!$N$22,'5年目 損益資金計画'!$N$22) -> 500000 | O22: =CHOOSE($U$2,'初年度 損益資金計画'!$O$22,'2年目 損益資金計画'!$O$22,'3年目 損益資金計画'!$O$22,'4年目 損益資金計画'!$O$22,'5年目 損益資金計画'!$O$22) -> 500000 | P22: =CHOOSE($U$2,'初年度 損益資金計画'!$P$22,'2年目 損益資金計画'!$P$22,'3年目 損益資金計画'!$P$22,'4年目 損益資金計画'!$P$22,'5年目 損益資金計画'!$P$22) -> 6000000
A23: =CHOOSE($U$2,'初年度 損益資金計画'!$A$23,'2年目 損益資金計画'!$A$23,'3年目 損益資金計画'!$A$23,'4年目 損益資金計画'!$A$23,'5年目 損益資金計画'!$A$23) -> 0 | C23: =CHOOSE($U$2,'初年度 損益資金計画'!$C$23,'2年目 損益資金計画'!$C$23,'3年目 損益資金計画'!$C$23,'4年目 損益資金計画'!$C$23,'5年目 損益資金計画'!$C$23) -> 材料経費 | D23: =CHOOSE($U$2,'初年度 損益資金計画'!$D$23,'2年目 損益資金計画'!$D$23,'3年目 損益資金計画'!$D$23,'4年目 損益資金計画'!$D$23,'5年目 損益資金計画'!$D$23) -> 0 | E23: =CHOOSE($U$2,'初年度 損益資金計画'!$E$23,'2年目 損益資金計画'!$E$23,'3年目 損益資金計画'!$E$23,'4年目 損益資金計画'!$E$23,'5年目 損益資金計画'!$E$23) -> 0 | F23: =CHOOSE($U$2,'初年度 損益資金計画'!$F$23,'2年目 損益資金計画'!$F$23,'3年目 損益資金計画'!$F$23,'4年目 損益資金計画'!$F$23,'5年目 損益資金計画'!$F$23) -> 0 | G23: =CHOOSE($U$2,'初年度 損益資金計画'!$G$23,'2年目 損益資金計画'!$G$23,'3年目 損益資金計画'!$G$23,'4年目 損益資金計画'!$G$23,'5年目 損益資金計画'!$G$23) -> 0 | H23: =CHOOSE($U$2,'初年度 損益資金計画'!$H$23,'2年目 損益資金計画'!$H$23,'3年目 損益資金計画'!$H$23,'4年目 損益資金計画'!$H$23,'5年目 損益資金計画'!$H$23) -> 0 | I23: =CHOOSE($U$2,'初年度 損益資金計画'!$I$23,'2年目 損益資金計画'!$I$23,'3年目 損益資金計画'!$I$23,'4年目 損益資金計画'!$I$23,'5年目 損益資金計画'!$I$23) -> 0 | J23: =CHOOSE($U$2,'初年度 損益資金計画'!$J$23,'2年目 損益資金計画'!$J$23,'3年目 損益資金計画'!$J$23,'4年目 損益資金計画'!$J$23,'5年目 損益資金計画'!$J$23) -> 0 | K23: =CHOOSE($U$2,'初年度 損益資金計画'!$K$23,'2年目 損益資金計画'!$K$23,'3年目 損益資金計画'!$K$23,'4年目 損益資金計画'!$K$23,'5年目 損益資金計画'!$K$23) -> 0 | L23: =CHOOSE($U$2,'初年度 損益資金計画'!$L$23,'2年目 損益資金計画'!$L$23,'3年目 損益資金計画'!$L$23,'4年目 損益資金計画'!$L$23,'5年目 損益資金計画'!$L$23) -> 0 | M23: =CHOOSE($U$2,'初年度 損益資金計画'!$M$23,'2年目 損益資金計画'!$M$23,'3年目 損益資金計画'!$M$23,'4年目 損益資金計画'!$M$23,'5年目 損益資金計画'!$M$23) -> 0 | N23: =CHOOSE($U$2,'初年度 損益資金計画'!$N$23,'2年目 損益資金計画'!$N$23,'3年目 損益資金計画'!$N$23,'4年目 損益資金計画'!$N$23,'5年目 損益資金計画'!$N$23) -> 0 | O23: =CHOOSE($U$2,'初年度 損益資金計画'!$O$23,'2年目 損益資金計画'!$O$23,'3年目 損益資金計画'!$O$23,'4年目 損益資金計画'!$O$23,'5年目 損益資金計画'!$O$23) -> 0 | P23: =CHOOSE($U$2,'初年度 損益資金計画'!$P$23,'2年目 損益資金計画'!$P$23,'3年目 損益資金計画'!$P$23,'4年目 損益資金計画'!$P$23,'5年目 損益資金計画'!$P$23) -> 0
A24: =CHOOSE($U$2,'初年度 損益資金計画'!$A$24,'2年目 損益資金計画'!$A$24,'3年目 損益資金計画'!$A$24,'4年目 損益資金計画'!$A$24,'5年目 損益資金計画'!$A$24) -> 0 | C24: =CHOOSE($U$2,'初年度 損益資金計画'!$C$24,'2年目 損益資金計画'!$C$24,'3年目 損益資金計画'!$C$24,'4年目 損益資金計画'!$C$24,'5年目 損益資金計画'!$C$24) -> 投資的費用 | D24: =CHOOSE($U$2,'初年度 損益資金計画'!$D$24,'2年目 損益資金計画'!$D$24,'3年目 損益資金計画'!$D$24,'4年目 損益資金計画'!$D$24,'5年目 損益資金計画'!$D$24) -> 0 | E24: =CHOOSE($U$2,'初年度 損益資金計画'!$E$24,'2年目 損益資金計画'!$E$24,'3年目 損益資金計画'!$E$24,'4年目 損益資金計画'!$E$24,'5年目 損益資金計画'!$E$24) -> 0 | F24: =CHOOSE($U$2,'初年度 損益資金計画'!$F$24,'2年目 損益資金計画'!$F$24,'3年目 損益資金計画'!$F$24,'4年目 損益資金計画'!$F$24,'5年目 損益資金計画'!$F$24) -> 0 | G24: =CHOOSE($U$2,'初年度 損益資金計画'!$G$24,'2年目 損益資金計画'!$G$24,'3年目 損益資金計画'!$G$24,'4年目 損益資金計画'!$G$24,'5年目 損益資金計画'!$G$24) -> 0 | H24: =CHOOSE($U$2,'初年度 損益資金計画'!$H$24,'2年目 損益資金計画'!$H$24,'3年目 損益資金計画'!$H$24,'4年目 損益資金計画'!$H$24,'5年目 損益資金計画'!$H$24) -> 0 | I24: =CHOOSE($U$2,'初年度 損益資金計画'!$I$24,'2年目 損益資金計画'!$I$24,'3年目 損益資金計画'!$I$24,'4年目 損益資金計画'!$I$24,'5年目 損益資金計画'!$I$24) -> 0 | J24: =CHOOSE($U$2,'初年度 損益資金計画'!$J$24,'2年目 損益資金計画'!$J$24,'3年目 損益資金計画'!$J$24,'4年目 損益資金計画'!$J$24,'5年目 損益資金計画'!$J$24) -> 0 | K24: =CHOOSE($U$2,'初年度 損益資金計画'!$K$24,'2年目 損益資金計画'!$K$24,'3年目 損益資金計画'!$K$24,'4年目 損益資金計画'!$K$24,'5年目 損益資金計画'!$K$24) -> 0 | L24: =CHOOSE($U$2,'初年度 損益資金計画'!$L$24,'2年目 損益資金計画'!$L$24,'3年目 損益資金計画'!$L$24,'4年目 損益資金計画'!$L$24,'5年目 損益資金計画'!$L$24) -> 0 | M24: =CHOOSE($U$2,'初年度 損益資金計画'!$M$24,'2年目 損益資金計画'!$M$24,'3年目 損益資金計画'!$M$24,'4年目 損益資金計画'!$M$24,'5年目 損益資金計画'!$M$24) -> 0 | N24: =CHOOSE($U$2,'初年度 損益資金計画'!$N$24,'2年目 損益資金計画'!$N$24,'3年目 損益資金計画'!$N$24,'4年目 損益資金計画'!$N$24,'5年目 損益資金計画'!$N$24) -> 0 | O24: =CHOOSE($U$2,'初年度 損益資金計画'!$O$24,'2年目 損益資金計画'!$O$24,'3年目 損益資金計画'!$O$24,'4年目 損益資金計画'!$O$24,'5年目 損益資金計画'!$O$24) -> 0 | P24: =CHOOSE($U$2,'初年度 損益資金計画'!$P$24,'2年目 損益資金計画'!$P$24,'3年目 損益資金計画'!$P$24,'4年目 損益資金計画'!$P$24,'5年目 損益資金計画'!$P$24) -> 0
A25: =CHOOSE($U$2,'初年度 損益資金計画'!$A$25,'2年目 損益資金計画'!$A$25,'3年目 損益資金計画'!$A$25,'4年目 損益資金計画'!$A$25,'5年目 損益資金計画'!$A$25) -> 0 | C25: =CHOOSE($U$2,'初年度 損益資金計画'!$C$25,'2年目 損益資金計画'!$C$25,'3年目 損益資金計画'!$C$25,'4年目 損益資金計画'!$C$25,'5年目 損益資金計画'!$C$25) -> 0 | D25: =CHOOSE($U$2,'初年度 損益資金計画'!$D$25,'2年目 損益資金計画'!$D$25,'3年目 損益資金計画'!$D$25,'4年目 損益資金計画'!$D$25,'5年目 損益資金計画'!$D$25) -> 0 | E25: =CHOOSE($U$2,'初年度 損益資金計画'!$E$25,'2年目 損益資金計画'!$E$25,'3年目 損益資金計画'!$E$25,'4年目 損益資金計画'!$E$25,'5年目 損益資金計画'!$E$25) -> 0 | F25: =CHOOSE($U$2,'初年度 損益資金計画'!$F$25,'2年目 損益資金計画'!$F$25,'3年目 損益資金計画'!$F$25,'4年目 損益資金計画'!$F$25,'5年目 損益資金計画'!$F$25) -> 0 | G25: =CHOOSE($U$2,'初年度 損益資金計画'!$G$25,'2年目 損益資金計画'!$G$25,'3年目 損益資金計画'!$G$25,'4年目 損益資金計画'!$G$25,'5年目 損益資金計画'!$G$25) -> 0 | H25: =CHOOSE($U$2,'初年度 損益資金計画'!$H$25,'2年目 損益資金計画'!$H$25,'3年目 損益資金計画'!$H$25,'4年目 損益資金計画'!$H$25,'5年目 損益資金計画'!$H$25) -> 0 | I25: =CHOOSE($U$2,'初年度 損益資金計画'!$I$25,'2年目 損益資金計画'!$I$25,'3年目 損益資金計画'!$I$25,'4年目 損益資金計画'!$I$25,'5年目 損益資金計画'!$I$25) -> 0 | J25: =CHOOSE($U$2,'初年度 損益資金計画'!$J$25,'2年目 損益資金計画'!$J$25,'3年目 損益資金計画'!$J$25,'4年目 損益資金計画'!$J$25,'5年目 損益資金計画'!$J$25) -> 0 | K25: =CHOOSE($U$2,'初年度 損益資金計画'!$K$25,'2年目 損益資金計画'!$K$25,'3年目 損益資金計画'!$K$25,'4年目 損益資金計画'!$K$25,'5年目 損益資金計画'!$K$25) -> 0 | L25: =CHOOSE($U$2,'初年度 損益資金計画'!$L$25,'2年目 損益資金計画'!$L$25,'3年目 損益資金計画'!$L$25,'4年目 損益資金計画'!$L$25,'5年目 損益資金計画'!$L$25) -> 0 | M25: =CHOOSE($U$2,'初年度 損益資金計画'!$M$25,'2年目 損益資金計画'!$M$25,'3年目 損益資金計画'!$M$25,'4年目 損益資金計画'!$M$25,'5年目 損益資金計画'!$M$25) -> 0 | N25: =CHOOSE($U$2,'初年度 損益資金計画'!$N$25,'2年目 損益資金計画'!$N$25,'3年目 損益資金計画'!$N$25,'4年目 損益資金計画'!$N$25,'5年目 損益資金計画'!$N$25) -> 0 | O25: =CHOOSE($U$2,'初年度 損益資金計画'!$O$25,'2年目 損益資金計画'!$O$25,'3年目 損益資金計画'!$O$25,'4年目 損益資金計画'!$O$25,'5年目 損益資金計画'!$O$25) -> 0 | P25: =CHOOSE($U$2,'初年度 損益資金計画'!$P$25,'2年目 損益資金計画'!$P$25,'3年目 損益資金計画'!$P$25,'4年目 損益資金計画'!$P$25,'5年目 損益資金計画'!$P$25) -> 0
A26: =CHOOSE($U$2,'初年度 損益資金計画'!$A$26,'2年目 損益資金計画'!$A$26,'3年目 損益資金計画'!$A$26,'4年目 損益資金計画'!$A$26,'5年目 損益資金計画'!$A$26) -> （売上総利益） | D26: =CHOOSE($U$2,'初年度 損益資金計画'!$D$26,'2年目 損益資金計画'!$D$26,'3年目 損益資金計画'!$D$26,'4年目 損益資金計画'!$D$26,'5年目 損益資金計画'!$D$26) -> 44570 | E26: =CHOOSE($U$2,'初年度 損益資金計画'!$E$26,'2年目 損益資金計画'!$E$26,'3年目 損益資金計画'!$E$26,'4年目 損益資金計画'!$E$26,'5年目 損益資金計画'!$E$26) -> 1005970 | F26: =CHOOSE($U$2,'初年度 損益資金計画'!$F$26,'2年目 損益資金計画'!$F$26,'3年目 損益資金計画'!$F$26,'4年目 損益資金計画'!$F$26,'5年目 損益資金計画'!$F$26) -> 1453470 | G26: =CHOOSE($U$2,'初年度 損益資金計画'!$G$26,'2年目 損益資金計画'!$G$26,'3年目 損益資金計画'!$G$26,'4年目 損益資金計画'!$G$26,'5年目 損益資金計画'!$G$26) -> 1495370 | H26: =CHOOSE($U$2,'初年度 損益資金計画'!$H$26,'2年目 損益資金計画'!$H$26,'3年目 損益資金計画'!$H$26,'4年目 損益資金計画'!$H$26,'5年目 損益資金計画'!$H$26) -> 1803070 | I26: =CHOOSE($U$2,'初年度 損益資金計画'!$I$26,'2年目 損益資金計画'!$I$26,'3年目 損益資金計画'!$I$26,'4年目 損益資金計画'!$I$26,'5年目 損益資金計画'!$I$26) -> 2082670 | J26: =CHOOSE($U$2,'初年度 損益資金計画'!$J$26,'2年目 損益資金計画'!$J$26,'3年目 損益資金計画'!$J$26,'4年目 損益資金計画'!$J$26,'5年目 損益資金計画'!$J$26) -> 2229570 | K26: =CHOOSE($U$2,'初年度 損益資金計画'!$K$26,'2年目 損益資金計画'!$K$26,'3年目 損益資金計画'!$K$26,'4年目 損益資金計画'!$K$26,'5年目 損益資金計画'!$K$26) -> 2376370 | L26: =CHOOSE($U$2,'初年度 損益資金計画'!$L$26,'2年目 損益資金計画'!$L$26,'3年目 損益資金計画'!$L$26,'4年目 損益資金計画'!$L$26,'5年目 損益資金計画'!$L$26) -> 1297470 | M26: =CHOOSE($U$2,'初年度 損益資金計画'!$M$26,'2年目 損益資金計画'!$M$26,'3年目 損益資金計画'!$M$26,'4年目 損益資金計画'!$M$26,'5年目 損益資金計画'!$M$26) -> 2166570 | N26: =CHOOSE($U$2,'初年度 損益資金計画'!$N$26,'2年目 損益資金計画'!$N$26,'3年目 損益資金計画'!$N$26,'4年目 損益資金計画'!$N$26,'5年目 損益資金計画'!$N$26) -> 2642170 | O26: =CHOOSE($U$2,'初年度 損益資金計画'!$O$26,'2年目 損益資金計画'!$O$26,'3年目 損益資金計画'!$O$26,'4年目 損益資金計画'!$O$26,'5年目 損益資金計画'!$O$26) -> 3327270 | P26: =CHOOSE($U$2,'初年度 損益資金計画'!$P$26,'2年目 損益資金計画'!$P$26,'3年目 損益資金計画'!$P$26,'4年目 損益資金計画'!$P$26,'5年目 損益資金計画'!$P$26) -> 21924540
A27: =CHOOSE($U$2,'初年度 損益資金計画'!$A$27,'2年目 損益資金計画'!$A$27,'3年目 損益資金計画'!$A$27,'4年目 損益資金計画'!$A$27,'5年目 損益資金計画'!$A$27) -> （販管費） | D27: =CHOOSE($U$2,'初年度 損益資金計画'!$D$27,'2年目 損益資金計画'!$D$27,'3年目 損益資金計画'!$D$27,'4年目 損益資金計画'!$D$27,'5年目 損益資金計画'!$D$27) -> 296100 | E27: =CHOOSE($U$2,'初年度 損益資金計画'!$E$27,'2年目 損益資金計画'!$E$27,'3年目 損益資金計画'!$E$27,'4年目 損益資金計画'!$E$27,'5年目 損益資金計画'!$E$27) -> 296100 | F27: =CHOOSE($U$2,'初年度 損益資金計画'!$F$27,'2年目 損益資金計画'!$F$27,'3年目 損益資金計画'!$F$27,'4年目 損益資金計画'!$F$27,'5年目 損益資金計画'!$F$27) -> 296100 | G27: =CHOOSE($U$2,'初年度 損益資金計画'!$G$27,'2年目 損益資金計画'!$G$27,'3年目 損益資金計画'!$G$27,'4年目 損益資金計画'!$G$27,'5年目 損益資金計画'!$G$27) -> 296100 | H27: =CHOOSE($U$2,'初年度 損益資金計画'!$H$27,'2年目 損益資金計画'!$H$27,'3年目 損益資金計画'!$H$27,'4年目 損益資金計画'!$H$27,'5年目 損益資金計画'!$H$27) -> 296100 | I27: =CHOOSE($U$2,'初年度 損益資金計画'!$I$27,'2年目 損益資金計画'!$I$27,'3年目 損益資金計画'!$I$27,'4年目 損益資金計画'!$I$27,'5年目 損益資金計画'!$I$27) -> 296100 | J27: =CHOOSE($U$2,'初年度 損益資金計画'!$J$27,'2年目 損益資金計画'!$J$27,'3年目 損益資金計画'!$J$27,'4年目 損益資金計画'!$J$27,'5年目 損益資金計画'!$J$27) -> 296100 | K27: =CHOOSE($U$2,'初年度 損益資金計画'!$K$27,'2年目 損益資金計画'!$K$27,'3年目 損益資金計画'!$K$27,'4年目 損益資金計画'!$K$27,'5年目 損益資金計画'!$K$27) -> 296100 | L27: =CHOOSE($U$2,'初年度 損益資金計画'!$L$27,'2年目 損益資金計画'!$L$27,'3年目 損益資金計画'!$L$27,'4年目 損益資金計画'!$L$27,'5年目 損益資金計画'!$L$27) -> 296100 | M27: =CHOOSE($U$2,'初年度 損益資金計画'!$M$27,'2年目 損益資金計画'!$M$27,'3年目 損益資金計画'!$M$27,'4年目 損益資金計画'!$M$27,'5年目 損益資金計画'!$M$27) -> 296100 | N27: =CHOOSE($U$2,'初年度 損益資金計画'!$N$27,'2年目 損益資金計画'!$N$27,'3年目 損益資金計画'!$N$27,'4年目 損益資金計画'!$N$27,'5年目 損益資金計画'!$N$27) -> 296100 | O27: =CHOOSE($U$2,'初年度 損益資金計画'!$O$27,'2年目 損益資金計画'!$O$27,'3年目 損益資金計画'!$O$27,'4年目 損益資金計画'!$O$27,'5年目 損益資金計画'!$O$27) -> 296100 | P27: =CHOOSE($U$2,'初年度 損益資金計画'!$P$27,'2年目 損益資金計画'!$P$27,'3年目 損益資金計画'!$P$27,'4年目 損益資金計画'!$P$27,'5年目 損益資金計画'!$P$27) -> 3553200
A28: =CHOOSE($U$2,'初年度 損益資金計画'!$A$28,'2年目 損益資金計画'!$A$28,'3年目 損益資金計画'!$A$28,'4年目 損益資金計画'!$A$28,'5年目 損益資金計画'!$A$28) -> 0 | C28: =CHOOSE($U$2,'初年度 損益資金計画'!$C$28,'2年目 損益資金計画'!$C$28,'3年目 損益資金計画'!$C$28,'4年目 損益資金計画'!$C$28,'5年目 損益資金計画'!$C$28) -> 役員報酬 | D28: =CHOOSE($U$2,'初年度 損益資金計画'!$D$28,'2年目 損益資金計画'!$D$28,'3年目 損益資金計画'!$D$28,'4年目 損益資金計画'!$D$28,'5年目 損益資金計画'!$D$28) -> 180000 | E28: =CHOOSE($U$2,'初年度 損益資金計画'!$E$28,'2年目 損益資金計画'!$E$28,'3年目 損益資金計画'!$E$28,'4年目 損益資金計画'!$E$28,'5年目 損益資金計画'!$E$28) -> 180000 | F28: =CHOOSE($U$2,'初年度 損益資金計画'!$F$28,'2年目 損益資金計画'!$F$28,'3年目 損益資金計画'!$F$28,'4年目 損益資金計画'!$F$28,'5年目 損益資金計画'!$F$28) -> 180000 | G28: =CHOOSE($U$2,'初年度 損益資金計画'!$G$28,'2年目 損益資金計画'!$G$28,'3年目 損益資金計画'!$G$28,'4年目 損益資金計画'!$G$28,'5年目 損益資金計画'!$G$28) -> 180000 | H28: =CHOOSE($U$2,'初年度 損益資金計画'!$H$28,'2年目 損益資金計画'!$H$28,'3年目 損益資金計画'!$H$28,'4年目 損益資金計画'!$H$28,'5年目 損益資金計画'!$H$28) -> 180000 | I28: =CHOOSE($U$2,'初年度 損益資金計画'!$I$28,'2年目 損益資金計画'!$I$28,'3年目 損益資金計画'!$I$28,'4年目 損益資金計画'!$I$28,'5年目 損益資金計画'!$I$28) -> 180000 | J28: =CHOOSE($U$2,'初年度 損益資金計画'!$J$28,'2年目 損益資金計画'!$J$28,'3年目 損益資金計画'!$J$28,'4年目 損益資金計画'!$J$28,'5年目 損益資金計画'!$J$28) -> 180000 | K28: =CHOOSE($U$2,'初年度 損益資金計画'!$K$28,'2年目 損益資金計画'!$K$28,'3年目 損益資金計画'!$K$28,'4年目 損益資金計画'!$K$28,'5年目 損益資金計画'!$K$28) -> 180000 | L28: =CHOOSE($U$2,'初年度 損益資金計画'!$L$28,'2年目 損益資金計画'!$L$28,'3年目 損益資金計画'!$L$28,'4年目 損益資金計画'!$L$28,'5年目 損益資金計画'!$L$28) -> 180000 | M28: =CHOOSE($U$2,'初年度 損益資金計画'!$M$28,'2年目 損益資金計画'!$M$28,'3年目 損益資金計画'!$M$28,'4年目 損益資金計画'!$M$28,'5年目 損益資金計画'!$M$28) -> 180000 | N28: =CHOOSE($U$2,'初年度 損益資金計画'!$N$28,'2年目 損益資金計画'!$N$28,'3年目 損益資金計画'!$N$28,'4年目 損益資金計画'!$N$28,'5年目 損益資金計画'!$N$28) -> 180000 | O28: =CHOOSE($U$2,'初年度 損益資金計画'!$O$28,'2年目 損益資金計画'!$O$28,'3年目 損益資金計画'!$O$28,'4年目 損益資金計画'!$O$28,'5年目 損益資金計画'!$O$28) -> 180000 | P28: =CHOOSE($U$2,'初年度 損益資金計画'!$P$28,'2年目 損益資金計画'!$P$28,'3年目 損益資金計画'!$P$28,'4年目 損益資金計画'!$P$28,'5年目 損益資金計画'!$P$28) -> 2160000
C29: =CHOOSE($U$2,'初年度 損益資金計画'!$C$29,'2年目 損益資金計画'!$C$29,'3年目 損益資金計画'!$C$29,'4年目 損益資金計画'!$C$29,'5年目 損益資金計画'!$C$29) -> 給料手当 | D29: =CHOOSE($U$2,'初年度 損益資金計画'!$D$29,'2年目 損益資金計画'!$D$29,'3年目 損益資金計画'!$D$29,'4年目 損益資金計画'!$D$29,'5年目 損益資金計画'!$D$29) -> 0 | E29: =CHOOSE($U$2,'初年度 損益資金計画'!$E$29,'2年目 損益資金計画'!$E$29,'3年目 損益資金計画'!$E$29,'4年目 損益資金計画'!$E$29,'5年目 損益資金計画'!$E$29) -> 0 | F29: =CHOOSE($U$2,'初年度 損益資金計画'!$F$29,'2年目 損益資金計画'!$F$29,'3年目 損益資金計画'!$F$29,'4年目 損益資金計画'!$F$29,'5年目 損益資金計画'!$F$29) -> 0 | G29: =CHOOSE($U$2,'初年度 損益資金計画'!$G$29,'2年目 損益資金計画'!$G$29,'3年目 損益資金計画'!$G$29,'4年目 損益資金計画'!$G$29,'5年目 損益資金計画'!$G$29) -> 0 | H29: =CHOOSE($U$2,'初年度 損益資金計画'!$H$29,'2年目 損益資金計画'!$H$29,'3年目 損益資金計画'!$H$29,'4年目 損益資金計画'!$H$29,'5年目 損益資金計画'!$H$29) -> 0 | I29: =CHOOSE($U$2,'初年度 損益資金計画'!$I$29,'2年目 損益資金計画'!$I$29,'3年目 損益資金計画'!$I$29,'4年目 損益資金計画'!$I$29,'5年目 損益資金計画'!$I$29) -> 0 | J29: =CHOOSE($U$2,'初年度 損益資金計画'!$J$29,'2年目 損益資金計画'!$J$29,'3年目 損益資金計画'!$J$29,'4年目 損益資金計画'!$J$29,'5年目 損益資金計画'!$J$29) -> 0 | K29: =CHOOSE($U$2,'初年度 損益資金計画'!$K$29,'2年目 損益資金計画'!$K$29,'3年目 損益資金計画'!$K$29,'4年目 損益資金計画'!$K$29,'5年目 損益資金計画'!$K$29) -> 0 | L29: =CHOOSE($U$2,'初年度 損益資金計画'!$L$29,'2年目 損益資金計画'!$L$29,'3年目 損益資金計画'!$L$29,'4年目 損益資金計画'!$L$29,'5年目 損益資金計画'!$L$29) -> 0 | M29: =CHOOSE($U$2,'初年度 損益資金計画'!$M$29,'2年目 損益資金計画'!$M$29,'3年目 損益資金計画'!$M$29,'4年目 損益資金計画'!$M$29,'5年目 損益資金計画'!$M$29) -> 0 | N29: =CHOOSE($U$2,'初年度 損益資金計画'!$N$29,'2年目 損益資金計画'!$N$29,'3年目 損益資金計画'!$N$29,'4年目 損益資金計画'!$N$29,'5年目 損益資金計画'!$N$29) -> 0 | O29: =CHOOSE($U$2,'初年度 損益資金計画'!$O$29,'2年目 損益資金計画'!$O$29,'3年目 損益資金計画'!$O$29,'4年目 損益資金計画'!$O$29,'5年目 損益資金計画'!$O$29) -> 0 | P29: =CHOOSE($U$2,'初年度 損益資金計画'!$P$29,'2年目 損益資金計画'!$P$29,'3年目 損益資金計画'!$P$29,'4年目 損益資金計画'!$P$29,'5年目 損益資金計画'!$P$29) -> 0
C30: =CHOOSE($U$2,'初年度 損益資金計画'!$C$30,'2年目 損益資金計画'!$C$30,'3年目 損益資金計画'!$C$30,'4年目 損益資金計画'!$C$30,'5年目 損益資金計画'!$C$30) -> 法定福利費 | D30: =CHOOSE($U$2,'初年度 損益資金計画'!$D$30,'2年目 損益資金計画'!$D$30,'3年目 損益資金計画'!$D$30,'4年目 損益資金計画'!$D$30,'5年目 損益資金計画'!$D$30) -> 26100 | E30: =CHOOSE($U$2,'初年度 損益資金計画'!$E$30,'2年目 損益資金計画'!$E$30,'3年目 損益資金計画'!$E$30,'4年目 損益資金計画'!$E$30,'5年目 損益資金計画'!$E$30) -> 26100 | F30: =CHOOSE($U$2,'初年度 損益資金計画'!$F$30,'2年目 損益資金計画'!$F$30,'3年目 損益資金計画'!$F$30,'4年目 損益資金計画'!$F$30,'5年目 損益資金計画'!$F$30) -> 26100 | G30: =CHOOSE($U$2,'初年度 損益資金計画'!$G$30,'2年目 損益資金計画'!$G$30,'3年目 損益資金計画'!$G$30,'4年目 損益資金計画'!$G$30,'5年目 損益資金計画'!$G$30) -> 26100 | H30: =CHOOSE($U$2,'初年度 損益資金計画'!$H$30,'2年目 損益資金計画'!$H$30,'3年目 損益資金計画'!$H$30,'4年目 損益資金計画'!$H$30,'5年目 損益資金計画'!$H$30) -> 26100 | I30: =CHOOSE($U$2,'初年度 損益資金計画'!$I$30,'2年目 損益資金計画'!$I$30,'3年目 損益資金計画'!$I$30,'4年目 損益資金計画'!$I$30,'5年目 損益資金計画'!$I$30) -> 26100 | J30: =CHOOSE($U$2,'初年度 損益資金計画'!$J$30,'2年目 損益資金計画'!$J$30,'3年目 損益資金計画'!$J$30,'4年目 損益資金計画'!$J$30,'5年目 損益資金計画'!$J$30) -> 26100 | K30: =CHOOSE($U$2,'初年度 損益資金計画'!$K$30,'2年目 損益資金計画'!$K$30,'3年目 損益資金計画'!$K$30,'4年目 損益資金計画'!$K$30,'5年目 損益資金計画'!$K$30) -> 26100 | L30: =CHOOSE($U$2,'初年度 損益資金計画'!$L$30,'2年目 損益資金計画'!$L$30,'3年目 損益資金計画'!$L$30,'4年目 損益資金計画'!$L$30,'5年目 損益資金計画'!$L$30) -> 26100 | M30: =CHOOSE($U$2,'初年度 損益資金計画'!$M$30,'2年目 損益資金計画'!$M$30,'3年目 損益資金計画'!$M$30,'4年目 損益資金計画'!$M$30,'5年目 損益資金計画'!$M$30) -> 26100 | N30: =CHOOSE($U$2,'初年度 損益資金計画'!$N$30,'2年目 損益資金計画'!$N$30,'3年目 損益資金計画'!$N$30,'4年目 損益資金計画'!$N$30,'5年目 損益資金計画'!$N$30) -> 26100 | O30: =CHOOSE($U$2,'初年度 損益資金計画'!$O$30,'2年目 損益資金計画'!$O$30,'3年目 損益資金計画'!$O$30,'4年目 損益資金計画'!$O$30,'5年目 損益資金計画'!$O$30) -> 26100 | P30: =CHOOSE($U$2,'初年度 損益資金計画'!$P$30,'2年目 損益資金計画'!$P$30,'3年目 損益資金計画'!$P$30,'4年目 損益資金計画'!$P$30,'5年目 損益資金計画'!$P$30) -> 313200
C31: =CHOOSE($U$2,'初年度 損益資金計画'!$C$31,'2年目 損益資金計画'!$C$31,'3年目 損益資金計画'!$C$31,'4年目 損益資金計画'!$C$31,'5年目 損益資金計画'!$C$31) -> 諸経費 | D31: =CHOOSE($U$2,'初年度 損益資金計画'!$D$31,'2年目 損益資金計画'!$D$31,'3年目 損益資金計画'!$D$31,'4年目 損益資金計画'!$D$31,'5年目 損益資金計画'!$D$31) -> 30000 | E31: =CHOOSE($U$2,'初年度 損益資金計画'!$E$31,'2年目 損益資金計画'!$E$31,'3年目 損益資金計画'!$E$31,'4年目 損益資金計画'!$E$31,'5年目 損益資金計画'!$E$31) -> 30000 | F31: =CHOOSE($U$2,'初年度 損益資金計画'!$F$31,'2年目 損益資金計画'!$F$31,'3年目 損益資金計画'!$F$31,'4年目 損益資金計画'!$F$31,'5年目 損益資金計画'!$F$31) -> 30000 | G31: =CHOOSE($U$2,'初年度 損益資金計画'!$G$31,'2年目 損益資金計画'!$G$31,'3年目 損益資金計画'!$G$31,'4年目 損益資金計画'!$G$31,'5年目 損益資金計画'!$G$31) -> 30000 | H31: =CHOOSE($U$2,'初年度 損益資金計画'!$H$31,'2年目 損益資金計画'!$H$31,'3年目 損益資金計画'!$H$31,'4年目 損益資金計画'!$H$31,'5年目 損益資金計画'!$H$31) -> 30000 | I31: =CHOOSE($U$2,'初年度 損益資金計画'!$I$31,'2年目 損益資金計画'!$I$31,'3年目 損益資金計画'!$I$31,'4年目 損益資金計画'!$I$31,'5年目 損益資金計画'!$I$31) -> 30000 | J31: =CHOOSE($U$2,'初年度 損益資金計画'!$J$31,'2年目 損益資金計画'!$J$31,'3年目 損益資金計画'!$J$31,'4年目 損益資金計画'!$J$31,'5年目 損益資金計画'!$J$31) -> 30000 | K31: =CHOOSE($U$2,'初年度 損益資金計画'!$K$31,'2年目 損益資金計画'!$K$31,'3年目 損益資金計画'!$K$31,'4年目 損益資金計画'!$K$31,'5年目 損益資金計画'!$K$31) -> 30000 | L31: =CHOOSE($U$2,'初年度 損益資金計画'!$L$31,'2年目 損益資金計画'!$L$31,'3年目 損益資金計画'!$L$31,'4年目 損益資金計画'!$L$31,'5年目 損益資金計画'!$L$31) -> 30000 | M31: =CHOOSE($U$2,'初年度 損益資金計画'!$M$31,'2年目 損益資金計画'!$M$31,'3年目 損益資金計画'!$M$31,'4年目 損益資金計画'!$M$31,'5年目 損益資金計画'!$M$31) -> 30000 | N31: =CHOOSE($U$2,'初年度 損益資金計画'!$N$31,'2年目 損益資金計画'!$N$31,'3年目 損益資金計画'!$N$31,'4年目 損益資金計画'!$N$31,'5年目 損益資金計画'!$N$31) -> 30000 | O31: =CHOOSE($U$2,'初年度 損益資金計画'!$O$31,'2年目 損益資金計画'!$O$31,'3年目 損益資金計画'!$O$31,'4年目 損益資金計画'!$O$31,'5年目 損益資金計画'!$O$31) -> 30000 | P31: =CHOOSE($U$2,'初年度 損益資金計画'!$P$31,'2年目 損益資金計画'!$P$31,'3年目 損益資金計画'!$P$31,'4年目 損益資金計画'!$P$31,'5年目 損益資金計画'!$P$31) -> 360000
C32: =CHOOSE($U$2,'初年度 損益資金計画'!$C$32,'2年目 損益資金計画'!$C$32,'3年目 損益資金計画'!$C$32,'4年目 損益資金計画'!$C$32,'5年目 損益資金計画'!$C$32) -> 本部管理費 | D32: =CHOOSE($U$2,'初年度 損益資金計画'!$D$32,'2年目 損益資金計画'!$D$32,'3年目 損益資金計画'!$D$32,'4年目 損益資金計画'!$D$32,'5年目 損益資金計画'!$D$32) -> 50000 | E32: =CHOOSE($U$2,'初年度 損益資金計画'!$E$32,'2年目 損益資金計画'!$E$32,'3年目 損益資金計画'!$E$32,'4年目 損益資金計画'!$E$32,'5年目 損益資金計画'!$E$32) -> 50000 | F32: =CHOOSE($U$2,'初年度 損益資金計画'!$F$32,'2年目 損益資金計画'!$F$32,'3年目 損益資金計画'!$F$32,'4年目 損益資金計画'!$F$32,'5年目 損益資金計画'!$F$32) -> 50000 | G32: =CHOOSE($U$2,'初年度 損益資金計画'!$G$32,'2年目 損益資金計画'!$G$32,'3年目 損益資金計画'!$G$32,'4年目 損益資金計画'!$G$32,'5年目 損益資金計画'!$G$32) -> 50000 | H32: =CHOOSE($U$2,'初年度 損益資金計画'!$H$32,'2年目 損益資金計画'!$H$32,'3年目 損益資金計画'!$H$32,'4年目 損益資金計画'!$H$32,'5年目 損益資金計画'!$H$32) -> 50000 | I32: =CHOOSE($U$2,'初年度 損益資金計画'!$I$32,'2年目 損益資金計画'!$I$32,'3年目 損益資金計画'!$I$32,'4年目 損益資金計画'!$I$32,'5年目 損益資金計画'!$I$32) -> 50000 | J32: =CHOOSE($U$2,'初年度 損益資金計画'!$J$32,'2年目 損益資金計画'!$J$32,'3年目 損益資金計画'!$J$32,'4年目 損益資金計画'!$J$32,'5年目 損益資金計画'!$J$32) -> 50000 | K32: =CHOOSE($U$2,'初年度 損益資金計画'!$K$32,'2年目 損益資金計画'!$K$32,'3年目 損益資金計画'!$K$32,'4年目 損益資金計画'!$K$32,'5年目 損益資金計画'!$K$32) -> 50000 | L32: =CHOOSE($U$2,'初年度 損益資金計画'!$L$32,'2年目 損益資金計画'!$L$32,'3年目 損益資金計画'!$L$32,'4年目 損益資金計画'!$L$32,'5年目 損益資金計画'!$L$32) -> 50000 | M32: =CHOOSE($U$2,'初年度 損益資金計画'!$M$32,'2年目 損益資金計画'!$M$32,'3年目 損益資金計画'!$M$32,'4年目 損益資金計画'!$M$32,'5年目 損益資金計画'!$M$32) -> 50000 | N32: =CHOOSE($U$2,'初年度 損益資金計画'!$N$32,'2年目 損益資金計画'!$N$32,'3年目 損益資金計画'!$N$32,'4年目 損益資金計画'!$N$32,'5年目 損益資金計画'!$N$32) -> 50000 | O32: =CHOOSE($U$2,'初年度 損益資金計画'!$O$32,'2年目 損益資金計画'!$O$32,'3年目 損益資金計画'!$O$32,'4年目 損益資金計画'!$O$32,'5年目 損益資金計画'!$O$32) -> 50000 | P32: =CHOOSE($U$2,'初年度 損益資金計画'!$P$32,'2年目 損益資金計画'!$P$32,'3年目 損益資金計画'!$P$32,'4年目 損益資金計画'!$P$32,'5年目 損益資金計画'!$P$32) -> 600000
C33: =CHOOSE($U$2,'初年度 損益資金計画'!$C$33,'2年目 損益資金計画'!$C$33,'3年目 損益資金計画'!$C$33,'4年目 損益資金計画'!$C$33,'5年目 損益資金計画'!$C$33) -> リース料 | D33: =CHOOSE($U$2,'初年度 損益資金計画'!$D$33,'2年目 損益資金計画'!$D$33,'3年目 損益資金計画'!$D$33,'4年目 損益資金計画'!$D$33,'5年目 損益資金計画'!$D$33) -> 0 | E33: =CHOOSE($U$2,'初年度 損益資金計画'!$E$33,'2年目 損益資金計画'!$E$33,'3年目 損益資金計画'!$E$33,'4年目 損益資金計画'!$E$33,'5年目 損益資金計画'!$E$33) -> 0 | F33: =CHOOSE($U$2,'初年度 損益資金計画'!$F$33,'2年目 損益資金計画'!$F$33,'3年目 損益資金計画'!$F$33,'4年目 損益資金計画'!$F$33,'5年目 損益資金計画'!$F$33) -> 0 | G33: =CHOOSE($U$2,'初年度 損益資金計画'!$G$33,'2年目 損益資金計画'!$G$33,'3年目 損益資金計画'!$G$33,'4年目 損益資金計画'!$G$33,'5年目 損益資金計画'!$G$33) -> 0 | H33: =CHOOSE($U$2,'初年度 損益資金計画'!$H$33,'2年目 損益資金計画'!$H$33,'3年目 損益資金計画'!$H$33,'4年目 損益資金計画'!$H$33,'5年目 損益資金計画'!$H$33) -> 0 | I33: =CHOOSE($U$2,'初年度 損益資金計画'!$I$33,'2年目 損益資金計画'!$I$33,'3年目 損益資金計画'!$I$33,'4年目 損益資金計画'!$I$33,'5年目 損益資金計画'!$I$33) -> 0 | J33: =CHOOSE($U$2,'初年度 損益資金計画'!$J$33,'2年目 損益資金計画'!$J$33,'3年目 損益資金計画'!$J$33,'4年目 損益資金計画'!$J$33,'5年目 損益資金計画'!$J$33) -> 0 | K33: =CHOOSE($U$2,'初年度 損益資金計画'!$K$33,'2年目 損益資金計画'!$K$33,'3年目 損益資金計画'!$K$33,'4年目 損益資金計画'!$K$33,'5年目 損益資金計画'!$K$33) -> 0 | L33: =CHOOSE($U$2,'初年度 損益資金計画'!$L$33,'2年目 損益資金計画'!$L$33,'3年目 損益資金計画'!$L$33,'4年目 損益資金計画'!$L$33,'5年目 損益資金計画'!$L$33) -> 0 | M33: =CHOOSE($U$2,'初年度 損益資金計画'!$M$33,'2年目 損益資金計画'!$M$33,'3年目 損益資金計画'!$M$33,'4年目 損益資金計画'!$M$33,'5年目 損益資金計画'!$M$33) -> 0 | N33: =CHOOSE($U$2,'初年度 損益資金計画'!$N$33,'2年目 損益資金計画'!$N$33,'3年目 損益資金計画'!$N$33,'4年目 損益資金計画'!$N$33,'5年目 損益資金計画'!$N$33) -> 0 | O33: =CHOOSE($U$2,'初年度 損益資金計画'!$O$33,'2年目 損益資金計画'!$O$33,'3年目 損益資金計画'!$O$33,'4年目 損益資金計画'!$O$33,'5年目 損益資金計画'!$O$33) -> 0 | P33: =CHOOSE($U$2,'初年度 損益資金計画'!$P$33,'2年目 損益資金計画'!$P$33,'3年目 損益資金計画'!$P$33,'4年目 損益資金計画'!$P$33,'5年目 損益資金計画'!$P$33) -> 0
C34: =CHOOSE($U$2,'初年度 損益資金計画'!$C$34,'2年目 損益資金計画'!$C$34,'3年目 損益資金計画'!$C$34,'4年目 損益資金計画'!$C$34,'5年目 損益資金計画'!$C$34) -> 地代家賃 | D34: =CHOOSE($U$2,'初年度 損益資金計画'!$D$34,'2年目 損益資金計画'!$D$34,'3年目 損益資金計画'!$D$34,'4年目 損益資金計画'!$D$34,'5年目 損益資金計画'!$D$34) -> 10000 | E34: =CHOOSE($U$2,'初年度 損益資金計画'!$E$34,'2年目 損益資金計画'!$E$34,'3年目 損益資金計画'!$E$34,'4年目 損益資金計画'!$E$34,'5年目 損益資金計画'!$E$34) -> 10000 | F34: =CHOOSE($U$2,'初年度 損益資金計画'!$F$34,'2年目 損益資金計画'!$F$34,'3年目 損益資金計画'!$F$34,'4年目 損益資金計画'!$F$34,'5年目 損益資金計画'!$F$34) -> 10000 | G34: =CHOOSE($U$2,'初年度 損益資金計画'!$G$34,'2年目 損益資金計画'!$G$34,'3年目 損益資金計画'!$G$34,'4年目 損益資金計画'!$G$34,'5年目 損益資金計画'!$G$34) -> 10000 | H34: =CHOOSE($U$2,'初年度 損益資金計画'!$H$34,'2年目 損益資金計画'!$H$34,'3年目 損益資金計画'!$H$34,'4年目 損益資金計画'!$H$34,'5年目 損益資金計画'!$H$34) -> 10000 | I34: =CHOOSE($U$2,'初年度 損益資金計画'!$I$34,'2年目 損益資金計画'!$I$34,'3年目 損益資金計画'!$I$34,'4年目 損益資金計画'!$I$34,'5年目 損益資金計画'!$I$34) -> 10000 | J34: =CHOOSE($U$2,'初年度 損益資金計画'!$J$34,'2年目 損益資金計画'!$J$34,'3年目 損益資金計画'!$J$34,'4年目 損益資金計画'!$J$34,'5年目 損益資金計画'!$J$34) -> 10000 | K34: =CHOOSE($U$2,'初年度 損益資金計画'!$K$34,'2年目 損益資金計画'!$K$34,'3年目 損益資金計画'!$K$34,'4年目 損益資金計画'!$K$34,'5年目 損益資金計画'!$K$34) -> 10000 | L34: =CHOOSE($U$2,'初年度 損益資金計画'!$L$34,'2年目 損益資金計画'!$L$34,'3年目 損益資金計画'!$L$34,'4年目 損益資金計画'!$L$34,'5年目 損益資金計画'!$L$34) -> 10000 | M34: =CHOOSE($U$2,'初年度 損益資金計画'!$M$34,'2年目 損益資金計画'!$M$34,'3年目 損益資金計画'!$M$34,'4年目 損益資金計画'!$M$34,'5年目 損益資金計画'!$M$34) -> 10000 | N34: =CHOOSE($U$2,'初年度 損益資金計画'!$N$34,'2年目 損益資金計画'!$N$34,'3年目 損益資金計画'!$N$34,'4年目 損益資金計画'!$N$34,'5年目 損益資金計画'!$N$34) -> 10000 | O34: =CHOOSE($U$2,'初年度 損益資金計画'!$O$34,'2年目 損益資金計画'!$O$34,'3年目 損益資金計画'!$O$34,'4年目 損益資金計画'!$O$34,'5年目 損益資金計画'!$O$34) -> 10000 | P34: =CHOOSE($U$2,'初年度 損益資金計画'!$P$34,'2年目 損益資金計画'!$P$34,'3年目 損益資金計画'!$P$34,'4年目 損益資金計画'!$P$34,'5年目 損益資金計画'!$P$34) -> 120000
C35: =CHOOSE($U$2,'初年度 損益資金計画'!$C$35,'2年目 損益資金計画'!$C$35,'3年目 損益資金計画'!$C$35,'4年目 損益資金計画'!$C$35,'5年目 損益資金計画'!$C$35) -> 減価償却 | D35: =CHOOSE($U$2,'初年度 損益資金計画'!$D$35,'2年目 損益資金計画'!$D$35,'3年目 損益資金計画'!$D$35,'4年目 損益資金計画'!$D$35,'5年目 損益資金計画'!$D$35) -> 0 | E35: =CHOOSE($U$2,'初年度 損益資金計画'!$E$35,'2年目 損益資金計画'!$E$35,'3年目 損益資金計画'!$E$35,'4年目 損益資金計画'!$E$35,'5年目 損益資金計画'!$E$35) -> 0 | F35: =CHOOSE($U$2,'初年度 損益資金計画'!$F$35,'2年目 損益資金計画'!$F$35,'3年目 損益資金計画'!$F$35,'4年目 損益資金計画'!$F$35,'5年目 損益資金計画'!$F$35) -> 0 | G35: =CHOOSE($U$2,'初年度 損益資金計画'!$G$35,'2年目 損益資金計画'!$G$35,'3年目 損益資金計画'!$G$35,'4年目 損益資金計画'!$G$35,'5年目 損益資金計画'!$G$35) -> 0 | H35: =CHOOSE($U$2,'初年度 損益資金計画'!$H$35,'2年目 損益資金計画'!$H$35,'3年目 損益資金計画'!$H$35,'4年目 損益資金計画'!$H$35,'5年目 損益資金計画'!$H$35) -> 0 | I35: =CHOOSE($U$2,'初年度 損益資金計画'!$I$35,'2年目 損益資金計画'!$I$35,'3年目 損益資金計画'!$I$35,'4年目 損益資金計画'!$I$35,'5年目 損益資金計画'!$I$35) -> 0 | J35: =CHOOSE($U$2,'初年度 損益資金計画'!$J$35,'2年目 損益資金計画'!$J$35,'3年目 損益資金計画'!$J$35,'4年目 損益資金計画'!$J$35,'5年目 損益資金計画'!$J$35) -> 0 | K35: =CHOOSE($U$2,'初年度 損益資金計画'!$K$35,'2年目 損益資金計画'!$K$35,'3年目 損益資金計画'!$K$35,'4年目 損益資金計画'!$K$35,'5年目 損益資金計画'!$K$35) -> 0 | L35: =CHOOSE($U$2,'初年度 損益資金計画'!$L$35,'2年目 損益資金計画'!$L$35,'3年目 損益資金計画'!$L$35,'4年目 損益資金計画'!$L$35,'5年目 損益資金計画'!$L$35) -> 0 | M35: =CHOOSE($U$2,'初年度 損益資金計画'!$M$35,'2年目 損益資金計画'!$M$35,'3年目 損益資金計画'!$M$35,'4年目 損益資金計画'!$M$35,'5年目 損益資金計画'!$M$35) -> 0 | N35: =CHOOSE($U$2,'初年度 損益資金計画'!$N$35,'2年目 損益資金計画'!$N$35,'3年目 損益資金計画'!$N$35,'4年目 損益資金計画'!$N$35,'5年目 損益資金計画'!$N$35) -> 0 | O35: =CHOOSE($U$2,'初年度 損益資金計画'!$O$35,'2年目 損益資金計画'!$O$35,'3年目 損益資金計画'!$O$35,'4年目 損益資金計画'!$O$35,'5年目 損益資金計画'!$O$35) -> 0 | P35: =CHOOSE($U$2,'初年度 損益資金計画'!$P$35,'2年目 損益資金計画'!$P$35,'3年目 損益資金計画'!$P$35,'4年目 損益資金計画'!$P$35,'5年目 損益資金計画'!$P$35) -> 0
A36: =CHOOSE($U$2,'初年度 損益資金計画'!$A$36,'2年目 損益資金計画'!$A$36,'3年目 損益資金計画'!$A$36,'4年目 損益資金計画'!$A$36,'5年目 損益資金計画'!$A$36) -> （営業利益） | D36: =CHOOSE($U$2,'初年度 損益資金計画'!$D$36,'2年目 損益資金計画'!$D$36,'3年目 損益資金計画'!$D$36,'4年目 損益資金計画'!$D$36,'5年目 損益資金計画'!$D$36) -> -251530 | E36: =CHOOSE($U$2,'初年度 損益資金計画'!$E$36,'2年目 損益資金計画'!$E$36,'3年目 損益資金計画'!$E$36,'4年目 損益資金計画'!$E$36,'5年目 損益資金計画'!$E$36) -> 709870 | F36: =CHOOSE($U$2,'初年度 損益資金計画'!$F$36,'2年目 損益資金計画'!$F$36,'3年目 損益資金計画'!$F$36,'4年目 損益資金計画'!$F$36,'5年目 損益資金計画'!$F$36) -> 1157370 | G36: =CHOOSE($U$2,'初年度 損益資金計画'!$G$36,'2年目 損益資金計画'!$G$36,'3年目 損益資金計画'!$G$36,'4年目 損益資金計画'!$G$36,'5年目 損益資金計画'!$G$36) -> 1199270 | H36: =CHOOSE($U$2,'初年度 損益資金計画'!$H$36,'2年目 損益資金計画'!$H$36,'3年目 損益資金計画'!$H$36,'4年目 損益資金計画'!$H$36,'5年目 損益資金計画'!$H$36) -> 1506970 | I36: =CHOOSE($U$2,'初年度 損益資金計画'!$I$36,'2年目 損益資金計画'!$I$36,'3年目 損益資金計画'!$I$36,'4年目 損益資金計画'!$I$36,'5年目 損益資金計画'!$I$36) -> 1786570 | J36: =CHOOSE($U$2,'初年度 損益資金計画'!$J$36,'2年目 損益資金計画'!$J$36,'3年目 損益資金計画'!$J$36,'4年目 損益資金計画'!$J$36,'5年目 損益資金計画'!$J$36) -> 1933470 | K36: =CHOOSE($U$2,'初年度 損益資金計画'!$K$36,'2年目 損益資金計画'!$K$36,'3年目 損益資金計画'!$K$36,'4年目 損益資金計画'!$K$36,'5年目 損益資金計画'!$K$36) -> 2080270 | L36: =CHOOSE($U$2,'初年度 損益資金計画'!$L$36,'2年目 損益資金計画'!$L$36,'3年目 損益資金計画'!$L$36,'4年目 損益資金計画'!$L$36,'5年目 損益資金計画'!$L$36) -> 1001370 | M36: =CHOOSE($U$2,'初年度 損益資金計画'!$M$36,'2年目 損益資金計画'!$M$36,'3年目 損益資金計画'!$M$36,'4年目 損益資金計画'!$M$36,'5年目 損益資金計画'!$M$36) -> 1870470 | N36: =CHOOSE($U$2,'初年度 損益資金計画'!$N$36,'2年目 損益資金計画'!$N$36,'3年目 損益資金計画'!$N$36,'4年目 損益資金計画'!$N$36,'5年目 損益資金計画'!$N$36) -> 2346070 | O36: =CHOOSE($U$2,'初年度 損益資金計画'!$O$36,'2年目 損益資金計画'!$O$36,'3年目 損益資金計画'!$O$36,'4年目 損益資金計画'!$O$36,'5年目 損益資金計画'!$O$36) -> 3031170 | P36: =CHOOSE($U$2,'初年度 損益資金計画'!$P$36,'2年目 損益資金計画'!$P$36,'3年目 損益資金計画'!$P$36,'4年目 損益資金計画'!$P$36,'5年目 損益資金計画'!$P$36) -> 18371340
A37: =CHOOSE($U$2,'初年度 損益資金計画'!$A$37,'2年目 損益資金計画'!$A$37,'3年目 損益資金計画'!$A$37,'4年目 損益資金計画'!$A$37,'5年目 損益資金計画'!$A$37) -> （営業外収益） | D37: =CHOOSE($U$2,'初年度 損益資金計画'!$D$37,'2年目 損益資金計画'!$D$37,'3年目 損益資金計画'!$D$37,'4年目 損益資金計画'!$D$37,'5年目 損益資金計画'!$D$37) -> 0 | E37: =CHOOSE($U$2,'初年度 損益資金計画'!$E$37,'2年目 損益資金計画'!$E$37,'3年目 損益資金計画'!$E$37,'4年目 損益資金計画'!$E$37,'5年目 損益資金計画'!$E$37) -> 0 | F37: =CHOOSE($U$2,'初年度 損益資金計画'!$F$37,'2年目 損益資金計画'!$F$37,'3年目 損益資金計画'!$F$37,'4年目 損益資金計画'!$F$37,'5年目 損益資金計画'!$F$37) -> 0 | G37: =CHOOSE($U$2,'初年度 損益資金計画'!$G$37,'2年目 損益資金計画'!$G$37,'3年目 損益資金計画'!$G$37,'4年目 損益資金計画'!$G$37,'5年目 損益資金計画'!$G$37) -> 0 | H37: =CHOOSE($U$2,'初年度 損益資金計画'!$H$37,'2年目 損益資金計画'!$H$37,'3年目 損益資金計画'!$H$37,'4年目 損益資金計画'!$H$37,'5年目 損益資金計画'!$H$37) -> 0 | I37: =CHOOSE($U$2,'初年度 損益資金計画'!$I$37,'2年目 損益資金計画'!$I$37,'3年目 損益資金計画'!$I$37,'4年目 損益資金計画'!$I$37,'5年目 損益資金計画'!$I$37) -> 0 | J37: =CHOOSE($U$2,'初年度 損益資金計画'!$J$37,'2年目 損益資金計画'!$J$37,'3年目 損益資金計画'!$J$37,'4年目 損益資金計画'!$J$37,'5年目 損益資金計画'!$J$37) -> 0 | K37: =CHOOSE($U$2,'初年度 損益資金計画'!$K$37,'2年目 損益資金計画'!$K$37,'3年目 損益資金計画'!$K$37,'4年目 損益資金計画'!$K$37,'5年目 損益資金計画'!$K$37) -> 0 | L37: =CHOOSE($U$2,'初年度 損益資金計画'!$L$37,'2年目 損益資金計画'!$L$37,'3年目 損益資金計画'!$L$37,'4年目 損益資金計画'!$L$37,'5年目 損益資金計画'!$L$37) -> 0 | M37: =CHOOSE($U$2,'初年度 損益資金計画'!$M$37,'2年目 損益資金計画'!$M$37,'3年目 損益資金計画'!$M$37,'4年目 損益資金計画'!$M$37,'5年目 損益資金計画'!$M$37) -> 0 | N37: =CHOOSE($U$2,'初年度 損益資金計画'!$N$37,'2年目 損益資金計画'!$N$37,'3年目 損益資金計画'!$N$37,'4年目 損益資金計画'!$N$37,'5年目 損益資金計画'!$N$37) -> 0 | O37: =CHOOSE($U$2,'初年度 損益資金計画'!$O$37,'2年目 損益資金計画'!$O$37,'3年目 損益資金計画'!$O$37,'4年目 損益資金計画'!$O$37,'5年目 損益資金計画'!$O$37) -> 0 | P37: =CHOOSE($U$2,'初年度 損益資金計画'!$P$37,'2年目 損益資金計画'!$P$37,'3年目 損益資金計画'!$P$37,'4年目 損益資金計画'!$P$37,'5年目 損益資金計画'!$P$37) -> 0
A38: =CHOOSE($U$2,'初年度 損益資金計画'!$A$38,'2年目 損益資金計画'!$A$38,'3年目 損益資金計画'!$A$38,'4年目 損益資金計画'!$A$38,'5年目 損益資金計画'!$A$38) -> （営業外損失） | D38: =CHOOSE($U$2,'初年度 損益資金計画'!$D$38,'2年目 損益資金計画'!$D$38,'3年目 損益資金計画'!$D$38,'4年目 損益資金計画'!$D$38,'5年目 損益資金計画'!$D$38) -> 0 | E38: =CHOOSE($U$2,'初年度 損益資金計画'!$E$38,'2年目 損益資金計画'!$E$38,'3年目 損益資金計画'!$E$38,'4年目 損益資金計画'!$E$38,'5年目 損益資金計画'!$E$38) -> 0 | F38: =CHOOSE($U$2,'初年度 損益資金計画'!$F$38,'2年目 損益資金計画'!$F$38,'3年目 損益資金計画'!$F$38,'4年目 損益資金計画'!$F$38,'5年目 損益資金計画'!$F$38) -> 0 | G38: =CHOOSE($U$2,'初年度 損益資金計画'!$G$38,'2年目 損益資金計画'!$G$38,'3年目 損益資金計画'!$G$38,'4年目 損益資金計画'!$G$38,'5年目 損益資金計画'!$G$38) -> 0 | H38: =CHOOSE($U$2,'初年度 損益資金計画'!$H$38,'2年目 損益資金計画'!$H$38,'3年目 損益資金計画'!$H$38,'4年目 損益資金計画'!$H$38,'5年目 損益資金計画'!$H$38) -> 0 | I38: =CHOOSE($U$2,'初年度 損益資金計画'!$I$38,'2年目 損益資金計画'!$I$38,'3年目 損益資金計画'!$I$38,'4年目 損益資金計画'!$I$38,'5年目 損益資金計画'!$I$38) -> 0 | J38: =CHOOSE($U$2,'初年度 損益資金計画'!$J$38,'2年目 損益資金計画'!$J$38,'3年目 損益資金計画'!$J$38,'4年目 損益資金計画'!$J$38,'5年目 損益資金計画'!$J$38) -> 0 | K38: =CHOOSE($U$2,'初年度 損益資金計画'!$K$38,'2年目 損益資金計画'!$K$38,'3年目 損益資金計画'!$K$38,'4年目 損益資金計画'!$K$38,'5年目 損益資金計画'!$K$38) -> 0 | L38: =CHOOSE($U$2,'初年度 損益資金計画'!$L$38,'2年目 損益資金計画'!$L$38,'3年目 損益資金計画'!$L$38,'4年目 損益資金計画'!$L$38,'5年目 損益資金計画'!$L$38) -> 0 | M38: =CHOOSE($U$2,'初年度 損益資金計画'!$M$38,'2年目 損益資金計画'!$M$38,'3年目 損益資金計画'!$M$38,'4年目 損益資金計画'!$M$38,'5年目 損益資金計画'!$M$38) -> 0 | N38: =CHOOSE($U$2,'初年度 損益資金計画'!$N$38,'2年目 損益資金計画'!$N$38,'3年目 損益資金計画'!$N$38,'4年目 損益資金計画'!$N$38,'5年目 損益資金計画'!$N$38) -> 0 | O38: =CHOOSE($U$2,'初年度 損益資金計画'!$O$38,'2年目 損益資金計画'!$O$38,'3年目 損益資金計画'!$O$38,'4年目 損益資金計画'!$O$38,'5年目 損益資金計画'!$O$38) -> 0 | P38: =CHOOSE($U$2,'初年度 損益資金計画'!$P$38,'2年目 損益資金計画'!$P$38,'3年目 損益資金計画'!$P$38,'4年目 損益資金計画'!$P$38,'5年目 損益資金計画'!$P$38) -> 0
A39: =CHOOSE($U$2,'初年度 損益資金計画'!$A$39,'2年目 損益資金計画'!$A$39,'3年目 損益資金計画'!$A$39,'4年目 損益資金計画'!$A$39,'5年目 損益資金計画'!$A$39) -> 0 | C39: =CHOOSE($U$2,'初年度 損益資金計画'!$C$39,'2年目 損益資金計画'!$C$39,'3年目 損益資金計画'!$C$39,'4年目 損益資金計画'!$C$39,'5年目 損益資金計画'!$C$39) -> 支払利息 | D39: =CHOOSE($U$2,'初年度 損益資金計画'!$D$39,'2年目 損益資金計画'!$D$39,'3年目 損益資金計画'!$D$39,'4年目 損益資金計画'!$D$39,'5年目 損益資金計画'!$D$39) -> 0 | E39: =CHOOSE($U$2,'初年度 損益資金計画'!$E$39,'2年目 損益資金計画'!$E$39,'3年目 損益資金計画'!$E$39,'4年目 損益資金計画'!$E$39,'5年目 損益資金計画'!$E$39) -> 0 | F39: =CHOOSE($U$2,'初年度 損益資金計画'!$F$39,'2年目 損益資金計画'!$F$39,'3年目 損益資金計画'!$F$39,'4年目 損益資金計画'!$F$39,'5年目 損益資金計画'!$F$39) -> 0 | G39: =CHOOSE($U$2,'初年度 損益資金計画'!$G$39,'2年目 損益資金計画'!$G$39,'3年目 損益資金計画'!$G$39,'4年目 損益資金計画'!$G$39,'5年目 損益資金計画'!$G$39) -> 0 | H39: =CHOOSE($U$2,'初年度 損益資金計画'!$H$39,'2年目 損益資金計画'!$H$39,'3年目 損益資金計画'!$H$39,'4年目 損益資金計画'!$H$39,'5年目 損益資金計画'!$H$39) -> 0 | I39: =CHOOSE($U$2,'初年度 損益資金計画'!$I$39,'2年目 損益資金計画'!$I$39,'3年目 損益資金計画'!$I$39,'4年目 損益資金計画'!$I$39,'5年目 損益資金計画'!$I$39) -> 0 | J39: =CHOOSE($U$2,'初年度 損益資金計画'!$J$39,'2年目 損益資金計画'!$J$39,'3年目 損益資金計画'!$J$39,'4年目 損益資金計画'!$J$39,'5年目 損益資金計画'!$J$39) -> 0 | K39: =CHOOSE($U$2,'初年度 損益資金計画'!$K$39,'2年目 損益資金計画'!$K$39,'3年目 損益資金計画'!$K$39,'4年目 損益資金計画'!$K$39,'5年目 損益資金計画'!$K$39) -> 0 | L39: =CHOOSE($U$2,'初年度 損益資金計画'!$L$39,'2年目 損益資金計画'!$L$39,'3年目 損益資金計画'!$L$39,'4年目 損益資金計画'!$L$39,'5年目 損益資金計画'!$L$39) -> 0 | M39: =CHOOSE($U$2,'初年度 損益資金計画'!$M$39,'2年目 損益資金計画'!$M$39,'3年目 損益資金計画'!$M$39,'4年目 損益資金計画'!$M$39,'5年目 損益資金計画'!$M$39) -> 0 | N39: =CHOOSE($U$2,'初年度 損益資金計画'!$N$39,'2年目 損益資金計画'!$N$39,'3年目 損益資金計画'!$N$39,'4年目 損益資金計画'!$N$39,'5年目 損益資金計画'!$N$39) -> 0 | O39: =CHOOSE($U$2,'初年度 損益資金計画'!$O$39,'2年目 損益資金計画'!$O$39,'3年目 損益資金計画'!$O$39,'4年目 損益資金計画'!$O$39,'5年目 損益資金計画'!$O$39) -> 0 | P39: =CHOOSE($U$2,'初年度 損益資金計画'!$P$39,'2年目 損益資金計画'!$P$39,'3年目 損益資金計画'!$P$39,'4年目 損益資金計画'!$P$39,'5年目 損益資金計画'!$P$39) -> 0
C40: =CHOOSE($U$2,'初年度 損益資金計画'!$C$40,'2年目 損益資金計画'!$C$40,'3年目 損益資金計画'!$C$40,'4年目 損益資金計画'!$C$40,'5年目 損益資金計画'!$C$40) -> 雑損失 | D40: =CHOOSE($U$2,'初年度 損益資金計画'!$D$40,'2年目 損益資金計画'!$D$40,'3年目 損益資金計画'!$D$40,'4年目 損益資金計画'!$D$40,'5年目 損益資金計画'!$D$40) -> 0 | E40: =CHOOSE($U$2,'初年度 損益資金計画'!$E$40,'2年目 損益資金計画'!$E$40,'3年目 損益資金計画'!$E$40,'4年目 損益資金計画'!$E$40,'5年目 損益資金計画'!$E$40) -> 0 | F40: =CHOOSE($U$2,'初年度 損益資金計画'!$F$40,'2年目 損益資金計画'!$F$40,'3年目 損益資金計画'!$F$40,'4年目 損益資金計画'!$F$40,'5年目 損益資金計画'!$F$40) -> 0 | G40: =CHOOSE($U$2,'初年度 損益資金計画'!$G$40,'2年目 損益資金計画'!$G$40,'3年目 損益資金計画'!$G$40,'4年目 損益資金計画'!$G$40,'5年目 損益資金計画'!$G$40) -> 0 | H40: =CHOOSE($U$2,'初年度 損益資金計画'!$H$40,'2年目 損益資金計画'!$H$40,'3年目 損益資金計画'!$H$40,'4年目 損益資金計画'!$H$40,'5年目 損益資金計画'!$H$40) -> 0 | I40: =CHOOSE($U$2,'初年度 損益資金計画'!$I$40,'2年目 損益資金計画'!$I$40,'3年目 損益資金計画'!$I$40,'4年目 損益資金計画'!$I$40,'5年目 損益資金計画'!$I$40) -> 0 | J40: =CHOOSE($U$2,'初年度 損益資金計画'!$J$40,'2年目 損益資金計画'!$J$40,'3年目 損益資金計画'!$J$40,'4年目 損益資金計画'!$J$40,'5年目 損益資金計画'!$J$40) -> 0 | K40: =CHOOSE($U$2,'初年度 損益資金計画'!$K$40,'2年目 損益資金計画'!$K$40,'3年目 損益資金計画'!$K$40,'4年目 損益資金計画'!$K$40,'5年目 損益資金計画'!$K$40) -> 0 | L40: =CHOOSE($U$2,'初年度 損益資金計画'!$L$40,'2年目 損益資金計画'!$L$40,'3年目 損益資金計画'!$L$40,'4年目 損益資金計画'!$L$40,'5年目 損益資金計画'!$L$40) -> 0 | M40: =CHOOSE($U$2,'初年度 損益資金計画'!$M$40,'2年目 損益資金計画'!$M$40,'3年目 損益資金計画'!$M$40,'4年目 損益資金計画'!$M$40,'5年目 損益資金計画'!$M$40) -> 0 | N40: =CHOOSE($U$2,'初年度 損益資金計画'!$N$40,'2年目 損益資金計画'!$N$40,'3年目 損益資金計画'!$N$40,'4年目 損益資金計画'!$N$40,'5年目 損益資金計画'!$N$40) -> 0 | O40: =CHOOSE($U$2,'初年度 損益資金計画'!$O$40,'2年目 損益資金計画'!$O$40,'3年目 損益資金計画'!$O$40,'4年目 損益資金計画'!$O$40,'5年目 損益資金計画'!$O$40) -> 0 | P40: =CHOOSE($U$2,'初年度 損益資金計画'!$P$40,'2年目 損益資金計画'!$P$40,'3年目 損益資金計画'!$P$40,'4年目 損益資金計画'!$P$40,'5年目 損益資金計画'!$P$40) -> 0
A41: =CHOOSE($U$2,'初年度 損益資金計画'!$A$41,'2年目 損益資金計画'!$A$41,'3年目 損益資金計画'!$A$41,'4年目 損益資金計画'!$A$41,'5年目 損益資金計画'!$A$41) -> （経常利益） | D41: =CHOOSE($U$2,'初年度 損益資金計画'!$D$41,'2年目 損益資金計画'!$D$41,'3年目 損益資金計画'!$D$41,'4年目 損益資金計画'!$D$41,'5年目 損益資金計画'!$D$41) -> -251530 | E41: =CHOOSE($U$2,'初年度 損益資金計画'!$E$41,'2年目 損益資金計画'!$E$41,'3年目 損益資金計画'!$E$41,'4年目 損益資金計画'!$E$41,'5年目 損益資金計画'!$E$41) -> 709870 | F41: =CHOOSE($U$2,'初年度 損益資金計画'!$F$41,'2年目 損益資金計画'!$F$41,'3年目 損益資金計画'!$F$41,'4年目 損益資金計画'!$F$41,'5年目 損益資金計画'!$F$41) -> 1157370 | G41: =CHOOSE($U$2,'初年度 損益資金計画'!$G$41,'2年目 損益資金計画'!$G$41,'3年目 損益資金計画'!$G$41,'4年目 損益資金計画'!$G$41,'5年目 損益資金計画'!$G$41) -> 1199270 | H41: =CHOOSE($U$2,'初年度 損益資金計画'!$H$41,'2年目 損益資金計画'!$H$41,'3年目 損益資金計画'!$H$41,'4年目 損益資金計画'!$H$41,'5年目 損益資金計画'!$H$41) -> 1506970 | I41: =CHOOSE($U$2,'初年度 損益資金計画'!$I$41,'2年目 損益資金計画'!$I$41,'3年目 損益資金計画'!$I$41,'4年目 損益資金計画'!$I$41,'5年目 損益資金計画'!$I$41) -> 1786570 | J41: =CHOOSE($U$2,'初年度 損益資金計画'!$J$41,'2年目 損益資金計画'!$J$41,'3年目 損益資金計画'!$J$41,'4年目 損益資金計画'!$J$41,'5年目 損益資金計画'!$J$41) -> 1933470 | K41: =CHOOSE($U$2,'初年度 損益資金計画'!$K$41,'2年目 損益資金計画'!$K$41,'3年目 損益資金計画'!$K$41,'4年目 損益資金計画'!$K$41,'5年目 損益資金計画'!$K$41) -> 2080270 | L41: =CHOOSE($U$2,'初年度 損益資金計画'!$L$41,'2年目 損益資金計画'!$L$41,'3年目 損益資金計画'!$L$41,'4年目 損益資金計画'!$L$41,'5年目 損益資金計画'!$L$41) -> 1001370 | M41: =CHOOSE($U$2,'初年度 損益資金計画'!$M$41,'2年目 損益資金計画'!$M$41,'3年目 損益資金計画'!$M$41,'4年目 損益資金計画'!$M$41,'5年目 損益資金計画'!$M$41) -> 1870470 | N41: =CHOOSE($U$2,'初年度 損益資金計画'!$N$41,'2年目 損益資金計画'!$N$41,'3年目 損益資金計画'!$N$41,'4年目 損益資金計画'!$N$41,'5年目 損益資金計画'!$N$41) -> 2346070 | O41: =CHOOSE($U$2,'初年度 損益資金計画'!$O$41,'2年目 損益資金計画'!$O$41,'3年目 損益資金計画'!$O$41,'4年目 損益資金計画'!$O$41,'5年目 損益資金計画'!$O$41) -> 3031170 | P41: =CHOOSE($U$2,'初年度 損益資金計画'!$P$41,'2年目 損益資金計画'!$P$41,'3年目 損益資金計画'!$P$41,'4年目 損益資金計画'!$P$41,'5年目 損益資金計画'!$P$41) -> 18371340
A42: =CHOOSE($U$2,'初年度 損益資金計画'!$A$42,'2年目 損益資金計画'!$A$42,'3年目 損益資金計画'!$A$42,'4年目 損益資金計画'!$A$42,'5年目 損益資金計画'!$A$42) -> （税引後利益） | D42: =CHOOSE($U$2,'初年度 損益資金計画'!$D$42,'2年目 損益資金計画'!$D$42,'3年目 損益資金計画'!$D$42,'4年目 損益資金計画'!$D$42,'5年目 損益資金計画'!$D$42) -> 0 | E42: =CHOOSE($U$2,'初年度 損益資金計画'!$E$42,'2年目 損益資金計画'!$E$42,'3年目 損益資金計画'!$E$42,'4年目 損益資金計画'!$E$42,'5年目 損益資金計画'!$E$42) -> 0 | F42: =CHOOSE($U$2,'初年度 損益資金計画'!$F$42,'2年目 損益資金計画'!$F$42,'3年目 損益資金計画'!$F$42,'4年目 損益資金計画'!$F$42,'5年目 損益資金計画'!$F$42) -> 0 | G42: =CHOOSE($U$2,'初年度 損益資金計画'!$G$42,'2年目 損益資金計画'!$G$42,'3年目 損益資金計画'!$G$42,'4年目 損益資金計画'!$G$42,'5年目 損益資金計画'!$G$42) -> 0 | H42: =CHOOSE($U$2,'初年度 損益資金計画'!$H$42,'2年目 損益資金計画'!$H$42,'3年目 損益資金計画'!$H$42,'4年目 損益資金計画'!$H$42,'5年目 損益資金計画'!$H$42) -> 0 | I42: =CHOOSE($U$2,'初年度 損益資金計画'!$I$42,'2年目 損益資金計画'!$I$42,'3年目 損益資金計画'!$I$42,'4年目 損益資金計画'!$I$42,'5年目 損益資金計画'!$I$42) -> 0 | J42: =CHOOSE($U$2,'初年度 損益資金計画'!$J$42,'2年目 損益資金計画'!$J$42,'3年目 損益資金計画'!$J$42,'4年目 損益資金計画'!$J$42,'5年目 損益資金計画'!$J$42) -> 0 | K42: =CHOOSE($U$2,'初年度 損益資金計画'!$K$42,'2年目 損益資金計画'!$K$42,'3年目 損益資金計画'!$K$42,'4年目 損益資金計画'!$K$42,'5年目 損益資金計画'!$K$42) -> 0 | L42: =CHOOSE($U$2,'初年度 損益資金計画'!$L$42,'2年目 損益資金計画'!$L$42,'3年目 損益資金計画'!$L$42,'4年目 損益資金計画'!$L$42,'5年目 損益資金計画'!$L$42) -> 0 | M42: =CHOOSE($U$2,'初年度 損益資金計画'!$M$42,'2年目 損益資金計画'!$M$42,'3年目 損益資金計画'!$M$42,'4年目 損益資金計画'!$M$42,'5年目 損益資金計画'!$M$42) -> 0 | N42: =CHOOSE($U$2,'初年度 損益資金計画'!$N$42,'2年目 損益資金計画'!$N$42,'3年目 損益資金計画'!$N$42,'4年目 損益資金計画'!$N$42,'5年目 損益資金計画'!$N$42) -> 0 | O42: =CHOOSE($U$2,'初年度 損益資金計画'!$O$42,'2年目 損益資金計画'!$O$42,'3年目 損益資金計画'!$O$42,'4年目 損益資金計画'!$O$42,'5年目 損益資金計画'!$O$42) -> 0 | P42: =CHOOSE($U$2,'初年度 損益資金計画'!$P$42,'2年目 損益資金計画'!$P$42,'3年目 損益資金計画'!$P$42,'4年目 損益資金計画'!$P$42,'5年目 損益資金計画'!$P$42) -> 14697072
A43: =CHOOSE($U$2,'初年度 損益資金計画'!$A$43,'2年目 損益資金計画'!$A$43,'3年目 損益資金計画'!$A$43,'4年目 損益資金計画'!$A$43,'5年目 損益資金計画'!$A$43) -> 令和9年度 資金繰表 | E43: =CHOOSE($U$2,'初年度 損益資金計画'!$E$43,'2年目 損益資金計画'!$E$43,'3年目 損益資金計画'!$E$43,'4年目 損益資金計画'!$E$43,'5年目 損益資金計画'!$E$43) -> 0 | F43: =CHOOSE($U$2,'初年度 損益資金計画'!$F$43,'2年目 損益資金計画'!$F$43,'3年目 損益資金計画'!$F$43,'4年目 損益資金計画'!$F$43,'5年目 損益資金計画'!$F$43) -> 0 | G43: =CHOOSE($U$2,'初年度 損益資金計画'!$G$43,'2年目 損益資金計画'!$G$43,'3年目 損益資金計画'!$G$43,'4年目 損益資金計画'!$G$43,'5年目 損益資金計画'!$G$43) -> 0 | H43: =CHOOSE($U$2,'初年度 損益資金計画'!$H$43,'2年目 損益資金計画'!$H$43,'3年目 損益資金計画'!$H$43,'4年目 損益資金計画'!$H$43,'5年目 損益資金計画'!$H$43) -> 0 | I43: =CHOOSE($U$2,'初年度 損益資金計画'!$I$43,'2年目 損益資金計画'!$I$43,'3年目 損益資金計画'!$I$43,'4年目 損益資金計画'!$I$43,'5年目 損益資金計画'!$I$43) -> 0 | J43: =CHOOSE($U$2,'初年度 損益資金計画'!$J$43,'2年目 損益資金計画'!$J$43,'3年目 損益資金計画'!$J$43,'4年目 損益資金計画'!$J$43,'5年目 損益資金計画'!$J$43) -> 0 | K43: =CHOOSE($U$2,'初年度 損益資金計画'!$K$43,'2年目 損益資金計画'!$K$43,'3年目 損益資金計画'!$K$43,'4年目 損益資金計画'!$K$43,'5年目 損益資金計画'!$K$43) -> 0 | L43: =CHOOSE($U$2,'初年度 損益資金計画'!$L$43,'2年目 損益資金計画'!$L$43,'3年目 損益資金計画'!$L$43,'4年目 損益資金計画'!$L$43,'5年目 損益資金計画'!$L$43) -> 0 | M43: =CHOOSE($U$2,'初年度 損益資金計画'!$M$43,'2年目 損益資金計画'!$M$43,'3年目 損益資金計画'!$M$43,'4年目 損益資金計画'!$M$43,'5年目 損益資金計画'!$M$43) -> 0 | N43: =CHOOSE($U$2,'初年度 損益資金計画'!$N$43,'2年目 損益資金計画'!$N$43,'3年目 損益資金計画'!$N$43,'4年目 損益資金計画'!$N$43,'5年目 損益資金計画'!$N$43) -> 0 | O43: =CHOOSE($U$2,'初年度 損益資金計画'!$O$43,'2年目 損益資金計画'!$O$43,'3年目 損益資金計画'!$O$43,'4年目 損益資金計画'!$O$43,'5年目 損益資金計画'!$O$43) -> 0 | P43: =CHOOSE($U$2,'初年度 損益資金計画'!$P$43,'2年目 損益資金計画'!$P$43,'3年目 損益資金計画'!$P$43,'4年目 損益資金計画'!$P$43,'5年目 損益資金計画'!$P$43) -> 0
A44: =CHOOSE($U$2,'初年度 損益資金計画'!$A$44,'2年目 損益資金計画'!$A$44,'3年目 損益資金計画'!$A$44,'4年目 損益資金計画'!$A$44,'5年目 損益資金計画'!$A$44) -> 0 | B44: =CHOOSE($U$2,'初年度 損益資金計画'!$B$44,'2年目 損益資金計画'!$B$44,'3年目 損益資金計画'!$B$44,'4年目 損益資金計画'!$B$44,'5年目 損益資金計画'!$B$44) -> 0 | D44: =CHOOSE($U$2,'初年度 損益資金計画'!$D$44,'2年目 損益資金計画'!$D$44,'3年目 損益資金計画'!$D$44,'4年目 損益資金計画'!$D$44,'5年目 損益資金計画'!$D$44) -> ４月 | E44: =CHOOSE($U$2,'初年度 損益資金計画'!$E$44,'2年目 損益資金計画'!$E$44,'3年目 損益資金計画'!$E$44,'4年目 損益資金計画'!$E$44,'5年目 損益資金計画'!$E$44) -> ５月 | F44: =CHOOSE($U$2,'初年度 損益資金計画'!$F$44,'2年目 損益資金計画'!$F$44,'3年目 損益資金計画'!$F$44,'4年目 損益資金計画'!$F$44,'5年目 損益資金計画'!$F$44) -> ６月 | G44: =CHOOSE($U$2,'初年度 損益資金計画'!$G$44,'2年目 損益資金計画'!$G$44,'3年目 損益資金計画'!$G$44,'4年目 損益資金計画'!$G$44,'5年目 損益資金計画'!$G$44) -> ７月 | H44: =CHOOSE($U$2,'初年度 損益資金計画'!$H$44,'2年目 損益資金計画'!$H$44,'3年目 損益資金計画'!$H$44,'4年目 損益資金計画'!$H$44,'5年目 損益資金計画'!$H$44) -> ８月 | I44: =CHOOSE($U$2,'初年度 損益資金計画'!$I$44,'2年目 損益資金計画'!$I$44,'3年目 損益資金計画'!$I$44,'4年目 損益資金計画'!$I$44,'5年目 損益資金計画'!$I$44) -> ９月 | J44: =CHOOSE($U$2,'初年度 損益資金計画'!$J$44,'2年目 損益資金計画'!$J$44,'3年目 損益資金計画'!$J$44,'4年目 損益資金計画'!$J$44,'5年目 損益資金計画'!$J$44) -> １０月 | K44: =CHOOSE($U$2,'初年度 損益資金計画'!$K$44,'2年目 損益資金計画'!$K$44,'3年目 損益資金計画'!$K$44,'4年目 損益資金計画'!$K$44,'5年目 損益資金計画'!$K$44) -> １１月 | L44: =CHOOSE($U$2,'初年度 損益資金計画'!$L$44,'2年目 損益資金計画'!$L$44,'3年目 損益資金計画'!$L$44,'4年目 損益資金計画'!$L$44,'5年目 損益資金計画'!$L$44) -> １２月 | M44: =CHOOSE($U$2,'初年度 損益資金計画'!$M$44,'2年目 損益資金計画'!$M$44,'3年目 損益資金計画'!$M$44,'4年目 損益資金計画'!$M$44,'5年目 損益資金計画'!$M$44) -> １月 | N44: =CHOOSE($U$2,'初年度 損益資金計画'!$N$44,'2年目 損益資金計画'!$N$44,'3年目 損益資金計画'!$N$44,'4年目 損益資金計画'!$N$44,'5年目 損益資金計画'!$N$44) -> ２月 | O44: =CHOOSE($U$2,'初年度 損益資金計画'!$O$44,'2年目 損益資金計画'!$O$44,'3年目 損益資金計画'!$O$44,'4年目 損益資金計画'!$O$44,'5年目 損益資金計画'!$O$44) -> ３月 | P44: =CHOOSE($U$2,'初年度 損益資金計画'!$P$44,'2年目 損益資金計画'!$P$44,'3年目 損益資金計画'!$P$44,'4年目 損益資金計画'!$P$44,'5年目 損益資金計画'!$P$44) -> 条件
A45: =CHOOSE($U$2,'初年度 損益資金計画'!$A$45,'2年目 損益資金計画'!$A$45,'3年目 損益資金計画'!$A$45,'4年目 損益資金計画'!$A$45,'5年目 損益資金計画'!$A$45) -> 0 | B45: =CHOOSE($U$2,'初年度 損益資金計画'!$B$45,'2年目 損益資金計画'!$B$45,'3年目 損益資金計画'!$B$45,'4年目 損益資金計画'!$B$45,'5年目 損益資金計画'!$B$45) -> 前月繰越 | D45: =CHOOSE($U$2,'初年度 損益資金計画'!$D$45,'2年目 損益資金計画'!$D$45,'3年目 損益資金計画'!$D$45,'4年目 損益資金計画'!$D$45,'5年目 損益資金計画'!$D$45) -> -2287140 | E45: =CHOOSE($U$2,'初年度 損益資金計画'!$E$45,'2年目 損益資金計画'!$E$45,'3年目 損益資金計画'!$E$45,'4年目 損益資金計画'!$E$45,'5年目 損益資金計画'!$E$45) -> -3371900 | F45: =CHOOSE($U$2,'初年度 損益資金計画'!$F$45,'2年目 損益資金計画'!$F$45,'3年目 損益資金計画'!$F$45,'4年目 損益資金計画'!$F$45,'5年目 損益資金計画'!$F$45) -> -4167830 | G45: =CHOOSE($U$2,'初年度 損益資金計画'!$G$45,'2年目 損益資金計画'!$G$45,'3年目 損益資金計画'!$G$45,'4年目 損益資金計画'!$G$45,'5年目 損益資金計画'!$G$45) -> -4369360 | H45: =CHOOSE($U$2,'初年度 損益資金計画'!$H$45,'2年目 損益資金計画'!$H$45,'3年目 損益資金計画'!$H$45,'4年目 損益資金計画'!$H$45,'5年目 損益資金計画'!$H$45) -> -4109490 | I45: =CHOOSE($U$2,'初年度 損益資金計画'!$I$45,'2年目 損益資金計画'!$I$45,'3年目 損益資金計画'!$I$45,'4年目 損益資金計画'!$I$45,'5年目 損益資金計画'!$I$45) -> -3402120 | J45: =CHOOSE($U$2,'初年度 損益資金計画'!$J$45,'2年目 損益資金計画'!$J$45,'3年目 損益資金計画'!$J$45,'4年目 損益資金計画'!$J$45,'5年目 損益資金計画'!$J$45) -> -2652850 | K45: =CHOOSE($U$2,'初年度 損益資金計画'!$K$45,'2年目 損益資金計画'!$K$45,'3年目 損益資金計画'!$K$45,'4年目 損益資金計画'!$K$45,'5年目 損益資金計画'!$K$45) -> -1595880 | L45: =CHOOSE($U$2,'初年度 損益資金計画'!$L$45,'2年目 損益資金計画'!$L$45,'3年目 損益資金計画'!$L$45,'4年目 損益資金計画'!$L$45,'5年目 損益資金計画'!$L$45) -> -259310 | M45: =CHOOSE($U$2,'初年度 損益資金計画'!$M$45,'2年目 損益資金計画'!$M$45,'3年目 損益資金計画'!$M$45,'4年目 損益資金計画'!$M$45,'5年目 損益資金計画'!$M$45) -> 1224160 | N45: =CHOOSE($U$2,'初年度 損益資金計画'!$N$45,'2年目 損益資金計画'!$N$45,'3年目 損益資金計画'!$N$45,'4年目 損益資金計画'!$N$45,'5年目 損益資金計画'!$N$45) -> 1950430 | O45: =CHOOSE($U$2,'初年度 損益資金計画'!$O$45,'2年目 損益資金計画'!$O$45,'3年目 損益資金計画'!$O$45,'4年目 損益資金計画'!$O$45,'5年目 損益資金計画'!$O$45) -> 3405800 | P45: =CHOOSE($U$2,'初年度 損益資金計画'!$P$45,'2年目 損益資金計画'!$P$45,'3年目 損益資金計画'!$P$45,'4年目 損益資金計画'!$P$45,'5年目 損益資金計画'!$P$45) -> 0
A46: =CHOOSE($U$2,'初年度 損益資金計画'!$A$46,'2年目 損益資金計画'!$A$46,'3年目 損益資金計画'!$A$46,'4年目 損益資金計画'!$A$46,'5年目 損益資金計画'!$A$46) -> 0 | B46: =CHOOSE($U$2,'初年度 損益資金計画'!$B$46,'2年目 損益資金計画'!$B$46,'3年目 損益資金計画'!$B$46,'4年目 損益資金計画'!$B$46,'5年目 損益資金計画'!$B$46) -> 経常収入 | D46: =CHOOSE($U$2,'初年度 損益資金計画'!$D$46,'2年目 損益資金計画'!$D$46,'3年目 損益資金計画'!$D$46,'4年目 損益資金計画'!$D$46,'5年目 損益資金計画'!$D$46) -> 598500 | E46: =CHOOSE($U$2,'初年度 損益資金計画'!$E$46,'2年目 損益資金計画'!$E$46,'3年目 損益資金計画'!$E$46,'4年目 損益資金計画'!$E$46,'5年目 損益資金計画'!$E$46) -> 1304000 | F46: =CHOOSE($U$2,'初年度 損益資金計画'!$F$46,'2年目 損益資金計画'!$F$46,'3年目 損益資金計画'!$F$46,'4年目 損益資金計画'!$F$46,'5年目 損益資金計画'!$F$46) -> 1898400 | G46: =CHOOSE($U$2,'初年度 損益資金計画'!$G$46,'2年目 損益資金計画'!$G$46,'3年目 損益資金計画'!$G$46,'4年目 損益資金計画'!$G$46,'5年目 損益資金計画'!$G$46) -> 2359800 | H46: =CHOOSE($U$2,'初年度 損益資金計画'!$H$46,'2年目 損益資金計画'!$H$46,'3年目 損益資金計画'!$H$46,'4年目 損益資金計画'!$H$46,'5年目 損益資金計画'!$H$46) -> 2807300 | I46: =CHOOSE($U$2,'初年度 損益資金計画'!$I$46,'2年目 損益資金計画'!$I$46,'3年目 損益資金計画'!$I$46,'4年目 損益資金計画'!$I$46,'5年目 損益資金計画'!$I$46) -> 2849200 | J46: =CHOOSE($U$2,'初年度 損益資金計画'!$J$46,'2年目 損益資金計画'!$J$46,'3年目 損益資金計画'!$J$46,'4年目 損益資金計画'!$J$46,'5年目 損益資金計画'!$J$46) -> 3156900 | K46: =CHOOSE($U$2,'初年度 損益資金計画'!$K$46,'2年目 損益資金計画'!$K$46,'3年目 損益資金計画'!$K$46,'4年目 損益資金計画'!$K$46,'5年目 損益資金計画'!$K$46) -> 3436500 | L46: =CHOOSE($U$2,'初年度 損益資金計画'!$L$46,'2年目 損益資金計画'!$L$46,'3年目 損益資金計画'!$L$46,'4年目 損益資金計画'!$L$46,'5年目 損益資金計画'!$L$46) -> 3583400 | M46: =CHOOSE($U$2,'初年度 損益資金計画'!$M$46,'2年目 損益資金計画'!$M$46,'3年目 損益資金計画'!$M$46,'4年目 損益資金計画'!$M$46,'5年目 損益資金計画'!$M$46) -> 3730200 | N46: =CHOOSE($U$2,'初年度 損益資金計画'!$N$46,'2年目 損益資金計画'!$N$46,'3年目 損益資金計画'!$N$46,'4年目 損益資金計画'!$N$46,'5年目 損益資金計画'!$N$46) -> 3555300 | O46: =CHOOSE($U$2,'初年度 損益資金計画'!$O$46,'2年目 損益資金計画'!$O$46,'3年目 損益資金計画'!$O$46,'4年目 損益資金計画'!$O$46,'5年目 損益資金計画'!$O$46) -> 3520400 | P46: =CHOOSE($U$2,'初年度 損益資金計画'!$P$46,'2年目 損益資金計画'!$P$46,'3年目 損益資金計画'!$P$46,'4年目 損益資金計画'!$P$46,'5年目 損益資金計画'!$P$46) -> 0
A47: =CHOOSE($U$2,'初年度 損益資金計画'!$A$47,'2年目 損益資金計画'!$A$47,'3年目 損益資金計画'!$A$47,'4年目 損益資金計画'!$A$47,'5年目 損益資金計画'!$A$47) -> 0 | B47: =CHOOSE($U$2,'初年度 損益資金計画'!$B$47,'2年目 損益資金計画'!$B$47,'3年目 損益資金計画'!$B$47,'4年目 損益資金計画'!$B$47,'5年目 損益資金計画'!$B$47) -> 0 | C47: =CHOOSE($U$2,'初年度 損益資金計画'!$C$47,'2年目 損益資金計画'!$C$47,'3年目 損益資金計画'!$C$47,'4年目 損益資金計画'!$C$47,'5年目 損益資金計画'!$C$47) -> 訓練給付金 | D47: =CHOOSE($U$2,'初年度 損益資金計画'!$D$47,'2年目 損益資金計画'!$D$47,'3年目 損益資金計画'!$D$47,'4年目 損益資金計画'!$D$47,'5年目 損益資金計画'!$D$47) -> 398500 | E47: =CHOOSE($U$2,'初年度 損益資金計画'!$E$47,'2年目 損益資金計画'!$E$47,'3年目 損益資金計画'!$E$47,'4年目 損益資金計画'!$E$47,'5年目 損益資金計画'!$E$47) -> 804000 | F47: =CHOOSE($U$2,'初年度 損益資金計画'!$F$47,'2年目 損益資金計画'!$F$47,'3年目 損益資金計画'!$F$47,'4年目 損益資金計画'!$F$47,'5年目 損益資金計画'!$F$47) -> 1398400 | G47: =CHOOSE($U$2,'初年度 損益資金計画'!$G$47,'2年目 損益資金計画'!$G$47,'3年目 損益資金計画'!$G$47,'4年目 損益資金計画'!$G$47,'5年目 損益資金計画'!$G$47) -> 1859800 | H47: =CHOOSE($U$2,'初年度 損益資金計画'!$H$47,'2年目 損益資金計画'!$H$47,'3年目 損益資金計画'!$H$47,'4年目 損益資金計画'!$H$47,'5年目 損益資金計画'!$H$47) -> 2307300 | I47: =CHOOSE($U$2,'初年度 損益資金計画'!$I$47,'2年目 損益資金計画'!$I$47,'3年目 損益資金計画'!$I$47,'4年目 損益資金計画'!$I$47,'5年目 損益資金計画'!$I$47) -> 2349200 | J47: =CHOOSE($U$2,'初年度 損益資金計画'!$J$47,'2年目 損益資金計画'!$J$47,'3年目 損益資金計画'!$J$47,'4年目 損益資金計画'!$J$47,'5年目 損益資金計画'!$J$47) -> 2656900 | K47: =CHOOSE($U$2,'初年度 損益資金計画'!$K$47,'2年目 損益資金計画'!$K$47,'3年目 損益資金計画'!$K$47,'4年目 損益資金計画'!$K$47,'5年目 損益資金計画'!$K$47) -> 2936500 | L47: =CHOOSE($U$2,'初年度 損益資金計画'!$L$47,'2年目 損益資金計画'!$L$47,'3年目 損益資金計画'!$L$47,'4年目 損益資金計画'!$L$47,'5年目 損益資金計画'!$L$47) -> 3083400 | M47: =CHOOSE($U$2,'初年度 損益資金計画'!$M$47,'2年目 損益資金計画'!$M$47,'3年目 損益資金計画'!$M$47,'4年目 損益資金計画'!$M$47,'5年目 損益資金計画'!$M$47) -> 3230200 | N47: =CHOOSE($U$2,'初年度 損益資金計画'!$N$47,'2年目 損益資金計画'!$N$47,'3年目 損益資金計画'!$N$47,'4年目 損益資金計画'!$N$47,'5年目 損益資金計画'!$N$47) -> 3055300 | O47: =CHOOSE($U$2,'初年度 損益資金計画'!$O$47,'2年目 損益資金計画'!$O$47,'3年目 損益資金計画'!$O$47,'4年目 損益資金計画'!$O$47,'5年目 損益資金計画'!$O$47) -> 3020400 | P47: =CHOOSE($U$2,'初年度 損益資金計画'!$P$47,'2年目 損益資金計画'!$P$47,'3年目 損益資金計画'!$P$47,'4年目 損益資金計画'!$P$47,'5年目 損益資金計画'!$P$47) -> 2か月後15日入金
A48: =CHOOSE($U$2,'初年度 損益資金計画'!$A$48,'2年目 損益資金計画'!$A$48,'3年目 損益資金計画'!$A$48,'4年目 損益資金計画'!$A$48,'5年目 損益資金計画'!$A$48) -> 0 | C48: =CHOOSE($U$2,'初年度 損益資金計画'!$C$48,'2年目 損益資金計画'!$C$48,'3年目 損益資金計画'!$C$48,'4年目 損益資金計画'!$C$48,'5年目 損益資金計画'!$C$48) -> 就労売上 | D48: =CHOOSE($U$2,'初年度 損益資金計画'!$D$48,'2年目 損益資金計画'!$D$48,'3年目 損益資金計画'!$D$48,'4年目 損益資金計画'!$D$48,'5年目 損益資金計画'!$D$48) -> 200000 | E48: =CHOOSE($U$2,'初年度 損益資金計画'!$E$48,'2年目 損益資金計画'!$E$48,'3年目 損益資金計画'!$E$48,'4年目 損益資金計画'!$E$48,'5年目 損益資金計画'!$E$48) -> 500000 | F48: =CHOOSE($U$2,'初年度 損益資金計画'!$F$48,'2年目 損益資金計画'!$F$48,'3年目 損益資金計画'!$F$48,'4年目 損益資金計画'!$F$48,'5年目 損益資金計画'!$F$48) -> 500000 | G48: =CHOOSE($U$2,'初年度 損益資金計画'!$G$48,'2年目 損益資金計画'!$G$48,'3年目 損益資金計画'!$G$48,'4年目 損益資金計画'!$G$48,'5年目 損益資金計画'!$G$48) -> 500000 | H48: =CHOOSE($U$2,'初年度 損益資金計画'!$H$48,'2年目 損益資金計画'!$H$48,'3年目 損益資金計画'!$H$48,'4年目 損益資金計画'!$H$48,'5年目 損益資金計画'!$H$48) -> 500000 | I48: =CHOOSE($U$2,'初年度 損益資金計画'!$I$48,'2年目 損益資金計画'!$I$48,'3年目 損益資金計画'!$I$48,'4年目 損益資金計画'!$I$48,'5年目 損益資金計画'!$I$48) -> 500000 | J48: =CHOOSE($U$2,'初年度 損益資金計画'!$J$48,'2年目 損益資金計画'!$J$48,'3年目 損益資金計画'!$J$48,'4年目 損益資金計画'!$J$48,'5年目 損益資金計画'!$J$48) -> 500000 | K48: =CHOOSE($U$2,'初年度 損益資金計画'!$K$48,'2年目 損益資金計画'!$K$48,'3年目 損益資金計画'!$K$48,'4年目 損益資金計画'!$K$48,'5年目 損益資金計画'!$K$48) -> 500000 | L48: =CHOOSE($U$2,'初年度 損益資金計画'!$L$48,'2年目 損益資金計画'!$L$48,'3年目 損益資金計画'!$L$48,'4年目 損益資金計画'!$L$48,'5年目 損益資金計画'!$L$48) -> 500000 | M48: =CHOOSE($U$2,'初年度 損益資金計画'!$M$48,'2年目 損益資金計画'!$M$48,'3年目 損益資金計画'!$M$48,'4年目 損益資金計画'!$M$48,'5年目 損益資金計画'!$M$48) -> 500000 | N48: =CHOOSE($U$2,'初年度 損益資金計画'!$N$48,'2年目 損益資金計画'!$N$48,'3年目 損益資金計画'!$N$48,'4年目 損益資金計画'!$N$48,'5年目 損益資金計画'!$N$48) -> 500000 | O48: =CHOOSE($U$2,'初年度 損益資金計画'!$O$48,'2年目 損益資金計画'!$O$48,'3年目 損益資金計画'!$O$48,'4年目 損益資金計画'!$O$48,'5年目 損益資金計画'!$O$48) -> 500000 | P48: =CHOOSE($U$2,'初年度 損益資金計画'!$P$48,'2年目 損益資金計画'!$P$48,'3年目 損益資金計画'!$P$48,'4年目 損益資金計画'!$P$48,'5年目 損益資金計画'!$P$48) -> 売上月末締め翌月末払い
A49: =CHOOSE($U$2,'初年度 損益資金計画'!$A$49,'2年目 損益資金計画'!$A$49,'3年目 損益資金計画'!$A$49,'4年目 損益資金計画'!$A$49,'5年目 損益資金計画'!$A$49) -> 0 | C49: =CHOOSE($U$2,'初年度 損益資金計画'!$C$49,'2年目 損益資金計画'!$C$49,'3年目 損益資金計画'!$C$49,'4年目 損益資金計画'!$C$49,'5年目 損益資金計画'!$C$49) -> その他 | D49: =CHOOSE($U$2,'初年度 損益資金計画'!$D$49,'2年目 損益資金計画'!$D$49,'3年目 損益資金計画'!$D$49,'4年目 損益資金計画'!$D$49,'5年目 損益資金計画'!$D$49) -> 0 | E49: =CHOOSE($U$2,'初年度 損益資金計画'!$E$49,'2年目 損益資金計画'!$E$49,'3年目 損益資金計画'!$E$49,'4年目 損益資金計画'!$E$49,'5年目 損益資金計画'!$E$49) -> 0 | F49: =CHOOSE($U$2,'初年度 損益資金計画'!$F$49,'2年目 損益資金計画'!$F$49,'3年目 損益資金計画'!$F$49,'4年目 損益資金計画'!$F$49,'5年目 損益資金計画'!$F$49) -> 0 | G49: =CHOOSE($U$2,'初年度 損益資金計画'!$G$49,'2年目 損益資金計画'!$G$49,'3年目 損益資金計画'!$G$49,'4年目 損益資金計画'!$G$49,'5年目 損益資金計画'!$G$49) -> 0 | H49: =CHOOSE($U$2,'初年度 損益資金計画'!$H$49,'2年目 損益資金計画'!$H$49,'3年目 損益資金計画'!$H$49,'4年目 損益資金計画'!$H$49,'5年目 損益資金計画'!$H$49) -> 0 | I49: =CHOOSE($U$2,'初年度 損益資金計画'!$I$49,'2年目 損益資金計画'!$I$49,'3年目 損益資金計画'!$I$49,'4年目 損益資金計画'!$I$49,'5年目 損益資金計画'!$I$49) -> 0 | J49: =CHOOSE($U$2,'初年度 損益資金計画'!$J$49,'2年目 損益資金計画'!$J$49,'3年目 損益資金計画'!$J$49,'4年目 損益資金計画'!$J$49,'5年目 損益資金計画'!$J$49) -> 0 | K49: =CHOOSE($U$2,'初年度 損益資金計画'!$K$49,'2年目 損益資金計画'!$K$49,'3年目 損益資金計画'!$K$49,'4年目 損益資金計画'!$K$49,'5年目 損益資金計画'!$K$49) -> 0 | L49: =CHOOSE($U$2,'初年度 損益資金計画'!$L$49,'2年目 損益資金計画'!$L$49,'3年目 損益資金計画'!$L$49,'4年目 損益資金計画'!$L$49,'5年目 損益資金計画'!$L$49) -> 0 | M49: =CHOOSE($U$2,'初年度 損益資金計画'!$M$49,'2年目 損益資金計画'!$M$49,'3年目 損益資金計画'!$M$49,'4年目 損益資金計画'!$M$49,'5年目 損益資金計画'!$M$49) -> 0 | N49: =CHOOSE($U$2,'初年度 損益資金計画'!$N$49,'2年目 損益資金計画'!$N$49,'3年目 損益資金計画'!$N$49,'4年目 損益資金計画'!$N$49,'5年目 損益資金計画'!$N$49) -> 0 | O49: =CHOOSE($U$2,'初年度 損益資金計画'!$O$49,'2年目 損益資金計画'!$O$49,'3年目 損益資金計画'!$O$49,'4年目 損益資金計画'!$O$49,'5年目 損益資金計画'!$O$49) -> 0 | P49: =CHOOSE($U$2,'初年度 損益資金計画'!$P$49,'2年目 損益資金計画'!$P$49,'3年目 損益資金計画'!$P$49,'4年目 損益資金計画'!$P$49,'5年目 損益資金計画'!$P$49) -> 月末締め翌月末払い
A50: =CHOOSE($U$2,'初年度 損益資金計画'!$A$50,'2年目 損益資金計画'!$A$50,'3年目 損益資金計画'!$A$50,'4年目 損益資金計画'!$A$50,'5年目 損益資金計画'!$A$50) -> 0 | C50: =CHOOSE($U$2,'初年度 損益資金計画'!$C$50,'2年目 損益資金計画'!$C$50,'3年目 損益資金計画'!$C$50,'4年目 損益資金計画'!$C$50,'5年目 損益資金計画'!$C$50) -> 他収入 | D50: =CHOOSE($U$2,'初年度 損益資金計画'!$D$50,'2年目 損益資金計画'!$D$50,'3年目 損益資金計画'!$D$50,'4年目 損益資金計画'!$D$50,'5年目 損益資金計画'!$D$50) -> 0 | E50: =CHOOSE($U$2,'初年度 損益資金計画'!$E$50,'2年目 損益資金計画'!$E$50,'3年目 損益資金計画'!$E$50,'4年目 損益資金計画'!$E$50,'5年目 損益資金計画'!$E$50) -> 0 | F50: =CHOOSE($U$2,'初年度 損益資金計画'!$F$50,'2年目 損益資金計画'!$F$50,'3年目 損益資金計画'!$F$50,'4年目 損益資金計画'!$F$50,'5年目 損益資金計画'!$F$50) -> 0 | G50: =CHOOSE($U$2,'初年度 損益資金計画'!$G$50,'2年目 損益資金計画'!$G$50,'3年目 損益資金計画'!$G$50,'4年目 損益資金計画'!$G$50,'5年目 損益資金計画'!$G$50) -> 0 | H50: =CHOOSE($U$2,'初年度 損益資金計画'!$H$50,'2年目 損益資金計画'!$H$50,'3年目 損益資金計画'!$H$50,'4年目 損益資金計画'!$H$50,'5年目 損益資金計画'!$H$50) -> 0 | I50: =CHOOSE($U$2,'初年度 損益資金計画'!$I$50,'2年目 損益資金計画'!$I$50,'3年目 損益資金計画'!$I$50,'4年目 損益資金計画'!$I$50,'5年目 損益資金計画'!$I$50) -> 0 | J50: =CHOOSE($U$2,'初年度 損益資金計画'!$J$50,'2年目 損益資金計画'!$J$50,'3年目 損益資金計画'!$J$50,'4年目 損益資金計画'!$J$50,'5年目 損益資金計画'!$J$50) -> 0 | K50: =CHOOSE($U$2,'初年度 損益資金計画'!$K$50,'2年目 損益資金計画'!$K$50,'3年目 損益資金計画'!$K$50,'4年目 損益資金計画'!$K$50,'5年目 損益資金計画'!$K$50) -> 0 | L50: =CHOOSE($U$2,'初年度 損益資金計画'!$L$50,'2年目 損益資金計画'!$L$50,'3年目 損益資金計画'!$L$50,'4年目 損益資金計画'!$L$50,'5年目 損益資金計画'!$L$50) -> 0 | M50: =CHOOSE($U$2,'初年度 損益資金計画'!$M$50,'2年目 損益資金計画'!$M$50,'3年目 損益資金計画'!$M$50,'4年目 損益資金計画'!$M$50,'5年目 損益資金計画'!$M$50) -> 0 | N50: =CHOOSE($U$2,'初年度 損益資金計画'!$N$50,'2年目 損益資金計画'!$N$50,'3年目 損益資金計画'!$N$50,'4年目 損益資金計画'!$N$50,'5年目 損益資金計画'!$N$50) -> 0 | O50: =CHOOSE($U$2,'初年度 損益資金計画'!$O$50,'2年目 損益資金計画'!$O$50,'3年目 損益資金計画'!$O$50,'4年目 損益資金計画'!$O$50,'5年目 損益資金計画'!$O$50) -> 0 | P50: =CHOOSE($U$2,'初年度 損益資金計画'!$P$50,'2年目 損益資金計画'!$P$50,'3年目 損益資金計画'!$P$50,'4年目 損益資金計画'!$P$50,'5年目 損益資金計画'!$P$50) -> 月末締め翌月末払い
A51: =CHOOSE($U$2,'初年度 損益資金計画'!$A$51,'2年目 損益資金計画'!$A$51,'3年目 損益資金計画'!$A$51,'4年目 損益資金計画'!$A$51,'5年目 損益資金計画'!$A$51) -> 0 | B51: =CHOOSE($U$2,'初年度 損益資金計画'!$B$51,'2年目 損益資金計画'!$B$51,'3年目 損益資金計画'!$B$51,'4年目 損益資金計画'!$B$51,'5年目 損益資金計画'!$B$51) -> 経常支出 | D51: =CHOOSE($U$2,'初年度 損益資金計画'!$D$51,'2年目 損益資金計画'!$D$51,'3年目 損益資金計画'!$D$51,'4年目 損益資金計画'!$D$51,'5年目 損益資金計画'!$D$51) -> 1683260 | E51: =CHOOSE($U$2,'初年度 損益資金計画'!$E$51,'2年目 損益資金計画'!$E$51,'3年目 損益資金計画'!$E$51,'4年目 損益資金計画'!$E$51,'5年目 損益資金計画'!$E$51) -> 2099930 | F51: =CHOOSE($U$2,'初年度 損益資金計画'!$F$51,'2年目 損益資金計画'!$F$51,'3年目 損益資金計画'!$F$51,'4年目 損益資金計画'!$F$51,'5年目 損益資金計画'!$F$51) -> 2099930 | G51: =CHOOSE($U$2,'初年度 損益資金計画'!$G$51,'2年目 損益資金計画'!$G$51,'3年目 損益資金計画'!$G$51,'4年目 損益資金計画'!$G$51,'5年目 損益資金計画'!$G$51) -> 2099930 | H51: =CHOOSE($U$2,'初年度 損益資金計画'!$H$51,'2年目 損益資金計画'!$H$51,'3年目 損益資金計画'!$H$51,'4年目 損益資金計画'!$H$51,'5年目 損益資金計画'!$H$51) -> 2099930 | I51: =CHOOSE($U$2,'初年度 損益資金計画'!$I$51,'2年目 損益資金計画'!$I$51,'3年目 損益資金計画'!$I$51,'4年目 損益資金計画'!$I$51,'5年目 損益資金計画'!$I$51) -> 2099930 | J51: =CHOOSE($U$2,'初年度 損益資金計画'!$J$51,'2年目 損益資金計画'!$J$51,'3年目 損益資金計画'!$J$51,'4年目 損益資金計画'!$J$51,'5年目 損益資金計画'!$J$51) -> 2099930 | K51: =CHOOSE($U$2,'初年度 損益資金計画'!$K$51,'2年目 損益資金計画'!$K$51,'3年目 損益資金計画'!$K$51,'4年目 損益資金計画'!$K$51,'5年目 損益資金計画'!$K$51) -> 2099930 | L51: =CHOOSE($U$2,'初年度 損益資金計画'!$L$51,'2年目 損益資金計画'!$L$51,'3年目 損益資金計画'!$L$51,'4年目 損益資金計画'!$L$51,'5年目 損益資金計画'!$L$51) -> 2099930 | M51: =CHOOSE($U$2,'初年度 損益資金計画'!$M$51,'2年目 損益資金計画'!$M$51,'3年目 損益資金計画'!$M$51,'4年目 損益資金計画'!$M$51,'5年目 損益資金計画'!$M$51) -> 3003930 | N51: =CHOOSE($U$2,'初年度 損益資金計画'!$N$51,'2年目 損益資金計画'!$N$51,'3年目 損益資金計画'!$N$51,'4年目 損益資金計画'!$N$51,'5年目 損益資金計画'!$N$51) -> 2099930 | O51: =CHOOSE($U$2,'初年度 損益資金計画'!$O$51,'2年目 損益資金計画'!$O$51,'3年目 損益資金計画'!$O$51,'4年目 損益資金計画'!$O$51,'5年目 損益資金計画'!$O$51) -> 2099930 | P51: =CHOOSE($U$2,'初年度 損益資金計画'!$P$51,'2年目 損益資金計画'!$P$51,'3年目 損益資金計画'!$P$51,'4年目 損益資金計画'!$P$51,'5年目 損益資金計画'!$P$51) -> 0
A52: =CHOOSE($U$2,'初年度 損益資金計画'!$A$52,'2年目 損益資金計画'!$A$52,'3年目 損益資金計画'!$A$52,'4年目 損益資金計画'!$A$52,'5年目 損益資金計画'!$A$52) -> 0 | B52: =CHOOSE($U$2,'初年度 損益資金計画'!$B$52,'2年目 損益資金計画'!$B$52,'3年目 損益資金計画'!$B$52,'4年目 損益資金計画'!$B$52,'5年目 損益資金計画'!$B$52) -> 0 | C52: =CHOOSE($U$2,'初年度 損益資金計画'!$C$52,'2年目 損益資金計画'!$C$52,'3年目 損益資金計画'!$C$52,'4年目 損益資金計画'!$C$52,'5年目 損益資金計画'!$C$52) -> 人件費（工賃・社保含） | D52: =CHOOSE($U$2,'初年度 損益資金計画'!$D$52,'2年目 損益資金計画'!$D$52,'3年目 損益資金計画'!$D$52,'4年目 損益資金計画'!$D$52,'5年目 損益資金計画'!$D$52) -> 1492260 | E52: =CHOOSE($U$2,'初年度 損益資金計画'!$E$52,'2年目 損益資金計画'!$E$52,'3年目 損益資金計画'!$E$52,'4年目 損益資金計画'!$E$52,'5年目 損益資金計画'!$E$52) -> 1938930 | F52: =CHOOSE($U$2,'初年度 損益資金計画'!$F$52,'2年目 損益資金計画'!$F$52,'3年目 損益資金計画'!$F$52,'4年目 損益資金計画'!$F$52,'5年目 損益資金計画'!$F$52) -> 1938930 | G52: =CHOOSE($U$2,'初年度 損益資金計画'!$G$52,'2年目 損益資金計画'!$G$52,'3年目 損益資金計画'!$G$52,'4年目 損益資金計画'!$G$52,'5年目 損益資金計画'!$G$52) -> 1938930 | H52: =CHOOSE($U$2,'初年度 損益資金計画'!$H$52,'2年目 損益資金計画'!$H$52,'3年目 損益資金計画'!$H$52,'4年目 損益資金計画'!$H$52,'5年目 損益資金計画'!$H$52) -> 1938930 | I52: =CHOOSE($U$2,'初年度 損益資金計画'!$I$52,'2年目 損益資金計画'!$I$52,'3年目 損益資金計画'!$I$52,'4年目 損益資金計画'!$I$52,'5年目 損益資金計画'!$I$52) -> 1938930 | J52: =CHOOSE($U$2,'初年度 損益資金計画'!$J$52,'2年目 損益資金計画'!$J$52,'3年目 損益資金計画'!$J$52,'4年目 損益資金計画'!$J$52,'5年目 損益資金計画'!$J$52) -> 1938930 | K52: =CHOOSE($U$2,'初年度 損益資金計画'!$K$52,'2年目 損益資金計画'!$K$52,'3年目 損益資金計画'!$K$52,'4年目 損益資金計画'!$K$52,'5年目 損益資金計画'!$K$52) -> 1938930 | L52: =CHOOSE($U$2,'初年度 損益資金計画'!$L$52,'2年目 損益資金計画'!$L$52,'3年目 損益資金計画'!$L$52,'4年目 損益資金計画'!$L$52,'5年目 損益資金計画'!$L$52) -> 1938930 | M52: =CHOOSE($U$2,'初年度 損益資金計画'!$M$52,'2年目 損益資金計画'!$M$52,'3年目 損益資金計画'!$M$52,'4年目 損益資金計画'!$M$52,'5年目 損益資金計画'!$M$52) -> 2842930 | N52: =CHOOSE($U$2,'初年度 損益資金計画'!$N$52,'2年目 損益資金計画'!$N$52,'3年目 損益資金計画'!$N$52,'4年目 損益資金計画'!$N$52,'5年目 損益資金計画'!$N$52) -> 1938930 | O52: =CHOOSE($U$2,'初年度 損益資金計画'!$O$52,'2年目 損益資金計画'!$O$52,'3年目 損益資金計画'!$O$52,'4年目 損益資金計画'!$O$52,'5年目 損益資金計画'!$O$52) -> 1938930 | P52: =CHOOSE($U$2,'初年度 損益資金計画'!$P$52,'2年目 損益資金計画'!$P$52,'3年目 損益資金計画'!$P$52,'4年目 損益資金計画'!$P$52,'5年目 損益資金計画'!$P$52) -> 月末締め翌月末払い
A53: =CHOOSE($U$2,'初年度 損益資金計画'!$A$53,'2年目 損益資金計画'!$A$53,'3年目 損益資金計画'!$A$53,'4年目 損益資金計画'!$A$53,'5年目 損益資金計画'!$A$53) -> 0 | C53: =CHOOSE($U$2,'初年度 損益資金計画'!$C$53,'2年目 損益資金計画'!$C$53,'3年目 損益資金計画'!$C$53,'4年目 損益資金計画'!$C$53,'5年目 損益資金計画'!$C$53) -> 諸経費 | D53: =CHOOSE($U$2,'初年度 損益資金計画'!$D$53,'2年目 損益資金計画'!$D$53,'3年目 損益資金計画'!$D$53,'4年目 損益資金計画'!$D$53,'5年目 損益資金計画'!$D$53) -> 30000 | E53: =CHOOSE($U$2,'初年度 損益資金計画'!$E$53,'2年目 損益資金計画'!$E$53,'3年目 損益資金計画'!$E$53,'4年目 損益資金計画'!$E$53,'5年目 損益資金計画'!$E$53) -> 30000 | F53: =CHOOSE($U$2,'初年度 損益資金計画'!$F$53,'2年目 損益資金計画'!$F$53,'3年目 損益資金計画'!$F$53,'4年目 損益資金計画'!$F$53,'5年目 損益資金計画'!$F$53) -> 30000 | G53: =CHOOSE($U$2,'初年度 損益資金計画'!$G$53,'2年目 損益資金計画'!$G$53,'3年目 損益資金計画'!$G$53,'4年目 損益資金計画'!$G$53,'5年目 損益資金計画'!$G$53) -> 30000 | H53: =CHOOSE($U$2,'初年度 損益資金計画'!$H$53,'2年目 損益資金計画'!$H$53,'3年目 損益資金計画'!$H$53,'4年目 損益資金計画'!$H$53,'5年目 損益資金計画'!$H$53) -> 30000 | I53: =CHOOSE($U$2,'初年度 損益資金計画'!$I$53,'2年目 損益資金計画'!$I$53,'3年目 損益資金計画'!$I$53,'4年目 損益資金計画'!$I$53,'5年目 損益資金計画'!$I$53) -> 30000 | J53: =CHOOSE($U$2,'初年度 損益資金計画'!$J$53,'2年目 損益資金計画'!$J$53,'3年目 損益資金計画'!$J$53,'4年目 損益資金計画'!$J$53,'5年目 損益資金計画'!$J$53) -> 30000 | K53: =CHOOSE($U$2,'初年度 損益資金計画'!$K$53,'2年目 損益資金計画'!$K$53,'3年目 損益資金計画'!$K$53,'4年目 損益資金計画'!$K$53,'5年目 損益資金計画'!$K$53) -> 30000 | L53: =CHOOSE($U$2,'初年度 損益資金計画'!$L$53,'2年目 損益資金計画'!$L$53,'3年目 損益資金計画'!$L$53,'4年目 損益資金計画'!$L$53,'5年目 損益資金計画'!$L$53) -> 30000 | M53: =CHOOSE($U$2,'初年度 損益資金計画'!$M$53,'2年目 損益資金計画'!$M$53,'3年目 損益資金計画'!$M$53,'4年目 損益資金計画'!$M$53,'5年目 損益資金計画'!$M$53) -> 30000 | N53: =CHOOSE($U$2,'初年度 損益資金計画'!$N$53,'2年目 損益資金計画'!$N$53,'3年目 損益資金計画'!$N$53,'4年目 損益資金計画'!$N$53,'5年目 損益資金計画'!$N$53) -> 30000 | O53: =CHOOSE($U$2,'初年度 損益資金計画'!$O$53,'2年目 損益資金計画'!$O$53,'3年目 損益資金計画'!$O$53,'4年目 損益資金計画'!$O$53,'5年目 損益資金計画'!$O$53) -> 30000 | P53: =CHOOSE($U$2,'初年度 損益資金計画'!$P$53,'2年目 損益資金計画'!$P$53,'3年目 損益資金計画'!$P$53,'4年目 損益資金計画'!$P$53,'5年目 損益資金計画'!$P$53) -> 現金支払い
A54: =CHOOSE($U$2,'初年度 損益資金計画'!$A$54,'2年目 損益資金計画'!$A$54,'3年目 損益資金計画'!$A$54,'4年目 損益資金計画'!$A$54,'5年目 損益資金計画'!$A$54) -> 0 | C54: =CHOOSE($U$2,'初年度 損益資金計画'!$C$54,'2年目 損益資金計画'!$C$54,'3年目 損益資金計画'!$C$54,'4年目 損益資金計画'!$C$54,'5年目 損益資金計画'!$C$54) -> 掛支払 | D54: =CHOOSE($U$2,'初年度 損益資金計画'!$D$54,'2年目 損益資金計画'!$D$54,'3年目 損益資金計画'!$D$54,'4年目 損益資金計画'!$D$54,'5年目 損益資金計画'!$D$54) -> 161000 | E54: =CHOOSE($U$2,'初年度 損益資金計画'!$E$54,'2年目 損益資金計画'!$E$54,'3年目 損益資金計画'!$E$54,'4年目 損益資金計画'!$E$54,'5年目 損益資金計画'!$E$54) -> 131000 | F54: =CHOOSE($U$2,'初年度 損益資金計画'!$F$54,'2年目 損益資金計画'!$F$54,'3年目 損益資金計画'!$F$54,'4年目 損益資金計画'!$F$54,'5年目 損益資金計画'!$F$54) -> 131000 | G54: =CHOOSE($U$2,'初年度 損益資金計画'!$G$54,'2年目 損益資金計画'!$G$54,'3年目 損益資金計画'!$G$54,'4年目 損益資金計画'!$G$54,'5年目 損益資金計画'!$G$54) -> 131000 | H54: =CHOOSE($U$2,'初年度 損益資金計画'!$H$54,'2年目 損益資金計画'!$H$54,'3年目 損益資金計画'!$H$54,'4年目 損益資金計画'!$H$54,'5年目 損益資金計画'!$H$54) -> 131000 | I54: =CHOOSE($U$2,'初年度 損益資金計画'!$I$54,'2年目 損益資金計画'!$I$54,'3年目 損益資金計画'!$I$54,'4年目 損益資金計画'!$I$54,'5年目 損益資金計画'!$I$54) -> 131000 | J54: =CHOOSE($U$2,'初年度 損益資金計画'!$J$54,'2年目 損益資金計画'!$J$54,'3年目 損益資金計画'!$J$54,'4年目 損益資金計画'!$J$54,'5年目 損益資金計画'!$J$54) -> 131000 | K54: =CHOOSE($U$2,'初年度 損益資金計画'!$K$54,'2年目 損益資金計画'!$K$54,'3年目 損益資金計画'!$K$54,'4年目 損益資金計画'!$K$54,'5年目 損益資金計画'!$K$54) -> 131000 | L54: =CHOOSE($U$2,'初年度 損益資金計画'!$L$54,'2年目 損益資金計画'!$L$54,'3年目 損益資金計画'!$L$54,'4年目 損益資金計画'!$L$54,'5年目 損益資金計画'!$L$54) -> 131000 | M54: =CHOOSE($U$2,'初年度 損益資金計画'!$M$54,'2年目 損益資金計画'!$M$54,'3年目 損益資金計画'!$M$54,'4年目 損益資金計画'!$M$54,'5年目 損益資金計画'!$M$54) -> 131000 | N54: =CHOOSE($U$2,'初年度 損益資金計画'!$N$54,'2年目 損益資金計画'!$N$54,'3年目 損益資金計画'!$N$54,'4年目 損益資金計画'!$N$54,'5年目 損益資金計画'!$N$54) -> 131000 | O54: =CHOOSE($U$2,'初年度 損益資金計画'!$O$54,'2年目 損益資金計画'!$O$54,'3年目 損益資金計画'!$O$54,'4年目 損益資金計画'!$O$54,'5年目 損益資金計画'!$O$54) -> 131000 | P54: =CHOOSE($U$2,'初年度 損益資金計画'!$P$54,'2年目 損益資金計画'!$P$54,'3年目 損益資金計画'!$P$54,'4年目 損益資金計画'!$P$54,'5年目 損益資金計画'!$P$54) -> 販管費（月末締め翌月末払い）
A55: =CHOOSE($U$2,'初年度 損益資金計画'!$A$55,'2年目 損益資金計画'!$A$55,'3年目 損益資金計画'!$A$55,'4年目 損益資金計画'!$A$55,'5年目 損益資金計画'!$A$55) -> 0 | C55: =CHOOSE($U$2,'初年度 損益資金計画'!$C$55,'2年目 損益資金計画'!$C$55,'3年目 損益資金計画'!$C$55,'4年目 損益資金計画'!$C$55,'5年目 損益資金計画'!$C$55) -> 0 | D55: =CHOOSE($U$2,'初年度 損益資金計画'!$D$55,'2年目 損益資金計画'!$D$55,'3年目 損益資金計画'!$D$55,'4年目 損益資金計画'!$D$55,'5年目 損益資金計画'!$D$55) -> 0 | E55: =CHOOSE($U$2,'初年度 損益資金計画'!$E$55,'2年目 損益資金計画'!$E$55,'3年目 損益資金計画'!$E$55,'4年目 損益資金計画'!$E$55,'5年目 損益資金計画'!$E$55) -> 0 | F55: =CHOOSE($U$2,'初年度 損益資金計画'!$F$55,'2年目 損益資金計画'!$F$55,'3年目 損益資金計画'!$F$55,'4年目 損益資金計画'!$F$55,'5年目 損益資金計画'!$F$55) -> 0 | G55: =CHOOSE($U$2,'初年度 損益資金計画'!$G$55,'2年目 損益資金計画'!$G$55,'3年目 損益資金計画'!$G$55,'4年目 損益資金計画'!$G$55,'5年目 損益資金計画'!$G$55) -> 0 | H55: =CHOOSE($U$2,'初年度 損益資金計画'!$H$55,'2年目 損益資金計画'!$H$55,'3年目 損益資金計画'!$H$55,'4年目 損益資金計画'!$H$55,'5年目 損益資金計画'!$H$55) -> 0 | I55: =CHOOSE($U$2,'初年度 損益資金計画'!$I$55,'2年目 損益資金計画'!$I$55,'3年目 損益資金計画'!$I$55,'4年目 損益資金計画'!$I$55,'5年目 損益資金計画'!$I$55) -> 0 | J55: =CHOOSE($U$2,'初年度 損益資金計画'!$J$55,'2年目 損益資金計画'!$J$55,'3年目 損益資金計画'!$J$55,'4年目 損益資金計画'!$J$55,'5年目 損益資金計画'!$J$55) -> 0 | K55: =CHOOSE($U$2,'初年度 損益資金計画'!$K$55,'2年目 損益資金計画'!$K$55,'3年目 損益資金計画'!$K$55,'4年目 損益資金計画'!$K$55,'5年目 損益資金計画'!$K$55) -> 0 | L55: =CHOOSE($U$2,'初年度 損益資金計画'!$L$55,'2年目 損益資金計画'!$L$55,'3年目 損益資金計画'!$L$55,'4年目 損益資金計画'!$L$55,'5年目 損益資金計画'!$L$55) -> 0 | M55: =CHOOSE($U$2,'初年度 損益資金計画'!$M$55,'2年目 損益資金計画'!$M$55,'3年目 損益資金計画'!$M$55,'4年目 損益資金計画'!$M$55,'5年目 損益資金計画'!$M$55) -> 0 | N55: =CHOOSE($U$2,'初年度 損益資金計画'!$N$55,'2年目 損益資金計画'!$N$55,'3年目 損益資金計画'!$N$55,'4年目 損益資金計画'!$N$55,'5年目 損益資金計画'!$N$55) -> 0 | O55: =CHOOSE($U$2,'初年度 損益資金計画'!$O$55,'2年目 損益資金計画'!$O$55,'3年目 損益資金計画'!$O$55,'4年目 損益資金計画'!$O$55,'5年目 損益資金計画'!$O$55) -> 0 | P55: =CHOOSE($U$2,'初年度 損益資金計画'!$P$55,'2年目 損益資金計画'!$P$55,'3年目 損益資金計画'!$P$55,'4年目 損益資金計画'!$P$55,'5年目 損益資金計画'!$P$55) -> 0
A56: =CHOOSE($U$2,'初年度 損益資金計画'!$A$56,'2年目 損益資金計画'!$A$56,'3年目 損益資金計画'!$A$56,'4年目 損益資金計画'!$A$56,'5年目 損益資金計画'!$A$56) -> 0 | B56: =CHOOSE($U$2,'初年度 損益資金計画'!$B$56,'2年目 損益資金計画'!$B$56,'3年目 損益資金計画'!$B$56,'4年目 損益資金計画'!$B$56,'5年目 損益資金計画'!$B$56) -> 経常収支差額 | D56: =CHOOSE($U$2,'初年度 損益資金計画'!$D$56,'2年目 損益資金計画'!$D$56,'3年目 損益資金計画'!$D$56,'4年目 損益資金計画'!$D$56,'5年目 損益資金計画'!$D$56) -> -1084760 | E56: =CHOOSE($U$2,'初年度 損益資金計画'!$E$56,'2年目 損益資金計画'!$E$56,'3年目 損益資金計画'!$E$56,'4年目 損益資金計画'!$E$56,'5年目 損益資金計画'!$E$56) -> -795930 | F56: =CHOOSE($U$2,'初年度 損益資金計画'!$F$56,'2年目 損益資金計画'!$F$56,'3年目 損益資金計画'!$F$56,'4年目 損益資金計画'!$F$56,'5年目 損益資金計画'!$F$56) -> -201530 | G56: =CHOOSE($U$2,'初年度 損益資金計画'!$G$56,'2年目 損益資金計画'!$G$56,'3年目 損益資金計画'!$G$56,'4年目 損益資金計画'!$G$56,'5年目 損益資金計画'!$G$56) -> 259870 | H56: =CHOOSE($U$2,'初年度 損益資金計画'!$H$56,'2年目 損益資金計画'!$H$56,'3年目 損益資金計画'!$H$56,'4年目 損益資金計画'!$H$56,'5年目 損益資金計画'!$H$56) -> 707370 | I56: =CHOOSE($U$2,'初年度 損益資金計画'!$I$56,'2年目 損益資金計画'!$I$56,'3年目 損益資金計画'!$I$56,'4年目 損益資金計画'!$I$56,'5年目 損益資金計画'!$I$56) -> 749270 | J56: =CHOOSE($U$2,'初年度 損益資金計画'!$J$56,'2年目 損益資金計画'!$J$56,'3年目 損益資金計画'!$J$56,'4年目 損益資金計画'!$J$56,'5年目 損益資金計画'!$J$56) -> 1056970 | K56: =CHOOSE($U$2,'初年度 損益資金計画'!$K$56,'2年目 損益資金計画'!$K$56,'3年目 損益資金計画'!$K$56,'4年目 損益資金計画'!$K$56,'5年目 損益資金計画'!$K$56) -> 1336570 | L56: =CHOOSE($U$2,'初年度 損益資金計画'!$L$56,'2年目 損益資金計画'!$L$56,'3年目 損益資金計画'!$L$56,'4年目 損益資金計画'!$L$56,'5年目 損益資金計画'!$L$56) -> 1483470 | M56: =CHOOSE($U$2,'初年度 損益資金計画'!$M$56,'2年目 損益資金計画'!$M$56,'3年目 損益資金計画'!$M$56,'4年目 損益資金計画'!$M$56,'5年目 損益資金計画'!$M$56) -> 726270 | N56: =CHOOSE($U$2,'初年度 損益資金計画'!$N$56,'2年目 損益資金計画'!$N$56,'3年目 損益資金計画'!$N$56,'4年目 損益資金計画'!$N$56,'5年目 損益資金計画'!$N$56) -> 1455370 | O56: =CHOOSE($U$2,'初年度 損益資金計画'!$O$56,'2年目 損益資金計画'!$O$56,'3年目 損益資金計画'!$O$56,'4年目 損益資金計画'!$O$56,'5年目 損益資金計画'!$O$56) -> 1420470 | P56: =CHOOSE($U$2,'初年度 損益資金計画'!$P$56,'2年目 損益資金計画'!$P$56,'3年目 損益資金計画'!$P$56,'4年目 損益資金計画'!$P$56,'5年目 損益資金計画'!$P$56) -> 0
A57: =CHOOSE($U$2,'初年度 損益資金計画'!$A$57,'2年目 損益資金計画'!$A$57,'3年目 損益資金計画'!$A$57,'4年目 損益資金計画'!$A$57,'5年目 損益資金計画'!$A$57) -> 0 | B57: =CHOOSE($U$2,'初年度 損益資金計画'!$B$57,'2年目 損益資金計画'!$B$57,'3年目 損益資金計画'!$B$57,'4年目 損益資金計画'!$B$57,'5年目 損益資金計画'!$B$57) -> 財務収入 | D57: =CHOOSE($U$2,'初年度 損益資金計画'!$D$57,'2年目 損益資金計画'!$D$57,'3年目 損益資金計画'!$D$57,'4年目 損益資金計画'!$D$57,'5年目 損益資金計画'!$D$57) -> 0 | E57: =CHOOSE($U$2,'初年度 損益資金計画'!$E$57,'2年目 損益資金計画'!$E$57,'3年目 損益資金計画'!$E$57,'4年目 損益資金計画'!$E$57,'5年目 損益資金計画'!$E$57) -> 0 | F57: =CHOOSE($U$2,'初年度 損益資金計画'!$F$57,'2年目 損益資金計画'!$F$57,'3年目 損益資金計画'!$F$57,'4年目 損益資金計画'!$F$57,'5年目 損益資金計画'!$F$57) -> 0 | G57: =CHOOSE($U$2,'初年度 損益資金計画'!$G$57,'2年目 損益資金計画'!$G$57,'3年目 損益資金計画'!$G$57,'4年目 損益資金計画'!$G$57,'5年目 損益資金計画'!$G$57) -> 0 | H57: =CHOOSE($U$2,'初年度 損益資金計画'!$H$57,'2年目 損益資金計画'!$H$57,'3年目 損益資金計画'!$H$57,'4年目 損益資金計画'!$H$57,'5年目 損益資金計画'!$H$57) -> 0 | I57: =CHOOSE($U$2,'初年度 損益資金計画'!$I$57,'2年目 損益資金計画'!$I$57,'3年目 損益資金計画'!$I$57,'4年目 損益資金計画'!$I$57,'5年目 損益資金計画'!$I$57) -> 0 | J57: =CHOOSE($U$2,'初年度 損益資金計画'!$J$57,'2年目 損益資金計画'!$J$57,'3年目 損益資金計画'!$J$57,'4年目 損益資金計画'!$J$57,'5年目 損益資金計画'!$J$57) -> 0 | K57: =CHOOSE($U$2,'初年度 損益資金計画'!$K$57,'2年目 損益資金計画'!$K$57,'3年目 損益資金計画'!$K$57,'4年目 損益資金計画'!$K$57,'5年目 損益資金計画'!$K$57) -> 0 | L57: =CHOOSE($U$2,'初年度 損益資金計画'!$L$57,'2年目 損益資金計画'!$L$57,'3年目 損益資金計画'!$L$57,'4年目 損益資金計画'!$L$57,'5年目 損益資金計画'!$L$57) -> 0 | M57: =CHOOSE($U$2,'初年度 損益資金計画'!$M$57,'2年目 損益資金計画'!$M$57,'3年目 損益資金計画'!$M$57,'4年目 損益資金計画'!$M$57,'5年目 損益資金計画'!$M$57) -> 0 | N57: =CHOOSE($U$2,'初年度 損益資金計画'!$N$57,'2年目 損益資金計画'!$N$57,'3年目 損益資金計画'!$N$57,'4年目 損益資金計画'!$N$57,'5年目 損益資金計画'!$N$57) -> 0 | O57: =CHOOSE($U$2,'初年度 損益資金計画'!$O$57,'2年目 損益資金計画'!$O$57,'3年目 損益資金計画'!$O$57,'4年目 損益資金計画'!$O$57,'5年目 損益資金計画'!$O$57) -> 0 | P57: =CHOOSE($U$2,'初年度 損益資金計画'!$P$57,'2年目 損益資金計画'!$P$57,'3年目 損益資金計画'!$P$57,'4年目 損益資金計画'!$P$57,'5年目 損益資金計画'!$P$57) -> 0
A58: =CHOOSE($U$2,'初年度 損益資金計画'!$A$58,'2年目 損益資金計画'!$A$58,'3年目 損益資金計画'!$A$58,'4年目 損益資金計画'!$A$58,'5年目 損益資金計画'!$A$58) -> 0 | B58: =CHOOSE($U$2,'初年度 損益資金計画'!$B$58,'2年目 損益資金計画'!$B$58,'3年目 損益資金計画'!$B$58,'4年目 損益資金計画'!$B$58,'5年目 損益資金計画'!$B$58) -> 0 | C58: =CHOOSE($U$2,'初年度 損益資金計画'!$C$58,'2年目 損益資金計画'!$C$58,'3年目 損益資金計画'!$C$58,'4年目 損益資金計画'!$C$58,'5年目 損益資金計画'!$C$58) -> 資本金 | D58: =CHOOSE($U$2,'初年度 損益資金計画'!$D$58,'2年目 損益資金計画'!$D$58,'3年目 損益資金計画'!$D$58,'4年目 損益資金計画'!$D$58,'5年目 損益資金計画'!$D$58) -> 0 | E58: =CHOOSE($U$2,'初年度 損益資金計画'!$E$58,'2年目 損益資金計画'!$E$58,'3年目 損益資金計画'!$E$58,'4年目 損益資金計画'!$E$58,'5年目 損益資金計画'!$E$58) -> 0 | F58: =CHOOSE($U$2,'初年度 損益資金計画'!$F$58,'2年目 損益資金計画'!$F$58,'3年目 損益資金計画'!$F$58,'4年目 損益資金計画'!$F$58,'5年目 損益資金計画'!$F$58) -> 0 | G58: =CHOOSE($U$2,'初年度 損益資金計画'!$G$58,'2年目 損益資金計画'!$G$58,'3年目 損益資金計画'!$G$58,'4年目 損益資金計画'!$G$58,'5年目 損益資金計画'!$G$58) -> 0 | H58: =CHOOSE($U$2,'初年度 損益資金計画'!$H$58,'2年目 損益資金計画'!$H$58,'3年目 損益資金計画'!$H$58,'4年目 損益資金計画'!$H$58,'5年目 損益資金計画'!$H$58) -> 0 | I58: =CHOOSE($U$2,'初年度 損益資金計画'!$I$58,'2年目 損益資金計画'!$I$58,'3年目 損益資金計画'!$I$58,'4年目 損益資金計画'!$I$58,'5年目 損益資金計画'!$I$58) -> 0 | J58: =CHOOSE($U$2,'初年度 損益資金計画'!$J$58,'2年目 損益資金計画'!$J$58,'3年目 損益資金計画'!$J$58,'4年目 損益資金計画'!$J$58,'5年目 損益資金計画'!$J$58) -> 0 | K58: =CHOOSE($U$2,'初年度 損益資金計画'!$K$58,'2年目 損益資金計画'!$K$58,'3年目 損益資金計画'!$K$58,'4年目 損益資金計画'!$K$58,'5年目 損益資金計画'!$K$58) -> 0 | L58: =CHOOSE($U$2,'初年度 損益資金計画'!$L$58,'2年目 損益資金計画'!$L$58,'3年目 損益資金計画'!$L$58,'4年目 損益資金計画'!$L$58,'5年目 損益資金計画'!$L$58) -> 0 | M58: =CHOOSE($U$2,'初年度 損益資金計画'!$M$58,'2年目 損益資金計画'!$M$58,'3年目 損益資金計画'!$M$58,'4年目 損益資金計画'!$M$58,'5年目 損益資金計画'!$M$58) -> 0 | N58: =CHOOSE($U$2,'初年度 損益資金計画'!$N$58,'2年目 損益資金計画'!$N$58,'3年目 損益資金計画'!$N$58,'4年目 損益資金計画'!$N$58,'5年目 損益資金計画'!$N$58) -> 0 | O58: =CHOOSE($U$2,'初年度 損益資金計画'!$O$58,'2年目 損益資金計画'!$O$58,'3年目 損益資金計画'!$O$58,'4年目 損益資金計画'!$O$58,'5年目 損益資金計画'!$O$58) -> 0 | P58: =CHOOSE($U$2,'初年度 損益資金計画'!$P$58,'2年目 損益資金計画'!$P$58,'3年目 損益資金計画'!$P$58,'4年目 損益資金計画'!$P$58,'5年目 損益資金計画'!$P$58) -> 0
A59: =CHOOSE($U$2,'初年度 損益資金計画'!$A$59,'2年目 損益資金計画'!$A$59,'3年目 損益資金計画'!$A$59,'4年目 損益資金計画'!$A$59,'5年目 損益資金計画'!$A$59) -> 0 | C59: =CHOOSE($U$2,'初年度 損益資金計画'!$C$59,'2年目 損益資金計画'!$C$59,'3年目 損益資金計画'!$C$59,'4年目 損益資金計画'!$C$59,'5年目 損益資金計画'!$C$59) -> 資本準備金 | D59: =CHOOSE($U$2,'初年度 損益資金計画'!$D$59,'2年目 損益資金計画'!$D$59,'3年目 損益資金計画'!$D$59,'4年目 損益資金計画'!$D$59,'5年目 損益資金計画'!$D$59) -> 0 | E59: =CHOOSE($U$2,'初年度 損益資金計画'!$E$59,'2年目 損益資金計画'!$E$59,'3年目 損益資金計画'!$E$59,'4年目 損益資金計画'!$E$59,'5年目 損益資金計画'!$E$59) -> 0 | F59: =CHOOSE($U$2,'初年度 損益資金計画'!$F$59,'2年目 損益資金計画'!$F$59,'3年目 損益資金計画'!$F$59,'4年目 損益資金計画'!$F$59,'5年目 損益資金計画'!$F$59) -> 0 | G59: =CHOOSE($U$2,'初年度 損益資金計画'!$G$59,'2年目 損益資金計画'!$G$59,'3年目 損益資金計画'!$G$59,'4年目 損益資金計画'!$G$59,'5年目 損益資金計画'!$G$59) -> 0 | H59: =CHOOSE($U$2,'初年度 損益資金計画'!$H$59,'2年目 損益資金計画'!$H$59,'3年目 損益資金計画'!$H$59,'4年目 損益資金計画'!$H$59,'5年目 損益資金計画'!$H$59) -> 0 | I59: =CHOOSE($U$2,'初年度 損益資金計画'!$I$59,'2年目 損益資金計画'!$I$59,'3年目 損益資金計画'!$I$59,'4年目 損益資金計画'!$I$59,'5年目 損益資金計画'!$I$59) -> 0 | J59: =CHOOSE($U$2,'初年度 損益資金計画'!$J$59,'2年目 損益資金計画'!$J$59,'3年目 損益資金計画'!$J$59,'4年目 損益資金計画'!$J$59,'5年目 損益資金計画'!$J$59) -> 0 | K59: =CHOOSE($U$2,'初年度 損益資金計画'!$K$59,'2年目 損益資金計画'!$K$59,'3年目 損益資金計画'!$K$59,'4年目 損益資金計画'!$K$59,'5年目 損益資金計画'!$K$59) -> 0 | L59: =CHOOSE($U$2,'初年度 損益資金計画'!$L$59,'2年目 損益資金計画'!$L$59,'3年目 損益資金計画'!$L$59,'4年目 損益資金計画'!$L$59,'5年目 損益資金計画'!$L$59) -> 0 | M59: =CHOOSE($U$2,'初年度 損益資金計画'!$M$59,'2年目 損益資金計画'!$M$59,'3年目 損益資金計画'!$M$59,'4年目 損益資金計画'!$M$59,'5年目 損益資金計画'!$M$59) -> 0 | N59: =CHOOSE($U$2,'初年度 損益資金計画'!$N$59,'2年目 損益資金計画'!$N$59,'3年目 損益資金計画'!$N$59,'4年目 損益資金計画'!$N$59,'5年目 損益資金計画'!$N$59) -> 0 | O59: =CHOOSE($U$2,'初年度 損益資金計画'!$O$59,'2年目 損益資金計画'!$O$59,'3年目 損益資金計画'!$O$59,'4年目 損益資金計画'!$O$59,'5年目 損益資金計画'!$O$59) -> 0 | P59: =CHOOSE($U$2,'初年度 損益資金計画'!$P$59,'2年目 損益資金計画'!$P$59,'3年目 損益資金計画'!$P$59,'4年目 損益資金計画'!$P$59,'5年目 損益資金計画'!$P$59) -> 0
A60: =CHOOSE($U$2,'初年度 損益資金計画'!$A$60,'2年目 損益資金計画'!$A$60,'3年目 損益資金計画'!$A$60,'4年目 損益資金計画'!$A$60,'5年目 損益資金計画'!$A$60) -> 0 | C60: =CHOOSE($U$2,'初年度 損益資金計画'!$C$60,'2年目 損益資金計画'!$C$60,'3年目 損益資金計画'!$C$60,'4年目 損益資金計画'!$C$60,'5年目 損益資金計画'!$C$60) -> 役員貸付 | D60: =CHOOSE($U$2,'初年度 損益資金計画'!$D$60,'2年目 損益資金計画'!$D$60,'3年目 損益資金計画'!$D$60,'4年目 損益資金計画'!$D$60,'5年目 損益資金計画'!$D$60) -> 0 | E60: =CHOOSE($U$2,'初年度 損益資金計画'!$E$60,'2年目 損益資金計画'!$E$60,'3年目 損益資金計画'!$E$60,'4年目 損益資金計画'!$E$60,'5年目 損益資金計画'!$E$60) -> 0 | F60: =CHOOSE($U$2,'初年度 損益資金計画'!$F$60,'2年目 損益資金計画'!$F$60,'3年目 損益資金計画'!$F$60,'4年目 損益資金計画'!$F$60,'5年目 損益資金計画'!$F$60) -> 0 | G60: =CHOOSE($U$2,'初年度 損益資金計画'!$G$60,'2年目 損益資金計画'!$G$60,'3年目 損益資金計画'!$G$60,'4年目 損益資金計画'!$G$60,'5年目 損益資金計画'!$G$60) -> 0 | H60: =CHOOSE($U$2,'初年度 損益資金計画'!$H$60,'2年目 損益資金計画'!$H$60,'3年目 損益資金計画'!$H$60,'4年目 損益資金計画'!$H$60,'5年目 損益資金計画'!$H$60) -> 0 | I60: =CHOOSE($U$2,'初年度 損益資金計画'!$I$60,'2年目 損益資金計画'!$I$60,'3年目 損益資金計画'!$I$60,'4年目 損益資金計画'!$I$60,'5年目 損益資金計画'!$I$60) -> 0 | J60: =CHOOSE($U$2,'初年度 損益資金計画'!$J$60,'2年目 損益資金計画'!$J$60,'3年目 損益資金計画'!$J$60,'4年目 損益資金計画'!$J$60,'5年目 損益資金計画'!$J$60) -> 0 | K60: =CHOOSE($U$2,'初年度 損益資金計画'!$K$60,'2年目 損益資金計画'!$K$60,'3年目 損益資金計画'!$K$60,'4年目 損益資金計画'!$K$60,'5年目 損益資金計画'!$K$60) -> 0 | L60: =CHOOSE($U$2,'初年度 損益資金計画'!$L$60,'2年目 損益資金計画'!$L$60,'3年目 損益資金計画'!$L$60,'4年目 損益資金計画'!$L$60,'5年目 損益資金計画'!$L$60) -> 0 | M60: =CHOOSE($U$2,'初年度 損益資金計画'!$M$60,'2年目 損益資金計画'!$M$60,'3年目 損益資金計画'!$M$60,'4年目 損益資金計画'!$M$60,'5年目 損益資金計画'!$M$60) -> 0 | N60: =CHOOSE($U$2,'初年度 損益資金計画'!$N$60,'2年目 損益資金計画'!$N$60,'3年目 損益資金計画'!$N$60,'4年目 損益資金計画'!$N$60,'5年目 損益資金計画'!$N$60) -> 0 | O60: =CHOOSE($U$2,'初年度 損益資金計画'!$O$60,'2年目 損益資金計画'!$O$60,'3年目 損益資金計画'!$O$60,'4年目 損益資金計画'!$O$60,'5年目 損益資金計画'!$O$60) -> 0 | P60: =CHOOSE($U$2,'初年度 損益資金計画'!$P$60,'2年目 損益資金計画'!$P$60,'3年目 損益資金計画'!$P$60,'4年目 損益資金計画'!$P$60,'5年目 損益資金計画'!$P$60) -> 0
A61: =CHOOSE($U$2,'初年度 損益資金計画'!$A$61,'2年目 損益資金計画'!$A$61,'3年目 損益資金計画'!$A$61,'4年目 損益資金計画'!$A$61,'5年目 損益資金計画'!$A$61) -> 0 | C61: =CHOOSE($U$2,'初年度 損益資金計画'!$C$61,'2年目 損益資金計画'!$C$61,'3年目 損益資金計画'!$C$61,'4年目 損益資金計画'!$C$61,'5年目 損益資金計画'!$C$61) -> 金融機関借入 | D61: =CHOOSE($U$2,'初年度 損益資金計画'!$D$61,'2年目 損益資金計画'!$D$61,'3年目 損益資金計画'!$D$61,'4年目 損益資金計画'!$D$61,'5年目 損益資金計画'!$D$61) -> 0 | E61: =CHOOSE($U$2,'初年度 損益資金計画'!$E$61,'2年目 損益資金計画'!$E$61,'3年目 損益資金計画'!$E$61,'4年目 損益資金計画'!$E$61,'5年目 損益資金計画'!$E$61) -> 0 | F61: =CHOOSE($U$2,'初年度 損益資金計画'!$F$61,'2年目 損益資金計画'!$F$61,'3年目 損益資金計画'!$F$61,'4年目 損益資金計画'!$F$61,'5年目 損益資金計画'!$F$61) -> 0 | G61: =CHOOSE($U$2,'初年度 損益資金計画'!$G$61,'2年目 損益資金計画'!$G$61,'3年目 損益資金計画'!$G$61,'4年目 損益資金計画'!$G$61,'5年目 損益資金計画'!$G$61) -> 0 | H61: =CHOOSE($U$2,'初年度 損益資金計画'!$H$61,'2年目 損益資金計画'!$H$61,'3年目 損益資金計画'!$H$61,'4年目 損益資金計画'!$H$61,'5年目 損益資金計画'!$H$61) -> 0 | I61: =CHOOSE($U$2,'初年度 損益資金計画'!$I$61,'2年目 損益資金計画'!$I$61,'3年目 損益資金計画'!$I$61,'4年目 損益資金計画'!$I$61,'5年目 損益資金計画'!$I$61) -> 0 | J61: =CHOOSE($U$2,'初年度 損益資金計画'!$J$61,'2年目 損益資金計画'!$J$61,'3年目 損益資金計画'!$J$61,'4年目 損益資金計画'!$J$61,'5年目 損益資金計画'!$J$61) -> 0 | K61: =CHOOSE($U$2,'初年度 損益資金計画'!$K$61,'2年目 損益資金計画'!$K$61,'3年目 損益資金計画'!$K$61,'4年目 損益資金計画'!$K$61,'5年目 損益資金計画'!$K$61) -> 0 | L61: =CHOOSE($U$2,'初年度 損益資金計画'!$L$61,'2年目 損益資金計画'!$L$61,'3年目 損益資金計画'!$L$61,'4年目 損益資金計画'!$L$61,'5年目 損益資金計画'!$L$61) -> 0 | M61: =CHOOSE($U$2,'初年度 損益資金計画'!$M$61,'2年目 損益資金計画'!$M$61,'3年目 損益資金計画'!$M$61,'4年目 損益資金計画'!$M$61,'5年目 損益資金計画'!$M$61) -> 0 | N61: =CHOOSE($U$2,'初年度 損益資金計画'!$N$61,'2年目 損益資金計画'!$N$61,'3年目 損益資金計画'!$N$61,'4年目 損益資金計画'!$N$61,'5年目 損益資金計画'!$N$61) -> 0 | O61: =CHOOSE($U$2,'初年度 損益資金計画'!$O$61,'2年目 損益資金計画'!$O$61,'3年目 損益資金計画'!$O$61,'4年目 損益資金計画'!$O$61,'5年目 損益資金計画'!$O$61) -> 0 | P61: =CHOOSE($U$2,'初年度 損益資金計画'!$P$61,'2年目 損益資金計画'!$P$61,'3年目 損益資金計画'!$P$61,'4年目 損益資金計画'!$P$61,'5年目 損益資金計画'!$P$61) -> 0
A62: =CHOOSE($U$2,'初年度 損益資金計画'!$A$62,'2年目 損益資金計画'!$A$62,'3年目 損益資金計画'!$A$62,'4年目 損益資金計画'!$A$62,'5年目 損益資金計画'!$A$62) -> 0 | C62: =CHOOSE($U$2,'初年度 損益資金計画'!$C$62,'2年目 損益資金計画'!$C$62,'3年目 損益資金計画'!$C$62,'4年目 損益資金計画'!$C$62,'5年目 損益資金計画'!$C$62) -> 私募債 | D62: =CHOOSE($U$2,'初年度 損益資金計画'!$D$62,'2年目 損益資金計画'!$D$62,'3年目 損益資金計画'!$D$62,'4年目 損益資金計画'!$D$62,'5年目 損益資金計画'!$D$62) -> 0 | E62: =CHOOSE($U$2,'初年度 損益資金計画'!$E$62,'2年目 損益資金計画'!$E$62,'3年目 損益資金計画'!$E$62,'4年目 損益資金計画'!$E$62,'5年目 損益資金計画'!$E$62) -> 0 | F62: =CHOOSE($U$2,'初年度 損益資金計画'!$F$62,'2年目 損益資金計画'!$F$62,'3年目 損益資金計画'!$F$62,'4年目 損益資金計画'!$F$62,'5年目 損益資金計画'!$F$62) -> 0 | G62: =CHOOSE($U$2,'初年度 損益資金計画'!$G$62,'2年目 損益資金計画'!$G$62,'3年目 損益資金計画'!$G$62,'4年目 損益資金計画'!$G$62,'5年目 損益資金計画'!$G$62) -> 0 | H62: =CHOOSE($U$2,'初年度 損益資金計画'!$H$62,'2年目 損益資金計画'!$H$62,'3年目 損益資金計画'!$H$62,'4年目 損益資金計画'!$H$62,'5年目 損益資金計画'!$H$62) -> 0 | I62: =CHOOSE($U$2,'初年度 損益資金計画'!$I$62,'2年目 損益資金計画'!$I$62,'3年目 損益資金計画'!$I$62,'4年目 損益資金計画'!$I$62,'5年目 損益資金計画'!$I$62) -> 0 | J62: =CHOOSE($U$2,'初年度 損益資金計画'!$J$62,'2年目 損益資金計画'!$J$62,'3年目 損益資金計画'!$J$62,'4年目 損益資金計画'!$J$62,'5年目 損益資金計画'!$J$62) -> 0 | K62: =CHOOSE($U$2,'初年度 損益資金計画'!$K$62,'2年目 損益資金計画'!$K$62,'3年目 損益資金計画'!$K$62,'4年目 損益資金計画'!$K$62,'5年目 損益資金計画'!$K$62) -> 0 | L62: =CHOOSE($U$2,'初年度 損益資金計画'!$L$62,'2年目 損益資金計画'!$L$62,'3年目 損益資金計画'!$L$62,'4年目 損益資金計画'!$L$62,'5年目 損益資金計画'!$L$62) -> 0 | M62: =CHOOSE($U$2,'初年度 損益資金計画'!$M$62,'2年目 損益資金計画'!$M$62,'3年目 損益資金計画'!$M$62,'4年目 損益資金計画'!$M$62,'5年目 損益資金計画'!$M$62) -> 0 | N62: =CHOOSE($U$2,'初年度 損益資金計画'!$N$62,'2年目 損益資金計画'!$N$62,'3年目 損益資金計画'!$N$62,'4年目 損益資金計画'!$N$62,'5年目 損益資金計画'!$N$62) -> 0 | O62: =CHOOSE($U$2,'初年度 損益資金計画'!$O$62,'2年目 損益資金計画'!$O$62,'3年目 損益資金計画'!$O$62,'4年目 損益資金計画'!$O$62,'5年目 損益資金計画'!$O$62) -> 0 | P62: =CHOOSE($U$2,'初年度 損益資金計画'!$P$62,'2年目 損益資金計画'!$P$62,'3年目 損益資金計画'!$P$62,'4年目 損益資金計画'!$P$62,'5年目 損益資金計画'!$P$62) -> 0
A63: =CHOOSE($U$2,'初年度 損益資金計画'!$A$63,'2年目 損益資金計画'!$A$63,'3年目 損益資金計画'!$A$63,'4年目 損益資金計画'!$A$63,'5年目 損益資金計画'!$A$63) -> 0 | C63: =CHOOSE($U$2,'初年度 損益資金計画'!$C$63,'2年目 損益資金計画'!$C$63,'3年目 損益資金計画'!$C$63,'4年目 損益資金計画'!$C$63,'5年目 損益資金計画'!$C$63) -> 減価償却 | D63: =CHOOSE($U$2,'初年度 損益資金計画'!$D$63,'2年目 損益資金計画'!$D$63,'3年目 損益資金計画'!$D$63,'4年目 損益資金計画'!$D$63,'5年目 損益資金計画'!$D$63) -> 0 | E63: =CHOOSE($U$2,'初年度 損益資金計画'!$E$63,'2年目 損益資金計画'!$E$63,'3年目 損益資金計画'!$E$63,'4年目 損益資金計画'!$E$63,'5年目 損益資金計画'!$E$63) -> 0 | F63: =CHOOSE($U$2,'初年度 損益資金計画'!$F$63,'2年目 損益資金計画'!$F$63,'3年目 損益資金計画'!$F$63,'4年目 損益資金計画'!$F$63,'5年目 損益資金計画'!$F$63) -> 0 | G63: =CHOOSE($U$2,'初年度 損益資金計画'!$G$63,'2年目 損益資金計画'!$G$63,'3年目 損益資金計画'!$G$63,'4年目 損益資金計画'!$G$63,'5年目 損益資金計画'!$G$63) -> 0 | H63: =CHOOSE($U$2,'初年度 損益資金計画'!$H$63,'2年目 損益資金計画'!$H$63,'3年目 損益資金計画'!$H$63,'4年目 損益資金計画'!$H$63,'5年目 損益資金計画'!$H$63) -> 0 | I63: =CHOOSE($U$2,'初年度 損益資金計画'!$I$63,'2年目 損益資金計画'!$I$63,'3年目 損益資金計画'!$I$63,'4年目 損益資金計画'!$I$63,'5年目 損益資金計画'!$I$63) -> 0 | J63: =CHOOSE($U$2,'初年度 損益資金計画'!$J$63,'2年目 損益資金計画'!$J$63,'3年目 損益資金計画'!$J$63,'4年目 損益資金計画'!$J$63,'5年目 損益資金計画'!$J$63) -> 0 | K63: =CHOOSE($U$2,'初年度 損益資金計画'!$K$63,'2年目 損益資金計画'!$K$63,'3年目 損益資金計画'!$K$63,'4年目 損益資金計画'!$K$63,'5年目 損益資金計画'!$K$63) -> 0 | L63: =CHOOSE($U$2,'初年度 損益資金計画'!$L$63,'2年目 損益資金計画'!$L$63,'3年目 損益資金計画'!$L$63,'4年目 損益資金計画'!$L$63,'5年目 損益資金計画'!$L$63) -> 0 | M63: =CHOOSE($U$2,'初年度 損益資金計画'!$M$63,'2年目 損益資金計画'!$M$63,'3年目 損益資金計画'!$M$63,'4年目 損益資金計画'!$M$63,'5年目 損益資金計画'!$M$63) -> 0 | N63: =CHOOSE($U$2,'初年度 損益資金計画'!$N$63,'2年目 損益資金計画'!$N$63,'3年目 損益資金計画'!$N$63,'4年目 損益資金計画'!$N$63,'5年目 損益資金計画'!$N$63) -> 0 | O63: =CHOOSE($U$2,'初年度 損益資金計画'!$O$63,'2年目 損益資金計画'!$O$63,'3年目 損益資金計画'!$O$63,'4年目 損益資金計画'!$O$63,'5年目 損益資金計画'!$O$63) -> 0 | P63: =CHOOSE($U$2,'初年度 損益資金計画'!$P$63,'2年目 損益資金計画'!$P$63,'3年目 損益資金計画'!$P$63,'4年目 損益資金計画'!$P$63,'5年目 損益資金計画'!$P$63) -> 0
A64: =CHOOSE($U$2,'初年度 損益資金計画'!$A$64,'2年目 損益資金計画'!$A$64,'3年目 損益資金計画'!$A$64,'4年目 損益資金計画'!$A$64,'5年目 損益資金計画'!$A$64) -> 0 | C64: =CHOOSE($U$2,'初年度 損益資金計画'!$C$64,'2年目 損益資金計画'!$C$64,'3年目 損益資金計画'!$C$64,'4年目 損益資金計画'!$C$64,'5年目 損益資金計画'!$C$64) -> 補助金 | D64: =CHOOSE($U$2,'初年度 損益資金計画'!$D$64,'2年目 損益資金計画'!$D$64,'3年目 損益資金計画'!$D$64,'4年目 損益資金計画'!$D$64,'5年目 損益資金計画'!$D$64) -> 0 | E64: =CHOOSE($U$2,'初年度 損益資金計画'!$E$64,'2年目 損益資金計画'!$E$64,'3年目 損益資金計画'!$E$64,'4年目 損益資金計画'!$E$64,'5年目 損益資金計画'!$E$64) -> 0 | F64: =CHOOSE($U$2,'初年度 損益資金計画'!$F$64,'2年目 損益資金計画'!$F$64,'3年目 損益資金計画'!$F$64,'4年目 損益資金計画'!$F$64,'5年目 損益資金計画'!$F$64) -> 0 | G64: =CHOOSE($U$2,'初年度 損益資金計画'!$G$64,'2年目 損益資金計画'!$G$64,'3年目 損益資金計画'!$G$64,'4年目 損益資金計画'!$G$64,'5年目 損益資金計画'!$G$64) -> 0 | H64: =CHOOSE($U$2,'初年度 損益資金計画'!$H$64,'2年目 損益資金計画'!$H$64,'3年目 損益資金計画'!$H$64,'4年目 損益資金計画'!$H$64,'5年目 損益資金計画'!$H$64) -> 0 | I64: =CHOOSE($U$2,'初年度 損益資金計画'!$I$64,'2年目 損益資金計画'!$I$64,'3年目 損益資金計画'!$I$64,'4年目 損益資金計画'!$I$64,'5年目 損益資金計画'!$I$64) -> 0 | J64: =CHOOSE($U$2,'初年度 損益資金計画'!$J$64,'2年目 損益資金計画'!$J$64,'3年目 損益資金計画'!$J$64,'4年目 損益資金計画'!$J$64,'5年目 損益資金計画'!$J$64) -> 0 | K64: =CHOOSE($U$2,'初年度 損益資金計画'!$K$64,'2年目 損益資金計画'!$K$64,'3年目 損益資金計画'!$K$64,'4年目 損益資金計画'!$K$64,'5年目 損益資金計画'!$K$64) -> 0 | L64: =CHOOSE($U$2,'初年度 損益資金計画'!$L$64,'2年目 損益資金計画'!$L$64,'3年目 損益資金計画'!$L$64,'4年目 損益資金計画'!$L$64,'5年目 損益資金計画'!$L$64) -> 0 | M64: =CHOOSE($U$2,'初年度 損益資金計画'!$M$64,'2年目 損益資金計画'!$M$64,'3年目 損益資金計画'!$M$64,'4年目 損益資金計画'!$M$64,'5年目 損益資金計画'!$M$64) -> 0 | N64: =CHOOSE($U$2,'初年度 損益資金計画'!$N$64,'2年目 損益資金計画'!$N$64,'3年目 損益資金計画'!$N$64,'4年目 損益資金計画'!$N$64,'5年目 損益資金計画'!$N$64) -> 0 | O64: =CHOOSE($U$2,'初年度 損益資金計画'!$O$64,'2年目 損益資金計画'!$O$64,'3年目 損益資金計画'!$O$64,'4年目 損益資金計画'!$O$64,'5年目 損益資金計画'!$O$64) -> 0 | P64: =CHOOSE($U$2,'初年度 損益資金計画'!$P$64,'2年目 損益資金計画'!$P$64,'3年目 損益資金計画'!$P$64,'4年目 損益資金計画'!$P$64,'5年目 損益資金計画'!$P$64) -> 0
A65: =CHOOSE($U$2,'初年度 損益資金計画'!$A$65,'2年目 損益資金計画'!$A$65,'3年目 損益資金計画'!$A$65,'4年目 損益資金計画'!$A$65,'5年目 損益資金計画'!$A$65) -> 0 | B65: =CHOOSE($U$2,'初年度 損益資金計画'!$B$65,'2年目 損益資金計画'!$B$65,'3年目 損益資金計画'!$B$65,'4年目 損益資金計画'!$B$65,'5年目 損益資金計画'!$B$65) -> 財務支出 | D65: =CHOOSE($U$2,'初年度 損益資金計画'!$D$65,'2年目 損益資金計画'!$D$65,'3年目 損益資金計画'!$D$65,'4年目 損益資金計画'!$D$65,'5年目 損益資金計画'!$D$65) -> 0 | E65: =CHOOSE($U$2,'初年度 損益資金計画'!$E$65,'2年目 損益資金計画'!$E$65,'3年目 損益資金計画'!$E$65,'4年目 損益資金計画'!$E$65,'5年目 損益資金計画'!$E$65) -> 0 | F65: =CHOOSE($U$2,'初年度 損益資金計画'!$F$65,'2年目 損益資金計画'!$F$65,'3年目 損益資金計画'!$F$65,'4年目 損益資金計画'!$F$65,'5年目 損益資金計画'!$F$65) -> 0 | G65: =CHOOSE($U$2,'初年度 損益資金計画'!$G$65,'2年目 損益資金計画'!$G$65,'3年目 損益資金計画'!$G$65,'4年目 損益資金計画'!$G$65,'5年目 損益資金計画'!$G$65) -> 0 | H65: =CHOOSE($U$2,'初年度 損益資金計画'!$H$65,'2年目 損益資金計画'!$H$65,'3年目 損益資金計画'!$H$65,'4年目 損益資金計画'!$H$65,'5年目 損益資金計画'!$H$65) -> 0 | I65: =CHOOSE($U$2,'初年度 損益資金計画'!$I$65,'2年目 損益資金計画'!$I$65,'3年目 損益資金計画'!$I$65,'4年目 損益資金計画'!$I$65,'5年目 損益資金計画'!$I$65) -> 0 | J65: =CHOOSE($U$2,'初年度 損益資金計画'!$J$65,'2年目 損益資金計画'!$J$65,'3年目 損益資金計画'!$J$65,'4年目 損益資金計画'!$J$65,'5年目 損益資金計画'!$J$65) -> 0 | K65: =CHOOSE($U$2,'初年度 損益資金計画'!$K$65,'2年目 損益資金計画'!$K$65,'3年目 損益資金計画'!$K$65,'4年目 損益資金計画'!$K$65,'5年目 損益資金計画'!$K$65) -> 0 | L65: =CHOOSE($U$2,'初年度 損益資金計画'!$L$65,'2年目 損益資金計画'!$L$65,'3年目 損益資金計画'!$L$65,'4年目 損益資金計画'!$L$65,'5年目 損益資金計画'!$L$65) -> 0 | M65: =CHOOSE($U$2,'初年度 損益資金計画'!$M$65,'2年目 損益資金計画'!$M$65,'3年目 損益資金計画'!$M$65,'4年目 損益資金計画'!$M$65,'5年目 損益資金計画'!$M$65) -> 0 | N65: =CHOOSE($U$2,'初年度 損益資金計画'!$N$65,'2年目 損益資金計画'!$N$65,'3年目 損益資金計画'!$N$65,'4年目 損益資金計画'!$N$65,'5年目 損益資金計画'!$N$65) -> 0 | O65: =CHOOSE($U$2,'初年度 損益資金計画'!$O$65,'2年目 損益資金計画'!$O$65,'3年目 損益資金計画'!$O$65,'4年目 損益資金計画'!$O$65,'5年目 損益資金計画'!$O$65) -> 0 | P65: =CHOOSE($U$2,'初年度 損益資金計画'!$P$65,'2年目 損益資金計画'!$P$65,'3年目 損益資金計画'!$P$65,'4年目 損益資金計画'!$P$65,'5年目 損益資金計画'!$P$65) -> 0
A66: =CHOOSE($U$2,'初年度 損益資金計画'!$A$66,'2年目 損益資金計画'!$A$66,'3年目 損益資金計画'!$A$66,'4年目 損益資金計画'!$A$66,'5年目 損益資金計画'!$A$66) -> 0 | B66: =CHOOSE($U$2,'初年度 損益資金計画'!$B$66,'2年目 損益資金計画'!$B$66,'3年目 損益資金計画'!$B$66,'4年目 損益資金計画'!$B$66,'5年目 損益資金計画'!$B$66) -> 0 | C66: =CHOOSE($U$2,'初年度 損益資金計画'!$C$66,'2年目 損益資金計画'!$C$66,'3年目 損益資金計画'!$C$66,'4年目 損益資金計画'!$C$66,'5年目 損益資金計画'!$C$66) -> 営業権買取等 | D66: =CHOOSE($U$2,'初年度 損益資金計画'!$D$66,'2年目 損益資金計画'!$D$66,'3年目 損益資金計画'!$D$66,'4年目 損益資金計画'!$D$66,'5年目 損益資金計画'!$D$66) -> 0 | E66: =CHOOSE($U$2,'初年度 損益資金計画'!$E$66,'2年目 損益資金計画'!$E$66,'3年目 損益資金計画'!$E$66,'4年目 損益資金計画'!$E$66,'5年目 損益資金計画'!$E$66) -> 0 | F66: =CHOOSE($U$2,'初年度 損益資金計画'!$F$66,'2年目 損益資金計画'!$F$66,'3年目 損益資金計画'!$F$66,'4年目 損益資金計画'!$F$66,'5年目 損益資金計画'!$F$66) -> 0 | G66: =CHOOSE($U$2,'初年度 損益資金計画'!$G$66,'2年目 損益資金計画'!$G$66,'3年目 損益資金計画'!$G$66,'4年目 損益資金計画'!$G$66,'5年目 損益資金計画'!$G$66) -> 0 | H66: =CHOOSE($U$2,'初年度 損益資金計画'!$H$66,'2年目 損益資金計画'!$H$66,'3年目 損益資金計画'!$H$66,'4年目 損益資金計画'!$H$66,'5年目 損益資金計画'!$H$66) -> 0 | I66: =CHOOSE($U$2,'初年度 損益資金計画'!$I$66,'2年目 損益資金計画'!$I$66,'3年目 損益資金計画'!$I$66,'4年目 損益資金計画'!$I$66,'5年目 損益資金計画'!$I$66) -> 0 | J66: =CHOOSE($U$2,'初年度 損益資金計画'!$J$66,'2年目 損益資金計画'!$J$66,'3年目 損益資金計画'!$J$66,'4年目 損益資金計画'!$J$66,'5年目 損益資金計画'!$J$66) -> 0 | K66: =CHOOSE($U$2,'初年度 損益資金計画'!$K$66,'2年目 損益資金計画'!$K$66,'3年目 損益資金計画'!$K$66,'4年目 損益資金計画'!$K$66,'5年目 損益資金計画'!$K$66) -> 0 | L66: =CHOOSE($U$2,'初年度 損益資金計画'!$L$66,'2年目 損益資金計画'!$L$66,'3年目 損益資金計画'!$L$66,'4年目 損益資金計画'!$L$66,'5年目 損益資金計画'!$L$66) -> 0 | M66: =CHOOSE($U$2,'初年度 損益資金計画'!$M$66,'2年目 損益資金計画'!$M$66,'3年目 損益資金計画'!$M$66,'4年目 損益資金計画'!$M$66,'5年目 損益資金計画'!$M$66) -> 0 | N66: =CHOOSE($U$2,'初年度 損益資金計画'!$N$66,'2年目 損益資金計画'!$N$66,'3年目 損益資金計画'!$N$66,'4年目 損益資金計画'!$N$66,'5年目 損益資金計画'!$N$66) -> 0 | O66: =CHOOSE($U$2,'初年度 損益資金計画'!$O$66,'2年目 損益資金計画'!$O$66,'3年目 損益資金計画'!$O$66,'4年目 損益資金計画'!$O$66,'5年目 損益資金計画'!$O$66) -> 0 | P66: =CHOOSE($U$2,'初年度 損益資金計画'!$P$66,'2年目 損益資金計画'!$P$66,'3年目 損益資金計画'!$P$66,'4年目 損益資金計画'!$P$66,'5年目 損益資金計画'!$P$66) -> 0
A67: =CHOOSE($U$2,'初年度 損益資金計画'!$A$67,'2年目 損益資金計画'!$A$67,'3年目 損益資金計画'!$A$67,'4年目 損益資金計画'!$A$67,'5年目 損益資金計画'!$A$67) -> 0 | C67: =CHOOSE($U$2,'初年度 損益資金計画'!$C$67,'2年目 損益資金計画'!$C$67,'3年目 損益資金計画'!$C$67,'4年目 損益資金計画'!$C$67,'5年目 損益資金計画'!$C$67) -> 金融機関返済 | D67: =CHOOSE($U$2,'初年度 損益資金計画'!$D$67,'2年目 損益資金計画'!$D$67,'3年目 損益資金計画'!$D$67,'4年目 損益資金計画'!$D$67,'5年目 損益資金計画'!$D$67) -> 0 | E67: =CHOOSE($U$2,'初年度 損益資金計画'!$E$67,'2年目 損益資金計画'!$E$67,'3年目 損益資金計画'!$E$67,'4年目 損益資金計画'!$E$67,'5年目 損益資金計画'!$E$67) -> 0 | F67: =CHOOSE($U$2,'初年度 損益資金計画'!$F$67,'2年目 損益資金計画'!$F$67,'3年目 損益資金計画'!$F$67,'4年目 損益資金計画'!$F$67,'5年目 損益資金計画'!$F$67) -> 0 | G67: =CHOOSE($U$2,'初年度 損益資金計画'!$G$67,'2年目 損益資金計画'!$G$67,'3年目 損益資金計画'!$G$67,'4年目 損益資金計画'!$G$67,'5年目 損益資金計画'!$G$67) -> 0 | H67: =CHOOSE($U$2,'初年度 損益資金計画'!$H$67,'2年目 損益資金計画'!$H$67,'3年目 損益資金計画'!$H$67,'4年目 損益資金計画'!$H$67,'5年目 損益資金計画'!$H$67) -> 0 | I67: =CHOOSE($U$2,'初年度 損益資金計画'!$I$67,'2年目 損益資金計画'!$I$67,'3年目 損益資金計画'!$I$67,'4年目 損益資金計画'!$I$67,'5年目 損益資金計画'!$I$67) -> 0 | J67: =CHOOSE($U$2,'初年度 損益資金計画'!$J$67,'2年目 損益資金計画'!$J$67,'3年目 損益資金計画'!$J$67,'4年目 損益資金計画'!$J$67,'5年目 損益資金計画'!$J$67) -> 0 | K67: =CHOOSE($U$2,'初年度 損益資金計画'!$K$67,'2年目 損益資金計画'!$K$67,'3年目 損益資金計画'!$K$67,'4年目 損益資金計画'!$K$67,'5年目 損益資金計画'!$K$67) -> 0 | L67: =CHOOSE($U$2,'初年度 損益資金計画'!$L$67,'2年目 損益資金計画'!$L$67,'3年目 損益資金計画'!$L$67,'4年目 損益資金計画'!$L$67,'5年目 損益資金計画'!$L$67) -> 0 | M67: =CHOOSE($U$2,'初年度 損益資金計画'!$M$67,'2年目 損益資金計画'!$M$67,'3年目 損益資金計画'!$M$67,'4年目 損益資金計画'!$M$67,'5年目 損益資金計画'!$M$67) -> 0 | N67: =CHOOSE($U$2,'初年度 損益資金計画'!$N$67,'2年目 損益資金計画'!$N$67,'3年目 損益資金計画'!$N$67,'4年目 損益資金計画'!$N$67,'5年目 損益資金計画'!$N$67) -> 0 | O67: =CHOOSE($U$2,'初年度 損益資金計画'!$O$67,'2年目 損益資金計画'!$O$67,'3年目 損益資金計画'!$O$67,'4年目 損益資金計画'!$O$67,'5年目 損益資金計画'!$O$67) -> 0 | P67: =CHOOSE($U$2,'初年度 損益資金計画'!$P$67,'2年目 損益資金計画'!$P$67,'3年目 損益資金計画'!$P$67,'4年目 損益資金計画'!$P$67,'5年目 損益資金計画'!$P$67) -> 0
A68: =CHOOSE($U$2,'初年度 損益資金計画'!$A$68,'2年目 損益資金計画'!$A$68,'3年目 損益資金計画'!$A$68,'4年目 損益資金計画'!$A$68,'5年目 損益資金計画'!$A$68) -> 0 | C68: =CHOOSE($U$2,'初年度 損益資金計画'!$C$68,'2年目 損益資金計画'!$C$68,'3年目 損益資金計画'!$C$68,'4年目 損益資金計画'!$C$68,'5年目 損益資金計画'!$C$68) -> 店舗出店コスト | D68: =CHOOSE($U$2,'初年度 損益資金計画'!$D$68,'2年目 損益資金計画'!$D$68,'3年目 損益資金計画'!$D$68,'4年目 損益資金計画'!$D$68,'5年目 損益資金計画'!$D$68) -> 0 | E68: =CHOOSE($U$2,'初年度 損益資金計画'!$E$68,'2年目 損益資金計画'!$E$68,'3年目 損益資金計画'!$E$68,'4年目 損益資金計画'!$E$68,'5年目 損益資金計画'!$E$68) -> 0 | F68: =CHOOSE($U$2,'初年度 損益資金計画'!$F$68,'2年目 損益資金計画'!$F$68,'3年目 損益資金計画'!$F$68,'4年目 損益資金計画'!$F$68,'5年目 損益資金計画'!$F$68) -> 0 | G68: =CHOOSE($U$2,'初年度 損益資金計画'!$G$68,'2年目 損益資金計画'!$G$68,'3年目 損益資金計画'!$G$68,'4年目 損益資金計画'!$G$68,'5年目 損益資金計画'!$G$68) -> 0 | H68: =CHOOSE($U$2,'初年度 損益資金計画'!$H$68,'2年目 損益資金計画'!$H$68,'3年目 損益資金計画'!$H$68,'4年目 損益資金計画'!$H$68,'5年目 損益資金計画'!$H$68) -> 0 | I68: =CHOOSE($U$2,'初年度 損益資金計画'!$I$68,'2年目 損益資金計画'!$I$68,'3年目 損益資金計画'!$I$68,'4年目 損益資金計画'!$I$68,'5年目 損益資金計画'!$I$68) -> 0 | J68: =CHOOSE($U$2,'初年度 損益資金計画'!$J$68,'2年目 損益資金計画'!$J$68,'3年目 損益資金計画'!$J$68,'4年目 損益資金計画'!$J$68,'5年目 損益資金計画'!$J$68) -> 0 | K68: =CHOOSE($U$2,'初年度 損益資金計画'!$K$68,'2年目 損益資金計画'!$K$68,'3年目 損益資金計画'!$K$68,'4年目 損益資金計画'!$K$68,'5年目 損益資金計画'!$K$68) -> 0 | L68: =CHOOSE($U$2,'初年度 損益資金計画'!$L$68,'2年目 損益資金計画'!$L$68,'3年目 損益資金計画'!$L$68,'4年目 損益資金計画'!$L$68,'5年目 損益資金計画'!$L$68) -> 0 | M68: =CHOOSE($U$2,'初年度 損益資金計画'!$M$68,'2年目 損益資金計画'!$M$68,'3年目 損益資金計画'!$M$68,'4年目 損益資金計画'!$M$68,'5年目 損益資金計画'!$M$68) -> 0 | N68: =CHOOSE($U$2,'初年度 損益資金計画'!$N$68,'2年目 損益資金計画'!$N$68,'3年目 損益資金計画'!$N$68,'4年目 損益資金計画'!$N$68,'5年目 損益資金計画'!$N$68) -> 0 | O68: =CHOOSE($U$2,'初年度 損益資金計画'!$O$68,'2年目 損益資金計画'!$O$68,'3年目 損益資金計画'!$O$68,'4年目 損益資金計画'!$O$68,'5年目 損益資金計画'!$O$68) -> 0 | P68: =CHOOSE($U$2,'初年度 損益資金計画'!$P$68,'2年目 損益資金計画'!$P$68,'3年目 損益資金計画'!$P$68,'4年目 損益資金計画'!$P$68,'5年目 損益資金計画'!$P$68) -> 0
A69: =CHOOSE($U$2,'初年度 損益資金計画'!$A$69,'2年目 損益資金計画'!$A$69,'3年目 損益資金計画'!$A$69,'4年目 損益資金計画'!$A$69,'5年目 損益資金計画'!$A$69) -> 0 | C69: =CHOOSE($U$2,'初年度 損益資金計画'!$C$69,'2年目 損益資金計画'!$C$69,'3年目 損益資金計画'!$C$69,'4年目 損益資金計画'!$C$69,'5年目 損益資金計画'!$C$69) -> その他 | D69: =CHOOSE($U$2,'初年度 損益資金計画'!$D$69,'2年目 損益資金計画'!$D$69,'3年目 損益資金計画'!$D$69,'4年目 損益資金計画'!$D$69,'5年目 損益資金計画'!$D$69) -> 0 | E69: =CHOOSE($U$2,'初年度 損益資金計画'!$E$69,'2年目 損益資金計画'!$E$69,'3年目 損益資金計画'!$E$69,'4年目 損益資金計画'!$E$69,'5年目 損益資金計画'!$E$69) -> 0 | F69: =CHOOSE($U$2,'初年度 損益資金計画'!$F$69,'2年目 損益資金計画'!$F$69,'3年目 損益資金計画'!$F$69,'4年目 損益資金計画'!$F$69,'5年目 損益資金計画'!$F$69) -> 0 | G69: =CHOOSE($U$2,'初年度 損益資金計画'!$G$69,'2年目 損益資金計画'!$G$69,'3年目 損益資金計画'!$G$69,'4年目 損益資金計画'!$G$69,'5年目 損益資金計画'!$G$69) -> 0 | H69: =CHOOSE($U$2,'初年度 損益資金計画'!$H$69,'2年目 損益資金計画'!$H$69,'3年目 損益資金計画'!$H$69,'4年目 損益資金計画'!$H$69,'5年目 損益資金計画'!$H$69) -> 0 | I69: =CHOOSE($U$2,'初年度 損益資金計画'!$I$69,'2年目 損益資金計画'!$I$69,'3年目 損益資金計画'!$I$69,'4年目 損益資金計画'!$I$69,'5年目 損益資金計画'!$I$69) -> 0 | J69: =CHOOSE($U$2,'初年度 損益資金計画'!$J$69,'2年目 損益資金計画'!$J$69,'3年目 損益資金計画'!$J$69,'4年目 損益資金計画'!$J$69,'5年目 損益資金計画'!$J$69) -> 0 | K69: =CHOOSE($U$2,'初年度 損益資金計画'!$K$69,'2年目 損益資金計画'!$K$69,'3年目 損益資金計画'!$K$69,'4年目 損益資金計画'!$K$69,'5年目 損益資金計画'!$K$69) -> 0 | L69: =CHOOSE($U$2,'初年度 損益資金計画'!$L$69,'2年目 損益資金計画'!$L$69,'3年目 損益資金計画'!$L$69,'4年目 損益資金計画'!$L$69,'5年目 損益資金計画'!$L$69) -> 0 | M69: =CHOOSE($U$2,'初年度 損益資金計画'!$M$69,'2年目 損益資金計画'!$M$69,'3年目 損益資金計画'!$M$69,'4年目 損益資金計画'!$M$69,'5年目 損益資金計画'!$M$69) -> 0 | N69: =CHOOSE($U$2,'初年度 損益資金計画'!$N$69,'2年目 損益資金計画'!$N$69,'3年目 損益資金計画'!$N$69,'4年目 損益資金計画'!$N$69,'5年目 損益資金計画'!$N$69) -> 0 | O69: =CHOOSE($U$2,'初年度 損益資金計画'!$O$69,'2年目 損益資金計画'!$O$69,'3年目 損益資金計画'!$O$69,'4年目 損益資金計画'!$O$69,'5年目 損益資金計画'!$O$69) -> 0 | P69: =CHOOSE($U$2,'初年度 損益資金計画'!$P$69,'2年目 損益資金計画'!$P$69,'3年目 損益資金計画'!$P$69,'4年目 損益資金計画'!$P$69,'5年目 損益資金計画'!$P$69) -> 0
A70: =CHOOSE($U$2,'初年度 損益資金計画'!$A$70,'2年目 損益資金計画'!$A$70,'3年目 損益資金計画'!$A$70,'4年目 損益資金計画'!$A$70,'5年目 損益資金計画'!$A$70) -> 0 | C70: =CHOOSE($U$2,'初年度 損益資金計画'!$C$70,'2年目 損益資金計画'!$C$70,'3年目 損益資金計画'!$C$70,'4年目 損益資金計画'!$C$70,'5年目 損益資金計画'!$C$70) -> 0 | D70: =CHOOSE($U$2,'初年度 損益資金計画'!$D$70,'2年目 損益資金計画'!$D$70,'3年目 損益資金計画'!$D$70,'4年目 損益資金計画'!$D$70,'5年目 損益資金計画'!$D$70) -> 0 | E70: =CHOOSE($U$2,'初年度 損益資金計画'!$E$70,'2年目 損益資金計画'!$E$70,'3年目 損益資金計画'!$E$70,'4年目 損益資金計画'!$E$70,'5年目 損益資金計画'!$E$70) -> 0 | F70: =CHOOSE($U$2,'初年度 損益資金計画'!$F$70,'2年目 損益資金計画'!$F$70,'3年目 損益資金計画'!$F$70,'4年目 損益資金計画'!$F$70,'5年目 損益資金計画'!$F$70) -> 0 | G70: =CHOOSE($U$2,'初年度 損益資金計画'!$G$70,'2年目 損益資金計画'!$G$70,'3年目 損益資金計画'!$G$70,'4年目 損益資金計画'!$G$70,'5年目 損益資金計画'!$G$70) -> 0 | H70: =CHOOSE($U$2,'初年度 損益資金計画'!$H$70,'2年目 損益資金計画'!$H$70,'3年目 損益資金計画'!$H$70,'4年目 損益資金計画'!$H$70,'5年目 損益資金計画'!$H$70) -> 0 | I70: =CHOOSE($U$2,'初年度 損益資金計画'!$I$70,'2年目 損益資金計画'!$I$70,'3年目 損益資金計画'!$I$70,'4年目 損益資金計画'!$I$70,'5年目 損益資金計画'!$I$70) -> 0 | J70: =CHOOSE($U$2,'初年度 損益資金計画'!$J$70,'2年目 損益資金計画'!$J$70,'3年目 損益資金計画'!$J$70,'4年目 損益資金計画'!$J$70,'5年目 損益資金計画'!$J$70) -> 0 | K70: =CHOOSE($U$2,'初年度 損益資金計画'!$K$70,'2年目 損益資金計画'!$K$70,'3年目 損益資金計画'!$K$70,'4年目 損益資金計画'!$K$70,'5年目 損益資金計画'!$K$70) -> 0 | L70: =CHOOSE($U$2,'初年度 損益資金計画'!$L$70,'2年目 損益資金計画'!$L$70,'3年目 損益資金計画'!$L$70,'4年目 損益資金計画'!$L$70,'5年目 損益資金計画'!$L$70) -> 0 | M70: =CHOOSE($U$2,'初年度 損益資金計画'!$M$70,'2年目 損益資金計画'!$M$70,'3年目 損益資金計画'!$M$70,'4年目 損益資金計画'!$M$70,'5年目 損益資金計画'!$M$70) -> 0 | N70: =CHOOSE($U$2,'初年度 損益資金計画'!$N$70,'2年目 損益資金計画'!$N$70,'3年目 損益資金計画'!$N$70,'4年目 損益資金計画'!$N$70,'5年目 損益資金計画'!$N$70) -> 0 | O70: =CHOOSE($U$2,'初年度 損益資金計画'!$O$70,'2年目 損益資金計画'!$O$70,'3年目 損益資金計画'!$O$70,'4年目 損益資金計画'!$O$70,'5年目 損益資金計画'!$O$70) -> 0 | P70: =CHOOSE($U$2,'初年度 損益資金計画'!$P$70,'2年目 損益資金計画'!$P$70,'3年目 損益資金計画'!$P$70,'4年目 損益資金計画'!$P$70,'5年目 損益資金計画'!$P$70) -> 0
A71: =CHOOSE($U$2,'初年度 損益資金計画'!$A$71,'2年目 損益資金計画'!$A$71,'3年目 損益資金計画'!$A$71,'4年目 損益資金計画'!$A$71,'5年目 損益資金計画'!$A$71) -> 0 | B71: =CHOOSE($U$2,'初年度 損益資金計画'!$B$71,'2年目 損益資金計画'!$B$71,'3年目 損益資金計画'!$B$71,'4年目 損益資金計画'!$B$71,'5年目 損益資金計画'!$B$71) -> 税金 | D71: =CHOOSE($U$2,'初年度 損益資金計画'!$D$71,'2年目 損益資金計画'!$D$71,'3年目 損益資金計画'!$D$71,'4年目 損益資金計画'!$D$71,'5年目 損益資金計画'!$D$71) -> 0 | E71: =CHOOSE($U$2,'初年度 損益資金計画'!$E$71,'2年目 損益資金計画'!$E$71,'3年目 損益資金計画'!$E$71,'4年目 損益資金計画'!$E$71,'5年目 損益資金計画'!$E$71) -> 0 | F71: =CHOOSE($U$2,'初年度 損益資金計画'!$F$71,'2年目 損益資金計画'!$F$71,'3年目 損益資金計画'!$F$71,'4年目 損益資金計画'!$F$71,'5年目 損益資金計画'!$F$71) -> 0 | G71: =CHOOSE($U$2,'初年度 損益資金計画'!$G$71,'2年目 損益資金計画'!$G$71,'3年目 損益資金計画'!$G$71,'4年目 損益資金計画'!$G$71,'5年目 損益資金計画'!$G$71) -> 0 | H71: =CHOOSE($U$2,'初年度 損益資金計画'!$H$71,'2年目 損益資金計画'!$H$71,'3年目 損益資金計画'!$H$71,'4年目 損益資金計画'!$H$71,'5年目 損益資金計画'!$H$71) -> 0 | I71: =CHOOSE($U$2,'初年度 損益資金計画'!$I$71,'2年目 損益資金計画'!$I$71,'3年目 損益資金計画'!$I$71,'4年目 損益資金計画'!$I$71,'5年目 損益資金計画'!$I$71) -> 0 | J71: =CHOOSE($U$2,'初年度 損益資金計画'!$J$71,'2年目 損益資金計画'!$J$71,'3年目 損益資金計画'!$J$71,'4年目 損益資金計画'!$J$71,'5年目 損益資金計画'!$J$71) -> 0 | K71: =CHOOSE($U$2,'初年度 損益資金計画'!$K$71,'2年目 損益資金計画'!$K$71,'3年目 損益資金計画'!$K$71,'4年目 損益資金計画'!$K$71,'5年目 損益資金計画'!$K$71) -> 0 | L71: =CHOOSE($U$2,'初年度 損益資金計画'!$L$71,'2年目 損益資金計画'!$L$71,'3年目 損益資金計画'!$L$71,'4年目 損益資金計画'!$L$71,'5年目 損益資金計画'!$L$71) -> 0 | M71: =CHOOSE($U$2,'初年度 損益資金計画'!$M$71,'2年目 損益資金計画'!$M$71,'3年目 損益資金計画'!$M$71,'4年目 損益資金計画'!$M$71,'5年目 損益資金計画'!$M$71) -> 0 | N71: =CHOOSE($U$2,'初年度 損益資金計画'!$N$71,'2年目 損益資金計画'!$N$71,'3年目 損益資金計画'!$N$71,'4年目 損益資金計画'!$N$71,'5年目 損益資金計画'!$N$71) -> 0 | O71: =CHOOSE($U$2,'初年度 損益資金計画'!$O$71,'2年目 損益資金計画'!$O$71,'3年目 損益資金計画'!$O$71,'4年目 損益資金計画'!$O$71,'5年目 損益資金計画'!$O$71) -> 3674268 | P71: =CHOOSE($U$2,'初年度 損益資金計画'!$P$71,'2年目 損益資金計画'!$P$71,'3年目 損益資金計画'!$P$71,'4年目 損益資金計画'!$P$71,'5年目 損益資金計画'!$P$71) -> 0
A72: =CHOOSE($U$2,'初年度 損益資金計画'!$A$72,'2年目 損益資金計画'!$A$72,'3年目 損益資金計画'!$A$72,'4年目 損益資金計画'!$A$72,'5年目 損益資金計画'!$A$72) -> 0 | B72: =CHOOSE($U$2,'初年度 損益資金計画'!$B$72,'2年目 損益資金計画'!$B$72,'3年目 損益資金計画'!$B$72,'4年目 損益資金計画'!$B$72,'5年目 損益資金計画'!$B$72) -> 翌月繰越 | D72: =CHOOSE($U$2,'初年度 損益資金計画'!$D$72,'2年目 損益資金計画'!$D$72,'3年目 損益資金計画'!$D$72,'4年目 損益資金計画'!$D$72,'5年目 損益資金計画'!$D$72) -> -3371900 | E72: =CHOOSE($U$2,'初年度 損益資金計画'!$E$72,'2年目 損益資金計画'!$E$72,'3年目 損益資金計画'!$E$72,'4年目 損益資金計画'!$E$72,'5年目 損益資金計画'!$E$72) -> -4167830 | F72: =CHOOSE($U$2,'初年度 損益資金計画'!$F$72,'2年目 損益資金計画'!$F$72,'3年目 損益資金計画'!$F$72,'4年目 損益資金計画'!$F$72,'5年目 損益資金計画'!$F$72) -> -4369360 | G72: =CHOOSE($U$2,'初年度 損益資金計画'!$G$72,'2年目 損益資金計画'!$G$72,'3年目 損益資金計画'!$G$72,'4年目 損益資金計画'!$G$72,'5年目 損益資金計画'!$G$72) -> -4109490 | H72: =CHOOSE($U$2,'初年度 損益資金計画'!$H$72,'2年目 損益資金計画'!$H$72,'3年目 損益資金計画'!$H$72,'4年目 損益資金計画'!$H$72,'5年目 損益資金計画'!$H$72) -> -3402120 | I72: =CHOOSE($U$2,'初年度 損益資金計画'!$I$72,'2年目 損益資金計画'!$I$72,'3年目 損益資金計画'!$I$72,'4年目 損益資金計画'!$I$72,'5年目 損益資金計画'!$I$72) -> -2652850 | J72: =CHOOSE($U$2,'初年度 損益資金計画'!$J$72,'2年目 損益資金計画'!$J$72,'3年目 損益資金計画'!$J$72,'4年目 損益資金計画'!$J$72,'5年目 損益資金計画'!$J$72) -> -1595880 | K72: =CHOOSE($U$2,'初年度 損益資金計画'!$K$72,'2年目 損益資金計画'!$K$72,'3年目 損益資金計画'!$K$72,'4年目 損益資金計画'!$K$72,'5年目 損益資金計画'!$K$72) -> -259310 | L72: =CHOOSE($U$2,'初年度 損益資金計画'!$L$72,'2年目 損益資金計画'!$L$72,'3年目 損益資金計画'!$L$72,'4年目 損益資金計画'!$L$72,'5年目 損益資金計画'!$L$72) -> 1224160 | M72: =CHOOSE($U$2,'初年度 損益資金計画'!$M$72,'2年目 損益資金計画'!$M$72,'3年目 損益資金計画'!$M$72,'4年目 損益資金計画'!$M$72,'5年目 損益資金計画'!$M$72) -> 1950430 | N72: =CHOOSE($U$2,'初年度 損益資金計画'!$N$72,'2年目 損益資金計画'!$N$72,'3年目 損益資金計画'!$N$72,'4年目 損益資金計画'!$N$72,'5年目 損益資金計画'!$N$72) -> 3405800 | O72: =CHOOSE($U$2,'初年度 損益資金計画'!$O$72,'2年目 損益資金計画'!$O$72,'3年目 損益資金計画'!$O$72,'4年目 損益資金計画'!$O$72,'5年目 損益資金計画'!$O$72) -> 1152002 | P72: =CHOOSE($U$2,'初年度 損益資金計画'!$P$72,'2年目 損益資金計画'!$P$72,'3年目 損益資金計画'!$P$72,'4年目 損益資金計画'!$P$72,'5年目 損益資金計画'!$P$72) -> 0
A73: =CHOOSE($U$2,'初年度 損益資金計画'!$A$73,'2年目 損益資金計画'!$A$73,'3年目 損益資金計画'!$A$73,'4年目 損益資金計画'!$A$73,'5年目 損益資金計画'!$A$73) -> 0 | B73: =CHOOSE($U$2,'初年度 損益資金計画'!$B$73,'2年目 損益資金計画'!$B$73,'3年目 損益資金計画'!$B$73,'4年目 損益資金計画'!$B$73,'5年目 損益資金計画'!$B$73) -> 0 | D73: =CHOOSE($U$2,'初年度 損益資金計画'!$D$73,'2年目 損益資金計画'!$D$73,'3年目 損益資金計画'!$D$73,'4年目 損益資金計画'!$D$73,'5年目 損益資金計画'!$D$73) -> 0 | E73: =CHOOSE($U$2,'初年度 損益資金計画'!$E$73,'2年目 損益資金計画'!$E$73,'3年目 損益資金計画'!$E$73,'4年目 損益資金計画'!$E$73,'5年目 損益資金計画'!$E$73) -> 0 | F73: =CHOOSE($U$2,'初年度 損益資金計画'!$F$73,'2年目 損益資金計画'!$F$73,'3年目 損益資金計画'!$F$73,'4年目 損益資金計画'!$F$73,'5年目 損益資金計画'!$F$73) -> 0 | G73: =CHOOSE($U$2,'初年度 損益資金計画'!$G$73,'2年目 損益資金計画'!$G$73,'3年目 損益資金計画'!$G$73,'4年目 損益資金計画'!$G$73,'5年目 損益資金計画'!$G$73) -> 0 | H73: =CHOOSE($U$2,'初年度 損益資金計画'!$H$73,'2年目 損益資金計画'!$H$73,'3年目 損益資金計画'!$H$73,'4年目 損益資金計画'!$H$73,'5年目 損益資金計画'!$H$73) -> 0 | I73: =CHOOSE($U$2,'初年度 損益資金計画'!$I$73,'2年目 損益資金計画'!$I$73,'3年目 損益資金計画'!$I$73,'4年目 損益資金計画'!$I$73,'5年目 損益資金計画'!$I$73) -> 0 | J73: =CHOOSE($U$2,'初年度 損益資金計画'!$J$73,'2年目 損益資金計画'!$J$73,'3年目 損益資金計画'!$J$73,'4年目 損益資金計画'!$J$73,'5年目 損益資金計画'!$J$73) -> 0 | K73: =CHOOSE($U$2,'初年度 損益資金計画'!$K$73,'2年目 損益資金計画'!$K$73,'3年目 損益資金計画'!$K$73,'4年目 損益資金計画'!$K$73,'5年目 損益資金計画'!$K$73) -> 0 | L73: =CHOOSE($U$2,'初年度 損益資金計画'!$L$73,'2年目 損益資金計画'!$L$73,'3年目 損益資金計画'!$L$73,'4年目 損益資金計画'!$L$73,'5年目 損益資金計画'!$L$73) -> 0 | M73: =CHOOSE($U$2,'初年度 損益資金計画'!$M$73,'2年目 損益資金計画'!$M$73,'3年目 損益資金計画'!$M$73,'4年目 損益資金計画'!$M$73,'5年目 損益資金計画'!$M$73) -> 0 | N73: =CHOOSE($U$2,'初年度 損益資金計画'!$N$73,'2年目 損益資金計画'!$N$73,'3年目 損益資金計画'!$N$73,'4年目 損益資金計画'!$N$73,'5年目 損益資金計画'!$N$73) -> 0 | O73: =CHOOSE($U$2,'初年度 損益資金計画'!$O$73,'2年目 損益資金計画'!$O$73,'3年目 損益資金計画'!$O$73,'4年目 損益資金計画'!$O$73,'5年目 損益資金計画'!$O$73) -> 0 | P73: =CHOOSE($U$2,'初年度 損益資金計画'!$P$73,'2年目 損益資金計画'!$P$73,'3年目 損益資金計画'!$P$73,'4年目 損益資金計画'!$P$73,'5年目 損益資金計画'!$P$73) -> 0

Sheet 表紙

Sheet 収支計画書（人材配置等）
D2: 令和３年 | Q2: 令和4年 | AD2: 令和５年 | AQ2: 令和６年 | BD2: 令和７年
E3: ４月 | F3: ５月 | G3: ６月 | H3: ７月 | I3: ８月 | J3: ９月 | K3: １０月 | L3: １１月 | M3: １２月 | N3: １月 | O3: ２月 | P3: ３月 | R3: ４月 | S3: ５月 | T3: ６月 | U3: ７月 | V3: ８月 | W3: ９月 | X3: １０月 | Y3: １１月 | Z3: １２月 | AA3: １月 | AB3: ２月 | AC3: ３月 | AE3: 1月 | AF3: 2月 | AG3: 3月 | AH3: 4月 | AI3: 5月 | AJ3: 6月 | AK3: 7月 | AL3: 8月 | AM3: 9月 | AN3: 10月 | AO3: 11月 | AP3: 12月 | AR3: 1月 | AS3: 2月 | AT3: 3月 | AU3: 4月 | AV3: 5月 | AW3: 6月 | AX3: 7月 | AY3: 8月 | AZ3: 9月 | BA3: 10月 | BB3: 11月 | BC3: 12月 | BE3: 1月 | BF3: 2月 | BG3: 3月 | BH3: 4月 | BI3: 5月 | BJ3: 6月 | BK3: 7月 | BL3: 8月 | BM3: 9月 | BN3: 10月 | BO3: 11月 | BP3: 12月
A4: 稼働日 | E4: 22 | F4: 20 | G4: 23 | H4: 22 | I4: 23 | J4: 22 | K4: 23 | L4: 22 | M4: 18 | N4: 19 | O4: 19 | P4: 23 | R4: 20 | S4: 19 | T4: 22 | U4: 21 | V4: 20 | W4: 21 | X4: 21 | Y4: 21 | Z4: 19 | AA4: 18 | AB4: 20 | AC4: 23 | AE4: 22 | AF4: 20 | AG4: 23 | AH4: 22 | AI4: 23 | AJ4: 22 | AK4: 23 | AL4: 22 | AM4: 22 | AN4: 23 | AO4: 22 | AP4: 22 | AR4: 22 | AS4: 20 | AT4: 23 | AU4: 22 | AV4: 23 | AW4: 22 | AX4: 23 | AY4: 22 | AZ4: 22 | BA4: 23 | BB4: 22 | BC4: 22 | BE4: 22 | BF4: 20 | BG4: 23 | BH4: 22 | BI4: 23 | BJ4: 22 | BK4: 23 | BL4: 22 | BM4: 22 | BN4: 23 | BO4: 22 | BP4: 22
A5: 稼働率 | E5: 0.8 | F5: 0.8 | G5: 0.8 | H5: 0.8 | I5: 0.8 | J5: 0.8 | K5: 0.8 | L5: 0.8 | M5: 0.8 | N5: 0.8 | O5: 0.8 | P5: 0.8 | R5: 0.8 | S5: 0.8 | T5: 0.8 | U5: 0.8 | V5: 0.8 | W5: 0.8 | X5: 0.8 | Y5: 0.8 | Z5: 0.8 | AA5: 0.8 | AB5: 0.8 | AC5: 0.8 | AE5: 0.8 | AF5: 0.8 | AG5: 0.8 | AH5: 0.8 | AI5: 0.8 | AJ5: 0.8 | AK5: 0.8 | AL5: 0.8 | AM5: 0.8 | AN5: 0.8 | AO5: 0.8 | AP5: 0.8 | AR5: 0.8 | AS5: 0.8 | AT5: 0.8 | AU5: 0.8 | AV5: 0.8 | AW5: 0.8 | AX5: 0.8 | AY5: 0.8 | AZ5: 0.8 | BA5: 0.8 | BB5: 0.8 | BC5: 0.8 | BE5: 0.8 | BF5: 0.8 | BG5: 0.8 | BH5: 0.8 | BI5: 0.8 | BJ5: 0.8 | BK5: 0.8 | BL5: 0.8 | BM5: 0.8 | BN5: 0.8 | BO5: 0.8 | BP5: 0.8
A6: 就労B利用者数 | AR6: 10 | AS6: 10 | AT6: 10 | AU6: 10 | AV6: 10 | AW6: 10 | AX6: 10 | AY6: 10 | AZ6: 10 | BA6: 10 | BB6: 10 | BC6: 10 | BE6: 10 | BF6: 10 | BG6: 10 | BH6: 10 | BI6: 10 | BJ6: 10 | BK6: 10 | BL6: 10 | BM6: 10 | BN6: 10 | BO6: 10 | BP6: 10
A7: 就労B施設外利用者数 | AR7: 10 | AS7: 10 | AT7: 10 | AU7: 10 | AV7: 10 | AW7: 10 | AX7: 10 | AY7: 10 | AZ7: 10 | BA7: 10 | BB7: 10 | BC7: 10 | BE7: 10 | BF7: 10 | BG7: 10 | BH7: 10 | BI7: 10 | BJ7: 10 | BK7: 10 | BL7: 10 | BM7: 10 | BN7: 10 | BO7: 10 | BP7: 10
A8: B合計 | E8: =SUM(E6:E7) -> 0 | F8: =SUM(F6:F7) -> 0 | G8: =SUM(G6:G7) -> 0 | H8: =SUM(H6:H7) -> 0 | I8: =SUM(I6:I7) -> 0 | J8: =SUM(J6:J7) -> 0 | K8: =SUM(K6:K7) -> 0 | L8: =SUM(L6:L7) -> 0 | ... P8: =SUM(P6:P7) -> 0 | R8: =SUM(R6:R7) -> 0 | S8: =SUM(S6:S7) -> 0 | T8: =SUM(T6:T7) -> 0 | U8: =SUM(U6:U7) -> 0 | V8: =SUM(V6:V7) -> 0 | W8: =SUM(W6:W7) -> 0 | X8: =SUM(X6:X7) -> 0 | Y8: =SUM(Y6:Y7) -> 0 | ... AC8: =SUM(AC6:AC7) -> 0 | AE8: =SUM(AE6:AE7) -> 0 | AF8: =SUM(AF6:AF7) -> 0 | AG8: =SUM(AG6:AG7) -> 0 | AH8: =SUM(AH6:AH7) -> 0 | AI8: =SUM(AI6:AI7) -> 0 | AJ8: =SUM(AJ6:AJ7) -> 0 | AK8: =SUM(AK6:AK7) -> 0 | AL8: =SUM(AL6:AL7) -> 0 | ... AP8: =SUM(AP6:AP7) -> 0 | AR8: =SUM(AR6:AR7) -> 20 | AS8: =SUM(AS6:AS7) -> 20 | AT8: =SUM(AT6:AT7) -> 20 | AU8: =SUM(AU6:AU7) -> 20 | AV8: =SUM(AV6:AV7) -> 20 | AW8: =SUM(AW6:AW7) -> 20 | AX8: =SUM(AX6:AX7) -> 20 | AY8: =SUM(AY6:AY7) -> 20 | ... BC8: =SUM(BC6:BC7) -> 20 | BE8: =SUM(BE6:BE7) -> 20 | BF8: =SUM(BF6:BF7) -> 20 | BG8: =SUM(BG6:BG7) -> 20 | BH8: =SUM(BH6:BH7) -> 20 | BI8: =SUM(BI6:BI7) -> 20 | BJ8: =SUM(BJ6:BJ7) -> 20 | BK8: =SUM(BK6:BK7) -> 20 | BL8: =SUM(BL6:BL7) -> 20 | ... BP8: =SUM(BP6:BP7) -> 20
A9: 就労移行利用者数 | M9: 2 | N9: 2 | O9: 3 | P9: 5 | R9: 10 | S9: 14 | T9: 15 | U9: 16 | V9: 17 | W9: 17 | X9: 17 | Y9: 17 | Z9: 17 | AA9: 17 | AB9: 17 | AC9: 17 | AE9: 10 | AF9: 10 | AG9: 10 | AH9: 10 | AI9: 10 | AJ9: 10 | AK9: 10 | AL9: 10 | AM9: 10 | AN9: 10 | AO9: 10 | AP9: 10 | AR9: 10 | AS9: 10 | AT9: 10 | AU9: 10 | AV9: 10 | AW9: 10 | AX9: 10 | AY9: 10 | AZ9: 10 | BA9: 10 | BB9: 10 | BC9: 10 | BE9: 10 | BF9: 10 | BG9: 10 | BH9: 10 | BI9: 10 | BJ9: 10 | BK9: 10 | BL9: 10 | BM9: 10 | BN9: 10 | BO9: 10 | BP9: 10
A10: 就労移行施設外利用者数 | V10: 2 | W10: 3 | X10: 4 | Y10: 5 | Z10: 6 | AA10: 7 | AB10: 8 | AC10: 9 | AE10: 10 | AF10: 10 | AG10: 10 | AH10: 10 | AI10: 10 | AJ10: 10 | AK10: 10 | AL10: 10 | AM10: 10 | AN10: 10 | AO10: 10 | AP10: 10 | AR10: 10 | AS10: 10 | AT10: 10 | AU10: 10 | AV10: 10 | AW10: 10 | AX10: 10 | AY10: 10 | AZ10: 10 | BA10: 10 | BB10: 10 | BC10: 10 | BE10: 10 | BF10: 10 | BG10: 10 | BH10: 10 | BI10: 10 | BJ10: 10 | BK10: 10 | BL10: 10 | BM10: 10 | BN10: 10 | BO10: 10 | BP10: 10
A11: 移行合計 | E11: =SUM(E9:E10) -> 0 | F11: =SUM(F9:F10) -> 0 | G11: =SUM(G9:G10) -> 0 | H11: =SUM(H9:H10) -> 0 | I11: =SUM(I9:I10) -> 0 | J11: =SUM(J9:J10) -> 0 | K11: =SUM(K9:K10) -> 0 | L11: =SUM(L9:L10) -> 0 | ... P11: =SUM(P9:P10) -> 5 | R11: =SUM(R9:R10) -> 10 | S11: =SUM(S9:S10) -> 14 | T11: =SUM(T9:T10) -> 15 | U11: =SUM(U9:U10) -> 16 | V11: =SUM(V9:V10) -> 19 | W11: =SUM(W9:W10) -> 20 | X11: =SUM(X9:X10) -> 21 | Y11: =SUM(Y9:Y10) -> 22 | ... AC11: =SUM(AC9:AC10) -> 26 | AE11: =SUM(AE9:AE10) -> 20 | AF11: =SUM(AF9:AF10) -> 20 | AG11: =SUM(AG9:AG10) -> 20 | AH11: =SUM(AH9:AH10) -> 20 | AI11: =SUM(AI9:AI10) -> 20 | AJ11: =SUM(AJ9:AJ10) -> 20 | AK11: =SUM(AK9:AK10) -> 20 | AL11: =SUM(AL9:AL10) -> 20 | ... AP11: =SUM(AP9:AP10) -> 20 | AR11: =SUM(AR9:AR10) -> 20 | AS11: =SUM(AS9:AS10) -> 20 | AT11: =SUM(AT9:AT10) -> 20 | AU11: =SUM(AU9:AU10) -> 20 | AV11: =SUM(AV9:AV10) -> 20 | AW11: =SUM(AW9:AW10) -> 20 | AX11: =SUM(AX9:AX10) -> 20 | AY11: =SUM(AY9:AY10) -> 20 | ... BC11: =SUM(BC9:BC10) -> 20 | BE11: =SUM(BE9:BE10) -> 20 | BF11: =SUM(BF9:BF10) -> 20 | BG11: =SUM(BG9:BG10) -> 20 | BH11: =SUM(BH9:BH10) -> 20 | BI11: =SUM(BI9:BI10) -> 20 | BJ11: =SUM(BJ9:BJ10) -> 20 | BK11: =SUM(BK9:BK10) -> 20 | BL11: =SUM(BL9:BL10) -> 20 | ... BP11: =SUM(BP9:BP10) -> 20
A12: 合計人数 | E12: =E8:F8+E11 -> 0 | F12: =F8:G8+F11 -> 0 | G12: =G8:H8+G11 -> 0 | H12: =H8:I8+H11 -> 0 | I12: =I8:J8+I11 -> 0 | J12: =J8:K8+J11 -> 0 | K12: =K8:L8+K11 -> 0 | L12: =L8:M8+L11 -> 0 | ... P12: =P8:Q8+P11 -> 5 | R12: =R8:S8+R11 -> 10 | S12: =S8:T8+S11 -> 14 | T12: =T8:U8+T11 -> 15 | U12: =U8:V8+U11 -> 16 | V12: =V8:W8+V11 -> 19 | W12: =W8:X8+W11 -> 20 | X12: =X8:Y8+X11 -> 21 | Y12: =Y8:Z8+Y11 -> 22 | ... AC12: =AC8:AD8+AC11 -> 26 | AE12: =AE8:AF8+AE11 -> 20 | AF12: =AF8:AG8+AF11 -> 20 | AG12: =AG8:AH8+AG11 -> 20 | AH12: =AH8:AI8+AH11 -> 20 | AI12: =AI8:AJ8+AI11 -> 20 | AJ12: =AJ8:AK8+AJ11 -> 20 | AK12: =AK8:AL8+AK11 -> 20 | AL12: =AL8:AM8+AL11 -> 20 | ... AO12: =AO8:AP8+AO11 -> 20 | AP12: =AP8+AP11 -> 20 | AR12: =AR8:AS8+AR11 -> 40 | AS12: =AS8:AT8+AS11 -> 40 | AT12: =AT8:AU8+AT11 -> 40 | AU12: =AU8:AV8+AU11 -> 40 | AV12: =AV8:AW8+AV11 -> 40 | AW12: =AW8:AX8+AW11 -> 40 | AX12: =AX8:AY8+AX11 -> 40 | AY12: =AY8:AZ8+AY11 -> 40 | ... BB12: =BB8:BC8+BB11 -> 40 | BC12: =BC8+BC11 -> 40 | BE12: =BE8:BF8+BE11 -> 40 | BF12: =BF8:BG8+BF11 -> 40 | BG12: =BG8:BH8+BG11 -> 40 | BH12: =BH8:BI8+BH11 -> 40 | BI12: =BI8:BJ8+BI11 -> 40 | BJ12: =BJ8:BK8+BJ11 -> 40 | BK12: =BK8:BL8+BK11 -> 40 | BL12: =BL8:BM8+BL11 -> 40 | ... BO12: =BO8:BP8+BO11 -> 40 | BP12: =BP8+BP11 -> 40
A14: B通常給付金 | E14: =ROUNDDOWN(E6*E23*E4*E5,-2) -> 0 | F14: =ROUNDDOWN(F6*F23*F4*F5,-2) -> 0 | G14: =ROUNDDOWN(G6*G23*G4*G5,-2) -> 0 | H14: =ROUNDDOWN(H6*H23*H4*H5,-2) -> 0 | I14: =ROUNDDOWN(I6*I23*I4*I5,-2) -> 0 | J14: =ROUNDDOWN(J6*J23*J4*J5,-2) -> 0 | K14: =ROUNDDOWN(K6*K23*K4*K5,-2) -> 0 | L14: =ROUNDDOWN(L6*L23*L4*L5,-2) -> 0 | ... P14: =ROUNDDOWN(P6*P23*P4*P5,-2) -> 0 | R14: =ROUNDDOWN(R6*R23*R4*R5,-2) -> 0 | S14: =ROUNDDOWN(S6*S23*S4*S5,-2) -> 0 | T14: =ROUNDDOWN(T6*T23*T4*T5,-2) -> 0 | U14: =ROUNDDOWN(U6*U23*U4*U5,-2) -> 0 | V14: =ROUNDDOWN(V6*V23*V4*V5,-2) -> 0 | W14: =ROUNDDOWN(W6*W23*W4*W5,-2) -> 0 | X14: =ROUNDDOWN(X6*X23*X4*X5,-2) -> 0 | Y14: =ROUNDDOWN(Y6*Y23*Y4*Y5,-2) -> 0 | ... AC14: =ROUNDDOWN(AC6*AC23*AC4*AC5,-2) -> 0 | AE14: =ROUNDDOWN(AE6*AE23*AE4*AE5,-2) -> 0 | AF14: =ROUNDDOWN(AF6*AF23*AF4*AF5,-2) -> 0 | AG14: =ROUNDDOWN(AG6*AG23*AG4*AG5,-2) -> 0 | AH14: =ROUNDDOWN(AH6*AH23*AH4*AH5,-2) -> 0 | AI14: =ROUNDDOWN(AI6*AI23*AI4*AI5,-2) -> 0 | AJ14: =ROUNDDOWN(AJ6*AJ23*AJ4*AJ5,-2) -> 0 | AK14: =ROUNDDOWN(AK6*AK23*AK4*AK5,-2) -> 0 | AL14: =ROUNDDOWN(AL6*AL23*AL4*AL5,-2) -> 0 | ... AP14: =ROUNDDOWN(AP6*AP23*AP4*AP5,-2) -> 0 | AR14: =ROUNDDOWN(AR6*AR23*AR4*AR5,-2) -> 1036600 | AS14: =ROUNDDOWN(AS6*AS23*AS4*AS5,-2) -> 942400 | AT14: =ROUNDDOWN(AT6*AT23*AT4*AT5,-2) -> 1083700 | AU14: =ROUNDDOWN(AU6*AU23*AU4*AU5,-2) -> 1036600 | AV14: =ROUNDDOWN(AV6*AV23*AV4*AV5,-2) -> 1083700 | AW14: =ROUNDDOWN(AW6*AW23*AW4*AW5,-2) -> 1036600 | AX14: =ROUNDDOWN(AX6*AX23*AX4*AX5,-2) -> 1083700 | AY14: =ROUNDDOWN(AY6*AY23*AY4*AY5,-2) -> 1036600 | ... BC14: =ROUNDDOWN(BC6*BC23*BC4*BC5,-2) -> 1036600 | BE14: =ROUNDDOWN(BE6*BE23*BE4*BE5,-2) -> 1036600 | BF14: =ROUNDDOWN(BF6*BF23*BF4*BF5,-2) -> 942400 | BG14: =ROUNDDOWN(BG6*BG23*BG4*BG5,-2) -> 1083700 | BH14: =ROUNDDOWN(BH6*BH23*BH4*BH5,-2) -> 1036600 | BI14: =ROUNDDOWN(BI6*BI23*BI4*BI5,-2) -> 1083700 | BJ14: =ROUNDDOWN(BJ6*BJ23*BJ4*BJ5,-2) -> 1036600 | BK14: =ROUNDDOWN(BK6*BK23*BK4*BK5,-2) -> 1083700 | BL14: =ROUNDDOWN(BL6*BL23*BL4*BL5,-2) -> 1036600 | ... BP14: =ROUNDDOWN(BP6*BP23*BP4*BP5,-2) -> 1036600
A15: B施設外給付金 | E15: =ROUNDDOWN(E7*E24*E4*E29,-2) -> 0 | F15: =F7*F24*F4*F29 -> 0 | G15: =G7*G24*G4*G29 -> 0 | H15: =H7*H24*H4*H29 -> 0 | I15: =I7*I24*I4*I29 -> 0 | J15: =J7*J24*J4*J29 -> 0 | K15: =K7*K24*K4*K29 -> 0 | L15: =L7*L24*L4*L29 -> 0 | M15: =M7*M24*M4*M29 -> 0 | ... P15: =P7*P24*P4*P29 -> 0 | R15: =ROUNDDOWN(R7*R24*R4*R29,-2) -> 0 | S15: =S7*S24*S4*S29 -> 0 | T15: =T7*T24*T4*T29 -> 0 | U15: =U7*U24*U4*U29 -> 0 | V15: =V7*V24*V4*V29 -> 0 | W15: =W7*W24*W4*W29 -> 0 | X15: =X7*X24*X4*X29 -> 0 | Y15: =Y7*Y24*Y4*Y29 -> 0 | Z15: =Z7*Z24*Z4*Z29 -> 0 | ... AC15: =AC7*AC24*AC4*AC29 -> 0 | AE15: =ROUNDDOWN(AE7*AE24*AE4*AE29,-2) -> 0 | AF15: =AF7*AF24*AF4*AF29 -> 0 | AG15: =AG7*AG24*AG4*AG29 -> 0 | AH15: =AH7*AH24*AH4*AH29 -> 0 | AI15: =AI7*AI24*AI4*AI29 -> 0 | AJ15: =AJ7*AJ24*AJ4*AJ29 -> 0 | AK15: =AK7*AK24*AK4*AK29 -> 0 | AL15: =AL7*AL24*AL4*AL29 -> 0 | AM15: =AM7*AM24*AM4*AM29 -> 0 | ... AP15: =AP7*AP24*AP4*AP29 -> 0 | AR15: =ROUNDDOWN(AR7*AR24*AR4*AR29,-2) -> 1136800 | AS15: =AS7*AS24*AS4*AS29 -> 1033500 | AT15: =AT7*AT24*AT4*AT29 -> 1188525 | AU15: =AU7*AU24*AU4*AU29 -> 1136850 | AV15: =AV7*AV24*AV4*AV29 -> 1188525 | AW15: =AW7*AW24*AW4*AW29 -> 1136850 | AX15: =AX7*AX24*AX4*AX29 -> 1188525 | AY15: =AY7*AY24*AY4*AY29 -> 1136850 | AZ15: =AZ7*AZ24*AZ4*AZ29 -> 1136850 | ... BC15: =BC7*BC24*BC4*BC29 -> 1136850 | BE15: =ROUNDDOWN(BE7*BE24*BE4*BE29,-2) -> 1136800 | BF15: =BF7*BF24*BF4*BF29 -> 1033500 | BG15: =BG7*BG24*BG4*BG29 -> 1188525 | BH15: =BH7*BH24*BH4*BH29 -> 1136850 | BI15: =BI7*BI24*BI4*BI29 -> 1188525 | BJ15: =BJ7*BJ24*BJ4*BJ29 -> 1136850 | BK15: =BK7*BK24*BK4*BK29 -> 1188525 | BL15: =BL7*BL24*BL4*BL29 -> 1136850 | BM15: =BM7*BM24*BM4*BM29 -> 1136850 | ... BP15: =BP7*BP24*BP4*BP29 -> 1136850
A16: B加算 | E16: =ROUNDDOWN(((E6+E7)*(E27+E28*0.8))*E4,-2) -> 0 | F16: =ROUNDDOWN(((F6+F7)*(F27+F28*0.8))*F4,-2) -> 0 | G16: =ROUNDDOWN(((G6+G7)*(G27+G28*0.8))*G4,-2) -> 0 | H16: =ROUNDDOWN(((H6+H7)*(H27+H28*0.8))*H4,-2) -> 0 | I16: =ROUNDDOWN(((I6+I7)*(I27+I28*0.8))*I4,-2) -> 0 | J16: =ROUNDDOWN(((J6+J7)*(J27+J28*0.8))*J4,-2) -> 0 | K16: =ROUNDDOWN(((K6+K7)*(K27+K28*0.8))*K4,-2) -> 0 | L16: =ROUNDDOWN(((L6+L7)*(L27+L28*0.8))*L4,-2) -> 0 | ... P16: =ROUNDDOWN(((P6+P7)*(P27+P28*0.8))*P4,-2) -> 0 | R16: =ROUNDDOWN(((R6+R7)*(R27+R28*0.8))*R4,-2) -> 0 | S16: =ROUNDDOWN(((S6+S7)*(S27+S28*0.8))*S4,-2) -> 0 | T16: =ROUNDDOWN(((T6+T7)*(T27+T28*0.8))*T4,-2) -> 0 | U16: =ROUNDDOWN(((U6+U7)*(U27+U28*0.8))*U4,-2) -> 0 | V16: =ROUNDDOWN(((V6+V7)*(V27+V28*0.8))*V4,-2) -> 0 | W16: =ROUNDDOWN(((W6+W7)*(W27+W28*0.8))*W4,-2) -> 0 | X16: =ROUNDDOWN(((X6+X7)*(X27+X28*0.8))*X4,-2) -> 0 | Y16: =ROUNDDOWN(((Y6+Y7)*(Y27+Y28*0.8))*Y4,-2) -> 0 | ... AC16: =ROUNDDOWN(((AC6+AC7)*(AC27+AC28*0.8))*AC4,-2) -> 0 | AE16: =ROUNDDOWN(((AE6+AE7)*(AE27+AE28*0.8))*AE4,-2) -> 0 | AF16: =ROUNDDOWN(((AF6+AF7)*(AF27+AF28*0.8))*AF4,-2) -> 0 | AG16: =ROUNDDOWN(((AG6+AG7)*(AG27+AG28*0.8))*AG4,-2) -> 0 | AH16: =ROUNDDOWN(((AH6+AH7)*(AH27+AH28*0.8))*AH4,-2) -> 0 | AI16: =ROUNDDOWN(((AI6+AI7)*(AI27+AI28*0.8))*AI4,-2) -> 0 | AJ16: =ROUNDDOWN(((AJ6+AJ7)*(AJ27+AJ28*0.8))*AJ4,-2) -> 0 | AK16: =ROUNDDOWN(((AK6+AK7)*(AK27+AK28*0.8))*AK4,-2) -> 0 | AL16: =ROUNDDOWN(((AL6+AL7)*(AL27+AL28*0.8))*AL4,-2) -> 0 | ... AP16: =ROUNDDOWN(((AP6+AP7)*(AP27+AP28*0.8))*AP4,-2) -> 0 | AR16: =ROUNDDOWN(((AR6+AR7)*(AR27+AR28*0.8))*AR4,-2) -> 581600 | AS16: =ROUNDDOWN(((AS6+AS7)*(AS27+AS28*0.8))*AS4,-2) -> 528800 | AT16: =ROUNDDOWN(((AT6+AT7)*(AT27+AT28*0.8))*AT4,-2) -> 608100 | AU16: =ROUNDDOWN(((AU6+AU7)*(AU27+AU28*0.8))*AU4,-2) -> 581600 | AV16: =ROUNDDOWN(((AV6+AV7)*(AV27+AV28*0.8))*AV4,-2) -> 608100 | AW16: =ROUNDDOWN(((AW6+AW7)*(AW27+AW28*0.8))*AW4,-2) -> 581600 | AX16: =ROUNDDOWN(((AX6+AX7)*(AX27+AX28*0.8))*AX4,-2) -> 608100 | AY16: =ROUNDDOWN(((AY6+AY7)*(AY27+AY28*0.8))*AY4,-2) -> 581600 | ... BC16: =ROUNDDOWN(((BC6+BC7)*(BC27+BC28*0.8))*BC4,-2) -> 581600 | BE16: =ROUNDDOWN(((BE6+BE7)*(BE27+BE28*0.8))*BE4,-2) -> 581600 | BF16: =ROUNDDOWN(((BF6+BF7)*(BF27+BF28*0.8))*BF4,-2) -> 528800 | BG16: =ROUNDDOWN(((BG6+BG7)*(BG27+BG28*0.8))*BG4,-2) -> 608100 | BH16: =ROUNDDOWN(((BH6+BH7)*(BH27+BH28*0.8))*BH4,-2) -> 581600 | BI16: =ROUNDDOWN(((BI6+BI7)*(BI27+BI28*0.8))*BI4,-2) -> 608100 | BJ16: =ROUNDDOWN(((BJ6+BJ7)*(BJ27+BJ28*0.8))*BJ4,-2) -> 581600 | BK16: =ROUNDDOWN(((BK6+BK7)*(BK27+BK28*0.8))*BK4,-2) -> 608100 | BL16: =ROUNDDOWN(((BL6+BL7)*(BL27+BL28*0.8))*BL4,-2) -> 581600 | ... BP16: =ROUNDDOWN(((BP6+BP7)*(BP27+BP28*0.8))*BP4,-2) -> 581600
A17: 移行通常給付金 | E17: =ROUNDDOWN(E9*E25*E4*E5,-2) -> 0 | F17: =ROUNDDOWN(F9*F25*F4*F5,-2) -> 0 | G17: =ROUNDDOWN(G9*G25*G4*G5,-2) -> 0 | H17: =ROUNDDOWN(H9*H25*H4*H5,-2) -> 0 | I17: =ROUNDDOWN(I9*I25*I4*I5,-2) -> 0 | J17: =ROUNDDOWN(J9*J25*J4*J5,-2) -> 0 | K17: =ROUNDDOWN(K9*K25*K4*K5,-2) -> 0 | L17: =ROUNDDOWN(L9*L25*L4*L5,-2) -> 0 | ... P17: =ROUNDDOWN(P9*P25*P4*P5,-2) -> 754400 | R17: =ROUNDDOWN(R9*R25*R4*R5,-2) -> 1312000 | S17: =ROUNDDOWN(S9*S25*S4*S5,-2) -> 1744900 | T17: =ROUNDDOWN(T9*T25*T4*T5,-2) -> 2164800 | U17: =ROUNDDOWN(U9*U25*U4*U5,-2) -> 2204100 | V17: =ROUNDDOWN(V9*V25*V4*V5,-2) -> 2230400 | W17: =ROUNDDOWN(W9*W25*W4*W5,-2) -> 2341900 | X17: =ROUNDDOWN(X9*X25*X4*X5,-2) -> 2341900 | Y17: =ROUNDDOWN(Y9*Y25*Y4*Y5,-2) -> 2341900 | ... AC17: =ROUNDDOWN(AC9*AC25*AC4*AC5,-2) -> 2564900 | AE17: =ROUNDDOWN(AE9*AE25*AE4*AE5,-2) -> 1422000 | AF17: =ROUNDDOWN(AF9*AF25*AF4*AF5,-2) -> 1292800 | AG17: =ROUNDDOWN(AG9*AG25*AG4*AG5,-2) -> 1486700 | AH17: =ROUNDDOWN(AH9*AH25*AH4*AH5,-2) -> 1422000 | AI17: =ROUNDDOWN(AI9*AI25*AI4*AI5,-2) -> 1486700 | AJ17: =ROUNDDOWN(AJ9*AJ25*AJ4*AJ5,-2) -> 1422000 | AK17: =ROUNDDOWN(AK9*AK25*AK4*AK5,-2) -> 1486700 | AL17: =ROUNDDOWN(AL9*AL25*AL4*AL5,-2) -> 1422000 | ... AP17: =ROUNDDOWN(AP9*AP25*AP4*AP5,-2) -> 1422000 | AR17: =ROUNDDOWN(AR9*AR25*AR4*AR5,-2) -> 1422000 | AS17: =ROUNDDOWN(AS9*AS25*AS4*AS5,-2) -> 1292800 | AT17: =ROUNDDOWN(AT9*AT25*AT4*AT5,-2) -> 1486700 | AU17: =ROUNDDOWN(AU9*AU25*AU4*AU5,-2) -> 1422000 | AV17: =ROUNDDOWN(AV9*AV25*AV4*AV5,-2) -> 1486700 | AW17: =ROUNDDOWN(AW9*AW25*AW4*AW5,-2) -> 1422000 | AX17: =ROUNDDOWN(AX9*AX25*AX4*AX5,-2) -> 1486700 | AY17: =ROUNDDOWN(AY9*AY25*AY4*AY5,-2) -> 1422000 | ... BC17: =ROUNDDOWN(BC9*BC25*BC4*BC5,-2) -> 1422000 | BE17: =ROUNDDOWN(BE9*BE25*BE4*BE5,-2) -> 1422000 | BF17: =ROUNDDOWN(BF9*BF25*BF4*BF5,-2) -> 1292800 | BG17: =ROUNDDOWN(BG9*BG25*BG4*BG5,-2) -> 1486700 | BH17: =ROUNDDOWN(BH9*BH25*BH4*BH5,-2) -> 1422000 | BI17: =ROUNDDOWN(BI9*BI25*BI4*BI5,-2) -> 1486700 | BJ17: =ROUNDDOWN(BJ9*BJ25*BJ4*BJ5,-2) -> 1422000 | BK17: =ROUNDDOWN(BK9*BK25*BK4*BK5,-2) -> 1486700 | BL17: =ROUNDDOWN(BL9*BL25*BL4*BL5,-2) -> 1422000 | ... BP17: =ROUNDDOWN(BP9*BP25*BP4*BP5,-2) -> 1422000
A18: 移行施設外給付金 | E18: =ROUNDDOWN(E10*E26*E4*E5,-2) -> 0 | F18: =ROUNDDOWN(F10*F26*F4*F5,-2) -> 0 | G18: =ROUNDDOWN(G10*G26*G4*G5,-2) -> 0 | H18: =ROUNDDOWN(H10*H26*H4*H5,-2) -> 0 | I18: =ROUNDDOWN(I10*I26*I4*I5,-2) -> 0 | J18: =ROUNDDOWN(J10*J26*J4*J5,-2) -> 0 | K18: =ROUNDDOWN(K10*K26*K4*K5,-2) -> 0 | L18: =ROUNDDOWN(L10*L26*L4*L5,-2) -> 0 | ... P18: =ROUNDDOWN(P10*P26*P4*P5,-2) -> 0 | R18: =ROUNDDOWN(R10*R26*R4*R5,-2) -> 0 | S18: =ROUNDDOWN(S10*S26*S4*S5,-2) -> 0 | T18: =ROUNDDOWN(T10*T26*T4*T5,-2) -> 0 | U18: =ROUNDDOWN(U10*U26*U4*U5,-2) -> 0 | V18: =ROUNDDOWN(V10*V26*V4*V5,-2) -> 262400 | W18: =ROUNDDOWN(W10*W26*W4*W5,-2) -> 413200 | X18: =ROUNDDOWN(X10*X26*X4*X5,-2) -> 551000 | Y18: =ROUNDDOWN(Y10*Y26*Y4*Y5,-2) -> 688800 | ... AC18: =ROUNDDOWN(AC10*AC26*AC4*AC5,-2) -> 1357900 | AE18: =ROUNDDOWN(AE10*AE26*AE4*AE5,-2) -> 1598000 | AF18: =ROUNDDOWN(AF10*AF26*AF4*AF5,-2) -> 1452800 | AG18: =ROUNDDOWN(AG10*AG26*AG4*AG5,-2) -> 1670700 | AH18: =ROUNDDOWN(AH10*AH26*AH4*AH5,-2) -> 1598000 | AI18: =ROUNDDOWN(AI10*AI26*AI4*AI5,-2) -> 1670700 | AJ18: =ROUNDDOWN(AJ10*AJ26*AJ4*AJ5,-2) -> 1598000 | AK18: =ROUNDDOWN(AK10*AK26*AK4*AK5,-2) -> 1670700 | AL18: =ROUNDDOWN(AL10*AL26*AL4*AL5,-2) -> 1598000 | ... AP18: =ROUNDDOWN(AP10*AP26*AP4*AP5,-2) -> 1598000 | AR18: =ROUNDDOWN(AR10*AR26*AR4*AR5,-2) -> 1598000 | AS18: =ROUNDDOWN(AS10*AS26*AS4*AS5,-2) -> 1452800 | AT18: =ROUNDDOWN(AT10*AT26*AT4*AT5,-2) -> 1670700 | AU18: =ROUNDDOWN(AU10*AU26*AU4*AU5,-2) -> 1598000 | AV18: =ROUNDDOWN(AV10*AV26*AV4*AV5,-2) -> 1670700 | AW18: =ROUNDDOWN(AW10*AW26*AW4*AW5,-2) -> 1598000 | AX18: =ROUNDDOWN(AX10*AX26*AX4*AX5,-2) -> 1670700 | AY18: =ROUNDDOWN(AY10*AY26*AY4*AY5,-2) -> 1598000 | ... BC18: =ROUNDDOWN(BC10*BC26*BC4*BC5,-2) -> 1598000 | BE18: =ROUNDDOWN(BE10*BE26*BE4*BE5,-2) -> 1598000 | BF18: =ROUNDDOWN(BF10*BF26*BF4*BF5,-2) -> 1452800 | BG18: =ROUNDDOWN(BG10*BG26*BG4*BG5,-2) -> 1670700 | BH18: =ROUNDDOWN(BH10*BH26*BH4*BH5,-2) -> 1598000 | BI18: =ROUNDDOWN(BI10*BI26*BI4*BI5,-2) -> 1670700 | BJ18: =ROUNDDOWN(BJ10*BJ26*BJ4*BJ5,-2) -> 1598000 | BK18: =ROUNDDOWN(BK10*BK26*BK4*BK5,-2) -> 1670700 | BL18: =ROUNDDOWN(BL10*BL26*BL4*BL5,-2) -> 1598000 | ... BP18: =ROUNDDOWN(BP10*BP26*BP4*BP5,-2) -> 1598000
A19: 移行加算 | E19: =ROUNDDOWN((E9+E10)*E4*E5*E28,-2) -> 0 | F19: =ROUNDDOWN((F9+F10)*F4*F5*F28,-2) -> 0 | G19: =ROUNDDOWN((G9+G10)*G4*G5*G28,-2) -> 0 | H19: =ROUNDDOWN((H9+H10)*H4*H5*H28,-2) -> 0 | I19: =ROUNDDOWN((I9+I10)*I4*I5*I28,-2) -> 0 | J19: =ROUNDDOWN((J9+J10)*J4*J5*J28,-2) -> 0 | K19: =ROUNDDOWN((K9+K10)*K4*K5*K28,-2) -> 0 | L19: =ROUNDDOWN((L9+L10)*L4*L5*L28,-2) -> 0 | ... P19: =ROUNDDOWN((P9+P10)*P4*P5*P28,-2) -> 49600 | R19: =ROUNDDOWN((R9+R10)*R4*R5*R28,-2) -> 86400 | S19: =ROUNDDOWN((S9+S10)*S4*S5*S28,-2) -> 114900 | T19: =ROUNDDOWN((T9+T10)*T4*T5*T28,-2) -> 142500 | U19: =ROUNDDOWN((U9+U10)*U4*U5*U28,-2) -> 145100 | V19: =ROUNDDOWN((V9+V10)*V4*V5*V28,-2) -> 164100 | W19: =ROUNDDOWN((W9+W10)*W4*W5*W28,-2) -> 181400 | X19: =ROUNDDOWN((X9+X10)*X4*X5*X28,-2) -> 190500 | Y19: =ROUNDDOWN((Y9+Y10)*Y4*Y5*Y28,-2) -> 199500 | ... AC19: =ROUNDDOWN((AC9+AC10)*AC4*AC5*AC28,-2) -> 258300 | AE19: =ROUNDDOWN((AE9+AE10)*AE4*AE5*AE28,-2) -> 190000 | AF19: =ROUNDDOWN((AF9+AF10)*AF4*AF5*AF28,-2) -> 172800 | AG19: =ROUNDDOWN((AG9+AG10)*AG4*AG5*AG28,-2) -> 198700 | AH19: =ROUNDDOWN((AH9+AH10)*AH4*AH5*AH28,-2) -> 190000 | AI19: =ROUNDDOWN((AI9+AI10)*AI4*AI5*AI28,-2) -> 198700 | AJ19: =ROUNDDOWN((AJ9+AJ10)*AJ4*AJ5*AJ28,-2) -> 190000 | AK19: =ROUNDDOWN((AK9+AK10)*AK4*AK5*AK28,-2) -> 198700 | AL19: =ROUNDDOWN((AL9+AL10)*AL4*AL5*AL28,-2) -> 190000 | ... AP19: =ROUNDDOWN((AP9+AP10)*AP4*AP5*AP28,-2) -> 190000 | AR19: =ROUNDDOWN((AR9+AR10)*AR4*AR5*AR28,-2) -> 190000 | AS19: =ROUNDDOWN((AS9+AS10)*AS4*AS5*AS28,-2) -> 172800 | AT19: =ROUNDDOWN((AT9+AT10)*AT4*AT5*AT28,-2) -> 198700 | AU19: =ROUNDDOWN((AU9+AU10)*AU4*AU5*AU28,-2) -> 190000 | AV19: =ROUNDDOWN((AV9+AV10)*AV4*AV5*AV28,-2) -> 198700 | AW19: =ROUNDDOWN((AW9+AW10)*AW4*AW5*AW28,-2) -> 190000 | AX19: =ROUNDDOWN((AX9+AX10)*AX4*AX5*AX28,-2) -> 198700 | AY19: =ROUNDDOWN((AY9+AY10)*AY4*AY5*AY28,-2) -> 190000 | ... BC19: =ROUNDDOWN((BC9+BC10)*BC4*BC5*BC28,-2) -> 190000 | BE19: =ROUNDDOWN((BE9+BE10)*BE4*BE5*BE28,-2) -> 190000 | BF19: =ROUNDDOWN((BF9+BF10)*BF4*BF5*BF28,-2) -> 172800 | BG19: =ROUNDDOWN((BG9+BG10)*BG4*BG5*BG28,-2) -> 198700 | BH19: =ROUNDDOWN((BH9+BH10)*BH4*BH5*BH28,-2) -> 190000 | BI19: =ROUNDDOWN((BI9+BI10)*BI4*BI5*BI28,-2) -> 198700 | BJ19: =ROUNDDOWN((BJ9+BJ10)*BJ4*BJ5*BJ28,-2) -> 190000 | BK19: =ROUNDDOWN((BK9+BK10)*BK4*BK5*BK28,-2) -> 198700 | BL19: =ROUNDDOWN((BL9+BL10)*BL4*BL5*BL28,-2) -> 190000 | ... BP19: =ROUNDDOWN((BP9+BP10)*BP4*BP5*BP28,-2) -> 190000
A20: 給付費合計 | E20: =SUM(E14:E19) -> 0 | F20: =SUM(F14:F19) -> 0 | G20: =SUM(G14:G19) -> 0 | H20: =SUM(H14:H19) -> 0 | I20: =SUM(I14:I19) -> 0 | J20: =SUM(J14:J19) -> 0 | K20: =SUM(K14:K19) -> 0 | L20: =SUM(L14:L19) -> 0 | ... P20: =SUM(P14:P19) -> 804000 | R20: =SUM(R14:R19) -> 1398400 | S20: =SUM(S14:S19) -> 1859800 | T20: =SUM(T14:T19) -> 2307300 | U20: =SUM(U14:U19) -> 2349200 | V20: =SUM(V14:V19) -> 2656900 | W20: =SUM(W14:W19) -> 2936500 | X20: =SUM(X14:X19) -> 3083400 | Y20: =SUM(Y14:Y19) -> 3230200 | ... AC20: =SUM(AC14:AC19) -> 4181100 | AE20: =SUM(AE14:AE19) -> 3210000 | AF20: =SUM(AF14:AF19) -> 2918400 | AG20: =SUM(AG14:AG19) -> 3356100 | AH20: =SUM(AH14:AH19) -> 3210000 | AI20: =SUM(AI14:AI19) -> 3356100 | AJ20: =SUM(AJ14:AJ19) -> 3210000 | AK20: =SUM(AK14:AK19) -> 3356100 | AL20: =SUM(AL14:AL19) -> 3210000 | ... AP20: =SUM(AP14:AP19) -> 3210000 | AR20: =SUM(AR14:AR19) -> 5965000 | AS20: =SUM(AS14:AS19) -> 5423100 | AT20: =SUM(AT14:AT19) -> 6236425 | AU20: =SUM(AU14:AU19) -> 5965050 | AV20: =SUM(AV14:AV19) -> 6236425 | AW20: =SUM(AW14:AW19) -> 5965050 | AX20: =SUM(AX14:AX19) -> 6236425 | AY20: =SUM(AY14:AY19) -> 5965050 | ... BC20: =SUM(BC14:BC19) -> 5965050 | BE20: =SUM(BE14:BE19) -> 5965000 | BF20: =SUM(BF14:BF19) -> 5423100 | BG20: =SUM(BG14:BG19) -> 6236425 | BH20: =SUM(BH14:BH19) -> 5965050 | BI20: =SUM(BI14:BI19) -> 6236425 | BJ20: =SUM(BJ14:BJ19) -> 5965050 | BK20: =SUM(BK14:BK19) -> 6236425 | BL20: =SUM(BL14:BL19) -> 5965050 | ... BP20: =SUM(BP14:BP19) -> 5965050
A21: 給付費合計（千円） | E21: =E20/1000 -> 0 | F21: =F20/1000 -> 0 | G21: =G20/1000 -> 0 | H21: =H20/1000 -> 0 | I21: =I20/1000 -> 0 | J21: =J20/1000 -> 0 | K21: =K20/1000 -> 0 | L21: =L20/1000 -> 0 | ... P21: =P20/1000 -> 804 | R21: =R20/1000 -> 1398.4 | S21: =S20/1000 -> 1859.8 | T21: =T20/1000 -> 2307.3 | U21: =U20/1000 -> 2349.2 | V21: =V20/1000 -> 2656.9 | W21: =W20/1000 -> 2936.5 | X21: =X20/1000 -> 3083.4 | Y21: =Y20/1000 -> 3230.2 | ... AC21: =AC20/1000 -> 4181.1 | AE21: =AE20/1000 -> 3210 | AF21: =AF20/1000 -> 2918.4 | AG21: =AG20/1000 -> 3356.1 | AH21: =AH20/1000 -> 3210 | AI21: =AI20/1000 -> 3356.1 | AJ21: =AJ20/1000 -> 3210 | AK21: =AK20/1000 -> 3356.1 | AL21: =AL20/1000 -> 3210 | ... AP21: =AP20/1000 -> 3210 | AR21: =AR20/1000 -> 5965 | AS21: =AS20/1000 -> 5423.1 | AT21: =AT20/1000 -> 6236.425 | AU21: =AU20/1000 -> 5965.05 | AV21: =AV20/1000 -> 6236.425 | AW21: =AW20/1000 -> 5965.05 | AX21: =AX20/1000 -> 6236.425 | AY21: =AY20/1000 -> 5965.05 | ... BC21: =BC20/1000 -> 5965.05 | BE21: =BE20/1000 -> 5965 | BF21: =BF20/1000 -> 5423.1 | BG21: =BG20/1000 -> 6236.425 | BH21: =BH20/1000 -> 5965.05 | BI21: =BI20/1000 -> 6236.425 | BJ21: =BJ20/1000 -> 5965.05 | BK21: =BK20/1000 -> 6236.425 | BL21: =BL20/1000 -> 5965.05 | ... BP21: =BP20/1000 -> 5965.05
A23: B基本報酬 | E23: 5890 | F23: 5890 | G23: 5890 | H23: 5890 | I23: 5890 | J23: 5890 | K23: 5890 | L23: 5890 | M23: 5890 | N23: 5890 | O23: 5890 | P23: 5890 | R23: 5890 | S23: 5890 | T23: 5890 | U23: 5890 | V23: 5890 | W23: 5890 | X23: 5890 | Y23: 5890 | Z23: 5890 | AA23: 5890 | AB23: 5890 | AC23: 5890 | AE23: 5890 | AF23: 5890 | AG23: 5890 | AH23: 5890 | AI23: 5890 | AJ23: 5890 | AK23: 5890 | AL23: 5890 | AM23: 5890 | AN23: 5890 | AO23: 5890 | AP23: 5890 | AR23: 5890 | AS23: 5890 | AT23: 5890 | AU23: 5890 | AV23: 5890 | AW23: 5890 | AX23: 5890 | AY23: 5890 | AZ23: 5890 | BA23: 5890 | BB23: 5890 | BC23: 5890 | BE23: 5890 | BF23: 5890 | BG23: 5890 | BH23: 5890 | BI23: 5890 | BJ23: 5890 | BK23: 5890 | BL23: 5890 | BM23: 5890 | BN23: 5890 | BO23: 5890 | BP23: 5890
A24: B施設外基本報酬 | E24: 6890 | F24: 6890 | G24: 6890 | H24: 6890 | I24: 6890 | J24: 6890 | K24: 6890 | L24: 6890 | M24: 6890 | N24: 6890 | O24: 6890 | P24: 6890 | R24: 6890 | S24: 6890 | T24: 6890 | U24: 6890 | V24: 6890 | W24: 6890 | X24: 6890 | Y24: 6890 | Z24: 6890 | AA24: 6890 | AB24: 6890 | AC24: 6890 | AE24: 6890 | AF24: 6890 | AG24: 6890 | AH24: 6890 | AI24: 6890 | AJ24: 6890 | AK24: 6890 | AL24: 6890 | AM24: 6890 | AN24: 6890 | AO24: 6890 | AP24: 6890 | AR24: 6890 | AS24: 6890 | AT24: 6890 | AU24: 6890 | AV24: 6890 | AW24: 6890 | AX24: 6890 | AY24: 6890 | AZ24: 6890 | BA24: 6890 | BB24: 6890 | BC24: 6890 | BE24: 6890 | BF24: 6890 | BG24: 6890 | BH24: 6890 | BI24: 6890 | BJ24: 6890 | BK24: 6890 | BL24: 6890 | BM24: 6890 | BN24: 6890 | BO24: 6890 | BP24: 6890
A25: 移行基本報酬 | E25: 8200 | F25: =E25 -> 8200 | G25: =F25 -> 8200 | H25: =G25 -> 8200 | I25: =H25 -> 8200 | J25: =I25 -> 8200 | K25: =J25 -> 8200 | L25: =K25 -> 8200 | M25: =L25 -> 8200 | ... O25: =N25 -> 8200 | P25: 8200 | R25: =P25 -> 8200 | S25: =R25 -> 8200 | T25: =S25 -> 8200 | U25: =T25 -> 8200 | V25: =U25 -> 8200 | W25: =V25 -> 8200 | X25: =W25 -> 8200 | Y25: =X25 -> 8200 | Z25: =Y25 -> 8200 | ... AC25: =AB25 -> 8200 | AE25: 8080 | AF25: 8080 | AG25: 8080 | AH25: 8080 | AI25: 8080 | AJ25: 8080 | AK25: 8080 | AL25: 8080 | AM25: 8080 | AN25: 8080 | AO25: 8080 | AP25: 8080 | AR25: 8080 | AS25: 8080 | AT25: 8080 | AU25: 8080 | AV25: 8080 | AW25: 8080 | AX25: 8080 | AY25: 8080 | AZ25: 8080 | BA25: 8080 | BB25: 8080 | BC25: 8080 | BE25: 8080 | BF25: 8080 | BG25: 8080 | BH25: 8080 | BI25: 8080 | BJ25: 8080 | BK25: 8080 | BL25: 8080 | BM25: 8080 | BN25: 8080 | BO25: 8080 | BP25: 8080
A26: 移行施設外基本報酬 | E26: =E25 -> 8200 | F26: =F25 -> 8200 | G26: =G25 -> 8200 | H26: =H25 -> 8200 | I26: =I25 -> 8200 | J26: =J25 -> 8200 | K26: =K25 -> 8200 | L26: =L25 -> 8200 | ... P26: =P25 -> 8200 | R26: =R25 -> 8200 | S26: =S25 -> 8200 | T26: =T25 -> 8200 | U26: =U25 -> 8200 | V26: =V25 -> 8200 | W26: =W25 -> 8200 | X26: =X25 -> 8200 | Y26: =Y25 -> 8200 | ... AC26: =AC25 -> 8200 | AE26: 9080 | AF26: 9080 | AG26: 9080 | AH26: 9080 | AI26: 9080 | AJ26: 9080 | AK26: 9080 | AL26: 9080 | AM26: 9080 | AN26: 9080 | AO26: 9080 | AP26: 9080 | AR26: 9080 | AS26: 9080 | AT26: 9080 | AU26: 9080 | AV26: 9080 | AW26: 9080 | AX26: 9080 | AY26: 9080 | AZ26: 9080 | BA26: 9080 | BB26: 9080 | BC26: 9080 | BE26: 9080 | BF26: 9080 | BG26: 9080 | BH26: 9080 | BI26: 9080 | BJ26: 9080 | BK26: 9080 | BL26: 9080 | BM26: 9080 | BN26: 9080 | BO26: 9080 | BP26: 9080
A27: 目標工賃達成指導員加算 | E27: 890 | F27: 890 | G27: 890 | H27: 890 | I27: 890 | J27: 890 | K27: 890 | L27: 890 | M27: 890 | N27: 890 | O27: 890 | P27: 890 | R27: 890 | S27: 890 | T27: 890 | U27: 890 | V27: 890 | W27: 890 | X27: 890 | Y27: 890 | Z27: 890 | AA27: 890 | AB27: 890 | AC27: 890 | AE27: 890 | AF27: 890 | AG27: 890 | AH27: 890 | AI27: 890 | AJ27: 890 | AK27: 890 | AL27: 890 | AM27: 890 | AN27: 890 | AO27: 890 | AP27: 890 | AR27: 890 | AS27: 890 | AT27: 890 | AU27: 890 | AV27: 890 | AW27: 890 | AX27: 890 | AY27: 890 | AZ27: 890 | BA27: 890 | BB27: 890 | BC27: 890 | BE27: 890 | BF27: 890 | BG27: 890 | BH27: 890 | BI27: 890 | BJ27: 890 | BK27: 890 | BL27: 890 | BM27: 890 | BN27: 890 | BO27: 890 | BP27: 890
A28: 送迎加算 | E28: 540 | F28: 540 | G28: 540 | H28: 540 | I28: 540 | J28: 540 | K28: 540 | L28: 540 | M28: 540 | N28: 540 | O28: 540 | P28: 540 | R28: 540 | S28: 540 | T28: 540 | U28: 540 | V28: 540 | W28: 540 | X28: 540 | Y28: 540 | Z28: 540 | AA28: 540 | AB28: 540 | AC28: 540 | AE28: 540 | AF28: 540 | AG28: 540 | AH28: 540 | AI28: 540 | AJ28: 540 | AK28: 540 | AL28: 540 | AM28: 540 | AN28: 540 | AO28: 540 | AP28: 540 | AR28: 540 | AS28: 540 | AT28: 540 | AU28: 540 | AV28: 540 | AW28: 540 | AX28: 540 | AY28: 540 | AZ28: 540 | BA28: 540 | BB28: 540 | BC28: 540 | BE28: 540 | BF28: 540 | BG28: 540 | BH28: 540 | BI28: 540 | BJ28: 540 | BK28: 540 | BL28: 540 | BM28: 540 | BN28: 540 | BO28: 540 | BP28: 540
A29: 稼働率 | E29: 0.8 | F29: 0.8 | G29: 0.8 | H29: 0.8 | I29: 0.8 | J29: 0.8 | K29: 0.8 | L29: 0.8 | M29: 0.8 | N29: 0.8 | O29: 0.8 | P29: 0.8 | R29: 0.75 | S29: 0.75 | T29: 0.75 | U29: 0.75 | V29: 0.75 | W29: 0.75 | X29: 0.75 | Y29: 0.75 | Z29: 0.75 | AA29: 0.75 | AB29: 0.75 | AC29: 0.75 | AE29: 0.75 | AF29: 0.75 | AG29: 0.75 | AH29: 0.75 | AI29: 0.75 | AJ29: 0.75 | AK29: 0.75 | AL29: 0.75 | AM29: 0.75 | AN29: 0.75 | AO29: 0.75 | AP29: 0.75 | AR29: 0.75 | AS29: 0.75 | AT29: 0.75 | AU29: 0.75 | AV29: 0.75 | AW29: 0.75 | AX29: 0.75 | AY29: 0.75 | AZ29: 0.75 | BA29: 0.75 | BB29: 0.75 | BC29: 0.75 | BE29: 0.75 | BF29: 0.75 | BG29: 0.75 | BH29: 0.75 | BI29: 0.75 | BJ29: 0.75 | BK29: 0.75 | BL29: 0.75 | BM29: 0.75 | BN29: 0.75 | BO29: 0.75 | BP29: 0.75
A32: B人員配置 | E32: =ROUNDUP(E6/7.5,0) -> 0 | F32: =ROUNDUP(F6/7.5,0) -> 0 | G32: =ROUNDUP(G6/7.5,1) -> 0 | H32: =ROUNDUP(H6/7.5,1) -> 0 | I32: =ROUNDUP(I6/7.5,1) -> 0 | J32: =ROUNDUP(J6/7.5,1) -> 0 | K32: =ROUNDUP(K6/7.5,1) -> 0 | L32: =ROUNDUP(L6/7.5,1) -> 0 | M32: =ROUNDUP(M6/7.5,1) -> 0 | N32: =ROUNDUP(N6/7.5,1) -> 0 | ... P32: =ROUNDUP(P6/7.5,1) -> 0 | R32: =ROUNDUP(R6/7.5,0) -> 0 | S32: =ROUNDUP(S6/7.5,0) -> 0 | T32: =ROUNDUP(T6/7.5,1) -> 0 | U32: =ROUNDUP(U6/7.5,1) -> 0 | V32: =ROUNDUP(V6/7.5,1) -> 0 | W32: =ROUNDUP(W6/7.5,1) -> 0 | X32: =ROUNDUP(X6/7.5,1) -> 0 | Y32: =ROUNDUP(Y6/7.5,1) -> 0 | Z32: =ROUNDUP(Z6/7.5,1) -> 0 | AA32: =ROUNDUP(AA6/7.5,1) -> 0 | ... AC32: =ROUNDUP(AC6/7.5,1) -> 0 | AE32: =ROUNDUP(AE6/7.5,0) -> 0 | AF32: =ROUNDUP(AF6/7.5,0) -> 0 | AG32: =ROUNDUP(AG6/7.5,1) -> 0 | AH32: =ROUNDUP(AH6/7.5,1) -> 0 | AI32: =ROUNDUP(AI6/7.5,1) -> 0 | AJ32: =ROUNDUP(AJ6/7.5,1) -> 0 | AK32: =ROUNDUP(AK6/7.5,1) -> 0 | AL32: =ROUNDUP(AL6/7.5,1) -> 0 | AM32: =ROUNDUP(AM6/7.5,1) -> 0 | AN32: =ROUNDUP(AN6/7.5,1) -> 0 | ... AP32: =ROUNDUP(AP6/7.5,1) -> 0 | AR32: =ROUNDUP(AR6/7.5,0) -> 2 | AS32: =ROUNDUP(AS6/7.5,0) -> 2 | AT32: =ROUNDUP(AT6/7.5,1) -> 1.4 | AU32: =ROUNDUP(AU6/7.5,1) -> 1.4 | AV32: =ROUNDUP(AV6/7.5,1) -> 1.4 | AW32: =ROUNDUP(AW6/7.5,1) -> 1.4 | AX32: =ROUNDUP(AX6/7.5,1) -> 1.4 | AY32: =ROUNDUP(AY6/7.5,1) -> 1.4 | AZ32: =ROUNDUP(AZ6/7.5,1) -> 1.4 | BA32: =ROUNDUP(BA6/7.5,1) -> 1.4 | ... BC32: =ROUNDUP(BC6/7.5,1) -> 1.4 | BE32: =ROUNDUP(BE6/7.5,0) -> 2 | BF32: =ROUNDUP(BF6/7.5,0) -> 2 | BG32: =ROUNDUP(BG6/7.5,1) -> 1.4 | BH32: =ROUNDUP(BH6/7.5,1) -> 1.4 | BI32: =ROUNDUP(BI6/7.5,1) -> 1.4 | BJ32: =ROUNDUP(BJ6/7.5,1) -> 1.4 | BK32: =ROUNDUP(BK6/7.5,1) -> 1.4 | BL32: =ROUNDUP(BL6/7.5,1) -> 1.4 | BM32: =ROUNDUP(BM6/7.5,1) -> 1.4 | BN32: =ROUNDUP(BN6/7.5,1) -> 1.4 | ... BP32: =ROUNDUP(BP6/7.5,1) -> 1.4
A33: B人工賃向上・施設外 | E33: =IF(E7/7.5<1,2,1+E7/7.5) -> 2 | F33: =IF(F7/7.5<1,2,1+F7/7.5) -> 2 | G33: =IF(G7/7.5<1,2,1+G7/7.5) -> 2 | H33: =IF(H7/7.5<1,2,1+H7/7.5) -> 2 | I33: =IF(I7/7.5<1,2,1+I7/7.5) -> 2 | J33: =IF(J7/7.5<1,2,1+J7/7.5) -> 2 | K33: =IF(K7/7.5<1,2,1+K7/7.5) -> 2 | L33: =IF(L7/7.5<1,2,1+L7/7.5) -> 2 | ... P33: =IF(P7/7.5<1,2,1+P7/7.5) -> 2 | R33: =IF(R7/7.5<1,2,1+R7/7.5) -> 2 | S33: =IF(S7/7.5<1,2,1+S7/7.5) -> 2 | T33: =IF(T7/7.5<1,2,1+T7/7.5) -> 2 | U33: =IF(U7/7.5<1,2,1+U7/7.5) -> 2 | V33: =IF(V7/7.5<1,2,1+V7/7.5) -> 2 | W33: =IF(W7/7.5<1,2,1+W7/7.5) -> 2 | X33: =IF(X7/7.5<1,2,1+X7/7.5) -> 2 | Y33: =IF(Y7/7.5<1,2,1+Y7/7.5) -> 2 | ... AC33: =IF(AC7/7.5<1,2,1+AC7/7.5) -> 2 | AE33: =IF(AE7/7.5<1,2,1+AE7/7.5) -> 2 | AF33: =IF(AF7/7.5<1,2,1+AF7/7.5) -> 2 | AG33: =IF(AG7/7.5<1,2,1+AG7/7.5) -> 2 | AH33: =IF(AH7/7.5<1,2,1+AH7/7.5) -> 2 | AI33: =IF(AI7/7.5<1,2,1+AI7/7.5) -> 2 | AJ33: =IF(AJ7/7.5<1,2,1+AJ7/7.5) -> 2 | AK33: =IF(AK7/7.5<1,2,1+AK7/7.5) -> 2 | AL33: =IF(AL7/7.5<1,2,1+AL7/7.5) -> 2 | ... AP33: =IF(AP7/7.5<1,2,1+AP7/7.5) -> 2 | AR33: =IF(AR7/7.5<1,2,1+AR7/7.5) -> 2.3333333 | AS33: =IF(AS7/7.5<1,2,1+AS7/7.5) -> 2.3333333 | AT33: =IF(AT7/7.5<1,2,1+AT7/7.5) -> 2.3333333 | AU33: =IF(AU7/7.5<1,2,1+AU7/7.5) -> 2.3333333 | AV33: =IF(AV7/7.5<1,2,1+AV7/7.5) -> 2.3333333 | AW33: =IF(AW7/7.5<1,2,1+AW7/7.5) -> 2.3333333 | AX33: =IF(AX7/7.5<1,2,1+AX7/7.5) -> 2.3333333 | AY33: =IF(AY7/7.5<1,2,1+AY7/7.5) -> 2.3333333 | ... BC33: =IF(BC7/7.5<1,2,1+BC7/7.5) -> 2.3333333 | BE33: =IF(BE7/7.5<1,2,1+BE7/7.5) -> 2.3333333 | BF33: =IF(BF7/7.5<1,2,1+BF7/7.5) -> 2.3333333 | BG33: =IF(BG7/7.5<1,2,1+BG7/7.5) -> 2.3333333 | BH33: =IF(BH7/7.5<1,2,1+BH7/7.5) -> 2.3333333 | BI33: =IF(BI7/7.5<1,2,1+BI7/7.5) -> 2.3333333 | BJ33: =IF(BJ7/7.5<1,2,1+BJ7/7.5) -> 2.3333333 | BK33: =IF(BK7/7.5<1,2,1+BK7/7.5) -> 2.3333333 | BL33: =IF(BL7/7.5<1,2,1+BL7/7.5) -> 2.3333333 | ... BP33: =IF(BP7/7.5<1,2,1+BP7/7.5) -> 2.3333333
A34: 移行人員配置 | E34: =ROUNDUP(E9/6,0) -> 0 | F34: =(F9+F10)/6 -> 0 | G34: =(G9+G10)/6 -> 0 | H34: =(H9+H10)/6 -> 0 | I34: =(I9+I10)/6 -> 0 | J34: =(J9+J10)/6 -> 0 | K34: =(K9+K10)/6 -> 0 | L34: =(L9+L10)/6 -> 0 | M34: =(M9+M10)/6 -> 0.33333333 | ... P34: =(P9+P10)/6 -> 0.83333333 | R34: =ROUNDUP(R9/6,1) -> 1.7 | S34: =(S9+S10)/6 -> 2.3333333 | T34: =(T9+T10)/6 -> 2.5 | U34: =(U9+U10)/6 -> 2.6666667 | V34: =(V9+V10)/6 -> 3.1666667 | W34: =(W9+W10)/6 -> 3.3333333 | X34: =(X9+X10)/6 -> 3.5 | Y34: =(Y9+Y10)/6 -> 3.6666667 | Z34: =(Z9+Z10)/6 -> 3.8333333 | ... AC34: =(AC9+AC10)/6 -> 4.3333333 | AE34: =ROUNDUP(AE9/6,1) -> 1.7 | AF34: =(AF9+AF10)/6 -> 3.3333333 | AG34: =(AG9+AG10)/6 -> 3.3333333 | AH34: =(AH9+AH10)/6 -> 3.3333333 | AI34: =(AI9+AI10)/6 -> 3.3333333 | AJ34: =(AJ9+AJ10)/6 -> 3.3333333 | AK34: =(AK9+AK10)/6 -> 3.3333333 | AL34: =(AL9+AL10)/6 -> 3.3333333 | AM34: =(AM9+AM10)/6 -> 3.3333333 | ... AP34: =(AP9+AP10)/6 -> 3.3333333 | AR34: =ROUNDUP(AR9/6,1) -> 1.7 | AS34: =(AS9+AS10)/6 -> 3.3333333 | AT34: =(AT9+AT10)/6 -> 3.3333333 | AU34: =(AU9+AU10)/6 -> 3.3333333 | AV34: =(AV9+AV10)/6 -> 3.3333333 | AW34: =(AW9+AW10)/6 -> 3.3333333 | AX34: =(AX9+AX10)/6 -> 3.3333333 | AY34: =(AY9+AY10)/6 -> 3.3333333 | AZ34: =(AZ9+AZ10)/6 -> 3.3333333 | ... BC34: =(BC9+BC10)/6 -> 3.3333333 | BE34: =ROUNDUP(BE9/6,1) -> 1.7 | BF34: =(BF9+BF10)/6 -> 3.3333333 | BG34: =(BG9+BG10)/6 -> 3.3333333 | BH34: =(BH9+BH10)/6 -> 3.3333333 | BI34: =(BI9+BI10)/6 -> 3.3333333 | BJ34: =(BJ9+BJ10)/6 -> 3.3333333 | BK34: =(BK9+BK10)/6 -> 3.3333333 | BL34: =(BL9+BL10)/6 -> 3.3333333 | BM34: =(BM9+BM10)/6 -> 3.3333333 | ... BP34: =(BP9+BP10)/6 -> 3.3333333
A35: 移行就労支援員配置 | E35: =IF((E9+E10)/15<1,1,(E9+E10)/15) -> 1 | F35: =IF((F9+F10)/15<1,1,(F9+F10)/15) -> 1 | G35: =IF((G9+G10)/15<1,1,(G9+G10)/15) -> 1 | H35: =IF((H9+H10)/15<1,1,(H9+H10)/15) -> 1 | I35: =IF((I9+I10)/15<1,1,(I9+I10)/15) -> 1 | J35: =IF((J9+J10)/15<1,1,(J9+J10)/15) -> 1 | K35: =IF((K9+K10)/15<1,1,(K9+K10)/15) -> 1 | L35: =IF((L9+L10)/15<1,1,(L9+L10)/15) -> 1 | ... P35: =IF((P9+P10)/15<1,1,(P9+P10)/15) -> 1 | R35: =IF((R9+R10)/15<1,1,(R9+R10)/15) -> 1 | S35: =IF((S9+S10)/15<1,1,(S9+S10)/15) -> 1 | T35: =IF((T9+T10)/15<1,1,(T9+T10)/15) -> 1 | U35: =IF((U9+U10)/15<1,1,(U9+U10)/15) -> 1.0666667 | V35: =IF((V9+V10)/15<1,1,(V9+V10)/15) -> 1.2666667 | W35: =IF((W9+W10)/15<1,1,(W9+W10)/15) -> 1.3333333 | X35: =IF((X9+X10)/15<1,1,(X9+X10)/15) -> 1.4 | Y35: =IF((Y9+Y10)/15<1,1,(Y9+Y10)/15) -> 1.4666667 | ... AC35: =IF((AC9+AC10)/15<1,1,(AC9+AC10)/15) -> 1.7333333 | AE35: =IF((AE9+AE10)/15<1,1,(AE9+AE10)/15) -> 1.3333333 | AF35: =IF((AF9+AF10)/15<1,1,(AF9+AF10)/15) -> 1.3333333 | AG35: =IF((AG9+AG10)/15<1,1,(AG9+AG10)/15) -> 1.3333333 | AH35: =IF((AH9+AH10)/15<1,1,(AH9+AH10)/15) -> 1.3333333 | AI35: =IF((AI9+AI10)/15<1,1,(AI9+AI10)/15) -> 1.3333333 | AJ35: =IF((AJ9+AJ10)/15<1,1,(AJ9+AJ10)/15) -> 1.3333333 | AK35: =IF((AK9+AK10)/15<1,1,(AK9+AK10)/15) -> 1.3333333 | AL35: =IF((AL9+AL10)/15<1,1,(AL9+AL10)/15) -> 1.3333333 | ... AP35: =IF((AP9+AP10)/15<1,1,(AP9+AP10)/15) -> 1.3333333 | AR35: =IF((AR9+AR10)/15<1,1,(AR9+AR10)/15) -> 1.3333333 | AS35: =IF((AS9+AS10)/15<1,1,(AS9+AS10)/15) -> 1.3333333 | AT35: =IF((AT9+AT10)/15<1,1,(AT9+AT10)/15) -> 1.3333333 | AU35: =IF((AU9+AU10)/15<1,1,(AU9+AU10)/15) -> 1.3333333 | AV35: =IF((AV9+AV10)/15<1,1,(AV9+AV10)/15) -> 1.3333333 | AW35: =IF((AW9+AW10)/15<1,1,(AW9+AW10)/15) -> 1.3333333 | AX35: =IF((AX9+AX10)/15<1,1,(AX9+AX10)/15) -> 1.3333333 | AY35: =IF((AY9+AY10)/15<1,1,(AY9+AY10)/15) -> 1.3333333 | ... BC35: =IF((BC9+BC10)/15<1,1,(BC9+BC10)/15) -> 1.3333333 | BE35: =IF((BE9+BE10)/15<1,1,(BE9+BE10)/15) -> 1.3333333 | BF35: =IF((BF9+BF10)/15<1,1,(BF9+BF10)/15) -> 1.3333333 | BG35: =IF((BG9+BG10)/15<1,1,(BG9+BG10)/15) -> 1.3333333 | BH35: =IF((BH9+BH10)/15<1,1,(BH9+BH10)/15) -> 1.3333333 | BI35: =IF((BI9+BI10)/15<1,1,(BI9+BI10)/15) -> 1.3333333 | BJ35: =IF((BJ9+BJ10)/15<1,1,(BJ9+BJ10)/15) -> 1.3333333 | BK35: =IF((BK9+BK10)/15<1,1,(BK9+BK10)/15) -> 1.3333333 | BL35: =IF((BL9+BL10)/15<1,1,(BL9+BL10)/15) -> 1.3333333 | ... BP35: =IF((BP9+BP10)/15<1,1,(BP9+BP10)/15) -> 1.3333333
A36: 移行施設外支援配置 | E36: =IF(E10/6<1,1,E10/6) -> 1 | F36: =IF(F10/6<1,1,F10/6) -> 1 | G36: =IF(G10/6<1,1,G10/6) -> 1 | H36: =IF(H10/6<1,1,H10/6) -> 1 | I36: =IF(I10/6<1,1,I10/6) -> 1 | J36: =IF(J10/6<1,1,J10/6) -> 1 | K36: =IF(K10/6<1,1,K10/6) -> 1 | L36: =IF(L10/6<1,1,L10/6) -> 1 | ... P36: =IF(P10/6<1,1,P10/6) -> 1 | R36: =IF(R10/6<1,1,R10/6) -> 1 | S36: =IF(S10/6<1,1,S10/6) -> 1 | T36: =IF(T10/6<1,1,T10/6) -> 1 | U36: =IF(U10/6<1,1,U10/6) -> 1 | V36: =IF(V10/6<1,1,V10/6) -> 1 | W36: =IF(W10/6<1,1,W10/6) -> 1 | X36: =IF(X10/6<1,1,X10/6) -> 1 | Y36: =IF(Y10/6<1,1,Y10/6) -> 1 | ... AC36: =IF(AC10/6<1,1,AC10/6) -> 1.5 | AE36: =IF(AE10/6<1,1,AE10/6) -> 1.6666667 | AF36: =IF(AF10/6<1,1,AF10/6) -> 1.6666667 | AG36: =IF(AG10/6<1,1,AG10/6) -> 1.6666667 | AH36: =IF(AH10/6<1,1,AH10/6) -> 1.6666667 | AI36: =IF(AI10/6<1,1,AI10/6) -> 1.6666667 | AJ36: =IF(AJ10/6<1,1,AJ10/6) -> 1.6666667 | AK36: =IF(AK10/6<1,1,AK10/6) -> 1.6666667 | AL36: =IF(AL10/6<1,1,AL10/6) -> 1.6666667 | ... AP36: =IF(AP10/6<1,1,AP10/6) -> 1.6666667 | AR36: =IF(AR10/6<1,1,AR10/6) -> 1.6666667 | AS36: =IF(AS10/6<1,1,AS10/6) -> 1.6666667 | AT36: =IF(AT10/6<1,1,AT10/6) -> 1.6666667 | AU36: =IF(AU10/6<1,1,AU10/6) -> 1.6666667 | AV36: =IF(AV10/6<1,1,AV10/6) -> 1.6666667 | AW36: =IF(AW10/6<1,1,AW10/6) -> 1.6666667 | AX36: =IF(AX10/6<1,1,AX10/6) -> 1.6666667 | AY36: =IF(AY10/6<1,1,AY10/6) -> 1.6666667 | ... BC36: =IF(BC10/6<1,1,BC10/6) -> 1.6666667 | BE36: =IF(BE10/6<1,1,BE10/6) -> 1.6666667 | BF36: =IF(BF10/6<1,1,BF10/6) -> 1.6666667 | BG36: =IF(BG10/6<1,1,BG10/6) -> 1.6666667 | BH36: =IF(BH10/6<1,1,BH10/6) -> 1.6666667 | BI36: =IF(BI10/6<1,1,BI10/6) -> 1.6666667 | BJ36: =IF(BJ10/6<1,1,BJ10/6) -> 1.6666667 | BK36: =IF(BK10/6<1,1,BK10/6) -> 1.6666667 | BL36: =IF(BL10/6<1,1,BL10/6) -> 1.6666667 | ... BP36: =IF(BP10/6<1,1,BP10/6) -> 1.6666667
A38: 管理者 | K38: =900*7*20 -> 126000 | L38: 126000 | M38: 126000 | N38: 230000 | O38: 230000 | P38: 230000 | R38: =P38 -> 230000 | S38: =R38 -> 230000 | T38: =S38 -> 230000 | U38: =T38 -> 230000 | V38: =U38 -> 230000 | W38: =V38 -> 230000 | X38: =W38 -> 230000 | Y38: =X38 -> 230000 | Z38: =Y38 -> 230000 | ... AC38: =AB38 -> 230000 | BE38: 180000 | BF38: 180000 | BG38: 180000 | BH38: 180000 | BI38: 180000 | BJ38: 180000 | BK38: 180000 | BL38: 180000 | BM38: 180000 | BN38: 180000 | BO38: 180000 | BP38: 180000
A39: サビ管 ⇒ 山内（１２月） | R39: =P39 -> 0 | S39: =R39 -> 0 | T39: =S39 -> 0 | U39: =T39 -> 0 | V39: =U39 -> 0 | W39: =V39 -> 0 | X39: =W39 -> 0 | Y39: =X39 -> 0 | Z39: =Y39 -> 0 | ... AC39: =AB39 -> 0
A40: 職業指導員 | L40: =900*7*20 -> 126000 | M40: 126000 | N40: 126000 | O40: 200000 | P40: 200000 | R40: 200000 | S40: =R40 -> 200000 | T40: =S40 -> 200000 | U40: =T40 -> 200000 | V40: =U40 -> 200000 | W40: =V40 -> 200000 | X40: =W40 -> 200000 | Y40: =X40 -> 200000 | Z40: =Y40 -> 200000 | ... AC40: =AB40 -> 200000 | BE40: 150000 | BF40: 150000 | BG40: 150000 | BH40: 150000 | BI40: 150000 | BJ40: 150000 | BK40: 150000 | BL40: 150000 | BM40: 150000 | BN40: 150000 | BO40: 150000 | BP40: 150000
A41: 職業指導員 | L41: =900*7*20 -> 126000 | M41: 126000 | N41: 126000 | O41: 200000 | P41: 200000 | R41: 200000 | S41: =R41 -> 200000 | T41: =S41 -> 200000 | U41: =T41 -> 200000 | V41: =U41 -> 200000 | W41: =V41 -> 200000 | X41: =W41 -> 200000 | Y41: =X41 -> 200000 | Z41: =Y41 -> 200000 | ... AC41: =AB41 -> 200000 | BE41: 180000 | BF41: 180000 | BG41: 180000 | BH41: 180000 | BI41: 180000 | BJ41: 180000 | BK41: 180000 | BL41: 180000 | BM41: 180000 | BN41: 180000 | BO41: 180000 | BP41: 180000
A42: 職業指導員 | N42: =900*7*20 -> 126000 | O42: =900*7*20 -> 126000 | P42: 126000 | R42: =P42 -> 126000 | S42: =R42 -> 126000 | T42: =S42 -> 126000 | U42: =T42 -> 126000 | V42: =U42 -> 126000 | W42: =V42 -> 126000 | X42: =W42 -> 126000 | Y42: =X42 -> 126000 | Z42: =Y42 -> 126000 | ... AC42: =AB42 -> 126000 | BE42: 180000 | BF42: 180000 | BG42: 180000 | BH42: 180000 | BI42: 180000 | BJ42: 180000 | BK42: 180000 | BL42: 180000 | BM42: 180000 | BN42: 180000 | BO42: 180000 | BP42: 180000
A43: 生活支援員 | L43: 80000 | M43: 80000 | N43: 80000 | O43: 80000 | P43: 80000 | R43: =P43 -> 80000 | S43: =R43 -> 80000 | T43: =S43 -> 80000 | U43: =T43 -> 80000 | V43: =U43 -> 80000 | W43: =V43 -> 80000 | X43: =W43 -> 80000 | Y43: =X43 -> 80000 | Z43: =Y43 -> 80000 | ... AC43: =AB43 -> 80000 | BE43: 180000 | BF43: 180000 | BG43: 180000 | BH43: 180000 | BI43: 180000 | BJ43: 180000 | BK43: 180000 | BL43: 180000 | BM43: 180000 | BN43: 180000 | BO43: 180000 | BP43: 180000
BE44: 150000 | BF44: 150000 | BG44: 150000 | BH44: 150000 | BI44: 150000 | BJ44: 150000 | BK44: 150000 | BL44: 150000 | BM44: 150000 | BN44: 150000 | BO44: 150000 | BP44: 150000
A45: 就労支援員 | L45: 0 | M45: 0 | N45: 126000 | O45: 126000 | P45: 126000 | R45: 200000 | S45: =R45 -> 200000 | T45: =S45 -> 200000 | U45: =T45 -> 200000 | V45: =U45 -> 200000 | W45: =V45 -> 200000 | X45: =W45 -> 200000 | Y45: =X45 -> 200000 | Z45: =Y45 -> 200000 | ... AC45: =AB45 -> 200000 | BE45: 250000 | BF45: 250000 | BG45: 250000 | BH45: 250000 | BI45: 250000 | BJ45: 250000 | BK45: 250000 | BL45: 250000 | BM45: 250000 | BN45: 250000 | BO45: 250000 | BP45: 250000
A46: 就労支援員 | S46: =R46 -> 0 | T46: =S46 -> 0 | U46: =T46 -> 0 | V46: =U46 -> 0 | W46: =V46 -> 0 | X46: =W46 -> 0 | Y46: =X46 -> 0 | Z46: =Y46 -> 0 | ... AC46: =AB46 -> 0 | BE46: 180000 | BF46: 180000 | BG46: 180000 | BH46: 180000 | BI46: 180000 | BJ46: 180000 | BK46: 180000 | BL46: 180000 | BM46: 180000 | BN46: 180000 | BO46: 180000 | BP46: 180000
A47: 生活支援員等 | S47: =R47 -> 0 | T47: =S47 -> 0 | U47: =T47 -> 0 | V47: =U47 -> 0 | W47: =V47 -> 0 | X47: =W47 -> 0 | Y47: =X47 -> 0 | Z47: =Y47 -> 0 | ... AC47: =AB47 -> 0 | BE47: 180000 | BF47: 180000 | BG47: 180000 | BH47: 180000 | BI47: 180000 | BJ47: 180000 | BK47: 180000 | BL47: 180000 | BM47: 180000 | BN47: 180000 | BO47: 180000 | BP47: 180000
A48: 就労支援員 | S48: =R48 -> 0 | T48: =S48 -> 0 | U48: =T48 -> 0 | V48: =U48 -> 0 | W48: =V48 -> 0 | X48: =W48 -> 0 | Y48: =X48 -> 0 | Z48: =Y48 -> 0 | ... AC48: =AB48 -> 0 | BE48: 250000 | BF48: 250000 | BG48: 250000 | BH48: 250000 | BI48: 250000 | BJ48: 250000 | BK48: 250000 | BL48: 250000 | BM48: 250000 | BN48: 250000 | BO48: 250000 | BP48: 250000
A49: 講師 | R49: 55000 | S49: =R49 -> 55000 | T49: =S49 -> 55000 | U49: =T49 -> 55000 | V49: =U49 -> 55000 | W49: =V49 -> 55000 | X49: =W49 -> 55000 | Y49: =X49 -> 55000 | Z49: =Y49 -> 55000 | ... AC49: =AB49 -> 55000 | BE49: 300000 | BF49: 300000 | BG49: 300000 | BH49: 300000 | BI49: 300000 | BJ49: 300000 | BK49: 300000 | BL49: 300000 | BM49: 300000 | BN49: 300000 | BO49: 300000 | BP49: 300000
A50: 講師 | R50: =P50 -> 0 | S50: =R50 -> 0 | T50: =S50 -> 0 | U50: =T50 -> 0 | V50: =U50 -> 0 | W50: =V50 -> 0 | X50: =W50 -> 0 | Y50: =X50 -> 0 | Z50: =Y50 -> 0 | ... AC50: =AB50 -> 0 | BE50: 300000 | BF50: 300000 | BG50: 300000 | BH50: 300000 | BI50: 300000 | BJ50: 300000 | BK50: 300000 | BL50: 300000 | BM50: 300000 | BN50: 300000 | BO50: 300000 | BP50: 300000
A51: 講師 | R51: =P51 -> 0 | S51: =R51 -> 0 | T51: =S51 -> 0 | U51: =T51 -> 0 | V51: =U51 -> 0 | W51: =V51 -> 0 | X51: =W51 -> 0 | Y51: =X51 -> 0 | Z51: =Y51 -> 0 | ... AC51: =AB51 -> 0 | BE51: 250000 | BF51: 250000 | BG51: 250000 | BH51: 250000 | BI51: 250000 | BJ51: 250000 | BK51: 250000 | BL51: 250000 | BM51: 250000 | BN51: 250000 | BO51: 250000 | BP51: 250000
A52: 講師 | R52: =P52 -> 0 | S52: =R52 -> 0 | T52: =S52 -> 0 | U52: =T52 -> 0 | V52: =U52 -> 0 | W52: =V52 -> 0 | X52: =W52 -> 0 | Y52: =X52 -> 0 | Z52: =Y52 -> 0 | ... AC52: =AB52 -> 0 | BE52: 180000 | BF52: 180000 | BG52: 180000 | BH52: 180000 | BI52: 180000 | BJ52: 180000 | BK52: 180000 | BL52: 180000 | BM52: 180000 | BN52: 180000 | BO52: 180000 | BP52: 180000
A53: 賞与 | Z53: 800000 | BJ53: 2000000 | BP53: 3000000
A54: 人件費合計 | E54: =SUM(E38:E52) -> 0 | F54: =SUM(F38:F52) -> 0 | G54: =SUM(G38:G52) -> 0 | H54: =SUM(H38:H52) -> 0 | I54: =SUM(I38:I52) -> 0 | J54: =SUM(J38:J52) -> 0 | K54: =SUM(K38:K52) -> 126000 | L54: =SUM(L38:L52) -> 458000 | ... P54: =SUM(P38:P52) -> 962000 | R54: =SUM(R38:R53) -> 1091000 | S54: =SUM(S38:S53) -> 1091000 | T54: =SUM(T38:T53) -> 1091000 | U54: =SUM(U38:U53) -> 1091000 | V54: =SUM(V38:V53) -> 1091000 | W54: =SUM(W38:W53) -> 1091000 | X54: =SUM(X38:X53) -> 1091000 | Y54: =SUM(Y38:Y53) -> 1091000 | ... AC54: =SUM(AC38:AC53) -> 1091000 | AE54: =SUM(AE38:AE52) -> 0 | AF54: =SUM(AF38:AF52) -> 0 | AG54: =SUM(AG38:AG52) -> 0 | AH54: =SUM(AH38:AH52) -> 0 | AI54: =SUM(AI38:AI52) -> 0 | AJ54: =SUM(AJ38:AJ52) -> 0 | AK54: =SUM(AK38:AK52) -> 0 | AL54: =SUM(AL38:AL52) -> 0 | ... AP54: =SUM(AP38:AP52) -> 0 | AR54: =SUM(AR38:AR52) -> 0 | AS54: =SUM(AS38:AS52) -> 0 | AT54: =SUM(AT38:AT52) -> 0 | AU54: =SUM(AU38:AU52) -> 0 | AV54: =SUM(AV38:AV52) -> 0 | AW54: =SUM(AW38:AW52) -> 0 | AX54: =SUM(AX38:AX52) -> 0 | AY54: =SUM(AY38:AY52) -> 0 | ... BC54: =SUM(BC38:BC52) -> 0 | BE54: =SUM(BE38:BE52) -> 2910000 | BF54: =SUM(BF38:BF52) -> 2910000 | BG54: =SUM(BG38:BG52) -> 2910000 | BH54: =SUM(BH38:BH52) -> 2910000 | BI54: =SUM(BI38:BI52) -> 2910000 | BJ54: =SUM(BJ38:BJ52) -> 2910000 | BK54: =SUM(BK38:BK52) -> 2910000 | BL54: =SUM(BL38:BL52) -> 2910000 | ... BP54: =SUM(BP38:BP52) -> 2910000
A55: 社会保険 | E55: =E54*0.1 -> 0 | F55: =F54*0.1 -> 0 | G55: =G54*0.1 -> 0 | H55: =H54*0.1 -> 0 | I55: =I54*0.1 -> 0 | J55: =J54*0.1 -> 0 | K55: =K54*0.13 -> 16380 | L55: =L54*0.13 -> 59540 | M55: =M54*0.13 -> 59540 | N55: =N54*0.13 -> 105820 | O55: =O54*0.13 -> 125060 | P55: =P54*0.13 -> 125060 | R55: =R54*0.13 -> 141830 | S55: =S54*0.13 -> 141830 | T55: =T54*0.13 -> 141830 | U55: =U54*0.13 -> 141830 | V55: =V54*0.13 -> 141830 | W55: =W54*0.13 -> 141830 | X55: =X54*0.13 -> 141830 | Y55: =Y54*0.13 -> 141830 | ... AC55: =AC54*0.13 -> 141830 | AE55: =AE54*0.1 -> 0 | AF55: =AF54*0.1 -> 0 | AG55: =AG54*0.1 -> 0 | AH55: =AH54*0.1 -> 0 | AI55: =AI54*0.1 -> 0 | AJ55: =AJ54*0.1 -> 0 | AK55: =AK54*0.1 -> 0 | AL55: =AL54*0.1 -> 0 | ... AP55: =AP54*0.1 -> 0 | AR55: =AR54*0.1 -> 0 | AS55: =AS54*0.1 -> 0 | AT55: =AT54*0.1 -> 0 | AU55: =AU54*0.1 -> 0 | AV55: =AV54*0.1 -> 0 | AW55: =AW54*0.1 -> 0 | AX55: =AX54*0.1 -> 0 | AY55: =AY54*0.1 -> 0 | ... BC55: =BC54*0.1 -> 0 | BE55: =BE54*0.1 -> 291000 | BF55: =BF54*0.1 -> 291000 | BG55: =BG54*0.1 -> 291000 | BH55: =BH54*0.1 -> 291000 | BI55: =BI54*0.1 -> 291000 | BJ55: =BJ54*0.1 -> 291000 | BK55: =BK54*0.1 -> 291000 | BL55: =BL54*0.1 -> 291000 | ... BP55: =BP54*0.1 -> 291000
A56: 人件費総計 | E56: =E54+E55 -> 0 | F56: =F54+F55 -> 0 | G56: =G54+G55 -> 0 | H56: =H54+H55 -> 0 | I56: =I54+I55 -> 0 | J56: =J54+J55 -> 0 | K56: =K54+K55 -> 142380 | L56: =L54+L55 -> 517540 | ... P56: =P54+P55 -> 1087060 | R56: =R54+R55 -> 1232830 | S56: =S54+S55 -> 1232830 | T56: =T54+T55 -> 1232830 | U56: =U54+U55 -> 1232830 | V56: =V54+V55 -> 1232830 | W56: =W54+W55 -> 1232830 | X56: =X54+X55 -> 1232830 | Y56: =Y54+Y55 -> 1232830 | ... AC56: =AC54+AC55 -> 1232830 | AE56: =AE54+AE55 -> 0 | AF56: =AF54+AF55 -> 0 | AG56: =AG54+AG55 -> 0 | AH56: =AH54+AH55 -> 0 | AI56: =AI54+AI55 -> 0 | AJ56: =AJ54+AJ55 -> 0 | AK56: =AK54+AK55 -> 0 | AL56: =AL54+AL55 -> 0 | ... AP56: =AP54+AP55 -> 0 | AR56: =AR54+AR55 -> 0 | AS56: =AS54+AS55 -> 0 | AT56: =AT54+AT55 -> 0 | AU56: =AU54+AU55 -> 0 | AV56: =AV54+AV55 -> 0 | AW56: =AW54+AW55 -> 0 | AX56: =AX54+AX55 -> 0 | AY56: =AY54+AY55 -> 0 | ... BC56: =BC54+BC55 -> 0 | BE56: =BE54+BE55 -> 3201000 | BF56: =BF54+BF55 -> 3201000 | BG56: =BG54+BG55 -> 3201000 | BH56: =BH54+BH55 -> 3201000 | BI56: =BI54+BI55 -> 3201000 | BJ56: =BJ54+BJ55 -> 3201000 | BK56: =BK54+BK55 -> 3201000 | BL56: =BL54+BL55 -> 3201000 | ... BP56: =BP54+BP55 -> 3201000
A58: 家賃 | K58: 43000 | L58: 43000 | M58: 43000 | N58: 51000 | O58: 51000 | P58: 51000 | R58: =P58 -> 51000 | S58: =R58 -> 51000 | T58: =S58 -> 51000 | U58: =T58 -> 51000 | V58: =U58 -> 51000 | W58: =V58 -> 51000 | X58: =W58 -> 51000 | Y58: =X58 -> 51000 | Z58: =Y58 -> 51000 | ... AC58: =AB58 -> 51000 | AK58: 43000 | AL58: 43000 | AM58: 43000 | AN58: 43000 | AO58: 43000 | AP58: 43000 | AX58: 43000 | AY58: 43000 | AZ58: 43000 | BA58: 43000 | BB58: 43000 | BC58: 43000
A59: 通信・光熱費 | K59: 10000 | L59: 15000 | M59: 15000 | N59: 15000 | O59: 15000 | P59: 15000 | R59: =P59 -> 15000 | S59: =R59 -> 15000 | T59: =S59 -> 15000 | U59: =T59 -> 15000 | V59: =U59 -> 15000 | W59: =V59 -> 15000 | X59: =W59 -> 15000 | Y59: =X59 -> 15000 | Z59: =Y59 -> 15000 | ... AC59: =AB59 -> 15000
A60: 交通費 | K60: 35000 | L60: 35000 | M60: 35000 | N60: 35000 | O60: 35000 | P60: 35000 | R60: 35000 | S60: 35000 | T60: 35000 | U60: 35000 | V60: 35000 | W60: 35000 | X60: 35000 | Y60: 35000 | Z60: 35000 | AA60: 35000 | AB60: 35000 | AC60: 35000
A61: 諸費 | K61: 20000 | L61: 20000 | M61: 20000 | N61: 20000 | O61: 20000 | P61: 20000 | R61: =P61 -> 20000 | S61: =R61 -> 20000 | T61: =S61 -> 20000 | U61: =T61 -> 20000 | V61: =U61 -> 20000 | W61: =V61 -> 20000 | X61: =W61 -> 20000 | Y61: =X61 -> 20000 | Z61: =Y61 -> 20000 | ... AC61: =AB61 -> 20000
A62: 固定費総計 | E62: =SUM(E58:E61) -> 0 | F62: =SUM(F58:F61) -> 0 | G62: =SUM(G58:G61) -> 0 | H62: =SUM(H58:H61) -> 0 | I62: =SUM(I58:I61) -> 0 | J62: =SUM(J58:J61) -> 0 | K62: =SUM(K58:K61) -> 108000 | L62: =SUM(L58:L61) -> 113000 | ... P62: =SUM(P58:P61) -> 121000 | R62: =SUM(R58:R61) -> 121000 | S62: =SUM(S58:S61) -> 121000 | T62: =SUM(T58:T61) -> 121000 | U62: =SUM(U58:U61) -> 121000 | V62: =SUM(V58:V61) -> 121000 | W62: =SUM(W58:W61) -> 121000 | X62: =SUM(X58:X61) -> 121000 | Y62: =SUM(Y58:Y61) -> 121000 | ... AC62: =SUM(AC58:AC61) -> 121000

Sheet 損益及び資金計画書
A1: R3年 | S1: R４年
D2: ４月 | E2: ５月 | F2: ６月 | G2: ７月 | H2: ８月 | I2: ９月 | J2: １０月 | K2: １１月 | L2: １２月 | M2: １月 | N2: ２月 | O2: ３月 | P2: 合計 | Q2: 対売上比率 | V2: ４月 | W2: ５月 | X2: ６月 | Y2: ７月 | Z2: ８月 | AA2: ９月 | AB2: １０月 | AC2: １１月 | AD2: １２月 | AE2: １月 | AF2: ２月 | AG2: ３月 | AH2: 合計 | AI2: 対売上比率
A3: 総売上 | D3: =D5+D9+D13+D12 -> 0 | E3: =E5+E9+E13+E12 -> 0 | F3: =F5+F9+F13+F12 -> 0 | G3: =G5+G9+G13+G12 -> 0 | H3: =H5+H9+H13+H12 -> 0 | I3: =I5+I9+I13+I12 -> 0 | J3: =J5+J9+J13+J12 -> 0 | K3: =K5+K9+K13+K12 -> 200000 | ... O3: =O5+O9+O13+O12 -> 1004000 | P3: =SUM(D3:O3) -> 2719700 | Q3: =P3/P3 -> 1 | S3: 総売上 | V3: =V5+V9+V13+V12 -> 1898400 | W3: =W5+W9+W13+W12 -> 2359800 | X3: =X5+X9+X13+X12 -> 2807300 | Y3: =Y5+Y9+Y13+Y12 -> 2849200 | Z3: =Z5+Z9+Z13+Z12 -> 3156900 | AA3: =AA5+AA9+AA13+AA12 -> 3436500 | AB3: =AB5+AB9+AB13+AB12 -> 3583400 | AC3: =AC5+AC9+AC13+AC12 -> 3730200 | ... AG3: =AG5+AG9+AG13+AG12 -> 4681100 | AH3: =SUM(V3:AG3) -> 39574500 | AI3: =AH3/P3 -> 14.551053
C4: 利用者総数 | D4: ='収支計画書（人材配置等）'!E12 -> 0 | E4: ='収支計画書（人材配置等）'!F12 -> 0 | F4: ='収支計画書（人材配置等）'!G12 -> 0 | G4: ='収支計画書（人材配置等）'!H12 -> 0 | H4: ='収支計画書（人材配置等）'!I12 -> 0 | I4: ='収支計画書（人材配置等）'!J12 -> 0 | J4: ='収支計画書（人材配置等）'!K12 -> 0 | K4: ='収支計画書（人材配置等）'!L12 -> 0 | ... M4: ='収支計画書（人材配置等）'!N12 -> 2 | N4: 2 | O4: 4 | U4: 利用者総数 | V4: ='収支計画書（人材配置等）'!R12 -> 10 | W4: ='収支計画書（人材配置等）'!S12 -> 14 | X4: ='収支計画書（人材配置等）'!T12 -> 15 | Y4: ='収支計画書（人材配置等）'!U12 -> 16 | Z4: ='収支計画書（人材配置等）'!V12 -> 19 | AA4: ='収支計画書（人材配置等）'!W12 -> 20 | AB4: ='収支計画書（人材配置等）'!X12 -> 21 | AC4: ='収支計画書（人材配置等）'!Y12 -> 22 | ... AG4: ='収支計画書（人材配置等）'!AC12 -> 26
B5: 訓練給付金等 | D5: =SUM(D6:D8) -> 0 | E5: =SUM(E6:E8) -> 0 | F5: =SUM(F6:F8) -> 0 | G5: =SUM(G6:G8) -> 0 | H5: =SUM(H6:H8) -> 0 | I5: =SUM(I6:I8) -> 0 | J5: =SUM(J6:J8) -> 0 | K5: =SUM(K6:K8) -> 0 | ... O5: =SUM(O6:O8) -> 804000 | P5: =SUM(D5:O5) -> 1719700 | Q5: =IF(P5=0,"",P5/$P$3) -> 0.63231239 | T5: 訓練給付金等 | V5: =SUM(V6:V8) -> 1398400 | W5: =SUM(W6:W8) -> 1859800 | X5: =SUM(X6:X8) -> 2307300 | Y5: =SUM(Y6:Y8) -> 2349200 | Z5: =SUM(Z6:Z8) -> 2656900 | AA5: =SUM(AA6:AA8) -> 2936500 | AB5: =SUM(AB6:AB8) -> 3083400 | AC5: =SUM(AC6:AC8) -> 3230200 | ... AG5: =SUM(AG6:AG8) -> 4181100 | AH5: =SUM(V5:AG5) -> 33574500 | AI5: =IF(AH5=0,"",AH5/AH$3) -> 0.84838722
D6: ='収支計画書（人材配置等）'!E20 -> 0 | E6: ='収支計画書（人材配置等）'!F20 -> 0 | F6: ='収支計画書（人材配置等）'!G20 -> 0 | G6: ='収支計画書（人材配置等）'!H20 -> 0 | H6: ='収支計画書（人材配置等）'!I20 -> 0 | I6: ='収支計画書（人材配置等）'!J20 -> 0 | J6: ='収支計画書（人材配置等）'!K20 -> 0 | K6: ='収支計画書（人材配置等）'!L20 -> 0 | ... O6: ='収支計画書（人材配置等）'!P20 -> 804000 | P6: =SUM(D6:O6) -> 1719700 | Q6: =IF(P6=0,"",P6/$P$3) -> 0.63231239 | U6: コーリングサポ笠岡 | V6: ='収支計画書（人材配置等）'!R20 -> 1398400 | W6: ='収支計画書（人材配置等）'!S20 -> 1859800 | X6: ='収支計画書（人材配置等）'!T20 -> 2307300 | Y6: ='収支計画書（人材配置等）'!U20 -> 2349200 | Z6: ='収支計画書（人材配置等）'!V20 -> 2656900 | AA6: ='収支計画書（人材配置等）'!W20 -> 2936500 | AB6: ='収支計画書（人材配置等）'!X20 -> 3083400 | AC6: ='収支計画書（人材配置等）'!Y20 -> 3230200 | ... AG6: ='収支計画書（人材配置等）'!AC20 -> 4181100 | AH6: =SUM(V6:AG6) -> 33574500 | AI6: =IF(AH6=0,"",AH6/AH$3) -> 0.84838722
AH7: =SUM(V7:AG7) -> 0 | AI7: =IF(AH7=0,"",AH7/AH$3)
P8: =SUM(D8:O8)*5000 -> 0 | Q8: =IF(P8=0,"",P8/$P$3) | AH8: =SUM(V8:AG8) -> 0 | AI8: =IF(AH8=0,"",AH8/AH$3)
B9: 福祉的就労売上 | D9: =SUM(D10:D11) -> 0 | E9: =SUM(E10:E11) -> 0 | F9: =SUM(F10:F11) -> 0 | G9: =SUM(G10:G11) -> 0 | H9: =SUM(H10:H11) -> 0 | I9: =SUM(I10:I11) -> 0 | J9: =SUM(J10:J11) -> 0 | K9: =SUM(K10:K11) -> 200000 | ... O9: =SUM(O10:O11) -> 200000 | P9: =SUM(D9:O9) -> 1000000 | Q9: =IF(P9=0,"",P9/$P$3) -> 0.36768761 | T9: 福祉的就労売上 | V9: =SUM(V10:V11) -> 500000 | W9: =SUM(W10:W11) -> 500000 | X9: =SUM(X10:X11) -> 500000 | Y9: =SUM(Y10:Y11) -> 500000 | Z9: =SUM(Z10:Z11) -> 500000 | AA9: =SUM(AA10:AA11) -> 500000 | AB9: =SUM(AB10:AB11) -> 500000 | AC9: =SUM(AC10:AC11) -> 500000 | ... AG9: =SUM(AG10:AG11) -> 500000 | AH9: =SUM(V9:AG9) -> 6000000 | AI9: =IF(AH9=0,"",AH9/AH$3) -> 0.15161278
K10: 200000 | L10: 200000 | M10: 200000 | N10: 200000 | O10: 200000 | P10: =SUM(D10:O10) -> 1000000 | Q10: =IF(P10=0,"",P10/$P$3) -> 0.36768761 | V10: 500000 | W10: 500000 | X10: 500000 | Y10: 500000 | Z10: 500000 | AA10: 500000 | AB10: 500000 | AC10: 500000 | AD10: 500000 | AE10: 500000 | AF10: 500000 | AG10: 500000 | AH10: =SUM(V10:AG10) -> 6000000 | AI10: =IF(AH10=0,"",AH10/AH$3) -> 0.15161278
Q11: =IF(P11=0,"",P11/$P$3) | AH11: =SUM(V11:AG11) -> 0 | AI11: =IF(AH11=0,"",AH11/AH$3)
B12: 特定困難者受給 | P12: =SUM(D12:O12) -> 0 | T12: 特定困難者受給 | AH12: =SUM(V12:AG12) -> 0 | AI12: =IF(AH12=0,"",AH12/AH$3)
B13: その他収入 | P13: =SUM(D13:O13) -> 0 | Q13: =IF(P13=0,"",P13/$P$3) | T13: その他収入 | AH13: =SUM(V13:AG13) -> 0 | AI13: =IF(AH13=0,"",AH13/AH$3)
B14: 事業原価 | D14: =SUM(D16:D20) -> 0 | E14: =SUM(E16:E20) -> 0 | F14: =SUM(F16:F20) -> 0 | G14: =SUM(G16:G20) -> 0 | H14: =SUM(H16:H20) -> 0 | I14: =SUM(I16:I20) -> 0 | J14: =SUM(J16:J20) -> 250380 | K14: =K15+K21 -> 830540 | L14: =L15+L21 -> 830540 | M14: =M15+M21 -> 1240820 | N14: =N15+N21 -> 1408060 | O14: =O15+O21 -> 1408060 | P14: =SUM(D14:O14) -> 5968400 | Q14: =IF(P14=0,"",P14/$P$3) -> 2.1945067 | T14: 部門別経費 | V14: =V15+V21 -> 1853830 | W14: =SUM(W16:W20) -> 1353830 | X14: =SUM(X16:X20) -> 1353830 | Y14: =SUM(Y16:Y20) -> 1353830 | Z14: =SUM(Z16:Z20) -> 1353830 | AA14: =SUM(AA16:AA20) -> 1353830 | AB14: =SUM(AB16:AB20) -> 1353830 | AC14: =SUM(AC16:AC20) -> 1353830 | AD14: =SUM(AD16:AD20) -> 2257830 | ... AG14: =SUM(AG16:AG20) -> 1353830 | AH14: =SUM(V14:AG14) -> 17649960 | AI14: =IF(AH14=0,"",AH14/AH$3) -> 0.44599325
B15: 訓練給付金等 | D15: =SUM(D16:D20) -> 0 | E15: =SUM(E16:E20) -> 0 | F15: =SUM(F16:F20) -> 0 | G15: =SUM(G16:G20) -> 0 | H15: =SUM(H16:H20) -> 0 | I15: =SUM(I16:I20) -> 0 | J15: =SUM(J16:J20) -> 250380 | K15: =SUM(K16:K20) -> 630540 | ... O15: =SUM(O16:O20) -> 1208060 | P15: =SUM(D15:O15) -> 4968400 | T15: 訓練給付金等 | V15: =SUM(V16:V20) -> 1353830 | W15: =SUM(W16:W20) -> 1353830 | X15: =SUM(X16:X20) -> 1353830 | Y15: =SUM(Y16:Y20) -> 1353830 | Z15: =SUM(Z16:Z20) -> 1353830 | AA15: =SUM(AA16:AA20) -> 1353830 | AB15: =SUM(AB16:AB20) -> 1353830 | AC15: =SUM(AC16:AC20) -> 1353830 | ... AG15: =SUM(AG16:AG20) -> 1353830 | AH15: =SUM(V15:AG15) -> 17149960 | AI15: =IF(AH15=0,"",AH15/AH$3) -> 0.43335885
C16: 人件費 | D16: ='収支計画書（人材配置等）'!E54 -> 0 | E16: ='収支計画書（人材配置等）'!F54 -> 0 | F16: ='収支計画書（人材配置等）'!G54 -> 0 | G16: ='収支計画書（人材配置等）'!H54 -> 0 | H16: ='収支計画書（人材配置等）'!I54 -> 0 | I16: ='収支計画書（人材配置等）'!J54 -> 0 | J16: ='収支計画書（人材配置等）'!K54 -> 126000 | K16: ='収支計画書（人材配置等）'!L54 -> 458000 | ... O16: ='収支計画書（人材配置等）'!P54 -> 962000 | P16: =SUM(D16:O16) -> 3780000 | Q16: =IF(P16=0,"",P16/$P$3) -> 1.3898592 | U16: 人件費 | V16: ='収支計画書（人材配置等）'!R54 -> 1091000 | W16: ='収支計画書（人材配置等）'!S54 -> 1091000 | X16: ='収支計画書（人材配置等）'!T54 -> 1091000 | Y16: ='収支計画書（人材配置等）'!U54 -> 1091000 | Z16: ='収支計画書（人材配置等）'!V54 -> 1091000 | AA16: ='収支計画書（人材配置等）'!W54 -> 1091000 | AB16: ='収支計画書（人材配置等）'!X54 -> 1091000 | AC16: ='収支計画書（人材配置等）'!Y54 -> 1091000 | ... AG16: ='収支計画書（人材配置等）'!AC54 -> 1091000 | AH16: =SUM(V16:AG16) -> 13892000 | AI16: =IF(AH16=0,"",AH16/AH$3) -> 0.35103413
C17: 社会保険料 | D17: ='収支計画書（人材配置等）'!E55 -> 0 | E17: ='収支計画書（人材配置等）'!F55 -> 0 | F17: ='収支計画書（人材配置等）'!G55 -> 0 | G17: ='収支計画書（人材配置等）'!H55 -> 0 | H17: ='収支計画書（人材配置等）'!I55 -> 0 | I17: ='収支計画書（人材配置等）'!J55 -> 0 | J17: ='収支計画書（人材配置等）'!K55 -> 16380 | K17: ='収支計画書（人材配置等）'!L55 -> 59540 | ... O17: ='収支計画書（人材配置等）'!P55 -> 125060 | P17: =SUM(D17:O17) -> 491400 | Q17: =IF(P17=0,"",P17/$P$3) -> 0.18068169 | U17: 社会保険料 | V17: ='収支計画書（人材配置等）'!R55 -> 141830 | W17: ='収支計画書（人材配置等）'!S55 -> 141830 | X17: ='収支計画書（人材配置等）'!T55 -> 141830 | Y17: ='収支計画書（人材配置等）'!U55 -> 141830 | Z17: ='収支計画書（人材配置等）'!V55 -> 141830 | AA17: ='収支計画書（人材配置等）'!W55 -> 141830 | AB17: ='収支計画書（人材配置等）'!X55 -> 141830 | AC17: ='収支計画書（人材配置等）'!Y55 -> 141830 | ... AG17: ='収支計画書（人材配置等）'!AC55 -> 141830 | AH17: =SUM(V17:AG17) -> 1805960 | AI17: =IF(AH17=0,"",AH17/AH$3) -> 0.045634436
