Workbook

Sheet 事業評価【A案・税引前】
E1: 1 | F1: 2 | G1: 3 | H1: 4 | I1: 5 | J1: 6 | K1: 7 | L1: 8 | M1: 9
B2: 企業価値A案（税引前） | M2: 【千円】
D3: H23年度 | E3: H24年度 | F3: H25年度 | G3: H26年度 | H3: H27年度 | I3: H28年度 | J3: H29年度 | K3: H30年度 | L3: H31年度 | M3: H32年度
B4: 前年度繰越 | D4: 0 | E4: =D40 -> #REF! | F4: =E40 -> #REF! | G4: =F40 -> #REF! | H4: =G40 -> #REF! | I4: =H40 -> #REF! | J4: =I40 -> #REF! | K4: =J40 -> #REF! | L4: =K40 -> #REF! | M4: =L40 -> #REF!
B5: 経常収入 | D5: =SUM(基礎!D55:O55) -> 39760360 | E5: =SUM(基礎!V55:AG55) -> 129071704 | F5: =SUM(基礎!AM55:AX55) -> 146958399 | G5: =SUM(基礎!#REF!) -> #REF! | H5: =SUM(基礎!#REF!) -> #REF! | I5: =SUM(基礎!#REF!) -> #REF! | J5: =SUM(基礎!#REF!) -> #REF! | K5: =SUM(基礎!#REF!) -> #REF! | L5: =SUM(基礎!#REF!) -> #REF! | M5: =SUM(基礎!#REF!) -> #REF!
C6: 店舗現金売上 | D6: =SUM(基礎!D56:O56) -> 31990360 | E6: =SUM(基礎!V56:AG56) -> 107291682 | F6: =SUM(基礎!AM56:AX56) -> 122868375 | G6: =SUM(基礎!#REF!) -> #REF! | H6: =SUM(基礎!#REF!) -> #REF! | I6: =SUM(基礎!#REF!) -> #REF! | J6: =SUM(基礎!#REF!) -> #REF! | K6: =SUM(基礎!#REF!) -> #REF! | L6: =SUM(基礎!#REF!) -> #REF! | M6: =SUM(基礎!#REF!) -> #REF!
C7: 店舗催事売掛入金 | D7: =SUM(基礎!D57:O57) -> 7770000 | E7: =SUM(基礎!V57:AG57) -> 21780022 | F7: =SUM(基礎!AM57:AX57) -> 24090024 | G7: =SUM(基礎!#REF!) -> #REF! | H7: =SUM(基礎!#REF!) -> #REF! | I7: =SUM(基礎!#REF!) -> #REF! | J7: =SUM(基礎!#REF!) -> #REF! | K7: =SUM(基礎!#REF!) -> #REF! | L7: =SUM(基礎!#REF!) -> #REF! | M7: =SUM(基礎!#REF!) -> #REF!
C8: FCロイヤリティ | D8: =SUM(基礎!D58:O58) -> 0 | E8: =SUM(基礎!V58:AG58) -> 0 | F8: =SUM(基礎!AM58:AX58) -> 0 | G8: =SUM(基礎!#REF!) -> #REF! | H8: =SUM(基礎!#REF!) -> #REF! | I8: =SUM(基礎!#REF!) -> #REF! | J8: =SUM(基礎!#REF!) -> #REF! | K8: =SUM(基礎!#REF!) -> #REF! | L8: =SUM(基礎!#REF!) -> #REF! | M8: =SUM(基礎!#REF!) -> #REF!
C9: 他収入 | D9: =SUM(基礎!D59:O59) -> 0 | E9: =SUM(基礎!V59:AG59) -> 0 | F9: =SUM(基礎!AM59:AX59) -> 0 | G9: =SUM(基礎!#REF!) -> #REF! | H9: =SUM(基礎!#REF!) -> #REF! | I9: =SUM(基礎!#REF!) -> #REF! | J9: =SUM(基礎!#REF!) -> #REF! | K9: =SUM(基礎!#REF!) -> #REF! | L9: =SUM(基礎!#REF!) -> #REF! | M9: =SUM(基礎!#REF!) -> #REF!
B10: 経常支出 | D10: =SUM(基礎!D60:O60) -> 59863907 | E10: =SUM(基礎!V60:AG60) -> 1.2840054e+08 | F10: =SUM(基礎!AM60:AX60) -> 1.3755498e+08 | G10: =SUM(基礎!#REF!) -> #REF! | H10: =SUM(基礎!#REF!) -> #REF! | I10: =SUM(基礎!#REF!) -> #REF! | J10: =SUM(基礎!#REF!) -> #REF! | K10: =SUM(基礎!#REF!) -> #REF! | L10: =SUM(基礎!#REF!) -> #REF! | M10: =SUM(基礎!#REF!) -> #REF!
C11: 店舗仕入買掛 | D11: =SUM(基礎!D61:O61) -> 48137000 | E11: =SUM(基礎!V61:AG61) -> 107027000 | F11: =SUM(基礎!AM61:AX61) -> 118214000 | G11: =SUM(基礎!#REF!) -> #REF! | H11: =SUM(基礎!#REF!) -> #REF! | I11: =SUM(基礎!#REF!) -> #REF! | J11: =SUM(基礎!#REF!) -> #REF! | K11: =SUM(基礎!#REF!) -> #REF! | L11: =SUM(基礎!#REF!) -> #REF! | M11: =SUM(基礎!#REF!) -> #REF!
C12: 店舗人件費 | D12: =SUM(基礎!D62:O62) -> 5340000 | E12: =SUM(基礎!V62:AG62) -> 11780000 | F12: =SUM(基礎!AM62:AX62) -> 12100000 | G12: =SUM(基礎!#REF!) -> #REF! | H12: =SUM(基礎!#REF!) -> #REF! | I12: =SUM(基礎!#REF!) -> #REF! | J12: =SUM(基礎!#REF!) -> #REF! | K12: =SUM(基礎!#REF!) -> #REF! | L12: =SUM(基礎!#REF!) -> #REF! | M12: =SUM(基礎!#REF!) -> #REF!
C13: 販管費（ｻｲﾄ１） | D13: =SUM(基礎!D63:O63) -> 6141906.9 | E13: =SUM(基礎!V63:AG63) -> 9593542.4 | F13: =SUM(基礎!AM63:AX63) -> 7240976.5 | G13: =SUM(基礎!#REF!) -> #REF! | H13: =SUM(基礎!#REF!) -> #REF! | I13: =SUM(基礎!#REF!) -> #REF! | J13: =SUM(基礎!#REF!) -> #REF! | K13: =SUM(基礎!#REF!) -> #REF! | L13: =SUM(基礎!#REF!) -> #REF! | M13: =SUM(基礎!#REF!) -> #REF!
C14: 販管費（ｻｲﾄ２） | D14: =SUM(基礎!D64:O64) -> 0 | E14: =SUM(基礎!V64:AG64) -> 0 | F14: =SUM(基礎!AM64:AX64) -> 0 | G14: =SUM(基礎!#REF!) -> #REF! | H14: =SUM(基礎!#REF!) -> #REF! | I14: =SUM(基礎!#REF!) -> #REF! | J14: =SUM(基礎!#REF!) -> #REF! | K14: =SUM(基礎!#REF!) -> #REF! | L14: =SUM(基礎!#REF!) -> #REF! | M14: =SUM(基礎!#REF!) -> #REF!
C15: 支払利息 | D15: =SUM(基礎!D65:O65) -> 245000 | E15: =SUM(基礎!V65:AG65) -> 0 | F15: =SUM(基礎!AM65:AX65) -> 0 | G15: =SUM(基礎!#REF!) -> #REF! | H15: =SUM(基礎!#REF!) -> #REF! | I15: =SUM(基礎!#REF!) -> #REF! | J15: =SUM(基礎!#REF!) -> #REF! | K15: =SUM(基礎!#REF!) -> #REF! | L15: =SUM(基礎!#REF!) -> #REF! | M15: =SUM(基礎!#REF!) -> #REF!
C16: 固定資産購入等 | D16: =SUM(基礎!D66:O66) -> 0 | E16: =SUM(基礎!V66:AG66) -> 0 | F16: =SUM(基礎!AM66:AX66) -> 0 | G16: =SUM(基礎!#REF!) -> #REF! | H16: =SUM(基礎!#REF!) -> #REF! | I16: =SUM(基礎!#REF!) -> #REF! | J16: =SUM(基礎!#REF!) -> #REF! | K16: =SUM(基礎!#REF!) -> #REF! | L16: =SUM(基礎!#REF!) -> #REF! | M16: =SUM(基礎!#REF!) -> #REF!
C17: 他支出 | D17: =SUM(基礎!D67:O67) -> 0 | E17: =SUM(基礎!V67:AG67) -> 0 | F17: =SUM(基礎!AM67:AX67) -> 0 | G17: =SUM(基礎!#REF!) -> #REF! | H17: =SUM(基礎!#REF!) -> #REF! | I17: =SUM(基礎!#REF!) -> #REF! | J17: =SUM(基礎!#REF!) -> #REF! | K17: =SUM(基礎!#REF!) -> #REF! | L17: =SUM(基礎!#REF!) -> #REF! | M17: =SUM(基礎!#REF!) -> #REF!
B18: 経常収支差額 | D18: =SUM(基礎!D68:O68) -> -20103547 | E18: =SUM(基礎!V68:AG68) -> 671161.56 | F18: =SUM(基礎!AM68:AX68) -> 9403422.5 | G18: =SUM(基礎!#REF!) -> #REF! | H18: =SUM(基礎!#REF!) -> #REF! | I18: =SUM(基礎!#REF!) -> #REF! | J18: =SUM(基礎!#REF!) -> #REF! | K18: =SUM(基礎!#REF!) -> #REF! | L18: =SUM(基礎!#REF!) -> #REF! | M18: =SUM(基礎!#REF!) -> #REF!
B19: 財務収入 | D19: =SUM(D20:D27) -> #REF! | E19: =SUM(基礎!V69:AG69) -> 0 | F19: =SUM(基礎!AM69:AX69) -> 0 | G19: =SUM(基礎!#REF!) -> #REF! | H19: =SUM(基礎!#REF!) -> #REF! | I19: =SUM(基礎!#REF!) -> #REF! | J19: =SUM(基礎!#REF!) -> #REF! | K19: =SUM(基礎!#REF!) -> #REF! | L19: =SUM(基礎!#REF!) -> #REF! | M19: =SUM(基礎!#REF!) -> #REF!
C20: 資本金 | D20: 0 | E20: =SUM(基礎!V70:AG70) -> 0 | F20: =SUM(基礎!AM70:AX70) -> 0 | G20: =SUM(基礎!#REF!) -> #REF! | H20: =SUM(基礎!#REF!) -> #REF! | I20: =SUM(基礎!#REF!) -> #REF! | J20: =SUM(基礎!#REF!) -> #REF! | K20: =SUM(基礎!#REF!) -> #REF! | L20: =SUM(基礎!#REF!) -> #REF! | M20: =SUM(基礎!#REF!) -> #REF!
C21: 役員借入 | D21: =SUM(基礎!D71:O71) -> 8000000 | E21: =SUM(基礎!V71:AG71) -> 0 | F21: =SUM(基礎!AM71:AX71) -> 0 | G21: =SUM(基礎!#REF!) -> #REF! | H21: =SUM(基礎!#REF!) -> #REF! | I21: =SUM(基礎!#REF!) -> #REF! | J21: =SUM(基礎!#REF!) -> #REF! | K21: =SUM(基礎!#REF!) -> #REF! | L21: =SUM(基礎!#REF!) -> #REF! | M21: =SUM(基礎!#REF!) -> #REF!
C22: 金融機関借入 | D22: =SUM(基礎!D72:O72) -> 15000000 | E22: =SUM(基礎!V72:AG72) -> 0 | F22: =SUM(基礎!AM72:AX72) -> 0 | G22: =SUM(基礎!#REF!) -> #REF! | H22: =SUM(基礎!#REF!) -> #REF! | I22: =SUM(基礎!#REF!) -> #REF! | J22: =SUM(基礎!#REF!) -> #REF! | K22: =SUM(基礎!#REF!) -> #REF! | L22: =SUM(基礎!#REF!) -> #REF! | M22: =SUM(基礎!#REF!) -> #REF!
C23: 固定資産売却 | D23: =SUM(基礎!D73:O73) -> 0 | E23: =SUM(基礎!V73:AG73) -> 0 | F23: =SUM(基礎!AM73:AX73) -> 0 | G23: =SUM(基礎!#REF!) -> #REF! | H23: =SUM(基礎!#REF!) -> #REF! | I23: =SUM(基礎!#REF!) -> #REF! | J23: =SUM(基礎!#REF!) -> #REF! | K23: =SUM(基礎!#REF!) -> #REF! | L23: =SUM(基礎!#REF!) -> #REF! | M23: =SUM(基礎!#REF!) -> #REF!
C24: FC保証金 | D24: =SUM(基礎!#REF!) -> #REF! | E24: =SUM(基礎!#REF!) -> #REF! | F24: =SUM(基礎!#REF!) -> #REF! | G24: =SUM(基礎!#REF!) -> #REF! | H24: =SUM(基礎!#REF!) -> #REF! | I24: =SUM(基礎!#REF!) -> #REF! | J24: =SUM(基礎!#REF!) -> #REF! | K24: =SUM(基礎!#REF!) -> #REF! | ... M24: =SUM(基礎!#REF!) -> #REF!
C25: 地区本部保証金 | D25: =SUM(基礎!#REF!) -> #REF! | E25: =SUM(基礎!#REF!) -> #REF! | F25: =SUM(基礎!#REF!) -> #REF! | G25: =SUM(基礎!#REF!) -> #REF! | H25: =SUM(基礎!#REF!) -> #REF! | I25: =SUM(基礎!#REF!) -> #REF! | J25: =SUM(基礎!#REF!) -> #REF! | K25: =SUM(基礎!#REF!) -> #REF! | ... M25: =SUM(基礎!#REF!) -> #REF!
C26: 減価償却 | D26: =SUM(基礎!D74:O74) -> 0 | E26: =SUM(基礎!V74:AG74) -> 0 | F26: =SUM(基礎!AM74:AX74) -> 0 | G26: =SUM(基礎!#REF!) -> #REF! | H26: =SUM(基礎!#REF!) -> #REF! | I26: =SUM(基礎!#REF!) -> #REF! | J26: =SUM(基礎!#REF!) -> #REF! | K26: =SUM(基礎!#REF!) -> #REF! | L26: =SUM(基礎!#REF!) -> #REF! | M26: =SUM(基礎!#REF!) -> #REF!
C27: その他 | D27: =SUM(基礎!D76:O76) -> 0 | E27: =SUM(基礎!V76:AG76) -> 0 | F27: =SUM(基礎!AM76:AX76) -> 0 | G27: =SUM(基礎!#REF!) -> #REF! | H27: =SUM(基礎!#REF!) -> #REF! | I27: =SUM(基礎!#REF!) -> #REF! | J27: =SUM(基礎!#REF!) -> #REF! | K27: =SUM(基礎!#REF!) -> #REF! | L27: =SUM(基礎!#REF!) -> #REF! | M27: =SUM(基礎!#REF!) -> #REF!
B28: 財務支出 | D28: =SUM(D29:D35) -> #REF! | E28: =SUM(E29:E35) -> #REF! | F28: =SUM(F29:F35) -> #REF! | G28: =SUM(G29:G35) -> #REF! | H28: =SUM(H29:H35) -> #REF! | I28: =SUM(I29:I35) -> #REF! | J28: =SUM(J29:J35) -> #REF! | K28: =SUM(K29:K35) -> #REF! | ... N28: =SUM(N29:N35) -> 0
C29: 役員返済 | D29: 24000 | E29: 24000 | F29: 24000 | G29: 24000 | H29: 24000 | I29: 0 | J29: 0 | K29: 0 | L29: 0 | M29: 0
C30: 金融機関返済 | D30: =SUM(基礎!D79:O79) -> 399000 | E30: =SUM(基礎!V79:AG79) -> 684000 | F30: =SUM(基礎!AM79:AX79) -> 627000 | G30: =SUM(基礎!#REF!) -> #REF! | H30: =SUM(基礎!#REF!) -> #REF! | I30: =SUM(基礎!#REF!) -> #REF! | J30: =SUM(基礎!#REF!) -> #REF! | K30: =SUM(基礎!#REF!) -> #REF! | L30: =SUM(基礎!#REF!) -> #REF! | M30: =SUM(基礎!#REF!) -> #REF!
C31: FC保証金返却 | D31: =SUM(基礎!#REF!) -> #REF! | E31: =SUM(基礎!#REF!) -> #REF! | F31: =SUM(基礎!#REF!) -> #REF! | G31: =SUM(基礎!#REF!) -> #REF! | H31: =SUM(基礎!#REF!) -> #REF! | I31: =SUM(基礎!#REF!) -> #REF! | J31: =SUM(基礎!#REF!) -> #REF! | K31: =SUM(基礎!#REF!) -> #REF! | ... M31: =SUM(基礎!#REF!) -> #REF!
C32: 地区本部保証金返却 | D32: =SUM(基礎!#REF!) -> #REF! | E32: =SUM(基礎!#REF!) -> #REF! | F32: =SUM(基礎!#REF!) -> #REF! | G32: =SUM(基礎!#REF!) -> #REF! | H32: =SUM(基礎!#REF!) -> #REF! | I32: =SUM(基礎!#REF!) -> #REF! | J32: =SUM(基礎!#REF!) -> #REF! | K32: =SUM(基礎!#REF!) -> #REF! | ... M32: =SUM(基礎!#REF!) -> #REF!
C33: FC本部（システム等） | D33: =SUM(基礎!#REF!) -> #REF! | E33: =SUM(基礎!#REF!) -> #REF! | F33: =SUM(基礎!#REF!) -> #REF! | G33: =SUM(基礎!#REF!) -> #REF! | H33: =SUM(基礎!#REF!) -> #REF! | I33: =SUM(基礎!#REF!) -> #REF! | J33: =SUM(基礎!#REF!) -> #REF! | K33: =SUM(基礎!#REF!) -> #REF! | ... M33: =SUM(基礎!#REF!) -> #REF!
C34: 店舗出店コスト | D34: =SUM(基礎!D80:O80) -> 3000000 | E34: =SUM(基礎!V80:AG80) -> 0 | F34: =SUM(基礎!AM80:AX80) -> 0 | G34: =SUM(基礎!#REF!) -> #REF! | H34: =SUM(基礎!#REF!) -> #REF! | I34: =SUM(基礎!#REF!) -> #REF! | J34: =SUM(基礎!#REF!) -> #REF! | K34: =SUM(基礎!#REF!) -> #REF! | L34: =SUM(基礎!#REF!) -> #REF! | M34: =SUM(基礎!#REF!) -> #REF!
C35: その他 | D35: =SUM(基礎!D82:O82) -> 0 | E35: =SUM(基礎!V82:AG82) -> 0 | F35: =SUM(基礎!AM82:AX82) -> 0 | G35: =SUM(基礎!#REF!) -> #REF! | H35: =SUM(基礎!#REF!) -> #REF! | I35: =SUM(基礎!#REF!) -> #REF! | J35: =SUM(基礎!#REF!) -> #REF! | K35: =SUM(基礎!#REF!) -> #REF! | L35: =SUM(基礎!#REF!) -> #REF! | M35: =SUM(基礎!#REF!) -> #REF!
B36: 財務収支差額 | D36: =D19-D28 -> #REF! | E36: =E19-E28 -> #REF! | F36: =F19-F28 -> #REF! | G36: =G19-G28 -> #REF! | H36: =H19-H28 -> #REF! | I36: =I19-I28 -> #REF! | J36: =J19-J28 -> #REF! | K36: =K19-K28 -> #REF! | ... M36: =M19-M28 -> #REF!
B37: CF | D37: =D18+D36 -> #REF! | E37: =E18+E36 -> #REF! | F37: =F18+F36 -> #REF! | G37: =G18+G36 -> #REF! | H37: =H18+H36 -> #REF! | I37: =I18+I36 -> #REF! | J37: =J18+J36 -> #REF! | K37: =K18+K36 -> #REF! | ... M37: =M18+M36 -> #REF!
B38: 税金 | D38: =PL!D28 -> 0 | E38: =PL!E28 -> 579164.6 | F38: =PL!F28 -> 17192711 | G38: =PL!#REF! -> #REF! | H38: =PL!#REF! -> #REF! | I38: =PL!#REF! -> #REF! | J38: =PL!#REF! -> #REF! | K38: =PL!#REF! -> #REF! | L38: =PL!#REF! -> #REF! | M38: =PL!#REF! -> #REF!
B39: 税引後CF | D39: =D37-D38 -> #REF! | E39: =E37-E38 -> #REF! | F39: =F37-F38 -> #REF! | G39: =G37-G38 -> #REF! | H39: =H37-H38 -> #REF! | I39: =I37-I38 -> #REF! | J39: =J37-J38 -> #REF! | K39: =K37-K38 -> #REF! | ... M39: =M37-M38 -> #REF!
B40: 翌年度繰越 | D40: =D4+D39 -> #REF! | E40: =E4+E39 -> #REF! | F40: =F4+F39 -> #REF! | G40: =G4+G39 -> #REF! | H40: =H4+H39 -> #REF! | I40: =I4+I39 -> #REF! | J40: =J4+J39 -> #REF! | K40: =K4+K39 -> #REF! | ... M40: =M4+M39 -> #REF!
B42: 現在価値（税引前）【割引率1.5％】 | D42: =D37 -> #REF! | E42: =E37/(1+$N$42)^(E1-1) -> #REF! | F42: =F37/(1+$N$42)^(F1) -> #REF! | G42: =G37/(1+$N$42)^(G1) -> #REF! | H42: =H37/(1+$N$42)^(H1) -> #REF! | I42: =I37/(1+$N$42)^(I1) -> #REF! | J42: =J37/(1+$N$42)^(J1) -> #REF! | K42: =K37/(1+$N$42)^(K1) -> #REF! | L42: =L37/(1+$N$42)^(L1) -> #REF! | M42: =M37/(1+$N$42)^(M1) -> #REF! | N42: 0.015
B43: 現在価値（税引後）【割引率1.5％】 | D43: =D39/(1+$N$42) -> #REF! | E43: =E39/(1+$N$42)^(E1) -> #REF! | F43: =F39/(1+$N$42)^(F1) -> #REF! | G43: =G39/(1+$N$42)^(G1) -> #REF! | H43: =H39/(1+$N$42)^(H1) -> #REF! | I43: =I39/(1+$N$42)^(I1) -> #REF! | J43: =J39/(1+$N$42)^(J1) -> #REF! | K43: =K39/(1+$N$42)^(K1) -> #REF! | L43: =L39/(1+$N$42)^(L1) -> #REF! | M43: =M39/(1+$N$42)^(M1) -> #REF! | N43: 0.015
B45: 事業費算定
B46: ＤＣＦ方式の評価額（税引前当期利益ベース） | E46: =SUM(D42:M42) -> #REF!
B47: ＤＣＦ方式の評価額（税引後当期利益ベース） | E47: =SUM(D43:M43) -> #REF!
G49: 事業価値の評価額 | I49: 算入割合
B50: ＤＣＦ方式による評価額（税引前当期利益ベース） | G50: =E46 -> #REF! | I50: =66.7% -> 0.667
B51: 純資産方式による評価額 | G51: 0 | I51: 0.333
B52: ＤＣＦ方式を２、純資産方式を１として加重平均で求めた修正評価額 | G52: =G50*I50+G51*I51 -> #REF!
B53: 事業価値の範囲（+10％） | G53: =G52*1.1 -> #REF! | I53: 0.1
B54: 事業価値の範囲（-10％） | G54: =G52*0.9 -> #REF! | I54: -0.1

Sheet 事業評価【A案・税引後】
E1: 1 | F1: 2 | G1: 3 | H1: 4 | I1: 5 | J1: 6 | K1: 7 | L1: 8 | M1: 9
B2: 企業価値A案（税引後） | M2: 【千円】
D3: H23年度 | E3: H24年度 | F3: H25年度 | G3: H26年度 | H3: H27年度 | I3: H28年度 | J3: H29年度 | K3: H30年度 | L3: H31年度 | M3: H32年度
B4: 前年度繰越 | D4: 0 | E4: =D40 -> #REF! | F4: =E40 -> #REF! | G4: =F40 -> #REF! | H4: =G40 -> #REF! | I4: =H40 -> #REF! | J4: =I40 -> #REF! | K4: =J40 -> #REF! | L4: =K40 -> #REF! | M4: =L40 -> #REF!
B5: 経常収入 | D5: =SUM(基礎!D55:O55) -> 39760360 | E5: =SUM(基礎!V55:AG55) -> 129071704 | F5: =SUM(基礎!AM55:AX55) -> 146958399 | G5: =SUM(基礎!#REF!) -> #REF! | H5: =SUM(基礎!#REF!) -> #REF! | I5: =SUM(基礎!#REF!) -> #REF! | J5: =SUM(基礎!#REF!) -> #REF! | K5: =SUM(基礎!#REF!) -> #REF! | L5: =SUM(基礎!#REF!) -> #REF! | M5: =SUM(基礎!#REF!) -> #REF!
C6: 店舗現金売上 | D6: =SUM(基礎!D56:O56) -> 31990360 | E6: =SUM(基礎!V56:AG56) -> 107291682 | F6: =SUM(基礎!AM56:AX56) -> 122868375 | G6: =SUM(基礎!#REF!) -> #REF! | H6: =SUM(基礎!#REF!) -> #REF! | I6: =SUM(基礎!#REF!) -> #REF! | J6: =SUM(基礎!#REF!) -> #REF! | K6: =SUM(基礎!#REF!) -> #REF! | L6: =SUM(基礎!#REF!) -> #REF! | M6: =SUM(基礎!#REF!) -> #REF!
C7: 店舗催事売掛入金 | D7: =SUM(基礎!D57:O57) -> 7770000 | E7: =SUM(基礎!V57:AG57) -> 21780022 | F7: =SUM(基礎!AM57:AX57) -> 24090024 | G7: =SUM(基礎!#REF!) -> #REF! | H7: =SUM(基礎!#REF!) -> #REF! | I7: =SUM(基礎!#REF!) -> #REF! | J7: =SUM(基礎!#REF!) -> #REF! | K7: =SUM(基礎!#REF!) -> #REF! | L7: =SUM(基礎!#REF!) -> #REF! | M7: =SUM(基礎!#REF!) -> #REF!
C8: FCロイヤリティ | D8: =SUM(基礎!D58:O58) -> 0 | E8: =SUM(基礎!V58:AG58) -> 0 | F8: =SUM(基礎!AM58:AX58) -> 0 | G8: =SUM(基礎!#REF!) -> #REF! | H8: =SUM(基礎!#REF!) -> #REF! | I8: =SUM(基礎!#REF!) -> #REF! | J8: =SUM(基礎!#REF!) -> #REF! | K8: =SUM(基礎!#REF!) -> #REF! | L8: =SUM(基礎!#REF!) -> #REF! | M8: =SUM(基礎!#REF!) -> #REF!
C9: 他収入 | D9: =SUM(基礎!D59:O59) -> 0 | E9: =SUM(基礎!V59:AG59) -> 0 | F9: =SUM(基礎!AM59:AX59) -> 0 | G9: =SUM(基礎!#REF!) -> #REF! | H9: =SUM(基礎!#REF!) -> #REF! | I9: =SUM(基礎!#REF!) -> #REF! | J9: =SUM(基礎!#REF!) -> #REF! | K9: =SUM(基礎!#REF!) -> #REF! | L9: =SUM(基礎!#REF!) -> #REF! | M9: =SUM(基礎!#REF!) -> #REF!
B10: 経常支出 | D10: =SUM(基礎!D60:O60) -> 59863907 | E10: =SUM(基礎!V60:AG60) -> 1.2840054e+08 | F10: =SUM(基礎!AM60:AX60) -> 1.3755498e+08 | G10: =SUM(基礎!#REF!) -> #REF! | H10: =SUM(基礎!#REF!) -> #REF! | I10: =SUM(基礎!#REF!) -> #REF! | J10: =SUM(基礎!#REF!) -> #REF! | K10: =SUM(基礎!#REF!) -> #REF! | L10: =SUM(基礎!#REF!) -> #REF! | M10: =SUM(基礎!#REF!) -> #REF!
C11: 店舗仕入買掛 | D11: =SUM(基礎!D61:O61) -> 48137000 | E11: =SUM(基礎!V61:AG61) -> 107027000 | F11: =SUM(基礎!AM61:AX61) -> 118214000 | G11: =SUM(基礎!#REF!) -> #REF! | H11: =SUM(基礎!#REF!) -> #REF! | I11: =SUM(基礎!#REF!) -> #REF! | J11: =SUM(基礎!#REF!) -> #REF! | K11: =SUM(基礎!#REF!) -> #REF! | L11: =SUM(基礎!#REF!) -> #REF! | M11: =SUM(基礎!#REF!) -> #REF!
C12: 店舗人件費 | D12: =SUM(基礎!D62:O62) -> 5340000 | E12: =SUM(基礎!V62:AG62) -> 11780000 | F12: =SUM(基礎!AM62:AX62) -> 12100000 | G12: =SUM(基礎!#REF!) -> #REF! | H12: =SUM(基礎!#REF!) -> #REF! | I12: =SUM(基礎!#REF!) -> #REF! | J12: =SUM(基礎!#REF!) -> #REF! | K12: =SUM(基礎!#REF!) -> #REF! | L12: =SUM(基礎!#REF!) -> #REF! | M12: =SUM(基礎!#REF!) -> #REF!
C13: 販管費（ｻｲﾄ１） | D13: =SUM(基礎!D63:O63) -> 6141906.9 | E13: =SUM(基礎!V63:AG63) -> 9593542.4 | F13: =SUM(基礎!AM63:AX63) -> 7240976.5 | G13: =SUM(基礎!#REF!) -> #REF! | H13: =SUM(基礎!#REF!) -> #REF! | I13: =SUM(基礎!#REF!) -> #REF! | J13: =SUM(基礎!#REF!) -> #REF! | K13: =SUM(基礎!#REF!) -> #REF! | L13: =SUM(基礎!#REF!) -> #REF! | M13: =SUM(基礎!#REF!) -> #REF!
C14: 販管費（ｻｲﾄ２） | D14: =SUM(基礎!D64:O64) -> 0 | E14: =SUM(基礎!V64:AG64) -> 0 | F14: =SUM(基礎!AM64:AX64) -> 0 | G14: =SUM(基礎!#REF!) -> #REF! | H14: =SUM(基礎!#REF!) -> #REF! | I14: =SUM(基礎!#REF!) -> #REF! | J14: =SUM(基礎!#REF!) -> #REF! | K14: =SUM(基礎!#REF!) -> #REF! | L14: =SUM(基礎!#REF!) -> #REF! | M14: =SUM(基礎!#REF!) -> #REF!
C15: 支払利息 | D15: =SUM(基礎!D65:O65) -> 245000 | E15: =SUM(基礎!V65:AG65) -> 0 | F15: =SUM(基礎!AM65:AX65) -> 0 | G15: =SUM(基礎!#REF!) -> #REF! | H15: =SUM(基礎!#REF!) -> #REF! | I15: =SUM(基礎!#REF!) -> #REF! | J15: =SUM(基礎!#REF!) -> #REF! | K15: =SUM(基礎!#REF!) -> #REF! | L15: =SUM(基礎!#REF!) -> #REF! | M15: =SUM(基礎!#REF!) -> #REF!
C16: 固定資産購入等 | D16: =SUM(基礎!D66:O66) -> 0 | E16: =SUM(基礎!V66:AG66) -> 0 | F16: =SUM(基礎!AM66:AX66) -> 0 | G16: =SUM(基礎!#REF!) -> #REF! | H16: =SUM(基礎!#REF!) -> #REF! | I16: =SUM(基礎!#REF!) -> #REF! | J16: =SUM(基礎!#REF!) -> #REF! | K16: =SUM(基礎!#REF!) -> #REF! | L16: =SUM(基礎!#REF!) -> #REF! | M16: =SUM(基礎!#REF!) -> #REF!
C17: 他支出 | D17: =SUM(基礎!D67:O67) -> 0 | E17: =SUM(基礎!V67:AG67) -> 0 | F17: =SUM(基礎!AM67:AX67) -> 0 | G17: =SUM(基礎!#REF!) -> #REF! | H17: =SUM(基礎!#REF!) -> #REF! | I17: =SUM(基礎!#REF!) -> #REF! | J17: =SUM(基礎!#REF!) -> #REF! | K17: =SUM(基礎!#REF!) -> #REF! | L17: =SUM(基礎!#REF!) -> #REF! | M17: =SUM(基礎!#REF!) -> #REF!
B18: 経常収支差額 | D18: =SUM(基礎!D68:O68) -> -20103547 | E18: =SUM(基礎!V68:AG68) -> 671161.56 | F18: =SUM(基礎!AM68:AX68) -> 9403422.5 | G18: =SUM(基礎!#REF!) -> #REF! | H18: =SUM(基礎!#REF!) -> #REF! | I18: =SUM(基礎!#REF!) -> #REF! | J18: =SUM(基礎!#REF!) -> #REF! | K18: =SUM(基礎!#REF!) -> #REF! | L18: =SUM(基礎!#REF!) -> #REF! | M18: =SUM(基礎!#REF!) -> #REF!
B19: 財務収入 | D19: =SUM(D20:D27) -> #REF! | E19: =SUM(基礎!V69:AG69) -> 0 | F19: =SUM(基礎!AM69:AX69) -> 0 | G19: =SUM(基礎!#REF!) -> #REF! | H19: =SUM(基礎!#REF!) -> #REF! | I19: =SUM(基礎!#REF!) -> #REF! | J19: =SUM(基礎!#REF!) -> #REF! | K19: =SUM(基礎!#REF!) -> #REF! | L19: =SUM(基礎!#REF!) -> #REF! | M19: =SUM(基礎!#REF!) -> #REF!
C20: 資本金 | D20: 0 | E20: =SUM(基礎!V70:AG70) -> 0 | F20: =SUM(基礎!AM70:AX70) -> 0 | G20: =SUM(基礎!#REF!) -> #REF! | H20: =SUM(基礎!#REF!) -> #REF! | I20: =SUM(基礎!#REF!) -> #REF! | J20: =SUM(基礎!#REF!) -> #REF! | K20: =SUM(基礎!#REF!) -> #REF! | L20: =SUM(基礎!#REF!) -> #REF! | M20: =SUM(基礎!#REF!) -> #REF!
C21: 役員借入 | D21: =SUM(基礎!D71:O71) -> 8000000 | E21: =SUM(基礎!V71:AG71) -> 0 | F21: =SUM(基礎!AM71:AX71) -> 0 | G21: =SUM(基礎!#REF!) -> #REF! | H21: =SUM(基礎!#REF!) -> #REF! | I21: =SUM(基礎!#REF!) -> #REF! | J21: =SUM(基礎!#REF!) -> #REF! | K21: =SUM(基礎!#REF!) -> #REF! | L21: =SUM(基礎!#REF!) -> #REF! | M21: =SUM(基礎!#REF!) -> #REF!
C22: 金融機関借入 | D22: =SUM(基礎!D72:O72) -> 15000000 | E22: =SUM(基礎!V72:AG72) -> 0 | F22: =SUM(基礎!AM72:AX72) -> 0 | G22: =SUM(基礎!#REF!) -> #REF! | H22: =SUM(基礎!#REF!) -> #REF! | I22: =SUM(基礎!#REF!) -> #REF! | J22: =SUM(基礎!#REF!) -> #REF! | K22: =SUM(基礎!#REF!) -> #REF! | L22: =SUM(基礎!#REF!) -> #REF! | M22: =SUM(基礎!#REF!) -> #REF!
C23: 固定資産売却 | D23: =SUM(基礎!D73:O73) -> 0 | E23: =SUM(基礎!V73:AG73) -> 0 | F23: =SUM(基礎!AM73:AX73) -> 0 | G23: =SUM(基礎!#REF!) -> #REF! | H23: =SUM(基礎!#REF!) -> #REF! | I23: =SUM(基礎!#REF!) -> #REF! | J23: =SUM(基礎!#REF!) -> #REF! | K23: =SUM(基礎!#REF!) -> #REF! | L23: =SUM(基礎!#REF!) -> #REF! | M23: =SUM(基礎!#REF!) -> #REF!
C24: FC保証金 | D24: =SUM(基礎!#REF!) -> #REF! | E24: =SUM(基礎!#REF!) -> #REF! | F24: =SUM(基礎!#REF!) -> #REF! | G24: =SUM(基礎!#REF!) -> #REF! | H24: =SUM(基礎!#REF!) -> #REF! | I24: =SUM(基礎!#REF!) -> #REF! | J24: =SUM(基礎!#REF!) -> #REF! | K24: =SUM(基礎!#REF!) -> #REF! | ... M24: =SUM(基礎!#REF!) -> #REF!
C25: 地区本部保証金 | D25: =SUM(基礎!#REF!) -> #REF! | E25: =SUM(基礎!#REF!) -> #REF! | F25: =SUM(基礎!#REF!) -> #REF! | G25: =SUM(基礎!#REF!) -> #REF! | H25: =SUM(基礎!#REF!) -> #REF! | I25: =SUM(基礎!#REF!) -> #REF! | J25: =SUM(基礎!#REF!) -> #REF! | K25: =SUM(基礎!#REF!) -> #REF! | ... M25: =SUM(基礎!#REF!) -> #REF!
C26: 減価償却 | D26: =SUM(基礎!D74:O74) -> 0 | E26: =SUM(基礎!V74:AG74) -> 0 | F26: =SUM(基礎!AM74:AX74) -> 0 | G26: =SUM(基礎!#REF!) -> #REF! | H26: =SUM(基礎!#REF!) -> #REF! | I26: =SUM(基礎!#REF!) -> #REF! | J26: =SUM(基礎!#REF!) -> #REF! | K26: =SUM(基礎!#REF!) -> #REF! | L26: =SUM(基礎!#REF!) -> #REF! | M26: =SUM(基礎!#REF!) -> #REF!
C27: その他 | D27: =SUM(基礎!D76:O76) -> 0 | E27: =SUM(基礎!V76:AG76) -> 0 | F27: =SUM(基礎!AM76:AX76) -> 0 | G27: =SUM(基礎!#REF!) -> #REF! | H27: =SUM(基礎!#REF!) -> #REF! | I27: =SUM(基礎!#REF!) -> #REF! | J27: =SUM(基礎!#REF!) -> #REF! | K27: =SUM(基礎!#REF!) -> #REF! | L27: =SUM(基礎!#REF!) -> #REF! | M27: =SUM(基礎!#REF!) -> #REF!
B28: 財務支出 | D28: =SUM(D29:D35) -> #REF! | E28: =SUM(E29:E35) -> #REF! | F28: =SUM(F29:F35) -> #REF! | G28: =SUM(G29:G35) -> #REF! | H28: =SUM(H29:H35) -> #REF! | I28: =SUM(I29:I35) -> #REF! | J28: =SUM(J29:J35) -> #REF! | K28: =SUM(K29:K35) -> #REF! | ... N28: =SUM(N29:N35) -> 0
C29: 役員返済 | D29: 24000 | E29: 24000 | F29: 24000 | G29: 24000 | H29: 24000 | I29: 0 | J29: 0 | K29: 0 | L29: 0 | M29: 0
C30: 金融機関返済 | D30: =SUM(基礎!D79:O79) -> 399000 | E30: =SUM(基礎!V79:AG79) -> 684000 | F30: =SUM(基礎!AM79:AX79) -> 627000 | G30: =SUM(基礎!#REF!) -> #REF! | H30: =SUM(基礎!#REF!) -> #REF! | I30: =SUM(基礎!#REF!) -> #REF! | J30: =SUM(基礎!#REF!) -> #REF! | K30: =SUM(基礎!#REF!) -> #REF! | L30: =SUM(基礎!#REF!) -> #REF! | M30: =SUM(基礎!#REF!) -> #REF!
C31: FC保証金返却 | D31: =SUM(基礎!#REF!) -> #REF! | E31: =SUM(基礎!#REF!) -> #REF! | F31: =SUM(基礎!#REF!) -> #REF! | G31: =SUM(基礎!#REF!) -> #REF! | H31: =SUM(基礎!#REF!) -> #REF! | I31: =SUM(基礎!#REF!) -> #REF! | J31: =SUM(基礎!#REF!) -> #REF! | K31: =SUM(基礎!#REF!) -> #REF! | ... M31: =SUM(基礎!#REF!) -> #REF!
C32: 地区本部保証金返却 | D32: =SUM(基礎!#REF!) -> #REF! | E32: =SUM(基礎!#REF!) -> #REF! | F32: =SUM(基礎!#REF!) -> #REF! | G32: =SUM(基礎!#REF!) -> #REF! | H32: =SUM(基礎!#REF!) -> #REF! | I32: =SUM(基礎!#REF!) -> #REF! | J32: =SUM(基礎!#REF!) -> #REF! | K32: =SUM(基礎!#REF!) -> #REF! | ... M32: =SUM(基礎!#REF!) -> #REF!
C33: FC本部（システム等） | D33: =SUM(基礎!#REF!) -> #REF! | E33: =SUM(基礎!#REF!) -> #REF! | F33: =SUM(基礎!#REF!) -> #REF! | G33: =SUM(基礎!#REF!) -> #REF! | H33: =SUM(基礎!#REF!) -> #REF! | I33: =SUM(基礎!#REF!) -> #REF! | J33: =SUM(基礎!#REF!) -> #REF! | K33: =SUM(基礎!#REF!) -> #REF! | ... M33: =SUM(基礎!#REF!) -> #REF!
C34: 店舗出店コスト | D34: =SUM(基礎!D80:O80) -> 3000000 | E34: =SUM(基礎!V80:AG80) -> 0 | F34: =SUM(基礎!AM80:AX80) -> 0 | G34: =SUM(基礎!#REF!) -> #REF! | H34: =SUM(基礎!#REF!) -> #REF! | I34: =SUM(基礎!#REF!) -> #REF! | J34: =SUM(基礎!#REF!) -> #REF! | K34: =SUM(基礎!#REF!) -> #REF! | L34: =SUM(基礎!#REF!) -> #REF! | M34: =SUM(基礎!#REF!) -> #REF!
C35: その他 | D35: =SUM(基礎!D82:O82) -> 0 | E35: =SUM(基礎!V82:AG82) -> 0 | F35: =SUM(基礎!AM82:AX82) -> 0 | G35: =SUM(基礎!#REF!) -> #REF! | H35: =SUM(基礎!#REF!) -> #REF! | I35: =SUM(基礎!#REF!) -> #REF! | J35: =SUM(基礎!#REF!) -> #REF! | K35: =SUM(基礎!#REF!) -> #REF! | L35: =SUM(基礎!#REF!) -> #REF! | M35: =SUM(基礎!#REF!) -> #REF!
B36: 財務収支差額 | D36: =D19-D28 -> #REF! | E36: =E19-E28 -> #REF! | F36: =F19-F28 -> #REF! | G36: =G19-G28 -> #REF! | H36: =H19-H28 -> #REF! | I36: =I19-I28 -> #REF! | J36: =J19-J28 -> #REF! | K36: =K19-K28 -> #REF! | ... M36: =M19-M28 -> #REF!
B37: CF | D37: =D18+D36 -> #REF! | E37: =E18+E36 -> #REF! | F37: =F18+F36 -> #REF! | G37: =G18+G36 -> #REF! | H37: =H18+H36 -> #REF! | I37: =I18+I36 -> #REF! | J37: =J18+J36 -> #REF! | K37: =K18+K36 -> #REF! | ... M37: =M18+M36 -> #REF!
B38: 税金 | D38: =PL!D28 -> 0 | E38: =PL!E28 -> 579164.6 | F38: =PL!F28 -> 17192711 | G38: =PL!#REF! -> #REF! | H38: =PL!#REF! -> #REF! | I38: =PL!#REF! -> #REF! | J38: =PL!#REF! -> #REF! | K38: =PL!#REF! -> #REF! | L38: =PL!#REF! -> #REF! | M38: =PL!#REF! -> #REF!
B39: 税引後CF | D39: =D37-D38 -> #REF! | E39: =E37-E38 -> #REF! | F39: =F37-F38 -> #REF! | G39: =G37-G38 -> #REF! | H39: =H37-H38 -> #REF! | I39: =I37-I38 -> #REF! | J39: =J37-J38 -> #REF! | K39: =K37-K38 -> #REF! | ... M39: =M37-M38 -> #REF!
B40: 翌年度繰越 | D40: =D4+D39 -> #REF! | E40: =E4+E39 -> #REF! | F40: =F4+F39 -> #REF! | G40: =G4+G39 -> #REF! | H40: =H4+H39 -> #REF! | I40: =I4+I39 -> #REF! | J40: =J4+J39 -> #REF! | K40: =K4+K39 -> #REF! | ... M40: =M4+M39 -> #REF!
B42: 現在価値（税引前）【割引率1.5％】 | D42: =D37 -> #REF! | E42: =E37/(1+$N$42)^(E1-1) -> #REF! | F42: =F37/(1+$N$42)^(F1) -> #REF! | G42: =G37/(1+$N$42)^(G1) -> #REF! | H42: =H37/(1+$N$42)^(H1) -> #REF! | I42: =I37/(1+$N$42)^(I1) -> #REF! | J42: =J37/(1+$N$42)^(J1) -> #REF! | K42: =K37/(1+$N$42)^(K1) -> #REF! | L42: =L37/(1+$N$42)^(L1) -> #REF! | M42: =M37/(1+$N$42)^(M1) -> #REF! | N42: 0.015
B43: 現在価値（税引後）【割引率1.5％】 | D43: =D39/(1+$N$42) -> #REF! | E43: =E39/(1+$N$42)^(E1) -> #REF! | F43: =F39/(1+$N$42)^(F1) -> #REF! | G43: =G39/(1+$N$42)^(G1) -> #REF! | H43: =H39/(1+$N$42)^(H1) -> #REF! | I43: =I39/(1+$N$42)^(I1) -> #REF! | J43: =J39/(1+$N$42)^(J1) -> #REF! | K43: =K39/(1+$N$42)^(K1) -> #REF! | L43: =L39/(1+$N$42)^(L1) -> #REF! | M43: =M39/(1+$N$42)^(M1) -> #REF! | N43: 0.015
B45: 事業費算定
B46: ＤＣＦ方式の評価額（税引前当期利益ベース） | E46: =SUM(D42:M42) -> #REF!
B47: ＤＣＦ方式の評価額（税引後当期利益ベース） | E47: =SUM(D43:M43) -> #REF!
G49: 事業価値の評価額 | I49: 算入割合
B50: ＤＣＦ方式による評価額（税引後当期利益ベース） | G50: =E47 -> #REF! | I50: =66.7% -> 0.667
B51: 純資産方式による評価額 | G51: 0 | I51: 0.333
B52: ＤＣＦ方式を２、純資産方式を１として加重平均で求めた修正評価額 | G52: =G50*I50+G51*I51 -> #REF!
B53: 事業価値の範囲（+10％） | G53: =G52*1.1 -> #REF! | I53: 0.1
B54: 事業価値の範囲（-10％） | G54: =G52*0.9 -> #REF! | I54: -0.1

Sheet Sheet2
B2: 現在 | F2: R3 | J2: R4 | N2: R5 | R2: R6 | V2: R7
F3: 4-6 | G3: 7-9 | H3: 10-12 | I3: 1-3 | J3: 4-6 | K3: 7-9 | L3: 10-12 | M3: 1-3 | N3: 4-6 | O3: 7-9 | P3: 10-12 | Q3: 1-3 | R3: 4-6 | S3: 7-9 | T3: 10-12 | U3: 1-3 | V3: 4-6 | W3: 7-9 | X3: 10-12 | Y3: 1-3
B4: 直営(累計） | F4: =SUM(F6:F15) -> 1 | G4: =SUM(G6:G15)+F4 -> 3 | H4: =SUM(H6:H15)+G4 -> 4 | I4: =SUM(I6:I15)+H4 -> 5 | J4: =SUM(J6:J15)+I4 -> 5 | K4: =SUM(K6:K15)+J4 -> 5 | L4: =SUM(L6:L15)+K4 -> 5 | M4: =SUM(M6:M15)+L4 -> 5 | N4: =SUM(N6:N15)+M4 -> 5 | ... Y4: =SUM(Y6:Y15)+X4 -> 5
C5: 福祉
D6: 就労移行支援 | E6: 0.5 | F6: 1 | G6: 0.5 | H6: 1 | I6: 1
D7: 就労継続支援A型
D8: 就労継続支援B型 | E8: 0.5 | G8: 0.5
D9: 相談支援等 | G9: 1
C11: 教育
D12: 個別塾 | E12: 1
D13: はくし | E13: 1
D14: メディカルフィットネス
B16: FC | F16: =SUM(F17:F24) -> 0 | G16: =SUM(G17:G24)+F16 -> 1 | H16: =SUM(H17:H24)+G16 -> 1 | I16: =SUM(I17:I24)+H16 -> 1 | J16: =SUM(J17:J24)+I16 -> 1 | K16: =SUM(K17:K24)+J16 -> 1 | L16: =SUM(L17:L24)+K16 -> 1 | M16: =SUM(M17:M24)+L16 -> 1 | N16: =SUM(N17:N24)+M16 -> 1 | ... Y16: =SUM(Y17:Y24)+X16 -> 1
D17: 就労移行支援 | G17: 1
D18: 就労継続支援A型
D19: 就労継続支援B型
D20: 個別塾
D21: オンライン塾
D22: メディカルフィットネス
B23: 優先調達事業
D24: 自治体アウトソーシング
D25: DX事業
D26: メディア事業
D27: ファーム事業

Sheet 売上計画
D1: H23年度 | H1: H24年度 | L1: H25年度 | P1: H26年度 | T1: H27年度 | X1: H28年度 | AB1: H29年度 | AF1: H30年度
D2: Phase 1：基盤構築フェーズ | I2: Phase 2：高成長フェーズ（目標は100%成長） | P2: Phase3：安定成長フェーズ（目標は50%成長） | X2: Phase4：海外進出基盤構築フェーズ | AB2: Phase5：海外成長フェーズ | AF2: Phase6：海外安定成長フェーズ
C3: 月平均売上 | D3: 5 | E3: 6-8 | F3: 9-11 | G3: 12-2 | H3: 3-5 | I3: 6-8 | J3: 9-11 | K3: 12-2 | L3: 3-5 | M3: 6-8 | N3: 9-11 | O3: 12-2 | P3: 3-5 | Q3: 6-8 | R3: 9-11 | S3: 12-2 | T3: 3-5 | U3: 6-8 | V3: 9-11 | W3: 12-2 | X3: 3-5 | Y3: 6-8 | Z3: 9-11 | AA3: 12-2 | AB3: 3-5 | AC3: 6-8 | AD3: 9-11 | AE3: 12-2 | AF3: 3-5 | AG3: 6-8 | AH3: 9-11 | AI3: 12-2
A4: 直営 | B4: 都市型 | C4: 9000 | D4: 1 | E4: 1 | F4: 1 | G4: 2 | H4: 3 | I4: 3 | J4: 3 | K4: 3 | L4: 3 | M4: 4 | N4: 5 | O4: 6 | P4: 6 | Q4: 6 | R4: 7 | S4: 7 | T4: 7 | U4: 9 | V4: 9 | W4: 10 | X4: 10 | Y4: 12 | Z4: 14 | AA4: 16 | AB4: 18 | AC4: 20 | AD4: 22 | AE4: 24 | AF4: 26 | AG4: 28 | AH4: 30 | AI4: 31
B5: サテライト型 | C5: 6000 | D5: 1 | E5: 1 | F5: 1 | G5: 2 | H5: 3 | I5: 3 | J5: 3 | K5: 3 | L5: 3 | M5: 4 | N5: 5 | O5: 6 | P5: 6 | Q5: 6 | R5: 6 | S5: 7 | T5: 7 | U5: 9 | V5: 9 | W5: 10 | X5: 11 | Y5: 12 | Z5: 13 | AA5: 14 | AB5: 14 | AC5: 15 | AD5: 16 | AE5: 18 | AF5: 18 | AG5: 19 | AH5: 20 | AI5: 20
B6: 郊外型 | C6: 7500 | D6: 1 | E6: 1 | F6: 1 | G6: 2 | H6: 2 | I6: 2 | J6: 3 | K6: 3 | L6: 3 | M6: 4 | N6: 4 | O6: 5 | P6: 6 | Q6: 6 | R6: 6 | S6: 7 | T6: 7 | U6: 9 | V6: 9 | W6: 10 | X6: 10 | Y6: 10 | Z6: 10 | AA6: 10 | AB6: 10 | AC6: 10 | AD6: 10 | AE6: 12 | AF6: 12 | AG6: 12 | AH6: 13 | AI6: 13
B7: SC内 | C7: 6000 | D7: 1 | E7: 1 | F7: 1 | G7: 2 | H7: 2 | I7: 2 | J7: 2 | K7: 2 | L7: 2 | M7: 2 | N7: 2 | O7: 3 | P7: 3 | Q7: 3 | R7: 3 | S7: 4 | T7: 4 | U7: 4 | V7: 4 | W7: 5 | X7: 5 | Y7: 5 | Z7: 5 | AA7: 5 | AB7: 5 | AC7: 5 | AD7: 5 | AE7: 6 | AF7: 6 | AG7: 6 | AH7: 6 | AI7: 6
B8: 売上小計 | D8: =(($C4*D4)+($C5*D5)+($C6*D6)+($C7*D7))*1 -> 28500 | E8: =(($C4*E4)+($C5*E5)+($C6*E6)+($C7*E7))*3 -> 85500 | F8: =(($C4*F4)+($C5*F5)+($C6*F6)+($C7*F7))*3 -> 85500 | G8: =(($C4*G4)+($C5*G5)+($C6*G6)+($C7*G7))*3 -> 171000 | H8: =(($C4*H4)+($C5*H5)+($C6*H6)+($C7*H7))*3 -> 216000 | I8: =(($C4*I4)+($C5*I5)+($C6*I6)+($C7*I7))*3 -> 216000 | J8: =(($C4*J4)+($C5*J5)+($C6*J6)+($C7*J7))*3 -> 238500 | K8: =(($C4*K4)+($C5*K5)+($C6*K6)+($C7*K7))*3 -> 238500 | L8: =(($C4*L4)+($C5*L5)+($C6*L6)+($C7*L7))*3 -> 238500 | ... AI8: =(($C4*AI4)+($C5*AI5)+($C6*AI6)+($C7*AI7))*3 -> 1597500
B9: 店舗数 | D9: =SUM(D4:D7) -> 4 | E9: =SUM(E4:E7) -> 4 | F9: =SUM(F4:F7) -> 4 | G9: =SUM(G4:G7) -> 8 | H9: =SUM(H4:H7) -> 10 | I9: =SUM(I4:I7) -> 10 | J9: =SUM(J4:J7) -> 11 | K9: =SUM(K4:K7) -> 11 | ... AI9: =SUM(AI4:AI7) -> 70
A11: FC | B11: 都市型 | C11: =9000 -> 9000 | E11: 1 | F11: 2 | G11: 2 | H11: 3 | I11: 4 | J11: 4 | K11: 6 | L11: 6 | M11: 9 | N11: 9 | O11: 12 | P11: 14 | Q11: 16 | R11: 18 | S11: 20 | T11: 22 | U11: 24 | V11: 26 | W11: 28 | X11: 31 | Y11: 34 | Z11: 37 | AA11: 40 | AB11: 43 | AC11: 46 | AD11: 49 | AE11: 54 | AF11: 55 | AG11: 58 | AH11: 61 | AI11: 64
B12: サテライト型 | C12: =6000 -> 6000 | E12: 1 | F12: 1 | G12: 2 | H12: 2 | I12: 4 | J12: 4 | K12: 6 | L12: 6 | M12: 9 | N12: 9 | O12: 12 | P12: 14 | Q12: 16 | R12: 18 | S12: 20 | T12: 22 | U12: 24 | V12: 26 | W12: 28 | X12: 31 | Y12: 34 | Z12: 37 | AA12: 42 | AB12: 43 | AC12: 46 | AD12: 49 | AE12: 54 | AF12: 55 | AG12: 58 | AH12: 61 | AI12: 64
B13: 郊外型 | C13: =7500 -> 7500 | E13: 1 | F13: 1 | G13: 2 | H13: 2 | I13: 4 | J13: 4 | K13: 6 | L13: 6 | M13: 9 | N13: 9 | O13: 12 | P13: 14 | Q13: 16 | R13: 18 | S13: 20 | T13: 22 | U13: 24 | V13: 26 | W13: 28 | X13: 31 | Y13: 34 | Z13: 37 | AA13: 40 | AB13: 43 | AC13: 46 | AD13: 49 | AE13: 52 | AF13: 55 | AG13: 58 | AH13: 61 | AI13: 64
B14: SC内 | C14: =6000 -> 6000 | E14: 1 | F14: 2 | G14: 2 | H14: 2 | I14: 2 | J14: 2 | K14: 3 | L14: 3 | M14: 3 | N14: 4 | O14: 4 | P14: 4 | Q14: 4 | R14: 4 | S14: 5 | T14: 5 | U14: 5 | V14: 5 | W14: 6 | X14: 6 | Y14: 6 | Z14: 6 | AA14: 8 | AB14: 8 | AC14: 10 | AD14: 10 | AE14: 10 | AF14: 12 | AG14: 12 | AH14: 12 | AI14: 13
B15: 店舗売上小計 | D15: =(($C11*D11)+($C12*D12)+($C13*D13)+($C14*D14))*3 -> 0 | E15: =(($C11*E11)+($C12*E12)+($C13*E13)+($C14*E14))*3 -> 85500 | F15: =(($C11*F11)+($C12*F12)+($C13*F13)+($C14*F14))*3 -> 130500 | G15: =(($C11*G11)+($C12*G12)+($C13*G13)+($C14*G14))*3 -> 171000 | H15: =(($C11*H11)+($C12*H12)+($C13*H13)+($C14*H14))*3 -> 198000 | I15: =(($C11*I11)+($C12*I12)+($C13*I13)+($C14*I14))*3 -> 306000 | J15: =(($C11*J11)+($C12*J12)+($C13*J13)+($C14*J14))*3 -> 306000 | K15: =(($C11*K11)+($C12*K12)+($C13*K13)+($C14*K14))*3 -> 459000 | ... AI15: =(($C11*AI11)+($C12*AI12)+($C13*AI13)+($C14*AI14))*3 -> 4554000
B16: ロイヤルティ売上 | D16: =D15*0.06 -> 0 | E16: =E15*0.06 -> 5130 | F16: =F15*0.06 -> 7830 | G16: =G15*0.06 -> 10260 | H16: =H15*0.06 -> 11880 | I16: =I15*0.06 -> 18360 | J16: =J15*0.06 -> 18360 | K16: =K15*0.06 -> 27540 | ... AI16: =AI15*0.06 -> 273240
B17: 店舗数 | D17: =SUM(D11:D14) -> 0 | E17: =SUM(E11:E14) -> 4 | F17: =SUM(F11:F14) -> 6 | G17: =SUM(G11:G14) -> 8 | H17: =SUM(H11:H14) -> 9 | I17: =SUM(I11:I14) -> 14 | J17: =SUM(J11:J14) -> 14 | K17: =SUM(K11:K14) -> 21 | ... AI17: =SUM(AI11:AI14) -> 205
B19: 全店舗数 | D19: =D9+D17 -> 4 | E19: =E9+E17 -> 8 | F19: =F9+F17 -> 10 | G19: =G9+G17 -> 16 | H19: =H9+H17 -> 19 | I19: =I9+I17 -> 24 | J19: =J9+J17 -> 25 | K19: =K9+K17 -> 32 | ... AI19: =AI9+AI17 -> 275
B20: 直営FC合計売上 | D20: =D8+D16 -> 28500 | E20: =E8+E16 -> 90630 | F20: =F8+F16 -> 93330 | G20: =G8+G16 -> 181260 | H20: =H8+H16 -> 227880 | I20: =I8+I16 -> 234360 | J20: =J8+J16 -> 256860 | K20: =K8+K16 -> 266040 | ... AI20: =AI8+AI16 -> 1870740
B21: 年間売上 | G21: =SUM(D20:G20) -> 393720 | K21: =SUM(H20:K20) -> 985140 | O21: =SUM(L20:O20) -> 1492920 | S21: =SUM(P20:S20) -> 2242260 | W21: =SUM(T20:W20) -> 3096180 | AA21: =SUM(X20:AA20) -> 4169340 | AE21: =SUM(AB20:AE20) -> 5540940 | AI21: =SUM(AF20:AI20) -> 7064820
B22: 前年比 | K22: =K21/G21 -> 2.5021335 | O22: =O21/K21 -> 1.5154394 | S22: =S21/O21 -> 1.5019291 | W22: =W21/S21 -> 1.3808301 | AA22: =AA21/W21 -> 1.3466078 | AE22: =AE21/AA21 -> 1.3289729 | AI22: =AI21/AE21 -> 1.2750219
K23: ※２年目までに政令指定都市をカバー | O23: ※３年目までに中核市をカバー | S23: ※４年目終了で上場基準を満たして上場準備。海外進出準備 | AI23: ※５年間で展開して店舗数を３年間で達成し倍増する
W24: ※５年目終了で上場し、海外進出に向けて資金調達
U25: ■海外展開分
X26: Phase4：海外進出基盤構築フェーズ | AB26: Phase5：海外成長フェーズ
W27: 月平均売上 | X27: 3-5 | Y27: 6-8 | Z27: 9-11 | AA27: 12-2 | AB27: 3-5 | AC27: 6-8 | AD27: 9-11 | AE27: 12-2 | AF27: 3-5 | AG27: 6-8 | AH27: 9-11 | AI27: 12-2
U28: 直営 | V28: 都市型 | W28: 500 | X28: 3 | Y28: 3 | Z28: 3 | AA28: 5 | AB28: 6 | AC28: 9 | AD28: 12 | AE28: 15 | AF28: 17 | AG28: 19 | AH28: 21 | AI28: 23
V29: サテライト型 | W29: 200 | X29: 3 | Y29: 3 | Z29: 3 | AA29: 5 | AB29: 6 | AC29: 9 | AD29: 12 | AE29: 15 | AF29: 17 | AG29: 19 | AH29: 21 | AI29: 23
V30: 郊外型 | W30: 250 | X30: 3 | Y30: 3 | Z30: 3 | AA30: 5 | AB30: 6 | AC30: 9 | AD30: 12 | AE30: 15 | AF30: 17 | AG30: 19 | AH30: 21 | AI30: 23
V31: SC内 | W31: 100 | X31: 3 | Y31: 3 | Z31: 3 | AA31: 5 | AB31: 6 | AC31: 9 | AD31: 12 | AE31: 15 | AF31: 17 | AG31: 19 | AH31: 21 | AI31: 23
V32: 売上小計 | X32: =(($W28*X28)+($W29*X29)+($W30*X30)+($W31*X31))*3 -> 9450 | Y32: =(($W28*Y28)+($W29*Y29)+($W30*Y30)+($W31*Y31))*3 -> 9450 | Z32: =(($W28*Z28)+($W29*Z29)+($W30*Z30)+($W31*Z31))*3 -> 9450 | AA32: =(($W28*AA28)+($W29*AA29)+($W30*AA30)+($W31*AA31))*3 -> 15750 | AB32: =(($W28*AB28)+($W29*AB29)+($W30*AB30)+($W31*AB31))*3 -> 18900 | AC32: =(($W28*AC28)+($W29*AC29)+($W30*AC30)+($W31*AC31))*3 -> 28350 | AD32: =(($W28*AD28)+($W29*AD29)+($W30*AD30)+($W31*AD31))*3 -> 37800 | AE32: =(($W28*AE28)+($W29*AE29)+($W30*AE30)+($W31*AE31))*3 -> 47250 | ... AI32: =(($W28*AI28)+($W29*AI29)+($W30*AI30)+($W31*AI31))*3 -> 72450
V33: 店舗数 | X33: =SUM(X28:X31) -> 12 | Y33: =SUM(Y28:Y31) -> 12 | Z33: =SUM(Z28:Z31) -> 12 | AA33: =SUM(AA28:AA31) -> 20 | AB33: =SUM(AB28:AB31) -> 24 | AC33: =SUM(AC28:AC31) -> 36 | AD33: =SUM(AD28:AD31) -> 48 | AE33: =SUM(AE28:AE31) -> 60 | ... AI33: =SUM(AI28:AI31) -> 92
U35: FC | V35: 都市型 | W35: 500 | X35: 0 | Y35: 0 | Z35: 1 | AA35: 1 | AB35: 3 | AC35: 5 | AD35: 11 | AE35: 17 | AF35: 29 | AG35: 41 | AH35: 53 | AI35: 65
V36: サテライト型 | W36: 200 | X36: 0 | Y36: 0 | Z36: 1 | AA36: 1 | AB36: 3 | AC36: 5 | AD36: 11 | AE36: 17 | AF36: 29 | AG36: 41 | AH36: 53 | AI36: 65
V37: 郊外型 | W37: 250 | X37: 0 | Y37: 0 | Z37: 1 | AA37: 1 | AB37: 3 | AC37: 5 | AD37: 11 | AE37: 17 | AF37: 29 | AG37: 41 | AH37: 53 | AI37: 65
V38: SC内 | W38: 100 | X38: 0 | Y38: 0 | Z38: 1 | AA38: 1 | AB38: 3 | AC38: 5 | AD38: 11 | AE38: 17 | AF38: 29 | AG38: 41 | AH38: 53 | AI38: 65
V39: 店舗売上小計 | X39: =(($W35*X35)+($W36*X36)+($W37*X37)+($W38*X38))*3 -> 0 | Y39: =(($W35*Y35)+($W36*Y36)+($W37*Y37)+($W38*Y38))*3 -> 0 | Z39: =(($W35*Z35)+($W36*Z36)+($W37*Z37)+($W38*Z38))*3 -> 3150 | AA39: =(($W35*AA35)+($W36*AA36)+($W37*AA37)+($W38*AA38))*3 -> 3150 | AB39: =(($W35*AB35)+($W36*AB36)+($W37*AB37)+($W38*AB38))*3 -> 9450 | AC39: =(($W35*AC35)+($W36*AC36)+($W37*AC37)+($W38*AC38))*3 -> 15750 | AD39: =(($W35*AD35)+($W36*AD36)+($W37*AD37)+($W38*AD38))*3 -> 34650 | AE39: =(($W35*AE35)+($W36*AE36)+($W37*AE37)+($W38*AE38))*3 -> 53550 | ... AI39: =(($W35*AI35)+($W36*AI36)+($W37*AI37)+($W38*AI38))*3 -> 204750
V40: ロイヤルティ売上 | X40: =X39*0.06 -> 0 | Y40: =Y39*0.06 -> 0 | Z40: =Z39*0.06 -> 189 | AA40: =AA39*0.06 -> 189 | AB40: =AB39*0.06 -> 567 | AC40: =AC39*0.06 -> 945 | AD40: =AD39*0.06 -> 2079 | AE40: =AE39*0.06 -> 3213 | ... AI40: =AI39*0.06 -> 12285
V41: 店舗数 | X41: =SUM(X35:X38) -> 0 | Y41: =SUM(Y35:Y38) -> 0 | Z41: =SUM(Z35:Z38) -> 4 | AA41: =SUM(AA35:AA38) -> 4 | AB41: =SUM(AB35:AB38) -> 12 | AC41: =SUM(AC35:AC38) -> 20 | AD41: =SUM(AD35:AD38) -> 44 | AE41: =SUM(AE35:AE38) -> 68 | ... AI41: =SUM(AI35:AI38) -> 260
V43: 海外店舗数 | X43: =X33+X41 -> 12 | Y43: =Y33+Y41 -> 12 | Z43: =Z33+Z41 -> 16 | AA43: =AA33+AA41 -> 24 | AB43: =AB33+AB41 -> 36 | AC43: =AC33+AC41 -> 56 | AD43: =AD33+AD41 -> 92 | AE43: =AE33+AE41 -> 128 | ... AI43: =AI33+AI41 -> 352
V44: 直営FC合計売上 | X44: =X32+X40 -> 9450 | Y44: =Y32+Y40 -> 9450 | Z44: =Z32+Z40 -> 9639 | AA44: =AA32+AA40 -> 15939 | AB44: =AB32+AB40 -> 19467 | AC44: =AC32+AC40 -> 29295 | AD44: =AD32+AD40 -> 39879 | AE44: =AE32+AE40 -> 50463 | ... AI44: =AI32+AI40 -> 84735
V45: 年間売上 | AA45: =SUM(X44:AA44) -> 44478 | AE45: =SUM(AB44:AE44) -> 139104 | AI45: =SUM(AF44:AI44) -> 287532
V46: 前年比 | AE46: =AE45/AA45 -> 3.1274788 | AI46: =AI45/AE45 -> 2.067029
X47: ※米国、アジア２カ国で各国1店舗を展開 | AA47: ※展開好調国で進出都市拡大 | AD47: ※未進出国への進出 | AF47: ※展開好調国で進出都市拡大
Z48: ※海外FC展開開始 | AD48: ※各国でのFC本格展開 | AG48: ※各国でのFC本格展開

Sheet シェル 
A1: シェル（笠岡）
D2: 令和３年 | Q2: 令和4年 | R2: 令和４年 | T2: 30000 | AD2: 令和５年 | AE2: 令和４年 | AG2: 30000 | AQ2: 令和６年 | AR2: 令和４年 | AT2: 30000 | BD2: 令和７年 | BE2: 令和４年 | BG2: 30000
E3: 1月 | F3: 2月 | G3: 3月 | H3: 4月 | I3: 5月 | J3: 6月 | K3: 7月 | L3: 8月 | M3: 9月 | N3: 10月 | O3: 11月 | P3: 12月 | R3: 1月 | S3: 2月 | T3: 3月 | U3: 4月 | V3: 5月 | W3: 6月 | X3: 7月 | Y3: 8月 | Z3: 9月 | AA3: 10月 | AB3: 11月 | AC3: 12月 | AE3: 1月 | AF3: 2月 | AG3: 3月 | AH3: 4月 | AI3: 5月 | AJ3: 6月 | AK3: 7月 | AL3: 8月 | AM3: 9月 | AN3: 10月 | AO3: 11月 | AP3: 12月 | AR3: 1月 | AS3: 2月 | AT3: 3月 | AU3: 4月 | AV3: 5月 | AW3: 6月 | AX3: 7月 | AY3: 8月 | AZ3: 9月 | BA3: 10月 | BB3: 11月 | BC3: 12月 | BE3: 1月 | BF3: 2月 | BG3: 3月 | BH3: 4月 | BI3: 5月 | BJ3: 6月 | BK3: 7月 | BL3: 8月 | BM3: 9月 | BN3: 10月 | BO3: 11月 | BP3: 12月
A4: 稼働日 | E4: 22 | F4: 20 | G4: 23 | H4: 22 | I4: 23 | J4: 22 | K4: 23 | L4: 22 | M4: 22 | N4: 23 | O4: 22 | P4: 22 | R4: 22 | S4: 20 | T4: 23 | U4: 22 | V4: 23 | W4: 22 | X4: 23 | Y4: 22 | Z4: 22 | AA4: 23 | AB4: 22 | AC4: 22 | AE4: 22 | AF4: 20 | AG4: 23 | AH4: 22 | AI4: 23 | AJ4: 22 | AK4: 23 | AL4: 22 | AM4: 22 | AN4: 23 | AO4: 22 | AP4: 22 | AR4: 22 | AS4: 20 | AT4: 23 | AU4: 22 | AV4: 23 | AW4: 22 | AX4: 23 | AY4: 22 | AZ4: 22 | BA4: 23 | BB4: 22 | BC4: 22 | BE4: 22 | BF4: 20 | BG4: 23 | BH4: 22 | BI4: 23 | BJ4: 22 | BK4: 23 | BL4: 22 | BM4: 22 | BN4: 23 | BO4: 22 | BP4: 22
A5: 稼働率 | E5: 0.8 | F5: 0.8 | G5: 0.8 | H5: 0.8 | I5: 0.8 | J5: 0.8 | K5: 0.8 | L5: 0.8 | M5: 0.8 | N5: 0.8 | O5: 0.8 | P5: 0.8 | R5: 0.8 | S5: 0.8 | T5: 0.8 | U5: 0.8 | V5: 0.8 | W5: 0.8 | X5: 0.8 | Y5: 0.8 | Z5: 0.8 | AA5: 0.8 | AB5: 0.8 | AC5: 0.8 | AE5: 0.8 | AF5: 0.8 | AG5: 0.8 | AH5: 0.8 | AI5: 0.8 | AJ5: 0.8 | AK5: 0.8 | AL5: 0.8 | AM5: 0.8 | AN5: 0.8 | AO5: 0.8 | AP5: 0.8 | AR5: 0.8 | AS5: 0.8 | AT5: 0.8 | AU5: 0.8 | AV5: 0.8 | AW5: 0.8 | AX5: 0.8 | AY5: 0.8 | AZ5: 0.8 | BA5: 0.8 | BB5: 0.8 | BC5: 0.8 | BE5: 0.8 | BF5: 0.8 | BG5: 0.8 | BH5: 0.8 | BI5: 0.8 | BJ5: 0.8 | BK5: 0.8 | BL5: 0.8 | BM5: 0.8 | BN5: 0.8 | BO5: 0.8 | BP5: 0.8
A6: 就労B利用者数 | E6: 7 | F6: 7 | G6: 10 | H6: 10 | I6: 10 | J6: 10 | K6: 10 | L6: 10 | M6: 10 | N6: 10 | O6: 10 | P6: 10 | R6: 10 | S6: 10 | T6: 10 | U6: 10 | V6: 10 | W6: 10 | X6: 10 | Y6: 10 | Z6: 10 | AA6: 10 | AB6: 10 | AC6: 10 | AE6: 10 | AF6: 10 | AG6: 10 | AH6: 10 | AI6: 10 | AJ6: 10 | AK6: 10 | AL6: 10 | AM6: 10 | AN6: 10 | AO6: 10 | AP6: 10 | AR6: 10 | AS6: 10 | AT6: 10 | AU6: 10 | AV6: 10 | AW6: 10 | AX6: 10 | AY6: 10 | AZ6: 10 | BA6: 10 | BB6: 10 | BC6: 10 | BE6: 10 | BF6: 10 | BG6: 10 | BH6: 10 | BI6: 10 | BJ6: 10 | BK6: 10 | BL6: 10 | BM6: 10 | BN6: 10 | BO6: 10 | BP6: 10
A7: 就労B施設外利用者数 | K7: 2 | L7: 3 | M7: 4 | N7: 5 | O7: 6 | P7: 7 | R7: 8 | S7: 9 | T7: 10 | U7: 10 | V7: 10 | W7: 10 | X7: 10 | Y7: 10 | Z7: 10 | AA7: 10 | AB7: 10 | AC7: 10 | AE7: 10 | AF7: 10 | AG7: 10 | AH7: 10 | AI7: 10 | AJ7: 10 | AK7: 10 | AL7: 10 | AM7: 10 | AN7: 10 | AO7: 10 | AP7: 10 | AR7: 10 | AS7: 10 | AT7: 10 | AU7: 10 | AV7: 10 | AW7: 10 | AX7: 10 | AY7: 10 | AZ7: 10 | BA7: 10 | BB7: 10 | BC7: 10 | BE7: 10 | BF7: 10 | BG7: 10 | BH7: 10 | BI7: 10 | BJ7: 10 | BK7: 10 | BL7: 10 | BM7: 10 | BN7: 10 | BO7: 10 | BP7: 10
A8: B合計 | E8: =SUM(E6:E7) -> 7 | F8: =SUM(F6:F7) -> 7 | G8: =SUM(G6:G7) -> 10 | H8: =SUM(H6:H7) -> 10 | I8: =SUM(I6:I7) -> 10 | J8: =SUM(J6:J7) -> 10 | K8: =SUM(K6:K7) -> 12 | L8: =SUM(L6:L7) -> 13 | ... P8: =SUM(P6:P7) -> 17 | R8: =SUM(R6:R7) -> 18 | S8: =SUM(S6:S7) -> 19 | T8: =SUM(T6:T7) -> 20 | U8: =SUM(U6:U7) -> 20 | V8: =SUM(V6:V7) -> 20 | W8: =SUM(W6:W7) -> 20 | X8: =SUM(X6:X7) -> 20 | Y8: =SUM(Y6:Y7) -> 20 | ... AC8: =SUM(AC6:AC7) -> 20 | AE8: =SUM(AE6:AE7) -> 20 | AF8: =SUM(AF6:AF7) -> 20 | AG8: =SUM(AG6:AG7) -> 20 | AH8: =SUM(AH6:AH7) -> 20 | AI8: =SUM(AI6:AI7) -> 20 | AJ8: =SUM(AJ6:AJ7) -> 20 | AK8: =SUM(AK6:AK7) -> 20 | AL8: =SUM(AL6:AL7) -> 20 | ... AP8: =SUM(AP6:AP7) -> 20 | AR8: =SUM(AR6:AR7) -> 20 | AS8: =SUM(AS6:AS7) -> 20 | AT8: =SUM(AT6:AT7) -> 20 | AU8: =SUM(AU6:AU7) -> 20 | AV8: =SUM(AV6:AV7) -> 20 | AW8: =SUM(AW6:AW7) -> 20 | AX8: =SUM(AX6:AX7) -> 20 | AY8: =SUM(AY6:AY7) -> 20 | ... BC8: =SUM(BC6:BC7) -> 20 | BE8: =SUM(BE6:BE7) -> 20 | BF8: =SUM(BF6:BF7) -> 20 | BG8: =SUM(BG6:BG7) -> 20 | BH8: =SUM(BH6:BH7) -> 20 | BI8: =SUM(BI6:BI7) -> 20 | BJ8: =SUM(BJ6:BJ7) -> 20 | BK8: =SUM(BK6:BK7) -> 20 | BL8: =SUM(BL6:BL7) -> 20 | ... BP8: =SUM(BP6:BP7) -> 20
A9: 就労移行利用者数 | E9: 4 | F9: 5 | G9: 5 | H9: 6 | I9: 6 | J9: 4 | K9: 5 | L9: 6 | M9: 6 | N9: 7 | O9: 8 | P9: 9 | R9: 10 | S9: 10 | T9: 10 | U9: 10 | V9: 10 | W9: 10 | X9: 10 | Y9: 10 | Z9: 10 | AA9: 10 | AB9: 10 | AC9: 10 | AE9: 10 | AF9: 10 | AG9: 10 | AH9: 10 | AI9: 10 | AJ9: 10 | AK9: 10 | AL9: 10 | AM9: 10 | AN9: 10 | AO9: 10 | AP9: 10 | AR9: 10 | AS9: 10 | AT9: 10 | AU9: 10 | AV9: 10 | AW9: 10 | AX9: 10 | AY9: 10 | AZ9: 10 | BA9: 10 | BB9: 10 | BC9: 10 | BE9: 10 | BF9: 10 | BG9: 10 | BH9: 10 | BI9: 10 | BJ9: 10 | BK9: 10 | BL9: 10 | BM9: 10 | BN9: 10 | BO9: 10 | BP9: 10
A10: 就労移行施設外利用者数 | M10: 2 | N10: 4 | O10: 6 | P10: 8 | R10: 10 | S10: 10 | T10: 10 | U10: 10 | V10: 10 | W10: 10 | X10: 10 | Y10: 10 | Z10: 10 | AA10: 10 | AB10: 10 | AC10: 10 | AE10: 10 | AF10: 10 | AG10: 10 | AH10: 10 | AI10: 10 | AJ10: 10 | AK10: 10 | AL10: 10 | AM10: 10 | AN10: 10 | AO10: 10 | AP10: 10 | AR10: 10 | AS10: 10 | AT10: 10 | AU10: 10 | AV10: 10 | AW10: 10 | AX10: 10 | AY10: 10 | AZ10: 10 | BA10: 10 | BB10: 10 | BC10: 10 | BE10: 10 | BF10: 10 | BG10: 10 | BH10: 10 | BI10: 10 | BJ10: 10 | BK10: 10 | BL10: 10 | BM10: 10 | BN10: 10 | BO10: 10 | BP10: 10
A11: 移行合計 | E11: =SUM(E9:E10) -> 4 | F11: =SUM(F9:F10) -> 5 | G11: =SUM(G9:G10) -> 5 | H11: =SUM(H9:H10) -> 6 | I11: =SUM(I9:I10) -> 6 | J11: =SUM(J9:J10) -> 4 | K11: =SUM(K9:K10) -> 5 | L11: =SUM(L9:L10) -> 6 | ... P11: =SUM(P9:P10) -> 17 | R11: =SUM(R9:R10) -> 20 | S11: =SUM(S9:S10) -> 20 | T11: =SUM(T9:T10) -> 20 | U11: =SUM(U9:U10) -> 20 | V11: =SUM(V9:V10) -> 20 | W11: =SUM(W9:W10) -> 20 | X11: =SUM(X9:X10) -> 20 | Y11: =SUM(Y9:Y10) -> 20 | ... AC11: =SUM(AC9:AC10) -> 20 | AE11: =SUM(AE9:AE10) -> 20 | AF11: =SUM(AF9:AF10) -> 20 | AG11: =SUM(AG9:AG10) -> 20 | AH11: =SUM(AH9:AH10) -> 20 | AI11: =SUM(AI9:AI10) -> 20 | AJ11: =SUM(AJ9:AJ10) -> 20 | AK11: =SUM(AK9:AK10) -> 20 | AL11: =SUM(AL9:AL10) -> 20 | ... AP11: =SUM(AP9:AP10) -> 20 | AR11: =SUM(AR9:AR10) -> 20 | AS11: =SUM(AS9:AS10) -> 20 | AT11: =SUM(AT9:AT10) -> 20 | AU11: =SUM(AU9:AU10) -> 20 | AV11: =SUM(AV9:AV10) -> 20 | AW11: =SUM(AW9:AW10) -> 20 | AX11: =SUM(AX9:AX10) -> 20 | AY11: =SUM(AY9:AY10) -> 20 | ... BC11: =SUM(BC9:BC10) -> 20 | BE11: =SUM(BE9:BE10) -> 20 | BF11: =SUM(BF9:BF10) -> 20 | BG11: =SUM(BG9:BG10) -> 20 | BH11: =SUM(BH9:BH10) -> 20 | BI11: =SUM(BI9:BI10) -> 20 | BJ11: =SUM(BJ9:BJ10) -> 20 | BK11: =SUM(BK9:BK10) -> 20 | BL11: =SUM(BL9:BL10) -> 20 | ... BP11: =SUM(BP9:BP10) -> 20
A12: 合計人数 | E12: =E8:F8+E11 -> 11 | F12: =F8:G8+F11 -> 12 | G12: =G8:H8+G11 -> 15 | H12: =H8:I8+H11 -> 16 | I12: =I8:J8+I11 -> 16 | J12: =J8:K8+J11 -> 14 | K12: =K8:L8+K11 -> 17 | L12: =L8:M8+L11 -> 19 | ... P12: =P8:Q8+P11 -> 34 | R12: =R8:S8+R11 -> 38 | S12: =S8:T8+S11 -> 39 | T12: =T8:U8+T11 -> 40 | U12: =U8:V8+U11 -> 40 | V12: =V8:W8+V11 -> 40 | W12: =W8:X8+W11 -> 40 | X12: =X8:Y8+X11 -> 40 | Y12: =Y8:Z8+Y11 -> 40 | ... AC12: =AC8:AD8+AC11 -> 40 | AE12: =AE8:AF8+AE11 -> 40 | AF12: =AF8:AG8+AF11 -> 40 | AG12: =AG8:AH8+AG11 -> 40 | AH12: =AH8:AI8+AH11 -> 40 | AI12: =AI8:AJ8+AI11 -> 40 | AJ12: =AJ8:AK8+AJ11 -> 40 | AK12: =AK8:AL8+AK11 -> 40 | AL12: =AL8:AM8+AL11 -> 40 | ... AO12: =AO8:AP8+AO11 -> 40 | AP12: =AP8:AP8+AP11 -> 40 | AR12: =AR8:AS8+AR11 -> 40 | AS12: =AS8:AT8+AS11 -> 40 | AT12: =AT8:AU8+AT11 -> 40 | AU12: =AU8:AV8+AU11 -> 40 | AV12: =AV8:AW8+AV11 -> 40 | AW12: =AW8:AX8+AW11 -> 40 | AX12: =AX8:AY8+AX11 -> 40 | AY12: =AY8:AZ8+AY11 -> 40 | ... BB12: =BB8:BC8+BB11 -> 40 | BC12: =BC8:BC8+BC11 -> 40 | BE12: =BE8:BF8+BE11 -> 40 | BF12: =BF8:BG8+BF11 -> 40 | BG12: =BG8:BH8+BG11 -> 40 | BH12: =BH8:BI8+BH11 -> 40 | BI12: =BI8:BJ8+BI11 -> 40 | BJ12: =BJ8:BK8+BJ11 -> 40 | BK12: =BK8:BL8+BK11 -> 40 | BL12: =BL8:BM8+BL11 -> 40 | ... BO12: =BO8:BP8+BO11 -> 40 | BP12: =BP8:BP8+BP11 -> 40
A14: B通常給付金 | E14: =ROUNDDOWN(E6*E23*E4*E5,-2) -> 725600 | F14: =ROUNDDOWN(F6*F23*F4*F5,-2) -> 659600 | G14: =ROUNDDOWN(G6*G23*G4*G5,-2) -> 1083700 | H14: =ROUNDDOWN(H6*H23*H4*H5,-2) -> 1036600 | I14: =ROUNDDOWN(I6*I23*I4*I5,-2) -> 1083700 | J14: =ROUNDDOWN(J6*J23*J4*J5,-2) -> 1036600 | K14: =ROUNDDOWN(K6*K23*K4*K5,-2) -> 1083700 | L14: =ROUNDDOWN(L6*L23*L4*L5,-2) -> 1036600 | ... P14: =ROUNDDOWN(P6*P23*P4*P5,-2) -> 1036600 | R14: =ROUNDDOWN(R6*R23*R4*R5,-2) -> 1036600 | S14: =ROUNDDOWN(S6*S23*S4*S5,-2) -> 942400 | T14: =ROUNDDOWN(T6*T23*T4*T5,-2) -> 1083700 | U14: =ROUNDDOWN(U6*U23*U4*U5,-2) -> 1036600 | V14: =ROUNDDOWN(V6*V23*V4*V5,-2) -> 1083700 | W14: =ROUNDDOWN(W6*W23*W4*W5,-2) -> 1036600 | X14: =ROUNDDOWN(X6*X23*X4*X5,-2) -> 1083700 | Y14: =ROUNDDOWN(Y6*Y23*Y4*Y5,-2) -> 1036600 | ... AC14: =ROUNDDOWN(AC6*AC23*AC4*AC5,-2) -> 1036600 | AE14: =ROUNDDOWN(AE6*AE23*AE4*AE5,-2) -> 1036600 | AF14: =ROUNDDOWN(AF6*AF23*AF4*AF5,-2) -> 942400 | AG14: =ROUNDDOWN(AG6*AG23*AG4*AG5,-2) -> 1083700 | AH14: =ROUNDDOWN(AH6*AH23*AH4*AH5,-2) -> 1036600 | AI14: =ROUNDDOWN(AI6*AI23*AI4*AI5,-2) -> 1083700 | AJ14: =ROUNDDOWN(AJ6*AJ23*AJ4*AJ5,-2) -> 1036600 | AK14: =ROUNDDOWN(AK6*AK23*AK4*AK5,-2) -> 1083700 | AL14: =ROUNDDOWN(AL6*AL23*AL4*AL5,-2) -> 1036600 | ... AP14: =ROUNDDOWN(AP6*AP23*AP4*AP5,-2) -> 1036600 | AR14: =ROUNDDOWN(AR6*AR23*AR4*AR5,-2) -> 1036600 | AS14: =ROUNDDOWN(AS6*AS23*AS4*AS5,-2) -> 942400 | AT14: =ROUNDDOWN(AT6*AT23*AT4*AT5,-2) -> 1083700 | AU14: =ROUNDDOWN(AU6*AU23*AU4*AU5,-2) -> 1036600 | AV14: =ROUNDDOWN(AV6*AV23*AV4*AV5,-2) -> 1083700 | AW14: =ROUNDDOWN(AW6*AW23*AW4*AW5,-2) -> 1036600 | AX14: =ROUNDDOWN(AX6*AX23*AX4*AX5,-2) -> 1083700 | AY14: =ROUNDDOWN(AY6*AY23*AY4*AY5,-2) -> 1036600 | ... BC14: =ROUNDDOWN(BC6*BC23*BC4*BC5,-2) -> 1036600 | BE14: =ROUNDDOWN(BE6*BE23*BE4*BE5,-2) -> 1036600 | BF14: =ROUNDDOWN(BF6*BF23*BF4*BF5,-2) -> 942400 | BG14: =ROUNDDOWN(BG6*BG23*BG4*BG5,-2) -> 1083700 | BH14: =ROUNDDOWN(BH6*BH23*BH4*BH5,-2) -> 1036600 | BI14: =ROUNDDOWN(BI6*BI23*BI4*BI5,-2) -> 1083700 | BJ14: =ROUNDDOWN(BJ6*BJ23*BJ4*BJ5,-2) -> 1036600 | BK14: =ROUNDDOWN(BK6*BK23*BK4*BK5,-2) -> 1083700 | BL14: =ROUNDDOWN(BL6*BL23*BL4*BL5,-2) -> 1036600 | ... BP14: =ROUNDDOWN(BP6*BP23*BP4*BP5,-2) -> 1036600
A15: B施設外給付金 | E15: =ROUNDDOWN(E7*E24*E4*E29,-2) -> 0 | F15: =F7*F24*F4*F29 -> 0 | G15: =G7*G24*G4*G29 -> 0 | H15: =H7*H24*H4*H29 -> 0 | I15: =I7*I24*I4*I29 -> 0 | J15: =J7*J24*J4*J29 -> 0 | K15: =K7*K24*K4*K29 -> 253552 | L15: =L7*L24*L4*L29 -> 363792 | M15: =M7*M24*M4*M29 -> 485056 | ... P15: =P7*P24*P4*P29 -> 848848 | R15: =ROUNDDOWN(R7*R24*R4*R29,-2) -> 909400 | S15: =S7*S24*S4*S29 -> 930150 | T15: =T7*T24*T4*T29 -> 1188525 | U15: =U7*U24*U4*U29 -> 1136850 | V15: =V7*V24*V4*V29 -> 1188525 | W15: =W7*W24*W4*W29 -> 1136850 | X15: =X7*X24*X4*X29 -> 1188525 | Y15: =Y7*Y24*Y4*Y29 -> 1136850 | Z15: =Z7*Z24*Z4*Z29 -> 1136850 | ... AC15: =AC7*AC24*AC4*AC29 -> 1136850 | AE15: =ROUNDDOWN(AE7*AE24*AE4*AE29,-2) -> 1136800 | AF15: =AF7*AF24*AF4*AF29 -> 1033500 | AG15: =AG7*AG24*AG4*AG29 -> 1188525 | AH15: =AH7*AH24*AH4*AH29 -> 1136850 | AI15: =AI7*AI24*AI4*AI29 -> 1188525 | AJ15: =AJ7*AJ24*AJ4*AJ29 -> 1136850 | AK15: =AK7*AK24*AK4*AK29 -> 1188525 | AL15: =AL7*AL24*AL4*AL29 -> 1136850 | AM15: =AM7*AM24*AM4*AM29 -> 1136850 | ... AP15: =AP7*AP24*AP4*AP29 -> 1136850 | AR15: =ROUNDDOWN(AR7*AR24*AR4*AR29,-2) -> 1136800 | AS15: =AS7*AS24*AS4*AS29 -> 1033500 | AT15: =AT7*AT24*AT4*AT29 -> 1188525 | AU15: =AU7*AU24*AU4*AU29 -> 1136850 | AV15: =AV7*AV24*AV4*AV29 -> 1188525 | AW15: =AW7*AW24*AW4*AW29 -> 1136850 | AX15: =AX7*AX24*AX4*AX29 -> 1188525 | AY15: =AY7*AY24*AY4*AY29 -> 1136850 | AZ15: =AZ7*AZ24*AZ4*AZ29 -> 1136850 | ... BC15: =BC7*BC24*BC4*BC29 -> 1136850 | BE15: =ROUNDDOWN(BE7*BE24*BE4*BE29,-2) -> 1136800 | BF15: =BF7*BF24*BF4*BF29 -> 1033500 | BG15: =BG7*BG24*BG4*BG29 -> 1188525 | BH15: =BH7*BH24*BH4*BH29 -> 1136850 | BI15: =BI7*BI24*BI4*BI29 -> 1188525 | BJ15: =BJ7*BJ24*BJ4*BJ29 -> 1136850 | BK15: =BK7*BK24*BK4*BK29 -> 1188525 | BL15: =BL7*BL24*BL4*BL29 -> 1136850 | BM15: =BM7*BM24*BM4*BM29 -> 1136850 | ... BP15: =BP7*BP24*BP4*BP29 -> 1136850
A16: B加算 | E16: =ROUNDDOWN(((E6+E7)*(E27+E28*0.8))*E4,-2) -> 203500 | F16: =ROUNDDOWN(((F6+F7)*(F27+F28*0.8))*F4,-2) -> 185000 | G16: =ROUNDDOWN(((G6+G7)*(G27+G28*0.8))*G4,-2) -> 304000 | H16: =ROUNDDOWN(((H6+H7)*(H27+H28*0.8))*H4,-2) -> 290800 | I16: =ROUNDDOWN(((I6+I7)*(I27+I28*0.8))*I4,-2) -> 304000 | J16: =ROUNDDOWN(((J6+J7)*(J27+J28*0.8))*J4,-2) -> 290800 | K16: =ROUNDDOWN(((K6+K7)*(K27+K28*0.8))*K4,-2) -> 364800 | L16: =ROUNDDOWN(((L6+L7)*(L27+L28*0.8))*L4,-2) -> 378000 | ... P16: =ROUNDDOWN(((P6+P7)*(P27+P28*0.8))*P4,-2) -> 494400 | R16: =ROUNDDOWN(((R6+R7)*(R27+R28*0.8))*R4,-2) -> 523500 | S16: =ROUNDDOWN(((S6+S7)*(S27+S28*0.8))*S4,-2) -> 502300 | T16: =ROUNDDOWN(((T6+T7)*(T27+T28*0.8))*T4,-2) -> 608100 | U16: =ROUNDDOWN(((U6+U7)*(U27+U28*0.8))*U4,-2) -> 581600 | V16: =ROUNDDOWN(((V6+V7)*(V27+V28*0.8))*V4,-2) -> 608100 | W16: =ROUNDDOWN(((W6+W7)*(W27+W28*0.8))*W4,-2) -> 581600 | X16: =ROUNDDOWN(((X6+X7)*(X27+X28*0.8))*X4,-2) -> 608100 | Y16: =ROUNDDOWN(((Y6+Y7)*(Y27+Y28*0.8))*Y4,-2) -> 581600 | ... AC16: =ROUNDDOWN(((AC6+AC7)*(AC27+AC28*0.8))*AC4,-2) -> 581600 | AE16: =ROUNDDOWN(((AE6+AE7)*(AE27+AE28*0.8))*AE4,-2) -> 581600 | AF16: =ROUNDDOWN(((AF6+AF7)*(AF27+AF28*0.8))*AF4,-2) -> 528800 | AG16: =ROUNDDOWN(((AG6+AG7)*(AG27+AG28*0.8))*AG4,-2) -> 608100 | AH16: =ROUNDDOWN(((AH6+AH7)*(AH27+AH28*0.8))*AH4,-2) -> 581600 | AI16: =ROUNDDOWN(((AI6+AI7)*(AI27+AI28*0.8))*AI4,-2) -> 608100 | AJ16: =ROUNDDOWN(((AJ6+AJ7)*(AJ27+AJ28*0.8))*AJ4,-2) -> 581600 | AK16: =ROUNDDOWN(((AK6+AK7)*(AK27+AK28*0.8))*AK4,-2) -> 608100 | AL16: =ROUNDDOWN(((AL6+AL7)*(AL27+AL28*0.8))*AL4,-2) -> 581600 | ... AP16: =ROUNDDOWN(((AP6+AP7)*(AP27+AP28*0.8))*AP4,-2) -> 581600 | AR16: =ROUNDDOWN(((AR6+AR7)*(AR27+AR28*0.8))*AR4,-2) -> 581600 | AS16: =ROUNDDOWN(((AS6+AS7)*(AS27+AS28*0.8))*AS4,-2) -> 528800 | AT16: =ROUNDDOWN(((AT6+AT7)*(AT27+AT28*0.8))*AT4,-2) -> 608100 | AU16: =ROUNDDOWN(((AU6+AU7)*(AU27+AU28*0.8))*AU4,-2) -> 581600 | AV16: =ROUNDDOWN(((AV6+AV7)*(AV27+AV28*0.8))*AV4,-2) -> 608100 | AW16: =ROUNDDOWN(((AW6+AW7)*(AW27+AW28*0.8))*AW4,-2) -> 581600 | AX16: =ROUNDDOWN(((AX6+AX7)*(AX27+AX28*0.8))*AX4,-2) -> 608100 | AY16: =ROUNDDOWN(((AY6+AY7)*(AY27+AY28*0.8))*AY4,-2) -> 581600 | ... BC16: =ROUNDDOWN(((BC6+BC7)*(BC27+BC28*0.8))*BC4,-2) -> 581600 | BE16: =ROUNDDOWN(((BE6+BE7)*(BE27+BE28*0.8))*BE4,-2) -> 581600 | BF16: =ROUNDDOWN(((BF6+BF7)*(BF27+BF28*0.8))*BF4,-2) -> 528800 | BG16: =ROUNDDOWN(((BG6+BG7)*(BG27+BG28*0.8))*BG4,-2) -> 608100 | BH16: =ROUNDDOWN(((BH6+BH7)*(BH27+BH28*0.8))*BH4,-2) -> 581600 | BI16: =ROUNDDOWN(((BI6+BI7)*(BI27+BI28*0.8))*BI4,-2) -> 608100 | BJ16: =ROUNDDOWN(((BJ6+BJ7)*(BJ27+BJ28*0.8))*BJ4,-2) -> 581600 | BK16: =ROUNDDOWN(((BK6+BK7)*(BK27+BK28*0.8))*BK4,-2) -> 608100 | BL16: =ROUNDDOWN(((BL6+BL7)*(BL27+BL28*0.8))*BL4,-2) -> 581600 | ... BP16: =ROUNDDOWN(((BP6+BP7)*(BP27+BP28*0.8))*BP4,-2) -> 581600
A17: 移行通常給付金 | E17: =ROUNDDOWN(E9*E25*E4*E5,-2) -> 568800 | F17: =ROUNDDOWN(F9*F25*F4*F5,-2) -> 646400 | G17: =ROUNDDOWN(G9*G25*G4*G5,-2) -> 743300 | H17: =ROUNDDOWN(H9*H25*H4*H5,-2) -> 853200 | I17: =ROUNDDOWN(I9*I25*I4*I5,-2) -> 892000 | J17: =ROUNDDOWN(J9*J25*J4*J5,-2) -> 568800 | K17: =ROUNDDOWN(K9*K25*K4*K5,-2) -> 743300 | L17: =ROUNDDOWN(L9*L25*L4*L5,-2) -> 853200 | ... P17: =ROUNDDOWN(P9*P25*P4*P5,-2) -> 1279800 | R17: =ROUNDDOWN(R9*R25*R4*R5,-2) -> 1422000 | S17: =ROUNDDOWN(S9*S25*S4*S5,-2) -> 1292800 | T17: =ROUNDDOWN(T9*T25*T4*T5,-2) -> 1486700 | U17: =ROUNDDOWN(U9*U25*U4*U5,-2) -> 1422000 | V17: =ROUNDDOWN(V9*V25*V4*V5,-2) -> 1486700 | W17: =ROUNDDOWN(W9*W25*W4*W5,-2) -> 1422000 | X17: =ROUNDDOWN(X9*X25*X4*X5,-2) -> 1486700 | Y17: =ROUNDDOWN(Y9*Y25*Y4*Y5,-2) -> 1422000 | ... AC17: =ROUNDDOWN(AC9*AC25*AC4*AC5,-2) -> 1422000 | AE17: =ROUNDDOWN(AE9*AE25*AE4*AE5,-2) -> 1422000 | AF17: =ROUNDDOWN(AF9*AF25*AF4*AF5,-2) -> 1292800 | AG17: =ROUNDDOWN(AG9*AG25*AG4*AG5,-2) -> 1486700 | AH17: =ROUNDDOWN(AH9*AH25*AH4*AH5,-2) -> 1422000 | AI17: =ROUNDDOWN(AI9*AI25*AI4*AI5,-2) -> 1486700 | AJ17: =ROUNDDOWN(AJ9*AJ25*AJ4*AJ5,-2) -> 1422000 | AK17: =ROUNDDOWN(AK9*AK25*AK4*AK5,-2) -> 1486700 | AL17: =ROUNDDOWN(AL9*AL25*AL4*AL5,-2) -> 1422000 | ... AP17: =ROUNDDOWN(AP9*AP25*AP4*AP5,-2) -> 1422000 | AR17: =ROUNDDOWN(AR9*AR25*AR4*AR5,-2) -> 1422000 | AS17: =ROUNDDOWN(AS9*AS25*AS4*AS5,-2) -> 1292800 | AT17: =ROUNDDOWN(AT9*AT25*AT4*AT5,-2) -> 1486700 | AU17: =ROUNDDOWN(AU9*AU25*AU4*AU5,-2) -> 1422000 | AV17: =ROUNDDOWN(AV9*AV25*AV4*AV5,-2) -> 1486700 | AW17: =ROUNDDOWN(AW9*AW25*AW4*AW5,-2) -> 1422000 | AX17: =ROUNDDOWN(AX9*AX25*AX4*AX5,-2) -> 1486700 | AY17: =ROUNDDOWN(AY9*AY25*AY4*AY5,-2) -> 1422000 | ... BC17: =ROUNDDOWN(BC9*BC25*BC4*BC5,-2) -> 1422000 | BE17: =ROUNDDOWN(BE9*BE25*BE4*BE5,-2) -> 1422000 | BF17: =ROUNDDOWN(BF9*BF25*BF4*BF5,-2) -> 1292800 | BG17: =ROUNDDOWN(BG9*BG25*BG4*BG5,-2) -> 1486700 | BH17: =ROUNDDOWN(BH9*BH25*BH4*BH5,-2) -> 1422000 | BI17: =ROUNDDOWN(BI9*BI25*BI4*BI5,-2) -> 1486700 | BJ17: =ROUNDDOWN(BJ9*BJ25*BJ4*BJ5,-2) -> 1422000 | BK17: =ROUNDDOWN(BK9*BK25*BK4*BK5,-2) -> 1486700 | BL17: =ROUNDDOWN(BL9*BL25*BL4*BL5,-2) -> 1422000 | ... BP17: =ROUNDDOWN(BP9*BP25*BP4*BP5,-2) -> 1422000
A18: 移行施設外給付金 | E18: =ROUNDDOWN(E10*E26*E4*E5,-2) -> 0 | F18: =ROUNDDOWN(F10*F26*F4*F5,-2) -> 0 | G18: =ROUNDDOWN(G10*G26*G4*G5,-2) -> 0 | H18: =ROUNDDOWN(H10*H26*H4*H5,-2) -> 0 | I18: =ROUNDDOWN(I10*I26*I4*I5,-2) -> 0 | J18: =ROUNDDOWN(J10*J26*J4*J5,-2) -> 0 | K18: =ROUNDDOWN(K10*K26*K4*K5,-2) -> 0 | L18: =ROUNDDOWN(L10*L26*L4*L5,-2) -> 0 | ... P18: =ROUNDDOWN(P10*P26*P4*P5,-2) -> 1278400 | R18: =ROUNDDOWN(R10*R26*R4*R5,-2) -> 1598000 | S18: =ROUNDDOWN(S10*S26*S4*S5,-2) -> 1452800 | T18: =ROUNDDOWN(T10*T26*T4*T5,-2) -> 1670700 | U18: =ROUNDDOWN(U10*U26*U4*U5,-2) -> 1598000 | V18: =ROUNDDOWN(V10*V26*V4*V5,-2) -> 1670700 | W18: =ROUNDDOWN(W10*W26*W4*W5,-2) -> 1598000 | X18: =ROUNDDOWN(X10*X26*X4*X5,-2) -> 1670700 | Y18: =ROUNDDOWN(Y10*Y26*Y4*Y5,-2) -> 1598000 | ... AC18: =ROUNDDOWN(AC10*AC26*AC4*AC5,-2) -> 1598000 | AE18: =ROUNDDOWN(AE10*AE26*AE4*AE5,-2) -> 1598000 | AF18: =ROUNDDOWN(AF10*AF26*AF4*AF5,-2) -> 1452800 | AG18: =ROUNDDOWN(AG10*AG26*AG4*AG5,-2) -> 1670700 | AH18: =ROUNDDOWN(AH10*AH26*AH4*AH5,-2) -> 1598000 | AI18: =ROUNDDOWN(AI10*AI26*AI4*AI5,-2) -> 1670700 | AJ18: =ROUNDDOWN(AJ10*AJ26*AJ4*AJ5,-2) -> 1598000 | AK18: =ROUNDDOWN(AK10*AK26*AK4*AK5,-2) -> 1670700 | AL18: =ROUNDDOWN(AL10*AL26*AL4*AL5,-2) -> 1598000 | ... AP18: =ROUNDDOWN(AP10*AP26*AP4*AP5,-2) -> 1598000 | AR18: =ROUNDDOWN(AR10*AR26*AR4*AR5,-2) -> 1598000 | AS18: =ROUNDDOWN(AS10*AS26*AS4*AS5,-2) -> 1452800 | AT18: =ROUNDDOWN(AT10*AT26*AT4*AT5,-2) -> 1670700 | AU18: =ROUNDDOWN(AU10*AU26*AU4*AU5,-2) -> 1598000 | AV18: =ROUNDDOWN(AV10*AV26*AV4*AV5,-2) -> 1670700 | AW18: =ROUNDDOWN(AW10*AW26*AW4*AW5,-2) -> 1598000 | AX18: =ROUNDDOWN(AX10*AX26*AX4*AX5,-2) -> 1670700 | AY18: =ROUNDDOWN(AY10*AY26*AY4*AY5,-2) -> 1598000 | ... BC18: =ROUNDDOWN(BC10*BC26*BC4*BC5,-2) -> 1598000 | BE18: =ROUNDDOWN(BE10*BE26*BE4*BE5,-2) -> 1598000 | BF18: =ROUNDDOWN(BF10*BF26*BF4*BF5,-2) -> 1452800 | BG18: =ROUNDDOWN(BG10*BG26*BG4*BG5,-2) -> 1670700 | BH18: =ROUNDDOWN(BH10*BH26*BH4*BH5,-2) -> 1598000 | BI18: =ROUNDDOWN(BI10*BI26*BI4*BI5,-2) -> 1670700 | BJ18: =ROUNDDOWN(BJ10*BJ26*BJ4*BJ5,-2) -> 1598000 | BK18: =ROUNDDOWN(BK10*BK26*BK4*BK5,-2) -> 1670700 | BL18: =ROUNDDOWN(BL10*BL26*BL4*BL5,-2) -> 1598000 | ... BP18: =ROUNDDOWN(BP10*BP26*BP4*BP5,-2) -> 1598000
A19: 移行加算 | E19: =ROUNDDOWN((E9+E10)*E4*E5*E28,-2) -> 38000 | F19: =ROUNDDOWN((F9+F10)*F4*F5*F28,-2) -> 43200 | G19: =ROUNDDOWN((G9+G10)*G4*G5*G28,-2) -> 49600 | H19: =ROUNDDOWN((H9+H10)*H4*H5*H28,-2) -> 57000 | I19: =ROUNDDOWN((I9+I10)*I4*I5*I28,-2) -> 59600 | J19: =ROUNDDOWN((J9+J10)*J4*J5*J28,-2) -> 38000 | K19: =ROUNDDOWN((K9+K10)*K4*K5*K28,-2) -> 49600 | L19: =ROUNDDOWN((L9+L10)*L4*L5*L28,-2) -> 57000 | ... P19: =ROUNDDOWN((P9+P10)*P4*P5*P28,-2) -> 161500 | R19: =ROUNDDOWN((R9+R10)*R4*R5*R28,-2) -> 190000 | S19: =ROUNDDOWN((S9+S10)*S4*S5*S28,-2) -> 172800 | T19: =ROUNDDOWN((T9+T10)*T4*T5*T28,-2) -> 198700 | U19: =ROUNDDOWN((U9+U10)*U4*U5*U28,-2) -> 190000 | V19: =ROUNDDOWN((V9+V10)*V4*V5*V28,-2) -> 198700 | W19: =ROUNDDOWN((W9+W10)*W4*W5*W28,-2) -> 190000 | X19: =ROUNDDOWN((X9+X10)*X4*X5*X28,-2) -> 198700 | Y19: =ROUNDDOWN((Y9+Y10)*Y4*Y5*Y28,-2) -> 190000 | ... AC19: =ROUNDDOWN((AC9+AC10)*AC4*AC5*AC28,-2) -> 190000 | AE19: =ROUNDDOWN((AE9+AE10)*AE4*AE5*AE28,-2) -> 190000 | AF19: =ROUNDDOWN((AF9+AF10)*AF4*AF5*AF28,-2) -> 172800 | AG19: =ROUNDDOWN((AG9+AG10)*AG4*AG5*AG28,-2) -> 198700 | AH19: =ROUNDDOWN((AH9+AH10)*AH4*AH5*AH28,-2) -> 190000 | AI19: =ROUNDDOWN((AI9+AI10)*AI4*AI5*AI28,-2) -> 198700 | AJ19: =ROUNDDOWN((AJ9+AJ10)*AJ4*AJ5*AJ28,-2) -> 190000 | AK19: =ROUNDDOWN((AK9+AK10)*AK4*AK5*AK28,-2) -> 198700 | AL19: =ROUNDDOWN((AL9+AL10)*AL4*AL5*AL28,-2) -> 190000 | ... AP19: =ROUNDDOWN((AP9+AP10)*AP4*AP5*AP28,-2) -> 190000 | AR19: =ROUNDDOWN((AR9+AR10)*AR4*AR5*AR28,-2) -> 190000 | AS19: =ROUNDDOWN((AS9+AS10)*AS4*AS5*AS28,-2) -> 172800 | AT19: =ROUNDDOWN((AT9+AT10)*AT4*AT5*AT28,-2) -> 198700 | AU19: =ROUNDDOWN((AU9+AU10)*AU4*AU5*AU28,-2) -> 190000 | AV19: =ROUNDDOWN((AV9+AV10)*AV4*AV5*AV28,-2) -> 198700 | AW19: =ROUNDDOWN((AW9+AW10)*AW4*AW5*AW28,-2) -> 190000 | AX19: =ROUNDDOWN((AX9+AX10)*AX4*AX5*AX28,-2) -> 198700 | AY19: =ROUNDDOWN((AY9+AY10)*AY4*AY5*AY28,-2) -> 190000 | ... BC19: =ROUNDDOWN((BC9+BC10)*BC4*BC5*BC28,-2) -> 190000 | BE19: =ROUNDDOWN((BE9+BE10)*BE4*BE5*BE28,-2) -> 190000 | BF19: =ROUNDDOWN((BF9+BF10)*BF4*BF5*BF28,-2) -> 172800 | BG19: =ROUNDDOWN((BG9+BG10)*BG4*BG5*BG28,-2) -> 198700 | BH19: =ROUNDDOWN((BH9+BH10)*BH4*BH5*BH28,-2) -> 190000 | BI19: =ROUNDDOWN((BI9+BI10)*BI4*BI5*BI28,-2) -> 198700 | BJ19: =ROUNDDOWN((BJ9+BJ10)*BJ4*BJ5*BJ28,-2) -> 190000 | BK19: =ROUNDDOWN((BK9+BK10)*BK4*BK5*BK28,-2) -> 198700 | BL19: =ROUNDDOWN((BL9+BL10)*BL4*BL5*BL28,-2) -> 190000 | ... BP19: =ROUNDDOWN((BP9+BP10)*BP4*BP5*BP28,-2) -> 190000
A20: 給付費合計 | E20: =SUM(E14:E19) -> 1535900 | F20: =SUM(F14:F19) -> 1534200 | G20: =SUM(G14:G19) -> 2180600 | H20: =SUM(H14:H19) -> 2237600 | I20: =SUM(I14:I19) -> 2339300 | J20: =SUM(J14:J19) -> 1934200 | K20: =SUM(K14:K19) -> 2494952 | L20: =SUM(L14:L19) -> 2688592 | ... P20: =SUM(P14:P19) -> 5099548 | R20: =SUM(R14:R19) -> 5679500 | S20: =SUM(S14:S19) -> 5293250 | T20: =SUM(T14:T19) -> 6236425 | U20: =SUM(U14:U19) -> 5965050 | V20: =SUM(V14:V19) -> 6236425 | W20: =SUM(W14:W19) -> 5965050 | X20: =SUM(X14:X19) -> 6236425 | Y20: =SUM(Y14:Y19) -> 5965050 | ... AC20: =SUM(AC14:AC19) -> 5965050 | AE20: =SUM(AE14:AE19) -> 5965000 | AF20: =SUM(AF14:AF19) -> 5423100 | AG20: =SUM(AG14:AG19) -> 6236425 | AH20: =SUM(AH14:AH19) -> 5965050 | AI20: =SUM(AI14:AI19) -> 6236425 | AJ20: =SUM(AJ14:AJ19) -> 5965050 | AK20: =SUM(AK14:AK19) -> 6236425 | AL20: =SUM(AL14:AL19) -> 5965050 | ... AP20: =SUM(AP14:AP19) -> 5965050 | AR20: =SUM(AR14:AR19) -> 5965000 | AS20: =SUM(AS14:AS19) -> 5423100 | AT20: =SUM(AT14:AT19) -> 6236425 | AU20: =SUM(AU14:AU19) -> 5965050 | AV20: =SUM(AV14:AV19) -> 6236425 | AW20: =SUM(AW14:AW19) -> 5965050 | AX20: =SUM(AX14:AX19) -> 6236425 | AY20: =SUM(AY14:AY19) -> 5965050 | ... BC20: =SUM(BC14:BC19) -> 5965050 | BE20: =SUM(BE14:BE19) -> 5965000 | BF20: =SUM(BF14:BF19) -> 5423100 | BG20: =SUM(BG14:BG19) -> 6236425 | BH20: =SUM(BH14:BH19) -> 5965050 | BI20: =SUM(BI14:BI19) -> 6236425 | BJ20: =SUM(BJ14:BJ19) -> 5965050 | BK20: =SUM(BK14:BK19) -> 6236425 | BL20: =SUM(BL14:BL19) -> 5965050 | ... BP20: =SUM(BP14:BP19) -> 5965050
A21: 給付費合計（千円） | E21: =E20/1000 -> 1535.9 | F21: =F20/1000 -> 1534.2 | G21: =G20/1000 -> 2180.6 | H21: =H20/1000 -> 2237.6 | I21: =I20/1000 -> 2339.3 | J21: =J20/1000 -> 1934.2 | K21: =K20/1000 -> 2494.952 | L21: =L20/1000 -> 2688.592 | ... P21: =P20/1000 -> 5099.548 | R21: =R20/1000 -> 5679.5 | S21: =S20/1000 -> 5293.25 | T21: =T20/1000 -> 6236.425 | U21: =U20/1000 -> 5965.05 | V21: =V20/1000 -> 6236.425 | W21: =W20/1000 -> 5965.05 | X21: =X20/1000 -> 6236.425 | Y21: =Y20/1000 -> 5965.05 | ... AC21: =AC20/1000 -> 5965.05 | AE21: =AE20/1000 -> 5965 | AF21: =AF20/1000 -> 5423.1 | AG21: =AG20/1000 -> 6236.425 | AH21: =AH20/1000 -> 5965.05 | AI21: =AI20/1000 -> 6236.425 | AJ21: =AJ20/1000 -> 5965.05 | AK21: =AK20/1000 -> 6236.425 | AL21: =AL20/1000 -> 5965.05 | ... AP21: =AP20/1000 -> 5965.05 | AR21: =AR20/1000 -> 5965 | AS21: =AS20/1000 -> 5423.1 | AT21: =AT20/1000 -> 6236.425 | AU21: =AU20/1000 -> 5965.05 | AV21: =AV20/1000 -> 6236.425 | AW21: =AW20/1000 -> 5965.05 | AX21: =AX20/1000 -> 6236.425 | AY21: =AY20/1000 -> 5965.05 | ... BC21: =BC20/1000 -> 5965.05 | BE21: =BE20/1000 -> 5965 | BF21: =BF20/1000 -> 5423.1 | BG21: =BG20/1000 -> 6236.425 | BH21: =BH20/1000 -> 5965.05 | BI21: =BI20/1000 -> 6236.425 | BJ21: =BJ20/1000 -> 5965.05 | BK21: =BK20/1000 -> 6236.425 | BL21: =BL20/1000 -> 5965.05 | ... BP21: =BP20/1000 -> 5965.05
A23: B基本報酬 | E23: 5890 | F23: 5890 | G23: 5890 | H23: 5890 | I23: 5890 | J23: 5890 | K23: 5890 | L23: 5890 | M23: 5890 | N23: 5890 | O23: 5890 | P23: 5890 | R23: 5890 | S23: 5890 | T23: 5890 | U23: 5890 | V23: 5890 | W23: 5890 | X23: 5890 | Y23: 5890 | Z23: 5890 | AA23: 5890 | AB23: 5890 | AC23: 5890 | AE23: 5890 | AF23: 5890 | AG23: 5890 | AH23: 5890 | AI23: 5890 | AJ23: 5890 | AK23: 5890 | AL23: 5890 | AM23: 5890 | AN23: 5890 | AO23: 5890 | AP23: 5890 | AR23: 5890 | AS23: 5890 | AT23: 5890 | AU23: 5890 | AV23: 5890 | AW23: 5890 | AX23: 5890 | AY23: 5890 | AZ23: 5890 | BA23: 5890 | BB23: 5890 | BC23: 5890 | BE23: 5890 | BF23: 5890 | BG23: 5890 | BH23: 5890 | BI23: 5890 | BJ23: 5890 | BK23: 5890 | BL23: 5890 | BM23: 5890 | BN23: 5890 | BO23: 5890 | BP23: 5890
A24: B施設外基本報酬 | E24: 6890 | F24: 6890 | G24: 6890 | H24: 6890 | I24: 6890 | J24: 6890 | K24: 6890 | L24: 6890 | M24: 6890 | N24: 6890 | O24: 6890 | P24: 6890 | R24: 6890 | S24: 6890 | T24: 6890 | U24: 6890 | V24: 6890 | W24: 6890 | X24: 6890 | Y24: 6890 | Z24: 6890 | AA24: 6890 | AB24: 6890 | AC24: 6890 | AE24: 6890 | AF24: 6890 | AG24: 6890 | AH24: 6890 | AI24: 6890 | AJ24: 6890 | AK24: 6890 | AL24: 6890 | AM24: 6890 | AN24: 6890 | AO24: 6890 | AP24: 6890 | AR24: 6890 | AS24: 6890 | AT24: 6890 | AU24: 6890 | AV24: 6890 | AW24: 6890 | AX24: 6890 | AY24: 6890 | AZ24: 6890 | BA24: 6890 | BB24: 6890 | BC24: 6890 | BE24: 6890 | BF24: 6890 | BG24: 6890 | BH24: 6890 | BI24: 6890 | BJ24: 6890 | BK24: 6890 | BL24: 6890 | BM24: 6890 | BN24: 6890 | BO24: 6890 | BP24: 6890
A25: 移行基本報酬 | E25: 8080 | F25: 8080 | G25: 8080 | H25: 8080 | I25: 8080 | J25: 8080 | K25: 8080 | L25: 8080 | M25: 8080 | N25: 8080 | O25: 8080 | P25: 8080 | R25: 8080 | S25: 8080 | T25: 8080 | U25: 8080 | V25: 8080 | W25: 8080 | X25: 8080 | Y25: 8080 | Z25: 8080 | AA25: 8080 | AB25: 8080 | AC25: 8080 | AE25: 8080 | AF25: 8080 | AG25: 8080 | AH25: 8080 | AI25: 8080 | AJ25: 8080 | AK25: 8080 | AL25: 8080 | AM25: 8080 | AN25: 8080 | AO25: 8080 | AP25: 8080 | AR25: 8080 | AS25: 8080 | AT25: 8080 | AU25: 8080 | AV25: 8080 | AW25: 8080 | AX25: 8080 | AY25: 8080 | AZ25: 8080 | BA25: 8080 | BB25: 8080 | BC25: 8080 | BE25: 8080 | BF25: 8080 | BG25: 8080 | BH25: 8080 | BI25: 8080 | BJ25: 8080 | BK25: 8080 | BL25: 8080 | BM25: 8080 | BN25: 8080 | BO25: 8080 | BP25: 8080
A26: 移行施設外基本報酬 | E26: 9080 | F26: 9080 | G26: 9080 | H26: 9080 | I26: 9080 | J26: 9080 | K26: 9080 | L26: 9080 | M26: 9080 | N26: 9080 | O26: 9080 | P26: 9080 | R26: 9080 | S26: 9080 | T26: 9080 | U26: 9080 | V26: 9080 | W26: 9080 | X26: 9080 | Y26: 9080 | Z26: 9080 | AA26: 9080 | AB26: 9080 | AC26: 9080 | AE26: 9080 | AF26: 9080 | AG26: 9080 | AH26: 9080 | AI26: 9080 | AJ26: 9080 | AK26: 9080 | AL26: 9080 | AM26: 9080 | AN26: 9080 | AO26: 9080 | AP26: 9080 | AR26: 9080 | AS26: 9080 | AT26: 9080 | AU26: 9080 | AV26: 9080 | AW26: 9080 | AX26: 9080 | AY26: 9080 | AZ26: 9080 | BA26: 9080 | BB26: 9080 | BC26: 9080 | BE26: 9080 | BF26: 9080 | BG26: 9080 | BH26: 9080 | BI26: 9080 | BJ26: 9080 | BK26: 9080 | BL26: 9080 | BM26: 9080 | BN26: 9080 | BO26: 9080 | BP26: 9080
A27: 目標工賃達成指導員加算 | E27: 890 | F27: 890 | G27: 890 | H27: 890 | I27: 890 | J27: 890 | K27: 890 | L27: 890 | M27: 890 | N27: 890 | O27: 890 | P27: 890 | R27: 890 | S27: 890 | T27: 890 | U27: 890 | V27: 890 | W27: 890 | X27: 890 | Y27: 890 | Z27: 890 | AA27: 890 | AB27: 890 | AC27: 890 | AE27: 890 | AF27: 890 | AG27: 890 | AH27: 890 | AI27: 890 | AJ27: 890 | AK27: 890 | AL27: 890 | AM27: 890 | AN27: 890 | AO27: 890 | AP27: 890 | AR27: 890 | AS27: 890 | AT27: 890 | AU27: 890 | AV27: 890 | AW27: 890 | AX27: 890 | AY27: 890 | AZ27: 890 | BA27: 890 | BB27: 890 | BC27: 890 | BE27: 890 | BF27: 890 | BG27: 890 | BH27: 890 | BI27: 890 | BJ27: 890 | BK27: 890 | BL27: 890 | BM27: 890 | BN27: 890 | BO27: 890 | BP27: 890
A28: 送迎加算 | E28: 540 | F28: 540 | G28: 540 | H28: 540 | I28: 540 | J28: 540 | K28: 540 | L28: 540 | M28: 540 | N28: 540 | O28: 540 | P28: 540 | R28: 540 | S28: 540 | T28: 540 | U28: 540 | V28: 540 | W28: 540 | X28: 540 | Y28: 540 | Z28: 540 | AA28: 540 | AB28: 540 | AC28: 540 | AE28: 540 | AF28: 540 | AG28: 540 | AH28: 540 | AI28: 540 | AJ28: 540 | AK28: 540 | AL28: 540 | AM28: 540 | AN28: 540 | AO28: 540 | AP28: 540 | AR28: 540 | AS28: 540 | AT28: 540 | AU28: 540 | AV28: 540 | AW28: 540 | AX28: 540 | AY28: 540 | AZ28: 540 | BA28: 540 | BB28: 540 | BC28: 540 | BE28: 540 | BF28: 540 | BG28: 540 | BH28: 540 | BI28: 540 | BJ28: 540 | BK28: 540 | BL28: 540 | BM28: 540 | BN28: 540 | BO28: 540 | BP28: 540
A29: 稼働率 | E29: 0.8 | F29: 0.8 | G29: 0.8 | H29: 0.8 | I29: 0.8 | J29: 0.8 | K29: 0.8 | L29: 0.8 | M29: 0.8 | N29: 0.8 | O29: 0.8 | P29: 0.8 | R29: 0.75 | S29: 0.75 | T29: 0.75 | U29: 0.75 | V29: 0.75 | W29: 0.75 | X29: 0.75 | Y29: 0.75 | Z29: 0.75 | AA29: 0.75 | AB29: 0.75 | AC29: 0.75 | AE29: 0.75 | AF29: 0.75 | AG29: 0.75 | AH29: 0.75 | AI29: 0.75 | AJ29: 0.75 | AK29: 0.75 | AL29: 0.75 | AM29: 0.75 | AN29: 0.75 | AO29: 0.75 | AP29: 0.75 | AR29: 0.75 | AS29: 0.75 | AT29: 0.75 | AU29: 0.75 | AV29: 0.75 | AW29: 0.75 | AX29: 0.75 | AY29: 0.75 | AZ29: 0.75 | BA29: 0.75 | BB29: 0.75 | BC29: 0.75 | BE29: 0.75 | BF29: 0.75 | BG29: 0.75 | BH29: 0.75 | BI29: 0.75 | BJ29: 0.75 | BK29: 0.75 | BL29: 0.75 | BM29: 0.75 | BN29: 0.75 | BO29: 0.75 | BP29: 0.75
A32: B人員配置 | E32: =ROUNDUP(E6/7.5,0) -> 1 | F32: =ROUNDUP(F6/7.5,0) -> 1 | G32: =ROUNDUP(G6/7.5,1) -> 1.4 | H32: =ROUNDUP(H6/7.5,1) -> 1.4 | I32: =ROUNDUP(I6/7.5,1) -> 1.4 | J32: =ROUNDUP(J6/7.5,1) -> 1.4 | K32: =ROUNDUP(K6/7.5,1) -> 1.4 | L32: =ROUNDUP(L6/7.5,1) -> 1.4 | M32: =ROUNDUP(M6/7.5,1) -> 1.4 | N32: =ROUNDUP(N6/7.5,1) -> 1.4 | ... P32: =ROUNDUP(P6/7.5,1) -> 1.4 | R32: =ROUNDUP(R6/7.5,0) -> 2 | S32: =ROUNDUP(S6/7.5,0) -> 2 | T32: =ROUNDUP(T6/7.5,1) -> 1.4 | U32: =ROUNDUP(U6/7.5,1) -> 1.4 | V32: =ROUNDUP(V6/7.5,1) -> 1.4 | W32: =ROUNDUP(W6/7.5,1) -> 1.4 | X32: =ROUNDUP(X6/7.5,1) -> 1.4 | Y32: =ROUNDUP(Y6/7.5,1) -> 1.4 | Z32: =ROUNDUP(Z6/7.5,1) -> 1.4 | AA32: =ROUNDUP(AA6/7.5,1) -> 1.4 | ... AC32: =ROUNDUP(AC6/7.5,1) -> 1.4 | AE32: =ROUNDUP(AE6/7.5,0) -> 2 | AF32: =ROUNDUP(AF6/7.5,0) -> 2 | AG32: =ROUNDUP(AG6/7.5,1) -> 1.4 | AH32: =ROUNDUP(AH6/7.5,1) -> 1.4 | AI32: =ROUNDUP(AI6/7.5,1) -> 1.4 | AJ32: =ROUNDUP(AJ6/7.5,1) -> 1.4 | AK32: =ROUNDUP(AK6/7.5,1) -> 1.4 | AL32: =ROUNDUP(AL6/7.5,1) -> 1.4 | AM32: =ROUNDUP(AM6/7.5,1) -> 1.4 | AN32: =ROUNDUP(AN6/7.5,1) -> 1.4 | ... AP32: =ROUNDUP(AP6/7.5,1) -> 1.4 | AR32: =ROUNDUP(AR6/7.5,0) -> 2 | AS32: =ROUNDUP(AS6/7.5,0) -> 2 | AT32: =ROUNDUP(AT6/7.5,1) -> 1.4 | AU32: =ROUNDUP(AU6/7.5,1) -> 1.4 | AV32: =ROUNDUP(AV6/7.5,1) -> 1.4 | AW32: =ROUNDUP(AW6/7.5,1) -> 1.4 | AX32: =ROUNDUP(AX6/7.5,1) -> 1.4 | AY32: =ROUNDUP(AY6/7.5,1) -> 1.4 | AZ32: =ROUNDUP(AZ6/7.5,1) -> 1.4 | BA32: =ROUNDUP(BA6/7.5,1) -> 1.4 | ... BC32: =ROUNDUP(BC6/7.5,1) -> 1.4 | BE32: =ROUNDUP(BE6/7.5,0) -> 2 | BF32: =ROUNDUP(BF6/7.5,0) -> 2 | BG32: =ROUNDUP(BG6/7.5,1) -> 1.4 | BH32: =ROUNDUP(BH6/7.5,1) -> 1.4 | BI32: =ROUNDUP(BI6/7.5,1) -> 1.4 | BJ32: =ROUNDUP(BJ6/7.5,1) -> 1.4 | BK32: =ROUNDUP(BK6/7.5,1) -> 1.4 | BL32: =ROUNDUP(BL6/7.5,1) -> 1.4 | BM32: =ROUNDUP(BM6/7.5,1) -> 1.4 | BN32: =ROUNDUP(BN6/7.5,1) -> 1.4 | ... BP32: =ROUNDUP(BP6/7.5,1) -> 1.4
A33: B人工賃向上・施設外 | E33: =IF(E7/7.5<1,2,1+E7/7.5) -> 2 | F33: =IF(F7/7.5<1,2,1+F7/7.5) -> 2 | G33: =IF(G7/7.5<1,2,1+G7/7.5) -> 2 | H33: =IF(H7/7.5<1,2,1+H7/7.5) -> 2 | I33: =IF(I7/7.5<1,2,1+I7/7.5) -> 2 | J33: =IF(J7/7.5<1,2,1+J7/7.5) -> 2 | K33: =IF(K7/7.5<1,2,1+K7/7.5) -> 2 | L33: =IF(L7/7.5<1,2,1+L7/7.5) -> 2 | ... P33: =IF(P7/7.5<1,2,1+P7/7.5) -> 2 | R33: =IF(R7/7.5<1,2,1+R7/7.5) -> 2.0666667 | S33: =IF(S7/7.5<1,2,1+S7/7.5) -> 2.2 | T33: =IF(T7/7.5<1,2,1+T7/7.5) -> 2.3333333 | U33: =IF(U7/7.5<1,2,1+U7/7.5) -> 2.3333333 | V33: =IF(V7/7.5<1,2,1+V7/7.5) -> 2.3333333 | W33: =IF(W7/7.5<1,2,1+W7/7.5) -> 2.3333333 | X33: =IF(X7/7.5<1,2,1+X7/7.5) -> 2.3333333 | Y33: =IF(Y7/7.5<1,2,1+Y7/7.5) -> 2.3333333 | ... AC33: =IF(AC7/7.5<1,2,1+AC7/7.5) -> 2.3333333 | AE33: =IF(AE7/7.5<1,2,1+AE7/7.5) -> 2.3333333 | AF33: =IF(AF7/7.5<1,2,1+AF7/7.5) -> 2.3333333 | AG33: =IF(AG7/7.5<1,2,1+AG7/7.5) -> 2.3333333 | AH33: =IF(AH7/7.5<1,2,1+AH7/7.5) -> 2.3333333 | AI33: =IF(AI7/7.5<1,2,1+AI7/7.5) -> 2.3333333 | AJ33: =IF(AJ7/7.5<1,2,1+AJ7/7.5) -> 2.3333333 | AK33: =IF(AK7/7.5<1,2,1+AK7/7.5) -> 2.3333333 | AL33: =IF(AL7/7.5<1,2,1+AL7/7.5) -> 2.3333333 | ... AP33: =IF(AP7/7.5<1,2,1+AP7/7.5) -> 2.3333333 | AR33: =IF(AR7/7.5<1,2,1+AR7/7.5) -> 2.3333333 | AS33: =IF(AS7/7.5<1,2,1+AS7/7.5) -> 2.3333333 | AT33: =IF(AT7/7.5<1,2,1+AT7/7.5) -> 2.3333333 | AU33: =IF(AU7/7.5<1,2,1+AU7/7.5) -> 2.3333333 | AV33: =IF(AV7/7.5<1,2,1+AV7/7.5) -> 2.3333333 | AW33: =IF(AW7/7.5<1,2,1+AW7/7.5) -> 2.3333333 | AX33: =IF(AX7/7.5<1,2,1+AX7/7.5) -> 2.3333333 | AY33: =IF(AY7/7.5<1,2,1+AY7/7.5) -> 2.3333333 | ... BC33: =IF(BC7/7.5<1,2,1+BC7/7.5) -> 2.3333333 | BE33: =IF(BE7/7.5<1,2,1+BE7/7.5) -> 2.3333333 | BF33: =IF(BF7/7.5<1,2,1+BF7/7.5) -> 2.3333333 | BG33: =IF(BG7/7.5<1,2,1+BG7/7.5) -> 2.3333333 | BH33: =IF(BH7/7.5<1,2,1+BH7/7.5) -> 2.3333333 | BI33: =IF(BI7/7.5<1,2,1+BI7/7.5) -> 2.3333333 | BJ33: =IF(BJ7/7.5<1,2,1+BJ7/7.5) -> 2.3333333 | BK33: =IF(BK7/7.5<1,2,1+BK7/7.5) -> 2.3333333 | BL33: =IF(BL7/7.5<1,2,1+BL7/7.5) -> 2.3333333 | ... BP33: =IF(BP7/7.5<1,2,1+BP7/7.5) -> 2.3333333
A34: 移行人員配置 | E34: =ROUNDUP(E9/6,0) -> 1 | F34: =(F9+F10)/6 -> 0.83333333 | G34: =(G9+G10)/6 -> 0.83333333 | H34: =(H9+H10)/6 -> 1 | I34: =(I9+I10)/6 -> 1 | J34: =(J9+J10)/6 -> 0.66666667 | K34: =(K9+K10)/6 -> 0.83333333 | L34: =(L9+L10)/6 -> 1 | M34: =(M9+M10)/6 -> 1.3333333 | ... P34: =(P9+P10)/6 -> 2.8333333 | R34: =ROUNDUP(R9/6,1) -> 1.7 | S34: =(S9+S10)/6 -> 3.3333333 | T34: =(T9+T10)/6 -> 3.3333333 | U34: =(U9+U10)/6 -> 3.3333333 | V34: =(V9+V10)/6 -> 3.3333333 | W34: =(W9+W10)/6 -> 3.3333333 | X34: =(X9+X10)/6 -> 3.3333333 | Y34: =(Y9+Y10)/6 -> 3.3333333 | Z34: =(Z9+Z10)/6 -> 3.3333333 | ... AC34: =(AC9+AC10)/6 -> 3.3333333 | AE34: =ROUNDUP(AE9/6,1) -> 1.7 | AF34: =(AF9+AF10)/6 -> 3.3333333 | AG34: =(AG9+AG10)/6 -> 3.3333333 | AH34: =(AH9+AH10)/6 -> 3.3333333 | AI34: =(AI9+AI10)/6 -> 3.3333333 | AJ34: =(AJ9+AJ10)/6 -> 3.3333333 | AK34: =(AK9+AK10)/6 -> 3.3333333 | AL34: =(AL9+AL10)/6 -> 3.3333333 | AM34: =(AM9+AM10)/6 -> 3.3333333 | ... AP34: =(AP9+AP10)/6 -> 3.3333333 | AR34: =ROUNDUP(AR9/6,1) -> 1.7 | AS34: =(AS9+AS10)/6 -> 3.3333333 | AT34: =(AT9+AT10)/6 -> 3.3333333 | AU34: =(AU9+AU10)/6 -> 3.3333333 | AV34: =(AV9+AV10)/6 -> 3.3333333 | AW34: =(AW9+AW10)/6 -> 3.3333333 | AX34: =(AX9+AX10)/6 -> 3.3333333 | AY34: =(AY9+AY10)/6 -> 3.3333333 | AZ34: =(AZ9+AZ10)/6 -> 3.3333333 | ... BC34: =(BC9+BC10)/6 -> 3.3333333 | BE34: =ROUNDUP(BE9/6,1) -> 1.7 | BF34: =(BF9+BF10)/6 -> 3.3333333 | BG34: =(BG9+BG10)/6 -> 3.3333333 | BH34: =(BH9+BH10)/6 -> 3.3333333 | BI34: =(BI9+BI10)/6 -> 3.3333333 | BJ34: =(BJ9+BJ10)/6 -> 3.3333333 | BK34: =(BK9+BK10)/6 -> 3.3333333 | BL34: =(BL9+BL10)/6 -> 3.3333333 | BM34: =(BM9+BM10)/6 -> 3.3333333 | ... BP34: =(BP9+BP10)/6 -> 3.3333333
A35: 移行就労支援員配置 | E35: =IF((E9+E10)/15<1,1,(E9+E10)/15) -> 1 | F35: =IF((F9+F10)/15<1,1,(F9+F10)/15) -> 1 | G35: =IF((G9+G10)/15<1,1,(G9+G10)/15) -> 1 | H35: =IF((H9+H10)/15<1,1,(H9+H10)/15) -> 1 | I35: =IF((I9+I10)/15<1,1,(I9+I10)/15) -> 1 | J35: =IF((J9+J10)/15<1,1,(J9+J10)/15) -> 1 | K35: =IF((K9+K10)/15<1,1,(K9+K10)/15) -> 1 | L35: =IF((L9+L10)/15<1,1,(L9+L10)/15) -> 1 | ... P35: =IF((P9+P10)/15<1,1,(P9+P10)/15) -> 1.1333333 | R35: =IF((R9+R10)/15<1,1,(R9+R10)/15) -> 1.3333333 | S35: =IF((S9+S10)/15<1,1,(S9+S10)/15) -> 1.3333333 | T35: =IF((T9+T10)/15<1,1,(T9+T10)/15) -> 1.3333333 | U35: =IF((U9+U10)/15<1,1,(U9+U10)/15) -> 1.3333333 | V35: =IF((V9+V10)/15<1,1,(V9+V10)/15) -> 1.3333333 | W35: =IF((W9+W10)/15<1,1,(W9+W10)/15) -> 1.3333333 | X35: =IF((X9+X10)/15<1,1,(X9+X10)/15) -> 1.3333333 | Y35: =IF((Y9+Y10)/15<1,1,(Y9+Y10)/15) -> 1.3333333 | ... AC35: =IF((AC9+AC10)/15<1,1,(AC9+AC10)/15) -> 1.3333333 | AE35: =IF((AE9+AE10)/15<1,1,(AE9+AE10)/15) -> 1.3333333 | AF35: =IF((AF9+AF10)/15<1,1,(AF9+AF10)/15) -> 1.3333333 | AG35: =IF((AG9+AG10)/15<1,1,(AG9+AG10)/15) -> 1.3333333 | AH35: =IF((AH9+AH10)/15<1,1,(AH9+AH10)/15) -> 1.3333333 | AI35: =IF((AI9+AI10)/15<1,1,(AI9+AI10)/15) -> 1.3333333 | AJ35: =IF((AJ9+AJ10)/15<1,1,(AJ9+AJ10)/15) -> 1.3333333 | AK35: =IF((AK9+AK10)/15<1,1,(AK9+AK10)/15) -> 1.3333333 | AL35: =IF((AL9+AL10)/15<1,1,(AL9+AL10)/15) -> 1.3333333 | ... AP35: =IF((AP9+AP10)/15<1,1,(AP9+AP10)/15) -> 1.3333333 | AR35: =IF((AR9+AR10)/15<1,1,(AR9+AR10)/15) -> 1.3333333 | AS35: =IF((AS9+AS10)/15<1,1,(AS9+AS10)/15) -> 1.3333333 | AT35: =IF((AT9+AT10)/15<1,1,(AT9+AT10)/15) -> 1.3333333 | AU35: =IF((AU9+AU10)/15<1,1,(AU9+AU10)/15) -> 1.3333333 | AV35: =IF((AV9+AV10)/15<1,1,(AV9+AV10)/15) -> 1.3333333 | AW35: =IF((AW9+AW10)/15<1,1,(AW9+AW10)/15) -> 1.3333333 | AX35: =IF((AX9+AX10)/15<1,1,(AX9+AX10)/15) -> 1.3333333 | AY35: =IF((AY9+AY10)/15<1,1,(AY9+AY10)/15) -> 1.3333333 | ... BC35: =IF((BC9+BC10)/15<1,1,(BC9+BC10)/15) -> 1.3333333 | BE35: =IF((BE9+BE10)/15<1,1,(BE9+BE10)/15) -> 1.3333333 | BF35: =IF((BF9+BF10)/15<1,1,(BF9+BF10)/15) -> 1.3333333 | BG35: =IF((BG9+BG10)/15<1,1,(BG9+BG10)/15) -> 1.3333333 | BH35: =IF((BH9+BH10)/15<1,1,(BH9+BH10)/15) -> 1.3333333 | BI35: =IF((BI9+BI10)/15<1,1,(BI9+BI10)/15) -> 1.3333333 | BJ35: =IF((BJ9+BJ10)/15<1,1,(BJ9+BJ10)/15) -> 1.3333333 | BK35: =IF((BK9+BK10)/15<1,1,(BK9+BK10)/15) -> 1.3333333 | BL35: =IF((BL9+BL10)/15<1,1,(BL9+BL10)/15) -> 1.3333333 | ... BP35: =IF((BP9+BP10)/15<1,1,(BP9+BP10)/15) -> 1.3333333
A36: 移行施設外支援配置 | E36: =IF(E10/6<1,1,E10/6) -> 1 | F36: =IF(F10/6<1,1,F10/6) -> 1 | G36: =IF(G10/6<1,1,G10/6) -> 1 | H36: =IF(H10/6<1,1,H10/6) -> 1 | I36: =IF(I10/6<1,1,I10/6) -> 1 | J36: =IF(J10/6<1,1,J10/6) -> 1 | K36: =IF(K10/6<1,1,K10/6) -> 1 | L36: =IF(L10/6<1,1,L10/6) -> 1 | ... P36: =IF(P10/6<1,1,P10/6) -> 1.3333333 | R36: =IF(R10/6<1,1,R10/6) -> 1.6666667 | S36: =IF(S10/6<1,1,S10/6) -> 1.6666667 | T36: =IF(T10/6<1,1,T10/6) -> 1.6666667 | U36: =IF(U10/6<1,1,U10/6) -> 1.6666667 | V36: =IF(V10/6<1,1,V10/6) -> 1.6666667 | W36: =IF(W10/6<1,1,W10/6) -> 1.6666667 | X36: =IF(X10/6<1,1,X10/6) -> 1.6666667 | Y36: =IF(Y10/6<1,1,Y10/6) -> 1.6666667 | ... AC36: =IF(AC10/6<1,1,AC10/6) -> 1.6666667 | AE36: =IF(AE10/6<1,1,AE10/6) -> 1.6666667 | AF36: =IF(AF10/6<1,1,AF10/6) -> 1.6666667 | AG36: =IF(AG10/6<1,1,AG10/6) -> 1.6666667 | AH36: =IF(AH10/6<1,1,AH10/6) -> 1.6666667 | AI36: =IF(AI10/6<1,1,AI10/6) -> 1.6666667 | AJ36: =IF(AJ10/6<1,1,AJ10/6) -> 1.6666667 | AK36: =IF(AK10/6<1,1,AK10/6) -> 1.6666667 | AL36: =IF(AL10/6<1,1,AL10/6) -> 1.6666667 | ... AP36: =IF(AP10/6<1,1,AP10/6) -> 1.6666667 | AR36: =IF(AR10/6<1,1,AR10/6) -> 1.6666667 | AS36: =IF(AS10/6<1,1,AS10/6) -> 1.6666667 | AT36: =IF(AT10/6<1,1,AT10/6) -> 1.6666667 | AU36: =IF(AU10/6<1,1,AU10/6) -> 1.6666667 | AV36: =IF(AV10/6<1,1,AV10/6) -> 1.6666667 | AW36: =IF(AW10/6<1,1,AW10/6) -> 1.6666667 | AX36: =IF(AX10/6<1,1,AX10/6) -> 1.6666667 | AY36: =IF(AY10/6<1,1,AY10/6) -> 1.6666667 | ... BC36: =IF(BC10/6<1,1,BC10/6) -> 1.6666667 | BE36: =IF(BE10/6<1,1,BE10/6) -> 1.6666667 | BF36: =IF(BF10/6<1,1,BF10/6) -> 1.6666667 | BG36: =IF(BG10/6<1,1,BG10/6) -> 1.6666667 | BH36: =IF(BH10/6<1,1,BH10/6) -> 1.6666667 | BI36: =IF(BI10/6<1,1,BI10/6) -> 1.6666667 | BJ36: =IF(BJ10/6<1,1,BJ10/6) -> 1.6666667 | BK36: =IF(BK10/6<1,1,BK10/6) -> 1.6666667 | BL36: =IF(BL10/6<1,1,BL10/6) -> 1.6666667 | ... BP36: =IF(BP10/6<1,1,BP10/6) -> 1.6666667
A38: 管理者 | E38: 130000 | F38: 130000 | G38: 130000 | H38: 130000 | I38: 130000 | J38: 130000 | K38: 130000 | L38: 250000 | M38: 250000 | N38: 250000 | O38: 250000 | P38: 250000 | R38: 250000 | S38: 250000 | T38: 250000 | U38: 250000 | V38: 250000 | W38: 250000 | X38: 250000 | Y38: 250000 | Z38: 250000 | AA38: 250000 | AB38: 250000 | AC38: 250000 | AE38: 250000 | AF38: 250000 | AG38: 250000 | AH38: 250000 | AI38: 250000 | AJ38: 250000 | AK38: 250000 | AL38: 250000 | AM38: 250000 | AN38: 250000 | AO38: 250000 | AP38: 250000 | AR38: 180000 | AS38: 180000 | AT38: 180000 | AU38: 180000 | AV38: 180000 | AW38: 180000 | AX38: 180000 | AY38: 180000 | AZ38: 180000 | BA38: 180000 | BB38: 180000 | BC38: 180000 | BE38: 180000 | BF38: 180000 | BG38: 180000 | BH38: 180000 | BI38: 180000 | BJ38: 180000 | BK38: 180000 | BL38: 180000 | BM38: 180000 | BN38: 180000 | BO38: 180000 | BP38: 180000
A39: サービス管理責任者
A40: B生活支援員等 | E40: 120000 | F40: 120000 | G40: 120000 | H40: 120000 | I40: 120000 | J40: 120000 | K40: 120000 | L40: 120000 | M40: 120000 | N40: 120000 | O40: 120000 | P40: 120000 | R40: 150000 | S40: 150000 | T40: 150000 | U40: 150000 | V40: 150000 | W40: 150000 | X40: 150000 | Y40: 150000 | Z40: 150000 | AA40: 150000 | AB40: 150000 | AC40: 150000 | AE40: 150000 | AF40: 150000 | AG40: 150000 | AH40: 150000 | AI40: 150000 | AJ40: 150000 | AK40: 150000 | AL40: 150000 | AM40: 150000 | AN40: 150000 | AO40: 150000 | AP40: 150000 | AR40: 150000 | AS40: 150000 | AT40: 150000 | AU40: 150000 | AV40: 150000 | AW40: 150000 | AX40: 150000 | AY40: 150000 | AZ40: 150000 | BA40: 150000 | BB40: 150000 | BC40: 150000 | BE40: 150000 | BF40: 150000 | BG40: 150000 | BH40: 150000 | BI40: 150000 | BJ40: 150000 | BK40: 150000 | BL40: 150000 | BM40: 150000 | BN40: 150000 | BO40: 150000 | BP40: 150000
A41: B生活支援員等 | E41: 180000 | F41: 180000 | G41: 180000 | H41: 180000 | I41: 180000 | J41: 180000 | K41: 180000 | L41: 180000 | M41: 180000 | N41: 180000 | O41: 180000 | P41: 180000 | R41: 180000 | S41: 180000 | T41: 180000 | U41: 180000 | V41: 180000 | W41: 180000 | X41: 180000 | Y41: 180000 | Z41: 180000 | AA41: 180000 | AB41: 180000 | AC41: 180000 | AE41: 180000 | AF41: 180000 | AG41: 180000 | AH41: 180000 | AI41: 180000 | AJ41: 180000 | AK41: 180000 | AL41: 180000 | AM41: 180000 | AN41: 180000 | AO41: 180000 | AP41: 180000 | AR41: 180000 | AS41: 180000 | AT41: 180000 | AU41: 180000 | AV41: 180000 | AW41: 180000 | AX41: 180000 | AY41: 180000 | AZ41: 180000 | BA41: 180000 | BB41: 180000 | BC41: 180000 | BE41: 180000 | BF41: 180000 | BG41: 180000 | BH41: 180000 | BI41: 180000 | BJ41: 180000 | BK41: 180000 | BL41: 180000 | BM41: 180000 | BN41: 180000 | BO41: 180000 | BP41: 180000
A42: B生活支援員等 | E42: 120000 | F42: 120000 | G42: 120000 | H42: 120000 | I42: 120000 | L42: 120000 | M42: 120000 | N42: 120000 | O42: 120000 | P42: 120000 | R42: 180000 | S42: 180000 | T42: 180000 | U42: 180000 | V42: 180000 | W42: 180000 | X42: 180000 | Y42: 180000 | Z42: 180000 | AA42: 180000 | AB42: 180000 | AC42: 180000 | AE42: 180000 | AF42: 180000 | AG42: 180000 | AH42: 180000 | AI42: 180000 | AJ42: 180000 | AK42: 180000 | AL42: 180000 | AM42: 180000 | AN42: 180000 | AO42: 180000 | AP42: 180000 | AR42: 180000 | AS42: 180000 | AT42: 180000 | AU42: 180000 | AV42: 180000 | AW42: 180000 | AX42: 180000 | AY42: 180000 | AZ42: 180000 | BA42: 180000 | BB42: 180000 | BC42: 180000 | BE42: 180000 | BF42: 180000 | BG42: 180000 | BH42: 180000 | BI42: 180000 | BJ42: 180000 | BK42: 180000 | BL42: 180000 | BM42: 180000 | BN42: 180000 | BO42: 180000 | BP42: 180000
A43: 目標工賃達成指導員 | E43: 180000 | F43: 180000 | G43: 180000 | H43: 180000 | I43: 180000 | J43: 180000 | K43: 180000 | L43: 180000 | M43: 180000 | N43: 180000 | O43: 180000 | P43: 180000 | R43: 180000 | S43: 180000 | T43: 180000 | U43: 180000 | V43: 180000 | W43: 180000 | X43: 180000 | Y43: 180000 | Z43: 180000 | AA43: 180000 | AB43: 180000 | AC43: 180000 | AE43: 180000 | AF43: 180000 | AG43: 180000 | AH43: 180000 | AI43: 180000 | AJ43: 180000 | AK43: 180000 | AL43: 180000 | AM43: 180000 | AN43: 180000 | AO43: 180000 | AP43: 180000 | AR43: 180000 | AS43: 180000 | AT43: 180000 | AU43: 180000 | AV43: 180000 | AW43: 180000 | AX43: 180000 | AY43: 180000 | AZ43: 180000 | BA43: 180000 | BB43: 180000 | BC43: 180000 | BE43: 180000 | BF43: 180000 | BG43: 180000 | BH43: 180000 | BI43: 180000 | BJ43: 180000 | BK43: 180000 | BL43: 180000 | BM43: 180000 | BN43: 180000 | BO43: 180000 | BP43: 180000
A44: B施設外支援員 | E44: 120000 | F44: 120000 | G44: 120000 | H44: 120000 | I44: 120000 | J44: 120000 | K44: 120000 | L44: 120000 | M44: 120000 | N44: 120000 | O44: 120000 | P44: 120000 | R44: 150000 | S44: 150000 | T44: 150000 | U44: 150000 | V44: 150000 | W44: 150000 | X44: 150000 | Y44: 150000 | Z44: 150000 | AA44: 150000 | AB44: 150000 | AC44: 150000 | AE44: 150000 | AF44: 150000 | AG44: 150000 | AH44: 150000 | AI44: 150000 | AJ44: 150000 | AK44: 150000 | AL44: 150000 | AM44: 150000 | AN44: 150000 | AO44: 150000 | AP44: 150000 | AR44: 150000 | AS44: 150000 | AT44: 150000 | AU44: 150000 | AV44: 150000 | AW44: 150000 | AX44: 150000 | AY44: 150000 | AZ44: 150000 | BA44: 150000 | BB44: 150000 | BC44: 150000 | BE44: 150000 | BF44: 150000 | BG44: 150000 | BH44: 150000 | BI44: 150000 | BJ44: 150000 | BK44: 150000 | BL44: 150000 | BM44: 150000 | BN44: 150000 | BO44: 150000 | BP44: 150000
A45: B施設外支援員 | E45: 280000 | F45: 280000 | G45: 280000 | H45: 280000 | I45: 280000 | L45: 280000 | M45: 280000 | N45: 280000 | O45: 280000 | P45: 280000 | R45: 300000 | S45: 300000 | T45: 300000 | U45: 300000 | V45: 300000 | W45: 300000 | X45: 300000 | Y45: 300000 | Z45: 300000 | AA45: 300000 | AB45: 300000 | AC45: 250000 | AE45: 250000 | AF45: 250000 | AG45: 250000 | AH45: 250000 | AI45: 250000 | AJ45: 250000 | AK45: 250000 | AL45: 250000 | AM45: 250000 | AN45: 250000 | AO45: 250000 | AP45: 250000 | AR45: 250000 | AS45: 250000 | AT45: 250000 | AU45: 250000 | AV45: 250000 | AW45: 250000 | AX45: 250000 | AY45: 250000 | AZ45: 250000 | BA45: 250000 | BB45: 250000 | BC45: 250000 | BE45: 250000 | BF45: 250000 | BG45: 250000 | BH45: 250000 | BI45: 250000 | BJ45: 250000 | BK45: 250000 | BL45: 250000 | BM45: 250000 | BN45: 250000 | BO45: 250000 | BP45: 250000
A46: 移行生活支援員等 | E46: 180000 | F46: 180000 | G46: 180000 | H46: 180000 | I46: 180000 | J46: 180000 | K46: 180000 | L46: 180000 | M46: 180000 | N46: 180000 | O46: 180000 | P46: 180000 | R46: 180000 | S46: 180000 | T46: 180000 | U46: 180000 | V46: 180000 | W46: 180000 | X46: 180000 | Y46: 180000 | Z46: 180000 | AA46: 180000 | AB46: 180000 | AC46: 180000 | AE46: 180000 | AF46: 180000 | AG46: 180000 | AH46: 180000 | AI46: 180000 | AJ46: 180000 | AK46: 180000 | AL46: 180000 | AM46: 180000 | AN46: 180000 | AO46: 180000 | AP46: 180000 | AR46: 180000 | AS46: 180000 | AT46: 180000 | AU46: 180000 | AV46: 180000 | AW46: 180000 | AX46: 180000 | AY46: 180000 | AZ46: 180000 | BA46: 180000 | BB46: 180000 | BC46: 180000 | BE46: 180000 | BF46: 180000 | BG46: 180000 | BH46: 180000 | BI46: 180000 | BJ46: 180000 | BK46: 180000 | BL46: 180000 | BM46: 180000 | BN46: 180000 | BO46: 180000 | BP46: 180000
A47: 移行生活支援員等 | E47: 180000 | F47: 180000 | G47: 180000 | H47: 180000 | I47: 180000 | J47: 180000 | K47: 180000 | L47: 180000 | M47: 180000 | N47: 180000 | O47: 180000 | P47: 180000 | R47: 180000 | S47: 180000 | T47: 180000 | U47: 180000 | V47: 180000 | W47: 180000 | X47: 180000 | Y47: 180000 | Z47: 180000 | AA47: 180000 | AB47: 180000 | AC47: 180000 | AE47: 180000 | AF47: 180000 | AG47: 180000 | AH47: 180000 | AI47: 180000 | AJ47: 180000 | AK47: 180000 | AL47: 180000 | AM47: 180000 | AN47: 180000 | AO47: 180000 | AP47: 180000 | AR47: 180000 | AS47: 180000 | AT47: 180000 | AU47: 180000 | AV47: 180000 | AW47: 180000 | AX47: 180000 | AY47: 180000 | AZ47: 180000 | BA47: 180000 | BB47: 180000 | BC47: 180000 | BE47: 180000 | BF47: 180000 | BG47: 180000 | BH47: 180000 | BI47: 180000 | BJ47: 180000 | BK47: 180000 | BL47: 180000 | BM47: 180000 | BN47: 180000 | BO47: 180000 | BP47: 180000
A48: 移行生活支援員等 | E48: 180000 | F48: 180000 | G48: 180000 | H48: 180000 | I48: 180000 | L48: 180000 | M48: 180000 | N48: 180000 | O48: 180000 | P48: 180000 | R48: 250000 | S48: 250000 | T48: 250000 | U48: 250000 | V48: 250000 | W48: 250000 | X48: 250000 | Y48: 250000 | Z48: 250000 | AA48: 250000 | AB48: 250000 | AC48: 250000 | AE48: 250000 | AF48: 250000 | AG48: 250000 | AH48: 250000 | AI48: 250000 | AJ48: 250000 | AK48: 250000 | AL48: 250000 | AM48: 250000 | AN48: 250000 | AO48: 250000 | AP48: 250000 | AR48: 250000 | AS48: 250000 | AT48: 250000 | AU48: 250000 | AV48: 250000 | AW48: 250000 | AX48: 250000 | AY48: 250000 | AZ48: 250000 | BA48: 250000 | BB48: 250000 | BC48: 250000 | BE48: 250000 | BF48: 250000 | BG48: 250000 | BH48: 250000 | BI48: 250000 | BJ48: 250000 | BK48: 250000 | BL48: 250000 | BM48: 250000 | BN48: 250000 | BO48: 250000 | BP48: 250000
A49: 施設外支援員 | E49: 250000 | F49: 250000 | G49: 250000 | H49: 250000 | I49: 250000 | J49: 150000 | K49: 150000 | L49: 250000 | M49: 250000 | N49: 250000 | O49: 250000 | P49: 250000 | R49: 300000 | S49: 300000 | T49: 300000 | U49: 300000 | V49: 300000 | W49: 300000 | X49: 300000 | Y49: 300000 | Z49: 300000 | AA49: 300000 | AB49: 300000 | AC49: 300000 | AE49: 300000 | AF49: 300000 | AG49: 300000 | AH49: 300000 | AI49: 300000 | AJ49: 300000 | AK49: 300000 | AL49: 300000 | AM49: 300000 | AN49: 300000 | AO49: 300000 | AP49: 300000 | AR49: 300000 | AS49: 300000 | AT49: 300000 | AU49: 300000 | AV49: 300000 | AW49: 300000 | AX49: 300000 | AY49: 300000 | AZ49: 300000 | BA49: 300000 | BB49: 300000 | BC49: 300000 | BE49: 300000 | BF49: 300000 | BG49: 300000 | BH49: 300000 | BI49: 300000 | BJ49: 300000 | BK49: 300000 | BL49: 300000 | BM49: 300000 | BN49: 300000 | BO49: 300000 | BP49: 300000
A50: 施設外支援員 | I50: 250000 | L50: 250000 | M50: 250000 | N50: 250000 | O50: 250000 | P50: 250000 | R50: 300000 | S50: 300000 | T50: 300000 | U50: 300000 | V50: 300000 | W50: 300000 | X50: 300000 | Y50: 300000 | Z50: 300000 | AA50: 300000 | AB50: 300000 | AC50: 300000 | AE50: 300000 | AF50: 300000 | AG50: 300000 | AH50: 300000 | AI50: 300000 | AJ50: 300000 | AK50: 300000 | AL50: 300000 | AM50: 300000 | AN50: 300000 | AO50: 300000 | AP50: 300000 | AR50: 300000 | AS50: 300000 | AT50: 300000 | AU50: 300000 | AV50: 300000 | AW50: 300000 | AX50: 300000 | AY50: 300000 | AZ50: 300000 | BA50: 300000 | BB50: 300000 | BC50: 300000 | BE50: 300000 | BF50: 300000 | BG50: 300000 | BH50: 300000 | BI50: 300000 | BJ50: 300000 | BK50: 300000 | BL50: 300000 | BM50: 300000 | BN50: 300000 | BO50: 300000 | BP50: 300000
A51: 就労支援員 | E51: 50000 | F51: 150000 | G51: 150000 | H51: 150000 | I51: 150000 | L51: 250000 | M51: 250000 | N51: 250000 | O51: 250000 | P51: 150000 | R51: 250000 | S51: 250000 | T51: 250000 | U51: 250000 | V51: 250000 | W51: 250000 | X51: 250000 | Y51: 250000 | Z51: 250000 | AA51: 250000 | AB51: 250000 | AC51: 250000 | AE51: 250000 | AF51: 250000 | AG51: 250000 | AH51: 250000 | AI51: 250000 | AJ51: 250000 | AK51: 250000 | AL51: 250000 | AM51: 250000 | AN51: 250000 | AO51: 250000 | AP51: 250000 | AR51: 250000 | AS51: 250000 | AT51: 250000 | AU51: 250000 | AV51: 250000 | AW51: 250000 | AX51: 250000 | AY51: 250000 | AZ51: 250000 | BA51: 250000 | BB51: 250000 | BC51: 250000 | BE51: 250000 | BF51: 250000 | BG51: 250000 | BH51: 250000 | BI51: 250000 | BJ51: 250000 | BK51: 250000 | BL51: 250000 | BM51: 250000 | BN51: 250000 | BO51: 250000 | BP51: 250000
A52: 就労支援員 | E52: 180000 | F52: 180000 | G52: 180000 | H52: 180000 | I52: 180000 | J52: 180000 | K52: 180000 | L52: 180000 | M52: 180000 | N52: 180000 | O52: 180000 | P52: 180000 | R52: 180000 | S52: 180000 | T52: 180000 | U52: 180000 | V52: 180000 | W52: 180000 | X52: 180000 | Y52: 180000 | Z52: 180000 | AA52: 180000 | AB52: 180000 | AC52: 180000 | AE52: 180000 | AF52: 180000 | AG52: 180000 | AH52: 180000 | AI52: 180000 | AJ52: 180000 | AK52: 180000 | AL52: 180000 | AM52: 180000 | AN52: 180000 | AO52: 180000 | AP52: 180000 | AR52: 180000 | AS52: 180000 | AT52: 180000 | AU52: 180000 | AV52: 180000 | AW52: 180000 | AX52: 180000 | AY52: 180000 | AZ52: 180000 | BA52: 180000 | BB52: 180000 | BC52: 180000 | BE52: 180000 | BF52: 180000 | BG52: 180000 | BH52: 180000 | BI52: 180000 | BJ52: 180000 | BK52: 180000 | BL52: 180000 | BM52: 180000 | BN52: 180000 | BO52: 180000 | BP52: 180000
A53: 賞与 | J53: 1000000 | P53: 2000000 | W53: 2000000 | AC53: 3000000 | AJ53: 2000000 | AP53: 3000000 | AW53: 2000000 | BC53: 3000000 | BJ53: 2000000 | BP53: 3000000
A54: 人件費合計 | E54: =SUM(E38:E52) -> 2150000 | F54: =SUM(F38:F52) -> 2250000 | G54: =SUM(G38:G52) -> 2250000 | H54: =SUM(H38:H52) -> 2250000 | I54: =SUM(I38:I52) -> 2500000 | J54: =SUM(J38:J52) -> 1420000 | K54: =SUM(K38:K52) -> 1420000 | L54: =SUM(L38:L52) -> 2720000 | ... P54: =SUM(P38:P52) -> 2620000 | R54: =SUM(R38:R52) -> 3030000 | S54: =SUM(S38:S52) -> 3030000 | T54: =SUM(T38:T52) -> 3030000 | U54: =SUM(U38:U52) -> 3030000 | V54: =SUM(V38:V52) -> 3030000 | W54: =SUM(W38:W52) -> 3030000 | X54: =SUM(X38:X52) -> 3030000 | Y54: =SUM(Y38:Y52) -> 3030000 | ... AC54: =SUM(AC38:AC52) -> 2980000 | AE54: =SUM(AE38:AE52) -> 2980000 | AF54: =SUM(AF38:AF52) -> 2980000 | AG54: =SUM(AG38:AG52) -> 2980000 | AH54: =SUM(AH38:AH52) -> 2980000 | AI54: =SUM(AI38:AI52) -> 2980000 | AJ54: =SUM(AJ38:AJ52) -> 2980000 | AK54: =SUM(AK38:AK52) -> 2980000 | AL54: =SUM(AL38:AL52) -> 2980000 | ... AP54: =SUM(AP38:AP52) -> 2980000 | AR54: =SUM(AR38:AR52) -> 2910000 | AS54: =SUM(AS38:AS52) -> 2910000 | AT54: =SUM(AT38:AT52) -> 2910000 | AU54: =SUM(AU38:AU52) -> 2910000 | AV54: =SUM(AV38:AV52) -> 2910000 | AW54: =SUM(AW38:AW52) -> 2910000 | AX54: =SUM(AX38:AX52) -> 2910000 | AY54: =SUM(AY38:AY52) -> 2910000 | ... BC54: =SUM(BC38:BC52) -> 2910000 | BE54: =SUM(BE38:BE52) -> 2910000 | BF54: =SUM(BF38:BF52) -> 2910000 | BG54: =SUM(BG38:BG52) -> 2910000 | BH54: =SUM(BH38:BH52) -> 2910000 | BI54: =SUM(BI38:BI52) -> 2910000 | BJ54: =SUM(BJ38:BJ52) -> 2910000 | BK54: =SUM(BK38:BK52) -> 2910000 | BL54: =SUM(BL38:BL52) -> 2910000 | ... BP54: =SUM(BP38:BP52) -> 2910000
A55: 社会保険 | E55: =E54*0.1 -> 215000 | F55: =F54*0.1 -> 225000 | G55: =G54*0.1 -> 225000 | H55: =H54*0.1 -> 225000 | I55: =I54*0.1 -> 250000 | J55: =J54*0.1 -> 142000 | K55: =K54*0.1 -> 142000 | L55: =L54*0.1 -> 272000 | ... P55: =P54*0.1 -> 262000 | R55: =R54*0.1 -> 303000 | S55: =S54*0.1 -> 303000 | T55: =T54*0.1 -> 303000 | U55: =U54*0.1 -> 303000 | V55: =V54*0.1 -> 303000 | W55: =W54*0.1 -> 303000 | X55: =X54*0.1 -> 303000 | Y55: =Y54*0.1 -> 303000 | ... AC55: =AC54*0.1 -> 298000 | AE55: =AE54*0.1 -> 298000 | AF55: =AF54*0.1 -> 298000 | AG55: =AG54*0.1 -> 298000 | AH55: =AH54*0.1 -> 298000 | AI55: =AI54*0.1 -> 298000 | AJ55: =AJ54*0.1 -> 298000 | AK55: =AK54*0.1 -> 298000 | AL55: =AL54*0.1 -> 298000 | ... AP55: =AP54*0.1 -> 298000 | AR55: =AR54*0.1 -> 291000 | AS55: =AS54*0.1 -> 291000 | AT55: =AT54*0.1 -> 291000 | AU55: =AU54*0.1 -> 291000 | AV55: =AV54*0.1 -> 291000 | AW55: =AW54*0.1 -> 291000 | AX55: =AX54*0.1 -> 291000 | AY55: =AY54*0.1 -> 291000 | ... BC55: =BC54*0.1 -> 291000 | BE55: =BE54*0.1 -> 291000 | BF55: =BF54*0.1 -> 291000 | BG55: =BG54*0.1 -> 291000 | BH55: =BH54*0.1 -> 291000 | BI55: =BI54*0.1 -> 291000 | BJ55: =BJ54*0.1 -> 291000 | BK55: =BK54*0.1 -> 291000 | BL55: =BL54*0.1 -> 291000 | ... BP55: =BP54*0.1 -> 291000
A56: 人件費総計 | E56: =E54+E55 -> 2365000 | F56: =F54+F55 -> 2475000 | G56: =G54+G55 -> 2475000 | H56: =H54+H55 -> 2475000 | I56: =I54+I55 -> 2750000 | J56: =J54+J55 -> 1562000 | K56: =K54+K55 -> 1562000 | L56: =L54+L55 -> 2992000 | ... P56: =P54+P55 -> 2882000 | R56: =R54+R55 -> 3333000 | S56: =S54+S55 -> 3333000 | T56: =T54+T55 -> 3333000 | U56: =U54+U55 -> 3333000 | V56: =V54+V55 -> 3333000 | W56: =W54+W55 -> 3333000 | X56: =X54+X55 -> 3333000 | Y56: =Y54+Y55 -> 3333000 | ... AC56: =AC54+AC55 -> 3278000 | AE56: =AE54+AE55 -> 3278000 | AF56: =AF54+AF55 -> 3278000 | AG56: =AG54+AG55 -> 3278000 | AH56: =AH54+AH55 -> 3278000 | AI56: =AI54+AI55 -> 3278000 | AJ56: =AJ54+AJ55 -> 3278000 | AK56: =AK54+AK55 -> 3278000 | AL56: =AL54+AL55 -> 3278000 | ... AP56: =AP54+AP55 -> 3278000 | AR56: =AR54+AR55 -> 3201000 | AS56: =AS54+AS55 -> 3201000 | AT56: =AT54+AT55 -> 3201000 | AU56: =AU54+AU55 -> 3201000 | AV56: =AV54+AV55 -> 3201000 | AW56: =AW54+AW55 -> 3201000 | AX56: =AX54+AX55 -> 3201000 | AY56: =AY54+AY55 -> 3201000 | ... BC56: =BC54+BC55 -> 3201000 | BE56: =BE54+BE55 -> 3201000 | BF56: =BF54+BF55 -> 3201000 | BG56: =BG54+BG55 -> 3201000 | BH56: =BH54+BH55 -> 3201000 | BI56: =BI54+BI55 -> 3201000 | BJ56: =BJ54+BJ55 -> 3201000 | BK56: =BK54+BK55 -> 3201000 | BL56: =BL54+BL55 -> 3201000 | ... BP56: =BP54+BP55 -> 3201000

Sheet ACT01
A1: ACT01
D2: 令和３年 | Q2: 令和4年 | R2: 令和４年 | T2: 30000 | AD2: 令和５年 | AE2: 令和４年 | AG2: 30000 | AQ2: 令和６年 | AR2: 令和４年 | AT2: 30000 | BD2: 令和７年 | BE2: 令和４年 | BG2: 30000
E3: 1月 | F3: 2月 | G3: 3月 | H3: 4月 | I3: 5月 | J3: 6月 | K3: 7月 | L3: 8月 | M3: 9月 | N3: 10月 | O3: 11月 | P3: 12月 | R3: 1月 | S3: 2月 | T3: 3月 | U3: 4月 | V3: 5月 | W3: 6月 | X3: 7月 | Y3: 8月 | Z3: 9月 | AA3: 10月 | AB3: 11月 | AC3: 12月 | AE3: 1月 | AF3: 2月 | AG3: 3月 | AH3: 4月 | AI3: 5月 | AJ3: 6月 | AK3: 7月 | AL3: 8月 | AM3: 9月 | AN3: 10月 | AO3: 11月 | AP3: 12月 | AR3: 1月 | AS3: 2月 | AT3: 3月 | AU3: 4月 | AV3: 5月 | AW3: 6月 | AX3: 7月 | AY3: 8月 | AZ3: 9月 | BA3: 10月 | BB3: 11月 | BC3: 12月 | BE3: 1月 | BF3: 2月 | BG3: 3月 | BH3: 4月 | BI3: 5月 | BJ3: 6月 | BK3: 7月 | BL3: 8月 | BM3: 9月 | BN3: 10月 | BO3: 11月 | BP3: 12月
A4: 稼働日 | E4: 22 | F4: 20 | G4: 23 | H4: 22 | I4: 23 | J4: 22 | K4: 23 | L4: 22 | M4: 22 | N4: 23 | O4: 22 | P4: 22 | R4: 22 | S4: 20 | T4: 23 | U4: 22 | V4: 23 | W4: 22 | X4: 23 | Y4: 22 | Z4: 22 | AA4: 23 | AB4: 22 | AC4: 22 | AE4: 22 | AF4: 20 | AG4: 23 | AH4: 22 | AI4: 23 | AJ4: 22 | AK4: 23 | AL4: 22 | AM4: 22 | AN4: 23 | AO4: 22 | AP4: 22 | AR4: 22 | AS4: 20 | AT4: 23 | AU4: 22 | AV4: 23 | AW4: 22 | AX4: 23 | AY4: 22 | AZ4: 22 | BA4: 23 | BB4: 22 | BC4: 22 | BE4: 22 | BF4: 20 | BG4: 23 | BH4: 22 | BI4: 23 | BJ4: 22 | BK4: 23 | BL4: 22 | BM4: 22 | BN4: 23 | BO4: 22 | BP4: 22
A5: 稼働率 | E5: 0.8 | F5: 0.8 | G5: 0.8 | H5: 0.8 | I5: 0.8 | J5: 0.8 | K5: 0.8 | L5: 0.8 | M5: 0.8 | N5: 0.8 | O5: 0.8 | P5: 0.8 | R5: 0.8 | S5: 0.8 | T5: 0.8 | U5: 0.8 | V5: 0.8 | W5: 0.8 | X5: 0.8 | Y5: 0.8 | Z5: 0.8 | AA5: 0.8 | AB5: 0.8 | AC5: 0.8 | AE5: 0.8 | AF5: 0.8 | AG5: 0.8 | AH5: 0.8 | AI5: 0.8 | AJ5: 0.8 | AK5: 0.8 | AL5: 0.8 | AM5: 0.8 | AN5: 0.8 | AO5: 0.8 | AP5: 0.8 | AR5: 0.8 | AS5: 0.8 | AT5: 0.8 | AU5: 0.8 | AV5: 0.8 | AW5: 0.8 | AX5: 0.8 | AY5: 0.8 | AZ5: 0.8 | BA5: 0.8 | BB5: 0.8 | BC5: 0.8 | BE5: 0.8 | BF5: 0.8 | BG5: 0.8 | BH5: 0.8 | BI5: 0.8 | BJ5: 0.8 | BK5: 0.8 | BL5: 0.8 | BM5: 0.8 | BN5: 0.8 | BO5: 0.8 | BP5: 0.8
A6: 就労B利用者数 | AR6: 10 | AS6: 10 | AT6: 10 | AU6: 10 | AV6: 10 | AW6: 10 | AX6: 10 | AY6: 10 | AZ6: 10 | BA6: 10 | BB6: 10 | BC6: 10 | BE6: 10 | BF6: 10 | BG6: 10 | BH6: 10 | BI6: 10 | BJ6: 10 | BK6: 10 | BL6: 10 | BM6: 10 | BN6: 10 | BO6: 10 | BP6: 10
A7: 就労B施設外利用者数 | AR7: 10 | AS7: 10 | AT7: 10 | AU7: 10 | AV7: 10 | AW7: 10 | AX7: 10 | AY7: 10 | AZ7: 10 | BA7: 10 | BB7: 10 | BC7: 10 | BE7: 10 | BF7: 10 | BG7: 10 | BH7: 10 | BI7: 10 | BJ7: 10 | BK7: 10 | BL7: 10 | BM7: 10 | BN7: 10 | BO7: 10 | BP7: 10
A8: B合計 | E8: =SUM(E6:E7) -> 0 | F8: =SUM(F6:F7) -> 0 | G8: =SUM(G6:G7) -> 0 | H8: =SUM(H6:H7) -> 0 | I8: =SUM(I6:I7) -> 0 | J8: =SUM(J6:J7) -> 0 | K8: =SUM(K6:K7) -> 0 | L8: =SUM(L6:L7) -> 0 | ... P8: =SUM(P6:P7) -> 0 | R8: =SUM(R6:R7) -> 0 | S8: =SUM(S6:S7) -> 0 | T8: =SUM(T6:T7) -> 0 | U8: =SUM(U6:U7) -> 0 | V8: =SUM(V6:V7) -> 0 | W8: =SUM(W6:W7) -> 0 | X8: =SUM(X6:X7) -> 0 | Y8: =SUM(Y6:Y7) -> 0 | ... AC8: =SUM(AC6:AC7) -> 0 | AE8: =SUM(AE6:AE7) -> 0 | AF8: =SUM(AF6:AF7) -> 0 | AG8: =SUM(AG6:AG7) -> 0 | AH8: =SUM(AH6:AH7) -> 0 | AI8: =SUM(AI6:AI7) -> 0 | AJ8: =SUM(AJ6:AJ7) -> 0 | AK8: =SUM(AK6:AK7) -> 0 | AL8: =SUM(AL6:AL7) -> 0 | ... AP8: =SUM(AP6:AP7) -> 0 | AR8: =SUM(AR6:AR7) -> 20 | AS8: =SUM(AS6:AS7) -> 20 | AT8: =SUM(AT6:AT7) -> 20 | AU8: =SUM(AU6:AU7) -> 20 | AV8: =SUM(AV6:AV7) -> 20 | AW8: =SUM(AW6:AW7) -> 20 | AX8: =SUM(AX6:AX7) -> 20 | AY8: =SUM(AY6:AY7) -> 20 | ... BC8: =SUM(BC6:BC7) -> 20 | BE8: =SUM(BE6:BE7) -> 20 | BF8: =SUM(BF6:BF7) -> 20 | BG8: =SUM(BG6:BG7) -> 20 | BH8: =SUM(BH6:BH7) -> 20 | BI8: =SUM(BI6:BI7) -> 20 | BJ8: =SUM(BJ6:BJ7) -> 20 | BK8: =SUM(BK6:BK7) -> 20 | BL8: =SUM(BL6:BL7) -> 20 | ... BP8: =SUM(BP6:BP7) -> 20
A9: 就労移行利用者数 | J9: 3 | K9: 5 | L9: 7 | M9: 9 | N9: 11 | O9: 12 | P9: 13 | R9: 14 | S9: 15 | T9: 15 | U9: 15 | V9: 15 | W9: 15 | X9: 15 | Y9: 15 | Z9: 15 | AA9: 15 | AB9: 15 | AC9: 15 | AE9: 15 | AF9: 15 | AG9: 15 | AH9: 15 | AI9: 15 | AJ9: 15 | AK9: 15 | AL9: 15 | AM9: 15 | AN9: 15 | AO9: 15 | AP9: 15 | AR9: 10 | AS9: 10 | AT9: 10 | AU9: 10 | AV9: 10 | AW9: 10 | AX9: 10 | AY9: 10 | AZ9: 10 | BA9: 10 | BB9: 10 | BC9: 10 | BE9: 10 | BF9: 10 | BG9: 10 | BH9: 10 | BI9: 10 | BJ9: 10 | BK9: 10 | BL9: 10 | BM9: 10 | BN9: 10 | BO9: 10 | BP9: 10
A10: 就労移行施設外利用者数 | P10: 1 | R10: 2 | S10: 3 | T10: 4 | U10: 5 | V10: 6 | W10: 7 | X10: 8 | Y10: 9 | Z10: 10 | AA10: 11 | AB10: 12 | AC10: 13 | AE10: 14 | AF10: 15 | AG10: 16 | AH10: 17 | AI10: 18 | AJ10: 19 | AK10: 20 | AL10: 21 | AM10: 22 | AN10: 23 | AO10: 24 | AP10: 25 | AR10: 10 | AS10: 10 | AT10: 10 | AU10: 10 | AV10: 10 | AW10: 10 | AX10: 10 | AY10: 10 | AZ10: 10 | BA10: 10 | BB10: 10 | BC10: 10 | BE10: 10 | BF10: 10 | BG10: 10 | BH10: 10 | BI10: 10 | BJ10: 10 | BK10: 10 | BL10: 10 | BM10: 10 | BN10: 10 | BO10: 10 | BP10: 10
A11: 移行合計 | E11: =SUM(E9:E10) -> 0 | F11: =SUM(F9:F10) -> 0 | G11: =SUM(G9:G10) -> 0 | H11: =SUM(H9:H10) -> 0 | I11: =SUM(I9:I10) -> 0 | J11: =SUM(J9:J10) -> 3 | K11: =SUM(K9:K10) -> 5 | L11: =SUM(L9:L10) -> 7 | ... P11: =SUM(P9:P10) -> 14 | R11: =SUM(R9:R10) -> 16 | S11: =SUM(S9:S10) -> 18 | T11: =SUM(T9:T10) -> 19 | U11: =SUM(U9:U10) -> 20 | V11: =SUM(V9:V10) -> 21 | W11: =SUM(W9:W10) -> 22 | X11: =SUM(X9:X10) -> 23 | Y11: =SUM(Y9:Y10) -> 24 | ... AC11: =SUM(AC9:AC10) -> 28 | AE11: =SUM(AE9:AE10) -> 29 | AF11: =SUM(AF9:AF10) -> 30 | AG11: =SUM(AG9:AG10) -> 31 | AH11: =SUM(AH9:AH10) -> 32 | AI11: =SUM(AI9:AI10) -> 33 | AJ11: =SUM(AJ9:AJ10) -> 34 | AK11: =SUM(AK9:AK10) -> 35 | AL11: =SUM(AL9:AL10) -> 36 | ... AP11: =SUM(AP9:AP10) -> 40 | AR11: =SUM(AR9:AR10) -> 20 | AS11: =SUM(AS9:AS10) -> 20 | AT11: =SUM(AT9:AT10) -> 20 | AU11: =SUM(AU9:AU10) -> 20 | AV11: =SUM(AV9:AV10) -> 20 | AW11: =SUM(AW9:AW10) -> 20 | AX11: =SUM(AX9:AX10) -> 20 | AY11: =SUM(AY9:AY10) -> 20 | ... BC11: =SUM(BC9:BC10) -> 20 | BE11: =SUM(BE9:BE10) -> 20 | BF11: =SUM(BF9:BF10) -> 20 | BG11: =SUM(BG9:BG10) -> 20 | BH11: =SUM(BH9:BH10) -> 20 | BI11: =SUM(BI9:BI10) -> 20 | BJ11: =SUM(BJ9:BJ10) -> 20 | BK11: =SUM(BK9:BK10) -> 20 | BL11: =SUM(BL9:BL10) -> 20 | ... BP11: =SUM(BP9:BP10) -> 20
A12: 合計人数 | E12: =E8:F8+E11 -> 0 | F12: =F8:G8+F11 -> 0 | G12: =G8:H8+G11 -> 0 | H12: =H8:I8+H11 -> 0 | I12: =I8:J8+I11 -> 0 | J12: =J8:K8+J11 -> 3 | K12: =K8:L8+K11 -> 5 | L12: =L8:M8+L11 -> 7 | ... P12: =P8:Q8+P11 -> 14 | R12: =R8:S8+R11 -> 16 | S12: =S8:T8+S11 -> 18 | T12: =T8:U8+T11 -> 19 | U12: =U8:V8+U11 -> 20 | V12: =V8:W8+V11 -> 21 | W12: =W8:X8+W11 -> 22 | X12: =X8:Y8+X11 -> 23 | Y12: =Y8:Z8+Y11 -> 24 | ... AC12: =AC8:AD8+AC11 -> 28 | AE12: =AE8:AF8+AE11 -> 29 | AF12: =AF8:AG8+AF11 -> 30 | AG12: =AG8:AH8+AG11 -> 31 | AH12: =AH8:AI8+AH11 -> 32 | AI12: =AI8:AJ8+AI11 -> 33 | AJ12: =AJ8:AK8+AJ11 -> 34 | AK12: =AK8:AL8+AK11 -> 35 | AL12: =AL8:AM8+AL11 -> 36 | ... AO12: =AO8:AP8+AO11 -> 39 | AP12: =AP8:AP8+AP11 -> 40 | AR12: =AR8:AS8+AR11 -> 40 | AS12: =AS8:AT8+AS11 -> 40 | AT12: =AT8:AU8+AT11 -> 40 | AU12: =AU8:AV8+AU11 -> 40 | AV12: =AV8:AW8+AV11 -> 40 | AW12: =AW8:AX8+AW11 -> 40 | AX12: =AX8:AY8+AX11 -> 40 | AY12: =AY8:AZ8+AY11 -> 40 | ... BB12: =BB8:BC8+BB11 -> 40 | BC12: =BC8:BC8+BC11 -> 40 | BE12: =BE8:BF8+BE11 -> 40 | BF12: =BF8:BG8+BF11 -> 40 | BG12: =BG8:BH8+BG11 -> 40 | BH12: =BH8:BI8+BH11 -> 40 | BI12: =BI8:BJ8+BI11 -> 40 | BJ12: =BJ8:BK8+BJ11 -> 40 | BK12: =BK8:BL8+BK11 -> 40 | BL12: =BL8:BM8+BL11 -> 40 | ... BO12: =BO8:BP8+BO11 -> 40 | BP12: =BP8:BP8+BP11 -> 40
A14: B通常給付金 | E14: =ROUNDDOWN(E6*E23*E4*E5,-2) -> 0 | F14: =ROUNDDOWN(F6*F23*F4*F5,-2) -> 0 | G14: =ROUNDDOWN(G6*G23*G4*G5,-2) -> 0 | H14: =ROUNDDOWN(H6*H23*H4*H5,-2) -> 0 | I14: =ROUNDDOWN(I6*I23*I4*I5,-2) -> 0 | J14: =ROUNDDOWN(J6*J23*J4*J5,-2) -> 0 | K14: =ROUNDDOWN(K6*K23*K4*K5,-2) -> 0 | L14: =ROUNDDOWN(L6*L23*L4*L5,-2) -> 0 | ... P14: =ROUNDDOWN(P6*P23*P4*P5,-2) -> 0 | R14: =ROUNDDOWN(R6*R23*R4*R5,-2) -> 0 | S14: =ROUNDDOWN(S6*S23*S4*S5,-2) -> 0 | T14: =ROUNDDOWN(T6*T23*T4*T5,-2) -> 0 | U14: =ROUNDDOWN(U6*U23*U4*U5,-2) -> 0 | V14: =ROUNDDOWN(V6*V23*V4*V5,-2) -> 0 | W14: =ROUNDDOWN(W6*W23*W4*W5,-2) -> 0 | X14: =ROUNDDOWN(X6*X23*X4*X5,-2) -> 0 | Y14: =ROUNDDOWN(Y6*Y23*Y4*Y5,-2) -> 0 | ... AC14: =ROUNDDOWN(AC6*AC23*AC4*AC5,-2) -> 0 | AE14: =ROUNDDOWN(AE6*AE23*AE4*AE5,-2) -> 0 | AF14: =ROUNDDOWN(AF6*AF23*AF4*AF5,-2) -> 0 | AG14: =ROUNDDOWN(AG6*AG23*AG4*AG5,-2) -> 0 | AH14: =ROUNDDOWN(AH6*AH23*AH4*AH5,-2) -> 0 | AI14: =ROUNDDOWN(AI6*AI23*AI4*AI5,-2) -> 0 | AJ14: =ROUNDDOWN(AJ6*AJ23*AJ4*AJ5,-2) -> 0 | AK14: =ROUNDDOWN(AK6*AK23*AK4*AK5,-2) -> 0 | AL14: =ROUNDDOWN(AL6*AL23*AL4*AL5,-2) -> 0 | ... AP14: =ROUNDDOWN(AP6*AP23*AP4*AP5,-2) -> 0 | AR14: =ROUNDDOWN(AR6*AR23*AR4*AR5,-2) -> 1036600 | AS14: =ROUNDDOWN(AS6*AS23*AS4*AS5,-2) -> 942400 | AT14: =ROUNDDOWN(AT6*AT23*AT4*AT5,-2) -> 1083700 | AU14: =ROUNDDOWN(AU6*AU23*AU4*AU5,-2) -> 1036600 | AV14: =ROUNDDOWN(AV6*AV23*AV4*AV5,-2) -> 1083700 | AW14: =ROUNDDOWN(AW6*AW23*AW4*AW5,-2) -> 1036600 | AX14: =ROUNDDOWN(AX6*AX23*AX4*AX5,-2) -> 1083700 | AY14: =ROUNDDOWN(AY6*AY23*AY4*AY5,-2) -> 1036600 | ... BC14: =ROUNDDOWN(BC6*BC23*BC4*BC5,-2) -> 1036600 | BE14: =ROUNDDOWN(BE6*BE23*BE4*BE5,-2) -> 1036600 | BF14: =ROUNDDOWN(BF6*BF23*BF4*BF5,-2) -> 942400 | BG14: =ROUNDDOWN(BG6*BG23*BG4*BG5,-2) -> 1083700 | BH14: =ROUNDDOWN(BH6*BH23*BH4*BH5,-2) -> 1036600 | BI14: =ROUNDDOWN(BI6*BI23*BI4*BI5,-2) -> 1083700 | BJ14: =ROUNDDOWN(BJ6*BJ23*BJ4*BJ5,-2) -> 1036600 | BK14: =ROUNDDOWN(BK6*BK23*BK4*BK5,-2) -> 1083700 | BL14: =ROUNDDOWN(BL6*BL23*BL4*BL5,-2) -> 1036600 | ... BP14: =ROUNDDOWN(BP6*BP23*BP4*BP5,-2) -> 1036600
A15: B施設外給付金 | E15: =ROUNDDOWN(E7*E24*E4*E29,-2) -> 0 | F15: =F7*F24*F4*F29 -> 0 | G15: =G7*G24*G4*G29 -> 0 | H15: =H7*H24*H4*H29 -> 0 | I15: =I7*I24*I4*I29 -> 0 | J15: =J7*J24*J4*J29 -> 0 | K15: =K7*K24*K4*K29 -> 0 | L15: =L7*L24*L4*L29 -> 0 | M15: =M7*M24*M4*M29 -> 0 | ... P15: =P7*P24*P4*P29 -> 0 | R15: =ROUNDDOWN(R7*R24*R4*R29,-2) -> 0 | S15: =S7*S24*S4*S29 -> 0 | T15: =T7*T24*T4*T29 -> 0 | U15: =U7*U24*U4*U29 -> 0 | V15: =V7*V24*V4*V29 -> 0 | W15: =W7*W24*W4*W29 -> 0 | X15: =X7*X24*X4*X29 -> 0 | Y15: =Y7*Y24*Y4*Y29 -> 0 | Z15: =Z7*Z24*Z4*Z29 -> 0 | ... AC15: =AC7*AC24*AC4*AC29 -> 0 | AE15: =ROUNDDOWN(AE7*AE24*AE4*AE29,-2) -> 0 | AF15: =AF7*AF24*AF4*AF29 -> 0 | AG15: =AG7*AG24*AG4*AG29 -> 0 | AH15: =AH7*AH24*AH4*AH29 -> 0 | AI15: =AI7*AI24*AI4*AI29 -> 0 | AJ15: =AJ7*AJ24*AJ4*AJ29 -> 0 | AK15: =AK7*AK24*AK4*AK29 -> 0 | AL15: =AL7*AL24*AL4*AL29 -> 0 | AM15: =AM7*AM24*AM4*AM29 -> 0 | ... AP15: =AP7*AP24*AP4*AP29 -> 0 | AR15: =ROUNDDOWN(AR7*AR24*AR4*AR29,-2) -> 1136800 | AS15: =AS7*AS24*AS4*AS29 -> 1033500 | AT15: =AT7*AT24*AT4*AT29 -> 1188525 | AU15: =AU7*AU24*AU4*AU29 -> 1136850 | AV15: =AV7*AV24*AV4*AV29 -> 1188525 | AW15: =AW7*AW24*AW4*AW29 -> 1136850 | AX15: =AX7*AX24*AX4*AX29 -> 1188525 | AY15: =AY7*AY24*AY4*AY29 -> 1136850 | AZ15: =AZ7*AZ24*AZ4*AZ29 -> 1136850 | ... BC15: =BC7*BC24*BC4*BC29 -> 1136850 | BE15: =ROUNDDOWN(BE7*BE24*BE4*BE29,-2) -> 1136800 | BF15: =BF7*BF24*BF4*BF29 -> 1033500 | BG15: =BG7*BG24*BG4*BG29 -> 1188525 | BH15: =BH7*BH24*BH4*BH29 -> 1136850 | BI15: =BI7*BI24*BI4*BI29 -> 1188525 | BJ15: =BJ7*BJ24*BJ4*BJ29 -> 1136850 | BK15: =BK7*BK24*BK4*BK29 -> 1188525 | BL15: =BL7*BL24*BL4*BL29 -> 1136850 | BM15: =BM7*BM24*BM4*BM29 -> 1136850 | ... BP15: =BP7*BP24*BP4*BP29 -> 1136850
A16: B加算 | E16: =ROUNDDOWN(((E6+E7)*(E27+E28*0.8))*E4,-2) -> 0 | F16: =ROUNDDOWN(((F6+F7)*(F27+F28*0.8))*F4,-2) -> 0 | G16: =ROUNDDOWN(((G6+G7)*(G27+G28*0.8))*G4,-2) -> 0 | H16: =ROUNDDOWN(((H6+H7)*(H27+H28*0.8))*H4,-2) -> 0 | I16: =ROUNDDOWN(((I6+I7)*(I27+I28*0.8))*I4,-2) -> 0 | J16: =ROUNDDOWN(((J6+J7)*(J27+J28*0.8))*J4,-2) -> 0 | K16: =ROUNDDOWN(((K6+K7)*(K27+K28*0.8))*K4,-2) -> 0 | L16: =ROUNDDOWN(((L6+L7)*(L27+L28*0.8))*L4,-2) -> 0 | ... P16: =ROUNDDOWN(((P6+P7)*(P27+P28*0.8))*P4,-2) -> 0 | R16: =ROUNDDOWN(((R6+R7)*(R27+R28*0.8))*R4,-2) -> 0 | S16: =ROUNDDOWN(((S6+S7)*(S27+S28*0.8))*S4,-2) -> 0 | T16: =ROUNDDOWN(((T6+T7)*(T27+T28*0.8))*T4,-2) -> 0 | U16: =ROUNDDOWN(((U6+U7)*(U27+U28*0.8))*U4,-2) -> 0 | V16: =ROUNDDOWN(((V6+V7)*(V27+V28*0.8))*V4,-2) -> 0 | W16: =ROUNDDOWN(((W6+W7)*(W27+W28*0.8))*W4,-2) -> 0 | X16: =ROUNDDOWN(((X6+X7)*(X27+X28*0.8))*X4,-2) -> 0 | Y16: =ROUNDDOWN(((Y6+Y7)*(Y27+Y28*0.8))*Y4,-2) -> 0 | ... AC16: =ROUNDDOWN(((AC6+AC7)*(AC27+AC28*0.8))*AC4,-2) -> 0 | AE16: =ROUNDDOWN(((AE6+AE7)*(AE27+AE28*0.8))*AE4,-2) -> 0 | AF16: =ROUNDDOWN(((AF6+AF7)*(AF27+AF28*0.8))*AF4,-2) -> 0 | AG16: =ROUNDDOWN(((AG6+AG7)*(AG27+AG28*0.8))*AG4,-2) -> 0 | AH16: =ROUNDDOWN(((AH6+AH7)*(AH27+AH28*0.8))*AH4,-2) -> 0 | AI16: =ROUNDDOWN(((AI6+AI7)*(AI27+AI28*0.8))*AI4,-2) -> 0 | AJ16: =ROUNDDOWN(((AJ6+AJ7)*(AJ27+AJ28*0.8))*AJ4,-2) -> 0 | AK16: =ROUNDDOWN(((AK6+AK7)*(AK27+AK28*0.8))*AK4,-2) -> 0 | AL16: =ROUNDDOWN(((AL6+AL7)*(AL27+AL28*0.8))*AL4,-2) -> 0 | ... AP16: =ROUNDDOWN(((AP6+AP7)*(AP27+AP28*0.8))*AP4,-2) -> 0 | AR16: =ROUNDDOWN(((AR6+AR7)*(AR27+AR28*0.8))*AR4,-2) -> 581600 | AS16: =ROUNDDOWN(((AS6+AS7)*(AS27+AS28*0.8))*AS4,-2) -> 528800 | AT16: =ROUNDDOWN(((AT6+AT7)*(AT27+AT28*0.8))*AT4,-2) -> 608100 | AU16: =ROUNDDOWN(((AU6+AU7)*(AU27+AU28*0.8))*AU4,-2) -> 581600 | AV16: =ROUNDDOWN(((AV6+AV7)*(AV27+AV28*0.8))*AV4,-2) -> 608100 | AW16: =ROUNDDOWN(((AW6+AW7)*(AW27+AW28*0.8))*AW4,-2) -> 581600 | AX16: =ROUNDDOWN(((AX6+AX7)*(AX27+AX28*0.8))*AX4,-2) -> 608100 | AY16: =ROUNDDOWN(((AY6+AY7)*(AY27+AY28*0.8))*AY4,-2) -> 581600 | ... BC16: =ROUNDDOWN(((BC6+BC7)*(BC27+BC28*0.8))*BC4,-2) -> 581600 | BE16: =ROUNDDOWN(((BE6+BE7)*(BE27+BE28*0.8))*BE4,-2) -> 581600 | BF16: =ROUNDDOWN(((BF6+BF7)*(BF27+BF28*0.8))*BF4,-2) -> 528800 | BG16: =ROUNDDOWN(((BG6+BG7)*(BG27+BG28*0.8))*BG4,-2) -> 608100 | BH16: =ROUNDDOWN(((BH6+BH7)*(BH27+BH28*0.8))*BH4,-2) -> 581600 | BI16: =ROUNDDOWN(((BI6+BI7)*(BI27+BI28*0.8))*BI4,-2) -> 608100 | BJ16: =ROUNDDOWN(((BJ6+BJ7)*(BJ27+BJ28*0.8))*BJ4,-2) -> 581600 | BK16: =ROUNDDOWN(((BK6+BK7)*(BK27+BK28*0.8))*BK4,-2) -> 608100 | BL16: =ROUNDDOWN(((BL6+BL7)*(BL27+BL28*0.8))*BL4,-2) -> 581600 | ... BP16: =ROUNDDOWN(((BP6+BP7)*(BP27+BP28*0.8))*BP4,-2) -> 581600
A17: 移行通常給付金 | E17: =ROUNDDOWN(E9*E25*E4*E5,-2) -> 0 | F17: =ROUNDDOWN(F9*F25*F4*F5,-2) -> 0 | G17: =ROUNDDOWN(G9*G25*G4*G5,-2) -> 0 | H17: =ROUNDDOWN(H9*H25*H4*H5,-2) -> 0 | I17: =ROUNDDOWN(I9*I25*I4*I5,-2) -> 0 | J17: =ROUNDDOWN(J9*J25*J4*J5,-2) -> 426600 | K17: =ROUNDDOWN(K9*K25*K4*K5,-2) -> 743300 | L17: =ROUNDDOWN(L9*L25*L4*L5,-2) -> 995400 | ... P17: =ROUNDDOWN(P9*P25*P4*P5,-2) -> 1848700 | R17: =ROUNDDOWN(R9*R25*R4*R5,-2) -> 1990900 | S17: =ROUNDDOWN(S9*S25*S4*S5,-2) -> 1939200 | T17: =ROUNDDOWN(T9*T25*T4*T5,-2) -> 2230000 | U17: =ROUNDDOWN(U9*U25*U4*U5,-2) -> 2133100 | V17: =ROUNDDOWN(V9*V25*V4*V5,-2) -> 2230000 | W17: =ROUNDDOWN(W9*W25*W4*W5,-2) -> 2133100 | X17: =ROUNDDOWN(X9*X25*X4*X5,-2) -> 2230000 | Y17: =ROUNDDOWN(Y9*Y25*Y4*Y5,-2) -> 2133100 | ... AC17: =ROUNDDOWN(AC9*AC25*AC4*AC5,-2) -> 2133100 | AE17: =ROUNDDOWN(AE9*AE25*AE4*AE5,-2) -> 2133100 | AF17: =ROUNDDOWN(AF9*AF25*AF4*AF5,-2) -> 1939200 | AG17: =ROUNDDOWN(AG9*AG25*AG4*AG5,-2) -> 2230000 | AH17: =ROUNDDOWN(AH9*AH25*AH4*AH5,-2) -> 2133100 | AI17: =ROUNDDOWN(AI9*AI25*AI4*AI5,-2) -> 2230000 | AJ17: =ROUNDDOWN(AJ9*AJ25*AJ4*AJ5,-2) -> 2133100 | AK17: =ROUNDDOWN(AK9*AK25*AK4*AK5,-2) -> 2230000 | AL17: =ROUNDDOWN(AL9*AL25*AL4*AL5,-2) -> 2133100 | ... AP17: =ROUNDDOWN(AP9*AP25*AP4*AP5,-2) -> 2133100 | AR17: =ROUNDDOWN(AR9*AR25*AR4*AR5,-2) -> 1422000 | AS17: =ROUNDDOWN(AS9*AS25*AS4*AS5,-2) -> 1292800 | AT17: =ROUNDDOWN(AT9*AT25*AT4*AT5,-2) -> 1486700 | AU17: =ROUNDDOWN(AU9*AU25*AU4*AU5,-2) -> 1422000 | AV17: =ROUNDDOWN(AV9*AV25*AV4*AV5,-2) -> 1486700 | AW17: =ROUNDDOWN(AW9*AW25*AW4*AW5,-2) -> 1422000 | AX17: =ROUNDDOWN(AX9*AX25*AX4*AX5,-2) -> 1486700 | AY17: =ROUNDDOWN(AY9*AY25*AY4*AY5,-2) -> 1422000 | ... BC17: =ROUNDDOWN(BC9*BC25*BC4*BC5,-2) -> 1422000 | BE17: =ROUNDDOWN(BE9*BE25*BE4*BE5,-2) -> 1422000 | BF17: =ROUNDDOWN(BF9*BF25*BF4*BF5,-2) -> 1292800 | BG17: =ROUNDDOWN(BG9*BG25*BG4*BG5,-2) -> 1486700 | BH17: =ROUNDDOWN(BH9*BH25*BH4*BH5,-2) -> 1422000 | BI17: =ROUNDDOWN(BI9*BI25*BI4*BI5,-2) -> 1486700 | BJ17: =ROUNDDOWN(BJ9*BJ25*BJ4*BJ5,-2) -> 1422000 | BK17: =ROUNDDOWN(BK9*BK25*BK4*BK5,-2) -> 1486700 | BL17: =ROUNDDOWN(BL9*BL25*BL4*BL5,-2) -> 1422000 | ... BP17: =ROUNDDOWN(BP9*BP25*BP4*BP5,-2) -> 1422000
A18: 移行施設外給付金 | E18: =ROUNDDOWN(E10*E26*E4*E5,-2) -> 0 | F18: =ROUNDDOWN(F10*F26*F4*F5,-2) -> 0 | G18: =ROUNDDOWN(G10*G26*G4*G5,-2) -> 0 | H18: =ROUNDDOWN(H10*H26*H4*H5,-2) -> 0 | I18: =ROUNDDOWN(I10*I26*I4*I5,-2) -> 0 | J18: =ROUNDDOWN(J10*J26*J4*J5,-2) -> 0 | K18: =ROUNDDOWN(K10*K26*K4*K5,-2) -> 0 | L18: =ROUNDDOWN(L10*L26*L4*L5,-2) -> 0 | ... P18: =ROUNDDOWN(P10*P26*P4*P5,-2) -> 159800 | R18: =ROUNDDOWN(R10*R26*R4*R5,-2) -> 319600 | S18: =ROUNDDOWN(S10*S26*S4*S5,-2) -> 435800 | T18: =ROUNDDOWN(T10*T26*T4*T5,-2) -> 668200 | U18: =ROUNDDOWN(U10*U26*U4*U5,-2) -> 799000 | V18: =ROUNDDOWN(V10*V26*V4*V5,-2) -> 1002400 | W18: =ROUNDDOWN(W10*W26*W4*W5,-2) -> 1118600 | X18: =ROUNDDOWN(X10*X26*X4*X5,-2) -> 1336500 | Y18: =ROUNDDOWN(Y10*Y26*Y4*Y5,-2) -> 1438200 | ... AC18: =ROUNDDOWN(AC10*AC26*AC4*AC5,-2) -> 2077500 | AE18: =ROUNDDOWN(AE10*AE26*AE4*AE5,-2) -> 2237300 | AF18: =ROUNDDOWN(AF10*AF26*AF4*AF5,-2) -> 2179200 | AG18: =ROUNDDOWN(AG10*AG26*AG4*AG5,-2) -> 2673100 | AH18: =ROUNDDOWN(AH10*AH26*AH4*AH5,-2) -> 2716700 | AI18: =ROUNDDOWN(AI10*AI26*AI4*AI5,-2) -> 3007200 | AJ18: =ROUNDDOWN(AJ10*AJ26*AJ4*AJ5,-2) -> 3036300 | AK18: =ROUNDDOWN(AK10*AK26*AK4*AK5,-2) -> 3341400 | AL18: =ROUNDDOWN(AL10*AL26*AL4*AL5,-2) -> 3355900 | ... AP18: =ROUNDDOWN(AP10*AP26*AP4*AP5,-2) -> 3995200 | AR18: =ROUNDDOWN(AR10*AR26*AR4*AR5,-2) -> 1598000 | AS18: =ROUNDDOWN(AS10*AS26*AS4*AS5,-2) -> 1452800 | AT18: =ROUNDDOWN(AT10*AT26*AT4*AT5,-2) -> 1670700 | AU18: =ROUNDDOWN(AU10*AU26*AU4*AU5,-2) -> 1598000 | AV18: =ROUNDDOWN(AV10*AV26*AV4*AV5,-2) -> 1670700 | AW18: =ROUNDDOWN(AW10*AW26*AW4*AW5,-2) -> 1598000 | AX18: =ROUNDDOWN(AX10*AX26*AX4*AX5,-2) -> 1670700 | AY18: =ROUNDDOWN(AY10*AY26*AY4*AY5,-2) -> 1598000 | ... BC18: =ROUNDDOWN(BC10*BC26*BC4*BC5,-2) -> 1598000 | BE18: =ROUNDDOWN(BE10*BE26*BE4*BE5,-2) -> 1598000 | BF18: =ROUNDDOWN(BF10*BF26*BF4*BF5,-2) -> 1452800 | BG18: =ROUNDDOWN(BG10*BG26*BG4*BG5,-2) -> 1670700 | BH18: =ROUNDDOWN(BH10*BH26*BH4*BH5,-2) -> 1598000 | BI18: =ROUNDDOWN(BI10*BI26*BI4*BI5,-2) -> 1670700 | BJ18: =ROUNDDOWN(BJ10*BJ26*BJ4*BJ5,-2) -> 1598000 | BK18: =ROUNDDOWN(BK10*BK26*BK4*BK5,-2) -> 1670700 | BL18: =ROUNDDOWN(BL10*BL26*BL4*BL5,-2) -> 1598000 | ... BP18: =ROUNDDOWN(BP10*BP26*BP4*BP5,-2) -> 1598000
A19: 移行加算 | E19: =ROUNDDOWN((E9+E10)*E4*E5*E28,-2) -> 0 | F19: =ROUNDDOWN((F9+F10)*F4*F5*F28,-2) -> 0 | G19: =ROUNDDOWN((G9+G10)*G4*G5*G28,-2) -> 0 | H19: =ROUNDDOWN((H9+H10)*H4*H5*H28,-2) -> 0 | I19: =ROUNDDOWN((I9+I10)*I4*I5*I28,-2) -> 0 | J19: =ROUNDDOWN((J9+J10)*J4*J5*J28,-2) -> 28500 | K19: =ROUNDDOWN((K9+K10)*K4*K5*K28,-2) -> 49600 | L19: =ROUNDDOWN((L9+L10)*L4*L5*L28,-2) -> 66500 | ... P19: =ROUNDDOWN((P9+P10)*P4*P5*P28,-2) -> 133000 | R19: =ROUNDDOWN((R9+R10)*R4*R5*R28,-2) -> 152000 | S19: =ROUNDDOWN((S9+S10)*S4*S5*S28,-2) -> 155500 | T19: =ROUNDDOWN((T9+T10)*T4*T5*T28,-2) -> 188700 | U19: =ROUNDDOWN((U9+U10)*U4*U5*U28,-2) -> 190000 | V19: =ROUNDDOWN((V9+V10)*V4*V5*V28,-2) -> 208600 | W19: =ROUNDDOWN((W9+W10)*W4*W5*W28,-2) -> 209000 | X19: =ROUNDDOWN((X9+X10)*X4*X5*X28,-2) -> 228500 | Y19: =ROUNDDOWN((Y9+Y10)*Y4*Y5*Y28,-2) -> 228000 | ... AC19: =ROUNDDOWN((AC9+AC10)*AC4*AC5*AC28,-2) -> 266100 | AE19: =ROUNDDOWN((AE9+AE10)*AE4*AE5*AE28,-2) -> 275600 | AF19: =ROUNDDOWN((AF9+AF10)*AF4*AF5*AF28,-2) -> 259200 | AG19: =ROUNDDOWN((AG9+AG10)*AG4*AG5*AG28,-2) -> 308000 | AH19: =ROUNDDOWN((AH9+AH10)*AH4*AH5*AH28,-2) -> 304100 | AI19: =ROUNDDOWN((AI9+AI10)*AI4*AI5*AI28,-2) -> 327800 | AJ19: =ROUNDDOWN((AJ9+AJ10)*AJ4*AJ5*AJ28,-2) -> 323100 | AK19: =ROUNDDOWN((AK9+AK10)*AK4*AK5*AK28,-2) -> 347700 | AL19: =ROUNDDOWN((AL9+AL10)*AL4*AL5*AL28,-2) -> 342100 | ... AP19: =ROUNDDOWN((AP9+AP10)*AP4*AP5*AP28,-2) -> 380100 | AR19: =ROUNDDOWN((AR9+AR10)*AR4*AR5*AR28,-2) -> 190000 | AS19: =ROUNDDOWN((AS9+AS10)*AS4*AS5*AS28,-2) -> 172800 | AT19: =ROUNDDOWN((AT9+AT10)*AT4*AT5*AT28,-2) -> 198700 | AU19: =ROUNDDOWN((AU9+AU10)*AU4*AU5*AU28,-2) -> 190000 | AV19: =ROUNDDOWN((AV9+AV10)*AV4*AV5*AV28,-2) -> 198700 | AW19: =ROUNDDOWN((AW9+AW10)*AW4*AW5*AW28,-2) -> 190000 | AX19: =ROUNDDOWN((AX9+AX10)*AX4*AX5*AX28,-2) -> 198700 | AY19: =ROUNDDOWN((AY9+AY10)*AY4*AY5*AY28,-2) -> 190000 | ... BC19: =ROUNDDOWN((BC9+BC10)*BC4*BC5*BC28,-2) -> 190000 | BE19: =ROUNDDOWN((BE9+BE10)*BE4*BE5*BE28,-2) -> 190000 | BF19: =ROUNDDOWN((BF9+BF10)*BF4*BF5*BF28,-2) -> 172800 | BG19: =ROUNDDOWN((BG9+BG10)*BG4*BG5*BG28,-2) -> 198700 | BH19: =ROUNDDOWN((BH9+BH10)*BH4*BH5*BH28,-2) -> 190000 | BI19: =ROUNDDOWN((BI9+BI10)*BI4*BI5*BI28,-2) -> 198700 | BJ19: =ROUNDDOWN((BJ9+BJ10)*BJ4*BJ5*BJ28,-2) -> 190000 | BK19: =ROUNDDOWN((BK9+BK10)*BK4*BK5*BK28,-2) -> 198700 | BL19: =ROUNDDOWN((BL9+BL10)*BL4*BL5*BL28,-2) -> 190000 | ... BP19: =ROUNDDOWN((BP9+BP10)*BP4*BP5*BP28,-2) -> 190000
A20: 給付費合計 | E20: =SUM(E14:E19) -> 0 | F20: =SUM(F14:F19) -> 0 | G20: =SUM(G14:G19) -> 0 | H20: =SUM(H14:H19) -> 0 | I20: =SUM(I14:I19) -> 0 | J20: =SUM(J14:J19) -> 455100 | K20: =SUM(K14:K19) -> 792900 | L20: =SUM(L14:L19) -> 1061900 | ... P20: =SUM(P14:P19) -> 2141500 | R20: =SUM(R14:R19) -> 2462500 | S20: =SUM(S14:S19) -> 2530500 | T20: =SUM(T14:T19) -> 3086900 | U20: =SUM(U14:U19) -> 3122100 | V20: =SUM(V14:V19) -> 3441000 | W20: =SUM(W14:W19) -> 3460700 | X20: =SUM(X14:X19) -> 3795000 | Y20: =SUM(Y14:Y19) -> 3799300 | ... AC20: =SUM(AC14:AC19) -> 4476700 | AE20: =SUM(AE14:AE19) -> 4646000 | AF20: =SUM(AF14:AF19) -> 4377600 | AG20: =SUM(AG14:AG19) -> 5211100 | AH20: =SUM(AH14:AH19) -> 5153900 | AI20: =SUM(AI14:AI19) -> 5565000 | AJ20: =SUM(AJ14:AJ19) -> 5492500 | AK20: =SUM(AK14:AK19) -> 5919100 | AL20: =SUM(AL14:AL19) -> 5831100 | ... AP20: =SUM(AP14:AP19) -> 6508400 | AR20: =SUM(AR14:AR19) -> 5965000 | AS20: =SUM(AS14:AS19) -> 5423100 | AT20: =SUM(AT14:AT19) -> 6236425 | AU20: =SUM(AU14:AU19) -> 5965050 | AV20: =SUM(AV14:AV19) -> 6236425 | AW20: =SUM(AW14:AW19) -> 5965050 | AX20: =SUM(AX14:AX19) -> 6236425 | AY20: =SUM(AY14:AY19) -> 5965050 | ... BC20: =SUM(BC14:BC19) -> 5965050 | BE20: =SUM(BE14:BE19) -> 5965000 | BF20: =SUM(BF14:BF19) -> 5423100 | BG20: =SUM(BG14:BG19) -> 6236425 | BH20: =SUM(BH14:BH19) -> 5965050 | BI20: =SUM(BI14:BI19) -> 6236425 | BJ20: =SUM(BJ14:BJ19) -> 5965050 | BK20: =SUM(BK14:BK19) -> 6236425 | BL20: =SUM(BL14:BL19) -> 5965050 | ... BP20: =SUM(BP14:BP19) -> 5965050
A21: 給付費合計（千円） | E21: =E20/1000 -> 0 | F21: =F20/1000 -> 0 | G21: =G20/1000 -> 0 | H21: =H20/1000 -> 0 | I21: =I20/1000 -> 0 | J21: =J20/1000 -> 455.1 | K21: =K20/1000 -> 792.9 | L21: =L20/1000 -> 1061.9 | ... P21: =P20/1000 -> 2141.5 | R21: =R20/1000 -> 2462.5 | S21: =S20/1000 -> 2530.5 | T21: =T20/1000 -> 3086.9 | U21: =U20/1000 -> 3122.1 | V21: =V20/1000 -> 3441 | W21: =W20/1000 -> 3460.7 | X21: =X20/1000 -> 3795 | Y21: =Y20/1000 -> 3799.3 | ... AC21: =AC20/1000 -> 4476.7 | AE21: =AE20/1000 -> 4646 | AF21: =AF20/1000 -> 4377.6 | AG21: =AG20/1000 -> 5211.1 | AH21: =AH20/1000 -> 5153.9 | AI21: =AI20/1000 -> 5565 | AJ21: =AJ20/1000 -> 5492.5 | AK21: =AK20/1000 -> 5919.1 | AL21: =AL20/1000 -> 5831.1 | ... AP21: =AP20/1000 -> 6508.4 | AR21: =AR20/1000 -> 5965 | AS21: =AS20/1000 -> 5423.1 | AT21: =AT20/1000 -> 6236.425 | AU21: =AU20/1000 -> 5965.05 | AV21: =AV20/1000 -> 6236.425 | AW21: =AW20/1000 -> 5965.05 | AX21: =AX20/1000 -> 6236.425 | AY21: =AY20/1000 -> 5965.05 | ... BC21: =BC20/1000 -> 5965.05 | BE21: =BE20/1000 -> 5965 | BF21: =BF20/1000 -> 5423.1 | BG21: =BG20/1000 -> 6236.425 | BH21: =BH20/1000 -> 5965.05 | BI21: =BI20/1000 -> 6236.425 | BJ21: =BJ20/1000 -> 5965.05 | BK21: =BK20/1000 -> 6236.425 | BL21: =BL20/1000 -> 5965.05 | ... BP21: =BP20/1000 -> 5965.05
A23: B基本報酬 | E23: 5890 | F23: 5890 | G23: 5890 | H23: 5890 | I23: 5890 | J23: 5890 | K23: 5890 | L23: 5890 | M23: 5890 | N23: 5890 | O23: 5890 | P23: 5890 | R23: 5890 | S23: 5890 | T23: 5890 | U23: 5890 | V23: 5890 | W23: 5890 | X23: 5890 | Y23: 5890 | Z23: 5890 | AA23: 5890 | AB23: 5890 | AC23: 5890 | AE23: 5890 | AF23: 5890 | AG23: 5890 | AH23: 5890 | AI23: 5890 | AJ23: 5890 | AK23: 5890 | AL23: 5890 | AM23: 5890 | AN23: 5890 | AO23: 5890 | AP23: 5890 | AR23: 5890 | AS23: 5890 | AT23: 5890 | AU23: 5890 | AV23: 5890 | AW23: 5890 | AX23: 5890 | AY23: 5890 | AZ23: 5890 | BA23: 5890 | BB23: 5890 | BC23: 5890 | BE23: 5890 | BF23: 5890 | BG23: 5890 | BH23: 5890 | BI23: 5890 | BJ23: 5890 | BK23: 5890 | BL23: 5890 | BM23: 5890 | BN23: 5890 | BO23: 5890 | BP23: 5890
A24: B施設外基本報酬 | E24: 6890 | F24: 6890 | G24: 6890 | H24: 6890 | I24: 6890 | J24: 6890 | K24: 6890 | L24: 6890 | M24: 6890 | N24: 6890 | O24: 6890 | P24: 6890 | R24: 6890 | S24: 6890 | T24: 6890 | U24: 6890 | V24: 6890 | W24: 6890 | X24: 6890 | Y24: 6890 | Z24: 6890 | AA24: 6890 | AB24: 6890 | AC24: 6890 | AE24: 6890 | AF24: 6890 | AG24: 6890 | AH24: 6890 | AI24: 6890 | AJ24: 6890 | AK24: 6890 | AL24: 6890 | AM24: 6890 | AN24: 6890 | AO24: 6890 | AP24: 6890 | AR24: 6890 | AS24: 6890 | AT24: 6890 | AU24: 6890 | AV24: 6890 | AW24: 6890 | AX24: 6890 | AY24: 6890 | AZ24: 6890 | BA24: 6890 | BB24: 6890 | BC24: 6890 | BE24: 6890 | BF24: 6890 | BG24: 6890 | BH24: 6890 | BI24: 6890 | BJ24: 6890 | BK24: 6890 | BL24: 6890 | BM24: 6890 | BN24: 6890 | BO24: 6890 | BP24: 6890
A25: 移行基本報酬 | E25: 8080 | F25: 8080 | G25: 8080 | H25: 8080 | I25: 8080 | J25: 8080 | K25: 8080 | L25: 8080 | M25: 8080 | N25: 8080 | O25: 8080 | P25: 8080 | R25: 8080 | S25: 8080 | T25: 8080 | U25: 8080 | V25: 8080 | W25: 8080 | X25: 8080 | Y25: 8080 | Z25: 8080 | AA25: 8080 | AB25: 8080 | AC25: 8080 | AE25: 8080 | AF25: 8080 | AG25: 8080 | AH25: 8080 | AI25: 8080 | AJ25: 8080 | AK25: 8080 | AL25: 8080 | AM25: 8080 | AN25: 8080 | AO25: 8080 | AP25: 8080 | AR25: 8080 | AS25: 8080 | AT25: 8080 | AU25: 8080 | AV25: 8080 | AW25: 8080 | AX25: 8080 | AY25: 8080 | AZ25: 8080 | BA25: 8080 | BB25: 8080 | BC25: 8080 | BE25: 8080 | BF25: 8080 | BG25: 8080 | BH25: 8080 | BI25: 8080 | BJ25: 8080 | BK25: 8080 | BL25: 8080 | BM25: 8080 | BN25: 8080 | BO25: 8080 | BP25: 8080
A26: 移行施設外基本報酬 | E26: 9080 | F26: 9080 | G26: 9080 | H26: 9080 | I26: 9080 | J26: 9080 | K26: 9080 | L26: 9080 | M26: 9080 | N26: 9080 | O26: 9080 | P26: 9080 | R26: 9080 | S26: 9080 | T26: 9080 | U26: 9080 | V26: 9080 | W26: 9080 | X26: 9080 | Y26: 9080 | Z26: 9080 | AA26: 9080 | AB26: 9080 | AC26: 9080 | AE26: 9080 | AF26: 9080 | AG26: 9080 | AH26: 9080 | AI26: 9080 | AJ26: 9080 | AK26: 9080 | AL26: 9080 | AM26: 9080 | AN26: 9080 | AO26: 9080 | AP26: 9080 | AR26: 9080 | AS26: 9080 | AT26: 9080 | AU26: 9080 | AV26: 9080 | AW26: 9080 | AX26: 9080 | AY26: 9080 | AZ26: 9080 | BA26: 9080 | BB26: 9080 | BC26: 9080 | BE26: 9080 | BF26: 9080 | BG26: 9080 | BH26: 9080 | BI26: 9080 | BJ26: 9080 | BK26: 9080 | BL26: 9080 | BM26: 9080 | BN26: 9080 | BO26: 9080 | BP26: 9080
A27: 目標工賃達成指導員加算 | E27: 890 | F27: 890 | G27: 890 | H27: 890 | I27: 890 | J27: 890 | K27: 890 | L27: 890 | M27: 890 | N27: 890 | O27: 890 | P27: 890 | R27: 890 | S27: 890 | T27: 890 | U27: 890 | V27: 890 | W27: 890 | X27: 890 | Y27: 890 | Z27: 890 | AA27: 890 | AB27: 890 | AC27: 890 | AE27: 890 | AF27: 890 | AG27: 890 | AH27: 890 | AI27: 890 | AJ27: 890 | AK27: 890 | AL27: 890 | AM27: 890 | AN27: 890 | AO27: 890 | AP27: 890 | AR27: 890 | AS27: 890 | AT27: 890 | AU27: 890 | AV27: 890 | AW27: 890 | AX27: 890 | AY27: 890 | AZ27: 890 | BA27: 890 | BB27: 890 | BC27: 890 | BE27: 890 | BF27: 890 | BG27: 890 | BH27: 890 | BI27: 890 | BJ27: 890 | BK27: 890 | BL27: 890 | BM27: 890 | BN27: 890 | BO27: 890 | BP27: 890
A28: 送迎加算 | E28: 540 | F28: 540 | G28: 540 | H28: 540 | I28: 540 | J28: 540 | K28: 540 | L28: 540 | M28: 540 | N28: 540 | O28: 540 | P28: 540 | R28: 540 | S28: 540 | T28: 540 | U28: 540 | V28: 540 | W28: 540 | X28: 540 | Y28: 540 | Z28: 540 | AA28: 540 | AB28: 540 | AC28: 540 | AE28: 540 | AF28: 540 | AG28: 540 | AH28: 540 | AI28: 540 | AJ28: 540 | AK28: 540 | AL28: 540 | AM28: 540 | AN28: 540 | AO28: 540 | AP28: 540 | AR28: 540 | AS28: 540 | AT28: 540 | AU28: 540 | AV28: 540 | AW28: 540 | AX28: 540 | AY28: 540 | AZ28: 540 | BA28: 540 | BB28: 540 | BC28: 540 | BE28: 540 | BF28: 540 | BG28: 540 | BH28: 540 | BI28: 540 | BJ28: 540 | BK28: 540 | BL28: 540 | BM28: 540 | BN28: 540 | BO28: 540 | BP28: 540
A29: 稼働率 | E29: 0.8 | F29: 0.8 | G29: 0.8 | H29: 0.8 | I29: 0.8 | J29: 0.8 | K29: 0.8 | L29: 0.8 | M29: 0.8 | N29: 0.8 | O29: 0.8 | P29: 0.8 | R29: 0.75 | S29: 0.75 | T29: 0.75 | U29: 0.75 | V29: 0.75 | W29: 0.75 | X29: 0.75 | Y29: 0.75 | Z29: 0.75 | AA29: 0.75 | AB29: 0.75 | AC29: 0.75 | AE29: 0.75 | AF29: 0.75 | AG29: 0.75 | AH29: 0.75 | AI29: 0.75 | AJ29: 0.75 | AK29: 0.75 | AL29: 0.75 | AM29: 0.75 | AN29: 0.75 | AO29: 0.75 | AP29: 0.75 | AR29: 0.75 | AS29: 0.75 | AT29: 0.75 | AU29: 0.75 | AV29: 0.75 | AW29: 0.75 | AX29: 0.75 | AY29: 0.75 | AZ29: 0.75 | BA29: 0.75 | BB29: 0.75 | BC29: 0.75 | BE29: 0.75 | BF29: 0.75 | BG29: 0.75 | BH29: 0.75 | BI29: 0.75 | BJ29: 0.75 | BK29: 0.75 | BL29: 0.75 | BM29: 0.75 | BN29: 0.75 | BO29: 0.75 | BP29: 0.75
A32: B人員配置 | E32: =ROUNDUP(E6/7.5,0) -> 0 | F32: =ROUNDUP(F6/7.5,0) -> 0 | G32: =ROUNDUP(G6/7.5,1) -> 0 | H32: =ROUNDUP(H6/7.5,1) -> 0 | I32: =ROUNDUP(I6/7.5,1) -> 0 | J32: =ROUNDUP(J6/7.5,1) -> 0 | K32: =ROUNDUP(K6/7.5,1) -> 0 | L32: =ROUNDUP(L6/7.5,1) -> 0 | M32: =ROUNDUP(M6/7.5,1) -> 0 | N32: =ROUNDUP(N6/7.5,1) -> 0 | ... P32: =ROUNDUP(P6/7.5,1) -> 0 | R32: =ROUNDUP(R6/7.5,0) -> 0 | S32: =ROUNDUP(S6/7.5,0) -> 0 | T32: =ROUNDUP(T6/7.5,1) -> 0 | U32: =ROUNDUP(U6/7.5,1) -> 0 | V32: =ROUNDUP(V6/7.5,1) -> 0 | W32: =ROUNDUP(W6/7.5,1) -> 0 | X32: =ROUNDUP(X6/7.5,1) -> 0 | Y32: =ROUNDUP(Y6/7.5,1) -> 0 | Z32: =ROUNDUP(Z6/7.5,1) -> 0 | AA32: =ROUNDUP(AA6/7.5,1) -> 0 | ... AC32: =ROUNDUP(AC6/7.5,1) -> 0 | AE32: =ROUNDUP(AE6/7.5,0) -> 0 | AF32: =ROUNDUP(AF6/7.5,0) -> 0 | AG32: =ROUNDUP(AG6/7.5,1) -> 0 | AH32: =ROUNDUP(AH6/7.5,1) -> 0 | AI32: =ROUNDUP(AI6/7.5,1) -> 0 | AJ32: =ROUNDUP(AJ6/7.5,1) -> 0 | AK32: =ROUNDUP(AK6/7.5,1) -> 0 | AL32: =ROUNDUP(AL6/7.5,1) -> 0 | AM32: =ROUNDUP(AM6/7.5,1) -> 0 | AN32: =ROUNDUP(AN6/7.5,1) -> 0 | ... AP32: =ROUNDUP(AP6/7.5,1) -> 0 | AR32: =ROUNDUP(AR6/7.5,0) -> 2 | AS32: =ROUNDUP(AS6/7.5,0) -> 2 | AT32: =ROUNDUP(AT6/7.5,1) -> 1.4 | AU32: =ROUNDUP(AU6/7.5,1) -> 1.4 | AV32: =ROUNDUP(AV6/7.5,1) -> 1.4 | AW32: =ROUNDUP(AW6/7.5,1) -> 1.4 | AX32: =ROUNDUP(AX6/7.5,1) -> 1.4 | AY32: =ROUNDUP(AY6/7.5,1) -> 1.4 | AZ32: =ROUNDUP(AZ6/7.5,1) -> 1.4 | BA32: =ROUNDUP(BA6/7.5,1) -> 1.4 | ... BC32: =ROUNDUP(BC6/7.5,1) -> 1.4 | BE32: =ROUNDUP(BE6/7.5,0) -> 2 | BF32: =ROUNDUP(BF6/7.5,0) -> 2 | BG32: =ROUNDUP(BG6/7.5,1) -> 1.4 | BH32: =ROUNDUP(BH6/7.5,1) -> 1.4 | BI32: =ROUNDUP(BI6/7.5,1) -> 1.4 | BJ32: =ROUNDUP(BJ6/7.5,1) -> 1.4 | BK32: =ROUNDUP(BK6/7.5,1) -> 1.4 | BL32: =ROUNDUP(BL6/7.5,1) -> 1.4 | BM32: =ROUNDUP(BM6/7.5,1) -> 1.4 | BN32: =ROUNDUP(BN6/7.5,1) -> 1.4 | ... BP32: =ROUNDUP(BP6/7.5,1) -> 1.4
A33: B人工賃向上・施設外 | E33: =IF(E7/7.5<1,2,1+E7/7.5) -> 2 | F33: =IF(F7/7.5<1,2,1+F7/7.5) -> 2 | G33: =IF(G7/7.5<1,2,1+G7/7.5) -> 2 | H33: =IF(H7/7.5<1,2,1+H7/7.5) -> 2 | I33: =IF(I7/7.5<1,2,1+I7/7.5) -> 2 | J33: =IF(J7/7.5<1,2,1+J7/7.5) -> 2 | K33: =IF(K7/7.5<1,2,1+K7/7.5) -> 2 | L33: =IF(L7/7.5<1,2,1+L7/7.5) -> 2 | ... P33: =IF(P7/7.5<1,2,1+P7/7.5) -> 2 | R33: =IF(R7/7.5<1,2,1+R7/7.5) -> 2 | S33: =IF(S7/7.5<1,2,1+S7/7.5) -> 2 | T33: =IF(T7/7.5<1,2,1+T7/7.5) -> 2 | U33: =IF(U7/7.5<1,2,1+U7/7.5) -> 2 | V33: =IF(V7/7.5<1,2,1+V7/7.5) -> 2 | W33: =IF(W7/7.5<1,2,1+W7/7.5) -> 2 | X33: =IF(X7/7.5<1,2,1+X7/7.5) -> 2 | Y33: =IF(Y7/7.5<1,2,1+Y7/7.5) -> 2 | ... AC33: =IF(AC7/7.5<1,2,1+AC7/7.5) -> 2 | AE33: =IF(AE7/7.5<1,2,1+AE7/7.5) -> 2 | AF33: =IF(AF7/7.5<1,2,1+AF7/7.5) -> 2 | AG33: =IF(AG7/7.5<1,2,1+AG7/7.5) -> 2 | AH33: =IF(AH7/7.5<1,2,1+AH7/7.5) -> 2 | AI33: =IF(AI7/7.5<1,2,1+AI7/7.5) -> 2 | AJ33: =IF(AJ7/7.5<1,2,1+AJ7/7.5) -> 2 | AK33: =IF(AK7/7.5<1,2,1+AK7/7.5) -> 2 | AL33: =IF(AL7/7.5<1,2,1+AL7/7.5) -> 2 | ... AP33: =IF(AP7/7.5<1,2,1+AP7/7.5) -> 2 | AR33: =IF(AR7/7.5<1,2,1+AR7/7.5) -> 2.3333333 | AS33: =IF(AS7/7.5<1,2,1+AS7/7.5) -> 2.3333333 | AT33: =IF(AT7/7.5<1,2,1+AT7/7.5) -> 2.3333333 | AU33: =IF(AU7/7.5<1,2,1+AU7/7.5) -> 2.3333333 | AV33: =IF(AV7/7.5<1,2,1+AV7/7.5) -> 2.3333333 | AW33: =IF(AW7/7.5<1,2,1+AW7/7.5) -> 2.3333333 | AX33: =IF(AX7/7.5<1,2,1+AX7/7.5) -> 2.3333333 | AY33: =IF(AY7/7.5<1,2,1+AY7/7.5) -> 2.3333333 | ... BC33: =IF(BC7/7.5<1,2,1+BC7/7.5) -> 2.3333333 | BE33: =IF(BE7/7.5<1,2,1+BE7/7.5) -> 2.3333333 | BF33: =IF(BF7/7.5<1,2,1+BF7/7.5) -> 2.3333333 | BG33: =IF(BG7/7.5<1,2,1+BG7/7.5) -> 2.3333333 | BH33: =IF(BH7/7.5<1,2,1+BH7/7.5) -> 2.3333333 | BI33: =IF(BI7/7.5<1,2,1+BI7/7.5) -> 2.3333333 | BJ33: =IF(BJ7/7.5<1,2,1+BJ7/7.5) -> 2.3333333 | BK33: =IF(BK7/7.5<1,2,1+BK7/7.5) -> 2.3333333 | BL33: =IF(BL7/7.5<1,2,1+BL7/7.5) -> 2.3333333 | ... BP33: =IF(BP7/7.5<1,2,1+BP7/7.5) -> 2.3333333
A34: 移行人員配置 | E34: =ROUNDUP(E9/6,0) -> 0 | F34: =(F9+F10)/6 -> 0 | G34: =(G9+G10)/6 -> 0 | H34: =(H9+H10)/6 -> 0 | I34: =(I9+I10)/6 -> 0 | J34: =(J9+J10)/6 -> 0.5 | K34: =(K9+K10)/6 -> 0.83333333 | L34: =(L9+L10)/6 -> 1.1666667 | M34: =(M9+M10)/6 -> 1.5 | ... P34: =(P9+P10)/6 -> 2.3333333 | R34: =ROUNDUP(R9/6,1) -> 2.4 | S34: =(S9+S10)/6 -> 3 | T34: =(T9+T10)/6 -> 3.1666667 | U34: =(U9+U10)/6 -> 3.3333333 | V34: =(V9+V10)/6 -> 3.5 | W34: =(W9+W10)/6 -> 3.6666667 | X34: =(X9+X10)/6 -> 3.8333333 | Y34: =(Y9+Y10)/6 -> 4 | Z34: =(Z9+Z10)/6 -> 4.1666667 | ... AC34: =(AC9+AC10)/6 -> 4.6666667 | AE34: =ROUNDUP(AE9/6,1) -> 2.5 | AF34: =(AF9+AF10)/6 -> 5 | AG34: =(AG9+AG10)/6 -> 5.1666667 | AH34: =(AH9+AH10)/6 -> 5.3333333 | AI34: =(AI9+AI10)/6 -> 5.5 | AJ34: =(AJ9+AJ10)/6 -> 5.6666667 | AK34: =(AK9+AK10)/6 -> 5.8333333 | AL34: =(AL9+AL10)/6 -> 6 | AM34: =(AM9+AM10)/6 -> 6.1666667 | ... AP34: =(AP9+AP10)/6 -> 6.6666667 | AR34: =ROUNDUP(AR9/6,1) -> 1.7 | AS34: =(AS9+AS10)/6 -> 3.3333333 | AT34: =(AT9+AT10)/6 -> 3.3333333 | AU34: =(AU9+AU10)/6 -> 3.3333333 | AV34: =(AV9+AV10)/6 -> 3.3333333 | AW34: =(AW9+AW10)/6 -> 3.3333333 | AX34: =(AX9+AX10)/6 -> 3.3333333 | AY34: =(AY9+AY10)/6 -> 3.3333333 | AZ34: =(AZ9+AZ10)/6 -> 3.3333333 | ... BC34: =(BC9+BC10)/6 -> 3.3333333 | BE34: =ROUNDUP(BE9/6,1) -> 1.7 | BF34: =(BF9+BF10)/6 -> 3.3333333 | BG34: =(BG9+BG10)/6 -> 3.3333333 | BH34: =(BH9+BH10)/6 -> 3.3333333 | BI34: =(BI9+BI10)/6 -> 3.3333333 | BJ34: =(BJ9+BJ10)/6 -> 3.3333333 | BK34: =(BK9+BK10)/6 -> 3.3333333 | BL34: =(BL9+BL10)/6 -> 3.3333333 | BM34: =(BM9+BM10)/6 -> 3.3333333 | ... BP34: =(BP9+BP10)/6 -> 3.3333333
A35: 移行就労支援員配置 | E35: =IF((E9+E10)/15<1,1,(E9+E10)/15) -> 1 | F35: =IF((F9+F10)/15<1,1,(F9+F10)/15) -> 1 | G35: =IF((G9+G10)/15<1,1,(G9+G10)/15) -> 1 | H35: =IF((H9+H10)/15<1,1,(H9+H10)/15) -> 1 | I35: =IF((I9+I10)/15<1,1,(I9+I10)/15) -> 1 | J35: =IF((J9+J10)/15<1,1,(J9+J10)/15) -> 1 | K35: =IF((K9+K10)/15<1,1,(K9+K10)/15) -> 1 | L35: =IF((L9+L10)/15<1,1,(L9+L10)/15) -> 1 | ... P35: =IF((P9+P10)/15<1,1,(P9+P10)/15) -> 1 | R35: =IF((R9+R10)/15<1,1,(R9+R10)/15) -> 1.0666667 | S35: =IF((S9+S10)/15<1,1,(S9+S10)/15) -> 1.2 | T35: =IF((T9+T10)/15<1,1,(T9+T10)/15) -> 1.2666667 | U35: =IF((U9+U10)/15<1,1,(U9+U10)/15) -> 1.3333333 | V35: =IF((V9+V10)/15<1,1,(V9+V10)/15) -> 1.4 | W35: =IF((W9+W10)/15<1,1,(W9+W10)/15) -> 1.4666667 | X35: =IF((X9+X10)/15<1,1,(X9+X10)/15) -> 1.5333333 | Y35: =IF((Y9+Y10)/15<1,1,(Y9+Y10)/15) -> 1.6 | ... AC35: =IF((AC9+AC10)/15<1,1,(AC9+AC10)/15) -> 1.8666667 | AE35: =IF((AE9+AE10)/15<1,1,(AE9+AE10)/15) -> 1.9333333 | AF35: =IF((AF9+AF10)/15<1,1,(AF9+AF10)/15) -> 2 | AG35: =IF((AG9+AG10)/15<1,1,(AG9+AG10)/15) -> 2.0666667 | AH35: =IF((AH9+AH10)/15<1,1,(AH9+AH10)/15) -> 2.1333333 | AI35: =IF((AI9+AI10)/15<1,1,(AI9+AI10)/15) -> 2.2 | AJ35: =IF((AJ9+AJ10)/15<1,1,(AJ9+AJ10)/15) -> 2.2666667 | AK35: =IF((AK9+AK10)/15<1,1,(AK9+AK10)/15) -> 2.3333333 | AL35: =IF((AL9+AL10)/15<1,1,(AL9+AL10)/15) -> 2.4 | ... AP35: =IF((AP9+AP10)/15<1,1,(AP9+AP10)/15) -> 2.6666667 | AR35: =IF((AR9+AR10)/15<1,1,(AR9+AR10)/15) -> 1.3333333 | AS35: =IF((AS9+AS10)/15<1,1,(AS9+AS10)/15) -> 1.3333333 | AT35: =IF((AT9+AT10)/15<1,1,(AT9+AT10)/15) -> 1.3333333 | AU35: =IF((AU9+AU10)/15<1,1,(AU9+AU10)/15) -> 1.3333333 | AV35: =IF((AV9+AV10)/15<1,1,(AV9+AV10)/15) -> 1.3333333 | AW35: =IF((AW9+AW10)/15<1,1,(AW9+AW10)/15) -> 1.3333333 | AX35: =IF((AX9+AX10)/15<1,1,(AX9+AX10)/15) -> 1.3333333 | AY35: =IF((AY9+AY10)/15<1,1,(AY9+AY10)/15) -> 1.3333333 | ... BC35: =IF((BC9+BC10)/15<1,1,(BC9+BC10)/15) -> 1.3333333 | BE35: =IF((BE9+BE10)/15<1,1,(BE9+BE10)/15) -> 1.3333333 | BF35: =IF((BF9+BF10)/15<1,1,(BF9+BF10)/15) -> 1.3333333 | BG35: =IF((BG9+BG10)/15<1,1,(BG9+BG10)/15) -> 1.3333333 | BH35: =IF((BH9+BH10)/15<1,1,(BH9+BH10)/15) -> 1.3333333 | BI35: =IF((BI9+BI10)/15<1,1,(BI9+BI10)/15) -> 1.3333333 | BJ35: =IF((BJ9+BJ10)/15<1,1,(BJ9+BJ10)/15) -> 1.3333333 | BK35: =IF((BK9+BK10)/15<1,1,(BK9+BK10)/15) -> 1.3333333 | BL35: =IF((BL9+BL10)/15<1,1,(BL9+BL10)/15) -> 1.3333333 | ... BP35: =IF((BP9+BP10)/15<1,1,(BP9+BP10)/15) -> 1.3333333
A36: 移行施設外支援配置 | E36: =IF(E10/6<1,1,E10/6) -> 1 | F36: =IF(F10/6<1,1,F10/6) -> 1 | G36: =IF(G10/6<1,1,G10/6) -> 1 | H36: =IF(H10/6<1,1,H10/6) -> 1 | I36: =IF(I10/6<1,1,I10/6) -> 1 | J36: =IF(J10/6<1,1,J10/6) -> 1 | K36: =IF(K10/6<1,1,K10/6) -> 1 | L36: =IF(L10/6<1,1,L10/6) -> 1 | ... P36: =IF(P10/6<1,1,P10/6) -> 1 | R36: =IF(R10/6<1,1,R10/6) -> 1 | S36: =IF(S10/6<1,1,S10/6) -> 1 | T36: =IF(T10/6<1,1,T10/6) -> 1 | U36: =IF(U10/6<1,1,U10/6) -> 1 | V36: =IF(V10/6<1,1,V10/6) -> 1 | W36: =IF(W10/6<1,1,W10/6) -> 1.1666667 | X36: =IF(X10/6<1,1,X10/6) -> 1.3333333 | Y36: =IF(Y10/6<1,1,Y10/6) -> 1.5 | ... AC36: =IF(AC10/6<1,1,AC10/6) -> 2.1666667 | AE36: =IF(AE10/6<1,1,AE10/6) -> 2.3333333 | AF36: =IF(AF10/6<1,1,AF10/6) -> 2.5 | AG36: =IF(AG10/6<1,1,AG10/6) -> 2.6666667 | AH36: =IF(AH10/6<1,1,AH10/6) -> 2.8333333 | AI36: =IF(AI10/6<1,1,AI10/6) -> 3 | AJ36: =IF(AJ10/6<1,1,AJ10/6) -> 3.1666667 | AK36: =IF(AK10/6<1,1,AK10/6) -> 3.3333333 | AL36: =IF(AL10/6<1,1,AL10/6) -> 3.5 | ... AP36: =IF(AP10/6<1,1,AP10/6) -> 4.1666667 | AR36: =IF(AR10/6<1,1,AR10/6) -> 1.6666667 | AS36: =IF(AS10/6<1,1,AS10/6) -> 1.6666667 | AT36: =IF(AT10/6<1,1,AT10/6) -> 1.6666667 | AU36: =IF(AU10/6<1,1,AU10/6) -> 1.6666667 | AV36: =IF(AV10/6<1,1,AV10/6) -> 1.6666667 | AW36: =IF(AW10/6<1,1,AW10/6) -> 1.6666667 | AX36: =IF(AX10/6<1,1,AX10/6) -> 1.6666667 | AY36: =IF(AY10/6<1,1,AY10/6) -> 1.6666667 | ... BC36: =IF(BC10/6<1,1,BC10/6) -> 1.6666667 | BE36: =IF(BE10/6<1,1,BE10/6) -> 1.6666667 | BF36: =IF(BF10/6<1,1,BF10/6) -> 1.6666667 | BG36: =IF(BG10/6<1,1,BG10/6) -> 1.6666667 | BH36: =IF(BH10/6<1,1,BH10/6) -> 1.6666667 | BI36: =IF(BI10/6<1,1,BI10/6) -> 1.6666667 | BJ36: =IF(BJ10/6<1,1,BJ10/6) -> 1.6666667 | BK36: =IF(BK10/6<1,1,BK10/6) -> 1.6666667 | BL36: =IF(BL10/6<1,1,BL10/6) -> 1.6666667 | ... BP36: =IF(BP10/6<1,1,BP10/6) -> 1.6666667
A38: 管理者 | E38: 210000 | F38: 210000 | G38: 210000 | H38: 250000 | I38: 250000 | J38: 250000 | K38: 250000 | L38: 250000 | M38: 250000 | N38: 250000 | O38: 250000 | P38: 250000 | R38: 250000 | S38: 250000 | T38: 250000 | U38: 250000 | V38: 250000 | W38: 250000 | X38: 250000 | Y38: 250000 | Z38: 250000 | AA38: 250000 | AB38: 250000 | AC38: 250000 | AE38: 300000 | AF38: 300000 | AG38: 300000 | AH38: 300000 | AI38: 300000 | AJ38: 300000 | AK38: 300000 | AL38: 300000 | AM38: 300000 | AN38: 300000 | AO38: 300000 | AP38: 300000 | AR38: 180000 | AS38: 180000 | AT38: 180000 | AU38: 180000 | AV38: 180000 | AW38: 180000 | AX38: 180000 | AY38: 180000 | AZ38: 180000 | BA38: 180000 | BB38: 180000 | BC38: 180000 | BE38: 180000 | BF38: 180000 | BG38: 180000 | BH38: 180000 | BI38: 180000 | BJ38: 180000 | BK38: 180000 | BL38: 180000 | BM38: 180000 | BN38: 180000 | BO38: 180000 | BP38: 180000
A39: サービス管理責任者 | J39: 100000 | K39: 100000 | L39: 200000 | M39: 200000 | N39: 200000 | O39: 200000 | P39: 200000 | R39: 210000 | S39: 210000 | T39: 210000 | U39: 210000 | V39: 210000 | W39: 210000 | X39: 210000 | Y39: 210000 | Z39: 210000 | AA39: 210000 | AB39: 210000 | AC39: 210000 | AE39: 300000 | AF39: 300000 | AG39: 300000 | AH39: 300000 | AI39: 300000 | AJ39: 300000 | AK39: 300000 | AL39: 300000 | AM39: 300000 | AN39: 300000 | AO39: 300000 | AP39: 300000
A40: 職業指導員 | J40: 180000 | K40: 180000 | L40: 180000 | M40: 180000 | N40: 180000 | O40: 180000 | P40: 180000 | R40: 200000 | S40: 200000 | T40: 200000 | U40: 200000 | V40: 200000 | W40: 200000 | X40: 200000 | Y40: 200000 | Z40: 200000 | AA40: 200000 | AB40: 200000 | AC40: 200000 | AE40: 250000 | AF40: 250000 | AG40: 250000 | AH40: 250000 | AI40: 250000 | AJ40: 250000 | AK40: 250000 | AL40: 250000 | AM40: 250000 | AN40: 250000 | AO40: 250000 | AP40: 250000 | AR40: 150000 | AS40: 150000 | AT40: 150000 | AU40: 150000 | AV40: 150000 | AW40: 150000 | AX40: 150000 | AY40: 150000 | AZ40: 150000 | BA40: 150000 | BB40: 150000 | BC40: 150000 | BE40: 150000 | BF40: 150000 | BG40: 150000 | BH40: 150000 | BI40: 150000 | BJ40: 150000 | BK40: 150000 | BL40: 150000 | BM40: 150000 | BN40: 150000 | BO40: 150000 | BP40: 150000
A41: 職業指導員 | J41: 120000 | K41: 120000 | L41: 180000 | M41: 180000 | N41: 180000 | O41: 180000 | P41: 180000 | R41: 200000 | S41: 200000 | T41: 200000 | U41: 200000 | V41: 200000 | W41: 200000 | X41: 200000 | Y41: 200000 | Z41: 200000 | AA41: 200000 | AB41: 200000 | AC41: 200000 | AE41: 250000 | AF41: 250000 | AG41: 250000 | AH41: 250000 | AI41: 250000 | AJ41: 250000 | AK41: 250000 | AL41: 250000 | AM41: 250000 | AN41: 250000 | AO41: 250000 | AP41: 250000 | AR41: 180000 | AS41: 180000 | AT41: 180000 | AU41: 180000 | AV41: 180000 | AW41: 180000 | AX41: 180000 | AY41: 180000 | AZ41: 180000 | BA41: 180000 | BB41: 180000 | BC41: 180000 | BE41: 180000 | BF41: 180000 | BG41: 180000 | BH41: 180000 | BI41: 180000 | BJ41: 180000 | BK41: 180000 | BL41: 180000 | BM41: 180000 | BN41: 180000 | BO41: 180000 | BP41: 180000
A42: 職業指導員 | L42: 180000 | M42: 180000 | N42: 180000 | O42: 180000 | P42: 180000 | R42: 200000 | S42: 200000 | T42: 200000 | U42: 200000 | V42: 200000 | W42: 200000 | X42: 200000 | Y42: 200000 | Z42: 200000 | AA42: 200000 | AB42: 200000 | AC42: 200000 | AE42: 250000 | AF42: 250000 | AG42: 250000 | AH42: 250000 | AI42: 250000 | AJ42: 250000 | AK42: 250000 | AL42: 250000 | AM42: 250000 | AN42: 250000 | AO42: 250000 | AP42: 250000 | AR42: 180000 | AS42: 180000 | AT42: 180000 | AU42: 180000 | AV42: 180000 | AW42: 180000 | AX42: 180000 | AY42: 180000 | AZ42: 180000 | BA42: 180000 | BB42: 180000 | BC42: 180000 | BE42: 180000 | BF42: 180000 | BG42: 180000 | BH42: 180000 | BI42: 180000 | BJ42: 180000 | BK42: 180000 | BL42: 180000 | BM42: 180000 | BN42: 180000 | BO42: 180000 | BP42: 180000
A43: 生活支援員 | J43: 120000 | K43: 120000 | L43: 180000 | M43: 180000 | N43: 180000 | O43: 180000 | P43: 180000 | R43: 200000 | S43: 200000 | T43: 200000 | U43: 200000 | V43: 200000 | W43: 200000 | X43: 200000 | Y43: 200000 | Z43: 200000 | AA43: 200000 | AB43: 200000 | AC43: 200000 | AE43: 250000 | AF43: 250000 | AG43: 250000 | AH43: 250000 | AI43: 250000 | AJ43: 250000 | AK43: 250000 | AL43: 250000 | AM43: 250000 | AN43: 250000 | AO43: 250000 | AP43: 250000 | AR43: 180000 | AS43: 180000 | AT43: 180000 | AU43: 180000 | AV43: 180000 | AW43: 180000 | AX43: 180000 | AY43: 180000 | AZ43: 180000 | BA43: 180000 | BB43: 180000 | BC43: 180000 | BE43: 180000 | BF43: 180000 | BG43: 180000 | BH43: 180000 | BI43: 180000 | BJ43: 180000 | BK43: 180000 | BL43: 180000 | BM43: 180000 | BN43: 180000 | BO43: 180000 | BP43: 180000
A44: 支援員等 | J44: 100000 | K44: 100000 | L44: 180000 | M44: 180000 | N44: 180000 | O44: 180000 | P44: 180000 | R44: 200000 | S44: 200000 | T44: 200000 | U44: 200000 | V44: 200000 | W44: 200000 | X44: 200000 | Y44: 200000 | Z44: 200000 | AA44: 200000 | AB44: 200000 | AC44: 200000 | AE44: 250000 | AF44: 250000 | AG44: 250000 | AH44: 250000 | AI44: 250000 | AJ44: 250000 | AK44: 250000 | AL44: 250000 | AM44: 250000 | AN44: 250000 | AO44: 250000 | AP44: 250000 | AR44: 150000 | AS44: 150000 | AT44: 150000 | AU44: 150000 | AV44: 150000 | AW44: 150000 | AX44: 150000 | AY44: 150000 | AZ44: 150000 | BA44: 150000 | BB44: 150000 | BC44: 150000 | BE44: 150000 | BF44: 150000 | BG44: 150000 | BH44: 150000 | BI44: 150000 | BJ44: 150000 | BK44: 150000 | BL44: 150000 | BM44: 150000 | BN44: 150000 | BO44: 150000 | BP44: 150000
A45: 支援員等 | O45: 100000 | P45: 100000 | R45: 100000 | S45: 100000 | T45: 100000 | U45: 100000 | V45: 100000 | W45: 100000 | X45: 100000 | Y45: 100000 | Z45: 100000 | AA45: 100000 | AB45: 100000 | AC45: 100000 | AE45: 100000 | AF45: 100000 | AG45: 100000 | AH45: 100000 | AI45: 100000 | AJ45: 100000 | AK45: 100000 | AL45: 100000 | AM45: 100000 | AN45: 100000 | AO45: 100000 | AP45: 100000 | AR45: 250000 | AS45: 250000 | AT45: 250000 | AU45: 250000 | AV45: 250000 | AW45: 250000 | AX45: 250000 | AY45: 250000 | AZ45: 250000 | BA45: 250000 | BB45: 250000 | BC45: 250000 | BE45: 250000 | BF45: 250000 | BG45: 250000 | BH45: 250000 | BI45: 250000 | BJ45: 250000 | BK45: 250000 | BL45: 250000 | BM45: 250000 | BN45: 250000 | BO45: 250000 | BP45: 250000
A46: 支援員等 | AE46: 130000 | AF46: 130000 | AG46: 130000 | AH46: 130000 | AI46: 130000 | AJ46: 130000 | AK46: 130000 | AL46: 130000 | AM46: 130000 | AN46: 130000 | AO46: 130000 | AP46: 130000 | AR46: 180000 | AS46: 180000 | AT46: 180000 | AU46: 180000 | AV46: 180000 | AW46: 180000 | AX46: 180000 | AY46: 180000 | AZ46: 180000 | BA46: 180000 | BB46: 180000 | BC46: 180000 | BE46: 180000 | BF46: 180000 | BG46: 180000 | BH46: 180000 | BI46: 180000 | BJ46: 180000 | BK46: 180000 | BL46: 180000 | BM46: 180000 | BN46: 180000 | BO46: 180000 | BP46: 180000
A47: 支援員等 | AR47: 180000 | AS47: 180000 | AT47: 180000 | AU47: 180000 | AV47: 180000 | AW47: 180000 | AX47: 180000 | AY47: 180000 | AZ47: 180000 | BA47: 180000 | BB47: 180000 | BC47: 180000 | BE47: 180000 | BF47: 180000 | BG47: 180000 | BH47: 180000 | BI47: 180000 | BJ47: 180000 | BK47: 180000 | BL47: 180000 | BM47: 180000 | BN47: 180000 | BO47: 180000 | BP47: 180000
A48: 就労支援員 | J48: 270000 | K48: 270000 | L48: 270000 | M48: 270000 | N48: 270000 | O48: 270000 | P48: 270000 | R48: 270000 | S48: 270000 | T48: 270000 | U48: 270000 | V48: 270000 | W48: 270000 | X48: 270000 | Y48: 270000 | Z48: 270000 | AA48: 270000 | AB48: 270000 | AC48: 270000 | AE48: 270000 | AF48: 270000 | AG48: 270000 | AH48: 270000 | AI48: 270000 | AJ48: 270000 | AK48: 270000 | AL48: 270000 | AM48: 270000 | AN48: 270000 | AO48: 270000 | AP48: 270000 | AR48: 250000 | AS48: 250000 | AT48: 250000 | AU48: 250000 | AV48: 250000 | AW48: 250000 | AX48: 250000 | AY48: 250000 | AZ48: 250000 | BA48: 250000 | BB48: 250000 | BC48: 250000 | BE48: 250000 | BF48: 250000 | BG48: 250000 | BH48: 250000 | BI48: 250000 | BJ48: 250000 | BK48: 250000 | BL48: 250000 | BM48: 250000 | BN48: 250000 | BO48: 250000 | BP48: 250000
A49: 就労支援員 | J49: 50000 | K49: 50000 | L49: 150000 | M49: 150000 | N49: 150000 | O49: 150000 | P49: 150000 | R49: 180000 | S49: 180000 | T49: 180000 | U49: 180000 | V49: 180000 | W49: 180000 | X49: 180000 | Y49: 180000 | Z49: 180000 | AA49: 180000 | AB49: 180000 | AC49: 180000 | AE49: 200000 | AF49: 200000 | AG49: 200000 | AH49: 200000 | AI49: 200000 | AJ49: 200000 | AK49: 200000 | AL49: 200000 | AM49: 200000 | AN49: 200000 | AO49: 200000 | AP49: 200000 | AR49: 300000 | AS49: 300000 | AT49: 300000 | AU49: 300000 | AV49: 300000 | AW49: 300000 | AX49: 300000 | AY49: 300000 | AZ49: 300000 | BA49: 300000 | BB49: 300000 | BC49: 300000 | BE49: 300000 | BF49: 300000 | BG49: 300000 | BH49: 300000 | BI49: 300000 | BJ49: 300000 | BK49: 300000 | BL49: 300000 | BM49: 300000 | BN49: 300000 | BO49: 300000 | BP49: 300000
A50: 就労支援員 | AR50: 300000 | AS50: 300000 | AT50: 300000 | AU50: 300000 | AV50: 300000 | AW50: 300000 | AX50: 300000 | AY50: 300000 | AZ50: 300000 | BA50: 300000 | BB50: 300000 | BC50: 300000 | BE50: 300000 | BF50: 300000 | BG50: 300000 | BH50: 300000 | BI50: 300000 | BJ50: 300000 | BK50: 300000 | BL50: 300000 | BM50: 300000 | BN50: 300000 | BO50: 300000 | BP50: 300000
AR51: 250000 | AS51: 250000 | AT51: 250000 | AU51: 250000 | AV51: 250000 | AW51: 250000 | AX51: 250000 | AY51: 250000 | AZ51: 250000 | BA51: 250000 | BB51: 250000 | BC51: 250000 | BE51: 250000 | BF51: 250000 | BG51: 250000 | BH51: 250000 | BI51: 250000 | BJ51: 250000 | BK51: 250000 | BL51: 250000 | BM51: 250000 | BN51: 250000 | BO51: 250000 | BP51: 250000
AE52: 180000 | AF52: 180000 | AG52: 180000 | AH52: 180000 | AI52: 180000 | AJ52: 180000 | AK52: 180000 | AL52: 180000 | AM52: 180000 | AN52: 180000 | AO52: 180000 | AP52: 180000 | AR52: 180000 | AS52: 180000 | AT52: 180000 | AU52: 180000 | AV52: 180000 | AW52: 180000 | AX52: 180000 | AY52: 180000 | AZ52: 180000 | BA52: 180000 | BB52: 180000 | BC52: 180000 | BE52: 180000 | BF52: 180000 | BG52: 180000 | BH52: 180000 | BI52: 180000 | BJ52: 180000 | BK52: 180000 | BL52: 180000 | BM52: 180000 | BN52: 180000 | BO52: 180000 | BP52: 180000
A53: 賞与 | J53: 300000 | P53: 1000000 | W53: 1500000 | AC53: 2000000 | AJ53: 1500000 | AP53: 2000000 | AW53: 2000000 | BC53: 3000000 | BJ53: 2000000 | BP53: 3000000
A54: 人件費合計 | E54: =SUM(E38:E52) -> 210000 | F54: =SUM(F38:F52) -> 210000 | G54: =SUM(G38:G52) -> 210000 | H54: =SUM(H38:H52) -> 250000 | I54: =SUM(I38:I52) -> 250000 | J54: =SUM(J38:J52) -> 1190000 | K54: =SUM(K38:K52) -> 1190000 | L54: =SUM(L38:L52) -> 1770000 | ... P54: =SUM(P38:P52) -> 1870000 | R54: =SUM(R38:R52) -> 2010000 | S54: =SUM(S38:S52) -> 2010000 | T54: =SUM(T38:T52) -> 2010000 | U54: =SUM(U38:U52) -> 2010000 | V54: =SUM(V38:V52) -> 2010000 | W54: =SUM(W38:W52) -> 2010000 | X54: =SUM(X38:X52) -> 2010000 | Y54: =SUM(Y38:Y52) -> 2010000 | ... AC54: =SUM(AC38:AC52) -> 2010000 | AE54: =SUM(AE38:AE52) -> 2730000 | AF54: =SUM(AF38:AF52) -> 2730000 | AG54: =SUM(AG38:AG52) -> 2730000 | AH54: =SUM(AH38:AH52) -> 2730000 | AI54: =SUM(AI38:AI52) -> 2730000 | AJ54: =SUM(AJ38:AJ52) -> 2730000 | AK54: =SUM(AK38:AK52) -> 2730000 | AL54: =SUM(AL38:AL52) -> 2730000 | ... AP54: =SUM(AP38:AP52) -> 2730000 | AR54: =SUM(AR38:AR52) -> 2910000 | AS54: =SUM(AS38:AS52) -> 2910000 | AT54: =SUM(AT38:AT52) -> 2910000 | AU54: =SUM(AU38:AU52) -> 2910000 | AV54: =SUM(AV38:AV52) -> 2910000 | AW54: =SUM(AW38:AW52) -> 2910000 | AX54: =SUM(AX38:AX52) -> 2910000 | AY54: =SUM(AY38:AY52) -> 2910000 | ... BC54: =SUM(BC38:BC52) -> 2910000 | BE54: =SUM(BE38:BE52) -> 2910000 | BF54: =SUM(BF38:BF52) -> 2910000 | BG54: =SUM(BG38:BG52) -> 2910000 | BH54: =SUM(BH38:BH52) -> 2910000 | BI54: =SUM(BI38:BI52) -> 2910000 | BJ54: =SUM(BJ38:BJ52) -> 2910000 | BK54: =SUM(BK38:BK52) -> 2910000 | BL54: =SUM(BL38:BL52) -> 2910000 | ... BP54: =SUM(BP38:BP52) -> 2910000
A55: 社会保険 | E55: =E54*0.1 -> 21000 | F55: =F54*0.1 -> 21000 | G55: =G54*0.1 -> 21000 | H55: =H54*0.1 -> 25000 | I55: =I54*0.1 -> 25000 | J55: =J54*0.1 -> 119000 | K55: =K54*0.1 -> 119000 | L55: =L54*0.1 -> 177000 | ... P55: =P54*0.1 -> 187000 | R55: =R54*0.1 -> 201000 | S55: =S54*0.1 -> 201000 | T55: =T54*0.1 -> 201000 | U55: =U54*0.1 -> 201000 | V55: =V54*0.1 -> 201000 | W55: =W54*0.1 -> 201000 | X55: =X54*0.1 -> 201000 | Y55: =Y54*0.1 -> 201000 | ... AC55: =AC54*0.1 -> 201000 | AE55: =AE54*0.1 -> 273000 | AF55: =AF54*0.1 -> 273000 | AG55: =AG54*0.1 -> 273000 | AH55: =AH54*0.1 -> 273000 | AI55: =AI54*0.1 -> 273000 | AJ55: =AJ54*0.1 -> 273000 | AK55: =AK54*0.1 -> 273000 | AL55: =AL54*0.1 -> 273000 | ... AP55: =AP54*0.1 -> 273000 | AR55: =AR54*0.1 -> 291000 | AS55: =AS54*0.1 -> 291000 | AT55: =AT54*0.1 -> 291000 | AU55: =AU54*0.1 -> 291000 | AV55: =AV54*0.1 -> 291000 | AW55: =AW54*0.1 -> 291000 | AX55: =AX54*0.1 -> 291000 | AY55: =AY54*0.1 -> 291000 | ... BC55: =BC54*0.1 -> 291000 | BE55: =BE54*0.1 -> 291000 | BF55: =BF54*0.1 -> 291000 | BG55: =BG54*0.1 -> 291000 | BH55: =BH54*0.1 -> 291000 | BI55: =BI54*0.1 -> 291000 | BJ55: =BJ54*0.1 -> 291000 | BK55: =BK54*0.1 -> 291000 | BL55: =BL54*0.1 -> 291000 | ... BP55: =BP54*0.1 -> 291000
A56: 人件費総計 | E56: =E54+E55 -> 231000 | F56: =F54+F55 -> 231000 | G56: =G54+G55 -> 231000 | H56: =H54+H55 -> 275000 | I56: =I54+I55 -> 275000 | J56: =J54+J55 -> 1309000 | K56: =K54+K55 -> 1309000 | L56: =L54+L55 -> 1947000 | ... P56: =P54+P55 -> 2057000 | R56: =R54+R55 -> 2211000 | S56: =S54+S55 -> 2211000 | T56: =T54+T55 -> 2211000 | U56: =U54+U55 -> 2211000 | V56: =V54+V55 -> 2211000 | W56: =W54+W55 -> 2211000 | X56: =X54+X55 -> 2211000 | Y56: =Y54+Y55 -> 2211000 | ... AC56: =AC54+AC55 -> 2211000 | AE56: =AE54+AE55 -> 3003000 | AF56: =AF54+AF55 -> 3003000 | AG56: =AG54+AG55 -> 3003000 | AH56: =AH54+AH55 -> 3003000 | AI56: =AI54+AI55 -> 3003000 | AJ56: =AJ54+AJ55 -> 3003000 | AK56: =AK54+AK55 -> 3003000 | AL56: =AL54+AL55 -> 3003000 | ... AP56: =AP54+AP55 -> 3003000 | AR56: =AR54+AR55 -> 3201000 | AS56: =AS54+AS55 -> 3201000 | AT56: =AT54+AT55 -> 3201000 | AU56: =AU54+AU55 -> 3201000 | AV56: =AV54+AV55 -> 3201000 | AW56: =AW54+AW55 -> 3201000 | AX56: =AX54+AX55 -> 3201000 | AY56: =AY54+AY55 -> 3201000 | ... BC56: =BC54+BC55 -> 3201000 | BE56: =BE54+BE55 -> 3201000 | BF56: =BF54+BF55 -> 3201000 | BG56: =BG54+BG55 -> 3201000 | BH56: =BH54+BH55 -> 3201000 | BI56: =BI54+BI55 -> 3201000 | BJ56: =BJ54+BJ55 -> 3201000 | BK56: =BK54+BK55 -> 3201000 | BL56: =BL54+BL55 -> 3201000 | ... BP56: =BP54+BP55 -> 3201000

Sheet ACT川崎
B1: シェル 川崎 利用者予定数及び人員配置等
B2: 令和３年 | E2: 月額工賃 | G2: 25000 | W2: 令和４年 | Y2: 30000 | AO2: 月額工賃 | AQ2: 40000
E3: 1月 | F3: 2月 | G3: 3月 | H3: 4月 | I3: 5月 | J3: 6月 | K3: 7月 | L3: 8月 | M3: 9月 | N3: 10月 | O3: 11月 | P3: 12月 | W3: 1月 | X3: 2月 | Y3: 3月 | Z3: 4月 | AA3: 5月 | AB3: 6月 | AC3: 7月 | AD3: 8月 | AE3: 9月 | AF3: 10月 | AG3: 11月 | AH3: 12月 | AO3: 1月 | AP3: 2月 | AQ3: 3月 | AR3: 4月 | AS3: 5月 | AT3: 6月 | AU3: 7月 | AV3: 8月 | AW3: 9月 | AX3: 10月 | AY3: 11月 | AZ3: 12月
B4: 稼働日 | E4: 22 | F4: 20 | G4: 23 | H4: 22 | I4: 23 | J4: 22 | K4: 23 | L4: 22 | M4: 22 | N4: 23 | O4: 22 | P4: 22 | W4: 22 | X4: 20 | Y4: 23 | Z4: 22 | AA4: 23 | AB4: 22 | AC4: 23 | AD4: 22 | AE4: 22 | AF4: 23 | AG4: 22 | AH4: 22
B5: 稼働率 | E5: 0.8 | F5: 0.8 | G5: 0.8 | H5: 0.8 | I5: 0.8 | J5: 0.8 | K5: 0.8 | L5: 0.8 | M5: 0.8 | N5: 0.8 | O5: 0.8 | P5: 0.8 | W5: 0.8 | X5: 0.8 | Y5: 0.8 | Z5: 0.8 | AA5: 0.8 | AB5: 0.8 | AC5: 0.8 | AD5: 0.8 | AE5: 0.8 | AF5: 0.8 | AG5: 0.8 | AH5: 0.8 | AO5: 0.8 | AP5: 0.8 | AQ5: 0.8 | AR5: 0.8 | AS5: 0.8 | AT5: 0.8 | AU5: 0.8 | AV5: 0.8 | AW5: 0.8 | AX5: 0.8 | AY5: 0.8 | AZ5: 0.8
B6: 就労B利用者数 | AO6: 18 | AP6: 18 | AQ6: 18 | AR6: 20 | AS6: 20 | AT6: 20 | AU6: 20 | AV6: 20 | AW6: 20 | AX6: 20 | AY6: 20 | AZ6: 20
B7: 就労B施設外利用者数 | U7: シェル（川崎） | AO7: 12 | AP7: 12 | AQ7: 14 | AR7: 14 | AS7: 14 | AT7: 14 | AU7: 16 | AV7: 16 | AW7: 16 | AX7: 16 | AY7: 18 | AZ7: 18
B8: B合計 | E8: =SUM(E6:E7) -> 0 | F8: =SUM(F6:F7) -> 0 | G8: =SUM(G6:G7) -> 0 | H8: =SUM(H6:H7) -> 0 | I8: =SUM(I6:I7) -> 0 | J8: =SUM(J6:J7) -> 0 | K8: =SUM(K6:K7) -> 0 | L8: =SUM(L6:L7) -> 0 | ... P8: =SUM(P6:P7) -> 0 | W8: =SUM(W6:W7) -> 0 | X8: =SUM(X6:X7) -> 0 | Y8: =SUM(Y6:Y7) -> 0 | Z8: =SUM(Z6:Z7) -> 0 | AA8: =SUM(AA6:AA7) -> 0 | AB8: =SUM(AB6:AB7) -> 0 | AC8: =SUM(AC6:AC7) -> 0 | AD8: =SUM(AD6:AD7) -> 0 | ... AH8: =SUM(AH6:AH7) -> 0
B9: 就労移行利用者数 | H9: 6 | I9: 8 | J9: 9 | K9: 10 | L9: 11 | M9: 12 | N9: 13 | O9: 14 | P9: 15 | W9: 15 | X9: 15 | Y9: 15 | Z9: 15 | AA9: 15 | AB9: 15 | AC9: 15 | AD9: 15 | AE9: 15 | AF9: 15 | AG9: 15 | AH9: 15
B10: 就労移行施設外利用者数 | W10: 2 | X10: 3 | Y10: 4 | Z10: 5 | AA10: 6 | AB10: 7 | AC10: 8 | AD10: 9 | AE10: 10 | AF10: 11 | AG10: 12 | AH10: 13
B11: 移行合計 | E11: =SUM(E9:E10) -> 0 | F11: =SUM(F9:F10) -> 0 | G11: =SUM(G9:G10) -> 0 | H11: =SUM(H9:H10) -> 6 | I11: =SUM(I9:I10) -> 8 | J11: =SUM(J9:J10) -> 9 | K11: =SUM(K9:K10) -> 10 | L11: =SUM(L9:L10) -> 11 | ... P11: =SUM(P9:P10) -> 15 | W11: =SUM(W9:W10) -> 17 | X11: =SUM(X9:X10) -> 18 | Y11: =SUM(Y9:Y10) -> 19 | Z11: =SUM(Z9:Z10) -> 20 | AA11: =SUM(AA9:AA10) -> 21 | AB11: =SUM(AB9:AB10) -> 22 | AC11: =SUM(AC9:AC10) -> 23 | AD11: =SUM(AD9:AD10) -> 24 | ... AH11: =SUM(AH9:AH10) -> 28
B12: 合計人数 | E12: =E8:F8+E11 -> 0 | F12: =F8:G8+F11 -> 0 | G12: =G8:H8+G11 -> 0 | H12: =H8:I8+H11 -> 6 | I12: =I8:J8+I11 -> 8 | J12: =J8:K8+J11 -> 9 | K12: =K8:L8+K11 -> 10 | L12: =L8:M8+L11 -> 11 | ... P12: =P8:Q8+P11 -> 15 | W12: =W8:X8+W11 -> 17 | X12: =X8:Y8+X11 -> 18 | Y12: =Y8:Z8+Y11 -> 19 | Z12: =Z8:AA8+Z11 -> 20 | AA12: =AA8:AB8+AA11 -> 21 | AB12: =AB8:AC8+AB11 -> 22 | AC12: =AC8:AD8+AC11 -> 23 | AD12: =AD8:AE8+AD11 -> 24 | ... AH12: =AH8:AI8+AH11 -> 28 | AO12: =$AQ$2*(AO6+AO7) -> 1200000 | AP12: =$AQ$2*(AP6+AP7) -> 1200000 | AQ12: =$AQ$2*(AQ6+AQ7) -> 1280000 | AR12: =$AQ$2*(AR6+AR7) -> 1360000 | AS12: =$AQ$2*(AS6+AS7) -> 1360000 | AT12: =$AQ$2*(AT6+AT7) -> 1360000 | AU12: =$AQ$2*(AU6+AU7) -> 1440000 | AV12: =$AQ$2*(AV6+AV7) -> 1440000 | ... AZ12: =$AQ$2*(AZ6+AZ7) -> 1520000
B14: B通常給付金 | E14: =ROUNDDOWN(E6*E23*E4*E5,-2) -> 0 | F14: =ROUNDDOWN(F6*F23*F4*F5,-2) -> 0 | G14: =ROUNDDOWN(G6*G23*G4*G5,-2) -> 0 | H14: =ROUNDDOWN(H6*H23*H4*H5,-2) -> 0 | I14: =ROUNDDOWN(I6*I23*I4*I5,-2) -> 0 | J14: =ROUNDDOWN(J6*J23*J4*J5,-2) -> 0 | K14: =ROUNDDOWN(K6*K23*K4*K5,-2) -> 0 | L14: =ROUNDDOWN(L6*L23*L4*L5,-2) -> 0 | ... P14: =ROUNDDOWN(P6*P23*P4*P5,-2) -> 0 | U14: シェル（川崎） | W14: =ROUNDDOWN(W6*W23*W4*W5,-2) -> 0 | X14: =ROUNDDOWN(X6*X23*X4*X5,-2) -> 0 | Y14: =ROUNDDOWN(Y6*Y23*Y4*Y5,-2) -> 0 | Z14: =ROUNDDOWN(Z6*Z23*Z4*Z5,-2) -> 0 | AA14: =ROUNDDOWN(AA6*AA23*AA4*AA5,-2) -> 0 | AB14: =ROUNDDOWN(AB6*AB23*AB4*AB5,-2) -> 0 | AC14: =ROUNDDOWN(AC6*AC23*AC4*AC5,-2) -> 0 | AD14: =ROUNDDOWN(AD6*AD23*AD4*AD5,-2) -> 0 | ... AH14: =ROUNDDOWN(AH6*AH23*AH4*AH5,-2) -> 0 | AO14: =ROUND((AO6*(AO23+AO27+AO28*0.6)*23*AO5),-2) -> 2352800 | AP14: =ROUND((AP6*(AP23+AP27+AP28*0.6)*23*AP5),-2) -> 2352800 | AQ14: =ROUND((AQ6*(AQ23+AQ27+AQ28*0.6)*23*AQ5),-2) -> 2352800 | AR14: =ROUND((AR6*(AR23+AR27+AR28*0.6)*23*AR5),-2) -> 2614300 | AS14: =ROUND((AS6*(AS23+AS27+AS28*0.6)*23*AS5),-2) -> 2614300 | AT14: =ROUND((AT6*(AT23+AT27+AT28*0.6)*23*AT5),-2) -> 2614300 | AU14: =ROUND((AU6*(AU23+AU27+AU28*0.6)*23*AU5),-2) -> 2614300 | AV14: =ROUND((AV6*(AV23+AV27+AV28*0.6)*23*AV5),-2) -> 2614300 | ... AZ14: =ROUND((AZ6*(AZ23+AZ27+AZ28*0.6)*23*AZ5),-2) -> 2614300
B15: B施設外給付金 | E15: =ROUNDDOWN(E7*E24*E4*E29,-2) -> 0 | F15: =F7*F24*F4*F29 -> 0 | G15: =G7*G24*G4*G29 -> 0 | H15: =H7*H24*H4*H29 -> 0 | I15: =I7*I24*I4*I29 -> 0 | J15: =J7*J24*J4*J29 -> 0 | K15: =K7*K24*K4*K29 -> 0 | L15: =L7*L24*L4*L29 -> 0 | M15: =M7*M24*M4*M29 -> 0 | ... P15: =P7*P24*P4*P29 -> 0 | W15: =ROUNDDOWN(W7*W24*W4*W29,-2) -> 0 | X15: =X7*X24*X4*X29 -> 0 | Y15: =Y7*Y24*Y4*Y29 -> 0 | Z15: =Z7*Z24*Z4*Z29 -> 0 | AA15: =AA7*AA24*AA4*AA29 -> 0 | AB15: =AB7*AB24*AB4*AB29 -> 0 | AC15: =AC7*AC24*AC4*AC29 -> 0 | AD15: =AD7*AD24*AD4*AD29 -> 0 | AE15: =AE7*AE24*AE4*AE29 -> 0 | ... AH15: =AH7*AH24*AH4*AH29 -> 0 | AO15: =ROUND((AO7*(AO27+AO24+AO28*0.6)*23*AO29),-2) -> 1677500 | AP15: =ROUND((AP7*(AP27+AP24+AP28*0.6)*23*AP29),-2) -> 1677500 | AQ15: =ROUND((AQ7*(AQ27+AQ24+AQ28*0.6)*23*AQ29),-2) -> 1957100 | AR15: =ROUND((AR7*(AR27+AR24+AR28*0.6)*23*AR29),-2) -> 1957100 | AS15: =ROUND((AS7*(AS27+AS24+AS28*0.6)*23*AS29),-2) -> 1957100 | AT15: =ROUND((AT7*(AT27+AT24+AT28*0.6)*23*AT29),-2) -> 1957100 | AU15: =ROUND((AU7*(AU27+AU24+AU28*0.6)*23*AU29),-2) -> 2236700 | AV15: =ROUND((AV7*(AV27+AV24+AV28*0.6)*23*AV29),-2) -> 2236700 | ... AZ15: =ROUND((AZ7*(AZ27+AZ24+AZ28*0.6)*23*AZ29),-2) -> 2516300
B16: B加算 | E16: =ROUNDDOWN(((E6+E7)*(E27+E28*0.8))*E4,-2) -> 0 | F16: =ROUNDDOWN(((F6+F7)*(F27+F28*0.8))*F4,-2) -> 0 | G16: =ROUNDDOWN(((G6+G7)*(G27+G28*0.8))*G4,-2) -> 0 | H16: =ROUNDDOWN(((H6+H7)*(H27+H28*0.8))*H4,-2) -> 0 | I16: =ROUNDDOWN(((I6+I7)*(I27+I28*0.8))*I4,-2) -> 0 | J16: =ROUNDDOWN(((J6+J7)*(J27+J28*0.8))*J4,-2) -> 0 | K16: =ROUNDDOWN(((K6+K7)*(K27+K28*0.8))*K4,-2) -> 0 | L16: =ROUNDDOWN(((L6+L7)*(L27+L28*0.8))*L4,-2) -> 0 | ... P16: =ROUNDDOWN(((P6+P7)*(P27+P28*0.8))*P4,-2) -> 0 | W16: =ROUNDDOWN(((W6+W7)*(W27+W28*0.8))*W4,-2) -> 0 | X16: =ROUNDDOWN(((X6+X7)*(X27+X28*0.8))*X4,-2) -> 0 | Y16: =ROUNDDOWN(((Y6+Y7)*(Y27+Y28*0.8))*Y4,-2) -> 0 | Z16: =ROUNDDOWN(((Z6+Z7)*(Z27+Z28*0.8))*Z4,-2) -> 0 | AA16: =ROUNDDOWN(((AA6+AA7)*(AA27+AA28*0.8))*AA4,-2) -> 0 | AB16: =ROUNDDOWN(((AB6+AB7)*(AB27+AB28*0.8))*AB4,-2) -> 0 | AC16: =ROUNDDOWN(((AC6+AC7)*(AC27+AC28*0.8))*AC4,-2) -> 0 | AD16: =ROUNDDOWN(((AD6+AD7)*(AD27+AD28*0.8))*AD4,-2) -> 0 | ... AH16: =ROUNDDOWN(((AH6+AH7)*(AH27+AH28*0.8))*AH4,-2) -> 0
B17: 移行通常給付金 | E17: =ROUNDDOWN(E9*E25*E4*E5,-2) -> 0 | F17: =ROUNDDOWN(F9*F25*F4*F5,-2) -> 0 | G17: =ROUNDDOWN(G9*G25*G4*G5,-2) -> 0 | H17: =ROUNDDOWN(H9*H25*H4*H5,-2) -> 853200 | I17: =ROUNDDOWN(I9*I25*I4*I5,-2) -> 1189300 | J17: =ROUNDDOWN(J9*J25*J4*J5,-2) -> 1279800 | K17: =ROUNDDOWN(K9*K25*K4*K5,-2) -> 1486700 | L17: =ROUNDDOWN(L9*L25*L4*L5,-2) -> 1564200 | ... P17: =ROUNDDOWN(P9*P25*P4*P5,-2) -> 2133100 | W17: =ROUNDDOWN(W9*W25*W4*W5,-2) -> 2133100 | X17: =ROUNDDOWN(X9*X25*X4*X5,-2) -> 1939200 | Y17: =ROUNDDOWN(Y9*Y25*Y4*Y5,-2) -> 2230000 | Z17: =ROUNDDOWN(Z9*Z25*Z4*Z5,-2) -> 2133100 | AA17: =ROUNDDOWN(AA9*AA25*AA4*AA5,-2) -> 2230000 | AB17: =ROUNDDOWN(AB9*AB25*AB4*AB5,-2) -> 2133100 | AC17: =ROUNDDOWN(AC9*AC25*AC4*AC5,-2) -> 2230000 | AD17: =ROUNDDOWN(AD9*AD25*AD4*AD5,-2) -> 2133100 | ... AH17: =ROUNDDOWN(AH9*AH25*AH4*AH5,-2) -> 2133100
B18: 移行施設外給付金 | E18: =ROUNDDOWN(E10*E26*E4*E5,-2) -> 0 | F18: =ROUNDDOWN(F10*F26*F4*F5,-2) -> 0 | G18: =ROUNDDOWN(G10*G26*G4*G5,-2) -> 0 | H18: =ROUNDDOWN(H10*H26*H4*H5,-2) -> 0 | I18: =ROUNDDOWN(I10*I26*I4*I5,-2) -> 0 | J18: =ROUNDDOWN(J10*J26*J4*J5,-2) -> 0 | K18: =ROUNDDOWN(K10*K26*K4*K5,-2) -> 0 | L18: =ROUNDDOWN(L10*L26*L4*L5,-2) -> 0 | ... P18: =ROUNDDOWN(P10*P26*P4*P5,-2) -> 0 | W18: =ROUNDDOWN(W10*W26*W4*W5,-2) -> 319600 | X18: =ROUNDDOWN(X10*X26*X4*X5,-2) -> 435800 | Y18: =ROUNDDOWN(Y10*Y26*Y4*Y5,-2) -> 668200 | Z18: =ROUNDDOWN(Z10*Z26*Z4*Z5,-2) -> 799000 | AA18: =ROUNDDOWN(AA10*AA26*AA4*AA5,-2) -> 1002400 | AB18: =ROUNDDOWN(AB10*AB26*AB4*AB5,-2) -> 1118600 | AC18: =ROUNDDOWN(AC10*AC26*AC4*AC5,-2) -> 1336500 | AD18: =ROUNDDOWN(AD10*AD26*AD4*AD5,-2) -> 1438200 | ... AH18: =ROUNDDOWN(AH10*AH26*AH4*AH5,-2) -> 2077500
B19: 移行加算 | E19: =ROUNDDOWN((E9+E10)*E4*E5*E28,-2) -> 0 | F19: =ROUNDDOWN((F9+F10)*F4*F5*F28,-2) -> 0 | G19: =ROUNDDOWN((G9+G10)*G4*G5*G28,-2) -> 0 | H19: =ROUNDDOWN((H9+H10)*H4*H5*H28,-2) -> 57000 | I19: =ROUNDDOWN((I9+I10)*I4*I5*I28,-2) -> 79400 | J19: =ROUNDDOWN((J9+J10)*J4*J5*J28,-2) -> 85500 | K19: =ROUNDDOWN((K9+K10)*K4*K5*K28,-2) -> 99300 | L19: =ROUNDDOWN((L9+L10)*L4*L5*L28,-2) -> 104500 | ... P19: =ROUNDDOWN((P9+P10)*P4*P5*P28,-2) -> 142500 | W19: =ROUNDDOWN((W9+W10)*W4*W5*W28,-2) -> 161500 | X19: =ROUNDDOWN((X9+X10)*X4*X5*X28,-2) -> 155500 | Y19: =ROUNDDOWN((Y9+Y10)*Y4*Y5*Y28,-2) -> 188700 | Z19: =ROUNDDOWN((Z9+Z10)*Z4*Z5*Z28,-2) -> 190000 | AA19: =ROUNDDOWN((AA9+AA10)*AA4*AA5*AA28,-2) -> 208600 | AB19: =ROUNDDOWN((AB9+AB10)*AB4*AB5*AB28,-2) -> 209000 | AC19: =ROUNDDOWN((AC9+AC10)*AC4*AC5*AC28,-2) -> 228500 | AD19: =ROUNDDOWN((AD9+AD10)*AD4*AD5*AD28,-2) -> 228000 | ... AH19: =ROUNDDOWN((AH9+AH10)*AH4*AH5*AH28,-2) -> 266100
B20: 給付費合計 | E20: =SUM(E14:E19) -> 0 | F20: =SUM(F14:F19) -> 0 | G20: =SUM(G14:G19) -> 0 | H20: =SUM(H14:H19) -> 910200 | I20: =SUM(I14:I19) -> 1268700 | J20: =SUM(J14:J19) -> 1365300 | K20: =SUM(K14:K19) -> 1586000 | L20: =SUM(L14:L19) -> 1668700 | ... P20: =SUM(P14:P19) -> 2275600 | W20: =SUM(W14:W19) -> 2614200 | X20: =SUM(X14:X19) -> 2530500 | Y20: =SUM(Y14:Y19) -> 3086900 | Z20: =SUM(Z14:Z19) -> 3122100 | AA20: =SUM(AA14:AA19) -> 3441000 | AB20: =SUM(AB14:AB19) -> 3460700 | AC20: =SUM(AC14:AC19) -> 3795000 | AD20: =SUM(AD14:AD19) -> 3799300 | ... AH20: =SUM(AH14:AH19) -> 4476700 | AO20: =SUM(AO14:AO15) -> 4030300 | AP20: =SUM(AP14:AP15) -> 4030300 | AQ20: =SUM(AQ14:AQ15) -> 4309900 | AR20: =SUM(AR14:AR15) -> 4571400 | AS20: =SUM(AS14:AS15) -> 4571400 | AT20: =SUM(AT14:AT15) -> 4571400 | AU20: =SUM(AU14:AU15) -> 4851000 | AV20: =SUM(AV14:AV15) -> 4851000 | ... AZ20: =SUM(AZ14:AZ15) -> 5130600
B21: 給付費合計（千円） | E21: =E20/1000 -> 0 | F21: =F20/1000 -> 0 | G21: =G20/1000 -> 0 | H21: =H20/1000 -> 910.2 | I21: =I20/1000 -> 1268.7 | J21: =J20/1000 -> 1365.3 | K21: =K20/1000 -> 1586 | L21: =L20/1000 -> 1668.7 | ... P21: =P20/1000 -> 2275.6 | W21: =W20/1000 -> 2614.2 | X21: =X20/1000 -> 2530.5 | Y21: =Y20/1000 -> 3086.9 | Z21: =Z20/1000 -> 3122.1 | AA21: =AA20/1000 -> 3441 | AB21: =AB20/1000 -> 3460.7 | AC21: =AC20/1000 -> 3795 | AD21: =AD20/1000 -> 3799.3 | ... AH21: =AH20/1000 -> 4476.7 | AO21: =AO20/1000 -> 4030.3 | AP21: =AP20/1000 -> 4030.3 | AQ21: =AQ20/1000 -> 4309.9 | AR21: =AR20/1000 -> 4571.4 | AS21: =AS20/1000 -> 4571.4 | AT21: =AT20/1000 -> 4571.4 | AU21: =AU20/1000 -> 4851 | AV21: =AV20/1000 -> 4851 | ... AZ21: =AZ20/1000 -> 5130.6
B23: B基本報酬 | E23: 5890 | F23: 5890 | G23: 5890 | H23: 5890 | I23: 5890 | J23: 5890 | K23: 5890 | L23: 5890 | M23: 5890 | N23: 5890 | O23: 5890 | P23: 5890 | W23: 5890 | X23: 5890 | Y23: 5890 | Z23: 5890 | AA23: 5890 | AB23: 5890 | AC23: 5890 | AD23: 5890 | AE23: 5890 | AF23: 5890 | AG23: 5890 | AH23: 5890 | AO23: 5890 | AP23: 5890 | AQ23: 5890 | AR23: 5890 | AS23: 5890 | AT23: 5890 | AU23: 5890 | AV23: 5890 | AW23: 5890 | AX23: 5890 | AY23: 5890 | AZ23: 5890
B24: B施設外基本報酬 | E24: 6890 | F24: 6890 | G24: 6890 | H24: 6890 | I24: 6890 | J24: 6890 | K24: 6890 | L24: 6890 | M24: 6890 | N24: 6890 | O24: 6890 | P24: 6890 | W24: 6890 | X24: 6890 | Y24: 6890 | Z24: 6890 | AA24: 6890 | AB24: 6890 | AC24: 6890 | AD24: 6890 | AE24: 6890 | AF24: 6890 | AG24: 6890 | AH24: 6890 | AO24: 6890 | AP24: 6890 | AQ24: 6890 | AR24: 6890 | AS24: 6890 | AT24: 6890 | AU24: 6890 | AV24: 6890 | AW24: 6890 | AX24: 6890 | AY24: 6890 | AZ24: 6890
B25: 移行基本報酬 | E25: 8080 | F25: 8080 | G25: 8080 | H25: 8080 | I25: 8080 | J25: 8080 | K25: 8080 | L25: 8080 | M25: 8080 | N25: 8080 | O25: 8080 | P25: 8080 | W25: 8080 | X25: 8080 | Y25: 8080 | Z25: 8080 | AA25: 8080 | AB25: 8080 | AC25: 8080 | AD25: 8080 | AE25: 8080 | AF25: 8080 | AG25: 8080 | AH25: 8080
B26: 移行施設外基本報酬 | E26: 9080 | F26: 9080 | G26: 9080 | H26: 9080 | I26: 9080 | J26: 9080 | K26: 9080 | L26: 9080 | M26: 9080 | N26: 9080 | O26: 9080 | P26: 9080 | W26: 9080 | X26: 9080 | Y26: 9080 | Z26: 9080 | AA26: 9080 | AB26: 9080 | AC26: 9080 | AD26: 9080 | AE26: 9080 | AF26: 9080 | AG26: 9080 | AH26: 9080
B27: 目標工賃達成指導員加算 | E27: 890 | F27: 890 | G27: 890 | H27: 890 | I27: 890 | J27: 890 | K27: 890 | L27: 890 | M27: 890 | N27: 890 | O27: 890 | P27: 890 | W27: 890 | X27: 890 | Y27: 890 | Z27: 890 | AA27: 890 | AB27: 890 | AC27: 890 | AD27: 890 | AE27: 890 | AF27: 890 | AG27: 890 | AH27: 890 | AO27: 890 | AP27: 890 | AQ27: 890 | AR27: 890 | AS27: 890 | AT27: 890 | AU27: 890 | AV27: 890 | AW27: 890 | AX27: 890 | AY27: 890 | AZ27: 890
B28: 送迎加算 | E28: 540 | F28: 540 | G28: 540 | H28: 540 | I28: 540 | J28: 540 | K28: 540 | L28: 540 | M28: 540 | N28: 540 | O28: 540 | P28: 540 | W28: 540 | X28: 540 | Y28: 540 | Z28: 540 | AA28: 540 | AB28: 540 | AC28: 540 | AD28: 540 | AE28: 540 | AF28: 540 | AG28: 540 | AH28: 540 | AO28: 540 | AP28: 540 | AQ28: 540 | AR28: 540 | AS28: 540 | AT28: 540 | AU28: 540 | AV28: 540 | AW28: 540 | AX28: 540 | AY28: 540 | AZ28: 540
B29: 稼働率 | E29: 0.8 | F29: 0.8 | G29: 0.8 | H29: 0.8 | I29: 0.8 | J29: 0.8 | K29: 0.8 | L29: 0.8 | M29: 0.8 | N29: 0.8 | O29: 0.8 | P29: 0.8 | W29: 0.75 | X29: 0.75 | Y29: 0.75 | Z29: 0.75 | AA29: 0.75 | AB29: 0.75 | AC29: 0.75 | AD29: 0.75 | AE29: 0.75 | AF29: 0.75 | AG29: 0.75 | AH29: 0.75 | AO29: 0.75 | AP29: 0.75 | AQ29: 0.75 | AR29: 0.75 | AS29: 0.75 | AT29: 0.75 | AU29: 0.75 | AV29: 0.75 | AW29: 0.75 | AX29: 0.75 | AY29: 0.75 | AZ29: 0.75
B32: B人員配置 | E32: =ROUNDUP(E6/7.5,0) -> 0 | F32: =ROUNDUP(F6/7.5,0) -> 0 | G32: =ROUNDUP(G6/7.5,1) -> 0 | H32: =ROUNDUP(H6/7.5,1) -> 0 | I32: =ROUNDUP(I6/7.5,1) -> 0 | J32: =ROUNDUP(J6/7.5,1) -> 0 | K32: =ROUNDUP(K6/7.5,1) -> 0 | L32: =ROUNDUP(L6/7.5,1) -> 0 | M32: =ROUNDUP(M6/7.5,1) -> 0 | N32: =ROUNDUP(N6/7.5,1) -> 0 | ... P32: =ROUNDUP(P6/7.5,1) -> 0 | W32: =ROUNDUP(W6/7.5,0) -> 0 | X32: =ROUNDUP(X6/7.5,0) -> 0 | Y32: =ROUNDUP(Y6/7.5,1) -> 0 | Z32: =ROUNDUP(Z6/7.5,1) -> 0 | AA32: =ROUNDUP(AA6/7.5,1) -> 0 | AB32: =ROUNDUP(AB6/7.5,1) -> 0 | AC32: =ROUNDUP(AC6/7.5,1) -> 0 | AD32: =ROUNDUP(AD6/7.5,1) -> 0 | AE32: =ROUNDUP(AE6/7.5,1) -> 0 | AF32: =ROUNDUP(AF6/7.5,1) -> 0 | ... AH32: =ROUNDUP(AH6/7.5,1) -> 0
B33: B人工賃向上・施設外 | E33: =IF(E7/7.5<1,2,1+E7/7.5) -> 2 | F33: =IF(F7/7.5<1,2,1+F7/7.5) -> 2 | G33: =IF(G7/7.5<1,2,1+G7/7.5) -> 2 | H33: =IF(H7/7.5<1,2,1+H7/7.5) -> 2 | I33: =IF(I7/7.5<1,2,1+I7/7.5) -> 2 | J33: =IF(J7/7.5<1,2,1+J7/7.5) -> 2 | K33: =IF(K7/7.5<1,2,1+K7/7.5) -> 2 | L33: =IF(L7/7.5<1,2,1+L7/7.5) -> 2 | ... P33: =IF(P7/7.5<1,2,1+P7/7.5) -> 2 | W33: =IF(W7/7.5<1,2,1+W7/7.5) -> 2 | X33: =IF(X7/7.5<1,2,1+X7/7.5) -> 2 | Y33: =IF(Y7/7.5<1,2,1+Y7/7.5) -> 2 | Z33: =IF(Z7/7.5<1,2,1+Z7/7.5) -> 2 | AA33: =IF(AA7/7.5<1,2,1+AA7/7.5) -> 2 | AB33: =IF(AB7/7.5<1,2,1+AB7/7.5) -> 2 | AC33: =IF(AC7/7.5<1,2,1+AC7/7.5) -> 2 | AD33: =IF(AD7/7.5<1,2,1+AD7/7.5) -> 2 | ... AH33: =IF(AH7/7.5<1,2,1+AH7/7.5) -> 2
B34: 移行人員配置 | E34: =ROUNDUP(E9/6,0) -> 0 | F34: =(F9+F10)/6 -> 0 | G34: =(G9+G10)/6 -> 0 | H34: =(H9+H10)/6 -> 1 | I34: =(I9+I10)/6 -> 1.3333333 | J34: =(J9+J10)/6 -> 1.5 | K34: =(K9+K10)/6 -> 1.6666667 | L34: =(L9+L10)/6 -> 1.8333333 | M34: =(M9+M10)/6 -> 2 | ... P34: =(P9+P10)/6 -> 2.5 | W34: =ROUNDUP(W9/6,1) -> 2.5 | X34: =(X9+X10)/6 -> 3 | Y34: =(Y9+Y10)/6 -> 3.1666667 | Z34: =(Z9+Z10)/6 -> 3.3333333 | AA34: =(AA9+AA10)/6 -> 3.5 | AB34: =(AB9+AB10)/6 -> 3.6666667 | AC34: =(AC9+AC10)/6 -> 3.8333333 | AD34: =(AD9+AD10)/6 -> 4 | AE34: =(AE9+AE10)/6 -> 4.1666667 | ... AH34: =(AH9+AH10)/6 -> 4.6666667
B35: 移行就労支援員配置 | E35: =IF((E9+E10)/15<1,1,(E9+E10)/15) -> 1 | F35: =IF((F9+F10)/15<1,1,(F9+F10)/15) -> 1 | G35: =IF((G9+G10)/15<1,1,(G9+G10)/15) -> 1 | H35: =IF((H9+H10)/15<1,1,(H9+H10)/15) -> 1 | I35: =IF((I9+I10)/15<1,1,(I9+I10)/15) -> 1 | J35: =IF((J9+J10)/15<1,1,(J9+J10)/15) -> 1 | K35: =IF((K9+K10)/15<1,1,(K9+K10)/15) -> 1 | L35: =IF((L9+L10)/15<1,1,(L9+L10)/15) -> 1 | ... P35: =IF((P9+P10)/15<1,1,(P9+P10)/15) -> 1 | W35: =IF((W9+W10)/15<1,1,(W9+W10)/15) -> 1.1333333 | X35: =IF((X9+X10)/15<1,1,(X9+X10)/15) -> 1.2 | Y35: =IF((Y9+Y10)/15<1,1,(Y9+Y10)/15) -> 1.2666667 | Z35: =IF((Z9+Z10)/15<1,1,(Z9+Z10)/15) -> 1.3333333 | AA35: =IF((AA9+AA10)/15<1,1,(AA9+AA10)/15) -> 1.4 | AB35: =IF((AB9+AB10)/15<1,1,(AB9+AB10)/15) -> 1.4666667 | AC35: =IF((AC9+AC10)/15<1,1,(AC9+AC10)/15) -> 1.5333333 | AD35: =IF((AD9+AD10)/15<1,1,(AD9+AD10)/15) -> 1.6 | ... AH35: =IF((AH9+AH10)/15<1,1,(AH9+AH10)/15) -> 1.8666667
B36: 移行施設外支援配置 | E36: =IF(E10/6<1,1,E10/6) -> 1 | F36: =IF(F10/6<1,1,F10/6) -> 1 | G36: =IF(G10/6<1,1,G10/6) -> 1 | H36: =IF(H10/6<1,1,H10/6) -> 1 | I36: =IF(I10/6<1,1,I10/6) -> 1 | J36: =IF(J10/6<1,1,J10/6) -> 1 | K36: =IF(K10/6<1,1,K10/6) -> 1 | L36: =IF(L10/6<1,1,L10/6) -> 1 | ... P36: =IF(P10/6<1,1,P10/6) -> 1 | W36: =IF(W10/6<1,1,W10/6) -> 1 | X36: =IF(X10/6<1,1,X10/6) -> 1 | Y36: =IF(Y10/6<1,1,Y10/6) -> 1 | Z36: =IF(Z10/6<1,1,Z10/6) -> 1 | AA36: =IF(AA10/6<1,1,AA10/6) -> 1 | AB36: =IF(AB10/6<1,1,AB10/6) -> 1.1666667 | AC36: =IF(AC10/6<1,1,AC10/6) -> 1.3333333 | AD36: =IF(AD10/6<1,1,AD10/6) -> 1.5 | ... AH36: =IF(AH10/6<1,1,AH10/6) -> 2.1666667
B38: 管理者 | E38: 210000 | F38: 210000 | G38: 210000 | H38: 250000 | I38: 250000 | J38: 250000 | K38: 250000 | L38: 250000 | M38: 250000 | N38: 250000 | O38: 250000 | P38: 250000 | W38: 250000 | X38: 250000 | Y38: 250000 | Z38: 250000 | AA38: 250000 | AB38: 250000 | AC38: 250000 | AD38: 250000 | AE38: 250000 | AF38: 250000 | AG38: 250000 | AH38: 250000 | AO38: 300000 | AP38: 300000 | AQ38: 300000 | AR38: 350000 | AS38: 350000 | AT38: 350000 | AU38: 350000 | AV38: 350000 | AW38: 350000 | AX38: 350000 | AY38: 350000 | AZ38: 350000
B39: サービス管理責任者 | H39: 180000 | I39: 180000 | J39: 180000 | K39: 180000 | L39: 180000 | M39: 180000 | N39: 180000 | O39: 180000 | P39: 180000 | W39: 180000 | X39: 180000 | Y39: 180000 | Z39: 180000 | AA39: 180000 | AB39: 180000 | AC39: 180000 | AD39: 180000 | AE39: 180000 | AF39: 180000 | AG39: 180000 | AH39: 180000 | AO39: 150000 | AP39: 150000 | AQ39: 150000 | AR39: 150000 | AS39: 150000 | AT39: 150000 | AU39: 150000 | AV39: 150000 | AW39: 150000 | AX39: 150000 | AY39: 150000 | AZ39: 150000
B40: 職業指導員 | H40: 200000 | I40: 180000 | J40: 180000 | K40: 180000 | L40: 180000 | M40: 180000 | N40: 180000 | O40: 180000 | P40: 180000 | W40: 250000 | X40: 250000 | Y40: 250000 | Z40: 250000 | AA40: 250000 | AB40: 250000 | AC40: 250000 | AD40: 250000 | AE40: 250000 | AF40: 250000 | AG40: 250000 | AH40: 250000 | AO40: 90000 | AP40: 90000 | AQ40: 90000 | AR40: 90000 | AS40: 90000 | AT40: 90000 | AU40: 90000 | AV40: 90000 | AW40: 90000 | AX40: 90000 | AY40: 90000 | AZ40: 90000
B41: 職業指導員 | H41: 140000 | I41: 120000 | J41: 120000 | K41: 120000 | L41: 120000 | M41: 120000 | N41: 120000 | O41: 120000 | P41: 120000 | W41: 180000 | X41: 180000 | Y41: 180000 | Z41: 180000 | AA41: 180000 | AB41: 180000 | AC41: 180000 | AD41: 180000 | AE41: 180000 | AF41: 180000 | AG41: 180000 | AH41: 180000 | AO41: 0 | AP41: 0 | AQ41: 0 | AR41: 0 | AS41: 0 | AT41: 0 | AU41: 0 | AV41: 0 | AW41: 0 | AX41: 0 | AY41: 0 | AZ41: 0
B42: 職業指導員 | H42: 120000 | I42: 100000 | J42: 100000 | K42: 100000 | L42: 100000 | M42: 100000 | N42: 100000 | O42: 100000 | P42: 100000 | W42: 180000 | X42: 180000 | Y42: 180000 | Z42: 180000 | AA42: 180000 | AB42: 180000 | AC42: 180000 | AD42: 180000 | AE42: 180000 | AF42: 180000 | AG42: 180000 | AH42: 180000 | AO42: 120000 | AP42: 120000 | AQ42: 120000 | AR42: 120000 | AS42: 120000 | AT42: 120000 | AU42: 120000 | AV42: 120000 | AW42: 120000 | AX42: 120000 | AY42: 120000 | AZ42: 120000
B43: 生活支援員 | H43: 140000 | I43: 120000 | J43: 120000 | K43: 120000 | L43: 120000 | M43: 120000 | N43: 120000 | O43: 120000 | P43: 120000 | W43: 180000 | X43: 180000 | Y43: 180000 | Z43: 180000 | AA43: 180000 | AB43: 180000 | AC43: 180000 | AD43: 180000 | AE43: 180000 | AF43: 180000 | AG43: 180000 | AH43: 180000 | AO43: 250000 | AP43: 250000 | AQ43: 250000 | AR43: 300000 | AS43: 300000 | AT43: 300000 | AU43: 300000 | AV43: 300000 | AW43: 300000 | AX43: 300000 | AY43: 300000 | AZ43: 300000
B44: 支援員等 | H44: 150000 | I44: 130000 | J44: 130000 | K44: 130000 | L44: 130000 | M44: 130000 | N44: 130000 | O44: 130000 | P44: 130000 | W44: 170000 | X44: 170000 | Y44: 170000 | Z44: 170000 | AA44: 170000 | AB44: 170000 | AC44: 170000 | AD44: 170000 | AE44: 170000 | AF44: 170000 | AG44: 170000 | AH44: 170000 | AO44: 120000 | AP44: 120000 | AQ44: 120000 | AR44: 150000 | AS44: 150000 | AT44: 150000 | AU44: 150000 | AV44: 150000 | AW44: 150000 | AX44: 150000 | AY44: 150000 | AZ44: 150000
B45: 支援員等 | W45: 130000 | X45: 130000 | Y45: 130000 | Z45: 130000 | AA45: 130000 | AB45: 130000 | AC45: 130000 | AD45: 130000 | AE45: 130000 | AF45: 130000 | AG45: 130000 | AH45: 130000
B46: 支援員等 | AE46: 130000 | AF46: 130000 | AG46: 130000 | AH46: 130000
B47: 支援員等
B48: 就労支援員 | W48: 180000 | X48: 180000 | Y48: 180000 | Z48: 180000 | AA48: 180000 | AB48: 180000 | AC48: 180000 | AD48: 180000 | AE48: 180000 | AF48: 180000 | AG48: 180000 | AH48: 180000
B49: 就労支援員 | H49: 50000 | I49: 50000 | J49: 50000 | K49: 50000 | L49: 50000 | M49: 50000 | N49: 50000 | O49: 50000 | P49: 50000 | W49: 50000 | X49: 50000 | Y49: 50000 | Z49: 50000 | AA49: 50000 | AB49: 50000 | AC49: 50000 | AD49: 50000 | AE49: 50000 | AF49: 50000 | AG49: 50000 | AH49: 50000 | AO49: 120000 | AP49: 120000 | AQ49: 120000 | AR49: 120000 | AS49: 120000 | AT49: 120000 | AU49: 120000 | AV49: 120000 | AW49: 120000 | AX49: 120000 | AY49: 120000 | AZ49: 120000
B50: 就労支援員 | AO50: 250000 | AP50: 250000 | AQ50: 250000 | AR50: 250000 | AS50: 250000 | AT50: 250000 | AU50: 250000 | AV50: 250000 | AW50: 250000 | AX50: 250000 | AY50: 250000 | AZ50: 250000
B51: 賞与 | J51: 300000 | P51: 1000000 | AB51: 1500000 | AH51: 2000000
B52: 人件費合計 | E52: =SUM(E38:E50) -> 210000 | F52: =SUM(F38:F50) -> 210000 | G52: =SUM(G38:G50) -> 210000 | H52: =SUM(H38:H50) -> 1230000 | I52: =SUM(I38:I50) -> 1130000 | J52: =SUM(J38:J50) -> 1130000 | K52: =SUM(K38:K50) -> 1130000 | L52: =SUM(L38:L50) -> 1130000 | ... P52: =SUM(P38:P50) -> 1130000 | W52: =SUM(W38:W50) -> 1750000 | X52: =SUM(X38:X50) -> 1750000 | Y52: =SUM(Y38:Y50) -> 1750000 | Z52: =SUM(Z38:Z50) -> 1750000 | AA52: =SUM(AA38:AA50) -> 1750000 | AB52: =SUM(AB38:AB50) -> 1750000 | AC52: =SUM(AC38:AC50) -> 1750000 | AD52: =SUM(AD38:AD50) -> 1750000 | ... AH52: =SUM(AH38:AH50) -> 1880000 | AO52: =SUM(AO38:AO50) -> 1400000 | AP52: =SUM(AP38:AP50) -> 1400000 | AQ52: =SUM(AQ38:AQ50) -> 1400000 | AR52: =SUM(AR38:AR50) -> 1530000 | AS52: =SUM(AS38:AS50) -> 1530000 | AT52: =SUM(AT38:AT50) -> 1530000 | AU52: =SUM(AU38:AU50) -> 1530000 | AV52: =SUM(AV38:AV50) -> 1530000 | ... AZ52: =SUM(AZ38:AZ50) -> 1530000
B53: 社会保険 | D53: 19％計算 | E53: =E52*0.1 -> 21000 | F53: =F52*0.1 -> 21000 | G53: =G52*0.1 -> 21000 | H53: =H52*0.1 -> 123000 | I53: =I52*0.1 -> 113000 | J53: =J52*0.1 -> 113000 | K53: =K52*0.1 -> 113000 | L53: =L52*0.1 -> 113000 | ... U53: =U52*0.1 -> 0 | W53: =W52*0.1 -> 175000 | X53: =X52*0.1 -> 175000 | Y53: =Y52*0.1 -> 175000 | Z53: =Z52*0.1 -> 175000 | AA53: =AA52*0.1 -> 175000 | AB53: =AB52*0.1 -> 175000 | AC53: =AC52*0.1 -> 175000 | AD53: =AD52*0.1 -> 175000 | ... AH53: =AH52*0.1 -> 188000 | AO53: =AO52*0.16 -> 224000 | AP53: =AP52*0.16 -> 224000 | AQ53: =AQ52*0.16 -> 224000 | AR53: =AR52*0.16 -> 244800 | AS53: =AS52*0.16 -> 244800 | AT53: =AT52*0.16 -> 244800 | AU53: =AU52*0.16 -> 244800 | AV53: =AV52*0.16 -> 244800 | ... AZ53: =AZ52*0.16 -> 244800
B54: 人件費総計 | E54: =E52+E53 -> 231000 | F54: =F52+F53 -> 231000 | G54: =G52+G53 -> 231000 | H54: =H52+H53 -> 1353000 | I54: =I52+I53 -> 1243000 | J54: =J52+J53 -> 1243000 | K54: =K52+K53 -> 1243000 | L54: =L52+L53 -> 1243000 | ... U54: =U52+U53 -> 0 | W54: =W52+W53 -> 1925000 | X54: =X52+X53 -> 1925000 | Y54: =Y52+Y53 -> 1925000 | Z54: =Z52+Z53 -> 1925000 | AA54: =AA52+AA53 -> 1925000 | AB54: =AB52+AB53 -> 1925000 | AC54: =AC52+AC53 -> 1925000 | AD54: =AD52+AD53 -> 1925000 | ... AH54: =AH52+AH53 -> 2068000

Sheet シェルあざみ野
B1: レモン 利用者予定数及び人員配置等
E2: 月額工賃 | F2: 60000 | X2: 月額工賃 | Y2: 40000 | AP2: 月額工賃 | AQ2: 50000
E3: 1月 | F3: 2月 | G3: 3月 | H3: 4月 | I3: 5月 | J3: 6月 | K3: 7月 | L3: 8月 | M3: 9月 | N3: 10月 | O3: 11月 | P3: 12月 | X3: 1月 | Y3: 2月 | Z3: 3月 | AA3: 4月 | AB3: 5月 | AC3: 6月 | AD3: 7月 | AE3: 8月 | AF3: 9月 | AG3: 10月 | AH3: 11月 | AI3: 12月 | AP3: 1月 | AQ3: 2月 | AR3: 3月 | AS3: 4月 | AT3: 5月 | AU3: 6月 | AV3: 7月 | AW3: 8月 | AX3: 9月 | AY3: 10月 | AZ3: 11月 | BA3: 12月
B4: 通常利用者数 | O4: 10 | P4: 10 | X4: 12 | Y4: 12 | Z4: 12 | AA4: 12 | AB4: 14 | AC4: 14 | AD4: 14 | AE4: 14 | AF4: 16 | AG4: 16 | AH4: 16 | AI4: 16 | AP4: 18 | AQ4: 18 | AR4: 18 | AS4: 18 | AT4: 20 | AU4: 20 | AV4: 20 | AW4: 20 | AX4: 20 | AY4: 20 | AZ4: 20 | BA4: 20
B5: 施設外利用者数 | O5: 4 | P5: 4 | X5: 4 | Y5: 4 | Z5: 6 | AA5: 6 | AB5: 6 | AC5: 6 | AD5: 8 | AE5: 8 | AF5: 8 | AG5: 8 | AH5: 10 | AI5: 10 | AP5: 10 | AQ5: 10 | AR5: 12 | AS5: 12 | AT5: 12 | AU5: 12 | AV5: 14 | AW5: 14 | AX5: 14 | AY5: 14 | AZ5: 16 | BA5: 16
B6: 人員配置 | O6: =18/6 -> 3 | P6: =18/6 -> 3 | X6: =18/6 -> 3 | Y6: =18/6 -> 3 | Z6: =18/6 -> 3 | AA6: =18/6 -> 3 | AB6: =18/6 -> 3 | AC6: =18/6 -> 3 | AD6: =18/6 -> 3 | AE6: =(AE4+AE5)/6 -> 3.6666667 | AF6: =(AF4+AF5)/6 -> 4 | AG6: =(AG4+AG5)/6 -> 4 | AH6: =(AH4+AH5)/6 -> 4.3333333 | AI6: =(AI4+AI5)/6 -> 4.3333333 | AP6: =(AP4+AP5)/6 -> 4.6666667 | AQ6: =(AQ4+AQ5)/6 -> 4.6666667 | AR6: =(AR4+AR5)/6 -> 5 | AS6: =(AS4+AS5)/6 -> 5 | AT6: =(AT4+AT5)/6 -> 5.3333333 | AU6: =(AU4+AU5)/6 -> 5.3333333 | AV6: =(AV4+AV5)/6 -> 5.6666667 | AW6: =(AW4+AW5)/6 -> 5.6666667 | ... BA6: =(BA4+BA5)/6 -> 6
B7: 就労支援員配置 | O7: =18/15 -> 1.2 | P7: =18/15 -> 1.2 | X7: =18/15 -> 1.2 | Y7: =18/15 -> 1.2 | Z7: =18/15 -> 1.2 | AA7: =18/15 -> 1.2 | AB7: =18/15 -> 1.2 | AC7: =18/15 -> 1.2 | AD7: =18/15 -> 1.2 | AE7: =(AE4+AE5)/15 -> 1.4666667 | AF7: =(AF4+AF5)/15 -> 1.6 | AG7: =(AG4+AG5)/15 -> 1.6 | AH7: =(AH4+AH5)/15 -> 1.7333333 | AI7: =(AI4+AI5)/15 -> 1.7333333 | AP7: =(AP4+AP5)/15 -> 1.8666667 | AQ7: =(AQ4+AQ5)/15 -> 1.8666667 | AR7: =(AR4+AR5)/15 -> 2 | AS7: =(AS4+AS5)/15 -> 2 | AT7: =(AT4+AT5)/15 -> 2.1333333 | AU7: =(AU4+AU5)/15 -> 2.1333333 | AV7: =(AV4+AV5)/15 -> 2.2666667 | AW7: =(AW4+AW5)/15 -> 2.2666667 | ... BA7: =(BA4+BA5)/15 -> 2.4
B8: 必要工賃原資 | L8: =$F$2*(L4+L5)*L21 -> 0 | M8: =$F$2*(M4+M5)*M21 -> 0 | N8: =$F$2*(N4+N5)*N21 -> 0 | O8: =$F$2*(O4+O5)*O21 -> 672000 | P8: =$F$2*(P4+P5)*P21 -> 672000 | X8: =$Y$2*(X4+X5)*X21 -> 512000 | Y8: =$Y$2*(Y4+Y5)*Y21 -> 512000 | Z8: =$Y$2*(Z4+Z5)*Z21 -> 576000 | AA8: =$Y$2*(AA4+AA5)*AA21 -> 576000 | AB8: =$Y$2*(AB4+AB5)*AB21 -> 640000 | AC8: =$Y$2*(AC4+AC5)*AC21 -> 640000 | AD8: =$Y$2*(AD4+AD5)*AD21 -> 704000 | AE8: =$Y$2*(AE4+AE5)*AE21 -> 704000 | ... AI8: =$Y$2*(AI4+AI5)*AI21 -> 832000 | AP8: =$F$2*(AP4+AP5)*AP21 -> 1344000 | AQ8: =$F$2*(AQ4+AQ5)*AQ21 -> 1344000 | AR8: =$F$2*(AR4+AR5)*AR21 -> 1440000 | AS8: =$F$2*(AS4+AS5)*AS21 -> 1440000 | AT8: =$F$2*(AT4+AT5)*AT21 -> 1536000 | AU8: =$F$2*(AU4+AU5)*AU21 -> 1536000 | AV8: =$F$2*(AV4+AV5)*AV21 -> 1632000 | AW8: =$F$2*(AW4+AW5)*AW21 -> 1632000 | ... BA8: =$F$2*(BA4+BA5)*BA21 -> 1728000
B10: 通常給付金 | E10: =E4*E15*23*E20 -> 0 | F10: =F4*F15*20*F20 -> 0 | G10: =G4*G15*23*G20 -> 0 | H10: =H4*H15*22*H20 -> 0 | I10: =I4*I15*23*I20 -> 0 | J10: =J4*J15*22*J20 -> 0 | K10: =K4*K15*23*K20 -> 0 | L10: =ROUND((L4*(L15+L17+L18*0.6)*23*L20),-2) -> 0 | M10: =ROUND((M4*(M15+M17+M18*0.6)*23*M20),-2) -> 0 | N10: =ROUND((N4*(N15+N17+N18*0.6)*23*N20),-2) -> 0 | O10: =ROUND((O4*(O15+O17+O18*0.6)*23*O20),-2) -> 1393800 | P10: =ROUND((P4*(P15+P17+P18*0.6)*23*P20),-2) -> 1393800 | X10: =ROUND((X4*(X15+X17+X18*0.6)*23*X20),-2) -> 1784100 | Y10: =ROUND((Y4*(Y15+Y17+Y18*0.6)*23*Y20),-2) -> 1784100 | Z10: =ROUND((Z4*(Z15+Z17+Z18*0.6)*23*Z20),-2) -> 1784100 | AA10: =ROUND((AA4*(AA15+AA17+AA18*0.6)*23*AA20),-2) -> 1784100 | AB10: =ROUND((AB4*(AB15+AB17+AB18*0.6)*23*AB20),-2) -> 2081400 | AC10: =ROUND((AC4*(AC15+AC17+AC18*0.6)*23*AC20),-2) -> 2081400 | AD10: =ROUND((AD4*(AD15+AD17+AD18*0.6)*23*AD20),-2) -> 2081400 | AE10: =ROUND((AE4*(AE15+AE17+AE18*0.6)*23*AE20),-2) -> 1951300 | ... AI10: =ROUND((AI4*(AI15+AI17+AI18*0.6)*23*AI20),-2) -> 2230100 | AP10: =ROUND((AP4*(AP15+AP17+AP18*0.6)*23*AP20),-2) -> 2676100 | AQ10: =ROUND((AQ4*(AQ15+AQ17+AQ18*0.6)*23*AQ20),-2) -> 2676100 | AR10: =ROUND((AR4*(AR15+AR17+AR18*0.6)*23*AR20),-2) -> 2676100 | AS10: =ROUND((AS4*(AS15+AS17+AS18*0.6)*23*AS20),-2) -> 2676100 | AT10: =ROUND((AT4*(AT15+AT17+AT18*0.6)*23*AT20),-2) -> 2973400 | AU10: =ROUND((AU4*(AU15+AU17+AU18*0.6)*23*AU20),-2) -> 2973400 | AV10: =ROUND((AV4*(AV15+AV17+AV18*0.6)*23*AV20),-2) -> 2973400 | AW10: =ROUND((AW4*(AW15+AW17+AW18*0.6)*23*AW20),-2) -> 2787600 | ... BA10: =ROUND((BA4*(BA15+BA17+BA18*0.6)*23*BA20),-2) -> 2787600
B11: 施設外給付金 | E11: =E5*E16*23*E21 -> 0 | F11: =F5*F16*20*F21 -> 0 | G11: =G5*G16*23*G21 -> 0 | H11: =H5*H16*22*H21 -> 0 | I11: =I5*I16*23*I21 -> 0 | J11: =J5*J16*22*J21 -> 0 | K11: =K5*K16*23*K21 -> 0 | L11: =ROUND((L5*(L17+L16+L18*0.6)*23*L21),-2) -> 0 | M11: =ROUND((M5*(M17+M16+M18*0.6)*23*M21),-2) -> 0 | N11: =ROUND((N5*(N17+N16+N18*0.6)*23*N21),-2) -> 0 | O11: =ROUND((O5*(O17+O16+O18*0.6)*23*O21),-2) -> 668300 | P11: =ROUND((P5*(P17+P16+P18*0.6)*23*P21),-2) -> 668300 | X11: =ROUND((X5*(X17+X16+X18*0.6)*23*X21),-2) -> 668300 | Y11: =ROUND((Y5*(Y17+Y16+Y18*0.6)*23*Y21),-2) -> 668300 | Z11: =ROUND((Z5*(Z17+Z16+Z18*0.6)*23*Z21),-2) -> 1002400 | AA11: =ROUND((AA5*(AA17+AA16+AA18*0.6)*23*AA21),-2) -> 1002400 | AB11: =ROUND((AB5*(AB17+AB16+AB18*0.6)*23*AB21),-2) -> 1002400 | AC11: =ROUND((AC5*(AC17+AC16+AC18*0.6)*23*AC21),-2) -> 1002400 | AD11: =ROUND((AD5*(AD17+AD16+AD18*0.6)*23*AD21),-2) -> 1336600 | AE11: =ROUND((AE5*(AE17+AE16+AE18*0.6)*23*AE21),-2) -> 1336600 | ... AI11: =ROUND((AI5*(AI17+AI16+AI18*0.6)*23*AI21),-2) -> 1670700 | AP11: =ROUND((AP5*(AP17+AP16+AP18*0.6)*23*AP21),-2) -> 1670700 | AQ11: =ROUND((AQ5*(AQ17+AQ16+AQ18*0.6)*23*AQ21),-2) -> 1670700 | AR11: =ROUND((AR5*(AR17+AR16+AR18*0.6)*23*AR21),-2) -> 2004900 | AS11: =ROUND((AS5*(AS17+AS16+AS18*0.6)*23*AS21),-2) -> 2004900 | AT11: =ROUND((AT5*(AT17+AT16+AT18*0.6)*23*AT21),-2) -> 2004900 | AU11: =ROUND((AU5*(AU17+AU16+AU18*0.6)*23*AU21),-2) -> 2004900 | AV11: =ROUND((AV5*(AV17+AV16+AV18*0.6)*23*AV21),-2) -> 2339000 | AW11: =ROUND((AW5*(AW17+AW16+AW18*0.6)*23*AW21),-2) -> 2339000 | ... BA11: =ROUND((BA5*(BA17+BA16+BA18*0.6)*23*BA21),-2) -> 2673200
B12: 給付費合計 | E12: =SUM(E10:E11) -> 0 | F12: =SUM(F10:F11) -> 0 | G12: =SUM(G10:G11) -> 0 | H12: =SUM(H10:H11) -> 0 | I12: =SUM(I10:I11) -> 0 | J12: =SUM(J10:J11) -> 0 | K12: =SUM(K10:K11) -> 0 | L12: =SUM(L10:L11) -> 0 | ... P12: =SUM(P10:P11) -> 2062100 | X12: =SUM(X10:X11) -> 2452400 | Y12: =SUM(Y10:Y11) -> 2452400 | Z12: =SUM(Z10:Z11) -> 2786500 | AA12: =SUM(AA10:AA11) -> 2786500 | AB12: =SUM(AB10:AB11) -> 3083800 | AC12: =SUM(AC10:AC11) -> 3083800 | AD12: =SUM(AD10:AD11) -> 3418000 | AE12: =SUM(AE10:AE11) -> 3287900 | ... AI12: =SUM(AI10:AI11) -> 3900800 | AP12: =SUM(AP10:AP11) -> 4346800 | AQ12: =SUM(AQ10:AQ11) -> 4346800 | AR12: =SUM(AR10:AR11) -> 4681000 | AS12: =SUM(AS10:AS11) -> 4681000 | AT12: =SUM(AT10:AT11) -> 4978300 | AU12: =SUM(AU10:AU11) -> 4978300 | AV12: =SUM(AV10:AV11) -> 5312400 | AW12: =SUM(AW10:AW11) -> 5126600 | ... BA12: =SUM(BA10:BA11) -> 5460800
B13: 給付費合計（千円） | L13: =L12/1000 -> 0 | M13: =M12/1000 -> 0 | N13: =N12/1000 -> 0 | O13: =O12/1000 -> 2062.1 | P13: =P12/1000 -> 2062.1 | X13: =X12/1000 -> 2452.4 | Y13: =Y12/1000 -> 2452.4 | Z13: =Z12/1000 -> 2786.5 | AA13: =AA12/1000 -> 2786.5 | AB13: =AB12/1000 -> 3083.8 | AC13: =AC12/1000 -> 3083.8 | AD13: =AD12/1000 -> 3418 | AE13: =AE12/1000 -> 3287.9 | ... AI13: =AI12/1000 -> 3900.8 | AP13: =AP12/1000 -> 4346.8 | AQ13: =AQ12/1000 -> 4346.8 | AR13: =AR12/1000 -> 4681 | AS13: =AS12/1000 -> 4681 | AT13: =AT12/1000 -> 4978.3 | AU13: =AU12/1000 -> 4978.3 | AV13: =AV12/1000 -> 5312.4 | AW13: =AW12/1000 -> 5126.6 | ... BA13: =BA12/1000 -> 5460.8
B15: 通常基本報酬 | E15: 8080 | F15: 8080 | G15: 8080 | H15: 8080 | I15: 8080 | J15: 8080 | K15: 8080 | L15: 8080 | M15: 8080 | N15: 8080 | O15: 8080 | P15: 8080 | X15: 8080 | Y15: 8080 | Z15: 8080 | AA15: 8080 | AB15: 8080 | AC15: 8080 | AD15: 8080 | AE15: 8080 | AF15: 8080 | AG15: 8080 | AH15: 8080 | AI15: 8080 | AP15: 8080 | AQ15: 8080 | AR15: 8080 | AS15: 8080 | AT15: 8080 | AU15: 8080 | AV15: 8080 | AW15: 8080 | AX15: 8080 | AY15: 8080 | AZ15: 8080 | BA15: 8080
B16: 施設外基本報酬 | E16: 9080 | F16: 9080 | G16: 9080 | H16: 9080 | I16: 9080 | J16: 9080 | K16: 9080 | L16: 9080 | M16: 9080 | N16: 9080 | O16: 9080 | P16: 9080 | X16: 9080 | Y16: 9080 | Z16: 9080 | AA16: 9080 | AB16: 9080 | AC16: 9080 | AD16: 9080 | AE16: 9080 | AF16: 9080 | AG16: 9080 | AH16: 9080 | AI16: 9080 | AP16: 9080 | AQ16: 9080 | AR16: 9080 | AS16: 9080 | AT16: 9080 | AU16: 9080 | AV16: 9080 | AW16: 9080 | AX16: 9080 | AY16: 9080 | AZ16: 9080 | BA16: 9080 | BC16: =120*15000 -> 1800000
B18: 送迎加算 | BC18: =240000*6 -> 1440000
B20: 稼働率 | E20: 0.8 | F20: 0.8 | G20: 0.8 | H20: 0.8 | I20: 0.8 | J20: 0.8 | K20: 0.8 | L20: 0.75 | M20: 0.75 | N20: 0.75 | O20: 0.75 | P20: 0.75 | X20: 0.8 | Y20: 0.8 | Z20: 0.8 | AA20: 0.8 | AB20: 0.8 | AC20: 0.8 | AD20: 0.8 | AE20: 0.75 | AF20: 0.75 | AG20: 0.75 | AH20: 0.75 | AI20: 0.75 | AP20: 0.8 | AQ20: 0.8 | AR20: 0.8 | AS20: 0.8 | AT20: 0.8 | AU20: 0.8 | AV20: 0.8 | AW20: 0.75 | AX20: 0.75 | AY20: 0.75 | AZ20: 0.75 | BA20: 0.75
B21: 稼働率 | E21: 0.8 | F21: 0.8 | G21: 0.8 | H21: 0.8 | I21: 0.8 | J21: 0.8 | K21: 0.8 | L21: 0.8 | M21: 0.8 | N21: 0.8 | O21: 0.8 | P21: 0.8 | X21: 0.8 | Y21: 0.8 | Z21: 0.8 | AA21: 0.8 | AB21: 0.8 | AC21: 0.8 | AD21: 0.8 | AE21: 0.8 | AF21: 0.8 | AG21: 0.8 | AH21: 0.8 | AI21: 0.8 | AP21: 0.8 | AQ21: 0.8 | AR21: 0.8 | AS21: 0.8 | AT21: 0.8 | AU21: 0.8 | AV21: 0.8 | AW21: 0.8 | AX21: 0.8 | AY21: 0.8 | AZ21: 0.8 | BA21: 0.8
B23: 配置人数 | L23: 3 | M23: 3 | N23: 3 | O23: 3 | P23: 3 | X23: 4 | Y23: 4 | Z23: 4 | AA23: 4 | AB23: 4 | AC23: 4 | AD23: 4 | AE23: 4 | AF23: 4 | AG23: 4 | AH23: 4 | AI23: 4 | AP23: 5 | AQ23: 6 | AR23: 6 | AS23: 6 | AT23: 6 | AU23: 6 | AV23: 6 | AW23: 6 | AX23: 6 | AY23: 6 | AZ23: 6 | BA23: 6
B24: 管理者 | C24: 7 | D24: 渡邊 | W24: B | AA24: 250000 | AB24: 250000 | AC24: 250000 | AD24: 250000 | AE24: 250000 | AF24: 250000 | AG24: 250000 | AH24: 250000 | AI24: 250000 | AO24: B | AP24: 250000 | AQ24: 250000 | AR24: 250000 | AS24: 300000 | AT24: 300000 | AU24: 300000 | AV24: 300000 | AW24: 300000 | AX24: 300000 | AY24: 300000 | AZ24: 300000 | BA24: 300000
B25: サービス管理責任者 | D25: 朝原 | L25: 200000 | M25: 200000 | N25: 200000 | O25: 200000 | P25: 200000 | W25: 朝原 | X25: 200000 | Y25: 200000 | Z25: 200000 | AA25: 250000 | AB25: 250000 | AC25: 250000 | AD25: 250000 | AE25: 250000 | AF25: 250000 | AG25: 250000 | AH25: 250000 | AI25: 250000 | AO25: 朝原 | AP25: 250000 | AQ25: 250000 | AR25: 250000 | AS25: 300000 | AT25: 300000 | AU25: 300000 | AV25: 300000 | AW25: 300000 | AX25: 300000 | AY25: 300000 | AZ25: 300000 | BA25: 300000
B26: 生活支援員等 | C26: 6.5 | D26: 渡邊 | L26: 120000 | M26: 120000 | N26: 120000 | O26: 160000 | P26: 160000 | W26: 渡邊 | X26: 160000 | Y26: 160000 | Z26: 160000 | AA26: 180000 | AB26: 180000 | AC26: 180000 | AD26: 180000 | AE26: 180000 | AF26: 180000 | AG26: 180000 | AH26: 180000 | AI26: 180000 | AO26: 渡邊 | AP26: 180000 | AQ26: 180000 | AR26: 180000 | AS26: 200000 | AT26: 200000 | AU26: 200000 | AV26: 200000 | AW26: 200000 | AX26: 200000 | AY26: 200000 | AZ26: 200000 | BA26: 200000
B27: 生活支援員等 | C27: 6.5 | D27: 田中 | L27: 120000 | M27: 120000 | N27: 120000 | O27: 160000 | P27: 160000 | W27: 秀川 | X27: 160000 | Y27: 160000 | Z27: 160000 | AA27: 160000 | AB27: 160000 | AC27: 160000 | AD27: 160000 | AE27: 160000 | AF27: 160000 | AG27: 160000 | AH27: 160000 | AI27: 160000 | AO27: 秀川 | AP27: 160000 | AQ27: 160000 | AR27: 160000 | AS27: 160000 | AT27: 160000 | AU27: 160000 | AV27: 160000 | AW27: 160000 | AX27: 160000 | AY27: 160000 | AZ27: 160000 | BA27: 160000
B28: 生活支援員等 | C28: 6.5 | D28: 村上 | H28: 60000 | I28: 60000 | J28: 60000 | K28: 60000 | L28: 120000 | M28: 120000 | N28: 120000 | O28: 160000 | P28: 160000 | W28: 村上 | X28: 160000 | Y28: 160000 | Z28: 160000 | AA28: 180000 | AB28: 180000 | AC28: 180000 | AD28: 180000 | AE28: 180000 | AF28: 180000 | AG28: 180000 | AH28: 180000 | AI28: 180000 | AO28: 村上 | AP28: 180000 | AQ28: 180000 | AR28: 180000 | AS28: 200000 | AT28: 200000 | AU28: 200000 | AV28: 200000 | AW28: 200000 | AX28: 200000 | AY28: 200000 | AZ28: 200000 | BA28: 200000
B29: 生活支援員等 | C29: 7 | W29: 瀧川 | X29: 180000 | Y29: 180000 | Z29: 180000 | AA29: 180000 | AB29: 180000 | AC29: 180000 | AD29: 180000 | AE29: 180000 | AF29: 180000 | AG29: 180000 | AH29: 180000 | AI29: 180000 | AO29: 瀧川 | AP29: 180000 | AQ29: 180000 | AR29: 180000 | AS29: 180000 | AT29: 180000 | AU29: 180000 | AV29: 180000 | AW29: 180000 | AX29: 180000 | AY29: 180000 | AZ29: 180000 | BA29: 180000
B30: 生活支援員等 | D30: A | W30: A | AE30: 120000 | AF30: 120000 | AG30: 120000 | AH30: 120000 | AI30: 120000 | AO30: A | AP30: 120000 | AQ30: 120000 | AR30: 120000 | AS30: 120000 | AT30: 120000 | AU30: 120000 | AV30: 120000 | AW30: 120000 | AX30: 120000 | AY30: 120000 | AZ30: 120000 | BA30: 120000
B31: 就労支援員 | C31: 7 | L31: 200000 | M31: 200000 | N31: 200000 | O31: 200000 | P31: 200000 | W31: 継 | X31: 200000 | Y31: 200000 | Z31: 200000 | AA31: 240000 | AB31: 240000 | AC31: 240000 | AD31: 240000 | AE31: 240000 | AF31: 240000 | AG31: 240000 | AH31: 240000 | AI31: 240000 | AO31: 継 | AP31: 300000 | AQ31: 300000 | AR31: 300000 | AS31: 300000 | AT31: 300000 | AU31: 300000 | AV31: 300000 | AW31: 300000 | AX31: 300000 | AY31: 300000 | AZ31: 300000 | BA31: 300000
B32: 就労支援員 | W32: C | X32: 180000 | Y32: 180000 | Z32: 180000 | AA32: 180000 | AB32: 180000 | AC32: 180000 | AD32: 180000 | AE32: 180000 | AF32: 180000 | AG32: 180000 | AH32: 180000 | AI32: 180000 | AO32: C | AP32: 180000 | AQ32: 180000 | AR32: 180000 | AS32: 180000 | AT32: 180000 | AU32: 180000 | AV32: 180000 | AW32: 180000 | AX32: 180000 | AY32: 180000 | AZ32: 180000 | BA32: 180000
B33: 就労支援員 | C33: 2 | W33: D | AO33: D | AP33: 120000 | AQ33: 120000 | AR33: 120000 | AS33: 120000 | AT33: 120000 | AU33: 120000 | AV33: 120000 | AW33: 120000 | AX33: 120000 | AY33: 120000 | AZ33: 120000 | BA33: 120000
B34: 就労支援員 | W34: E | AD34: 120000 | AE34: 120000 | AF34: 120000 | AG34: 120000 | AH34: 120000 | AI34: 120000 | AO34: E | AP34: 120000 | AQ34: 120000 | AR34: 120000 | AS34: 120000 | AT34: 120000 | AU34: 120000 | AV34: 120000 | AW34: 120000 | AX34: 120000 | AY34: 120000 | AZ34: 120000 | BA34: 120000
B35: 施設外支援員 | D35: 増井
B36: 施設外支援員 | D36: 寺田
B37: 賞与
E38: =SUM(E24:E36) -> 0 | F38: =SUM(F24:F36) -> 0 | G38: =SUM(G24:G36) -> 0 | H38: =SUM(H24:H36) -> 60000 | I38: =SUM(I24:I36) -> 60000 | J38: =SUM(J24:J36) -> 60000 | K38: =SUM(K24:K36) -> 60000 | L38: =SUM(L24:L36) -> 760000 | ... P38: =SUM(P24:P36) -> 880000 | X38: =SUM(X24:X36) -> 1240000 | Y38: =SUM(Y24:Y36) -> 1240000 | Z38: =SUM(Z24:Z36) -> 1240000 | AA38: =SUM(AA24:AA36) -> 1620000 | AB38: =SUM(AB24:AB36) -> 1620000 | AC38: =SUM(AC24:AC36) -> 1620000 | AD38: =SUM(AD24:AD36) -> 1740000 | AE38: =SUM(AE24:AE36) -> 1860000 | ... AI38: =SUM(AI24:AI36) -> 1860000 | AP38: =SUM(AP24:AP36) -> 2040000 | AQ38: =SUM(AQ24:AQ36) -> 2040000 | AR38: =SUM(AR24:AR36) -> 2040000 | AS38: =SUM(AS24:AS36) -> 2180000 | AT38: =SUM(AT24:AT36) -> 2180000 | AU38: =SUM(AU24:AU36) -> 2180000 | AV38: =SUM(AV24:AV36) -> 2180000 | AW38: =SUM(AW24:AW36) -> 2180000 | ... BA38: =SUM(BA24:BA36) -> 2180000
B39: 社会保険 | D39: 16％計算 | E39: =E38*0.16 -> 0 | F39: =F38*0.16 -> 0 | G39: =G38*0.16 -> 0 | H39: =H38*0.16 -> 9600 | I39: =I38*0.16 -> 9600 | J39: =J38*0.16 -> 9600 | K39: =K38*0.16 -> 9600 | L39: =(L38-L33-L35-L36)*0.16 -> 121600 | M39: =(M38-M33-M35-M36)*0.16 -> 121600 | N39: =(N38-N33-N35-N36)*0.16 -> 121600 | O39: =(O38-O33-O35-O36)*0.16 -> 140800 | P39: =(P38-P33-P35-P36)*0.16 -> 140800 | X39: =(X38-X33-X35-X36)*0.16 -> 198400 | Y39: =(Y38-Y33-Y35-Y36)*0.16 -> 198400 | Z39: =(Z38-Z33-Z35-Z36)*0.16 -> 198400 | AA39: =(AA38-AA33-AA35-AA36)*0.16 -> 259200 | AB39: =(AB38-AB33-AB35-AB36)*0.16 -> 259200 | AC39: =(AC38-AC33-AC35-AC36)*0.16 -> 259200 | AD39: =(AD38-AD33-AD35-AD36)*0.16 -> 278400 | AE39: =(AE38-AE33-AE35-AE36)*0.16 -> 297600 | ... AI39: =(AI38-AI33-AI35-AI36)*0.16 -> 297600 | AP39: =(AP38-AP33-AP35-AP36)*0.16 -> 307200 | AQ39: =(AQ38-AQ33-AQ35-AQ36)*0.16 -> 307200 | AR39: =(AR38-AR33-AR35-AR36)*0.16 -> 307200 | AS39: =(AS38-AS33-AS35-AS36)*0.16 -> 329600 | AT39: =(AT38-AT33-AT35-AT36)*0.16 -> 329600 | AU39: =(AU38-AU33-AU35-AU36)*0.16 -> 329600 | AV39: =(AV38-AV33-AV35-AV36)*0.16 -> 329600 | AW39: =(AW38-AW33-AW35-AW36)*0.16 -> 329600 | ... BA39: =(BA38-BA33-BA35-BA36)*0.16 -> 329600

Sheet 基礎
A1: R3年 損益計算書 | S1: R４年 損益計算書 | AK1: R5年 損益計算書
D2: １月 | E2: 2月 | F2: ３月 | G2: ４月 | H2: ５月 | I2: ６月 | J2: ７月 | K2: ８月 | L2: ９月 | M2: １０月 | N2: １１月 | O2: １２月 | P2: 合計 | Q2: 対売上比率 | V2: １月 | W2: 2月 | X2: ３月 | Y2: ４月 | Z2: ５月 | AA2: ６月 | AB2: ７月 | AC2: ８月 | AD2: ９月 | AE2: １０月 | AF2: １１月 | AG2: １２月 | AH2: 合計 | AI2: 対売上比率 | AN2: １月 | AO2: 2月 | AP2: ３月 | AQ2: ４月 | AR2: ５月 | AS2: ６月 | AT2: ７月 | AU2: ８月 | AV2: ９月 | AW2: １０月 | AX2: １１月 | AY2: １２月 | AZ2: 合計 | BA2: 対売上比率
A3: 総売上 | D3: =D5+D12+D18+D22+D21 -> 1865900 | E3: =E5+E12+E18+E22+E21 -> 1894200 | F3: =F5+F12+F18+F22+F21 -> 2630600 | G3: =G5+G12+G18+G22+G21 -> 2897600 | H3: =H5+H12+H18+H22+H21 -> 3059300 | I3: =I5+I12+I18+I22+I21 -> 2899300 | J3: =J5+J12+J18+J22+J21 -> 3947852 | K3: =K5+K12+K18+K22+K21 -> 4530492 | ... O3: =O5+O12+O18+O22+O21 -> 8681048 | P3: =SUM(D3:O3) -> 52264612 | Q3: =P3/P3 -> 1 | T3: 総売上 | V3: =V5+V12+V18+V22+V21+V19+V20 -> 9762000 | W3: =W5+W12+W18+W22+W21+W19+W20 -> 9533752 | X3: =X5+X12+X18+X22+X21+X19+X20 -> 11093327 | Y3: =Y5+Y12+Y18+Y22+Y21+Y19+Y20 -> 10887152 | Z3: =Z5+Z12+Z18+Z22+Z21+Z19+Z20 -> 11507427 | AA3: =AA5+AA12+AA18+AA22+AA21+AA19+AA20 -> 11285752 | AB3: =AB5+AB12+AB18+AB22+AB21+AB19+AB20 -> 11921427 | AC3: =AC5+AC12+AC18+AC22+AC21+AC19+AC20 -> 11684352 | ... AG3: =AG5+AG12+AG18+AG22+AG21+AG19+AG20 -> 12481753 | AH3: =SUM(V3:AG3) -> 136865475 | AI3: =AH3/P3 -> 2.6187026 | AL3: 総売上 | AN3: =AN5+AN12+AN18+AN22+AN21+AN19+AN20 -> 12681002 | AO3: =AO5+AO12+AO18+AO22+AO21+AO19+AO20 -> 11900702 | AP3: =AP5+AP12+AP18+AP22+AP21+AP19+AP20 -> 13577527 | AQ3: =AQ5+AQ12+AQ18+AQ22+AQ21+AQ19+AQ20 -> 13278952 | AR3: =AR5+AR12+AR18+AR22+AR21+AR19+AR20 -> 13991427 | AS3: =AS5+AS12+AS18+AS22+AS21+AS19+AS20 -> 13677552 | AT3: =AT5+AT12+AT18+AT22+AT21+AT19+AT20 -> 14405527 | AU3: =AU5+AU12+AU18+AU22+AU21+AU19+AU20 -> 14076152 | ... AY3: =AY5+AY12+AY18+AY22+AY21+AY19+AY20 -> 14873453 | AZ3: =SUM(AN3:AY3) -> 166438327 | BA3: =AZ3/AH3 -> 1.2160724
C4: 利用者総数 | D4: ='シェル '!E12+ACT川崎!E12 -> 11 | E4: ='シェル '!F12+ACT川崎!F12 -> 12 | F4: ='シェル '!G12+ACT川崎!G12 -> 15 | G4: ='シェル '!H12+ACT川崎!H12 -> 22 | H4: ='シェル '!I12+ACT川崎!I12 -> 24 | I4: ='シェル '!J12+'ACT01'!J12 -> 17 | J4: ='シェル '!K12+'ACT01'!K12 -> 22 | K4: ='シェル '!L12+'ACT01'!L12 -> 26 | L4: ='シェル '!M12+'ACT01'!M12 -> 31 | M4: ='シェル '!N12+'ACT01'!N12 -> 37 | N4: ='シェル '!O12+'ACT01'!O12 -> 42 | O4: ='シェル '!P12+'ACT01'!P12 -> 48 | U4: 利用者総数 | V4: ='シェル '!R12+'ACT01'!R12 -> 54 | W4: ='シェル '!S12+'ACT01'!S12 -> 57 | X4: ='シェル '!T12+'ACT01'!T12 -> 59 | Y4: ='シェル '!U12+'ACT01'!U12 -> 60 | Z4: ='シェル '!V12+'ACT01'!V12 -> 61 | AA4: ='シェル '!W12+'ACT01'!W12 -> 62 | AB4: ='シェル '!X12+'ACT01'!X12 -> 63 | AC4: ='シェル '!Y12+'ACT01'!Y12 -> 64 | ... AG4: ='シェル '!AC12+'ACT01'!AC12 -> 68 | AN4: ='シェル '!AE12+'ACT01'!AE12 -> 69 | AO4: ='シェル '!AF12+'ACT01'!AF12 -> 70 | AP4: ='シェル '!AG12+'ACT01'!AG12 -> 71 | AQ4: ='シェル '!AH12+'ACT01'!AH12 -> 72 | AR4: ='シェル '!AI12+'ACT01'!AI12 -> 73 | AS4: ='シェル '!AJ12+'ACT01'!AJ12 -> 74 | AT4: ='シェル '!AK12+'ACT01'!AK12 -> 75 | AU4: ='シェル '!AL12+'ACT01'!AL12 -> 76 | ... AY4: ='シェル '!AP12+'ACT01'!AP12 -> 80
B5: 訓練給付金等 | D5: =SUM(D6:D11) -> 1535900 | E5: =SUM(E6:E11) -> 1534200 | F5: =SUM(F6:F11) -> 2180600 | G5: =SUM(G6:G11) -> 2237600 | H5: =SUM(H6:H11) -> 2339300 | I5: =SUM(I6:I11) -> 2389300 | J5: =SUM(J6:J11) -> 3287852 | K5: =SUM(K6:K11) -> 3750492 | ... O5: =SUM(O6:O11) -> 7241048 | P5: =SUM(D5:O5) -> 43054612 | Q5: =IF(P5=0,"",P5/$P$3) -> 0.82378134 | T5: 訓練給付金等 | V5: =SUM(V6:V11) -> 8142000 | W5: =SUM(W6:W11) -> 7823750 | X5: =SUM(X6:X11) -> 9323325 | Y5: =SUM(Y6:Y11) -> 9087150 | Z5: =SUM(Z6:Z11) -> 9677425 | AA5: =SUM(AA6:AA11) -> 9425750 | AB5: =SUM(AB6:AB11) -> 10031425 | AC5: =SUM(AC6:AC11) -> 9764350 | ... AG5: =SUM(AG6:AG11) -> 10441750 | AH5: =SUM(V5:AG5) -> 114485450 | AI5: =IF(AH5=0,"",AH5/AH$3) -> 0.83648159 | AL5: 訓練給付金等 | AN5: =SUM(AN6:AN11) -> 10611000 | AO5: =SUM(AO6:AO11) -> 9800700 | AP5: =SUM(AP6:AP11) -> 11447525 | AQ5: =SUM(AQ6:AQ11) -> 11118950 | AR5: =SUM(AR6:AR11) -> 11801425 | AS5: =SUM(AS6:AS11) -> 11457550 | AT5: =SUM(AT6:AT11) -> 12155525 | AU5: =SUM(AU6:AU11) -> 11796150 | ... AY5: =SUM(AY6:AY11) -> 12473450 | AZ5: =SUM(AN5:AY5) -> 139618300 | BA5: =IF(AZ5=0,"",AZ5/AZ$3) -> 0.83885907
C6: シェル（笠岡） | D6: ='シェル '!E20 -> 1535900 | E6: ='シェル '!F20 -> 1534200 | F6: ='シェル '!G20 -> 2180600 | G6: ='シェル '!H20 -> 2237600 | H6: ='シェル '!I20 -> 2339300 | I6: ='シェル '!J20 -> 1934200 | J6: ='シェル '!K20 -> 2494952 | K6: ='シェル '!L20 -> 2688592 | ... O6: ='シェル '!P20 -> 5099548 | P6: =SUM(D6:O6) -> 33673012 | Q6: =IF(P6=0,"",P6/$P$3) -> 0.64427938 | U6: シェル（笠岡） | V6: ='シェル '!R20 -> 5679500 | W6: ='シェル '!S20 -> 5293250 | X6: ='シェル '!T20 -> 6236425 | Y6: ='シェル '!U20 -> 5965050 | Z6: ='シェル '!V20 -> 6236425 | AA6: ='シェル '!W20 -> 5965050 | AB6: ='シェル '!X20 -> 6236425 | AC6: ='シェル '!Y20 -> 5965050 | ... AG6: ='シェル '!AC20 -> 5965050 | AH6: =SUM(V6:AG6) -> 71708750 | AI6: =IF(AH6=0,"",AH6/AH$3) -> 0.523936 | AM6: シェル（笠岡） | AN6: ='シェル '!AE20 -> 5965000 | AO6: ='シェル '!AF20 -> 5423100 | AP6: ='シェル '!AG20 -> 6236425 | AQ6: ='シェル '!AH20 -> 5965050 | AR6: ='シェル '!AI20 -> 6236425 | AS6: ='シェル '!AJ20 -> 5965050 | AT6: ='シェル '!AK20 -> 6236425 | AU6: ='シェル '!AL20 -> 5965050 | ... AY6: ='シェル '!AP20 -> 5965050 | AZ6: =SUM(AN6:AY6) -> 72124100 | BA6: =IF(AZ6=0,"",AZ6/AZ$3) -> 0.43333829
C7: ACT01（川崎） | D7: ='ACT01'!E20 -> 0 | E7: ='ACT01'!F20 -> 0 | F7: ='ACT01'!G20 -> 0 | G7: ='ACT01'!H20 -> 0 | H7: ='ACT01'!I20 -> 0 | I7: ='ACT01'!J20 -> 455100 | J7: ='ACT01'!K20 -> 792900 | K7: ='ACT01'!L20 -> 1061900 | ... O7: ='ACT01'!P20 -> 2141500 | P7: =SUM(D7:O7) -> 9381600 | Q7: =IF(P7=0,"",P7/$P$3) -> 0.17950195 | U7: ACT01（川崎） | V7: ='ACT01'!R20 -> 2462500 | W7: ='ACT01'!S20 -> 2530500 | X7: ='ACT01'!T20 -> 3086900 | Y7: ='ACT01'!U20 -> 3122100 | Z7: ='ACT01'!V20 -> 3441000 | AA7: ='ACT01'!W20 -> 3460700 | AB7: ='ACT01'!X20 -> 3795000 | AC7: ='ACT01'!Y20 -> 3799300 | ... AG7: ='ACT01'!AC20 -> 4476700 | AH7: =SUM(V7:AG7) -> 42776700 | AI7: =IF(AH7=0,"",AH7/AH$3) -> 0.31254559 | AM7: ACT01（川崎） | AN7: ='ACT01'!AE20 -> 4646000 | AO7: ='ACT01'!AF20 -> 4377600 | AP7: ='ACT01'!AG20 -> 5211100 | AQ7: ='ACT01'!AH20 -> 5153900 | AR7: ='ACT01'!AI20 -> 5565000 | AS7: ='ACT01'!AJ20 -> 5492500 | AT7: ='ACT01'!AK20 -> 5919100 | AU7: ='ACT01'!AL20 -> 5831100 | ... AY7: ='ACT01'!AP20 -> 6508400 | AZ7: =SUM(AN7:AY7) -> 67494200 | BA7: =IF(AZ7=0,"",AZ7/AZ$3) -> 0.40552078
P8: =SUM(D8:O8)*3000 -> 0 | Q8: =IF(P8=0,"",P8/$P$3) | AH8: =SUM(V8:AG8) -> 0 | AI8: =IF(AH8=0,"",AH8/AH$3) | AZ8: =SUM(AN8:AY8) -> 0 | BA8: =IF(AZ8=0,"",AZ8/AZ$3)
P9: =SUM(D9:O9)*2500 -> 0 | Q9: =IF(P9=0,"",P9/$P$3) | AH9: =SUM(V9:AG9) -> 0 | AI9: =IF(AH9=0,"",AH9/AH$3) | AZ9: =SUM(AN9:AY9) -> 0 | BA9: =IF(AZ9=0,"",AZ9/AZ$3)
P10: =SUM(D10:O10)*5000 -> 0 | Q10: =IF(P10=0,"",P10/$P$3) | AH10: =SUM(V10:AG10) -> 0 | AI10: =IF(AH10=0,"",AH10/AH$3) | AZ10: =SUM(AN10:AY10) -> 0 | BA10: =IF(AZ10=0,"",AZ10/AZ$3)
P11: =SUM(D11:O11)*5000 -> 0 | Q11: =IF(P11=0,"",P11/$P$3) | AH11: =SUM(V11:AG11) -> 0 | AI11: =IF(AH11=0,"",AH11/AH$3) | AZ11: =SUM(AN11:AY11) -> 0 | BA11: =IF(AZ11=0,"",AZ11/AZ$3)
B12: 福祉的就労売上 | D12: =SUM(D13:D17) -> 330000 | E12: =SUM(E13:E17) -> 360000 | F12: =SUM(F13:F17) -> 450000 | G12: =SUM(G13:G17) -> 660000 | H12: =SUM(H13:H17) -> 720000 | I12: =SUM(I13:I17) -> 510000 | J12: =SUM(J13:J17) -> 660000 | K12: =SUM(K13:K17) -> 780000 | ... O12: =SUM(O13:O17) -> 1440000 | P12: =SUM(D12:O12) -> 9210000 | Q12: =IF(P12=0,"",P12/$P$3) -> 0.17621866 | T12: 福祉的就労売上 | V12: =SUM(V13:V17) -> 1620000 | W12: =SUM(W13:W17) -> 1710002 | X12: =SUM(X13:X17) -> 1770002 | Y12: =SUM(Y13:Y17) -> 1800002 | Z12: =SUM(Z13:Z17) -> 1830002 | AA12: =SUM(AA13:AA17) -> 1860002 | AB12: =SUM(AB13:AB17) -> 1890002 | AC12: =SUM(AC13:AC17) -> 1920002 | ... AG12: =SUM(AG13:AG17) -> 2040003 | AH12: =SUM(V12:AG12) -> 22380025 | AI12: =IF(AH12=0,"",AH12/AH$3) -> 0.16351841 | AL12: 福祉的就労売上 | AN12: =SUM(AN13:AN17) -> 2070002 | AO12: =SUM(AO13:AO17) -> 2100002 | AP12: =SUM(AP13:AP17) -> 2130002 | AQ12: =SUM(AQ13:AQ17) -> 2160002 | AR12: =SUM(AR13:AR17) -> 2190002 | AS12: =SUM(AS13:AS17) -> 2220002 | AT12: =SUM(AT13:AT17) -> 2250002 | AU12: =SUM(AU13:AU17) -> 2280002 | ... AY12: =SUM(AY13:AY17) -> 2400003 | AZ12: =SUM(AN12:AY12) -> 26820027 | BA12: =IF(AZ12=0,"",AZ12/AZ$3) -> 0.16114093
C13: シェル（笠岡） | D13: ='シェル '!E12*30000 -> 330000 | E13: ='シェル '!F12*30000 -> 360000 | F13: ='シェル '!G12*30000 -> 450000 | G13: ='シェル '!H12*30000 -> 480000 | H13: ='シェル '!I12*30000 -> 480000 | I13: ='シェル '!J12*30000 -> 420000 | J13: ='シェル '!K12*30000 -> 510000 | K13: ='シェル '!L12*30000 -> 570000 | ... O13: ='シェル '!P12*30000 -> 1020000 | P13: =SUM(D13:O13) -> 6960000 | Q13: =IF(P13=0,"",P13/$P$3) -> 0.1331685 | U13: シェル（笠岡） | V13: ='シェル '!R12*30000 -> 1140000 | W13: ='シェル '!S12*30000 -> 1170000 | X13: ='シェル '!T12*30000 -> 1200000 | Y13: ='シェル '!U12*30000 -> 1200000 | Z13: ='シェル '!V12*30000 -> 1200000 | AA13: ='シェル '!W12*30000 -> 1200000 | AB13: ='シェル '!X12*30000 -> 1200000 | AC13: ='シェル '!Y12*30000 -> 1200000 | ... AG13: ='シェル '!AC12*30000 -> 1200000 | AH13: =SUM(V13:AG13) -> 14310000 | AI13: =IF(AH13=0,"",AH13/AH$3) -> 0.10455522 | AM13: シェル（笠岡） | AN13: ='シェル '!AE12*30000 -> 1200000 | AO13: ='シェル '!AF12*30000 -> 1200000 | AP13: ='シェル '!AG12*30000 -> 1200000 | AQ13: ='シェル '!AH12*30000 -> 1200000 | AR13: ='シェル '!AI12*30000 -> 1200000 | AS13: ='シェル '!AJ12*30000 -> 1200000 | AT13: ='シェル '!AK12*30000 -> 1200000 | AU13: ='シェル '!AL12*30000 -> 1200000 | ... AY13: ='シェル '!AP12*30000 -> 1200000 | AZ13: ='シェル '!AD12*30000 -> 0 | BA13: =IF(AZ13=0,"",AZ13/AZ$3)
C14: シェル（川崎） | D14: =ACT川崎!E12*30000 -> 0 | E14: =ACT川崎!F12*30000 -> 0 | F14: =ACT川崎!G12*30000 -> 0 | G14: =ACT川崎!H12*30000 -> 180000 | H14: =ACT川崎!I12*30000 -> 240000 | I14: ='ACT01'!J12*30000 -> 90000 | J14: ='ACT01'!K12*30000 -> 150000 | K14: ='ACT01'!L12*30000 -> 210000 | L14: ='ACT01'!M12*30000 -> 270000 | M14: ='ACT01'!N12*30000 -> 330000 | N14: ='ACT01'!O12*30000 -> 360000 | O14: ='ACT01'!P12*30000 -> 420000 | P14: =SUM(D14:O14) -> 2250000 | Q14: =IF(P14=0,"",P14/$P$3) -> 0.043050162 | U14: ACT01（川崎） | V14: ='ACT01'!R12*30000 -> 480000 | W14: ='ACT01'!S12*30000 -> 540000 | X14: ='ACT01'!T12*30000 -> 570000 | Y14: ='ACT01'!U12*30000 -> 600000 | Z14: ='ACT01'!V12*30000 -> 630000 | AA14: ='ACT01'!W12*30000 -> 660000 | AB14: ='ACT01'!X12*30000 -> 690000 | AC14: ='ACT01'!Y12*30000 -> 720000 | ... AG14: ='ACT01'!AC12*30000 -> 840000 | AH14: =SUM(V14:AG14) -> 8070000 | AI14: =IF(AH14=0,"",AH14/AH$3) -> 0.058963007 | AM14: ACT01（川崎） | AN14: ='ACT01'!AE12*30000 -> 870000 | AO14: ='ACT01'!AF12*30000 -> 900000 | AP14: ='ACT01'!AG12*30000 -> 930000 | AQ14: ='ACT01'!AH12*30000 -> 960000 | AR14: ='ACT01'!AI12*30000 -> 990000 | AS14: ='ACT01'!AJ12*30000 -> 1020000 | AT14: ='ACT01'!AK12*30000 -> 1050000 | AU14: ='ACT01'!AL12*30000 -> 1080000 | ... AY14: ='ACT01'!AP12*30000 -> 1200000 | AZ14: ='ACT01'!AV12*30000 -> 1200000 | BA14: =IF(AZ14=0,"",AZ14/AZ$3) -> 0.0072098778
P15: =SUM(D15:O15) -> 0 | Q15: =IF(P15=0,"",P15/$P$3) | U15: その他 | AH15: =SUM(V15:AG15) -> 0 | AI15: =IF(AH15=0,"",AH15/AH$3) | AM15: その他 | AZ15: =SUM(AN15:AY15) -> 0 | BA15: =IF(AZ15=0,"",AZ15/AZ$3)
P16: =SUM(D16:O16) -> 0 | Q16: =IF(P16=0,"",P16/$P$3) | W16: =売上計画!$H14 -> 2 | X16: =売上計画!$H14 -> 2 | Y16: =売上計画!$I14 -> 2 | Z16: =売上計画!$I14 -> 2 | AA16: =売上計画!$I14 -> 2 | AB16: =売上計画!$J14 -> 2 | AC16: =売上計画!$J14 -> 2 | AD16: =売上計画!$J14 -> 2 | AE16: =売上計画!$K14 -> 3 | AF16: =売上計画!$K14 -> 3 | AG16: =売上計画!$K14 -> 3 | AH16: =SUM(V16:AG16) -> 25 | AI16: =IF(AH16=0,"",AH16/AH$3) -> 1.8266111e-07 | AN16: =売上計画!$H14 -> 2 | AO16: =売上計画!$H14 -> 2 | AP16: =売上計画!$H14 -> 2 | AQ16: =売上計画!$I14 -> 2 | AR16: =売上計画!$I14 -> 2 | AS16: =売上計画!$I14 -> 2 | AT16: =売上計画!$J14 -> 2 | AU16: =売上計画!$J14 -> 2 | AV16: =売上計画!$J14 -> 2 | AW16: =売上計画!$K14 -> 3 | AX16: =売上計画!$K14 -> 3 | AY16: =売上計画!$K14 -> 3 | AZ16: =SUM(AN16:AY16) -> 27 | BA16: =IF(AZ16=0,"",AZ16/AZ$3) -> 1.6222225e-07
P17: =SUM(D17:O17) -> 0 | Q17: =IF(P17=0,"",P17/$P$3) | AH17: =SUM(V17:AG17) -> 0 | AI17: =IF(AH17=0,"",AH17/AH$3) | AZ17: =SUM(AN17:AY17) -> 0 | BA17: =IF(AZ17=0,"",AZ17/AZ$3)
B18: SDGs事業 | P18: =SUM(D18:O18) -> 0 | Q18: =IF(P18=0,"",P18/$P$3) | T18: SDGs事業 | AH18: =SUM(V18:AG18) -> 0 | AI18: =IF(AH18=0,"",AH18/AH$3) | AL18: SDGs事業 | AZ18: =SUM(AN18:AY18) -> 0 | BA18: =IF(AZ18=0,"",AZ18/AZ$3)
AH19: =SUM(V19:AG19) -> 0 | AZ19: =SUM(AN19:AY19) -> 0
AH20: =SUM(V20:AG20) -> 0 | AZ20: =SUM(AN20:AY20) -> 0
