Workbook

Sheet PL
A1: PL
B2: R2 | C2: R3 | D2: R4 | E2: R5 | F2: R6
A3: 訓練給付金等 | B3: 43054612 | C3: 114485450 | D3: 139618300 | E3: 0 | F3: 0
A4: 福祉的就労売上 | B4: 9210000 | C4: 22380025 | D4: 26820027 | E4: 0 | F4: 0
A5: その他収入 | B5: 0 | C5: 0 | D5: 0 | E5: 0 | F5: 0
A6: 総売上 | B6: =B3+B4+B5 | C6: =C3+C4+C5 | D6: =D3+D4+D5 | E6: =E3+E4+E5 | F6: =F3+F4+F5
A8: 事業原価 | B8: 49636638 | C8: 104757564 | D8: 81972549 | E8: 0 | F8: 0
A9: 売上総利益 | B9: =B6-B8 | C9: =C6-C8 | D9: =D6-D8 | E9: =E6-E8 | F9: =F6-F8
A10: 経費 | B10: 9566638 | C10: 19804564 | D10: 18180549 | E10: 0 | F10: 0
A11: 総人件費（参考） | B11: 43375000 | C11: 87533000 | D11: 104856000 | E11: 0 | F11: 0
A12: 営業利益 | B12: =B9-B10 | C12: =C9-C10 | D12: =D9-D10 | E12: =E9-E10 | F12: =F9-F10
A14: 営業外収益 | B14: 0 | C14: 0 | D14: 0 | E14: 0 | F14: 0
A15: 支払利息 | B15: 245000 | C15: 420000 | D15: 420000 | E15: 0 | F15: 0
A16: 経常利益 | B16: =B12+B14-B15 | C16: =C12+C14-C15 | D16: =D12+D14-D15 | E16: =E12+E14-E15 | F16: =F12+F14-F15
A17: 法人税等（40%） | B17: =MAX(B16*0.4,0) | C17: =MAX(C16*0.4,0) | D17: =MAX(D16*0.4,0) | E17: =MAX(E16*0.4,0) | F17: =MAX(F16*0.4,0)
A18: 税引後利益 | B18: =B16-B17 | C18: =C16-C17 | D18: =D16-D17 | E18: =E16-E17 | F18: =F16-F17

Sheet CF
A1: CF
B2: R2 | C2: R3 | D2: R4 | E2: R5 | F2: R6
A3: 前期繰越 | B3: 0 | C3: =B15 | D3: =C15 | E3: =D15 | F3: =E15
A4: 【経常収支】
A5: 経常収入 | B5: 40560360 | C5: 129071704 | D5: 146958399 | E5: 0 | F5: 0
A6: 経常支出 | B6: 59863907 | C6: 128400542 | D6: 137554977 | E6: 0 | F6: 0
A7: 経常収支差額 | B7: =B5-B6 | C7: =C5-C6 | D7: =D5-D6 | E7: =E5-E6 | F7: =F5-F6
A8: 【財務収支】
A9: 財務収入 | B9: 23000000 | C9: 0 | D9: 0 | E9: 0 | F9: 0
A10: 財務支出 | B10: 3399000 | C10: 684000 | D10: 684000 | E10: 0 | F10: 0
A11: 財務収支差額 | B11: =B9-B10 | C11: =C9-C10 | D11: =D9-D10 | E11: =E9-E10 | F11: =F9-F10
A13: CF合計 | B13: =B7+B11 | C13: =C7+C11 | D13: =D7+D11 | E13: =E7+E11 | F13: =F7+F11
A14: 法人税等 | B14: =PL!B17 | C14: =PL!C17 | D14: =PL!D17 | E14: =PL!E17 | F14: =PL!F17
A15: 期末残高 | B15: =B3+B13-B14 | C15: =C3+C13-C14 | D15: =D3+D13-D14 | E15: =E3+E13-E14 | F15: =F3+F13-F14

Sheet BS
A1: BS
B2: R2 | C2: R3 | D2: R4 | E2: R5 | F2: R6
A3: 【資産】
A4: 現金預金 | B4: =CF!B15 | C4: =CF!C15 | D4: =CF!D15 | E4: =CF!E15 | F4: =CF!F15
A5: 売掛金 | B5: 12504252 | C5: 22754103 | D5: 0 | E5: 0 | F5: 0
A6: 流動資産合計 | B6: =B4+B5 | C6: =C4+C5 | D6: =D4+D5 | E6: =E4+E5 | F6: =F4+F5
A7: 固定資産 | B7: 0 | C7: 0 | D7: 0 | E7: 0 | F7: 0
A8: 資産合計 | B8: =B6+B7 | C8: =C6+C7 | D8: =D6+D7 | E8: =E6+E7 | F8: =F6+F7
A10: 【負債】
A11: 買掛金 | B11: 7122731 | C11: 9919753 | D11: 0 | E11: 0 | F11: 0
A12: 流動負債合計 | B12: =B11 | C12: =C11 | D12: =D11 | E12: =E11 | F12: =F11
A13: 長期借入金 | B13: 14601000 | C13: 13917000 | D13: 13290000 | E13: 0 | F13: 0
A14: 短期借入金 | B14: 8000000 | C14: 8000000 | D14: 8000000 | E14: 0 | F14: 0
A15: 固定負債合計 | B15: =B13+B14 | C15: =C13+C14 | D15: =D13+D14 | E15: =E13+E14 | F15: =F13+F14
A16: 負債合計 | B16: =B12+B15 | C16: =C12+C15 | D16: =D12+D15 | E16: =E12+E15 | F16: =F12+F15
A18: 【純資産】
A19: 資本金 | B19: 0 | C19: 0 | D19: 0 | E19: 0 | F19: 0
A20: 利益剰余金 | B20: =PL!B18 | C20: =B20+PL!C18 | D20: =C20+PL!D18 | E20: =D20+PL!E18 | F20: =E20+PL!F18
A21: 純資産合計 | B21: =B19+B20 | C21: =C19+C20 | D21: =D19+D20 | E21: =E19+E20 | F21: =F19+F20
A23: 負債+純資産合計 | B23: =B16+B21 | C23: =C16+C21 | D23: =D16+D21 | E23: =E16+E21 | F23: =F16+F21
A25: 貸借チェック（0=OK） | B25: =B8-B23 | C25: =C8-C23 | D25: =D8-D23 | E25: =E8-E23 | F25: =F8-F23

Sheet 凡例
A1: 色の意味
A3: 黄色 = 入力セル（手で入力する箇所）
A4: 緑色 = 自動計算（数式で連動）
A5: 赤色 = チェック（0なら貸借一致）
A7: 三表連動ルール
A8: PL税引後利益 → BS利益剰余金（累積加算）
A9: CF期末残高 → BS現金預金
A10: PL法人税 → CF法人税等
A11: CF前期繰越 = 前年CF期末残高
A12: BS貸借チェック = 資産合計 - (負債+純資産) → 0で一致
